Workbook
Name _k: 'RESUMEN ESCENARIO'!$G$5
Name TC: 'RESUMEN ESCENARIO'!$F$6

Sheet RESUMEN ESCENARIO
B3: ="PRESUPUESTO | "&$C$5&" | REV 0"&$F$7 -> PRESUPUESTO | GERMANIA | REV 09
B4: Código S10 | C4: xxxx
B5: Proyecto | C5: GERMANIA | E5: AC : | F5: 780
B6: Presupuesto | C6: =$B$3 -> PRESUPUESTO | GERMANIA | REV 09 | E6: TC : | F6: 3.35
B7: Cliente | C7: VYV INMOBILIARIA | E7: REV : | F7: 9
B8: Lugar | C8: SURQUILLO | E8: AREA CONSTRUIDA TOTAL : | F8: 30873.09 | G8: M2
B9: Fecha | C9: 46090 | E9: PLAZO : | F9: 23 | G9: MESES
I10: =C5 -> GERMANIA
B11: ITEM | C11: DESCRIPCIÓN | E11: MONTO PARCIAL (S/) | F11: MONTO PARCIAL (US$) | G11: TOTAL (S/) | I11: S/ x m2 | J11: $ x m2
B13: 1 | C13: OBRAS PROVISIONALES | E13: =+OP!H13*1 -> 3140623.8 | F13: =+OP!I13*1 -> 11303.6 | G13: =+E13+F13*TC -> 3178490.9 | I13: =+G13/$D$71 -> 102.95344 | J13: =I13/$F$6 -> 30.732371
B14: 2 | C14: SEGURIDAD Y SALUD | E14: =+OP!H117 -> 1028225.6 | G14: =+E14+F14*TC -> 1028225.6 | I14: =+G14/$D$71 -> 33.304915 | J14: =I14/$F$6 -> 9.9417656
C15: MALLAS ANTICAÍDAS Y ENCAPSULADO NUEVO ESTÁNDAR DE SEGURIDAD | E15: =+OP!K133-OP!J125-OP!J30 -> 240929.6 | G15: =+E15+F15*TC -> 240929.6 | I15: =+G15/$D$71 -> 7.8038706 | J15: =I15/$F$6 -> 2.3295136
B16: 3 | C16: ESTRUCTURAS SÓTANO | E16: =+'Est Sotano '!K303 -> 5904035.9 | F16: =+'Est Sotano '!L303 -> 555591.91 | G16: =+E16+F16*TC -> 7765268.8 | I16: =+G16/$D$71 -> 251.52224 | J16: =I16/$F$6 -> 75.081267
B17: 4 | C17: ESTRUCTURAS TORRE | E17: =+'EST TORRE'!J157 -> 6713422.4 | F17: =+'EST TORRE'!K157 -> 841442.12 | G17: =+E17+F17*TC -> 9532253.5 | I17: =+G17/$D$71 -> 308.75605 | J17: =I17/$F$6 -> 92.165986
C18: DETALLE DE FACHADA | E18: =200*(430.59+150)*1 -> 116118 | G18: =+E18+F18*TC -> 116118 | I18: =+G18/$D$71 -> 3.7611396 | J18: =I18/$F$6 -> 1.1227282
C19: DETALLE DE FACHADA EN ESTRUCTURAS | E19: =+'EST TORRE'!J171-E18 -> 151385.38 | F19: =+'EST TORRE'!K171 -> 20323.613 | G19: =+E19+F19*TC -> 219469.49 | I19: =+G19/$D$71 -> 7.1087632 | J19: =I19/$F$6 -> 2.1220189
B20: 5 | C20: ARQUITECTURA SÓTANO | E20: =+'ARQ SOT'!I273 -> 1221097.8 | F20: =+'ARQ SOT'!J273 -> 25709.83 | G20: =+E20+F20*TC -> 1307225.8 | I20: =+G20/$D$71 -> 42.341915 | J20: =I20/$F$6 -> 12.639378
B21: 6 | C21: ARQUITECTURA TORRE | E21: =+'ARQ TORRE'!H1158 -> 16503223 | F21: =+'ARQ TORRE'!I1158 -> 896699.08 | G21: =+E21+F21*TC -> 19507165 | I21: =+G21/$D$71 -> 631.8501 | J21: =I21/$F$6 -> 188.61197
B22: =B21+1 -> 7 | C22: INSTALACIONES ELÉCTRICAS | E22: =+IIEE!G9 -> 2904701.4 | F22: =+IIEE!H9 -> 492473.21 | G22: =+E22+F22*TC -> 4554486.6 | I22: =+G22/$D$71 -> 147.52286 | J22: =I22/$F$6 -> 44.036676
B23: =B22+1 -> 8 | C23: INSTALACIONES SANITARIAS | E23: =+IISS!G9 -> 2015202.8 | F23: =+IISS!H9 -> 54479.171 | G23: =+E23+F23*TC -> 2197708 | I23: =+G23/$D$71 -> 71.18523 | J23: =I23/$F$6 -> 21.249322
B24: =B23+1 -> 9 | C24: EQUIPAMIENTO DE BOMBAS (IISS) | F24: =+'CTO BOMBAS - ACIySPC ACT'!I9 -> 50453.28 | G24: =+E24+F24*TC -> 169018.49 | I24: =+G24/$D$71 -> 5.4746217 | J24: =I24/$F$6 -> 1.6342154
B25: 10 | C25: EQUIPAMIENTO DE PISCINA + REVESTIMIENTO DE LÁMINA (IISS) | E25: =+INSTALACIONES!I71 -> 72039.77 | G25: =+E25+F25*TC -> 72039.77 | I25: =+G25/$D$71 -> 2.3334163 | J25: =I25/$F$6 -> 0.69654217
B27: 11 | C27: SISTEMA DE AGUA CONTRAINCENDIO | F27: =+'CTO BOMBAS - ACIySPC ACT'!H22 -> 481507.87 | G27: =+E27+F27*TC -> 1613051.4 | I27: =+G27/$D$71 -> 52.247811 | J27: =I27/$F$6 -> 15.596361
B28: =B27+1 -> 12 | C28: EQUIPAMIENTO DE AGUA CONTRAINCENDIO | F28: =+'CTO BOMBAS - ACIySPC ACT'!H18 -> 66343.8 | G28: =+E28+F28*TC -> 222251.73 | I28: =+G28/$D$71 -> 7.1988819 | J28: =I28/$F$6 -> 2.14892
B29: =B28+1 -> 13 | C29: SISTEMA DE VENTILACIÓN Y EXTRACCIÓN | F29: =+IIMM!I9 -> 162567.43 | G29: =+E29+F29*TC -> 544600.87 | I29: =+G29/$D$71 -> 17.639986 | J29: =I29/$F$6 -> 5.2656674
B30: =B29+1 -> 14 | C30: SISTEMA DE GAS (2 PTOS DE GAS) GN tub cobre + Pe Al Pe (ingreso dep) | E30: =+INSTALACIONES!I69 -> 426957.93 | G30: =+E30+F30*TC -> 426957.93 | I30: =+G30/$D$71 -> 13.829452 | J30: =I30/$F$6 -> 4.1281948
B31: =B30+1 -> 15 | C31: SISTEMA DE DETECCIÓN Y ALARMA | F31: =+INSTALACIONES!I43 -> 84553.58 | G31: =+E31+F31*TC -> 283254.49 | I31: =+G31/$D$71 -> 9.1748022 | J31: =I31/$F$6 -> 2.7387469
B32: =B31+1 -> 16 | C32: SISTEMA DE CCTV | F32: =+INSTALACIONES!I75 -> 8827 | G32: =+E32+F32*TC -> 29570.45 | I32: =+G32/$D$71 -> 0.95780662 | J32: =I32/$F$6 -> 0.28591242
B33: =B32+1 -> 17 | C33: EQUIPAMIENTO (INTERCOMUNICADORES) | E33: =+INSTALACIONES!I9 -> 90543.89 | G33: =+E33+F33*TC -> 90543.89 | I33: =+G33/$D$71 -> 2.9327771 | J33: =I33/$F$6 -> 0.87545584
B34: =B33+1 -> 18 | C34: GRUPO ELECTROGENO | F34: =+IIMM!I131 -> 21663.56 | G34: =+E34+F34*TC -> 72572.926 | I34: =+G34/$D$71 -> 2.3506855 | J34: =I34/$F$6 -> 0.70169717
B35: =B34+1 -> 19 | C35: ASCENSORES | E35: =+'OBRA CIVIL ASCENSOR'!G3 -> 96048.425 | F35: =+IIMM!I135 -> 300590.71 | G35: =+E35+F35*TC -> 1103027.3 | I35: =+G35/$D$71 -> 35.727791 | J35: =I35/$F$6 -> 10.665012
B36: =B35+1 -> 20 | C36: PLATAFORMA DISCAPACITADOS | E36: 18500 | G36: =+E36+F36*TC -> 18500 | I36: =+G36/$D$71 -> 0.59922735 | J36: =I36/$F$6 -> 0.17887384
B37: =B36+1 -> 21 | C37: OBRAS EXTERIORES (NO SE INCLUYE) | G37: =+E37+F37*TC -> 0 | I37: =+G37/$D$71 -> 0 | J37: =I37/$F$6 -> 0
B38: =B37+1 -> 22 | C38: SISTEMA FOTOVOLTAICO | F38: =+INSTALACIONES!I73 -> 10563.38 | G38: =+E38+F38*TC -> 35387.323 | I38: =+G38/$D$71 -> 1.146219 | J38: =I38/$F$6 -> 0.34215493
C39: COSTO DIRECTO | E39: =SUM(E13:E38) -> 40643056 | F39: =SUM(F12:F38) -> 4085093.1 | G39: =SUM(G13:G38) -> 54328118 | I39: =SUM(I13:I38) -> 1759.724 | J39: =SUM(J13:J38) -> 525.29075
C41: GASTOS GENERALES | D41: =+G41/G39 -> 0.073670319 | E41: =+GG!G86 -> 4002369.8 | G41: =+E41 -> 4002369.8 | I41: =+G41/D71 -> 129.63943 | J41: =+I41/TC -> 38.698337
C42: POLICE SECURITY (VIGILANTE ARMADO A TIEMPO COMPLETO) | E42: =+GG!G89-GG!G72 -> 120954.24 | G42: =+E42+F42*TC -> 120954.24 | I42: =+G42/$D$71 -> 3.9177886 | J42: =I42/$F$6 -> 1.1694891
C43: UTILIDAD CD | D43: 0.054 | E43: =+E39*D43 -> 2194725 | F43: =+F39*D43 -> 220595.03 | G43: =+G39*D43 -> 2933718.4 | I43: =+G43/$D$71 -> 95.025097 | J43: =+I43/TC -> 28.365701
C45: VALOR DE VENTA | E45: =SUM(E39:E43) -> 46961105 | F45: =SUM(F39:F43) -> 4305688.2 | G45: =SUM(G39:G43) -> 61385160 | I45: =SUM(I39:I43) -> 1988.3063 | J45: =SUM(J39:J43) -> 593.52428
C46: IGV | D46: 0.18 | E46: =+E45*$D$46 -> 8452998.9 | F46: =+F45*$D$46 -> 775023.87 | G46: =+D46*G45 -> 11049329 | I46: =+G46/$D$71 -> 357.89514 | J46: =+I46/TC -> 106.83437
C48: TOTAL | E48: =SUM(E45:E46) -> 55414104 | F48: =SUM(F45:F46) -> 5080712 | G48: =SUM(G45:G46) -> 72434489 | I48: =SUM(I45:I46) -> 2346.2015 | J48: =+I48/TC -> 700.35865
B52: PARTIDA COMPLEMENTARIAS
B53: ITEM | C53: DESCRIPCIÓN | E53: MONTO PARCIAL (S/) | F53: MONTO PARCIAL (US$) | G53: TOTAL (S/)
C54: OFICINAS | E54: =+OFICINAS!J75 -> 404495.62 | G54: =+E54+F54*TC -> 404495.62 | I54: =+G54/$D$71 -> 13.101883 | J54: =I54/$F$6 -> 3.9110099
C55: PAISAJISMO (SERÁ CONTRATADO POR INMOBILIARIA) | E55: =+PAISAJISMO!F39*0+PAISAJISMO!F4*0 -> 0 | G55: =+E55+F55*TC -> 0 | I55: =+G55/$D$71 -> 0 | J55: =I55/$F$6 -> 0
C56: COSTO DIRECTO | E56: =SUM(E54)+E39 -> 41047552 | F56: =SUM(F55:F55)+F39 -> 4085093.1 | G56: =SUM(G54)+G39 -> 54732614 | I56: =SUM(I54:I55)+I39 -> 1772.8259 | J56: =SUM(J54:J55)+J39 -> 529.20176
C58: GASTOS GENERALES | D58: =+G58/G56 -> 0.075335778 | E58: =+E41+E42 -> 4123324 | G58: =+G41+G42 -> 4123324 | I58: =+G58/D71 -> 133.55722 | J58: =+I58/TC -> 39.867826
C59: UTILIDAD CD | D59: 0.054 | E59: =+E56*D59 -> 2216567.8 | F59: =+F56*D59 -> 220595.03 | G59: =+G56*D59 -> 2955561.1 | I59: =+G59/$D$71 -> 95.732599 | J59: =+I59/TC -> 28.576895
C61: VALOR DE VENTA | E61: =SUM(E56:E60) -> 47387443 | F61: =SUM(F56:F59) -> 4305688.2 | G61: =SUM(G56:G60) -> 61811499 | I61: =SUM(I56:I59) -> 2002.1157 | J61: =SUM(J56:J59) -> 597.64648
C62: IGV | D62: =+D46 -> 0.18 | E62: =+E61*D62 -> 8529739.8 | F62: =+F61*D62 -> 775023.87 | G62: =+G61*D62 -> 11126070 | I62: =+G62/$D$71 -> 360.38083 | J62: =+I62/TC -> 107.57637
C64: TOTAL | E64: =SUM(E61:E63) -> 55917183 | F64: =SUM(F61:F63) -> 5080712 | G64: =SUM(G61:G63) -> 72937569 | I64: =SUM(I61:I62) -> 2362.4965 | J64: =+I64/TC -> 705.22285
C69: Área techada sótanos = | D69: 8383.8 | E69: ( 7 Sótanos Inc. Cisterna)
C70: Área techada torre = | D70: 22489.29 | E70: (27 pisos + Azotea)
C71: Área techada total = | D71: =SUM(D69:D70) -> 30873.09
C72: Área de terreno = | D72: 1317
C73: N° Departamentos = | D73: 334

Sheet OP
A2: OBRAS PROVISIONALES
A4: Presupuesto | B4: ='RESUMEN ESCENARIO'!$C$5 -> GERMANIA
A5: Subpresupuesto | B5: =$A$2 -> OBRAS PROVISIONALES
A6: Cliente | B6: ='RESUMEN ESCENARIO'!$C$7 -> VYV INMOBILIARIA
A7: Lugar | B7: ='RESUMEN ESCENARIO'!$C$8 -> SURQUILLO
A8: Fecha | B8: ='RESUMEN ESCENARIO'!$C$9 -> 46090
A12: ITEM | B12: DESCRIPCION | C12: UND | D12: CANTIDAD | E12: P.U. (PEN) | F12: P.U. (USD) | G12: P.U. (TOTAL) | H12: PRECIO PARCIAL (PEN) | I12: PRECIO PARCIAL (USD) | J12: PRECIO TOTAL (PEN) | K12: TOTAL
A13: 01 | B13: OBRAS PROVISIONALES, TRABAJOS PRELIMINARES | H13: =SUM(H15:H116) -> 3140623.8 | I13: =SUM(I15:I116) -> 11303.6 | K13: =SUM(K14:K116) -> 3178490.9
A14: =A13+0.01 -> 1.01 | B14: CONSTRUCCIONES PROVISIONALES | G14: =IFERROR(IF(D14=0,"",(E14+F14*TC)),"") | H14: =IFERROR(IF(D14=0,"",$D14*E14),"") | I14: =IFERROR(IF(D14=0,"",$D14*F14),"") | J14: =IFERROR(IF(D14<>0,(D14*G14)," "),0) | K14: =SUM(J15:J35) -> 298874.19
A15: =A14+0.0001 -> 1.0101 | B15: OFICINA DE OBRA PARA CONTRATISTA | C15: glb | D15: 1 | E15: 8767.37 | G15: =IFERROR(IF(D15=0,"",(E15+F15*TC)),"") -> 8767.37 | H15: =+ROUND(D15*E15,2) -> 8767.37 | I15: =+ROUND(D15*F15,2) -> 0 | J15: =+ROUND(H15+I15*TC,2) -> 8767.37
A16: =A15+0.0001 -> 1.0102 | B16: OFICINA DE OBRA PARA SUPERVISIÓN | C16: glb | D16: 0 | E16: 8767.37 | G16: =IFERROR(IF(D16=0,"",(E16+F16*TC)),"") | H16: =+ROUND(D16*E16,2) -> 0 | I16: =+ROUND(D16*F16,2) -> 0 | J16: =+ROUND(H16+I16*TC,2) -> 0
A17: =A16+0.0001 -> 1.0103 | B17: OFICINA SALA DE REUNIONES | C17: glb | D17: 1 | E17: 3397.24 | G17: =IFERROR(IF(D17=0,"",(E17+F17*TC)),"") -> 3397.24 | H17: =+ROUND(D17*E17,2) -> 3397.24 | I17: =+ROUND(D17*F17,2) -> 0 | J17: =+ROUND(H17+I17*TC,2) -> 3397.24
A18: =A17+0.0001 -> 1.0104 | B18: ALMACEN DE OBRA | C18: glb | D18: 1 | E18: 10851.51 | G18: =IFERROR(IF(D18=0,"",(E18+F18*TC)),"") -> 10851.51 | H18: =+ROUND(D18*E18,2) -> 10851.51 | I18: =+ROUND(D18*F18,2) -> 0 | J18: =+ROUND(H18+I18*TC,2) -> 10851.51
A19: =A18+0.0001 -> 1.0105 | B19: COMEDOR PERSONAL OBRERO | C19: glb | D19: 1 | E19: 6304.45 | G19: =IFERROR(IF(D19=0,"",(E19+F19*TC)),"") -> 6304.45 | H19: =+ROUND(D19*E19,2) -> 6304.45 | I19: =+ROUND(D19*F19,2) -> 0 | J19: =+ROUND(H19+I19*TC,2) -> 6304.45
A20: =A19+0.0001 -> 1.0106 | B20: VESTUARIO PARA OBREROS | C20: glb | D20: 1 | E20: 7019.17 | G20: =IFERROR(IF(D20=0,"",(E20+F20*TC)),"") -> 7019.17 | H20: =+ROUND(D20*E20,2) -> 7019.17 | I20: =+ROUND(D20*F20,2) -> 0 | J20: =+ROUND(H20+I20*TC,2) -> 7019.17
A21: =A20+0.0001 -> 1.0107 | B21: TRASLADO DE CAMPAMENTO PROVISIONAL A SOTANOS | C21: und | D21: 1 | E21: 5847.24 | G21: =IFERROR(IF(D21=0,"",(E21+F21*TC)),"") -> 5847.24 | H21: =+ROUND(D21*E21,2) -> 5847.24 | I21: =+ROUND(D21*F21,2) -> 0 | J21: =+ROUND(H21+I21*TC,2) -> 5847.24
A22: =A21+0.0001 -> 1.0108 | B22: CASETA PARA GUARDIANIA | C22: glb | D22: 1 | E22: 850 | G22: =IFERROR(IF(D22=0,"",(E22+F22*TC)),"") -> 850 | H22: =+ROUND(D22*E22,2) -> 850 | I22: =+ROUND(D22*F22,2) -> 0 | J22: =+ROUND(H22+I22*TC,2) -> 850
A23: =A22+0.0001 -> 1.0109 | B23: BAÑOS PORTATILES DE OBRA PARA PERSONAL STAFF Y SUPERVISION COMPARTIDOS | C23: mes | D23: 10.5 | E23: 780 | G23: =IFERROR(IF(D23=0,"",(E23+F23*TC)),"") -> 780 | H23: =+ROUND(D23*E23,2) -> 8190 | I23: =+ROUND(D23*F23,2) -> 0 | J23: =+ROUND(H23+I23*TC,2) -> 8190
A24: =A23+0.0001 -> 1.011 | B24: CONSTRUCCION DE SSHH (1ER NIVEL) | C24: glb | D24: 1 | E24: 10162.1 | G24: =IFERROR(IF(D24=0,"",(E24+F24*TC)),"") -> 10162.1 | H24: =+ROUND(D24*E24,2) -> 10162.1 | I24: =+ROUND(D24*F24,2) -> 0 | J24: =+ROUND(H24+I24*TC,2) -> 10162.1
A25: =A24+0.0001 -> 1.0111 | B25: SSHH PORTATILES PARA OBREROS | C25: glb | D25: 1 | E25: 8745 | G25: =IFERROR(IF(D25=0,"",(E25+F25*TC)),"") -> 8745 | H25: =+ROUND(D25*E25,2) -> 8745 | I25: =+ROUND(D25*F25,2) -> 0 | J25: =+ROUND(H25+I25*TC,2) -> 8745
A26: =A25+0.0001 -> 1.0112 | B26: DUCHAS PORTATILES PARA OBREROS | C26: mes | D26: 10.5 | E26: 560 | G26: =IFERROR(IF(D26=0,"",(E26+F26*TC)),"") -> 560 | H26: =+ROUND(D26*E26,2) -> 5880 | I26: =+ROUND(D26*F26,2) -> 0 | J26: =+ROUND(H26+I26*TC,2) -> 5880
A27: =A26+0.0001 -> 1.0113 | B27: ALQUILER LAVAMANOS PARA OBREROS | C27: mes | D27: 10.5 | E27: 660 | G27: =IFERROR(IF(D27=0,"",(E27+F27*TC)),"") -> 660 | H27: =+ROUND(D27*E27,2) -> 6930 | I27: =+ROUND(D27*F27,2) -> 0 | J27: =+ROUND(H27+I27*TC,2) -> 6930
A28: =A27+0.0001 -> 1.0114 | B28: ALQUILER DE ESCUADRAS METÁLICAS | C28: ml | D28: 65.24 | E28: 984.39 | F28: 69.6 | G28: =IFERROR(IF(D28=0,"",(E28+F28*TC)),"") -> 1217.55 | H28: =+ROUND(D28*E28,2) -> 64221.6 | I28: =+ROUND(D28*F28,2) -> 4540.7 | J28: =+ROUND(H28+I28*TC,2) -> 79432.95
A29: =A28+0.0001 -> 1.0115 | B29: VENTILACION PROVISIONAL EN SOTANOS | C29: glb | D29: 1 | E29: 7350 | G29: =IFERROR(IF(D29=0,"",(E29+F29*TC)),"") -> 7350 | H29: =+ROUND(D29*E29,2) -> 7350 | I29: =+ROUND(D29*F29,2) -> 0 | J29: =+ROUND(H29+I29*TC,2) -> 7350
A30: =A29+0.0001 -> 1.0116 | B30: PROTECCIÓN DE VECINOS CON MALLA RASCHEL (ENCAPSULADO) | C30: glb | D30: 1 | E30: 82538 | G30: =IFERROR(IF(D30=0,"",(E30+F30*TC)),"") -> 82538 | H30: =+ROUND(D30*E30,2) -> 82538 | I30: =+ROUND(D30*F30,2) -> 0 | J30: =+ROUND(H30+I30*TC,2) -> 82538
A31: =A30+0.0001 -> 1.0117 | B31: RENOVACIÓN DE MALLA RACHEL | C31: glb | D31: 1 | E31: 13635.52 | G31: =IFERROR(IF(D31=0,"",(E31+F31*TC)),"") -> 13635.52 | H31: =+ROUND(D31*E31,2) -> 13635.52 | I31: =+ROUND(D31*F31,2) -> 0 | J31: =+ROUND(H31+I31*TC,2) -> 13635.52
A32: =A31+0.0001 -> 1.0118 | B32: CERCO METALICO DE OBRA | C32: ml | D32: 0 | E32: 475 | G32: =IFERROR(IF(D32=0,"",(E32+F32*TC)),"") | H32: =+ROUND(D32*E32,2) -> 0 | I32: =+ROUND(D32*F32,2) -> 0 | J32: =+ROUND(H32+I32*TC,2) -> 0
A33: =A32+0.0001 -> 1.0119 | B33: MANTENIMIENTO, BASTIDORES+MALLA Y DESMONTAJE DE CERCO METALICO | C33: ml | D33: 76.3 | E33: 341.07 | G33: =IFERROR(IF(D33=0,"",(E33+F33*TC)),"") -> 341.07 | H33: =+ROUND(D33*E33,2) -> 26023.64 | I33: =+ROUND(D33*F33,2) -> 0 | J33: =+ROUND(H33+I33*TC,2) -> 26023.64
A34: =A33+0.0001 -> 1.012 | B34: PROTECCION PERIMETRAL INICIAL DE VECINOS | C34: glb | D34: 1 | E34: 6250 | G34: =IFERROR(IF(D34=0,"",(E34+F34*TC)),"") -> 6250 | H34: =+ROUND(D34*E34,2) -> 6250 | I34: =+ROUND(D34*F34,2) -> 0 | J34: =+ROUND(H34+I34*TC,2) -> 6250
A35: =A34+0.0001 -> 1.0121 | B35: CARTEL DE OBRA | C35: glb | D35: 1 | E35: 700 | G35: =IFERROR(IF(D35=0,"",(E35+F35*TC)),"") -> 700 | H35: =+ROUND(D35*E35,2) -> 700 | I35: =+ROUND(D35*F35,2) -> 0 | J35: =+ROUND(H35+I35*TC,2) -> 700
A36: =A14+0.01 -> 1.02 | B36: CAMPAMENTO Y SALA DE VENTAS CLIENTE - NO SE CONSIDERA | F36: 0 | K36: =SUM(J37:J40) -> 0
A37: =A36+0.0001 -> 1.0201 | B37: ESCUADRAS Y TABLAS PARA CASETA DE VENTAS EN VOLADIZO | C37: ml | D37: 0 | E37: 984.39 | F37: 69.6 | G37: =IFERROR(IF(D37=0,"",(E37+F37*TC)),"") | H37: =+ROUND(D37*E37,2) -> 0 | I37: =+ROUND(D37*F37,2) -> 0 | J37: =+ROUND(H37+I37*TC,2) -> 0
A38: =A37+0.0001 -> 1.0202 | B38: TRASLADO DE CONTENEDOR SALA DE VENTAS CLIENTE (MOVIMIENTO 1 VEZ) | C38: und | D38: 0 | E38: 1683.26 | F38: 0 | G38: =IFERROR(IF(D38=0,"",(E38+F38*TC)),"") | H38: =+ROUND(D38*E38,2) -> 0 | I38: =+ROUND(D38*F38,2) -> 0 | J38: =+ROUND(H38+I38*TC,2) -> 0
A39: =A38+0.0001 -> 1.0203 | B39: ESCALERA METALICA (1-2 PISO) INGRESO DE SALA VENTAS A DEP PILOTO | C39: glb | D39: 0 | E39: 2400 | F39: 0 | G39: =IFERROR(IF(D39=0,"",(E39+F39*TC)),"") | H39: =+ROUND(D39*E39,2) -> 0 | I39: =+ROUND(D39*F39,2) -> 0 | J39: =+ROUND(H39+I39*TC,2) -> 0
A40: =A39+0.0001 -> 1.0204 | B40: PROTECCION A ACCESO VERTICAL (1- PISO) | C40: glb | D40: 0 | E40: 1500 | F40: 0 | G40: =IFERROR(IF(D40=0,"",(E40+F40*TC)),"") | H40: =+ROUND(D40*E40,2) -> 0 | I40: =+ROUND(D40*F40,2) -> 0 | J40: =+ROUND(H40+I40*TC,2) -> 0
A41: =A36+0.01 -> 1.03 | B41: MOVILIZACION DE CAMPAMENTO, MAQUINARIA Y HERRAMIENTAS | K41: =SUM(J42:J42) -> 48782
A42: =A41+0.0001 -> 1.0301 | B42: MOVILIZACION Y DESMOVILIZACION (FLETES DURANTE LA OBRA) | C42: glb | D42: 1 | E42: 42350 | F42: 1920 | G42: =IFERROR(IF(D42=0,"",(E42+F42*TC)),"") -> 48782 | H42: =+ROUND(D42*E42,2) -> 42350 | I42: =+ROUND(D42*F42,2) -> 1920 | J42: =+ROUND(H42+I42*TC,2) -> 48782
A43: =A41+0.01 -> 1.04 | B43: MAQUINARIA Y HERRAMIENTAS | K43: =SUM(J44:J52) -> 33250
A44: =A43+0.0001 -> 1.0401 | B44: NIVEL TOPOGRAFICO (INC CUADRILLA TOPOGRAFIA) | C44: glb | D44: 0 | G44: =IFERROR(IF(D44=0,"",(E44+F44*TC)),"") | H44: =+ROUND(D44*E44,2) -> 0 | I44: =+ROUND(D44*F44,2) -> 0 | J44: =+ROUND(H44+I44*TC,2) -> 0
A45: =A44+0.0001 -> 1.0402 | B45: TEODOLITO ELECTRICO (INC CUADRILLA TOPOGRAFIA) | C45: glb | D45: 0 | G45: =IFERROR(IF(D45=0,"",(E45+F45*TC)),"") | H45: =+ROUND(D45*E45,2) -> 0 | I45: =+ROUND(D45*F45,2) -> 0 | J45: =+ROUND(H45+I45*TC,2) -> 0
A46: =A45+0.0001 -> 1.0403 | B46: VIBRADOR ELECTRICO (INC EN APU DE CONCRETO) | C46: glb | D46: 0 | G46: =IFERROR(IF(D46=0,"",(E46+F46*TC)),"") | H46: =+ROUND(D46*E46,2) -> 0 | I46: =+ROUND(D46*F46,2) -> 0 | J46: =+ROUND(H46+I46*TC,2) -> 0
A47: =A46+0.0001 -> 1.0404 | B47: COMPACTADORA TIPO PLANCHA (INC EN APU EST SOT) | C47: glb | D47: 0 | G47: =IFERROR(IF(D47=0,"",(E47+F47*TC)),"") | H47: =+ROUND(D47*E47,2) -> 0 | I47: =+ROUND(D47*F47,2) -> 0 | J47: =+ROUND(H47+I47*TC,2) -> 0
A48: =A47+0.0001 -> 1.0405 | B48: APISONADOR TIPO CANGURO (INC EN APU EST SOT) | C48: glb | D48: 0 | G48: =IFERROR(IF(D48=0,"",(E48+F48*TC)),"") | H48: =+ROUND(D48*E48,2) -> 0 | I48: =+ROUND(D48*F48,2) -> 0 | J48: =+ROUND(H48+I48*TC,2) -> 0
A49: =A47+0.0001 -> 1.0405 | B49: MARTILLO ELECTRICO | C49: glb | D49: 4 | E49: 4600 | G49: =IFERROR(IF(D49=0,"",(E49+F49*TC)),"") -> 4600 | H49: =+ROUND(D49*E49,2) -> 18400 | I49: =+ROUND(D49*F49,2) -> 0 | J49: =+ROUND(H49+I49*TC,2) -> 18400
A50: =A49+0.0001 -> 1.0406 | B50: AMOLADORAS Y RADIALES | C50: glb | D50: 10 | E50: 675 | G50: =IFERROR(IF(D50=0,"",(E50+F50*TC)),"") -> 675 | H50: =+ROUND(D50*E50,2) -> 6750 | I50: =+ROUND(D50*F50,2) -> 0 | J50: =+ROUND(H50+I50*TC,2) -> 6750
A51: =A50+0.0001 -> 1.0407 | B51: KIT DE SOLAQUEO (ASPIRADORA DE POLVO UNIVERSAL) | C51: glb | D51: 3 | E51: 2250 | G51: =IFERROR(IF(D51=0,"",(E51+F51*TC)),"") -> 2250 | H51: =+ROUND(D51*E51,2) -> 6750 | I51: =+ROUND(D51*F51,2) -> 0 | J51: =+ROUND(H51+I51*TC,2) -> 6750
A52: =A51+0.0001 -> 1.0408 | B52: HIDROLAVADORA | C52: glb | D52: 1 | E52: 1350 | G52: =IFERROR(IF(D52=0,"",(E52+F52*TC)),"") -> 1350 | H52: =+ROUND(D52*E52,2) -> 1350 | I52: =+ROUND(D52*F52,2) -> 0 | J52: =+ROUND(H52+I52*TC,2) -> 1350
A53: =A43+0.01 -> 1.05 | B53: TRANSPORTE VERTICAL Y HORIZONTAL | F53: 0 | G53: =IFERROR(IF(D53=0,"",(E53+F53*TC)),"") | K53: =SUM(J54:J71) -> 1142907.8
A54: =A53+0.0001 -> 1.0501 | B54: ALQUILER GRUA TORRE
A55: =A54+0.000001 -> 1.050101 | B55: ALQUILER Y OPERACIÓN DE GRUA TORRE | C55: mes | D55: 10 | E55: 47273.28 | F55: 0 | G55: =IFERROR(IF(D55=0,"",(E55+F55*TC)),"") -> 47273.28 | H55: =+ROUND(D55*E55,2) -> 472732.8 | I55: =+ROUND(D55*F55,2) -> 0 | J55: =+ROUND(H55+I55*TC,2) -> 472732.8
A56: =A55+0.000001 -> 1.050102 | B56: MONTAJE GRUA TORRE | C56: glb | D56: 1 | E56: 85550 | F56: 0 | G56: =IFERROR(IF(D56=0,"",(E56+F56*TC)),"") -> 85550 | H56: =+ROUND(D56*E56,2) -> 85550 | I56: =+ROUND(D56*F56,2) -> 0 | J56: =+ROUND(H56+I56*TC,2) -> 85550
A57: =A56+0.000001 -> 1.050103 | B57: DESMONTAJE DE GRUA TORRE | C57: glb | D57: 1 | E57: 60460 | F57: 0 | G57: =IFERROR(IF(D57=0,"",(E57+F57*TC)),"") -> 60460 | H57: =+ROUND(D57*E57,2) -> 60460 | I57: =+ROUND(D57*F57,2) -> 0 | J57: =+ROUND(H57+I57*TC,2) -> 60460
A58: =A54+0.0001 -> 1.0502 | B58: CIMENTACIÓN PARA TORRE GRÚA
A59: =A58+0.000001 -> 1.050201 | B59: ZAPATA PARA TORRE GRUA | C59: glb | D59: 1 | E59: 45714.32 | F59: 3924.9 | G59: =IFERROR(IF(D59=0,"",(E59+F59*TC)),"") -> 58862.735 | H59: =+ROUND(D59*E59,2) -> 45714.32 | I59: =+ROUND(D59*F59,2) -> 3924.9 | J59: =+ROUND(H59+I59*TC,2) -> 58862.74
A60: =A58+0.0001 -> 1.0503 | B60: ALQUILER ELEVADOR VERTICAL
A61: =A60+0.000001 -> 1.050301 | B61: TRANSPORTE VERTICAL CON ELEVADOR | C61: mes | D61: 10 | E61: 13031 | F61: 0 | G61: =IFERROR(IF(D61=0,"",(E61+F61*TC)),"") -> 13031 | H61: =+ROUND(D61*E61,2) -> 130310 | I61: =+ROUND(D61*F61,2) -> 0 | J61: =+ROUND(H61+I61*TC,2) -> 130310
A62: =A61+0.000001 -> 1.050302 | B62: MONTAJE DE ELEVADOR | C62: glb | D62: 1 | E62: 32475 | F62: 0 | G62: =IFERROR(IF(D62=0,"",(E62+F62*TC)),"") -> 32475 | H62: =+ROUND(D62*E62,2) -> 32475 | I62: =+ROUND(D62*F62,2) -> 0 | J62: =+ROUND(H62+I62*TC,2) -> 32475
A63: =A62+0.000001 -> 1.050303 | B63: DESMONTAJE DE ELEVADOR | C63: glb | D63: 1 | E63: 16332 | F63: 0 | G63: =IFERROR(IF(D63=0,"",(E63+F63*TC)),"") -> 16332 | H63: =+ROUND(D63*E63,2) -> 16332 | I63: =+ROUND(D63*F63,2) -> 0 | J63: =+ROUND(H63+I63*TC,2) -> 16332
A64: =A60+0.0001 -> 1.0504 | B64: ACCESORIOS PARA ACARREO
A65: =A64+0.000001 -> 1.050401 | B65: PULPO DE CADENA, ESTROBO Y ESLINGA | C65: glb | D65: 1 | E65: 3967.6 | G65: =IFERROR(IF(D65=0,"",(E65+F65*TC)),"") -> 3967.6 | H65: =+ROUND(D65*E65,2) -> 3967.6 | I65: =+ROUND(D65*F65,2) -> 0 | J65: =+ROUND(H65+I65*TC,2) -> 3967.6
A66: =A65+0.000001 -> 1.050402 | B66: PLATAFORMAS Y STOCKAS PARA DESCARGAS DE PARIHUELAS (COMPRA 100%) | C66: und | D66: 2 | E66: 4940 | F66: 459 | G66: =IFERROR(IF(D66=0,"",(E66+F66*TC)),"") -> 6477.65 | H66: =+ROUND(D66*E66,2) -> 9880 | I66: =+ROUND(D66*F66,2) -> 918 | J66: =+ROUND(H66+I66*TC,2) -> 12955.3
A67: =A66+0.000001 -> 1.050403 | B67: INSTALACION Y DESISTALACION DE PLATAFORMA DESCARGA DE PARIHUELAS | C67: und | D67: 28 | E67: 222.75 | G67: =IFERROR(IF(D67=0,"",(E67+F67*TC)),"") -> 222.75 | H67: =+ROUND(D67*E67,2) -> 6237 | I67: =+ROUND(D67*F67,2) -> 0 | J67: =+ROUND(H67+I67*TC,2) -> 6237
A68: =A67+0.000001 -> 1.050404 | B68: ALQUILER GRUA TELESCOPICA PARA ACARREO | C68: día | D68: 0 | F68: 960 | G68: =IFERROR(IF(D68=0,"",(E68+F68*TC)),"") | H68: =+ROUND(D68*E68,2) -> 0 | I68: =+ROUND(D68*F68,2) -> 0 | J68: =+ROUND(H68+I68*TC,2) -> 0
A69: =A64+0.0001 -> 1.0505 | B69: TRASLADO Y ACARREO HORIZONTAL
A70: =A69+0.000001 -> 1.050501 | B70: TRASLADO Y ACARREO HORIZONTAL (PEONES) | C70: mes | D70: 23 | E70: 7468.06 | G70: =IFERROR(IF(D70=0,"",(E70+F70*TC)),"") -> 7468.06 | H70: =+ROUND(D70*E70,2) -> 171765.38 | I70: =+ROUND(D70*F70,2) -> 0 | J70: =+ROUND(H70+I70*TC,2) -> 171765.38
A71: =A70+0.000001 -> 1.050502 | B71: ALQUILER DE EQUIPO BOBCAT Y MONTACARGA | C71: mes | D71: 10 | E71: 9126 | G71: =IFERROR(IF(D71=0,"",(E71+F71*TC)),"") -> 9126 | H71: =+ROUND(D71*E71,2) -> 91260 | I71: =+ROUND(D71*F71,2) -> 0 | J71: =+ROUND(H71+I71*TC,2) -> 91260
A72: =A53+0.01 -> 1.06 | B72: INSTALACIONES PROVISIONALES, AGUA Y ENERGIA | F72: 0 | G72: =IFERROR(IF(D72=0,"",(E72+F72*TC)),"") | K72: =SUM(J74:J90) -> 363309.84
A73: =A72+0.0001 -> 1.0601 | B73: INSTALACIONES PROVISIONALES | G73: =IFERROR(IF(D73=0,"",(E73+F73*TC)),"")
A74: =A73+0.000001 -> 1.060101 | B74: INSTALACIÓN PROVISIONAL DE AGUA Y DESAGUE PARA LA CONSTRUCCIÓN | C74: glb | D74: 1 | E74: 17325.13 | G74: =IFERROR(IF(D74=0,"",(E74+F74*TC)),"") -> 17325.13 | H74: =+ROUND(D74*E74,2) -> 17325.13 | I74: =+ROUND(D74*F74,2) -> 0 | J74: =+ROUND(H74+I74*TC,2) -> 17325.13
A75: =A74+0.000001 -> 1.060102 | B75: INSTALACIÓN PROVISIONAL DE ENERGÍA PARA LA CONSTRUCCIÓN (VENTA DEL 60% A ALMACEN) | C75: glb | D75: 1 | E75: 93982.5 | G75: =IFERROR(IF(D75=0,"",(E75+F75*TC)),"") -> 93982.5 | H75: =+ROUND(D75*E75,2) -> 93982.5 | I75: =+ROUND(D75*F75,2) -> 0 | J75: =+ROUND(H75+I75*TC,2) -> 93982.5
A76: =A75+0.000001 -> 1.060103 | B76: OFICIAL DE IIEE E IISS, PARA CABLEADOS, INSTALACIONES PROVISIONALES DURANTE LA OBRA | C76: mes | D76: 18 | E76: 4686.24 | G76: =IFERROR(IF(D76=0,"",(E76+F76*TC)),"") -> 4686.24 | H76: =+ROUND(D76*E76,2) -> 84352.32 | I76: =+ROUND(D76*F76,2) -> 0 | J76: =+ROUND(H76+I76*TC,2) -> 84352.32
A77: =A76+0.000001 -> 1.060104 | B77: POZO A TIERRA PROVISIONAL (NORMATIVA) | C77: glb | D77: 1 | E77: 1300 | G77: =IFERROR(IF(D77=0,"",(E77+F77*TC)),"") -> 1300 | H77: =+ROUND(D77*E77,2) -> 1300 | I77: =+ROUND(D77*F77,2) -> 0 | J77: =+ROUND(H77+I77*TC,2) -> 1300
A78: =A77+0.000001 -> 1.060105 | B78: AMPLIACION DE CARGA | C78: glb | D78: 0 | E78: 13000 | G78: =IFERROR(IF(D78=0,"",(E78+F78*TC)),"") | H78: =+ROUND(D78*E78,2) -> 0 | I78: =+ROUND(D78*F78,2) -> 0 | J78: =+ROUND(H78+I78*TC,2) -> 0
A79: =A78+0.000001 -> 1.060106 | B79: CONSUMO DE AGUA PARA LA OBRA | C79: mes | D79: 23 | E79: 1500 | G79: =IFERROR(IF(D79=0,"",(E79+F79*TC)),"") -> 1500 | H79: =+ROUND(D79*E79,2) -> 34500 | I79: =+ROUND(D79*F79,2) -> 0 | J79: =+ROUND(H79+I79*TC,2) -> 34500
A80: =A79+0.000001 -> 1.060107 | B80: AGUA PARA LLENADO DE CISTERNA (PRUEBA HIDRAULICA) | C80: vje | D80: 13 | E80: 340 | G80: =IFERROR(IF(D80=0,"",(E80+F80*TC)),"") -> 340 | H80: =+ROUND(D80*E80,2) -> 4420 | I80: =+ROUND(D80*F80,2) -> 0 | J80: =+ROUND(H80+I80*TC,2) -> 4420
A81: =A80+0.000001 -> 1.060108 | B81: CONSUMO DE ELECTRICIDAD PARA LA OBRA | C81: mes | D81: 23 | E81: 5540.43 | G81: =IFERROR(IF(D81=0,"",(E81+F81*TC)),"") -> 5540.43 | H81: =+ROUND(D81*E81,2) -> 127429.89 | I81: =+ROUND(D81*F81,2) -> 0 | J81: =+ROUND(H81+I81*TC,2) -> 127429.89
A82: =A73+0.0001 -> 1.0602 | B82: GRUPO ELECTROGENO PARA GRUA TORRE ((SE CONSIDERA QUE SE CONECTA AL MEDIDOR PÚBLICO) | G82: =IFERROR(IF(D82=0,"",(E82+F82*TC)),"")
A83: =A82+0.000001 -> 1.060201 | B83: TRANSPORTE DE GRUPO ELECTROGENO 100KW PARA GRUA | C83: vez | D83: 0 | F83: 300 | G83: =IFERROR(IF(D83=0,"",(E83+F83*TC)),"") | H83: =+ROUND(D83*E83,2) -> 0 | I83: =+ROUND(D83*F83,2) -> 0 | J83: =+ROUND(H83+I83*TC,2) -> 0
A84: =A83+0.000001 -> 1.060202 | B84: ALQUILER DE GRUPO ELECTROGENO 100KW PARA TORRE GRUA (inc mantenimiento y combustible) | C84: mes | D84: 0 | F84: 6261.04 | G84: =IFERROR(IF(D84=0,"",(E84+F84*TC)),"") | H84: =+ROUND(D84*E84,2) -> 0 | I84: =+ROUND(D84*F84,2) -> 0 | J84: =+ROUND(H84+I84*TC,2) -> 0
A85: =A82+0.0001 -> 1.0603 | B85: GRUPO ELECTROGENO PARA ELEVADOR VERTICAL (SE CONSIDERA QUE SE CONECTA AL MEDIDOR PÚBLICO) | G85: =IFERROR(IF(D85=0,"",(E85+F85*TC)),"") | H85: =+ROUND(D85*E85,2) -> 0 | I85: =+ROUND(D85*F85,2) -> 0 | J85: =+ROUND(H85+I85*TC,2) -> 0
A86: =A85+0.000001 -> 1.060301 | B86: TRANSPORTE DE GRUPO ELECTROGENO 80KW PARA ELEVADOR | C86: vez | D86: 0 | F86: 220 | G86: =IFERROR(IF(D86=0,"",(E86+F86*TC)),"") | H86: =+ROUND(D86*E86,2) -> 0 | I86: =+ROUND(D86*F86,2) -> 0 | J86: =+ROUND(H86+I86*TC,2) -> 0
A87: =A86+0.000001 -> 1.060302 | B87: ALQUILER DE GRUPO ELECTROGENO 80 KW PARA ELEVADOR (inc mantenimiento y combustible) | C87: mes | D87: 0 | F87: 2353.68 | G87: =IFERROR(IF(D87=0,"",(E87+F87*TC)),"") | H87: =+ROUND(D87*E87,2) -> 0 | I87: =+ROUND(D87*F87,2) -> 0 | J87: =+ROUND(H87+I87*TC,2) -> 0
A88: =A85+0.0001 -> 1.0604 | B88: GRUPO ELECTROGENO PARA MAQUINA DE ANCLAJES (INC EN COSTO DE ANCLAJES) | G88: =IFERROR(IF(D88=0,"",(E88+F88*TC)),"") | H88: =+ROUND(D88*E88,2) -> 0 | I88: =+ROUND(D88*F88,2) -> 0 | J88: =+ROUND(H88+I88*TC,2) -> 0
A89: =A88+0.000001 -> 1.060401 | B89: TRANSPORTE DE GRUPO ELECTROGENO 80KW PARA MAQUINA DE ANCLAJES | C89: vez | D89: 0 | F89: 220 | G89: =IFERROR(IF(D89=0,"",(E89+F89*TC)),"") | H89: =+ROUND(D89*E89,2) -> 0 | I89: =+ROUND(D89*F89,2) -> 0 | J89: =+ROUND(H89+I89*TC,2) -> 0
A90: =A89+0.000001 -> 1.060402 | B90: ALQUILER DE GRUPO ELECTROGENO 80 KW PARA MAQUINA DE ANCLAJES (inc mantenimiento y combustible) | C90: mes | D90: 0 | F90: 1150.92 | G90: =IFERROR(IF(D90=0,"",(E90+F90*TC)),"") | H90: =+ROUND(D90*E90,2) -> 0 | I90: =+ROUND(D90*F90,2) -> 0 | J90: =+ROUND(H90+I90*TC,2) -> 0
A91: =A72+0.01 -> 1.07 | B91: TRAZOS, NIVELES Y REPLANTEO | K91: =SUM(J92) -> 447411.64
A92: =A91+0.0001 -> 1.0701 | B92: TRAZO Y REPLANTEO DURANTE LA EJECUCIÓN DE OBRA | C92: mes | D92: 23 | E92: 19452.68 | G92: =IFERROR(IF(D92=0,"",(E92+F92*TC)),"") -> 19452.68 | H92: =+ROUND(D92*E92,2) -> 447411.64 | I92: =+ROUND(D92*F92,2) -> 0 | J92: =+ROUND(H92+I92*TC,2) -> 447411.64
A93: =A91+0.01 -> 1.08 | B93: LIMPIEZA DE OBRA | F93: 0 | K93: =SUM(J94:J99) -> 464265.64
A94: =A93+0.0001 -> 1.0801 | B94: PERSONAL DE LIMPIEZA PERMANENTE EN OBRA | C94: mes | D94: 17 | E94: 5485.8 | G94: =IFERROR(IF(D94=0,"",(E94+F94*TC)),"") -> 5485.8 | H94: =+ROUND(D94*E94,2) -> 93258.6 | I94: =+ROUND(D94*F94,2) -> 0 | J94: =+ROUND(H94+I94*TC,2) -> 93258.6
A95: =A94+0.0001 -> 1.0802 | B95: ELIMINACIÓN MATERIAL DE DESMONTE, RESIDUOS, DURANTE LA OBRA | C95: m3 | D95: 2868 | E95: 39 | G95: =IFERROR(IF(D95=0,"",(E95+F95*TC)),"") -> 39 | H95: =+ROUND(D95*E95,2) -> 111852 | I95: =+ROUND(D95*F95,2) -> 0 | J95: =+ROUND(H95+I95*TC,2) -> 111852
A96: =A95+0.0001 -> 1.0803 | B96: ELIMINACIÓN MATERIAL DE DESMONTE, RESIDUOS CON CAJA ECOLOGICA (V= 8 M3), DURANTE LA OBRA | C96: vje | D96: 88 | E96: 550 | G96: =IFERROR(IF(D96=0,"",(E96+F96*TC)),"") -> 550 | H96: =+ROUND(D96*E96,2) -> 48400 | I96: =+ROUND(D96*F96,2) -> 0 | J96: =+ROUND(H96+I96*TC,2) -> 48400
A97: =A96+0.0001 -> 1.0804 | B97: CHUTE PARA ELIMINACION VERTICAL | C97: glb | D97: 1 | E97: 38029.48 | G97: =IFERROR(IF(D97=0,"",(E97+F97*TC)),"") -> 38029.48 | H97: =+ROUND(D97*E97,2) -> 38029.48 | I97: =+ROUND(D97*F97,2) -> 0 | J97: =+ROUND(H97+I97*TC,2) -> 38029.48
A98: =A97+0.0001 -> 1.0805 | B98: LIMPIEZA FINA DE DEPARTAMENTOS Y ZONAS COMUNES | C98: glb | D98: 1 | E98: 172725.56 | G98: =IFERROR(IF(D98=0,"",(E98+F98*TC)),"") -> 172725.56 | H98: =+ROUND(D98*E98,2) -> 172725.56 | I98: =+ROUND(D98*F98,2) -> 0 | J98: =+ROUND(H98+I98*TC,2) -> 172725.56
A99: =A98+0.0001 -> 1.0806 | B99: LIMPIEZA DE VIDRIOS FIJOS EXTERIORES | C99: m2 | G99: =IFERROR(IF(D99=0,"",(E99+F99*TC)),"") | H99: =+ROUND(D99*E99,2) -> 0 | I99: =+ROUND(D99*F99,2) -> 0 | J99: =+ROUND(H99+I99*TC,2) -> 0
A100: =A93+0.01 -> 1.09 | B100: SERVICIOS GENERAES - OTROS | F100: 0 | G100: =IFERROR(IF(D100=0,"",(E100+F100*TC)),"") | K100: =SUM(J102:J116) -> 379689.74
A101: =A100+0.0001 -> 1.0901 | B101: PROTECCION Y LIMPIEZA FINAL DE PISOS Y VENTANAS | G101: =IFERROR(IF(D101=0,"",(E101+F101*TC)),"")
A102: =A101+0.000001 -> 1.090101 | B102: PROTECCION CON CARTON Y PLASTICO (PISOS, TABLEROS, PCF) | C102: m2 | D102: 20240.361 | E102: 6.28 | G102: =IFERROR(IF(D102=0,"",(E102+F102*TC)),"") -> 6.28 | H102: =+ROUND(D102*E102,2) -> 127109.47 | I102: =+ROUND(D102*F102,2) -> 0 | J102: =+ROUND(H102+I102*TC,2) -> 127109.47
B103: PROTECCION DE VENTANA, MAMPARA Y BARANDA DE VIDRIOS (ES A COSTO DEL SUBCONTRATISTA) | C103: m2 | D103: 0 | G103: =IFERROR(IF(D103=0,"",(E103+F103*TC)),"") | H103: =+ROUND(D103*E103,2) -> 0 | I103: =+ROUND(D103*F103,2) -> 0 | J103: =+ROUND(H103+I103*TC,2) -> 0
B104: PLASTICO DE PROTECCION DE VENTANA, MAMPARA Y BARANDA DE VIDRIOS EXTERIORES, PARA EL TARRAJEO ( A COSTO DEL SUBCONTRATISTA) | C104: m2 | D104: 0 | G104: =IFERROR(IF(D104=0,"",(E104+F104*TC)),"") | H104: =+ROUND(D104*E104,2) -> 0 | I104: =+ROUND(D104*F104,2) -> 0 | J104: =+ROUND(H104+I104*TC,2) -> 0
A105: =A107+0.000001 -> 1.090202 | B105: PROTECCION DE BARANDAS DE FIERRO ESCALERAS Y FACHADAS | C105: ml | E105: 6.75 | G105: =IFERROR(IF(D105=0,"",(E105+F105*TC)),"") | H105: =+ROUND(D105*E105,2) -> 0 | I105: =+ROUND(D105*F105,2) -> 0 | J105: =+ROUND(H105+I105*TC,2) -> 0
...

Sheet GG
A2: Proyecto | B2: =+'RESUMEN ESCENARIO'!C6 -> PRESUPUESTO | GERMANIA | REV 09 | F2: Lugar | G2: =+'RESUMEN ESCENARIO'!C8 -> SURQUILLO
A3: Subpresupuesto | B3: Gastos Generales | F3: Fecha | G3: =+'RESUMEN ESCENARIO'!C9 -> 46090
A4: Cliente | B4: =+'RESUMEN ESCENARIO'!C7 -> VYV INMOBILIARIA
A6: GASTOS GENERALES
A9: ITEM | B9: DESCRIPCION | C9: UND | D9: CANTIDAD | E9: PRECIO | F9: PARCIAL | G9: Total
A10: 12 | B10: GASTOS GENERALES
A11: 12.01 | B11: PERSONAL STAFF | G11: =SUM(F12:F29) -> 2716500
A12: 12.01.01 | B12: Superintendente | C12: mes | D12: 6.9 | E12: 22500 | F12: =+D12*E12 -> 155250
A13: 12.01.02 | B13: Ingeniero Residente | C13: mes | D13: 24 | E13: 18750 | F13: =+D13*E13 -> 450000
A14: 12.01.03 | B14: Jefe de Oficina Técnica | C14: mes | D14: 24 | E14: 12000 | F14: =+D14*E14 -> 288000
A15: 12.01.04 | B15: Asistente de Oficina Técnica | C15: mes | D15: 17 | E15: 6750 | F15: =+D15*E15 -> 114750
A16: 12.01.05 | B16: Jefe de producción | C16: mes | D16: 17 | E16: 12000 | F16: =+D16*E16 -> 204000
A17: 12.01.06 | B17: Asistente de Producción | C17: mes | D17: 12 | E17: 6750 | F17: =+D17*E17 -> 81000
A18: 12.01.07 | B18: Ingeniero de Calidad | C18: mes | D18: 19 | E18: 9000 | F18: =+D18*E18 -> 171000
A19: 12.01.08 | B19: Asistente de Calidad | C19: mes | D19: 12 | E19: 6750 | F19: =+D19*E19 -> 81000
A20: 12.01.09 | B20: Ingeniero Electromecánico | C20: mes | D20: 19 | E20: 12000 | F20: =+D20*E20 -> 228000
A21: 12.01.11 | B21: Arquitecto de Acabados | C21: mes | D21: 15 | E21: 12000 | F21: =+D21*E21 -> 180000
A22: 12.01.12 | B22: Asistente de Acabados_1 | C22: mes | D22: 12 | E22: 6750 | F22: =+D22*E22 -> 81000
A23: 12.01.14 | B23: Prevencionista de Riesgos | C23: mes | D23: 23 | E23: 6750 | F23: =+D23*E23 -> 155250
... A27: 12.01.19 | B27: Asistente de Almacén | C27: mes | D27: 10 | E27: 5250 | F27: =+D27*E27 -> 52500
A30: 12.02 | B30: PERSONAL TECNICO | G30: =SUM(F31:F32) -> 287793.6
A31: 12.02.03 | B31: Maestro de Obra | C31: mes | D31: 16 | E31: 8097.1 | F31: =+D31*E31 -> 129553.6
A32: 12.02.11 | B32: Guardian de Obra | C32: mes | D32: 23 | E32: 6880 | F32: =+D32*E32 -> 158240
A34: 12.03 | B34: EQUIPO Y MOBILIARIO DE OFICINA | G34: =SUM(F35:F46) -> 145543.34
A35: 12.03.01 | B35: Computadora | C35: mes | D35: 23 | E35: 1078.4348 | F35: =+D35*E35 -> 24804
A36: 12.03.02 | B36: Celular | C36: und | D36: 23 | E36: 744.78261 | F36: =+D36*E36 -> 17130
A37: 12.03.03 | B37: Radio | C37: und | D37: 23 | E37: 685.32609 | F37: =+D37*E37 -> 15762.5
A38: 12.03.04 | B38: IMPRESORA A3 | C38: und | D38: 1 | E38: 2757 | F38: =+D38*E38 -> 2757
A39: 12.03.05 | B39: COMUNICACION TELEFONO EXTERNO / INTERNET | C39: und | D39: 24 | E39: 240 | F39: =+D39*E39 -> 5760
A40: 12.03.06 | B40: ESCRITORIOS Y SILLAS (CONTRATISTA) | C40: und | D40: 15 | E40: 250 | F40: =+D40*E40 -> 3750
A41: 12.03.07 | B41: MESAS DE TRABAJO Y DE REUNION | C41: und | D41: 1 | E41: 1000 | F41: =+D41*E41 -> 1000
A42: 12.03.08 | B42: UTILES DE OFICINA Y ECONOMATO | C42: glb | D42: 1 | E42: 7175 | F42: =+D42*E42 -> 7175
A43: 12.03.09 | B43: LICENCIA SOFWARE S10 | C43: glb | D43: 1 | E43: 17690.75 | F43: =+D43*E43 -> 17690.75
A44: 12.03.10 | B44: LICENCIA MS OFFICE 365 | C44: glb | D44: 1 | E44: 9794.4 | F44: =+D44*E44 -> 9794.4
A45: 12.03.11 | B45: LICENCIA AUTOCAD | C45: glb | D45: 1 | E45: 22772.75 | F45: =+D45*E45 -> 22772.75
A46: 12.03.12 | B46: LICENCIA REVIT | C46: glb | D46: 1 | E46: 17146.938 | F46: =+D46*E46 -> 17146.938
A48: 12.04 | B48: VARIOS | G48: =SUM(F49:F70) -> 610284.79
A49: 12.04.01 | B49: INSUMOS PARA LIMPIEZA | C49: mes | D49: 23 | E49: 250 | F49: =+D49*E49 -> 5750
A50: 12.04.02 | B50: PERSONAL DE LIMPIEZA (OFICINAS) | C50: mes | D50: 23 | E50: 967.5 | F50: =+D50*E50 -> 22252.5
A51: 12.04.03 | B51: FOTOCOPIADO | C51: mes | D51: 23 | E51: 300 | F51: =+D51*E51 -> 6900
A52: 12.04.04 | B52: COPIA DE PLANOS Y PLANOS DE REPLANTEO DE OBRA | C52: mes | D52: 23 | E52: 450 | F52: =+D52*E52 -> 10350
A53: 12.04.05 | B53: PLANOS Y EXPEDIENTE FIRMA DE CONTRATO (3 COPIAS) | C53: mes | D53: 1 | E53: 3600 | F53: =+D53*E53 -> 3600
A54: 12.04.06 | B54: DOSSIER DE CALIDAD | C54: glb | D54: 1 | E54: 5500 | F54: =+D54*E54 -> 5500
A55: 12.04.07 | B55: GASTOS ADMINISTRATIVOS | C55: mes | D55: 23 | E55: 500 | F55: =+D55*E55 -> 11500
A56: 12.04.08 | B56: AGUA POTABLE PARA PERSONAL | C56: mes | D56: 23 | E56: 588 | F56: =+D56*E56 -> 13524
A57: 12.04.09 | B57: BOTIQUIN DE OBRA | C57: mes | D57: 1 | E57: 600 | F57: =+D57*E57 -> 600
A58: 12.04.10 | B58: MANTENIMIENTO DE EQUIPOS PROPIO | C58: glb | D58: 1 | E58: 3000 | F58: =+D58*E58 -> 3000
A59: 12.04.11 | B59: MOVILIDAD | C59: mes | D59: 23 | E59: 500 | F59: =+D59*E59 -> 11500
A60: 12.04.12 | B60: CONTRIBUCION OFICINA CENTRAL | C60: mes | D60: 23 | E60: 20000 | F60: =+D60*E60 -> 460000
... A70: 12.02.14 | B70: Seguro de Vida Ley - Personal Obrero | C70: mes | D70: 67 | E70: 21.337643 | F70: =+D70*E70 -> 1429.622
A72: 12.05 | B72: PAZ SOCIAL | G72: =SUM(F73) -> 97545.76
A73: 12.05.01 | B73: POLICITY SECURITY | C73: mes | D73: 23 | E73: 4241.12 | F73: =+D73*E73 -> 97545.76
A75: 12.06 | B75: GASTOS ADMINISTRATIVOS Y FINANCIEROS | G75: =SUM(F76:F84) -> 144702.3
A76: 12.06.01 | B76: POLIZA CAR+RC | C76: glb | D76: 0 | E76: 92374.447 | F76: =+D76*E76 -> 0
A77: 12.06.02 | B77: POLIZA 3D | C77: glb | D77: 1 | E77: 2000 | F77: =+D77*E77 -> 2000
A78: 12.06.03 | B78: CARTA FIANZA POR ADELANTO | C78: mes | D78: 0 | E78: 27122.156 | F78: =+D78*E78 -> 0
A79: 12.06.04 | B79: CARTA FIANZA POR FIEL CUMPLIMIENTO | C79: mes | D79: 0 | E79: 18081.437 | F79: =+D79*E79 -> 0
A80: 12.06.05 | B80: CARTA FIANZA POR POST VENTA - 12 MESES (5%) | C80: mes | D80: 0 | E80: 9040.7187 | F80: =+D80*E80 -> 0
A81: 12.06.06 | B81: COSTO RETENCION FONDO GARANTIA 5 % | C81: mes | D81: 0 | E81: 9040.7187 | F81: =+D81*E81 -> 0
A82: 12.06.07 | B82: COSTO FINANCIERO DE CAPITAL DE TRABAJO | C82: glb | D82: 1 | E82: 16500 | F82: =+D82*E82 -> 16500
A83: 12.06.08 | B83: GASTOS FINANCIEROS - ITF - 0.005% | C83: glb | D83: 1 | E83: 3616.2875 | F83: =+D83*E83 -> 3616.2875
A84: 12.06.09 | B84: SENCICO | C84: glb | D84: 1 | E84: 122586.02 | F84: =+D84*E84 -> 122586.02
G86: =SUM(G11:G85) -> 4002369.8
A89: 12.05 | B89: PAZ SOCIAL | G89: =SUM(F90) -> 218500
A90: 12.05.01 | B90: POLICITY SECURITY | C90: mes | D90: 23 | E90: 9500 | F90: =+D90*E90 -> 218500

Sheet Est Sotano 
C3: ESTRUCTURAS SOTANOS
C5: Presupuesto: | D5: =+'RESUMEN ESCENARIO'!C6 -> PRESUPUESTO | GERMANIA | REV 09
C6: Subpresupuesto: | D6: =+C3 -> ESTRUCTURAS SOTANOS
C7: Cliente: | D7: =+'RESUMEN ESCENARIO'!C7 -> VYV INMOBILIARIA
C8: Lugar: | D8: =+'RESUMEN ESCENARIO'!C8 -> SURQUILLO
C10: ITEM | D10: DESCRIPCION | E10: UND | F10: CANTIDAD | G10: CANTIDAD | H10: P.U. (PEN) | I10: P.U. (USD) | J10: P.U. TOTAL (PEN) | K10: PRECIO PARCIAL (PEN) | L10: PRECIO PARCIAL (USD) | M10: PARCIAL TOTAL (PEN) | N10: TOTAL
C11: 02 | D11: ESTRUCTURAS SÓTANO
C12: 02.01 | D12: OBRAS PRELIMINARES MOVIMIENTOS DE TIERRA | N12: =SUM(K12:K20)+SUM(L12:L20)*TC -> 134326.52
C13: 02.01.01 | D13: MOVILIZACION Y DESMOVILIZACION DE EQUIPOS MOVIMIENTO TIERRAS | E13: glb | F13: 1 | G13: 1 | H13: 21000 | I13: 0 | J13: =+ROUND(H13+I13*TC,2) -> 21000 | K13: =H13*G13 -> 21000 | L13: =I13*G13 -> 0 | M13: =+ROUND(K13+L13*TC,2) -> 21000
C14: 02.01.02 | D14: EXTRACCION DE EQUIPOS MOVIMIENTO TIERRAS | E14: glb | F14: 1 | G14: 1 | H14: 26000 | I14: 0 | J14: =+ROUND(H14+I14*TC,2) -> 26000 | K14: =H14*G14 -> 26000 | L14: =I14*G14 -> 0 | M14: =+ROUND(K14+L14*TC,2) -> 26000
C15: 02.01.03 | D15: INSTALACION Y DESISTALACION DE PLATAFORMA | E15: glb | F15: 1 | G15: 1 | H15: 25000 | I15: 0 | J15: =+ROUND(H15+I15*TC,2) -> 25000 | K15: =H15*G15 -> 25000 | L15: =I15*G15 -> 0 | M15: =+ROUND(K15+L15*TC,2) -> 25000
C16: 02.01.04 | D16: EXTRACCION DE EQUIPOS PERFORACION CON GRUAS | E16: glb | F16: 4 | G16: 4 | I16: 720 | J16: =+ROUND(H16+I16*TC,2) -> 2412 | K16: =H16*G16 -> 0 | L16: =I16*G16 -> 2880 | M16: =+ROUND(K16+L16*TC,2) -> 9648
C17: 02.01.05 | D17: Control de polvo durante la excavación masiva. | E17: und | F17: 8 | G17: 8 | H17: 584.81554 | I17: 0 | J17: =+ROUND(H17+I17*TC,2) -> 584.82 | K17: =H17*G17 -> 4678.5243 | L17: =I17*G17 -> 0 | M17: =+ROUND(K17+L17*TC,2) -> 4678.52
D18: Biombo para eliminación en la via pública | E18: glb | F18: 1 | G18: 1 | H18: 4000 | I18: 0 | J18: =+ROUND(H18+I18*TC,2) -> 4000 | K18: =H18*G18 -> 4000 | L18: =I18*G18 -> 0 | M18: =+ROUND(K18+L18*TC,2) -> 4000
D19: Movilización y Desmovilización de Excavadora sobre orugas o neumática para el Proceso de Pasamanos | E19: glb | F19: 1 | G19: 1 | H19: 20000 | I19: 0 | J19: =+ROUND(H19+I19*TC,2) -> 20000 | K19: =H19*G19 -> 20000 | L19: =I19*G19 -> 0 | M19: =+ROUND(K19+L19*TC,2) -> 20000
D20: Movilización y Desmovilizacion de plataforma + escuadras para eliminacion (incluye montaje y desmontaje) | E20: glb | F20: 2 | G20: 2 | H20: 12000 | I20: 0 | J20: =+ROUND(H20+I20*TC,2) -> 12000 | K20: =H20*G20 -> 24000 | L20: =I20*G20 -> 0 | M20: =+ROUND(K20+L20*TC,2) -> 24000
C21: 02.02 | D21: MOVIMIENTO DE TIERRAS | G21: 0 | N21: =SUM(K21:K31)+SUM(L21:L31)*TC -> 1021804
C22: 02.02.01 | D22: EXCAVACIÓN Y ELIMINACION MASIVA POR NIVEL | G22: 0
C23: 02.02.01.01 | D23: Excavacion Masiva y Eliminación del Sótano 01 c/01 Excavadora por Rampa (Material contaminado) (botadero autorizado | E23: m3 | F23: 2000 | G23: 2000 | H23: 37.68 | I23: 0 | J23: =+ROUND(H23+I23*TC,2) -> 37.68 | K23: =H23*G23 -> 75360 | L23: =I23*G23 -> 0 | M23: =+ROUND(K23+L23*TC,2) -> 75360
D24: Excavacion Masiva y Eliminación del Sótano 01 c/01 Excavadora por Rampa (de -0.00 a -3.45 ) | F24: 2329.44 | G24: 2329.44 | H24: 27.68 | J24: =+ROUND(H24+I24*TC,2) -> 27.68 | K24: =H24*G24 -> 64478.899 | L24: =I24*G24 -> 0 | M24: =+ROUND(K24+L24*TC,2) -> 64478.9
C25: 02.02.01.03 | D25: Excavacion Masiva y Eliminación del Sótano 02 c/02 Excavadoras por Rampa (de -3.45 a -6.30) | E25: m3 | F25: 3576.47 | G25: 3576.47 | H25: 27.68 | I25: 0 | J25: =+ROUND(H25+I25*TC,2) -> 27.68 | K25: =H25*G25 -> 98996.69 | L25: =I25*G25 -> 0 | M25: =+ROUND(K25+L25*TC,2) -> 98996.69
C26: 02.02.01.04 | D26: Excavacion Masiva y Eliminación del Sótano 03 c/03 Excavadoras por Rampa y Pasamanos (de -6.30 a -9.15) | E26: m3 | F26: 3576.47 | G26: 3576.47 | H26: 27.68 | I26: 0 | J26: =+ROUND(H26+I26*TC,2) -> 27.68 | K26: =H26*G26 -> 98996.69 | L26: =I26*G26 -> 0 | M26: =+ROUND(K26+L26*TC,2) -> 98996.69
C27: 02.02.01.05 | D27: Excavacion Masiva y Eliminación del sótano 04 c/03 Excavadoras por plataforma + Pasamanos (de -9.15 a -12.00) | E27: m3 | F27: 3576.47 | G27: 3576.47 | H27: 32.68 | I27: 0 | J27: =+ROUND(H27+I27*TC,2) -> 32.68 | K27: =H27*G27 -> 116879.04 | L27: =I27*G27 -> 0 | M27: =+ROUND(K27+L27*TC,2) -> 116879.04
C28: 02.02.01.06 | D28: Excavacion Masiva y Eliminación del sótano 05 c/03 Excavadoras por plataforma + Pasamanos (de -12.00 a -14.85) | E28: m3 | F28: 3576.47 | G28: 3576.47 | H28: 32.68 | I28: 0 | J28: =+ROUND(H28+I28*TC,2) -> 32.68 | K28: =H28*G28 -> 116879.04 | L28: =I28*G28 -> 0 | M28: =+ROUND(K28+L28*TC,2) -> 116879.04
C29: 02.02.01.07 | D29: Excavacion Masiva y Eliminación del sótano 06 c/02 Excavadoras + Grúa Telescópica + balde (de -14.85 a -18.00) | E29: m3 | F29: 3952.95 | G29: 3952.95 | H29: 47.68 | I29: 0 | J29: =+ROUND(H29+I29*TC,2) -> 47.68 | K29: =H29*G29 -> 188476.66 | L29: =I29*G29 -> 0 | M29: =+ROUND(K29+L29*TC,2) -> 188476.66
C30: 02.02.01.09 | D30: Excavacion Masiva y Eliminación del sótano 07 c/02 Excavadoras + Grúa Telescópica + balde (de -18.00 a -19.80) + cisterna -22.82 | E30: m3 | F30: 5489.45 | G30: 5489.45 | H30: 47.68 | I30: 0 | J30: =+ROUND(H30+I30*TC,2) -> 47.68 | K30: =H30*G30 -> 261736.98 | L30: =I30*G30 -> 0 | M30: =+ROUND(K30+L30*TC,2) -> 261736.98
C31: 02.02.01.09 | D31: Excavacion de cisternas y cuarto de bombas (N -23.00) | E31: m3 | F31: 0 | G31: 0 | H31: 0 | I31: 0 | J31: =+ROUND(H31+I31*TC,2) -> 0 | K31: =H31*G31 -> 0 | L31: =I31*G31 -> 0 | M31: =+ROUND(K31+L31*TC,2) -> 0
C32: 02.02.02 | D32: EXCAVACIÓN LOCALIZADA | G32: 0 | H32: 0 | N32: =SUM(K32:K37)+SUM(L32:L37)*TC -> 58723.976
C33: 02.02.02.01 | D33: EXCAVACION Y ELIIMINACION DE ZAPATAS, CIMIENTOS DE MURO ANCLADO CON BALDE Y GRUA | E33: m3 | F33: 1114.73 | G33: 1114.73 | H33: 52.68 | I33: 0 | J33: =+ROUND(H33+I33*TC,2) -> 52.68 | K33: =H33*G33 -> 58723.976 | L33: =I33*G33 -> 0 | M33: =+ROUND(K33+L33*TC,2) -> 58723.98
C34: 02.02.02.02 | D34: EXCAVACION LOCALIZADA PARA VIGAS DE CIMENTACION | E34: m3 | G34: 0 | H34: 41.73 | I34: 0
C35: 02.02.02.01 | D35: EXCAVACION LOCALIZADA PARA PAÑO DE MUROS ANCLADOS BAJO LA LINEA DE TALUD (SEGÚN GRAFICO DEL 29/11 POR CORREO) | E35: m3 | G35: 0 | H35: 35 | I35: 0 | J35: =+ROUND(H35+I35*TC,2) -> 35 | K35: =H35*G35 -> 0 | L35: =I35*G35 -> 0 | M35: =+ROUND(K35+L35*TC,2) -> 0
C36: 02.02.02.03 | D36: EXCAVACION MANUAL PARA CIMIENTOS DE TABIQUES (BATEA DE CIMENTACION) | E36: m3 | G36: 0 | H36: 41.73 | I36: 0 | J36: =+ROUND(H36+I36*TC,2) -> 41.73 | K36: =H36*G36 -> 0 | L36: =I36*G36 -> 0 | M36: =+ROUND(K36+L36*TC,2) -> 0
C37: 02.02.02.03 | D37: EXCAVACION MANUAL PARA CALZADURA FALSA ZAPATA | E37: m3 | G37: 0 | H37: 62.59 | I37: 0 | J37: =+ROUND(H37+I37*TC,2) -> 62.59 | K37: =H37*G37 -> 0 | L37: =I37*G37 -> 0 | M37: =+ROUND(K37+L37*TC,2) -> 0
C38: 02.02.03 | D38: RELLENO Y COMPACTACIÓN | G38: 0 | N38: =SUM(K38:K40)+SUM(L38:L40)*TC -> 78165.476
C39: 02.02.03.01 | D39: RELLENO COMPACTADO CON MATERIAL PROPIO | E39: m3 | F39: 1605.7 | G39: 1605.7 | H39: 48.68 | I39: 0 | J39: =+ROUND(H39+I39*TC,2) -> 48.68 | K39: =H39*G39 -> 78165.476 | L39: =I39*G39 -> 0 | M39: =+ROUND(K39+L39*TC,2) -> 78165.48
C40: 02.02.02.01 | D40: RELLENO COMPACTADO CON MATERIAL PROPIO | E40: m3 | G40: 0 | H40: 43.91 | I40: 0 | J40: =+ROUND(H40+I40*TC,2) -> 43.91 | K40: =H40*G40 -> 0 | L40: =I40*G40 -> 0 | M40: =+ROUND(K40+L40*TC,2) -> 0
C41: 02.02.04 | D41: NIVELACION, APISONADO Y BASE DE AFIRMADO | G41: 0 | N41: =SUM(K41:K44)+SUM(L41:L44)*TC -> 83028.398
C42: 02.02.04.01 | D42: NIVELACION Y COMPACTACION DE SUBRASANTE | E42: m2 | F42: 1235.05 | G42: 1235.05 | H42: 10.68 | I42: 0 | J42: =+ROUND(H42+I42*TC,2) -> 10.68 | K42: =H42*G42 -> 13190.334 | L42: =I42*G42 -> 0 | M42: =+ROUND(K42+L42*TC,2) -> 13190.33
C43: 02.02.04.02 | D43: SUB BASE DE AFIRMADO COMPACTADO, e= 25 cm | E43: m2 | F43: 1235.05 | G43: 1235.05 | H43: 33.68 | I43: 0 | J43: =+ROUND(H43+I43*TC,2) -> 33.68 | K43: =H43*G43 -> 41596.484 | L43: =I43*G43 -> 0 | M43: =+ROUND(K43+L43*TC,2) -> 41596.48
C44: 02.02.04.03 | D44: BASE DE AFIRMADO COMPACTADO, E=15CM (conforme a EMS) | E44: m2 | F44: 1099.75 | G44: 1099.75 | H44: 25.68 | I44: 0 | J44: =+ROUND(H44+I44*TC,2) -> 25.68 | K44: =H44*G44 -> 28241.58 | L44: =I44*G44 -> 0 | M44: =+ROUND(K44+L44*TC,2) -> 28241.58
C45: 02.02.05 | D45: ELIMINACIÓN DE MATERIAL EXCEDENTE | G45: 0
C46: 02.02.05.01 | D46: ELIMINACION DE MATERIAL EXCEDENTE EN CISTERNA | E46: m3 | G46: 0 | H46: 0 | I46: 0 | J46: =+ROUND(H46+I46*TC,2) -> 0 | K46: =H46*G46 -> 0 | L46: =I46*G46 -> 0 | M46: =+ROUND(K46+L46*TC,2) -> 0
C47: 02.02.05.02 | D47: ACARREO Y ELIMINACION DE MATERIAL EXCEDENTE | E47: m3 | G47: 0 | H47: 38.98 | I47: 0 | J47: =+ROUND(H47+I47*TC,2) -> 38.98 | K47: =H47*G47 -> 0 | L47: =I47*G47 -> 0 | M47: =+ROUND(K47+L47*TC,2) -> 0
C48: 02.02.06 | D48: SACAR CIMENTACION DE PARED PERIMETRICA | G48: 0 | N48: =SUM(K48:K50)+SUM(L48:L50)*TC -> 26000
C49: 02.02.06.01 | D49: Demolición y eliminación de cimentación colindate a propiedad de terceros | E49: ml | F49: 147.8 | G49: 147.8 | H49: 175.9134 | I49: 0 | J49: =+ROUND(H49+I49*TC,2) -> 175.91 | K49: =H49*G49 -> 26000 | L49: =I49*G49 -> 0 | M49: =+ROUND(K49+L49*TC,2) -> 26000
C50: 02.02.06.02 | D50: Eliminacion de cimentacion | E50: m3 | F50: 0 | G50: 0 | H50: 49.654149 | I50: 0 | J50: =+ROUND(H50+I50*TC,2) -> 49.65 | K50: =H50*G50 -> 0 | L50: =I50*G50 -> 0 | M50: =+ROUND(K50+L50*TC,2) -> 0
C51: 02.02.07 | D51: ESTABILIZACION DE TALUD | G51: 0
C52: 02.02.07.01 | D52: ESTABILIZACION DE TALUD | E52: m2 | G52: 0 | H52: 0 | I52: 0 | J52: =+ROUND(H52+I52*TC,2) -> 0 | K52: =H52*G52 -> 0 | L52: =I52*G52 -> 0 | M52: =+ROUND(K52+L52*TC,2) -> 0
C53: 02.02.08 | D53: OTROS | G53: 0 | N53: =SUM(K53:K56)+SUM(L53:L56)*TC -> 185500
C54: 02.02.08.01 | D54: ALQUILER DE EXCAVADORA PARA EXCAV. MURO PANTALLA | E54: hm | F54: 700 | G54: 700 | H54: 175 | I54: 0 | J54: =+ROUND(H54+I54*TC,2) -> 175 | K54: =H54*G54 -> 122500 | L54: =I54*G54 -> 0 | M54: =+ROUND(K54+L54*TC,2) -> 122500
C55: 02.02.08.02 | D55: 2 Vigias para maquina excavadora durante la excavación | E55: mes | F55: 7 | G55: 7 | H55: 4000 | I55: 0 | J55: =+ROUND(H55+I55*TC,2) -> 4000 | K55: =H55*G55 -> 28000 | L55: =I55*G55 -> 0 | M55: =+ROUND(K55+L55*TC,2) -> 28000
C56: 02.02.08.03 | D56: Prevención de seguridad (Ssoma) | E56: mes | F56: 7 | G56: 7 | H56: 5000 | I56: 0 | J56: =+ROUND(H56+I56*TC,2) -> 5000 | K56: =H56*G56 -> 35000 | L56: =I56*G56 -> 0 | M56: =+ROUND(K56+L56*TC,2) -> 35000
C57: 02.03 | D57: CONCRETO SIMPLE | G57: 0 | N57: =SUM(K57:K62)+SUM(L57:L62)*TC -> 88824.773
C58: 02.03.01 | D58: SOLADOS | G58: 0
C59: 02.03.01.01 | D59: CONCRETO PREMEZCLADO, CEMENTO TIPO I, SOLADO f'c=100 kg/cm2 | E59: m2 | F59: 664.697 | G59: 664.7 | H59: 29.93 | I59: 0 | J59: =+ROUND(H59+I59*TC,2) -> 29.93 | K59: =H59*G59 -> 19894.471 | L59: =I59*G59 -> 0 | M59: =+ROUND(K59+L59*TC,2) -> 19894.47
C60: 02.03.02 | D60: SUBZAPATAS | G60: 0
C61: 02.03.02.01 | D61: CONCRETO PREMEZCLADO, CEMENTO TIPO I, FALZA ZAPATAS 1:12 + 40%P.G. | E61: m3 | F61: 184.37718 | G61: 184.38 | H61: 283.36 | I61: 0 | J61: =+ROUND(H61+I61*TC,2) -> 283.36 | K61: =H61*G61 -> 52245.917 | L61: =I61*G61 -> 0 | M61: =+ROUND(K61+L61*TC,2) -> 52245.92
C62: 02.03.02.02 | D62: ENCOFRADO EN SUBZAPATAS | E62: m2 | F62: 374.9337 | G62: 374.93 | H62: 44.5 | I62: 0 | J62: =+ROUND(H62+I62*TC,2) -> 44.5 | K62: =H62*G62 -> 16684.385 | L62: =I62*G62 -> 0 | M62: =+ROUND(K62+L62*TC,2) -> 16684.39
C63: 02.04 | D63: CONCRETO ARMADO | G63: 0 | N63: =SUM(K63:K95)+SUM(L63:L95)*TC -> 1593769.3
C64: 02.04.01 | D64: CIMIENTOS ARMADOS DE MURO ANCLADO | G64: 0
C65: 02.04.01.01 | D65: CONCRETO PREMEZCLADO, CEMENTO TIPO I, CIMIENTOS REFORZADOS f'c=280 kg/cm2 | E65: m3 | F65: 170.34432 | G65: 170.34 | H65: 520.68 | I65: 0 | J65: =+ROUND(H65+I65*TC,2) -> 520.68 | K65: =H65*G65 -> 88692.631 | L65: =I65*G65 -> 0 | M65: =+ROUND(K65+L65*TC,2) -> 88692.63
C66: 02.04.01.02 | D66: ENCOFRADO Y DESENCOFRADO PARA CIMIENTOS REFORZADOS | E66: m2 | F66: 149.149 | G66: 149.15 | H66: 46.5 | I66: 0 | J66: =+ROUND(H66+I66*TC,2) -> 46.5 | K66: =H66*G66 -> 6935.475 | L66: =I66*G66 -> 0 | M66: =+ROUND(K66+L66*TC,2) -> 6935.48
C67: 02.04.01.03 | D67: ACERO DE REFUERZO FY= 4200 kg/cm2, GRADO 60 | E67: kg | F67: 10207.834 | G67: 10207.83 | H67: 1.28 | I67: 0.89 | J67: =+ROUND(H67+I67*TC,2) -> 4.26 | K67: =H67*G67 -> 13066.022 | L67: =I67*G67 -> 9084.9687 | M67: =+ROUND(K67+L67*TC,2) -> 43500.67
C68: 02.04.01.04 | D68: CURADO DE ELEMENTOS ESTRUCTURALES EXPUESTOS | E68: m2 | F68: 336.304 | G68: 336.3 | H68: 1.48 | I68: 0 | J68: =+ROUND(H68+I68*TC,2) -> 1.48 | K68: =H68*G68 -> 497.724 | L68: =I68*G68 -> 0 | M68: =+ROUND(K68+L68*TC,2) -> 497.72
C69: 02.04.01.05 | D69: PINTURA ASFALTICA EN CIMENTACIONES | E69: m2 | F69: 156.60645 | G69: 156.61 | H69: 20.45 | I69: 0 | J69: =+ROUND(H69+I69*TC,2) -> 20.45 | K69: =H69*G69 -> 3202.6745 | L69: =I69*G69 -> 0 | M69: =+ROUND(K69+L69*TC,2) -> 3202.67
C70: 02.04.02 | D70: MURO PANTALLA (ANCLADO) | G70: 0
C71: 02.04.02.01 | D71: CONCRETO PREMEZCLADO, CEMENTO TIPO I, MURO PANTALLA f'c=350 kg/cm2 | E71: m3 | F71: 999.52312 | G71: 999.52 | H71: 609.91 | I71: 0 | J71: =+ROUND(H71+I71*TC,2) -> 609.91 | K71: =H71*G71 -> 609617.24 | L71: =I71*G71 -> 0 | M71: =+ROUND(K71+L71*TC,2) -> 609617.24
C72: 02.04.02.02 | D72: CONCRETO PREMEZCLADO, CEMENTO TIPO I, MURO PANTALLA f'c=420 kg/cm2 | E72: m3 | G72: 0 | H72: 658.88 | I72: 0 | J72: =+ROUND(H72+I72*TC,2) -> 658.88 | K72: =H72*G72 -> 0 | L72: =I72*G72 -> 0 | M72: =+ROUND(K72+L72*TC,2) -> 0
C73: 02.04.02.03 | D73: CONCRETO PREMEZCLADO, CEMENTO TIPO I, MURO PANTALLA f'c=350 kg/cm2 | E73: m3 | G73: 0 | H73: 609.91 | I73: 0 | J73: =+ROUND(H73+I73*TC,2) -> 609.91 | K73: =H73*G73 -> 0 | L73: =I73*G73 -> 0 | M73: =+ROUND(K73+L73*TC,2) -> 0
C74: 02.04.02.04 | D74: ENCOFRADO Y DESENCOFRADO PARA MURO PANTALLA | E74: m2 | F74: 2952.9257 | G74: 2952.93 | H74: 61.95 | I74: 0 | J74: =+ROUND(H74+I74*TC,2) -> 61.95 | K74: =H74*G74 -> 182934.01 | L74: =I74*G74 -> 0 | M74: =+ROUND(K74+L74*TC,2) -> 182934.01
C75: 02.04.02.05 | D75: ENCOFRADO Y DESENCOFRADO PARA MURO PANTALLA | E75: m2 | F75: 389.792 | G75: 389.79 | H75: 60 | I75: 0 | J75: =+ROUND(H75+I75*TC,2) -> 60 | K75: =H75*G75 -> 23387.4 | L75: =I75*G75 -> 0 | M75: =+ROUND(K75+L75*TC,2) -> 23387.4
C76: 02.04.02.06 | D76: ACERO DE REFUERZO FY= 4200 kg/cm2, GRADO 60 (MURO PANTALLA) | E76: kg | F76: 76173.291 | G76: 76173.29 | H76: 1.28 | I76: 0.89 | J76: =+ROUND(H76+I76*TC,2) -> 4.26 | K76: =H76*G76 -> 97501.811 | L76: =I76*G76 -> 67794.228 | M76: =+ROUND(K76+L76*TC,2) -> 324612.48
C77: 02.04.02.06 | D77: ACERO DE REFUERZO FY= 4200 kg/cm2, GRADO 60 | E77: kg | G77: 0 | H77: 1.24 | I77: 0.89 | J77: =+ROUND(H77+I77*TC,2) -> 4.22 | K77: =H77*G77 -> 0 | L77: =I77*G77 -> 0 | M77: =+ROUND(K77+L77*TC,2) -> 0
C78: 02.04.02.07 | D78: RECARGO POR CONSUMO MINIMO DE BOMBA | E78: m3 | F78: 745 | G78: 745 | H78: 41 | I78: 0 | J78: =+ROUND(H78+I78*TC,2) -> 41 | K78: =H78*G78 -> 30545 | L78: =I78*G78 -> 0 | M78: =+ROUND(K78+L78*TC,2) -> 30545
C79: 02.04.02.08 | D79: CONCRETO PREMEZCLADO, CEMENTO TIPO I, EN CACHIMBAS f'c=350 kg/cm2 | E79: m3 | F79: 23.3632 | G79: 23.36 | H79: 501.31 | I79: 0 | J79: =+ROUND(H79+I79*TC,2) -> 501.31 | K79: =H79*G79 -> 11710.602 | L79: =I79*G79 -> 0 | M79: =+ROUND(K79+L79*TC,2) -> 11710.6
C80: 02.04.02.09 | D80: ENCOFRADO Y DESENCOFRADO DE CACHIMBAS | E80: m2 | F80: 292.04 | G80: 292.04 | H80: 51.48 | I80: 0 | J80: =+ROUND(H80+I80*TC,2) -> 51.48 | K80: =H80*G80 -> 15034.219 | L80: =I80*G80 -> 0 | M80: =+ROUND(K80+L80*TC,2) -> 15034.22
C81: 02.04.02.11 | D81: PICADO DE CACHIMBAS DE MURO PANTALLA | E81: m3 | F81: 0 | G81: 0 | H81: 110.18 | I81: 0 | J81: =+ROUND(H81+I81*TC,2) -> 110.18 | K81: =H81*G81 -> 0 | L81: =I81*G81 -> 0 | M81: =+ROUND(K81+L81*TC,2) -> 0
C82: 02.04.02.11 | D82: PICADO DE PESTAÑAS DE ORIFICIO DE ANCLAJE | E82: und | F82: 172 | G82: 172 | H82: 36.44 | I82: 0 | J82: =+ROUND(H82+I82*TC,2) -> 36.44 | K82: =H82*G82 -> 6267.68 | L82: =I82*G82 -> 0 | M82: =+ROUND(K82+L82*TC,2) -> 6267.68
C83: 02.04.02.12 | D83: TECNOPOR EN ENCUENTRO DE LOSAS CON MURO PANTALLA | E83: ml | F83: 550.83 | G83: 550.83 | H83: 11.02 | I83: 0 | J83: =+ROUND(H83+I83*TC,2) -> 11.02 | K83: =H83*G83 -> 6070.1466 | L83: =I83*G83 -> 0 | M83: =+ROUND(K83+L83*TC,2) -> 6070.15
C84: 02.04.02.13 | D84: RETIRO DE TECNOPOR Y ESCARIFICADO EN ENCUENTRO DE LOSAS CON MURO PANTALLA | E84: ml | F84: 550.83 | G84: 550.83 | H84: 8.16 | I84: 0 | J84: =+ROUND(H84+I84*TC,2) -> 8.16 | K84: =H84*G84 -> 4494.7728 | L84: =I84*G84 -> 0 | M84: =+ROUND(K84+L84*TC,2) -> 4494.77
C85: 02.04.02.14 | D85: EPOXICO DE UNION Y ESCARIFICADO ENTRE LOSAS DE TECHO DE SOTANOS Y MURO PANTALLA | E85: ml | F85: 550.83 | G85: 550.83 | H85: 45.94 | I85: 0 | J85: =+ROUND(H85+I85*TC,2) -> 45.94 | K85: =H85*G85 -> 25305.13 | L85: =I85*G85 -> 0 | M85: =+ROUND(K85+L85*TC,2) -> 25305.13
C86: 02.04.02.18 | D86: TECNOPOR EN ENCUENTRO DE VIGAS CON MURO PANTALLA | E86: ml | F86: 86 | G86: 86 | H86: 11.02 | I86: 0 | J86: =+ROUND(H86+I86*TC,2) -> 11.02 | K86: =H86*G86 -> 947.72 | L86: =I86*G86 -> 0 | M86: =+ROUND(K86+L86*TC,2) -> 947.72
C87: 02.04.02.19 | D87: RETIRO DE TECNOPORT EN ENCUENTRO DE COLUMNAS CON MURO PANTALLA | E87: ml | F87: 86 | G87: 86 | H87: 8.16 | I87: 0 | J87: =+ROUND(H87+I87*TC,2) -> 8.16 | K87: =H87*G87 -> 701.76 | L87: =I87*G87 -> 0 | M87: =+ROUND(K87+L87*TC,2) -> 701.76
C88: 02.04.02.20 | D88: EPOXICO DE UNION ENTRE COLUMNAS CON MURO PANTALLA | E88: ml | F88: 86 | G88: 86 | H88: 45.94 | I88: 0 | J88: =+ROUND(H88+I88*TC,2) -> 45.94 | K88: =H88*G88 -> 3950.84 | L88: =I88*G88 -> 0 | M88: =+ROUND(K88+L88*TC,2) -> 3950.84
C89: 02.04.02.21 | D89: PERFILADO DE BANQUETAS Y TALUDES | E89: m2 | F89: 2952.9257 | G89: 2952.93 | H89: 7.5 | I89: 0 | J89: =+ROUND(H89+I89*TC,2) -> 7.5 | K89: =H89*G89 -> 22146.975 | L89: =I89*G89 -> 0 | M89: =+ROUND(K89+L89*TC,2) -> 22146.98
... C95: 02.04.02.27 | D95: CURADO DE ELEMENTOS ESTRUCTURALES EXPUESTOS | E95: m2 | F95: 2952.9257 | G95: 2952.93 | H95: 1.48 | I95: 0 | J95: =+ROUND(H95+I95*TC,2) -> 1.48 | K95: =H95*G95 -> 4370.3364 | L95: =I95*G95 -> 0 | M95: =+ROUND(K95+L95*TC,2) -> 4370.34
C96: 02.04.03 | D96: ANCLAJES DE MURO PANTALLA | G96: 0 | N96: =SUM(K96:K100)+SUM(L96:L100)*TC -> 654526.22
C97: 02.04.03.01 | D97: MOVILIZACIÓN Y DESMOVILIZACIÓN DE ANCLAJES | E97: glb | F97: 1 | G97: 1 | I97: 4000 | J97: =+ROUND(H97+I97*TC,2) -> 13400 | K97: =H97*G97 -> 0 | L97: =I97*G97 -> 4000 | M97: =+ROUND(K97+L97*TC,2) -> 13400
C98: 02.04.03.02 | D98: ANCLAJES POSTENSADOS SC | E98: und | F98: 172 | G98: 172 | I98: 1112.68 | J98: =+ROUND(H98+I98*TC,2) -> 3727.48 | K98: =H98*G98 -> 0 | L98: =I98*G98 -> 191380.96 | M98: =+ROUND(K98+L98*TC,2) -> 641126.22
C99: 02.04.03.02 | D99: TENSADO DE ANCLAJES | E99: und | F99: 0 | G99: 0 | H99: 0 | I99: 0 | J99: =+ROUND(H99+I99*TC,2) -> 0 | K99: =H99*G99 -> 0 | L99: =I99*G99 -> 0 | M99: =+ROUND(K99+L99*TC,2) -> 0
C100: 02.04.03.02 | D100: CAMBIO DE INGENIERÍA | E100: glb | F100: 0 | G100: 0 | H100: 5500 | I100: 0 | J100: =+ROUND(H100+I100*TC,2) -> 5500 | K100: =H100*G100 -> 0 | L100: =I100*G100 -> 0 | M100: =+ROUND(K100+L100*TC,2) -> 0
C101: 02.04.04 | D101: MURO PERIMETRAL (SIN ANCLAJES) | G101: 0 | J101: =+ROUND(H101+I101*TC,2) -> 0 | K101: =H101*G101 -> 0 | L101: =I101*G101 -> 0 | M101: =+ROUND(K101+L101*TC,2) -> 0 | N101: =SUM(K101:K108)+SUM(L101:L108)*TC -> 0
C102: 02.04.04.01 | D102: CONCRETO PREMEZCLADO, CEMENTO TIPO I, MURO PERIMETRAL f'c=280 kg/cm2 | E102: m3 | G102: 0 | H102: 495.48 | J102: =+ROUND(H102+I102*TC,2) -> 495.48 | K102: =H102*G102 -> 0 | L102: =I102*G102 -> 0 | M102: =+ROUND(K102+L102*TC,2) -> 0
C103: 02.04.04.01 | D103: CONCRETO PREMEZCLADO, CEMENTO TIPO I, MURO PERIMETRAL f'c=420 kg/cm2 | E103: m3 | G103: 0 | H103: 555.87 | J103: =+ROUND(H103+I103*TC,2) -> 555.87 | K103: =H103*G103 -> 0 | L103: =I103*G103 -> 0 | M103: =+ROUND(K103+L103*TC,2) -> 0
C104: 02.04.04.02 | D104: ENCOFRADO Y DESENCOFRADO MURO UNA CARA | E104: m2 | G104: 0 | H104: 55.75 | J104: =+ROUND(H104+I104*TC,2) -> 55.75 | K104: =H104*G104 -> 0 | L104: =I104*G104 -> 0 | M104: =+ROUND(K104+L104*TC,2) -> 0
C105: 02.04.04.03 | D105: ENCOFRADO Y DESENCOFRADO MURO UNA CARA A DOBLE ALTURA | E105: m2 | G105: 0 | H105: 0 | J105: =+ROUND(H105+I105*TC,2) -> 0 | K105: =H105*G105 -> 0 | L105: =I105*G105 -> 0 | M105: =+ROUND(K105+L105*TC,2) -> 0
C106: 02.04.04.04 | D106: PLASTICO CONTRA TERRENENO | E106: m2 | G106: 0 | H106: 5.52 | J106: =+ROUND(H106+I106*TC,2) -> 5.52 | K106: =H106*G106 -> 0 | L106: =I106*G106 -> 0 | M106: =+ROUND(K106+L106*TC,2) -> 0
C107: 02.04.04.05 | D107: ACERO DE REFUERZO FY= 4200 kg/cm2, GRADO 60 (MURO PANTALLA) | E107: kg | G107: 0 | H107: 1.28 | I107: 0.89 | J107: =+ROUND(H107+I107*TC,2) -> 4.26 | K107: =H107*G107 -> 0 | L107: =I107*G107 -> 0 | M107: =+ROUND(K107+L107*TC,2) -> 0
C108: 02.04.04.06 | D108: CURADO DE ELEMENTOS ESTRUCTURALES EXPUESTOS | E108: m2 | G108: 0 | H108: 1.48 | J108: =+ROUND(H108+I108*TC,2) -> 1.48 | K108: =H108*G108 -> 0 | L108: =I108*G108 -> 0 | M108: =+ROUND(K108+L108*TC,2) -> 0
C109: 02.04.04 | D109: ZAPATAS | G109: 0 | N109: =SUM(K109:K116)+SUM(L109:L116)*TC -> 490243.61
...

Sheet EST TORRE
B3: ESTRUCTURAS TORRE
B5: Presupuesto: | C5: =+'Est Sotano '!D5 -> PRESUPUESTO | GERMANIA | REV 09
B6: Subpresupuesto: | C6: ESTRUCTURAS TORRE
B7: Cliente: | C7: =+'Est Sotano '!D7 -> VYV INMOBILIARIA
B8: Lugar: | C8: =+'Est Sotano '!D8 -> SURQUILLO
B10: ITEM | C10: DESCRIPCION | D10: UND | E10: CANTIDAD | F10: CANTIDAD | G10: P.U. (PEN) | H10: P.U. (USD) | I10: P.U. TOTAL (PEN) | J10: PRECIO PARCIAL (PEN) | K10: PRECIO PARCIAL (USD) | L10: PARCIAL TOTAL (PEN) | M10: TOTAL
B11: 02 | C11: ESTRUCTURAS TORRE
B12: 02.01.01 | C12: PLACAS | M12: =SUM(J12:J21)+SUM(K12:K21)*TC -> 2036035.3
B13: 02.01.01.01 | C13: CONCRETO PREMEZCLADO, CEMENTO TIPO I, PLACAS f'c=210 kg/cm2 | D13: m3 | G13: 380.32 | H13: 0 | I13: =+ROUND(G13+H13*TC,2) -> 380.32 | J13: =G13*F13 -> 0 | K13: =H13*F13 -> 0 | L13: =+ROUND(J13+K13*TC,2) -> 0
B14: 02.01.01.02 | C14: CONCRETO PREMEZCLADO, CEMENTO TIPO I, PLACAS f'c=280 kg/cm2 | D14: m3 | E14: 1036.8555 | F14: 1036.86 | G14: 408.72 | H14: 0 | I14: =+ROUND(G14+H14*TC,2) -> 408.72 | J14: =G14*F14 -> 423785.42 | K14: =H14*F14 -> 0 | L14: =+ROUND(J14+K14*TC,2) -> 423785.42
B15: 02.01.01.03 | C15: CONCRETO PREMEZCLADO, CEMENTO TIPO I, PLACAS f'c=350 kg/cm2 | D15: m3 | E15: 324.2511 | F15: 324.25 | G15: 447.61 | H15: 0 | I15: =+ROUND(G15+H15*TC,2) -> 447.61 | J15: =G15*F15 -> 145137.54 | K15: =H15*F15 -> 0 | L15: =+ROUND(J15+K15*TC,2) -> 145137.54
B16: 02.01.01.04 | C16: CONCRETO PREMEZCLADO, CEMENTO TIPO I, PLACAS f'c=420 kg/cm2 | D16: m3 | E16: 227.7092 | F16: 227.71 | G16: 463.86 | H16: 0 | I16: =+ROUND(G16+H16*TC,2) -> 463.86 | J16: =G16*F16 -> 105625.56 | K16: =H16*F16 -> 0 | L16: =+ROUND(J16+K16*TC,2) -> 105625.56
B17: 02.01.01.05 | C17: ENCOFRADO Y DESENCOFRADO DE MUROS Y PLACAS | D17: m2 | E17: 8822.9539 | F17: 8822.95 | G17: 50.38 | H17: 0 | I17: =+ROUND(G17+H17*TC,2) -> 50.38 | J17: =G17*F17 -> 444500.22 | K17: =H17*F17 -> 0 | L17: =+ROUND(J17+K17*TC,2) -> 444500.22
B18: 02.01.01.06 | C18: ENCOFRADO Y DESENCOFRADO DE MUROS Y PLACAS DOBLE ALTURA | D18: m2 | E18: 1231.5432 | F18: 1231.54 | G18: 60.63 | H18: 0 | I18: =+ROUND(G18+H18*TC,2) -> 60.63 | J18: =G18*F18 -> 74668.27 | K18: =H18*F18 -> 0 | L18: =+ROUND(J18+K18*TC,2) -> 74668.27
B19: 02.01.01.07 | C19: ACERO DE REFUERZO FY= 4200 kg/cm2, GRADO 60 | D19: kg | E19: 196005.59 | F19: 196005.59 | G19: 1.24 | H19: 0.89 | I19: =+ROUND(G19+H19*TC,2) -> 4.22 | J19: =G19*F19 -> 243046.93 | K19: =H19*F19 -> 174444.98 | L19: =+ROUND(J19+K19*TC,2) -> 827437.6
B20: 02.01.01.08 | C20: CURADO DE ELEMENTOS ESTRUCTURALES EXPUESTOS | D20: m2 | E20: 10054.497 | F20: 10054.5 | G20: 1.48 | H20: 0 | I20: =+ROUND(G20+H20*TC,2) -> 1.48 | J20: =G20*F20 -> 14880.66 | K20: =H20*F20 -> 0 | L20: =+ROUND(J20+K20*TC,2) -> 14880.66
B21: 02.02.01 | C21: MUROS P/ JARDINERAS - - CORTES TECHO SOTANO 01 | F21: 0 | M21: =SUM(J21:J25)+SUM(K21:K25)*TC -> 12222.878
B22: 02.02.01.01 | C22: CONCRETO PREMEZCLADO, CEMENTO TIPO I, PLACAS f'c=210 kg/cm2 | D22: m3 | E22: 6.903428 | F22: 6.9 | G22: 380.32 | H22: 0 | I22: =+ROUND(G22+H22*TC,2) -> 380.32 | J22: =G22*F22 -> 2624.208 | K22: =H22*F22 -> 0 | L22: =+ROUND(J22+K22*TC,2) -> 2624.21
B23: 02.02.01.02 | C23: ENCOFRADO Y DESENCOFRADO DE MUROS Y PLACAS | D23: m2 | E23: 118.4168 | F23: 118.42 | G23: 50.38 | H23: 0 | I23: =+ROUND(G23+H23*TC,2) -> 50.38 | J23: =G23*F23 -> 5965.9996 | K23: =H23*F23 -> 0 | L23: =+ROUND(J23+K23*TC,2) -> 5966
B24: 02.02.01.03 | C24: ACERO DE REFUERZO FY= 4200 kg/cm2, GRADO 60 | D24: kg | E24: 819.0024 | F24: 819 | G24: 1.24 | H24: 0.89 | I24: =+ROUND(G24+H24*TC,2) -> 4.22 | J24: =G24*F24 -> 1015.56 | K24: =H24*F24 -> 728.91 | L24: =+ROUND(J24+K24*TC,2) -> 3457.41
B25: 02.02.01.04 | C25: CURADO DE ELEMENTOS ESTRUCTURALES EXPUESTOS | D25: m2 | E25: 118.4168 | F25: 118.42 | G25: 1.48 | H25: 0 | I25: =+ROUND(G25+H25*TC,2) -> 1.48 | J25: =G25*F25 -> 175.2616 | K25: =H25*F25 -> 0 | L25: =+ROUND(J25+K25*TC,2) -> 175.26
B26: 02.02.01 | C26: MUROS PISCINA | F26: 0 | M26: =SUM(J26:J30)+SUM(K26:K30)*TC -> 25634.017
B27: 02.02.01.01 | C27: CONCRETO PREMEZCLADO, CEMENTO TIPO I, PLACAS f'c=210 kg/cm2 | D27: m3 | E27: 21.86619 | F27: 21.87 | G27: 380.32 | H27: 0 | I27: =+ROUND(G27+H27*TC,2) -> 380.32 | J27: =G27*F27 -> 8317.5984 | K27: =H27*F27 -> 0 | L27: =+ROUND(J27+K27*TC,2) -> 8317.6
B28: 02.02.01.02 | C28: ENCOFRADO Y DESENCOFRADO DE MUROS Y PLACAS | D28: m2 | E28: 206.6775 | F28: 206.68 | G28: 50.38 | H28: 0 | I28: =+ROUND(G28+H28*TC,2) -> 50.38 | J28: =G28*F28 -> 10412.538 | K28: =H28*F28 -> 0 | L28: =+ROUND(J28+K28*TC,2) -> 10412.54
B29: 02.02.01.03 | C29: ACERO DE REFUERZO FY= 4200 kg/cm2, GRADO 60 | D29: kg | E29: 1562.9512 | F29: 1562.95 | G29: 1.24 | H29: 0.89 | I29: =+ROUND(G29+H29*TC,2) -> 4.22 | J29: =G29*F29 -> 1938.058 | K29: =H29*F29 -> 1391.0255 | L29: =+ROUND(J29+K29*TC,2) -> 6597.99
B30: 02.02.01.04 | C30: CURADO DE ELEMENTOS ESTRUCTURALES EXPUESTOS | D30: m2 | E30: 206.6775 | F30: 206.68 | G30: 1.48 | H30: 0 | I30: =+ROUND(G30+H30*TC,2) -> 1.48 | J30: =G30*F30 -> 305.8864 | K30: =H30*F30 -> 0 | L30: =+ROUND(J30+K30*TC,2) -> 305.89
B31: 02.03.01 | C31: COLUMNAS | F31: 0 | M31: =SUM(J31:J39)+SUM(K31:K39)*TC -> 972578.62
B32: 02.03.01.01 | C32: CONCRETO PREMEZCLADO, CEMENTO TIPO I, COLUMNAS f'c=210 kg/cm2 | D32: m3 | F32: 0 | G32: 385.51 | H32: 0 | I32: =+ROUND(G32+H32*TC,2) -> 385.51 | J32: =G32*F32 -> 0 | K32: =H32*F32 -> 0 | L32: =+ROUND(J32+K32*TC,2) -> 0
B33: 02.03.01.02 | C33: CONCRETO PREMEZCLADO, CEMENTO TIPO I, COLUMNAS f'c=280 kg/cm2 | D33: m3 | E33: 365.397 | F33: 365.4 | G33: 408.72 | H33: 0 | I33: =+ROUND(G33+H33*TC,2) -> 408.72 | J33: =G33*F33 -> 149346.29 | K33: =H33*F33 -> 0 | L33: =+ROUND(J33+K33*TC,2) -> 149346.29
B34: 02.03.01.03 | C34: CONCRETO PREMEZCLADO, CEMENTO TIPO I, COLUMNAS f'c=350 kg/cm2 | D34: m3 | E34: 121.2179 | F34: 121.22 | G34: 447.61 | H34: 0 | I34: =+ROUND(G34+H34*TC,2) -> 447.61 | J34: =G34*F34 -> 54259.284 | K34: =H34*F34 -> 0 | L34: =+ROUND(J34+K34*TC,2) -> 54259.28
B35: 02.03.01.04 | C35: CONCRETO PREMEZCLADO, CEMENTO TIPO I, COLUMNAS f'c=420 kg/cm2 | D35: m3 | E35: 86.0719 | F35: 86.07 | G35: 463.86 | H35: 0 | I35: =+ROUND(G35+H35*TC,2) -> 463.86 | J35: =G35*F35 -> 39924.43 | K35: =H35*F35 -> 0 | L35: =+ROUND(J35+K35*TC,2) -> 39924.43
B36: 02.03.01.05 | C36: ENCOFRADO Y DESENCOFRADO DE COLUMNAS | D36: m2 | E36: 2708.41 | F36: 2708.41 | G36: 50.78 | H36: 0 | I36: =+ROUND(G36+H36*TC,2) -> 50.78 | J36: =G36*F36 -> 137533.06 | K36: =H36*F36 -> 0 | L36: =+ROUND(J36+K36*TC,2) -> 137533.06
B37: 02.03.01.06 | C37: ENCOFRADO Y DESENCOFRADO DE COLUMNAS DOBLE ALTURA | D37: m2 | E37: 410.4276 | F37: 410.43 | G37: 61.03 | H37: 0 | I37: =+ROUND(G37+H37*TC,2) -> 61.03 | J37: =G37*F37 -> 25048.543 | K37: =H37*F37 -> 0 | L37: =+ROUND(J37+K37*TC,2) -> 25048.54
B38: 02.03.01.07 | C38: ACERO DE REFUERZO FY= 4200 kg/cm2, GRADO 60 | D38: kg | E38: 133092.77 | F38: 133092.77 | G38: 1.24 | H38: 0.89 | I38: =+ROUND(G38+H38*TC,2) -> 4.22 | J38: =G38*F38 -> 165035.03 | K38: =H38*F38 -> 118452.57 | L38: =+ROUND(J38+K38*TC,2) -> 561851.13
B39: 02.03.01.08 | C39: CURADO DE ELEMENTOS ESTRUCTURALES EXPUESTOS | D39: m2 | E39: 3118.8376 | F39: 3118.84 | G39: 1.48 | H39: 0 | I39: =+ROUND(G39+H39*TC,2) -> 1.48 | J39: =G39*F39 -> 4615.8832 | K39: =H39*F39 -> 0 | L39: =+ROUND(J39+K39*TC,2) -> 4615.88
B40: 02.04.01 | C40: VIGAS | F40: 0 | M40: =SUM(J40:J92)+SUM(K40:K92)*TC -> 5227691.3
B41: 02.04.01.01 | C41: CONCRETO PREMEZCLADO, CEMENTO TIPO I, VIGAS TORRE f'c=280 kg/cm2 | D41: m3 | E41: 1429.3867 | F41: 1429.39 | G41: 415.48 | H41: 0 | I41: =+ROUND(G41+H41*TC,2) -> 415.48 | J41: =G41*F41 -> 593882.96 | K41: =H41*F41 -> 0 | L41: =+ROUND(J41+K41*TC,2) -> 593882.96
B42: 02.04.01.02 | C42: CONCRETO PREMEZCLADO, CEMENTO TIPO I, VIGAS TORRE f'c=210 kg/cm2 | D42: m3 | F42: 0 | G42: 391.63 | H42: 0 | I42: =+ROUND(G42+H42*TC,2) -> 391.63 | J42: =G42*F42 -> 0 | K42: =H42*F42 -> 0 | L42: =+ROUND(J42+K42*TC,2) -> 0
B43: 02.04.01.03 | C43: CONCRETO PREMEZCLADO, CEMENTO TIPO I, VIGAS TORRE f'c=350 kg/cm2 | D43: m3 | E43: 45.8395 | F43: 45.84 | G43: 454.38 | H43: 0 | I43: =+ROUND(G43+H43*TC,2) -> 454.38 | J43: =G43*F43 -> 20828.779 | K43: =H43*F43 -> 0 | L43: =+ROUND(J43+K43*TC,2) -> 20828.78
B44: 02.04.01.03 | C44: CONCRETO PREMEZCLADO, CEMENTO TIPO I, VIGAS TORRE f'c=420 kg/cm2 | D44: m3 | E44: 49.0113 | F44: 49.01 | G44: 470.63 | H44: 0 | I44: =+ROUND(G44+H44*TC,2) -> 470.63 | J44: =G44*F44 -> 23065.576 | K44: =H44*F44 -> 0 | L44: =+ROUND(J44+K44*TC,2) -> 23065.58
B45: 02.04.01.04 | C45: ENCOFRADO Y DESENCOFRADO DE VIGAS | D45: m2 | E45: 7577.1832 | F45: 7577.18 | G45: 54.88 | H45: 0 | I45: =+ROUND(G45+H45*TC,2) -> 54.88 | J45: =G45*F45 -> 415835.64 | K45: =H45*F45 -> 0 | L45: =+ROUND(J45+K45*TC,2) -> 415835.64
B46: 02.04.01.05 | C46: ENCOFRADO Y DESENCOFRADO DE VIGAS DOBLE ALTURA | D46: m2 | F46: 0 | G46: 65.13 | H46: 0 | I46: =+ROUND(G46+H46*TC,2) -> 65.13 | J46: =G46*F46 -> 0 | K46: =H46*F46 -> 0 | L46: =+ROUND(J46+K46*TC,2) -> 0
B47: 02.04.01.06 | C47: ACERO DE REFUERZO FY= 4200 kg/cm2, GRADO 60 | D47: kg | E47: 330410.39 | F47: 330410.39 | G47: 1.24 | H47: 0.89 | I47: =+ROUND(G47+H47*TC,2) -> 4.22 | J47: =G47*F47 -> 409708.88 | K47: =H47*F47 -> 294065.25 | L47: =+ROUND(J47+K47*TC,2) -> 1394827.5
B48: 02.04.01.07 | C48: CURADO DE ELEMENTOS ESTRUCTURALES EXPUESTOS | D48: m2 | E48: 7577.1832 | F48: 7577.18 | G48: 1.48 | H48: 0 | I48: =+ROUND(G48+H48*TC,2) -> 1.48 | J48: =G48*F48 -> 11214.226 | K48: =H48*F48 -> 0 | L48: =+ROUND(J48+K48*TC,2) -> 11214.23
C49: PRELOSA ALIGERADA H=0.20M, UN SENTIDO | F49: 0
C50: CONCRETO PREMEZCLADO, CEMENTO TIPO I, LOSA ALIGERADA TORRE f'c=280 kg/cm2 | D50: m3 | E50: 91.262952 | F50: 91.26 | G50: 415.48 | H50: 0 | I50: =+ROUND(G50+H50*TC,2) -> 415.48 | J50: =G50*F50 -> 37916.705 | K50: =H50*F50 -> 0 | L50: =+ROUND(J50+K50*TC,2) -> 37916.7
C51: CONCRETO PREMEZCLADO, CEMENTO TIPO I, LOSA ALIGERADA TORRE f'c=350 kg/cm2 | D51: m3 | E51: 1.9425 | F51: 1.94 | G51: 454.37 | H51: 0 | I51: =+ROUND(G51+H51*TC,2) -> 454.37 | J51: =G51*F51 -> 881.4778 | K51: =H51*F51 -> 0 | L51: =+ROUND(J51+K51*TC,2) -> 881.48
C52: CONCRETO PREMEZCLADO, CEMENTO TIPO I, LOSA ALIGERADA TORRE f'c=420 kg/cm2 | D52: m3 | E52: 2.2185 | F52: 2.22 | G52: 470.62 | H52: 0 | I52: =+ROUND(G52+H52*TC,2) -> 470.62 | J52: =G52*F52 -> 1044.7764 | K52: =H52*F52 -> 0 | L52: =+ROUND(J52+K52*TC,2) -> 1044.78
C53: ENCOFRADO Y DESENCOFRADO DE PRELOSA ALIGERADA | D53: m2 | E53: 1064.82 | F53: 1064.82 | G53: 36.32 | H53: 0 | I53: =+ROUND(G53+H53*TC,2) -> 36.32 | J53: =G53*F53 -> 38674.262 | K53: =H53*F53 -> 0 | L53: =+ROUND(J53+K53*TC,2) -> 38674.26
C54: ENCOFRADO Y DESENCOFRADO DE PRELOSA ALIGERADA DOBLE ALTURA | D54: m2 | E54: 205.44 | F54: 205.44 | G54: 46.57 | H54: 0 | I54: =+ROUND(G54+H54*TC,2) -> 46.57 | J54: =G54*F54 -> 9567.3408 | K54: =H54*F54 -> 0 | L54: =+ROUND(J54+K54*TC,2) -> 9567.34
C55: SUMINISTRO DE PRELOSA ALIGERADA EN UNA DIRECCION H=20CM | D55: m2 | E55: 1270.26 | F55: 1270.26 | G55: 61.5 | H55: 0 | I55: =+ROUND(G55+H55*TC,2) -> 61.5 | J55: =G55*F55 -> 78120.99 | K55: =H55*F55 -> 0 | L55: =+ROUND(J55+K55*TC,2) -> 78120.99
C56: INSTALACIÓN DE PRELOSA E=5CM | D56: m2 | E56: 1270.26 | F56: 1270.26 | G56: 4.37 | H56: 0 | I56: =+ROUND(G56+H56*TC,2) -> 4.37 | J56: =G56*F56 -> 5551.0362 | K56: =H56*F56 -> 0 | L56: =+ROUND(J56+K56*TC,2) -> 5551.04
C57: ACERO DE REFUERZO FY= 4200 kg/cm2, GRADO 60 (PUESTO EN OBRA) | D57: kg | E57: 10194.718 | F57: 10194.72 | G57: 1.24 | H57: 0.89 | I57: =+ROUND(G57+H57*TC,2) -> 4.22 | J57: =G57*F57 -> 12641.453 | K57: =H57*F57 -> 9073.3008 | L57: =+ROUND(J57+K57*TC,2) -> 43037.01
C58: ACERO DE REFUERZO FY= 4200 kg/cm2, GRADO 60 (EMBEBIDO EN PRELOSA) | D58: kg | E58: 4999.2942 | F58: 4999.29 | G58: 0 | H58: 0.89 | I58: =+ROUND(G58+H58*TC,2) -> 2.98 | J58: =G58*F58 -> 0 | K58: =H58*F58 -> 4449.3681 | L58: =+ROUND(J58+K58*TC,2) -> 14905.38
C59: ACERO DE REFUERZO FY= 4200 kg/cm2, GRADO 60 BASE Y DISTRIBUCIÓN (EMBEBIDO EN PRELOSA) | D59: kg | E59: 2007.0108 | F59: 2007.01 | G59: 0 | H59: 0.89 | I59: =+ROUND(G59+H59*TC,2) -> 2.98 | J59: =G59*F59 -> 0 | K59: =H59*F59 -> 1786.2389 | L59: =+ROUND(J59+K59*TC,2) -> 5983.9
C60: ACERO DE REFUERZO FY= 4200 kg/cm2, GRADO 60 (COSTURA PRELOSA) | D60: kg | E60: 508.104 | F60: 508.1 | G60: 1.24 | H60: 0.89 | I60: =+ROUND(G60+H60*TC,2) -> 4.22 | J60: =G60*F60 -> 630.044 | K60: =H60*F60 -> 452.209 | L60: =+ROUND(J60+K60*TC,2) -> 2144.94
C61: CURADO DE ELEMENTOS ESTRUCTURALES EXPUESTOS | D61: m2 | E61: 1270.26 | F61: 1270.26 | G61: 1.48 | H61: 0 | I61: =+ROUND(G61+H61*TC,2) -> 1.48 | J61: =G61*F61 -> 1879.9848 | K61: =H61*F61 -> 0 | L61: =+ROUND(J61+K61*TC,2) -> 1879.98
C62: PRELOSA ALIGERADA H=0.20M, DOS SENTIDOS | F62: 0
C63: CONCRETO PREMEZCLADO, CEMENTO TIPO I, LOSA ALIGERADA TORRE f'c=280 kg/cm2 | D63: m3 | E63: 892.24488 | F63: 892.24 | G63: 415.48 | H63: 0 | I63: =+ROUND(G63+H63*TC,2) -> 415.48 | J63: =G63*F63 -> 370707.88 | K63: =H63*F63 -> 0 | L63: =+ROUND(J63+K63*TC,2) -> 370707.88
C64: CONCRETO PREMEZCLADO, CEMENTO TIPO I, LOSA ALIGERADA TORRE f'c=350 kg/cm2 | D64: m3 | E64: 11.2608 | F64: 11.26 | G64: 454.37 | H64: 0 | I64: =+ROUND(G64+H64*TC,2) -> 454.37 | J64: =G64*F64 -> 5116.2062 | K64: =H64*F64 -> 0 | L64: =+ROUND(J64+K64*TC,2) -> 5116.21
C65: CONCRETO PREMEZCLADO, CEMENTO TIPO I, LOSA ALIGERADA TORRE f'c=420 kg/cm2 | D65: m3 | E65: 11.7495 | F65: 11.75 | G65: 470.62 | H65: 0 | I65: =+ROUND(G65+H65*TC,2) -> 470.62 | J65: =G65*F65 -> 5529.785 | K65: =H65*F65 -> 0 | L65: =+ROUND(J65+K65*TC,2) -> 5529.79
C66: ENCOFRADO Y DESENCOFRADO DE PRELOSA ALIGERADA | D66: m2 | E66: 9122.88 | F66: 9122.88 | G66: 36.32 | H66: 0 | I66: =+ROUND(G66+H66*TC,2) -> 36.32 | J66: =G66*F66 -> 331343 | K66: =H66*F66 -> 0 | L66: =+ROUND(J66+K66*TC,2) -> 331343
C67: ENCOFRADO Y DESENCOFRADO DE PRELOSA ALIGERADA DOBLE ALTURA | D67: m2 | E67: 867.21 | F67: 867.21 | G67: 46.57 | H67: 0 | I67: =+ROUND(G67+H67*TC,2) -> 46.57 | J67: =G67*F67 -> 40385.97 | K67: =H67*F67 -> 0 | L67: =+ROUND(J67+K67*TC,2) -> 40385.97
C68: SUMINISTRO DE PRELOSA ALIGERADA EN DOS DIRECCIONES H=20CM | D68: m2 | E68: 9990.09 | F68: 9990.09 | G68: 58.5 | H68: 0 | I68: =+ROUND(G68+H68*TC,2) -> 58.5 | J68: =G68*F68 -> 584420.27 | K68: =H68*F68 -> 0 | L68: =+ROUND(J68+K68*TC,2) -> 584420.27
C69: INSTALACIÓN DE PRELOSA E=5CM | D69: m2 | E69: 9990.09 | F69: 9990.09 | G69: 4.37 | H69: 0 | I69: =+ROUND(G69+H69*TC,2) -> 4.37 | J69: =G69*F69 -> 43656.693 | K69: =H69*F69 -> 0 | L69: =+ROUND(J69+K69*TC,2) -> 43656.69
C70: ACERO DE REFUERZO FY= 4200 kg/cm2, GRADO 60 (PUESTO EN OBRA) | D70: kg | E70: 59610.779 | F70: 59610.78 | G70: 1.24 | H70: 0.89 | I70: =+ROUND(G70+H70*TC,2) -> 4.22 | J70: =G70*F70 -> 73917.367 | K70: =H70*F70 -> 53053.594 | L70: =+ROUND(J70+K70*TC,2) -> 251646.91
C71: ACERO DE REFUERZO FY= 4200 kg/cm2, GRADO 60 (EMBEBIDO EN PRELOSA) | D71: kg | E71: 76088.088 | F71: 76088.09 | G71: 0 | H71: 0.89 | I71: =+ROUND(G71+H71*TC,2) -> 2.98 | J71: =G71*F71 -> 0 | K71: =H71*F71 -> 67718.4 | L71: =+ROUND(J71+K71*TC,2) -> 226856.64
C72: ACERO DE REFUERZO FY= 4200 kg/cm2, GRADO 60 DE CONTINUIDAD (PUESTO EN OBRA) | D72: kg | E72: 17482.658 | F72: 17482.66 | G72: 1.24 | H72: 0.89 | I72: =+ROUND(G72+H72*TC,2) -> 4.22 | J72: =G72*F72 -> 21678.498 | K72: =H72*F72 -> 15559.567 | L72: =+ROUND(J72+K72*TC,2) -> 73803.05
C73: CURADO DE ELEMENTOS ESTRUCTURALES EXPUESTOS | D73: m2 | E73: 9990.09 | F73: 9990.09 | G73: 1.48 | H73: 0 | I73: =+ROUND(G73+H73*TC,2) -> 1.48 | J73: =G73*F73 -> 14785.333 | K73: =H73*F73 -> 0 | L73: =+ROUND(J73+K73*TC,2) -> 14785.33
C74: PRELOSA MACIZA H=0.20M | F74: 0
C75: CONCRETO PREMEZCLADO, CEMENTO TIPO I, LOSA MACIZA TORRE f'c=280 kg/cm2 | D75: m3 | E75: 322.2975 | F75: 322.3 | G75: 415.48 | H75: 0 | I75: =+ROUND(G75+H75*TC,2) -> 415.48 | J75: =G75*F75 -> 133909.2 | K75: =H75*F75 -> 0 | L75: =+ROUND(J75+K75*TC,2) -> 133909.2
C76: CONCRETO PREMEZCLADO, CEMENTO TIPO I, LOSA MACIZA TORRE f'c=350 kg/cm2 | D76: m3 | E76: 4.164 | F76: 4.16 | G76: 454.37 | H76: 0 | I76: =+ROUND(G76+H76*TC,2) -> 454.37 | J76: =G76*F76 -> 1890.1792 | K76: =H76*F76 -> 0 | L76: =+ROUND(J76+K76*TC,2) -> 1890.18
C77: CONCRETO PREMEZCLADO, CEMENTO TIPO I, LOSA MACIZA TORRE f'c=420 kg/cm2 | D77: m3 | E77: 4.515 | F77: 4.52 | G77: 470.62 | H77: 0 | I77: =+ROUND(G77+H77*TC,2) -> 470.62 | J77: =G77*F77 -> 2127.2024 | K77: =H77*F77 -> 0 | L77: =+ROUND(J77+K77*TC,2) -> 2127.2
C78: ENCOFRADO Y DESENCOFRADO DE PRELOSA ALIGERADA | D78: m2 | E78: 2093.18 | F78: 2093.18 | G78: 36.32 | H78: 0 | I78: =+ROUND(G78+H78*TC,2) -> 36.32 | J78: =G78*F78 -> 76024.298 | K78: =H78*F78 -> 0 | L78: =+ROUND(J78+K78*TC,2) -> 76024.3
C79: ENCOFRADO Y DESENCOFRADO DE PRELOSA ALIGERADA DOBLE ALTURA | D79: m2 | E79: 113.33 | F79: 113.33 | G79: 46.57 | H79: 0 | I79: =+ROUND(G79+H79*TC,2) -> 46.57 | J79: =G79*F79 -> 5277.7781 | K79: =H79*F79 -> 0 | L79: =+ROUND(J79+K79*TC,2) -> 5277.78
C80: SUMINISTRO DE PRELOSA MACIZA H=20CM | D80: m2 | E80: 2206.51 | F80: 2206.51 | G80: 47.5 | H80: 0 | I80: =+ROUND(G80+H80*TC,2) -> 47.5 | J80: =G80*F80 -> 104809.23 | K80: =H80*F80 -> 0 | L80: =+ROUND(J80+K80*TC,2) -> 104809.23
C81: INSTALACIÓN DE PRELOSA E=5CM | D81: m2 | E81: 2206.51 | F81: 2206.51 | G81: 4.37 | H81: 0 | I81: =+ROUND(G81+H81*TC,2) -> 4.37 | J81: =G81*F81 -> 9642.4487 | K81: =H81*F81 -> 0 | L81: =+ROUND(J81+K81*TC,2) -> 9642.45
C82: ACERO DE REFUERZO FY= 4200 kg/cm2, GRADO 60 (PUESTO EN OBRA) | D82: kg | E82: 19656.209 | F82: 19656.21 | G82: 1.24 | H82: 0.89 | I82: =+ROUND(G82+H82*TC,2) -> 4.22 | J82: =G82*F82 -> 24373.7 | K82: =H82*F82 -> 17494.027 | L82: =+ROUND(J82+K82*TC,2) -> 82978.69
C83: ACERO DE REFUERZO FY= 4200 kg/cm2, GRADO 60 (EMBEBIDO EN PRELOSA) | D83: kg | F83: 0 | G83: 0 | H83: 0.89 | I83: =+ROUND(G83+H83*TC,2) -> 2.98 | J83: =G83*F83 -> 0 | K83: =H83*F83 -> 0 | L83: =+ROUND(J83+K83*TC,2) -> 0
C84: ACERO DE REFUERZO FY= 4200 kg/cm2, GRADO 60 DE CONTINUIDAD (PUESTO EN OBRA) | D84: kg | E84: 3309.765 | F84: 3309.77 | G84: 1.24 | H84: 0.89 | I84: =+ROUND(G84+H84*TC,2) -> 4.22 | J84: =G84*F84 -> 4104.1148 | K84: =H84*F84 -> 2945.6953 | L84: =+ROUND(J84+K84*TC,2) -> 13972.19
C85: CURADO DE ELEMENTOS ESTRUCTURALES EXPUESTOS | D85: m2 | E85: 2206.51 | F85: 2206.51 | G85: 1.48 | H85: 0 | I85: =+ROUND(G85+H85*TC,2) -> 1.48 | J85: =G85*F85 -> 3265.6348 | K85: =H85*F85 -> 0 | L85: =+ROUND(J85+K85*TC,2) -> 3265.63
C86: VIGAS CHATAS | F86: 0
B87: 02.02.01.03 | C87: ACERO DE REFUERZO FY= 4200 kg/cm2, GRADO 60 | D87: kg | E87: 8014.3544 | F87: 8014.35 | G87: 1.24 | H87: 0.89 | I87: =+ROUND(G87+H87*TC,2) -> 4.22 | J87: =G87*F87 -> 9937.794 | K87: =H87*F87 -> 7132.7715 | L87: =+ROUND(J87+K87*TC,2) -> 33832.58
C88: SUMINISTRO DE PRELOSA MACIZA H=20CM | D88: m2 | E88: 1235.7864 | F88: 1235.79 | G88: 47.5 | H88: 0 | I88: =+ROUND(G88+H88*TC,2) -> 47.5 | J88: =G88*F88 -> 58700.025 | K88: =H88*F88 -> 0 | L88: =+ROUND(J88+K88*TC,2) -> 58700.03
C89: INSTALACIÓN DE PRELOSA E=5CM | D89: m2 | E89: 1235.7864 | F89: 1235.79 | G89: 4.37 | H89: 0 | I89: =+ROUND(G89+H89*TC,2) -> 4.37 | J89: =G89*F89 -> 5400.4023 | K89: =H89*F89 -> 0 | L89: =+ROUND(J89+K89*TC,2) -> 5400.4
C90: ENCOFRADO Y DESENCOFRADO DE PRELOSA ALIGERADA | D90: m2 | E90: 1086.053 | F90: 1086.05 | G90: 36.32 | H90: 0 | I90: =+ROUND(G90+H90*TC,2) -> 36.32 | J90: =G90*F90 -> 39445.336 | K90: =H90*F90 -> 0 | L90: =+ROUND(J90+K90*TC,2) -> 39445.34
C91: ENCOFRADO Y DESENCOFRADO DE PRELOSA ALIGERADA DOBLE ALTURA | D91: m2 | E91: 149.7334 | F91: 149.73 | G91: 46.57 | H91: 0 | I91: =+ROUND(G91+H91*TC,2) -> 46.57 | J91: =G91*F91 -> 6972.9261 | K91: =H91*F91 -> 0 | L91: =+ROUND(J91+K91*TC,2) -> 6972.93
C92: CURADO DE ELEMENTOS ESTRUCTURALES EXPUESTOS | D92: m2 | E92: 1235.7864 | F92: 1235.79 | G92: 1.48 | H92: 0 | I92: =+ROUND(G92+H92*TC,2) -> 1.48 | J92: =G92*F92 -> 1828.9692 | K92: =H92*F92 -> 0 | L92: =+ROUND(J92+K92*TC,2) -> 1828.97
B93: 02.05.01 | C93: LOSA MACIZA H=0.20 M | F93: 0 | M93: =SUM(J93:J100)+SUM(K93:K100)*TC -> 816297.85
B94: 02.05.01.01 | C94: CONCRETO PREMEZCLADO, CEMENTO TIPO I, LOSA ALIGERADA TORRE f'c=280 kg/cm2 | D94: m3 | E94: 690.13 | F94: 690.13 | G94: 415.48 | H94: 0 | I94: =+ROUND(G94+H94*TC,2) -> 415.48 | J94: =G94*F94 -> 286735.21 | K94: =H94*F94 -> 0 | L94: =+ROUND(J94+K94*TC,2) -> 286735.21
C95: CONCRETO PREMEZCLADO, CEMENTO TIPO I, LOSA ALIGERADA TORRE f'c=350 kg/cm2 | D95: m3 | E95: 31.042 | F95: 31.04 | G95: 454.37 | H95: 0 | I95: =+ROUND(G95+H95*TC,2) -> 454.37 | J95: =G95*F95 -> 14103.645 | K95: =H95*F95 -> 0 | L95: =+ROUND(J95+K95*TC,2) -> 14103.64
C96: CONCRETO PREMEZCLADO, CEMENTO TIPO I, LOSA ALIGERADA TORRE f'c=420 kg/cm2 | D96: m3 | E96: 25.92 | F96: 25.92 | G96: 470.62 | H96: 0 | I96: =+ROUND(G96+H96*TC,2) -> 470.62 | J96: =G96*F96 -> 12198.47 | K96: =H96*F96 -> 0 | L96: =+ROUND(J96+K96*TC,2) -> 12198.47
B97: 02.05.01.02 | C97: ENCOFRADO Y DESENCOFRADO DE LOSA MACIZA | D97: m2 | E97: 3338.98 | F97: 3338.98 | G97: 50.8 | H97: 0 | I97: =+ROUND(G97+H97*TC,2) -> 50.8 | J97: =G97*F97 -> 169620.18 | K97: =H97*F97 -> 0 | L97: =+ROUND(J97+K97*TC,2) -> 169620.18
B98: 02.05.01.04 | C98: ENCOFRADO Y DESENCOFRADO DE LOSA MACIZA DOBLE ALTURA | D98: m2 | E98: 396.48 | F98: 396.48 | G98: 60.7 | H98: 0 | I98: =+ROUND(G98+H98*TC,2) -> 60.7 | J98: =G98*F98 -> 24066.336 | K98: =H98*F98 -> 0 | L98: =+ROUND(J98+K98*TC,2) -> 24066.34
B99: 02.05.01.05 | C99: ACERO DE REFUERZO FY= 4200 kg/cm2, GRADO 60 | D99: kg | E99: 72023.105 | F99: 72023.1 | G99: 1.24 | H99: 0.89 | I99: =+ROUND(G99+H99*TC,2) -> 4.22 | J99: =G99*F99 -> 89308.644 | K99: =H99*F99 -> 64100.559 | L99: =+ROUND(J99+K99*TC,2) -> 304045.52
B100: 02.05.01.06 | C100: CURADO DE ELEMENTOS ESTRUCTURALES EXPUESTOS | D100: m2 | E100: 3735.46 | F100: 3735.46 | G100: 1.48 | H100: 0 | I100: =+ROUND(G100+H100*TC,2) -> 1.48 | J100: =G100*F100 -> 5528.4808 | K100: =H100*F100 -> 0 | L100: =+ROUND(J100+K100*TC,2) -> 5528.48
B101: 02.06.01 | C101: LOSA MACIZA H=0.25 m | F101: 0 | M101: =SUM(J101:J108)+SUM(K101:K108)*TC -> 14560.16
B102: 02.06.01.01 | C102: CONCRETO PREMEZCLADO, CEMENTO TIPO I, LOSA ALIGERADA TORRE f'c=280 kg/cm2 | D102: m3 | E102: 15.1925 | F102: 15.19 | G102: 415.48 | H102: 0 | I102: =+ROUND(G102+H102*TC,2) -> 415.48 | J102: =G102*F102 -> 6311.1412 | K102: =H102*F102 -> 0 | L102: =+ROUND(J102+K102*TC,2) -> 6311.14
B103: 02.06.01.02 | C103: CONCRETO PREMEZCLADO, CEMENTO TIPO I, LOSA ALIGERADA TORRE f'c=280 kg/cm2 | D103: m3 | F103: 0 | G103: 415.48 | H103: 0 | I103: =+ROUND(G103+H103*TC,2) -> 415.48 | J103: =G103*F103 -> 0 | K103: =H103*F103 -> 0 | L103: =+ROUND(J103+K103*TC,2) -> 0
B104: 02.06.01.03 | C104: CONCRETO PREMEZCLADO, CEMENTO TIPO I, LOSAS Y VIGAS, f'c=350 kg/cm2. (POR DETALLE DE VACIADO PARA CONCRETO DE DIFERENTES RESISTENCIAS EN TECHO ALREDEDOR DE COLUMNAS Y PLACAS) | D104: m3 | F104: 0 | G104: 0 | H104: 0 | I104: =+ROUND(G104+H104*TC,2) -> 0 | J104: =G104*F104 -> 0 | K104: =H104*F104 -> 0 | L104: =+ROUND(J104+K104*TC,2) -> 0
...

Sheet ARQ SOT
B2: ARQUITECTURA SÓTANOS
B4: Presupuesto | C4: =+'RESUMEN ESCENARIO'!C6 -> PRESUPUESTO | GERMANIA | REV 09
B5: Subpresupuesto | C5: =$B$2 -> ARQUITECTURA SÓTANOS
B6: Cliente | C6: =+'RESUMEN ESCENARIO'!C7 -> VYV INMOBILIARIA
B7: Lugar | C7: =+'RESUMEN ESCENARIO'!C8 -> SURQUILLO
B8: Fecha | C8: =+'RESUMEN ESCENARIO'!C9 -> 46090
B10: ITEM | C10: DESCRIPCION | D10: UND | E10: METRADO | F10: P.U. (PEN) | G10: P.U. (USD) | H10: P.U. TOTAL (PEN) | I10: PRECIO PARCIAL (PEN) | J10: PRECIO PARCIAL (USD) | K10: PARCIAL TOTAL (PEN) | L10: TOTAL
B11: 05 | C11: =$B$2 -> ARQUITECTURA SÓTANOS
B12: =B11+0.01 -> 5.01 | C12: MUROS Y TABIQUES | H12: =IFERROR(IF(D12<>0,(F12+G12*TC)," ")," ") | I12: =IFERROR(IF($E12=0,"",$E12*F12),"") | J12: =IFERROR(IF($E12=0,"",$E12*G12),"") | K12: =IFERROR(IF(E12<>0,(E12*H12)," "),0) | L12: =SUM(I12:I51)+SUM(J12:J51)*TC -> 244946.95
B13: =B12+0.0001 -> 5.0101 | C13: MUROS Y TABIQUES SILICO CALCAREOS | H13: =IFERROR(IF(D13<>0,(F13+G13*TC)," ")," ") | I13: =IFERROR(IF($E13=0,"",$E13*F13),"") | J13: =IFERROR(IF($E13=0,"",$E13*G13),"") | K13: =IFERROR(IF(E13<>0,(E13*H13)," "),0)
B14: =B12+0.0001 -> 5.0101 | C14: ALTURA < 2.60 | H14: =IFERROR(IF(D14<>0,(F14+G14*TC)," ")," ") | I14: =IFERROR(IF($E14=0,"",$E14*F14),"") | J14: =IFERROR(IF($E14=0,"",$E14*G14),"") | K14: =IFERROR(IF(E14<>0,(E14*H14)," "),0)
B15: =B14+0.000001 -> 5.010101 | C15: LADRILLO SILICO CALCAREO TIPO P7 H<2.6M | D15: m2
B16: =B14+0.000001 -> 5.010101 | C16: LADRILLO SILICO CALCAREO TIPO P10 H<2.6M | D16: m2 | E16: 348.42 | F16: 111.23 | H16: =+ROUND(F16+G16*TC,2) -> 111.23 | I16: =+ROUND(E16*F16,2) -> 38754.76 | J16: =+ROUND(E16*G16,2) -> 0 | K16: =+ROUND(I16+J16*TC,2) -> 38754.76
B17: =B15+0.000001 -> 5.010102 | C17: LADRILLO SILICO CALCAREO TIPO P12 H<2.6M | D17: m2 | E17: 103.8 | F17: 117.23 | H17: =+ROUND(F17+G17*TC,2) -> 117.23 | I17: =+ROUND(E17*F17,2) -> 12168.47 | J17: =+ROUND(E17*G17,2) -> 0 | K17: =+ROUND(I17+J17*TC,2) -> 12168.47
B18: =B17+0.000001 -> 5.010103 | C18: LADRILLO SILICO CALCAREO TIPO P14 H<2.6M | D18: m2 | E18: 1.4 | F18: 125.23 | H18: =+ROUND(F18+G18*TC,2) -> 125.23 | I18: =+ROUND(E18*F18,2) -> 175.32 | J18: =+ROUND(E18*G18,2) -> 0 | K18: =+ROUND(I18+J18*TC,2) -> 175.32
B19: =B18+0.000001 -> 5.010104 | C19: LADRILLO SILICO CALCAREO TIPO P20 H<2.6M | D19: m2 | E19: 0 | F19: 206.23 | H19: =+ROUND(F19+G19*TC,2) -> 206.23 | I19: =+ROUND(E19*F19,2) -> 0 | J19: =+ROUND(E19*G19,2) -> 0 | K19: =+ROUND(I19+J19*TC,2) -> 0
B20: =B14+0.0001 -> 5.0102 | C20: ALTURA > 2.60 | E20: 0
B21: =B20+0.000001 -> 5.010201 | C21: LADRILLO SILICO CALCAREO TIPO P7 H>2.6M | D21: m2 | E21: 6.71 | F21: 113.23 | H21: =+ROUND(F21+G21*TC,2) -> 113.23 | I21: =+ROUND(E21*F21,2) -> 759.77 | J21: =+ROUND(E21*G21,2) -> 0 | K21: =+ROUND(I21+J21*TC,2) -> 759.77
B22: =B21+0.000001 -> 5.010202 | C22: LADRILLO SILICO CALCAREO TIPO P10 H>2.6M | D22: m2 | E22: 767.55 | F22: 120.23 | H22: =+ROUND(F22+G22*TC,2) -> 120.23 | I22: =+ROUND(E22*F22,2) -> 92282.54 | J22: =+ROUND(E22*G22,2) -> 0 | K22: =+ROUND(I22+J22*TC,2) -> 92282.54
B23: =B22+0.000001 -> 5.010203 | C23: LADRILLO SILICO CALCAREO TIPO P12 H>2.6M | D23: m2 | E23: 60.95 | F23: 126.23 | H23: =+ROUND(F23+G23*TC,2) -> 126.23 | I23: =+ROUND(E23*F23,2) -> 7693.72 | J23: =+ROUND(E23*G23,2) -> 0 | K23: =+ROUND(I23+J23*TC,2) -> 7693.72
B24: =B23+0.000001 -> 5.010204 | C24: LADRILLO SILICO CALCAREO TIPO P14 H>2.6M | D24: m2 | E24: 0 | F24: 134.23 | H24: =+ROUND(F24+G24*TC,2) -> 134.23 | I24: =+ROUND(E24*F24,2) -> 0 | J24: =+ROUND(E24*G24,2) -> 0 | K24: =+ROUND(I24+J24*TC,2) -> 0
B25: =B24+0.000001 -> 5.010205 | C25: LADRILLO SILICO CALCAREO TIPO P20 H>2.6M | D25: m2 | E25: 0 | F25: 224.23 | H25: =+ROUND(F25+G25*TC,2) -> 224.23 | I25: =+ROUND(E25*F25,2) -> 0 | J25: =+ROUND(E25*G25,2) -> 0 | K25: =+ROUND(I25+J25*TC,2) -> 0
B26: =B15+0.0001 -> 5.010201 | C26: CORTAFUEGO < 2.60 | E26: 0
B27: =B26+0.000001 -> 5.010202 | C27: LADRILLO SILICO CALCAREO TIPO P10 RF:2 HRS H<2.6M (ALVEOLOS COMPLETAMENTE LLENO) | D27: m2 | E27: 0 | F27: 121.23 | H27: =+ROUND(F27+G27*TC,2) -> 121.23 | I27: =+ROUND(E27*F27,2) -> 0 | J27: =+ROUND(E27*G27,2) -> 0 | K27: =+ROUND(I27+J27*TC,2) -> 0
B28: =B27+0.000001 -> 5.010203 | C28: LADRILLO SILICO CALCAREO TIPO P12 RF:2 HRS H<2.6M (ALVEOLOS PARCIALMENTE LLENO) | D28: m2 | E28: 171.05 | F28: 117.23 | H28: =+ROUND(F28+G28*TC,2) -> 117.23 | I28: =+ROUND(E28*F28,2) -> 20052.19 | J28: =+ROUND(E28*G28,2) -> 0 | K28: =+ROUND(I28+J28*TC,2) -> 20052.19
B29: =B28+0.000001 -> 5.010204 | C29: LADRILLO SILICO CALCAREO TIPO P14 RF:2 HRS H<2.6M (ALVEOLOS PARCIALMENTE LLENO) | D29: m2 | E29: 0 | F29: 125.23 | H29: =+ROUND(F29+G29*TC,2) -> 125.23 | I29: =+ROUND(E29*F29,2) -> 0 | J29: =+ROUND(E29*G29,2) -> 0 | K29: =+ROUND(I29+J29*TC,2) -> 0
B30: =B20+0.0001 -> 5.0103 | C30: CORTAFUEGO > 2.60 | E30: 0
B31: =B30+0.000001 -> 5.010301 | C31: LADRILLO SILICO CALCAREO TIPO P10 RF:2 HRS H>2.6M (ALVEOLOS COMPLETAMENTE LLENO) | D31: m2 | E31: 0 | F31: 130.23 | H31: =+ROUND(F31+G31*TC,2) -> 130.23 | I31: =+ROUND(E31*F31,2) -> 0 | J31: =+ROUND(E31*G31,2) -> 0 | K31: =+ROUND(I31+J31*TC,2) -> 0
B32: =B31+0.000001 -> 5.010302 | C32: LADRILLO SILICO CALCAREO TIPO P12 RF:2 HRS H>2.6M (ALVEOLOS PARCIALMENTE LLENO) | D32: m2 | E32: 407.65 | F32: 126.23 | H32: =+ROUND(F32+G32*TC,2) -> 126.23 | I32: =+ROUND(E32*F32,2) -> 51457.66 | J32: =+ROUND(E32*G32,2) -> 0 | K32: =+ROUND(I32+J32*TC,2) -> 51457.66
B33: =B32+0.000001 -> 5.010303 | C33: LADRILLO SILICO CALCAREO TIPO P14 RF:2 HRS H>2.6M (ALVEOLOS PARCIALMENTE LLENO) | D33: m2 | E33: 0 | F33: 134.23 | H33: =+ROUND(F33+G33*TC,2) -> 134.23 | I33: =+ROUND(E33*F33,2) -> 0 | J33: =+ROUND(E33*G33,2) -> 0 | K33: =+ROUND(I33+J33*TC,2) -> 0
B34: =B33+0.000001 -> 5.010304 | C34: LADRILLO SILICO CALCAREO TIPO P20 RF:2 HRS H>2.6M (ALVEOLOS COMPLETAMENTE LLENO) | D34: m2 | E34: 0 | F34: 244.23 | H34: =+ROUND(F34+G34*TC,2) -> 244.23 | I34: =+ROUND(E34*F34,2) -> 0 | J34: =+ROUND(E34*G34,2) -> 0 | K34: =+ROUND(I34+J34*TC,2) -> 0
B35: =B30+0.0001 -> 5.0104 | C35: ACERO DE REFUERZO | E35: 0
B36: =B35+0.000001 -> 5.010401 | C36: ACERO DE REFUERZO FY= 4200 kg/cm2 GRADO 60 PARA TABIQUERÍA | D36: kg | E36: 2801.295 | F36: 0 | G36: 0.89 | H36: =+ROUND(F36+G36*TC,2) -> 2.98 | I36: =+ROUND(E36*F36,2) -> 0 | J36: =+ROUND(E36*G36,2) -> 2493.15 | K36: =+ROUND(I36+J36*TC,2) -> 8352.05
B37: =B35+0.0001 -> 5.0105 | C37: DINTELES | E37: 0
B38: =B37+0.000001 -> 5.010501 | C38: DINTELES DE LADRILLOS SILICO CALCAREO | D38: und | E38: 50 | F38: 125 | G38: 0 | H38: =+ROUND(F38+G38*TC,2) -> 125 | I38: =+ROUND(E38*F38,2) -> 6250 | J38: =+ROUND(E38*G38,2) -> 0 | K38: =+ROUND(I38+J38*TC,2) -> 6250
B39: =B38+0.000001 -> 5.010502 | C39: DINTELES DE LADRILLO SILICO CALCAREO RF | D39: und | E39: 14 | F39: 130 | G39: 0 | H39: =+ROUND(F39+G39*TC,2) -> 130 | I39: =+ROUND(E39*F39,2) -> 1820 | J39: =+ROUND(E39*G39,2) -> 0 | K39: =+ROUND(I39+J39*TC,2) -> 1820
B40: =B37+0.0001 -> 5.0106 | C40: TRABAJOS COMPLEMENTARIOS DE TABIQUERIA | E40: 0
B41: =B40+0.000001 -> 5.010601 | C41: PASES DE MANGUERA (0.20x20M) DOBLE PLACA DE ROCA DE YESO | D41: und | E41: 7 | F41: 70 | G41: 0 | H41: =+ROUND(F41+G41*TC,2) -> 70 | I41: =+ROUND(E41*F41,2) -> 490 | J41: =+ROUND(E41*G41,2) -> 0 | K41: =+ROUND(I41+J41*TC,2) -> 490
B42: =B13+0.0001 -> 5.0102 | C42: MUROS Y TABIQUES DRYWALL | E42: 0
B43: =B42+0.000001 -> 5.010201 | C43: DINTELES DRYWALL RF. DUCTOS INST. TEC. , H=0.30M APROX. | D43: ml | E43: 0 | G43: 0 | H43: =+ROUND(F43+G43*TC,2) -> 0 | I43: =+ROUND(E43*F43,2) -> 0 | J43: =+ROUND(E43*G43,2) -> 0 | K43: =+ROUND(I43+J43*TC,2) -> 0
B44: =B42+0.0001 -> 5.0103 | C44: PARAPETOS Y SARDINELES | E44: 0
B45: =B44+0.000001 -> 5.010301 | C45: PARAPETO A=0.10M , H=1.20ML (ESTACIONAM SOT) | D45: m2 | E45: 4.422 | F45: 111.23 | G45: 0 | H45: =+ROUND(F45+G45*TC,2) -> 111.23 | I45: =+ROUND(E45*F45,2) -> 491.86 | J45: =+ROUND(E45*G45,2) -> 0 | K45: =+ROUND(I45+J45*TC,2) -> 491.86
B46: =B45+0.000001 -> 5.010302 | C46: SARDINELES POZO SUMIDERO SOT (A=0.20M) , H=0.15M | D46: ml | E46: 0 | G46: 0 | H46: =+ROUND(F46+G46*TC,2) -> 0 | I46: =+ROUND(E46*F46,2) -> 0 | J46: =+ROUND(E46*G46,2) -> 0 | K46: =+ROUND(I46+J46*TC,2) -> 0
B47: =B46+0.000001 -> 5.010303 | C47: SARDINEL EN CUARTO DE ACOPIO H:0.10M (E=10CM) | D47: ml | E47: 6.7 | F47: 46.97 | G47: 0.78 | H47: =+ROUND(F47+G47*TC,2) -> 49.58 | I47: =+ROUND(E47*F47,2) -> 314.7 | J47: =+ROUND(E47*G47,2) -> 5.23 | K47: =+ROUND(I47+J47*TC,2) -> 332.22
B48: =B47+0.000001 -> 5.010304 | C48: SARDINLES CLOSET SOT (A=0.10M) , H=0.10M | D48: ml | E48: 0 | G48: 0.18 | H48: =+ROUND(F48+G48*TC,2) -> 0.6 | I48: =+ROUND(E48*F48,2) -> 0 | J48: =+ROUND(E48*G48,2) -> 0 | K48: =+ROUND(I48+J48*TC,2) -> 0
B49: =B47+0.0001 -> 5.010403 | C49: TRABAJOS DE CONCRETO | E49: 0 | F49: 70
B50: =B49+0.000001 -> 5.010404 | C50: LAVAMOPAS CUARTO DE ACOPIO | D50: ml | E50: 1.6 | F50: 367.94 | G50: 8.54 | H50: =+ROUND(F50+G50*TC,2) -> 396.55 | I50: =+ROUND(E50*F50,2) -> 588.7 | J50: =+ROUND(E50*G50,2) -> 13.66 | K50: =+ROUND(I50+J50*TC,2) -> 634.46
B51: =#REF!+0.000001 -> #REF! | C51: LAVADERO EN PETZONE | D51: ml | E51: 3.62 | F51: 420.18 | G51: 141.08 | H51: =+ROUND(F51+G51*TC,2) -> 892.8 | I51: =+ROUND(E51*F51,2) -> 1521.05 | J51: =+ROUND(E51*G51,2) -> 510.71 | K51: =+ROUND(I51+J51*TC,2) -> 3231.93
B52: =B12+0.01 -> 5.02 | C52: REVOQUES Y ENLUCIDOS | E52: 0 | L52: =SUM(I52:I59)+SUM(J52:J59)*TC -> 143104.25
B53: =B52+0.0001 -> 5.0201 | C53: SOLAQUEO DE MURO PANTALLA | D53: m2 | E53: 2791.047 | F53: 17.62 | H53: =+ROUND(F53+G53*TC,2) -> 17.62 | I53: =+ROUND(E53*F53,2) -> 49178.25 | J53: =+ROUND(E53*G53,2) -> 0 | K53: =+ROUND(I53+J53*TC,2) -> 49178.25
B54: =B53+0.0001 -> 5.0202 | C54: SOLAQUEO EN COLUMNAS Y PLACAS | D54: m2 | E54: 2305.5079 | F54: 17.23 | H54: =+ROUND(F54+G54*TC,2) -> 17.23 | I54: =+ROUND(E54*F54,2) -> 39723.9 | J54: =+ROUND(E54*G54,2) -> 0 | K54: =+ROUND(I54+J54*TC,2) -> 39723.9
B55: =B54+0.0001 -> 5.0203 | C55: SOLAQUEO EN COLUMNAS Y PLACAS A DOBLE ALTURA | D55: m2 | E55: 291.6255 | F55: 17.23 | H55: =+ROUND(F55+G55*TC,2) -> 17.23 | I55: =+ROUND(E55*F55,2) -> 5024.71 | J55: =+ROUND(E55*G55,2) -> 0 | K55: =+ROUND(I55+J55*TC,2) -> 5024.71
B56: =B54+0.0001 -> 5.0203 | C56: SOLAQUEO DE DUCTOS DE ASCENSORES | D56: m2 | E56: 372.359 | F56: 25.51 | H56: =+ROUND(F56+G56*TC,2) -> 25.51 | I56: =+ROUND(E56*F56,2) -> 9498.88 | J56: =+ROUND(E56*G56,2) -> 0 | K56: =+ROUND(I56+J56*TC,2) -> 9498.88
B57: =B56+0.0001 -> 5.0204 | C57: LIMPIEZA DE DUCTOS DE VENTILACION | D57: m2 | E57: 646.3968 | F57: 9.17 | H57: =+ROUND(F57+G57*TC,2) -> 9.17 | I57: =+ROUND(E57*F57,2) -> 5927.46 | J57: =+ROUND(E57*G57,2) -> 0 | K57: =+ROUND(I57+J57*TC,2) -> 5927.46
B58: =B57+0.0001 -> 5.0205 | C58: SOLAQUEO DE MUROS Y PLACAS DE ESCALERA | D58: m2 | E58: 263.1 | F58: 17.58 | H58: =+ROUND(F58+G58*TC,2) -> 17.58 | I58: =+ROUND(E58*F58,2) -> 4625.3 | J58: =+ROUND(E58*G58,2) -> 0 | K58: =+ROUND(I58+J58*TC,2) -> 4625.3
B59: =B58+0.0001 -> 5.0206 | C59: IMPERMEABILIZACION DE CISTERNAS: | D59: m2 | E59: 529.559 | F59: 55 | H59: =+ROUND(F59+G59*TC,2) -> 55 | I59: =+ROUND(E59*F59,2) -> 29125.75 | J59: =+ROUND(E59*G59,2) -> 0 | K59: =+ROUND(I59+J59*TC,2) -> 29125.75
B60: =B52+0.01 -> 5.03 | C60: CIELORASOS | E60: 0 | L60: =SUM(I60:I65)+SUM(J60:J65)*TC -> 108345.45
B61: =B60+0.0001 -> 5.0301 | C61: LIMPIEZA Y RESANE DE PRELOSAS EN SÓTANOS | D61: m2 | E61: 7024.616 | F61: 4.1 | H61: =+ROUND(F61+G61*TC,2) -> 4.1 | I61: =+ROUND(E61*F61,2) -> 28800.93 | J61: =+ROUND(E61*G61,2) -> 0 | K61: =+ROUND(I61+J61*TC,2) -> 28800.93
C62: SOLAQUEO DE CIELO RASO EN SÓTANOS (INC SOLAQUEO DE TECHO DE CISTERNA Y CTO BOMBAS) | D62: m2 | E62: 898.3605 | F62: 17.49 | H62: =+ROUND(F62+G62*TC,2) -> 17.49 | I62: =+ROUND(E62*F62,2) -> 15712.33 | J62: =+ROUND(E62*G62,2) -> 0 | K62: =+ROUND(I62+J62*TC,2) -> 15712.33
B63: =B61+0.0001 -> 5.0302 | C63: SOLAQUEO DE VIGAS EN SOTANOS (EN FONDO Y COSTADO) | D63: m2 | E63: 1646.7166 | F63: 23.98 | H63: =+ROUND(F63+G63*TC,2) -> 23.98 | I63: =+ROUND(E63*F63,2) -> 39488.26 | J63: =+ROUND(E63*G63,2) -> 0 | K63: =+ROUND(I63+J63*TC,2) -> 39488.26
B64: =B63+0.0001 -> 5.0303 | C64: SOLAQUEO DE VIGAS EN SOTANOS (EN FONDO Y COSTADO) A DOBLE ALTURA | D64: m2 | E64: 370.63448 | F64: 28.42 | H64: =+ROUND(F64+G64*TC,2) -> 28.42 | I64: =+ROUND(E64*F64,2) -> 10533.43 | J64: =+ROUND(E64*G64,2) -> 0 | K64: =+ROUND(I64+J64*TC,2) -> 10533.43
B65: =B63+0.0001 -> 5.0303 | C65: IMPERMEABILIZACION DE CISTERNAS: | D65: m2 | E65: 251.1 | F65: 55 | H65: =+ROUND(F65+G65*TC,2) -> 55 | I65: =+ROUND(E65*F65,2) -> 13810.5 | J65: =+ROUND(E65*G65,2) -> 0 | K65: =+ROUND(I65+J65*TC,2) -> 13810.5
B66: =B57+0.01 -> 5.0304 | C66: FALSOS CIELOS Y COBERTURAS | E66: 0 | L66: =SUM(I66:I68)+SUM(J66:J68)*TC -> 0
B67: =B66+0.0001 -> 5.0305 | C67: FALSO CIELO RASO DE DRYWALL ESCALERA | D67: m2 | E67: 0 | F67: 105 | H67: =+ROUND(F67+G67*TC,2) -> 105 | I67: =+ROUND(E67*F67,2) -> 0 | J67: =+ROUND(E67*G67,2) -> 0 | K67: =+ROUND(I67+J67*TC,2) -> 0
B68: =B60+0.01 -> 5.04 | C68: PISOS | E68: 0 | L68: =SUM(I68:I92)+SUM(J68:J92)*TC -> 276765.99
C69: NIVELACIÓN DE PISO | E69: 0
C70: NIVELACIÓN DE PISO | D70: m2 | E70: 126.08 | F70: 22.49 | H70: =+ROUND(F70+G70*TC,2) -> 22.49 | I70: =+ROUND(E70*F70,2) -> 2835.54 | J70: =+ROUND(E70*G70,2) -> 0 | K70: =+ROUND(I70+J70*TC,2) -> 2835.54
B71: =B68+0.0001 -> 5.0401 | C71: GRUPO ELECTROGENO | E71: 0 | H71: =+ROUND(F71+G71*TC,2) -> 0 | I71: =+ROUND(E71*F71,2) -> 0 | J71: =+ROUND(E71*G71,2) -> 0 | K71: =+ROUND(I71+J71*TC,2) -> 0
B72: =B71+0.000001 -> 5.040101 | C72: PISO CEMENTO PULIDO | D72: m2 | E72: 34.2 | F72: 46.92 | H72: =+ROUND(F72+G72*TC,2) -> 46.92 | I72: =+ROUND(E72*F72,2) -> 1604.66 | J72: =+ROUND(E72*G72,2) -> 0 | K72: =+ROUND(I72+J72*TC,2) -> 1604.66
B73: =B71+0.0001 -> 5.0402 | C73: HALL DE ASCENSORES | E73: 0
B74: =B73+0.000001 -> 5.040201 | C74: CERAMICO CEMENTO GRIS 45X45CM | D74: m2 | E74: 95.98 | F74: 72.34 | H74: =+ROUND(F74+G74*TC,2) -> 72.34 | I74: =+ROUND(E74*F74,2) -> 6943.19 | J74: =+ROUND(E74*G74,2) -> 0 | K74: =+ROUND(I74+J74*TC,2) -> 6943.19
B75: =B73+0.0001 -> 5.0403 | C75: DEPOSITOS, ESP ABIERTO Y PASILLO | E75: 0
B76: =B75+0.000001 -> 5.040301 | C76: PISO CEMENTO SEMIPULIDO | D76: m2 | E76: 531.09 | F76: 45.02 | H76: =+ROUND(F76+G76*TC,2) -> 45.02 | I76: =+ROUND(E76*F76,2) -> 23909.67 | J76: =+ROUND(E76*G76,2) -> 0 | K76: =+ROUND(I76+J76*TC,2) -> 23909.67
B77: =B75+0.0001 -> 5.0404 | C77: ESTACIONAMIENTOS VEHICULARES | E77: 0
B78: =B77+0.000001 -> 5.040401 | C78: CEMENTO FROTACHADO_ | D78: m2 | E78: 3666.43 | F78: 15.65 | H78: =+ROUND(F78+G78*TC,2) -> 15.65 | I78: =+ROUND(E78*F78,2) -> 57379.63 | J78: =+ROUND(E78*G78,2) -> 0 | K78: =+ROUND(I78+J78*TC,2) -> 57379.63
B79: =B77+0.0001 -> 5.0405 | C79: ESCALERA | E79: 0
B80: =B79+0.000001 -> 5.040501 | C80: PISO CEMENTO PULIDO | D80: m2 | E80: 50.03 | F80: 46.92 | H80: =+ROUND(F80+G80*TC,2) -> 46.92 | I80: =+ROUND(E80*F80,2) -> 2347.41 | J80: =+ROUND(E80*G80,2) -> 0 | K80: =+ROUND(I80+J80*TC,2) -> 2347.41
B81: =B79+0.0001 -> 5.0406 | C81: ESTACIONAMIENTO DE BICICLETAS | E81: 0
B82: =B81+0.000001 -> 5.040601 | C82: PISO CEMENTO BARRIDO | D82: m2 | E82: 138.32 | F82: 15.34 | H82: =+ROUND(F82+G82*TC,2) -> 15.34 | I82: =+ROUND(E82*F82,2) -> 2121.83 | J82: =+ROUND(E82*G82,2) -> 0 | K82: =+ROUND(I82+J82*TC,2) -> 2121.83
B83: =B81+0.0001 -> 5.0407 | C83: RAMPAS VEHICULAR | E83: 0
B84: =B83+0.000001 -> 5.040701 | C84: PISO CEMENTO BRUÑADO | D84: m2 | E84: 3327.39 | F84: 47.24 | H84: =+ROUND(F84+G84*TC,2) -> 47.24 | I84: =+ROUND(E84*F84,2) -> 157185.9 | J84: =+ROUND(E84*G84,2) -> 0 | K84: =+ROUND(I84+J84*TC,2) -> 157185.9
B85: =B83+0.0001 -> 5.0408 | C85: CTO BOMBAS / TRAMPA SOT. | E85: 0
B86: =B85+0.000001 -> 5.040801 | C86: PISO CEMENTO SEMIPULIDO | D86: m2 | E86: 123.57 | F86: 45.02 | H86: =+ROUND(F86+G86*TC,2) -> 45.02 | I86: =+ROUND(E86*F86,2) -> 5563.12 | J86: =+ROUND(E86*G86,2) -> 0 | K86: =+ROUND(I86+J86*TC,2) -> 5563.12
B87: =B85+0.0001 -> 5.0409 | C87: CISTERNA | E87: 0
B88: =B87+0.000001 -> 5.040901 | C88: IMPERMEABILIZADO EN CISTERNA | D88: m2 | E88: 251.1 | F88: 55 | H88: =+ROUND(F88+G88*TC,2) -> 55 | I88: =+ROUND(E88*F88,2) -> 13810.5 | J88: =+ROUND(E88*G88,2) -> 0 | K88: =+ROUND(I88+J88*TC,2) -> 13810.5
B89: =B87+0.0001 -> 5.041 | C89: CTO DE ACOPIO | E89: 0
B90: =B89+0.000001 -> 5.041001 | C90: CERAMICO AMERICA BLANCO 45x45CM. CELIMA | D90: m2 | E90: 18.5 | F90: 71.91 | H90: =+ROUND(F90+G90*TC,2) -> 71.91 | I90: =+ROUND(E90*F90,2) -> 1330.34 | J90: =+ROUND(E90*G90,2) -> 0 | K90: =+ROUND(I90+J90*TC,2) -> 1330.34
B91: =B89+0.0001 -> 5.0411 | C91: PET ZONE | E91: 0
B92: =B91+0.000001 -> 5.041101 | C92: PORCELANATO ESMALATADO WUART DE LUNE MATE 20 X 20 | D92: m2 | E92: 11.6 | F92: 149.5 | H92: =+ROUND(F92+G92*TC,2) -> 149.5 | I92: =+ROUND(E92*F92,2) -> 1734.2 | J92: =+ROUND(E92*G92,2) -> 0 | K92: =+ROUND(I92+J92*TC,2) -> 1734.2
B93: =B84+0.01 -> 5.050701 | C93: ZOCALOS | E93: 0 | L93: =SUM(I93:I99)+SUM(J93:J99)*TC -> 10954.814
B94: =B93+0.0001 -> 5.050801 | C94: ACOPIOS SOT | E94: 0
B95: =B94+0.000001 -> 5.050802 | C95: CERAMICO AMERICA BLANCO 45x45CM. CELIMA | D95: m2 | E95: 38.528 | F95: 71.91 | H95: =+ROUND(F95+G95*TC,2) -> 71.91 | I95: =+ROUND(E95*F95,2) -> 2770.55 | J95: =+ROUND(E95*G95,2) -> 0 | K95: =+ROUND(I95+J95*TC,2) -> 2770.55
B96: =B94+0.0001 -> 5.050901 | C96: PET ZONE | E96: 0
B97: =B96+0.000001 -> 5.050902 | C97: CERAMICO ESMALTADO URBAN BRICK BLACK MATE | D97: m2 | E97: 13.771 | F97: 126.12 | H97: =+ROUND(F97+G97*TC,2) -> 126.12 | I97: =+ROUND(E97*F97,2) -> 1736.8 | J97: =+ROUND(E97*G97,2) -> 0 | K97: =+ROUND(I97+J97*TC,2) -> 1736.8
B98: =B97+0.000001 -> 5.050903 | C98: TERRAZO MATIZADO (LAVADERO) - PET ZONE / SOT | D98: m2 | E98: 4.5 | F98: 78 | H98: =+ROUND(F98+G98*TC,2) -> 78 | I98: =+ROUND(E98*F98,2) -> 351 | J98: =+ROUND(E98*G98,2) -> 0 | K98: =+ROUND(I98+J98*TC,2) -> 351
B99: =B98+0.000001 -> 5.050904 | C99: WAL PANEL PINTADO COLOR AP54 - 1 GRAY FOAM. PANTONE COLOR CENTRO - PET ZONE / SOT | D99: m2 | E99: 16.544 | G99: 110 | H99: =+ROUND(F99+G99*TC,2) -> 368.5 | I99: =+ROUND(E99*F99,2) -> 0 | J99: =+ROUND(E99*G99,2) -> 1819.84 | K99: =+ROUND(I99+J99*TC,2) -> 6096.46
B100: =B68+0.01 -> 5.05 | C100: CONTRAZÓCALOS | E100: 0 | H100: =+ROUND(F100+G100*TC,2) -> 0 | I100: =+ROUND(E100*F100,2) -> 0 | J100: =+ROUND(E100*G100,2) -> 0 | K100: =+ROUND(I100+J100*TC,2) -> 0 | L100: =SUM(I100:I112)+SUM(J100:J112)*TC -> 35028.01
B101: =B100+0.0001 -> 5.0501 | C101: CTO BOMBAS / TRAMPA SOT. | E101: 0
B102: =B101+0.000001 -> 5.050101 | C102: Contrazócalo cemento pulido | D102: ml | E102: 68.48 | F102: 36 | H102: =+ROUND(F102+G102*TC,2) -> 36 | I102: =+ROUND(E102*F102,2) -> 2465.28 | J102: =+ROUND(E102*G102,2) -> 0 | K102: =+ROUND(I102+J102*TC,2) -> 2465.28
B103: =B101+0.0001 -> 5.0502 | C103: HALL ASCENSORES | E103: 0
...

Sheet ARQ TORRE
B2: ARQUITECTURA TORRE
B4: =+'ARQ SOT'!C4 -> PRESUPUESTO | GERMANIA | REV 09
B5: =+B2 -> ARQUITECTURA TORRE
B6: =+'ARQ SOT'!C6 -> VYV INMOBILIARIA
B7: =+'ARQ SOT'!C7 -> SURQUILLO
B8: =+'ARQ SOT'!C8 -> 46090
B10: DESCRIPCION | C10: UND | D10: METRADO | E10: P.U. (PEN) | F10: P.U. (USD) | G10: P.U. TOTAL (PEN) | H10: PRECIO PARCIAL (PEN) | I10: PRECIO PARCIAL (USD) | J10: PARCIAL TOTAL (PEN) | K10: TOTAL
B11: =#REF! -> #REF!
B12: MUROS Y TABIQUES | G12: =IFERROR(IF(C12<>0,E12+F12*TC," ")," ") | H12: =IFERROR(IF($D12=0,"",$D12*E12),"") | I12: =IFERROR(IF($D12=0,"",$D12*F12),"") | J12: =IFERROR(IF(D12<>0,(D12*G12)," "),0) | K12: =SUM(H12:H106)+SUM(I12:I106)*TC -> 4783846.7
B13: MUROS Y TABIQUES SILICO CALCAREOS | G13: =IFERROR(IF(C13<>0,(E13+F13*TC)," ")," ") | H13: =IFERROR(IF($D13=0,"",$D13*E13),"") | I13: =IFERROR(IF($D13=0,"",$D13*F13),"") | J13: =IFERROR(IF(D13<>0,(D13*G13)," "),0)
B14: ALTURA < 2.60 | G14: =IFERROR(IF(C14<>0,(E14+F14*TC)," ")," ") | H14: =IFERROR(IF($D14=0,"",$D14*E14),"") | I14: =IFERROR(IF($D14=0,"",$D14*F14),"") | J14: =IFERROR(IF(D14<>0,(D14*G14)," "),0)
B15: LADRILLO SILICO CALCAREO TIPO P7 H<2.6M | C15: m2 | D15: 645.25 | E15: 104.23 | F15: 0 | G15: =+ROUND(E15+F15*TC,2) -> 104.23 | H15: =+ROUND(D15*E15,2) -> 67254.41 | I15: =+ROUND(D15*F15,2) -> 0 | J15: =+ROUND(H15+I15*TC,2) -> 67254.41
B16: LADRILLO SILICO CALCAREO TIPO P10 H<2.6M | C16: m2 | D16: 14118.78 | E16: 111.23 | F16: 0 | G16: =+ROUND(E16+F16*TC,2) -> 111.23 | H16: =+ROUND(D16*E16,2) -> 1570431.9 | I16: =+ROUND(D16*F16,2) -> 0 | J16: =+ROUND(H16+I16*TC,2) -> 1570431.9
B17: LADRILLO SILICO CALCAREO TIPO P12 H<2.6M | C17: m2 | D17: 1073.75 | E17: 117.23 | F17: 0 | G17: =+ROUND(E17+F17*TC,2) -> 117.23 | H17: =+ROUND(D17*E17,2) -> 125875.71 | I17: =+ROUND(D17*F17,2) -> 0 | J17: =+ROUND(H17+I17*TC,2) -> 125875.71
B18: LADRILLO SILICO CALCAREO TIPO P14 H<2.6M | C18: m2 | D18: 120.89 | E18: 125.23 | F18: 0 | G18: =+ROUND(E18+F18*TC,2) -> 125.23 | H18: =+ROUND(D18*E18,2) -> 15139.05 | I18: =+ROUND(D18*F18,2) -> 0 | J18: =+ROUND(H18+I18*TC,2) -> 15139.05
B19: LADRILLO SILICO CALCAREO TIPO P20 H<2.6M | C19: m2 | E19: 206.23 | F19: 0 | G19: =+ROUND(E19+F19*TC,2) -> 206.23 | H19: =+ROUND(D19*E19,2) -> 0 | I19: =+ROUND(D19*F19,2) -> 0 | J19: =+ROUND(H19+I19*TC,2) -> 0
B20: LADRILLO SILICO CALCAREO TIPO P25 H<2.6M | C20: m2 | E20: 220.23 | F20: 0 | G20: =+ROUND(E20+F20*TC,2) -> 220.23 | H20: =+ROUND(D20*E20,2) -> 0 | I20: =+ROUND(D20*F20,2) -> 0 | J20: =+ROUND(H20+I20*TC,2) -> 0
B21: LADRILLO SILICO CALCAREO TIPO P30 H<2.6M | C21: m2 | E21: 220.23 | F21: 0 | G21: =+ROUND(E21+F21*TC,2) -> 220.23 | H21: =+ROUND(D21*E21,2) -> 0 | I21: =+ROUND(D21*F21,2) -> 0 | J21: =+ROUND(H21+I21*TC,2) -> 0
B22: LADRILLO SILICO CALCAREO TIPO P40 H<2.6M | C22: m2 | E22: 220.23 | F22: 0 | G22: =+ROUND(E22+F22*TC,2) -> 220.23 | H22: =+ROUND(D22*E22,2) -> 0 | I22: =+ROUND(D22*F22,2) -> 0 | J22: =+ROUND(H22+I22*TC,2) -> 0
B23: ALTURA > 2.60 | J23: =+ROUND(H23+I23*TC,2) -> 0
B24: LADRILLO SILICO CALCAREO TIPO P7 H>2.6M | C24: m2 | D24: 44 | E24: 113.23 | F24: 0 | G24: =+ROUND(E24+F24*TC,2) -> 113.23 | H24: =+ROUND(D24*E24,2) -> 4982.12 | I24: =+ROUND(D24*F24,2) -> 0 | J24: =+ROUND(H24+I24*TC,2) -> 4982.12
B25: LADRILLO SILICO CALCAREO TIPO P10 H>2.6M | C25: m2 | D25: 388.45 | E25: 120.23 | F25: 0 | G25: =+ROUND(E25+F25*TC,2) -> 120.23 | H25: =+ROUND(D25*E25,2) -> 46703.34 | I25: =+ROUND(D25*F25,2) -> 0 | J25: =+ROUND(H25+I25*TC,2) -> 46703.34
B26: LADRILLO SILICO CALCAREO TIPO P12 H>2.6M | C26: m2 | D26: 448.35 | E26: 126.23 | F26: 0 | G26: =+ROUND(E26+F26*TC,2) -> 126.23 | H26: =+ROUND(D26*E26,2) -> 56595.22 | I26: =+ROUND(D26*F26,2) -> 0 | J26: =+ROUND(H26+I26*TC,2) -> 56595.22
B27: LADRILLO SILICO CALCAREO TIPO P14 H>2.6M | C27: m2 | E27: 134.23 | F27: 0 | G27: =+ROUND(E27+F27*TC,2) -> 134.23 | H27: =+ROUND(D27*E27,2) -> 0 | I27: =+ROUND(D27*F27,2) -> 0 | J27: =+ROUND(H27+I27*TC,2) -> 0
B28: LADRILLO SILICO CALCAREO TIPO P20 H>2.6M | C28: m2 | E28: 224.23 | F28: 0 | G28: =+ROUND(E28+F28*TC,2) -> 224.23 | H28: =+ROUND(D28*E28,2) -> 0 | I28: =+ROUND(D28*F28,2) -> 0 | J28: =+ROUND(H28+I28*TC,2) -> 0
B29: LADRILLO SILICO CALCAREO TIPO P25 H>2.6M | C29: m2 | E29: 238.23 | F29: 0 | G29: =+ROUND(E29+F29*TC,2) -> 238.23 | H29: =+ROUND(D29*E29,2) -> 0 | I29: =+ROUND(D29*F29,2) -> 0 | J29: =+ROUND(H29+I29*TC,2) -> 0
B30: LADRILLO SILICO CALCAREO TIPO P55 H>2.6M | C30: m2 | E30: 0 | F30: 0 | G30: =+ROUND(E30+F30*TC,2) -> 0 | H30: =+ROUND(D30*E30,2) -> 0 | I30: =+ROUND(D30*F30,2) -> 0 | J30: =+ROUND(H30+I30*TC,2) -> 0
B31: CORTAFUEGO < 2.60 | J31: =+ROUND(H31+I31*TC,2) -> 0
B32: LADRILLO SILICO CALCAREO TIPO P10 RF:2 HRS H<2.6M (ALVEOLOS COMPLETAMENTE LLENO) | C32: m2 | D32: 1.34 | E32: 121.23 | F32: 0 | G32: =+ROUND(E32+F32*TC,2) -> 121.23 | H32: =+ROUND(D32*E32,2) -> 162.45 | I32: =+ROUND(D32*F32,2) -> 0 | J32: =+ROUND(H32+I32*TC,2) -> 162.45
B33: LADRILLO SILICO CALCAREO TIPO P12 RF:2 HRS H<2.6M (ALVEOLOS PARCIALMENTE LLENO) | C33: m2 | D33: 11970.5 | E33: 117.23 | F33: 0 | G33: =+ROUND(E33+F33*TC,2) -> 117.23 | H33: =+ROUND(D33*E33,2) -> 1403301.7 | I33: =+ROUND(D33*F33,2) -> 0 | J33: =+ROUND(H33+I33*TC,2) -> 1403301.7
B34: LADRILLO SILICO CALCAREO TIPO P14 RF:2 HRS H<2.6M (ALVEOLOS PARCIALMENTE LLENO) | C34: m2 | D34: 741.96 | E34: 125.23 | F34: 0 | G34: =+ROUND(E34+F34*TC,2) -> 125.23 | H34: =+ROUND(D34*E34,2) -> 92915.65 | I34: =+ROUND(D34*F34,2) -> 0 | J34: =+ROUND(H34+I34*TC,2) -> 92915.65
B35: LADRILLO SILICO CALCAREO TIPO P20 RF:2 HRS H<2.6M (ALVEOLOS PARCIALMENTE LLENO) | C35: m2 | E35: 226.23 | F35: 0 | G35: =+ROUND(E35+F35*TC,2) -> 226.23 | H35: =+ROUND(D35*E35,2) -> 0 | I35: =+ROUND(D35*F35,2) -> 0 | J35: =+ROUND(H35+I35*TC,2) -> 0
B36: LADRILLO SILICO CALCAREO TIPO P30 RF:2 HRS H<2.6M (ALVEOLOS PARCIALMENTE LLENO) | C36: m2 | E36: 220.23 | F36: 0 | G36: =+ROUND(E36+F36*TC,2) -> 220.23 | H36: =+ROUND(D36*E36,2) -> 0 | I36: =+ROUND(D36*F36,2) -> 0 | J36: =+ROUND(H36+I36*TC,2) -> 0
B37: LADRILLO SILICO CALCAREO TIPO P35 RF:2 HRS H<2.6M (ALVEOLOS PARCIALMENTE LLENO) | C37: m2 | E37: 220.23 | F37: 0 | G37: =+ROUND(E37+F37*TC,2) -> 220.23 | H37: =+ROUND(D37*E37,2) -> 0 | I37: =+ROUND(D37*F37,2) -> 0 | J37: =+ROUND(H37+I37*TC,2) -> 0
B38: LADRILLO SILICO CALCAREO TIPO P40 RF:2 HRS H<2.6M (ALVEOLOS PARCIALMENTE LLENO) | C38: m2 | E38: 220.23 | F38: 0 | G38: =+ROUND(E38+F38*TC,2) -> 220.23 | H38: =+ROUND(D38*E38,2) -> 0 | I38: =+ROUND(D38*F38,2) -> 0 | J38: =+ROUND(H38+I38*TC,2) -> 0
B39: LADRILLO SILICO CALCAREO TIPO P45 RF:2 HRS H<2.6M (ALVEOLOS PARCIALMENTE LLENO) | C39: m2 | E39: 220.23 | F39: 0 | G39: =+ROUND(E39+F39*TC,2) -> 220.23 | H39: =+ROUND(D39*E39,2) -> 0 | I39: =+ROUND(D39*F39,2) -> 0 | J39: =+ROUND(H39+I39*TC,2) -> 0
B40: LADRILLO SILICO CALCAREO TIPO P50 RF:2 HRS H<2.6M (ALVEOLOS PARCIALMENTE LLENO) | C40: m2 | E40: 220.23 | F40: 0 | G40: =+ROUND(E40+F40*TC,2) -> 220.23 | H40: =+ROUND(D40*E40,2) -> 0 | I40: =+ROUND(D40*F40,2) -> 0 | J40: =+ROUND(H40+I40*TC,2) -> 0
B41: CORTAFUEGO > 2.60 | J41: =+ROUND(H41+I41*TC,2) -> 0
B42: LADRILLO SILICO CALCAREO TIPO P7 RF:2 HRS H>2.6M (ALVEOLOS COMPLETAMENTE LLENO) | C42: m2 | E42: 123.23 | F42: 0 | G42: =+ROUND(E42+F42*TC,2) -> 123.23 | H42: =+ROUND(D42*E42,2) -> 0 | I42: =+ROUND(D42*F42,2) -> 0 | J42: =+ROUND(H42+I42*TC,2) -> 0
B43: LADRILLO SILICO CALCAREO TIPO P10 RF:2 HRS H>2.6M (ALVEOLOS COMPLETAMENTE LLENO) | C43: m2 | E43: 130.23 | F43: 0 | G43: =+ROUND(E43+F43*TC,2) -> 130.23 | H43: =+ROUND(D43*E43,2) -> 0 | I43: =+ROUND(D43*F43,2) -> 0 | J43: =+ROUND(H43+I43*TC,2) -> 0
B44: LADRILLO SILICO CALCAREO TIPO P12 RF:2 HRS H>2.6M (ALVEOLOS PARCIALMENTE LLENO) | C44: m2 | D44: 1804.9 | E44: 126.23 | F44: 0 | G44: =+ROUND(E44+F44*TC,2) -> 126.23 | H44: =+ROUND(D44*E44,2) -> 227832.53 | I44: =+ROUND(D44*F44,2) -> 0 | J44: =+ROUND(H44+I44*TC,2) -> 227832.53
B45: LADRILLO SILICO CALCAREO TIPO P14 RF:2 HRS H>2.6M (ALVEOLOS PARCIALMENTE LLENO) | C45: m2 | D45: 232.54 | E45: 134.23 | F45: 0 | G45: =+ROUND(E45+F45*TC,2) -> 134.23 | H45: =+ROUND(D45*E45,2) -> 31213.84 | I45: =+ROUND(D45*F45,2) -> 0 | J45: =+ROUND(H45+I45*TC,2) -> 31213.84
B46: LADRILLO SILICO CALCAREO TIPO P25 RF:2 HRS H>2.6M (ALVEOLOS COMPLETAMENTE LLENO) | C46: m2 | E46: 0 | F46: 0 | G46: =+ROUND(E46+F46*TC,2) -> 0 | H46: =+ROUND(D46*E46,2) -> 0 | I46: =+ROUND(D46*F46,2) -> 0 | J46: =+ROUND(H46+I46*TC,2) -> 0
B47: LADRILLO SILICO CALCAREO TIPO P30 RF:2 HRS H>2.6M (ALVEOLOS COMPLETAMENTE LLENO) | C47: m2 | E47: 0 | F47: 0 | G47: =+ROUND(E47+F47*TC,2) -> 0 | H47: =+ROUND(D47*E47,2) -> 0 | I47: =+ROUND(D47*F47,2) -> 0 | J47: =+ROUND(H47+I47*TC,2) -> 0
B48: LADRILLO SILICO CALCAREO TIPO P60 RF:2 HRS H>2.6M (ALVEOLOS COMPLETAMENTE LLENO) | C48: m2 | E48: 0 | F48: 0 | G48: =+ROUND(E48+F48*TC,2) -> 0 | H48: =+ROUND(D48*E48,2) -> 0 | I48: =+ROUND(D48*F48,2) -> 0 | J48: =+ROUND(H48+I48*TC,2) -> 0
B49: ACERO DE REFUERZO | J49: =+ROUND(H49+I49*TC,2) -> 0
B50: ACERO DE REFUERZO FY= 4200 kg/cm2 GRADO 60 PARA TABIQUERÍA | C50: kg | D50: 47386.065 | E50: 0 | F50: 0.89 | G50: =+ROUND(E50+F50*TC,2) -> 2.98 | H50: =+ROUND(D50*E50,2) -> 0 | I50: =+ROUND(D50*F50,2) -> 42173.6 | J50: =+ROUND(H50+I50*TC,2) -> 141281.56
B51: DINTELES | J51: =+ROUND(H51+I51*TC,2) -> 0
B52: DINTELES DE LADRILLOS SILICO CALCAREO | C52: und | D52: 2013 | E52: 125 | F52: 0 | G52: =+ROUND(E52+F52*TC,2) -> 125 | H52: =+ROUND(D52*E52,2) -> 251625 | I52: =+ROUND(D52*F52,2) -> 0 | J52: =+ROUND(H52+I52*TC,2) -> 251625
B53: DINTELES DE LADRILLO SILICO CALCAREO RF | C53: und | D53: 116 | E53: 130 | F53: 0 | G53: =+ROUND(E53+F53*TC,2) -> 130 | H53: =+ROUND(D53*E53,2) -> 15080 | I53: =+ROUND(D53*F53,2) -> 0 | J53: =+ROUND(H53+I53*TC,2) -> 15080
B54: TRABAJOS COMPLEMENTARIOS DE TABIQUERIA | J54: =+ROUND(H54+I54*TC,2) -> 0
B55: FORJADO DE TABLEROS | C55: und | D55: 334 | E55: 130 | F55: 0 | G55: =+ROUND(E55+F55*TC,2) -> 130 | H55: =+ROUND(D55*E55,2) -> 43420 | I55: =+ROUND(D55*F55,2) -> 0 | J55: =+ROUND(H55+I55*TC,2) -> 43420
B56: ENCOFRADO DE TUBERIAS DE MONTANTE DE VENTILACIÓN | C56: und | D56: 2300 | E56: 80 | F56: 0 | G56: =+ROUND(E56+F56*TC,2) -> 80 | H56: =+ROUND(D56*E56,2) -> 184000 | I56: =+ROUND(D56*F56,2) -> 0 | J56: =+ROUND(H56+I56*TC,2) -> 184000
B57: PASES DE MANGUERA (0.20x0.20M) | C57: und | D57: 106 | E57: 70 | F57: 0 | G57: =+ROUND(E57+F57*TC,2) -> 70 | H57: =+ROUND(D57*E57,2) -> 7420 | I57: =+ROUND(D57*F57,2) -> 0 | J57: =+ROUND(H57+I57*TC,2) -> 7420
B58: NICHOS PARA EXTRACTOR DE SSHH Y VESTIBULOS PREVIOS | C58: und | D58: 622 | E58: 70 | F58: 0 | G58: =+ROUND(E58+F58*TC,2) -> 70 | H58: =+ROUND(D58*E58,2) -> 43540 | I58: =+ROUND(D58*F58,2) -> 0 | J58: =+ROUND(H58+I58*TC,2) -> 43540
B59: OTROS TABIQUERIA | J59: =+ROUND(H59+I59*TC,2) -> 0
B60: CASETA, ALMACEN DE HERRAMIENTAS, VESTIBULO Y BANCAS-SC TABIQUERIA | C60: glb | E60: 0 | F60: 0 | G60: =+ROUND(E60+F60*TC,2) -> 0 | H60: =+ROUND(D60*E60,2) -> 0 | I60: =+ROUND(D60*F60,2) -> 0 | J60: =+ROUND(H60+I60*TC,2) -> 0
B61: SC PREVENCIONISTA DE RIESGO-SC TABIQUERIA | C61: mes | D61: 5 | E61: 4500 | F61: 0 | G61: =+ROUND(E61+F61*TC,2) -> 4500 | H61: =+ROUND(D61*E61,2) -> 22500 | I61: =+ROUND(D61*F61,2) -> 0 | J61: =+ROUND(H61+I61*TC,2) -> 22500
B62: MEDIDORES | J62: =+ROUND(H62+I62*TC,2) -> 0
B63: MURO DE ALBAÑILERIA KK E:25CM | C63: m2 | E63: 0 | F63: 0 | G63: =+ROUND(E63+F63*TC,2) -> 0 | H63: =+ROUND(D63*E63,2) -> 0 | I63: =+ROUND(D63*F63,2) -> 0 | J63: =+ROUND(H63+I63*TC,2) -> 0
B64: MURO DE ALBAÑILERIA KK BANCO DE MEDIDORES H=3.00M, E: 25CM | C64: m2 | E64: 113.3 | F64: 0 | G64: =+ROUND(E64+F64*TC,2) -> 113.3 | H64: =+ROUND(D64*E64,2) -> 0 | I64: =+ROUND(D64*F64,2) -> 0 | J64: =+ROUND(H64+I64*TC,2) -> 0
B65: MURO DE ALBAÑILERIA KK BANCO DE MEDIDORES H=6.00M, E: 25CM | C65: m2 | E65: 169.95 | F65: 0 | G65: =+ROUND(E65+F65*TC,2) -> 169.95 | H65: =+ROUND(D65*E65,2) -> 0 | I65: =+ROUND(D65*F65,2) -> 0 | J65: =+ROUND(H65+I65*TC,2) -> 0
B66: MUROS Y TABIQUES DRYWALL | J66: =+ROUND(H66+I66*TC,2) -> 0
B67: DRYWALL PERIMETRAL H=3.00M CON PLANCHA DE MATERIAL LIVIANO | C67: m2 | E67: 0 | F67: 0 | G67: =+ROUND(E67+F67*TC,2) -> 0 | H67: =+ROUND(D67*E67,2) -> 0 | I67: =+ROUND(D67*F67,2) -> 0 | J67: =+ROUND(H67+I67*TC,2) -> 0
B68: ESTRUCTURA DE MATERIAL LIGERO H: 3.00 M | C68: kg | E68: 0 | F68: 0 | G68: =+ROUND(E68+F68*TC,2) -> 0 | H68: =+ROUND(D68*E68,2) -> 0 | I68: =+ROUND(D68*F68,2) -> 0 | J68: =+ROUND(H68+I68*TC,2) -> 0
B69: DINTELES DE DRYWALL RH (SOBRE LAVANDERIAS) | C69: ml | E69: 0 | F69: 0 | G69: =+ROUND(E69+F69*TC,2) -> 0 | H69: =+ROUND(D69*E69,2) -> 0 | I69: =+ROUND(D69*F69,2) -> 0 | J69: =+ROUND(H69+I69*TC,2) -> 0
B70: DINTELES DE LADRILLO SILICO CALCAREO EN MAMPARAS | C70: ml | E70: 0 | F70: 0 | G70: =+ROUND(E70+F70*TC,2) -> 0 | H70: =+ROUND(D70*E70,2) -> 0 | I70: =+ROUND(D70*F70,2) -> 0 | J70: =+ROUND(H70+I70*TC,2) -> 0
B71: DINTEL FCR RF:2HRS (MONTANTES DUCTO) | C71: ml | E71: 0 | F71: 0 | G71: =+ROUND(E71+F71*TC,2) -> 0 | H71: =+ROUND(D71*E71,2) -> 0 | I71: =+ROUND(D71*F71,2) -> 0 | J71: =+ROUND(H71+I71*TC,2) -> 0
B72: SOBREMURO | C72: m2 | D72: 593.41 | E72: 110 | F72: 0 | G72: =+ROUND(E72+F72*TC,2) -> 110 | H72: =+ROUND(D72*E72,2) -> 65275.1 | I72: =+ROUND(D72*F72,2) -> 0 | J72: =+ROUND(H72+I72*TC,2) -> 65275.1
B73: TABIQUE DRYWALL E=0.10m | C73: m2 | D73: 1.27 | E73: 110 | F73: 0 | G73: =+ROUND(E73+F73*TC,2) -> 110 | H73: =+ROUND(D73*E73,2) -> 139.7 | I73: =+ROUND(D73*F73,2) -> 0 | J73: =+ROUND(H73+I73*TC,2) -> 139.7
B74: TABIQUE DRYWALL E=0.12m | C74: m2 | D74: 732.13 | E74: 125 | F74: 0 | G74: =+ROUND(E74+F74*TC,2) -> 125 | H74: =+ROUND(D74*E74,2) -> 91516.25 | I74: =+ROUND(D74*F74,2) -> 0 | J74: =+ROUND(H74+I74*TC,2) -> 91516.25
B75: PARAPETOS Y SARDINELES | J75: =+ROUND(H75+I75*TC,2) -> 0
B76: PARAPETOS EN VENTANAS (E=0.10M, H=VARIADAS) | C76: m2 | D76: 1130.6 | E76: 111.23 | F76: 0 | G76: =+ROUND(E76+F76*TC,2) -> 111.23 | H76: =+ROUND(D76*E76,2) -> 125756.64 | I76: =+ROUND(D76*F76,2) -> 0 | J76: =+ROUND(H76+I76*TC,2) -> 125756.64
B77: PARAPETOS EN VENTANAS (E=0.12M, H=VARIADAS) | C77: m2 | D77: 0 | E77: 117.23 | F77: 0 | G77: =+ROUND(E77+F77*TC,2) -> 117.23 | H77: =+ROUND(D77*E77,2) -> 0 | I77: =+ROUND(D77*F77,2) -> 0 | J77: =+ROUND(H77+I77*TC,2) -> 0
B78: PARAPETO E=0.10M, H=0.60M (JARDINERA FACHADA INTERNA) | C78: m2 | E78: 0 | F78: 0 | G78: =+ROUND(E78+F78*TC,2) -> 0 | H78: =+ROUND(D78*E78,2) -> 0 | I78: =+ROUND(D78*F78,2) -> 0 | J78: =+ROUND(H78+I78*TC,2) -> 0
B79: PARAPETO E=0.10M, H=0.90M (JARDINERA 1P Y AZOTEA) | C79: m2 | E79: 0 | F79: 0 | G79: =+ROUND(E79+F79*TC,2) -> 0 | H79: =+ROUND(D79*E79,2) -> 0 | I79: =+ROUND(D79*F79,2) -> 0 | J79: =+ROUND(H79+I79*TC,2) -> 0
B80: PARAPETO A=0.12M , H=1.20ML (ELEVADOR DISCAP) | C80: m2 | E80: 0 | F80: 0 | G80: =+ROUND(E80+F80*TC,2) -> 0 | H80: =+ROUND(D80*E80,2) -> 0 | I80: =+ROUND(D80*F80,2) -> 0 | J80: =+ROUND(H80+I80*TC,2) -> 0
B81: PARAPETO E=0.10M, H=1.20M/1.30M (AZOTEA - JARDINERA) | C81: m2 | E81: 0 | F81: 0 | G81: =+ROUND(E81+F81*TC,2) -> 0 | H81: =+ROUND(D81*E81,2) -> 0 | I81: =+ROUND(D81*F81,2) -> 0 | J81: =+ROUND(H81+I81*TC,2) -> 0
B82: PARAPETO E=0.10M, H=1.20M/1.30M (AZOTEA - JARDINERA) | C82: m2 | E82: 0 | F82: 0 | G82: =+ROUND(E82+F82*TC,2) -> 0 | H82: =+ROUND(D82*E82,2) -> 0 | I82: =+ROUND(D82*F82,2) -> 0 | J82: =+ROUND(H82+I82*TC,2) -> 0
B83: PARAPETO E=0.10M, H=1.20M/1.30M (AZOTEA - JARDINERA) | C83: m2 | E83: 0 | F83: 0 | G83: =+ROUND(E83+F83*TC,2) -> 0 | H83: =+ROUND(D83*E83,2) -> 0 | I83: =+ROUND(D83*F83,2) -> 0 | J83: =+ROUND(H83+I83*TC,2) -> 0
B84: PARAPETO E=0.10M, H=1.20M/1.30M (AZOTEA - JARDINERA) | C84: m2 | E84: 0 | F84: 0 | G84: =+ROUND(E84+F84*TC,2) -> 0 | H84: =+ROUND(D84*E84,2) -> 0 | I84: =+ROUND(D84*F84,2) -> 0 | J84: =+ROUND(H84+I84*TC,2) -> 0
B85: PARAPETO E=0.15M, H=1.30M (AZOTEA -JARDINERA) | C85: m2 | E85: 0 | F85: 0 | G85: =+ROUND(E85+F85*TC,2) -> 0 | H85: =+ROUND(D85*E85,2) -> 0 | I85: =+ROUND(D85*F85,2) -> 0 | J85: =+ROUND(H85+I85*TC,2) -> 0
B86: SARDINELES DUCHAS (A=0.10M) , H=0.10M | C86: ml | D86: 667.2 | E86: 45.36 | F86: 0.71 | G86: =+ROUND(E86+F86*TC,2) -> 47.74 | H86: =+ROUND(D86*E86,2) -> 30264.19 | I86: =+ROUND(D86*F86,2) -> 473.71 | J86: =+ROUND(H86+I86*TC,2) -> 31851.12
B87: SARDINEL MAMPARAS EN GENERAL (A=0.10M) , H=0.08M - DPTOS | C87: ml | E87: 45.36 | F87: 0.71 | G87: =+ROUND(E87+F87*TC,2) -> 47.74 | H87: =+ROUND(D87*E87,2) -> 0 | I87: =+ROUND(D87*F87,2) -> 0 | J87: =+ROUND(H87+I87*TC,2) -> 0
B88: SARDINEL VENTANAS | C88: ml | E88: 45.36 | F88: 0.71 | G88: =+ROUND(E88+F88*TC,2) -> 47.74 | H88: =+ROUND(D88*E88,2) -> 0 | I88: =+ROUND(D88*F88,2) -> 0 | J88: =+ROUND(H88+I88*TC,2) -> 0
B89: SARDINEL EN CLOSET DE LAVANDERÍA | C89: ml | E89: 45.21 | F89: 0.71 | G89: =+ROUND(E89+F89*TC,2) -> 47.59 | H89: =+ROUND(D89*E89,2) -> 0 | I89: =+ROUND(D89*F89,2) -> 0 | J89: =+ROUND(H89+I89*TC,2) -> 0
B90: SARDINEL EN CUARTO DE ACOPIO H:0.10M (E=10CM) | C90: ml | D90: 1.8 | E90: 45.21 | F90: 0.78 | G90: =+ROUND(E90+F90*TC,2) -> 47.82 | H90: =+ROUND(D90*E90,2) -> 81.38 | I90: =+ROUND(D90*F90,2) -> 1.4 | J90: =+ROUND(H90+I90*TC,2) -> 86.07
B91: SARDINEL MAMPARAS EN GENERAL (A=0.10M) , H=0.08M - DPTOS | C91: ml | E91: 45.36 | F91: 0.71 | G91: =+ROUND(E91+F91*TC,2) -> 47.74 | H91: =+ROUND(D91*E91,2) -> 0 | I91: =+ROUND(D91*F91,2) -> 0 | J91: =+ROUND(H91+I91*TC,2) -> 0
B92: SARDINEL DUCTOS TECNICOS H=0.10M, E=0.12M | C92: ml | D92: 424.97 | E92: 46.87 | F92: 0.85 | G92: =+ROUND(E92+F92*TC,2) -> 49.72 | H92: =+ROUND(D92*E92,2) -> 19918.34 | I92: =+ROUND(D92*F92,2) -> 361.22 | J92: =+ROUND(H92+I92*TC,2) -> 21128.43
B93: SARDINELES BARANDAS DE VIDRIO AZOTEA (A=0.12/0.15M , H=0.35M) - PARRILLAS 25P Y AZOT. | C93: ml | D93: 159.96 | E93: 46.87 | F93: 0.85 | G93: =+ROUND(E93+F93*TC,2) -> 49.72 | H93: =+ROUND(D93*E93,2) -> 7497.33 | I93: =+ROUND(D93*F93,2) -> 135.97 | J93: =+ROUND(H93+I93*TC,2) -> 7952.83
B94: SARDINELES JARDINES (A=0.10M , H=0.40M) - PARRILLAS 25P Y AZOT. | C94: ml | D94: 33.31 | E94: 76.41 | F94: 2.49 | G94: =+ROUND(E94+F94*TC,2) -> 84.75 | H94: =+ROUND(D94*E94,2) -> 2545.22 | I94: =+ROUND(D94*F94,2) -> 82.94 | J94: =+ROUND(H94+I94*TC,2) -> 2823.07
B95: SARDINELES A NIVEL DE VEREDA (A=0.10M , H=RAZ DE VERDAD) | C95: ml | D95: 38.99 | E95: 46.87 | F95: 0.85 | G95: =+ROUND(E95+F95*TC,2) -> 49.72 | H95: =+ROUND(D95*E95,2) -> 1827.46 | I95: =+ROUND(D95*F95,2) -> 33.14 | J95: =+ROUND(H95+I95*TC,2) -> 1938.48
B96: SARDINEL H = 0.10 E = 0.20 | C96: ml | E96: 0 | F96: 0 | G96: =+ROUND(E96+F96*TC,2) -> 0 | H96: =+ROUND(D96*E96,2) -> 0 | I96: =+ROUND(D96*F96,2) -> 0 | J96: =+ROUND(H96+I96*TC,2) -> 0
B97: SARDINEL H = 0.10 E = 0.41 | C97: ml | E97: 0 | F97: 0 | G97: =+ROUND(E97+F97*TC,2) -> 0 | H97: =+ROUND(D97*E97,2) -> 0 | I97: =+ROUND(D97*F97,2) -> 0 | J97: =+ROUND(H97+I97*TC,2) -> 0
B98: ESTRUCTURAS DE CONCRETO (TABLEROS, BANCAS) | J98: =+ROUND(H98+I98*TC,2) -> 0
B99: Bancas rectas de patio interior | C99: ml | E99: 0 | F99: 0 | G99: =+ROUND(E99+F99*TC,2) -> 0 | H99: =+ROUND(D99*E99,2) -> 0 | I99: =+ROUND(D99*F99,2) -> 0 | J99: =+ROUND(H99+I99*TC,2) -> 0
B100: BANCA CON JARDINERA DE CONCRETO , REVESTIDO CON TERRAZO NEGRO PREMEZCLADO COLOR NEGRO CARBÓN GRANO Nª1. *CONSIDERAR JUNTA DE DILATACIÒN CON PERFIL DE ALUMINIO(L=3.00M, A=0.55M, H=0.75M), INCL. ACABADO | C100: ml | D100: 18 | E100: 486.7 | F100: 8.54 | G100: =+ROUND(E100+F100*TC,2) -> 515.31 | H100: =+ROUND(D100*E100,2) -> 8760.6 | I100: =+ROUND(D100*F100,2) -> 153.72 | J100: =+ROUND(H100+I100*TC,2) -> 9275.56
B101: MUEBLE PARRILLA VACIADO DE CONCRETO CON TABLERO DE GRANITO NEGRO *CONSIDERAR PARRILLA A EMPOTRAR *CONSIDERAR LAVACOPAS *VER D-01 EN LÁMINA A-05 H: 90cm , A=0.60 , L=2.80m | C101: ml | D101: 16.8 | E101: 316.7 | F101: 83.54 | G101: =+ROUND(E101+F101*TC,2) -> 596.56 | H101: =+ROUND(D101*E101,2) -> 5320.56 | I101: =+ROUND(D101*F101,2) -> 1403.47 | J101: =+ROUND(H101+I101*TC,2) -> 10022.18
B102: BANQUETA DE MADERA Ò SIMILAR (L=5.60M, A=0.45M, H=0.45M) INCL. ACABADO | C102: ml | D102: 5.6 | E102: 0 | F102: 250 | G102: =+ROUND(E102+F102*TC,2) -> 837.5 | H102: =+ROUND(D102*E102,2) -> 0 | I102: =+ROUND(D102*F102,2) -> 1400 | J102: =+ROUND(H102+I102*TC,2) -> 4690
B103: TABLERO PARRILLAS | C103: ml | E103: 514.51 | F103: 10.68 | G103: =+ROUND(E103+F103*TC,2) -> 550.29 | H103: =+ROUND(D103*E103,2) -> 0 | I103: =+ROUND(D103*F103,2) -> 0 | J103: =+ROUND(H103+I103*TC,2) -> 0
...

Sheet OFICINAS
B2: DESCRIPCION | C2: UND | D2: METRADO | E2: P.U. (PEN) | F2: P.U. (USD) | G2: P.U. TOTAL (PEN) | H2: PRECIO PARCIAL (PEN) | I2: PRECIO PARCIAL (USD) | J2: PARCIAL TOTAL (PEN) | K2: TOTAL
B3: TABIQUERÍA | K3: =SUM(J4:J7) -> 85652.84
B4: =+'ARQ TORRE'!B44 -> LADRILLO SILICO CALCAREO TIPO P12 RF:2 HRS H>2.6M (ALVEOLOS PARCIALMENTE LLENO) | C4: m2 | D4: 528.65 | E4: 126.23 | G4: =+ROUND(E4+F4*TC,2) -> 126.23 | H4: =+ROUND(D4*E4,2) -> 66731.49 | I4: =+ROUND(D4*F4,2) -> 0 | J4: =+ROUND(H4+I4*TC,2) -> 66731.49
B5: LADRILLO SILICO CALCAREO TIPO P12 H>2.6M | C5: m2 | D5: 127.42 | E5: 126.23 | G5: =+ROUND(E5+F5*TC,2) -> 126.23 | H5: =+ROUND(D5*E5,2) -> 16084.23 | I5: =+ROUND(D5*F5,2) -> 0 | J5: =+ROUND(H5+I5*TC,2) -> 16084.23
B6: ACERO DE REFUERZO | G6: =+ROUND(E6+F6*TC,2) -> 0 | H6: =+ROUND(D6*E6,2) -> 0 | I6: =+ROUND(D6*F6,2) -> 0 | J6: =+ROUND(H6+I6*TC,2) -> 0
B7: ACERO DE REFUERZO FY= 4200 kg/cm2 GRADO 60 PARA TABIQUERÍA | C7: kg | D7: 951.57 | F7: 0.89 | G7: =+ROUND(E7+F7*TC,2) -> 2.98 | H7: =+ROUND(D7*E7,2) -> 0 | I7: =+ROUND(D7*F7,2) -> 846.9 | J7: =+ROUND(H7+I7*TC,2) -> 2837.12
B8: PUERTAS CONTRAPLACADAS | G8: =+ROUND(E8+F8*TC,2) -> 0 | H8: =+ROUND(D8*E8,2) -> 0 | I8: =+ROUND(D8*F8,2) -> 0 | J8: =+ROUND(H8+I8*TC,2) -> 0 | K8: =SUM(J9:J10) -> 2733.9
B9: PS.03(0.8x2.2)P. CONTRAPL. | C9: und | D9: 1 | E9: 124 | F9: 99 | G9: =+ROUND(E9+F9*TC,2) -> 455.65 | H9: =+ROUND(D9*E9,2) -> 124 | I9: =+ROUND(D9*F9,2) -> 99 | J9: =+ROUND(H9+I9*TC,2) -> 455.65
B10: PS.05(0.8x2.2)P. CONTRAPL. | C10: und | D10: 5 | E10: 124 | F10: 99 | G10: =+ROUND(E10+F10*TC,2) -> 455.65 | H10: =+ROUND(D10*E10,2) -> 620 | I10: =+ROUND(D10*F10,2) -> 495 | J10: =+ROUND(H10+I10*TC,2) -> 2278.25
B11: MAMPARAS | G11: =+ROUND(E11+F11*TC,2) -> 0 | H11: =+ROUND(D11*E11,2) -> 0 | I11: =+ROUND(D11*F11,2) -> 0 | J11: =+ROUND(H11+I11*TC,2) -> 0 | K11: =SUM(J12:J50) -> 179499.96
B12: MZ.11 (3.9x3.7)MAMP DE VIDRIO , MARCO ALUMN | C12: und | D12: 1 | E12: 7212.4131 | F12: 0 | G12: =+ROUND(E12+F12*TC,2) -> 7212.41 | H12: =+ROUND(D12*E12,2) -> 7212.41 | I12: =+ROUND(D12*F12,2) -> 0 | J12: =+ROUND(H12+I12*TC,2) -> 7212.41
B13: MZ.12 (4.26x3.7)MAMP DE VIDRIO , MARCO ALUMN | C13: und | D13: 1 | E13: 7878.1709 | F13: 0 | G13: =+ROUND(E13+F13*TC,2) -> 7878.17 | H13: =+ROUND(D13*E13,2) -> 7878.17 | I13: =+ROUND(D13*F13,2) -> 0 | J13: =+ROUND(H13+I13*TC,2) -> 7878.17
B14: MZ.13 (4.36x3.7)MAMP DE VIDRIO , MARCO ALUMN | C14: und | D14: 1 | E14: 8063.1093 | F14: 0 | G14: =+ROUND(E14+F14*TC,2) -> 8063.11 | H14: =+ROUND(D14*E14,2) -> 8063.11 | I14: =+ROUND(D14*F14,2) -> 0 | J14: =+ROUND(H14+I14*TC,2) -> 8063.11
B15: MZ.14 (5.46x3.7)MAMP DE VIDRIO , MARCO ALUMN | C15: und | D15: 1 | E15: 10097.38 | F15: 0 | G15: =+ROUND(E15+F15*TC,2) -> 10097.38 | H15: =+ROUND(D15*E15,2) -> 10097.38 | I15: =+ROUND(D15*F15,2) -> 0 | J15: =+ROUND(H15+I15*TC,2) -> 10097.38
B16: MZ.15 (3.6x3.7)MAMP DE VIDRIO , MARCO ALUMN | C16: und | D16: 1 | E16: 8773.8933 | F16: 0 | G16: =+ROUND(E16+F16*TC,2) -> 8773.89 | H16: =+ROUND(D16*E16,2) -> 8773.89 | I16: =+ROUND(D16*F16,2) -> 0 | J16: =+ROUND(H16+I16*TC,2) -> 8773.89
B17: MZ.16 (4.78x3.7)MAMP DE VIDRIO , MARCO ALUMN | C17: und | D17: 1 | E17: 8839.83 | F17: 0 | G17: =+ROUND(E17+F17*TC,2) -> 8839.83 | H17: =+ROUND(D17*E17,2) -> 8839.83 | I17: =+ROUND(D17*F17,2) -> 0 | J17: =+ROUND(H17+I17*TC,2) -> 8839.83
B18: MZ.17 (4.42x3.41)MAMP DE VIDRIO , MARCO ALUMN | C18: und | D18: 1 | E18: 8174.0723 | F18: 0 | G18: =+ROUND(E18+F18*TC,2) -> 8174.07 | H18: =+ROUND(D18*E18,2) -> 8174.07 | I18: =+ROUND(D18*F18,2) -> 0 | J18: =+ROUND(H18+I18*TC,2) -> 8174.07
B19: MZ.18' (2.78x3.41)MAMP DE VIDRIO , MARCO ALUMN | C19: und | D19: 1 | E19: 4373.2811 | F19: 0 | G19: =+ROUND(E19+F19*TC,2) -> 4373.28 | H19: =+ROUND(D19*E19,2) -> 4373.28 | I19: =+ROUND(D19*F19,2) -> 0 | J19: =+ROUND(H19+I19*TC,2) -> 4373.28
B20: MZ.18 (2.59x3.41)MAMP DE VIDRIO , MARCO ALUMN | C20: und | D20: 1 | E20: 2583.444 | F20: 0 | G20: =+ROUND(E20+F20*TC,2) -> 2583.44 | H20: =+ROUND(D20*E20,2) -> 2583.44 | I20: =+ROUND(D20*F20,2) -> 0 | J20: =+ROUND(H20+I20*TC,2) -> 2583.44
B21: MZ.19 (1.53x3.41)MAMP DE VIDRIO , MARCO ALUMN | C21: und | D21: 1 | E21: 9135.7212 | F21: 0 | G21: =+ROUND(E21+F21*TC,2) -> 9135.72 | H21: =+ROUND(D21*E21,2) -> 9135.72 | I21: =+ROUND(D21*F21,2) -> 0 | J21: =+ROUND(H21+I21*TC,2) -> 9135.72
B22: MZ.20 (4.94x3.7)MAMP DE VIDRIO , MARCO ALUMN | C22: und | D22: 1 | E22: 2780.4351 | F22: 0 | G22: =+ROUND(E22+F22*TC,2) -> 2780.44 | H22: =+ROUND(D22*E22,2) -> 2780.44 | I22: =+ROUND(D22*F22,2) -> 0 | J22: =+ROUND(H22+I22*TC,2) -> 2780.44
B23: MZ.21 (1.82x3.7)MAMP DE VIDRIO , MARCO ALUMN | C23: und | D23: 1 | E23: 6158.295 | F23: 0 | G23: =+ROUND(E23+F23*TC,2) -> 6158.29 | H23: =+ROUND(D23*E23,2) -> 6158.29 | I23: =+ROUND(D23*F23,2) -> 0 | J23: =+ROUND(H23+I23*TC,2) -> 6158.29
... B28: MZ.26 (3.25x3.52)MAMP DE VIDRIO , MARCO ALUMN | C28: und | D28: 1 | E28: 5012.6907 | F28: 0 | G28: =+ROUND(E28+F28*TC,2) -> 5012.69 | H28: =+ROUND(D28*E28,2) -> 5012.69 | I28: =+ROUND(D28*F28,2) -> 0 | J28: =+ROUND(H28+I28*TC,2) -> 5012.69
B29: PUERTAS VENTANAS | F29: 1 | G29: =+ROUND(E29+F29*TC,2) -> 3.35 | H29: =+ROUND(D29*E29,2) -> 0 | I29: =+ROUND(D29*F29,2) -> 0 | J29: =+ROUND(H29+I29*TC,2) -> 0
B30: PZ.01 (1.05x2.1)P. CONTRAPL. BATIENTE | C30: und | D30: 2 | E30: 1923.728 | F30: 0 | G30: =+ROUND(E30+F30*TC,2) -> 1923.73 | H30: =+ROUND(D30*E30,2) -> 3847.46 | I30: =+ROUND(D30*F30,2) -> 0 | J30: =+ROUND(H30+I30*TC,2) -> 3847.46
B31: PZ.02 (1.5x2.1)P. CONTRAPL. BATIENTE | C31: und | E31: 2451.0891 | F31: 0 | G31: =+ROUND(E31+F31*TC,2) -> 2451.09 | H31: =+ROUND(D31*E31,2) -> 0 | I31: =+ROUND(D31*F31,2) -> 0 | J31: =+ROUND(H31+I31*TC,2) -> 0
B32: PZ.04 (0.8x2.1)P. CONTRAPL. BATIENTE | C32: und | D32: 2 | E32: 1465.6982 | F32: 0 | G32: =+ROUND(E32+F32*TC,2) -> 1465.7 | H32: =+ROUND(D32*E32,2) -> 2931.4 | I32: =+ROUND(D32*F32,2) -> 0 | J32: =+ROUND(H32+I32*TC,2) -> 2931.4
B33: PZ.06 (1.06x2.1)P. CONTRAPL. BATIENTE | C33: und | D33: 1 | E33: 1960.3675 | F33: 0 | G33: =+ROUND(E33+F33*TC,2) -> 1960.37 | H33: =+ROUND(D33*E33,2) -> 1960.37 | I33: =+ROUND(D33*F33,2) -> 0 | J33: =+ROUND(H33+I33*TC,2) -> 1960.37
B34: PZ.07 (1.1x2.1)P. CONTRAPL. BATIENTE | C34: und | D34: 1 | E34: 2015.337 | F34: 0 | G34: =+ROUND(E34+F34*TC,2) -> 2015.34 | H34: =+ROUND(D34*E34,2) -> 2015.34 | I34: =+ROUND(D34*F34,2) -> 0 | J34: =+ROUND(H34+I34*TC,2) -> 2015.34
B35: PZ.08 (5.52x2.1)P. CONTRAPL. BATIENTE | C35: und | D35: 1 | E35: 7926.6583 | F35: 0 | G35: =+ROUND(E35+F35*TC,2) -> 7926.66 | H35: =+ROUND(D35*E35,2) -> 7926.66 | I35: =+ROUND(D35*F35,2) -> 0 | J35: =+ROUND(H35+I35*TC,2) -> 7926.66
B36: PZ.09 (4.44x2.1)P. CONTRAPL. BATIENTE | C36: und | D36: 1 | E36: 5801.3925 | F36: 0 | G36: =+ROUND(E36+F36*TC,2) -> 5801.39 | H36: =+ROUND(D36*E36,2) -> 5801.39 | I36: =+ROUND(D36*F36,2) -> 0 | J36: =+ROUND(H36+I36*TC,2) -> 5801.39
B37: PZ.10 (2.63x2.1)P. CONTRAPL. BATIENTE | C37: und | D37: 1 | E37: 4297.5649 | F37: 0 | G37: =+ROUND(E37+F37*TC,2) -> 4297.56 | H37: =+ROUND(D37*E37,2) -> 4297.56 | I37: =+ROUND(D37*F37,2) -> 0 | J37: =+ROUND(H37+I37*TC,2) -> 4297.56
B38: PZ.11 (2.63x2.1)P. CONTRAPL. BATIENTE | C38: und | D38: 1 | E38: 5947.9608 | F38: 0 | G38: =+ROUND(E38+F38*TC,2) -> 5947.96 | H38: =+ROUND(D38*E38,2) -> 5947.96 | I38: =+ROUND(D38*F38,2) -> 0 | J38: =+ROUND(H38+I38*TC,2) -> 5947.96
B39: PZ.12 (6.98x2.1)P. CONTRAPL. BATIENTE | C39: und | D39: 1 | E39: 8640.6885 | F39: 0 | G39: =+ROUND(E39+F39*TC,2) -> 8640.69 | H39: =+ROUND(D39*E39,2) -> 8640.69 | I39: =+ROUND(D39*F39,2) -> 0 | J39: =+ROUND(H39+I39*TC,2) -> 8640.69
B40: PZ.13 (1.52x2.2)P. CONTRAPL. BATIENTE | C40: und | D40: 1 | E40: 2483.7657 | F40: 0 | G40: =+ROUND(E40+F40*TC,2) -> 2483.77 | H40: =+ROUND(D40*E40,2) -> 2483.77 | I40: =+ROUND(D40*F40,2) -> 0 | J40: =+ROUND(H40+I40*TC,2) -> 2483.77
B41: PZ.14 (1.73x2.2)P. CONTRAPL. BATIENTE | C41: und | D41: 1 | E41: 3083.9143 | F41: 0 | G41: =+ROUND(E41+F41*TC,2) -> 3083.91 | H41: =+ROUND(D41*E41,2) -> 3083.91 | I41: =+ROUND(D41*F41,2) -> 0 | J41: =+ROUND(H41+I41*TC,2) -> 3083.91
B42: PZ.15 (6.69x2.2)P. CONTRAPL. BATIENTE | C42: und | D42: 1 | E42: 9606.7612 | F42: 0 | G42: =+ROUND(E42+F42*TC,2) -> 9606.76 | H42: =+ROUND(D42*E42,2) -> 9606.76 | I42: =+ROUND(D42*F42,2) -> 0 | J42: =+ROUND(H42+I42*TC,2) -> 9606.76
B43: PZ.16 (4.61x2.2)P. CONTRAPL. BATIENTE | C43: und | D43: 1 | E43: 5250.2741 | F43: 0 | G43: =+ROUND(E43+F43*TC,2) -> 5250.27 | H43: =+ROUND(D43*E43,2) -> 5250.27 | I43: =+ROUND(D43*F43,2) -> 0 | J43: =+ROUND(H43+I43*TC,2) -> 5250.27
B44: PUERTAS MELAMINE
B45: PC.04 (1.25 x 2.10m) | C45: und | D45: 1 | E45: 600 | F45: 0 | G45: =+ROUND(E45+F45*TC,2) -> 600 | H45: =+ROUND(D45*E45,2) -> 600 | I45: =+ROUND(D45*F45,2) -> 0 | J45: =+ROUND(H45+I45*TC,2) -> 600
B46: PC.05 (1.40 x 2.10m) | C46: und | D46: 2 | E46: 672 | F46: 0 | G46: =+ROUND(E46+F46*TC,2) -> 672 | H46: =+ROUND(D46*E46,2) -> 1344 | I46: =+ROUND(D46*F46,2) -> 0 | J46: =+ROUND(H46+I46*TC,2) -> 1344
B47: PC.03 (1.32 x 2.10m) | C47: und | D47: 8 | E47: 633.6 | F47: 0 | G47: =+ROUND(E47+F47*TC,2) -> 633.6 | H47: =+ROUND(D47*E47,2) -> 5068.8 | I47: =+ROUND(D47*F47,2) -> 0 | J47: =+ROUND(H47+I47*TC,2) -> 5068.8
B48: PC.01 (1.00 x 2.10m) | C48: und | D48: 1 | E48: 480 | F48: 0 | G48: =+ROUND(E48+F48*TC,2) -> 480 | H48: =+ROUND(D48*E48,2) -> 480 | I48: =+ROUND(D48*F48,2) -> 0 | J48: =+ROUND(H48+I48*TC,2) -> 480
B49: PP.10 (0.94x2)P. BATIENT MELAMINE | C49: und | D49: 1 | E49: 445 | F49: 0 | G49: =+ROUND(E49+F49*TC,2) -> 445 | H49: =+ROUND(D49*E49,2) -> 445 | I49: =+ROUND(D49*F49,2) -> 0 | J49: =+ROUND(H49+I49*TC,2) -> 445
B50: PP.19(1.3x2)P. BATIENT MELAMINE | C50: und | D50: 1 | E50: 578.5 | F50: 0 | G50: =+ROUND(E50+F50*TC,2) -> 578.5 | H50: =+ROUND(D50*E50,2) -> 578.5 | I50: =+ROUND(D50*F50,2) -> 0 | J50: =+ROUND(H50+I50*TC,2) -> 578.5
B51: PINTURA | G51: =+ROUND(E51+F51*TC,2) -> 0 | H51: =+ROUND(D51*E51,2) -> 0 | I51: =+ROUND(D51*F51,2) -> 0 | J51: =+ROUND(H51+I51*TC,2) -> 0 | K51: =SUM(J52:J56) -> 20118.74
B52: MUROS
B53: T2.17.03.01 - ACABADO POR DEFINIR - LOBBY DE OFICINAS, HALL DE ASCENSORES, CORREDORES Y ESCALERA OFICINAS | C53: m2 | D53: 544.6 | E53: 25.5 | F53: 0 | G53: =+ROUND(E53+F53*TC,2) -> 25.5 | H53: =+ROUND(D53*E53,2) -> 13887.3 | I53: =+ROUND(D53*F53,2) -> 0 | J53: =+ROUND(H53+I53*TC,2) -> 13887.3
B54: Empastado y pintado en Óleomate color Blanco - CPP(BAÑO) | C54: m2 | D54: 138.89 | E54: 27 | F54: 0 | G54: =+ROUND(E54+F54*TC,2) -> 27 | H54: =+ROUND(D54*E54,2) -> 3750.03 | I54: =+ROUND(D54*F54,2) -> 0 | J54: =+ROUND(H54+I54*TC,2) -> 3750.03
B55: CIELO RASO
B56: Empastado y pintado con pintura látex Blanco. Se considera pintura PATO. | C56: m2 | D56: 97.31 | E56: 25.5 | F56: 0 | G56: =+ROUND(E56+F56*TC,2) -> 25.5 | H56: =+ROUND(D56*E56,2) -> 2481.41 | I56: =+ROUND(D56*F56,2) -> 0 | J56: =+ROUND(H56+I56*TC,2) -> 2481.41
B57: PISOS | G57: =+ROUND(E57+F57*TC,2) -> 0 | H57: =+ROUND(D57*E57,2) -> 0 | I57: =+ROUND(D57*F57,2) -> 0 | J57: =+ROUND(H57+I57*TC,2) -> 0 | K57: =SUM(J58:J62) -> 47685.6
B58: NIVELACIÓN DE PISO | C58: m2 | D58: 52.34 | E58: 23.41 | F58: 0 | G58: =+ROUND(E58+F58*TC,2) -> 23.41 | H58: =+ROUND(D58*E58,2) -> 1225.28 | I58: =+ROUND(D58*F58,2) -> 0 | J58: =+ROUND(H58+I58*TC,2) -> 1225.28
B59: OFICINAS
B60: CERAMICO TERRE GRIS 60x60CM. CELIMA | C60: m2 | D60: 617.31 | E60: 69.38 | G60: =+ROUND(E60+F60*TC,2) -> 69.38 | H60: =+ROUND(D60*E60,2) -> 42828.97 | I60: =+ROUND(D60*F60,2) -> 0 | J60: =+ROUND(H60+I60*TC,2) -> 42828.97
B61: BAÑOS
B62: CERAMICO TERRE GRIS 60x60CM. CELIMA | C62: m2 | D62: 52.34 | E62: 69.38 | F62: 0 | G62: =+ROUND(E62+F62*TC,2) -> 69.38 | H62: =+ROUND(D62*E62,2) -> 3631.35 | I62: =+ROUND(D62*F62,2) -> 0 | J62: =+ROUND(H62+I62*TC,2) -> 3631.35
B63: APARATOS SANITARIOS | G63: =+ROUND(E63+F63*TC,2) -> 0 | H63: =+ROUND(D63*E63,2) -> 0 | I63: =+ROUND(D63*F63,2) -> 0 | J63: =+ROUND(H63+I63*TC,2) -> 0 | K63: =SUM(J65:J70) -> 3804.58
B64: SH MIXTO PARA EMPLEADOS | G64: =+ROUND(E64+F64*TC,2) -> 0 | H64: =+ROUND(D64*E64,2) -> 0 | I64: =+ROUND(D64*F64,2) -> 0 | J64: =+ROUND(H64+I64*TC,2) -> 0
B65: ONE PIECE TREBOL SAVONA LUX BLANCO C/PUL DESC/UNICA 4.8 LT | C65: und | D65: 4 | E65: 326.48 | F65: 0 | G65: =+ROUND(E65+F65*TC,2) -> 326.48 | H65: =+ROUND(D65*E65,2) -> 1305.92 | I65: =+ROUND(D65*F65,2) -> 0 | J65: =+ROUND(H65+I65*TC,2) -> 1305.92
B66: URINARIO CADET COLOR BLANCO, MARCA TREBOL | C66: und | D66: 4 | E66: 201.62 | F66: 0 | G66: =+ROUND(E66+F66*TC,2) -> 201.62 | H66: =+ROUND(D66*E66,2) -> 806.48 | I66: =+ROUND(D66*F66,2) -> 0 | J66: =+ROUND(H66+I66*TC,2) -> 806.48
B67: Lavatorio Ancón 2.0 | C67: und | D67: 4 | E67: 273.14 | F67: 0 | G67: =+ROUND(E67+F67*TC,2) -> 273.14 | H67: =+ROUND(D67*E67,2) -> 1092.56 | I67: =+ROUND(D67*F67,2) -> 0 | J67: =+ROUND(H67+I67*TC,2) -> 1092.56
B68: SH MUJERES | G68: =+ROUND(E68+F68*TC,2) -> 0 | H68: =+ROUND(D68*E68,2) -> 0 | I68: =+ROUND(D68*F68,2) -> 0 | J68: =+ROUND(H68+I68*TC,2) -> 0
B69: ONE PIECE TREBOL SAVONA LUX BLANCO C/PUL DESC/UNICA 4.8 LT | C69: und | D69: 1 | E69: 326.48 | F69: 0 | G69: =+ROUND(E69+F69*TC,2) -> 326.48 | H69: =+ROUND(D69*E69,2) -> 326.48 | I69: =+ROUND(D69*F69,2) -> 0 | J69: =+ROUND(H69+I69*TC,2) -> 326.48
B70: Lavatorio Ancón 2.0 | C70: und | D70: 1 | E70: 273.14 | F70: 0 | G70: =+ROUND(E70+F70*TC,2) -> 273.14 | H70: =+ROUND(D70*E70,2) -> 273.14 | I70: =+ROUND(D70*F70,2) -> 0 | J70: =+ROUND(H70+I70*TC,2) -> 273.14
B71: INSTALACIONES | G71: =+ROUND(E71+F71*TC,2) -> 0 | H71: =+ROUND(D71*E71,2) -> 0 | I71: =+ROUND(D71*F71,2) -> 0 | J71: =+ROUND(H71+I71*TC,2) -> 0 | K71: =SUM(J72:J73) -> 65000
B72: ASCENSORES | C72: und | D72: 0 | F72: 37205.48 | G72: =+ROUND(E72+F72*TC,2) -> 124638.36 | H72: =+ROUND(D72*E72,2) -> 0 | I72: =+ROUND(D72*F72,2) -> 0 | J72: =+ROUND(H72+I72*TC,2) -> 0
B73: IEE Y IISS | C73: glb | D73: 1 | E73: 65000 | G73: =+ROUND(E73+F73*TC,2) -> 65000 | H73: =+ROUND(D73*E73,2) -> 65000 | I73: =+ROUND(D73*F73,2) -> 0 | J73: =+ROUND(H73+I73*TC,2) -> 65000
J75: =SUM(J4:J74) -> 404495.62 | K75: =SUM(K3:K74) -> 404495.62

Sheet CTO BOMBAS - ACIySPC ACT
A2: CUARTO DE BOMBAS - ACI
H3: T.C | I3: 3.35
A4: Presupuesto | B4: GERMANIA
A5: Subpresupuesto | B5: EQUIPAMIENTO
A6: Cliente | B6: : V&V Bravo S.A.C | F6: Costo al | G6: 46133
A7: Lugar
A8: ITEM | B8: DESCRIPCION | C8: UND | D8: CANTIDAD | E8: P.U (S/.) | F8: P.U ($.) | G8: PARCIAL (S/.) | H8: PARCIAL ($) | I8: TOTAL
A9: 01 | B9: SISTEMA DE PRESION CONSTANTE Y SUMIDEROS | I9: =SUM(H11:H16) -> 50453.28
A10: 1 | B10: SISTEMA DE PRESIÓN CONSTANTE Y VELOCIDAD VARIABLE AGUA POTABLE I
A11: 0.01 | B11: Electrobomba multietapa vertical VSE 10 12-100 con motor de 10 HP 3F x 220V Marca: Barnes Caudal: 3.89 L/S Altura (HDT): 115.28 m | C11: Und. | D11: 4 | F11: 3642.5675 | G11: =+E11*D11 -> 0 | H11: =+F11*D11 -> 14570.27 | I11: =+G11+(H11*$I$3) -> 48810.405
A12: 1 | B12: SISTEMA DE PRESIÓN CONSTANTE Y VELOCIDAD VARIABLE AGUA POTABLE II
A13: 0.01 | B13: SISTEMA PRESION CONSTANTE N°2 Electrobomba multietapa vertical VSE 15 8-150 con motor de 15 HP 3F x 220V Marca: Barnes Caudal: 6.01 L/S Altura (HDT): 93.43 m | C13: Und. | D13: 4 | F13: 4626.615 | G13: =+E13*D13 -> 0 | H13: =+F13*D13 -> 18506.46 | I13: =+G13+(H13*$I$3) -> 61996.641
A14: 1 | B14: SUMINISTRO E INSTALACIÓN SISTEMA DE BOMBEOSUMIDERO
A15: 0.01 | B15: SISTEMA SUMIDERO Bomba Sumergible NE 3 30-2-220 de 60HZ con motor de 3HP 3 x 220D Marca: Barnes Caudal: 1.5 L/S Altura (HDT): 27 m | C15: Und. | D15: 2 | F15: 1614.255 | G15: =+E15*D15 -> 0 | H15: =+F15*D15 -> 3228.51 | I15: =+G15+(H15*$I$3) -> 10815.509
A16: 1 | B16: INSTALACION DE BOMBAS Y MANIFOLD | C16: glb | D16: 1 | F16: 14148.04 | G16: =+E16*D16 -> 0 | H16: =+F16*D16 -> 14148.04 | I16: =+G16+(H16*$I$3) -> 47395.934
A17: 01.01 | B17: EQUIPO DE AGUA CONTRAINCENDIO LISTADA UL | I17: =SUM(H18) -> 66343.8
A18: 01.01.01.09 | B18: Motobomba listada UL/FM – ESPAÑA Marca: GENERAL PUMPS Modelo: FGHC 125-100-400 Tipo: Horizontal Split Case Rotación: Horaria Punto de Diseño: - Caudal: 750 GPM | C18: glb | D18: 1 | F18: 66343.8 | G18: =+E18*D18 -> 0 | H18: =+F18*D18 -> 66343.8 | I18: =+G18+(H18*$I$3) -> 222251.73
B19: Instalación Equipo de Bombeo contraincendio en sala de Bombas | C19: glb
A20: 01.01 | B20: SISTEMA DE AGUA CONTRAINCENDIO - ROCIADORES Y GABINETES | I20: =SUM(H22) -> 481507.87
B21: RED DE TUBERIA COLGADA Y ADOSADAS DE ACERO SCH-10 Y SCH-40
B22: Suministro e Instalación de Sistema de Rociadores y Gabinetes *Suministro de materiales red de Gabinetes y Rociadores. *Montaje mecanico del sistema de Gabinetes y Rociadores | C22: glb | D22: 1 | F22: 481507.87 | G22: =+E22*D22 -> 0 | H22: =+F22*D22 -> 481507.87 | I22: =+G22+(H22*$I$3) -> 1613051.4

Sheet INSTALACIONES
A2: INSTALACIONES
H3: T.C | I3: 3.35
A4: Presupuesto | B4: GERMANIA
A5: Subpresupuesto | B5: INSTALACIONES MECANICAS
A6: Cliente | B6: : V&V Bravo S.A.C | F6: Costo al | G6: 46133
A7: Lugar
A8: ITEM | B8: DESCRIPCION | C8: UND | D8: CANTIDAD | E8: P.U (S/.) | F8: P.U ($.) | G8: PARCIAL (S/.) | H8: PARCIAL ($) | I8: TOTAL
A9: 01.01 | B9: INTERCOMUNICADORES | I9: =SUM(I11:I42) -> 90543.89
B10: DISPOSITIVOS PRINCIPALES DE COMUNICACIÓN
A11: 01.01.01.01 | B11: Terr/Caja Emp Newsfera 3mod | C11: und | D11: 1 | E11: 107.1 | G11: =+E11*D11 -> 107.1 | H11: =+F11*D11 -> 0 | I11: =+G11+(H11*$I$3) -> 107.1
A12: 01.01.01.02 | B12: Terr/Marco Sop Newsfera 3mod | C12: und | D12: 1 | E12: 327.6 | G12: =+E12*D12 -> 327.6 | H12: =+F12*D12 -> 0 | I12: =+G12+(H12*$I$3) -> 327.6
A13: 01.01.01.03 | B13: Terr/Mod Fon Newsfera SOFT 2H | C13: und | D13: 1 | E13: 735 | G13: =+E13*D13 -> 735 | H13: =+F13*D13 -> 0 | I13: =+G13+(H13*$I$3) -> 735
A14: 01.01.01.04 | B14: Terr/Mod Display Newsfera 2h | C14: und | D14: 1 | E14: 500.5 | G14: =+E14*D14 -> 500.5 | H14: =+F14*D14 -> 0 | I14: =+G14+(H14*$I$3) -> 500.5
A15: 01.01.01.05 | B15: Terr/Mod Teclado Newsfera 2h | C15: und | D15: 1 | E15: 443.8 | G15: =+E15*D15 -> 443.8 | H15: =+F15*D15 -> 0 | I15: =+G15+(H15*$I$3) -> 443.8
A16: 01.01.01.06 | B16: Terr/Placa Fon+ 1p Newsfera | C16: und | D16: 1 | E16: 98 | G16: =+E16*D16 -> 98 | H16: =+F16*D16 -> 0 | I16: =+G16+(H16*$I$3) -> 98
A17: 01.01.01.07 | B17: Terr/Placa P/Display Newsfera | C17: und | D17: 1 | E17: 90.3 | G17: =+E17*D17 -> 90.3 | H17: =+F17*D17 -> 0 | I17: =+G17+(H17*$I$3) -> 90.3
A18: 01.01.01.08 | B18: Terr/Placa P/Teclado Newsfera | C18: und | D18: 1 | E18: 282.1 | G18: =+E18*D18 -> 282.1 | H18: =+F18*D18 -> 0 | I18: =+G18+(H18*$I$3) -> 282.1
A19: 01.01.01.09 | B19: ACCESORIOS Y ELEMENTOS DE CONFIGURACIÓN DEL SISTEMA
A20: 01.01.01.10 | B20: Alimentador 2 hilos Audio/Video 6mod | C20: und | D20: 4 | E20: 423.5 | G20: =+E20*D20 -> 1694 | H20: =+F20*D20 -> 0 | I20: =+G20+(H20*$I$3) -> 1694
A21: 01.01.01.11 | B21: Modulo expansorr de instalacion de 2 hilos | C21: und | D21: 3 | E21: 1092 | G21: =+E21*D21 -> 3276 | H21: =+F21*D21 -> 0 | I21: =+G21+(H21*$I$3) -> 3276
A22: 01.01.01.12 | B22: Configurador N°1 (paquete de 10 piezas) | C22: und | D22: 10 | E22: 33.32 | G22: =+E22*D22 -> 333.2 | H22: =+F22*D22 -> 0 | I22: =+G22+(H22*$I$3) -> 333.2
A23: 01.01.01.13 | B23: Configurador N°2 (paquete de 10 piezas) | C23: und | D23: 10 | E23: 33.32 | G23: =+E23*D23 -> 333.2 | H23: =+F23*D23 -> 0 | I23: =+G23+(H23*$I$3) -> 333.2
A24: 01.01.01.14 | B24: Configurador N°3 (paquete de 10 piezas) | C24: und | D24: 10 | E24: 33.32 | G24: =+E24*D24 -> 333.2 | H24: =+F24*D24 -> 0 | I24: =+G24+(H24*$I$3) -> 333.2
A25: 01.01.01.15 | B25: Configurador N°4 (paquete de 10 piezas) | C25: und | D25: 10 | E25: 33.32 | G25: =+E25*D25 -> 333.2 | H25: =+F25*D25 -> 0 | I25: =+G25+(H25*$I$3) -> 333.2
A26: 01.01.01.16 | B26: Configurador N°5 (paquete de 10 piezas) | C26: und | D26: 10 | E26: 33.32 | G26: =+E26*D26 -> 333.2 | H26: =+F26*D26 -> 0 | I26: =+G26+(H26*$I$3) -> 333.2
A27: 01.01.01.17 | B27: Configurador N°6 (paquete de 10 piezas) | C27: und | D27: 7 | E27: 33.32 | G27: =+E27*D27 -> 233.24 | H27: =+F27*D27 -> 0 | I27: =+G27+(H27*$I$3) -> 233.24
A28: 01.01.01.18 | B28: Configurador N°7 (paquete de 10 piezas) | C28: und | D28: 7 | E28: 33.32 | G28: =+E28*D28 -> 233.24 | H28: =+F28*D28 -> 0 | I28: =+G28+(H28*$I$3) -> 233.24
A29: 01.01.01.19 | B29: Configurador N°8 (paquete de 10 piezas) | C29: und | D29: 7 | E29: 33.32 | G29: =+E29*D29 -> 233.24 | H29: =+F29*D29 -> 0 | I29: =+G29+(H29*$I$3) -> 233.24
A30: 01.01.01.20 | B30: Configurador N°9 (paquete de 10 piezas) | C30: und | D30: 37 | E30: 33.32 | G30: =+E30*D30 -> 1232.84 | H30: =+F30*D30 -> 0 | I30: =+G30+(H30*$I$3) -> 1232.84
A31: 01.01.01.21 | B31: ACCESORIOS Y ELEMENTOS DE CONFIGURACIÓN DEL SISTEMA
A32: 01.01.01.22 | B32: Centralita de conserjería digital 2 Hilos | C32: und | D32: 1 | E32: 3360 | G32: =+E32*D32 -> 3360 | H32: =+F32*D32 -> 0 | I32: =+G32+(H32*$I$3) -> 3360
A33: 01.01.01.23 | B33: Alimentador adicional 2 hilos, 2 mód. DIN, 27V - 600mA | C33: und | D33: 1 | E33: 454.3 | G33: =+E33*D33 -> 454.3 | H33: =+F33*D33 -> 0 | I33: =+G33+(H33*$I$3) -> 454.3
A34: 01.01.01.24 | B34: Toma 8 contactos serie LIGHT | C34: und | D34: 1 | E34: 61.95 | G34: =+E34*D34 -> 61.95 | H34: =+F34*D34 -> 0 | I34: =+G34+(H34*$I$3) -> 61.95
A35: 01.01.01.25 | B35: Placa Tecnopolímero 3 mód. LIVING-LIGHT Rectangular Blanco | C35: und | D35: 1 | E35: 19.67 | G35: =+E35*D35 -> 19.67 | H35: =+F35*D35 -> 0 | I35: =+G35+(H35*$I$3) -> 19.67
A36: 01.01.01.26 | B36: mód. ciego 1 mód. LIVING-LIGHT Blanco | C36: und | D36: 2 | E36: 3.059 | G36: =+E36*D36 -> 6.118 | H36: =+F36*D36 -> 0 | I36: =+G36+(H36*$I$3) -> 6.118
A37: 01.01.01.27 | B37: Soporte de resina para placas 3 mód. LIVING-LIGHT | C37: und | D37: 1 | E37: 4.669 | G37: =+E37*D37 -> 4.669 | H37: =+F37*D37 -> 0 | I37: =+G37+(H37*$I$3) -> 4.669
A38: 01.01.01.28 | B38: Cable 8h negro con conector para centralita | C38: und | D38: 1 | E38: 58.24 | G38: =+E38*D38 -> 58.24 | H38: =+F38*D38 -> 0 | I38: =+G38+(H38*$I$3) -> 58.24
A39: 01.01.01.29 | B39: DPTOS COMPUESTO POR:
A40: 01.01.01.30 | B40: 01 ANEXOS AUDIO
A41: 01.01.01.31 | B41: Telefono 2h audio sprint L2 | C41: und | D41: 354 | E41: 135.8 | G41: =+E41*D41 -> 48073.2 | H41: =+F41*D41 -> 0 | I41: =+G41+(H41*$I$3) -> 48073.2
A42: 01.01.01.33 | B42: Servicio de instalación y configuración de intercomunicadores incluye: Cableado estructuado y energizado de fuentes. Interconexión modulo | C42: glb | D42: 1 | E42: 27352.783 | G42: =+E42*D42 -> 27352.783 | H42: =+F42*D42 -> 0 | I42: =+G42+(H42*$I$3) -> 27352.783
A43: 01.02 | B43: DETECCION CONTRAINCENDIOS | I43: =SUM(H44:H68) -> 84553.58
B44: UNIDAD DE PROCESAMIENTO Y COMPLEMENTOS
B45: Panel de Alarma contra Incendio Convencional/Direccionable Marca: KIDDE Modelo: VS4-R-2 | C45: UND | D45: 1 | F45: 895 | G45: =+E45*D45 -> 0 | H45: =+F45*D45 -> 895 | I45: =+G45+(H45*$I$3) -> 2998.25
B46: Tarjeta expansora de 2 lazos/250 direcciones | C46: UND | D46: 2 | F46: 955 | G46: =+E46*D46 -> 0 | H46: =+F46*D46 -> 1910 | I46: =+G46+(H46*$I$3) -> 6398.5
B47: Bateria de 12v/7Ah | C47: UND | D47: 2 | F47: 65 | G47: =+E47*D47 -> 0 | H47: =+F47*D47 -> 130 | I47: =+G47+(H47*$I$3) -> 435.5
B48: DISPOSITIVOS DE INICIACIÓN
B49: Detector de Humo Convencional UL Marca: Sentek Modelo: SD 4H 119 | C49: UND | D49: 620 | F49: 16 | G49: =+E49*D49 -> 0 | H49: =+F49*D49 -> 9920 | I49: =+G49+(H49*$I$3) -> 33232
B50: Detector de Temperatura Convencional UL Marca: Hagroy Modelo: EPA 183 | C50: UND | D50: 337 | F50: 10.5 | G50: =+E50*D50 -> 0 | H50: =+F50*D50 -> 3538.5 | I50: =+G50+(H50*$I$3) -> 11853.975
B51: Detector de Humo/Temperatura Convencional UL Marca: SENTEK Modelo: SD H 1199 | C51: UND | D51: 4 | F51: 18.5 | G51: =+E51*D51 -> 0 | H51: =+F51*D51 -> 74 | I51: =+G51+(H51*$I$3) -> 247.9
B52: Detector de humo en ducto UL. Incluye tubo de muestro 8" Marca: KIDDE Modelo: GSA-SD | C52: UND | D52: 3 | F52: 137 | G52: =+E52*D52 -> 0 | H52: =+F52*D52 -> 411 | I52: =+G52+(H52*$I$3) -> 1376.85
B53: Estación manual doble acción convencional Marca: FIRE LITE HONEYWELL Modelo: | C53: UND | D53: 90 | F53: 25.5 | G53: =+E53*D53 -> 0 | H53: =+F53*D53 -> 2295 | I53: =+G53+(H53*$I$3) -> 7688.25
B54: Sensor de Aniego con procesador Marca :Winland | C54: UND | D54: 1 | F54: 155 | G54: =+E54*D54 -> 0 | H54: =+F54*D54 -> 155 | I54: =+G54+(H54*$I$3) -> 519.25
B55: DISPOSITIVO DE NOTIFICACIÓN
B56: Sirena con Luz Estroboscópica multicandela para Pared. Certicado UL Marca: Hagroy Modelo: SYSTEM SENSOR SY SYH | C56: UND | D56: 479 | F56: 32.5 | G56: =+E56*D56 -> 0 | H56: =+F56*D56 -> 15567.5 | I56: =+G56+(H56*$I$3) -> 52151.125
B57: Fuente de alimentación Booster NACs para sirenas. Certificado UL Marca: KIDDE Modelo: MIRBPS10A/230 | C57: UND | D57: 6 | F57: 465.98 | G57: =+E57*D57 -> 0 | H57: =+F57*D57 -> 2795.88 | I57: =+G57+(H57*$I$3) -> 9366.198
B58: MODULOS
B59: Módulo de monitoreo para zonificación de equipos convencionales * 373 zonas [ 1 zona por sótano en el edificio, 1 zona en cto de bomba,1 zonas por cada dpto,1 zona por cada area comun de cada piso] Marca: KIDDE Modelo: GSA-CT1 | C59: UND | D59: 373 | F59: 30.5 | G59: =+E59*D59 -> 0 | H59: =+F59*D59 -> 11376.5 | I59: =+G59+(H59*$I$3) -> 38111.275
B60: Módulo de monitoreo para interconexion en cuarto de bomba y sensor de aniego Marca: KIDDE Modelo: GSA-CT1 | C60: UND | D60: 9 | F60: 30.5 | G60: =+E60*D60 -> 0 | H60: =+F60*D60 -> 274.5 | I60: =+G60+(H60*$I$3) -> 919.575
B61: Módulo de monitoreo doble para interconexion * 1 en cada sótano para válvulas de sector. y sensores de flujo de agua Marca: KIDDE Modelo: GSA-CT2 | C61: UND | D61: 96 | F61: 54 | G61: =+E61*D61 -> 0 | H61: =+F61*D61 -> 5184 | I61: =+G61+(H61*$I$3) -> 17366.4
B62: Módulo de control para interconexión con sistema Ventilación, grupo electrógeno y transferencia * 3 en Tablero TC-VP para control de sistema presurizado Marca: KIDDE Modelo: GSA-CR | C62: UND | D62: 5 | F62: 41.5 | G62: =+E62*D62 -> 0 | H62: =+F62*D62 -> 207.5 | I62: =+G62+(H62*$I$3) -> 695.125
B63: Módulo de control para interconexión con sistema Extracción de CO * 1 en Tablero TC-CO para monitoreo o control del sistema Marca: KIDDE Modelo: GSA-CR | C63: UND | D63: 7 | F63: 41.5 | G63: =+E63*D63 -> 0 | H63: =+F63*D63 -> 290.5 | I63: =+G63+(H63*$I$3) -> 973.175
B64: Módulo de control para interconexión con sistema de ascensores * 1 en Tablero TC-CO para monitoreo o control del sistema Marca: KIDDE Modelo: GSA-CR | C64: UND | D64: 4 | F64: 41.5 | G64: =+E64*D64 -> 0 | H64: =+F64*D64 -> 166 | I64: =+G64+(H64*$I$3) -> 556.1
B65: Módulo de señal para zonificación de sirenas * 1 zona por cada nivel en el edificio Marca: KIDDE Modelo: GSA-CC1 | C65: UND | D65: 27 | F65: 40.75 | G65: =+E65*D65 -> 0 | H65: =+F65*D65 -> 1100.25 | I65: =+G65+(H65*$I$3) -> 3685.8375
B66: Módulo de aislamiento Marca: KIDDE Modelo: GSA-IM | C66: UND | D66: 1 | F66: 31.45 | G66: =+E66*D66 -> 0 | H66: =+F66*D66 -> 31.45 | I66: =+G66+(H66*$I$3) -> 105.3575
B67: INSTALACION
B68: Instalación, mano de obra y cableado | C68: Glb | D68: 1 | F68: 28231 | G68: =+E68*D68 -> 0 | H68: =+F68*D68 -> 28231 | I68: =+G68+(H68*$I$3) -> 94573.85
A69: 01.05 | B69: SISTEMA DE GAS | I69: =SUM(G70) -> 426957.93
A70: 01.01.01.05 | B70: Sistema de gas Redes internas PealPe Montantes de cobre | C70: glb | D70: 1 | E70: 426957.93 | G70: =+E70*D70 -> 426957.93 | H70: =+F70*D70 -> 0 | I70: =+G70+(H70*$I$3) -> 426957.93
A71: 01.05 | B71: PISCINA CONVENCIONAL | I71: =SUM(G72) -> 72039.77
A72: 01.01.01.05 | B72: Sistema de piscina convencional con revestimiento PVC | C72: glb | D72: 1 | E72: 72039.77 | G72: =+E72*D72 -> 72039.77 | H72: =+F72*D72 -> 0 | I72: =+G72+(H72*$I$3) -> 72039.77
A73: 01.05 | B73: SISTEMA FOTOVOLTAICO | I73: =SUM(H74) -> 10563.38
A74: 01.01.01.05 | B74: Sistema de paneles fotovoltaicos | C74: glb | D74: 1 | F74: 10563.38 | G74: =+E74*D74 -> 0 | H74: =+F74*D74 -> 10563.38 | I74: =+G74+(H74*$I$3) -> 35387.323
A75: 01.05 | B75: SISTEMA CCTV | I75: =SUM(H76:H86) -> 8827
A76: 01.01.01.05 | B76: Monitor a color LED de 24" Full HD Samsumg | C76: und | D76: 3 | F76: 225 | G76: =+E76*D76 -> 0 | H76: =+F76*D76 -> 675 | I76: =+G76+(H76*$I$3) -> 2261.25
A77: 01.01.01.06 | B77: Camaras TUBO a color Full HD 1/3" con lente de 2.8 mm, con infrarojo 700TVL de resolución 1080P, día y noche 0.01 Lux Mod. DS-12E16DOT | C77: und | D77: 38 | F77: 30.5 | G77: =+E77*D77 -> 0 | H77: =+F77*D77 -> 1159 | I77: =+G77+(H77*$I$3) -> 3882.65
A78: 01.01.01.07 | B78: Camaras MINI DOMO a color FULL HD 1/3" con lente de 2.8mm, con infrarojo 700TVL de resolución 1080P, día y noche 0.01 Lux Mod. HK-DS2CE56DOT | C78: und | D78: 8 | F78: 30.5 | G78: =+E78*D78 -> 0 | H78: =+F78*D78 -> 244 | I78: =+G78+(H78*$I$3) -> 817.4
A79: 01.01.01.08 | B79: Grabador digital DVR de 32 canales Mod. HK-DS7232HQHI | C79: und | D79: 1 | F79: 395 | G79: =+E79*D79 -> 0 | H79: =+F79*D79 -> 395 | I79: =+G79+(H79*$I$3) -> 1323.25
A80: 01.01.01.09 | B80: Grabador digital DVR de 08 canales Mod. HK-DS7208HQHI | C80: und | D80: 2 | F80: 155 | G80: =+E80*D80 -> 0 | H80: =+F80*D80 -> 310 | I80: =+G80+(H80*$I$3) -> 1038.5
A81: 01.01.01.10 | B81: Disco duro de 8 TB | C81: und | D81: 1 | F81: 355 | G81: =+E81*D81 -> 0 | H81: =+F81*D81 -> 355 | I81: =+G81+(H81*$I$3) -> 1189.25
A82: 01.01.01.11 | B82: Disco duro de 4 TB | C82: und | D82: 2 | F82: 139 | G82: =+E82*D82 -> 0 | H82: =+F82*D82 -> 278 | I82: =+G82+(H82*$I$3) -> 931.3
A83: 01.01.01.12 | B83: Fuentes de alimentación de 12V | C83: und | D83: 46 | F83: 6 | G83: =+E83*D83 -> 0 | H83: =+F83*D83 -> 276 | I83: =+G83+(H83*$I$3) -> 924.6
A84: 01.01.01.13 | B84: Ganinete metalico de 4 RU | C84: und | D84: 1 | F84: 155 | G84: =+E84*D84 -> 0 | H84: =+F84*D84 -> 155 | I84: =+G84+(H84*$I$3) -> 519.25
A85: 01.01.01.14 | B85: Instalacion,programacion,mano de obra y cableado
A86: 01.01.01.15 | B86: Cable utp cat 5e,cable mellizo,conectores,material menudo. | C86: glb | D86: 1 | F86: 4980 | G86: =+E86*D86 -> 0 | H86: =+F86*D86 -> 4980 | I86: =+G86+(H86*$I$3) -> 16683

Sheet IIMM
A2: INSTALACIONES MECANICAS
H3: T.C | I3: 3.35
A4: Presupuesto | B4: GERMANIA
A5: Subpresupuesto | B5: INSTALACIONES MECANICAS
A6: Cliente | B6: : V&V Bravo S.A.C | F6: Costo al | G6: 46133
A7: Lugar
A8: ITEM | B8: DESCRIPCION | C8: UND | D8: CANTIDAD | E8: P.U (S/.) | F8: P.U ($.) | G8: PARCIAL (S/.) | H8: PARCIAL ($) | I8: TOTAL
B9: VENTILACIÓN MECÁNICA | I9: =SUM(H10:H130) -> 162567.43
B10: VESTIBULO PREVIO VENTILADO Y ESCALERA
B11: INYECTOR CENTRÍFUGO EN GABINETE Marca: System air o similar Modelo: KVB Características: 5,600 CFM - 1.5"c.a. - 220V-3F-60Hz | C11: und | D11: 1 | F11: 1031.3887 | G11: =+E11*D11 -> 0 | H11: =+F11*D11 -> 1031.3887 | I11: =+G11+(H11*$I$3) -> 3455.1522
B12: INYECTOR CENTRÍFUGO EN GABINETE Marca: System air o similar Modelo: KVB Características: 7,860 CFM - 1.5"c.a. - 220V-3F-60Hz | C12: und | D12: 1 | F12: 1438.8887 | G12: =+E12*D12 -> 0 | H12: =+F12*D12 -> 1438.8887 | I12: =+G12+(H12*$I$3) -> 4820.2772
B13: INYECTOR CENTRÍFUGO EN GABINETE Marca: System air o similar Modelo: KVB Características: 8,200 CFM - 1.5"c.a. - 220V-3F-60Hz | C13: und | D13: 1 | F13: 1438.8887 | G13: =+E13*D13 -> 0 | H13: =+F13*D13 -> 1438.8887 | I13: =+G13+(H13*$I$3) -> 4820.2772
B14: INYECTOR CENTRÍFUGO EN GABINETE Marca: System air o similar Modelo: KVB Características: 9,600 CFM - 1.5"c.a. - 220V-3F-60Hz | C14: und | D14: 1 | F14: 2671.3887 | G14: =+E14*D14 -> 0 | H14: =+F14*D14 -> 2671.3887 | I14: =+G14+(H14*$I$3) -> 8949.1522
B15: EXTARCTOR CENTRÍFUGO EN GABINETE Marca: System air o similar Modelo: KVB Características: 8,400 CFM - 1.5"c.a. - 220V-3F-60Hz | C15: und | D15: 1 | F15: 1438.8887 | G15: =+E15*D15 -> 0 | H15: =+F15*D15 -> 1438.8887 | I15: =+G15+(H15*$I$3) -> 4820.2772
B16: EXTARCTOR CENTRÍFUGO EN GABINETE Marca: System air o similar Modelo: KVB Características: 11,780 CFM - 1.5"c.a. - 220V-3F-60Hz | C16: und | D16: 1 | F16: 2735.1387 | G16: =+E16*D16 -> 0 | H16: =+F16*D16 -> 2735.1387 | I16: =+G16+(H16*$I$3) -> 9162.7147
B17: SENSOR DE HUMO | C17: und | D17: 4 | F17: 181.38873 | G17: =+E17*D17 -> 0 | H17: =+F17*D17 -> 725.55492 | I17: =+G17+(H17*$I$3) -> 2430.609
B18: DAMPER BAROMÉTRICO 24"X24" ACP | C18: und | D18: 2 | F18: 375.13873 | G18: =+E18*D18 -> 0 | H18: =+F18*D18 -> 750.27746 | I18: =+G18+(H18*$I$3) -> 2513.4295
B19: FILTRO DE MALLA DE ALUMINIO DE 47"X47"X1" suministro e instalación | C19: und | D19: 1 | F19: 331.38873 | G19: =+E19*D19 -> 0 | H19: =+F19*D19 -> 331.38873 | I19: =+G19+(H19*$I$3) -> 1110.1522
B20: FILTRO DE MALLA DE ALUMINIO DE 48"X48"X1" suministro e instalación | C20: und | D20: 2 | F20: 343.88873 | G20: =+E20*D20 -> 0 | H20: =+F20*D20 -> 687.77746 | I20: =+G20+(H20*$I$3) -> 2304.0545
B21: FILTRO DE MALLA DE ALUMINIO DE 54"X54"X1" suministro e instalación | C21: und | D21: 1 | F21: 437.63873 | G21: =+E21*D21 -> 0 | H21: =+F21*D21 -> 437.63873 | I21: =+G21+(H21*$I$3) -> 1466.0897
B22: EXTRACCIÓN DE MONÓXIDO DE CARBONO
B23: INYECTOR AXIAL Marca: System air o similar Modelo: AWE Características: 4,100 CFM - 0.5"c.a. - 220V-3F-60Hz | C23: und | D23: 1 | F23: 275.13873 | G23: =+E23*D23 -> 0 | H23: =+F23*D23 -> 275.13873 | I23: =+G23+(H23*$I$3) -> 921.71475
B24: INYECTOR AXIAL Marca: System air o similar Modelo: AWE Características: 4,600 CFM - 0.5"c.a. - 220V-3F-60Hz | C24: und | D24: 2 | F24: 275.13873 | G24: =+E24*D24 -> 0 | H24: =+F24*D24 -> 550.27746 | I24: =+G24+(H24*$I$3) -> 1843.4295
B25: INYECTOR AXIAL Marca: System air o similar Modelo: AWE Características: 4,650 CFM - 0.5"c.a. - 220V-3F-60Hz | C25: und | D25: 8 | F25: 275.13873 | G25: =+E25*D25 -> 0 | H25: =+F25*D25 -> 2201.1098 | I25: =+G25+(H25*$I$3) -> 7373.718
B26: INYECTOR AXIAL Marca: System air o similar Modelo: AWE Características: 5,700 CFM - 0.5"c.a. - 220V-3F-60Hz | C26: und | D26: 2 | F26: 531.38873 | G26: =+E26*D26 -> 0 | H26: =+F26*D26 -> 1062.7775 | I26: =+G26+(H26*$I$3) -> 3560.3045
B27: EXTRACTOR AXIAL Marca: System air o similar Modelo: WPA Características: 3,600 CFM - 1.0"c.a. - 220V-3F-60Hz | C27: und | D27: 1 | F27: 757.63873 | G27: =+E27*D27 -> 0 | H27: =+F27*D27 -> 757.63873 | I27: =+G27+(H27*$I$3) -> 2538.0897
B28: EXTRACTOR AXIAL Marca: System air o similar Modelo: WPA Características: 4,600 CFM - 1.0"c.a. - 220V-3F-60Hz | C28: und | D28: 2 | F28: 757.63873 | G28: =+E28*D28 -> 0 | H28: =+F28*D28 -> 1515.2775 | I28: =+G28+(H28*$I$3) -> 5076.1795
B29: EXTRACTOR AXIAL Marca: System air o similar Modelo: WPA Características: 4,650 CFM - 1.0"c.a. - 220V-3F-60Hz | C29: und | D29: 6 | F29: 757.63873 | G29: =+E29*D29 -> 0 | H29: =+F29*D29 -> 4545.8324 | I29: =+G29+(H29*$I$3) -> 15228.538
B30: EXTRACTOR AXIAL Marca: System air o similar Modelo: WPA Características: 5,700 CFM - 1.0"c.a. - 220V-3F-60Hz | C30: und | D30: 2 | F30: 786.38873 | G30: =+E30*D30 -> 0 | H30: =+F30*D30 -> 1572.7775 | I30: =+G30+(H30*$I$3) -> 5268.8045
B31: EXTRACTOR AXIAL Marca: System air o similar Modelo: WPA Características: 6,700 CFM - 1.0"c.a. - 220V-3F-60Hz | C31: und | D31: 2 | F31: 812.63873 | G31: =+E31*D31 -> 0 | H31: =+F31*D31 -> 1625.2775 | I31: =+G31+(H31*$I$3) -> 5444.6795
B32: JET FAN TUBULAR Marca: System air o similar Modelo: AJ8M Características: 3,100 CFM - 25N - 220V-3F-60Hz | C32: und | D32: 27 | F32: 1125.1387 | G32: =+E32*D32 -> 0 | H32: =+F32*D32 -> 30378.746 | I32: =+G32+(H32*$I$3) -> 101768.8
B33: DETECTOR DE MONÓXIDO Marca: GREYSTONE Modelo: CMD5B1 Caracteristicas: Consumo: 50mA max - Señal de salida :0-20mA | C33: und | D33: 33 | F33: 156.38873 | G33: =+E33*D33 -> 0 | H33: =+F33*D33 -> 5160.8281 | I33: =+G33+(H33*$I$3) -> 17288.774
B34: Damper de gravedad de fabricación nacional suminsitro e instalación | C34: und | D34: 26 | F34: 137.63873 | G34: =+E34*D34 -> 0 | H34: =+F34*D34 -> 3578.607 | I34: =+G34+(H34*$I$3) -> 11988.333
B35: DAMPER CORTA FUEGO nacional 44"X41" Con fusible UL | C35: und | D35: 2 | F35: 375.13873 | G35: =+E35*D35 -> 0 | H35: =+F35*D35 -> 750.27746 | I35: =+G35+(H35*$I$3) -> 2513.4295
B36: VENTILACIÓN EN CUARTO DE BOMBAS
B37: INYECTOR CENTRÍFUGO EN GABINETE Marca: System air o similar Modelo: KVB Características: 4,500 CFM - 0.7"c.a. - 220V-3F-60Hz | C37: und | D37: 1 | F37: 816.38873 | G37: =+E37*D37 -> 0 | H37: =+F37*D37 -> 816.38873 | I37: =+G37+(H37*$I$3) -> 2734.9022
B38: EXTRACTOR CENTRÍFUGO EN GABINETE Marca: System air o similar Modelo: KVB Características: 4,500 CFM - 0.7"c.a. - 220V-3F-60Hz | C38: und | D38: 1 | F38: 816.38873 | G38: =+E38*D38 -> 0 | H38: =+F38*D38 -> 816.38873 | I38: =+G38+(H38*$I$3) -> 2734.9022
B39: DAMPER CORTA FUEGO nacional 46"X12" Con fusible UL | C39: und | D39: 2 | F39: 375.13873 | G39: =+E39*D39 -> 0 | H39: =+F39*D39 -> 750.27746 | I39: =+G39+(H39*$I$3) -> 2513.4295
B40: VENTILACIÓN EN CUARTO DE BASURA
B41: EXTRACTOR CENTRÍFUGO EN GABINETE Marca: System air o similar Modelo: CDRE Características: 500 CFM - 1.0"c.a. - 220V-1F-60Hz | C41: und | D41: 1 | F41: 446.38873 | G41: =+E41*D41 -> 0 | H41: =+F41*D41 -> 446.38873 | I41: =+G41+(H41*$I$3) -> 1495.4022
B42: EXTRACTOR CENTRÍFUGO EN GABINETE Marca: System air o similar Modelo: CDRE Características: 900 CFM - 1.0"c.a. - 220V-1F-60Hz | C42: und | D42: 1 | F42: 446.38873 | G42: =+E42*D42 -> 0 | H42: =+F42*D42 -> 446.38873 | I42: =+G42+(H42*$I$3) -> 1495.4022
B43: EXTRACTOR CENTRÍFUGO EN GABINETE Marca: System air o similar Modelo: CDRE Características: 900 CFM - 1.3"c.a. - 220V-1F-60Hz | C43: und | D43: 1 | F43: 521.38873 | G43: =+E43*D43 -> 0 | H43: =+F43*D43 -> 521.38873 | I43: =+G43+(H43*$I$3) -> 1746.6522
B44: DAMPER CORTA FUEGO nacional DE 12"X12" Con fusible UL | C44: und | D44: 1 | F44: 75.138731 | G44: =+E44*D44 -> 0 | H44: =+F44*D44 -> 75.138731 | I44: =+G44+(H44*$I$3) -> 251.71475
B45: DAMPER CORTA FUEGO nacional DE 14"X10" Con fusible UL | C45: und | D45: 1 | F45: 75.138731 | G45: =+E45*D45 -> 0 | H45: =+F45*D45 -> 75.138731 | I45: =+G45+(H45*$I$3) -> 251.71475
B46: DAMPER CORTA FUEGO nacional DE 15"X10" Con fusible UL | C46: und | D46: 1 | F46: 75.138731 | G46: =+E46*D46 -> 0 | H46: =+F46*D46 -> 75.138731 | I46: =+G46+(H46*$I$3) -> 251.71475
B47: DAMPER CORTA FUEGO nacional DE 18"X12" Con fusible UL | C47: und | D47: 1 | F47: 93.888731 | G47: =+E47*D47 -> 0 | H47: =+F47*D47 -> 93.888731 | I47: =+G47+(H47*$I$3) -> 314.52725
B48: DAMPER CORTA FUEGO nacional DE 18"X14" Con fusible UL | C48: und | D48: 2 | F48: 93.888731 | G48: =+E48*D48 -> 0 | H48: =+F48*D48 -> 187.77746 | I48: =+G48+(H48*$I$3) -> 629.0545
B49: Damper de gravedad de fabricación nacional de 10"X10" | C49: und | D49: 1 | F49: 17.638731 | G49: =+E49*D49 -> 0 | H49: =+F49*D49 -> 17.638731 | I49: =+G49+(H49*$I$3) -> 59.08975
B50: Damper de gravedad de fabricación nacional de 12"X12" | C50: und | D50: 1 | F50: 25.138731 | G50: =+E50*D50 -> 0 | H50: =+F50*D50 -> 25.138731 | I50: =+G50+(H50*$I$3) -> 84.21475
B51: VENTILACIÓN DE PASILLOS
B52: INYECTOR CENTRÍFUGO EN GABINETE Marca: System air o similar Modelo: KVB Características: 4,100 CFM - 1.5"c.a. - 220V-3F-60Hz | C52: und | D52: 1 | F52: 787.63873 | G52: =+E52*D52 -> 0 | H52: =+F52*D52 -> 787.63873 | I52: =+G52+(H52*$I$3) -> 2638.5897
B53: EXTRACTOR CENTRÍFUGO EN GABINETE Marca: System air o similar Modelo: KVB Características: 4,100 CFM - 1.5"c.a. - 220V-3F-60Hz | C53: und | D53: 1 | F53: 787.63873 | G53: =+E53*D53 -> 0 | H53: =+F53*D53 -> 787.63873 | I53: =+G53+(H53*$I$3) -> 2638.5897
B54: FILTRO DE MALLA DE ALUMINIO DE 34"X34"X1" suministro e instalación | C54: und | D54: 1 | F54: 175.13873 | G54: =+E54*D54 -> 0 | H54: =+F54*D54 -> 175.13873 | I54: =+G54+(H54*$I$3) -> 586.71475
B55: VENTILACIÓN DE ESCLUSA Y ACELERÓGRAFO
B56: INYECTOR HELICOCENTRÍFUGO Marca: System air o similar Modelo: k Características: 180 CFM - 0.7" c.a. - 220V-1F-60Hz | C56: und | D56: 1 | F56: 112.63873 | G56: =+E56*D56 -> 0 | H56: =+F56*D56 -> 112.63873 | I56: =+G56+(H56*$I$3) -> 377.33975
B57: EXTRACTOR HELICOCENTRÍFUGO Marca: System air o similar Modelo: k Características: 180 CFM - 0.7" c.a. - 220V-1F-60Hz | C57: und | D57: 1 | F57: 112.63873 | G57: =+E57*D57 -> 0 | H57: =+F57*D57 -> 112.63873 | I57: =+G57+(H57*$I$3) -> 377.33975
B58: EXTRACTOR AXIAL CON DAMPER Marca: System air o similar Modelo: BF SLIM 150 Características: 150 CFM - 0.05" c.a. - 220V-1F-60Hz | C58: und | D58: 1 | F58: 15.138731 | G58: =+E58*D58 -> 0 | H58: =+F58*D58 -> 15.138731 | I58: =+G58+(H58*$I$3) -> 50.71475
B59: DAMPER CORTA FUEGO nacional DE 6"X4" Con fusible UL | C59: und | D59: 2 | F59: 31.388731 | G59: =+E59*D59 -> 0 | H59: =+F59*D59 -> 62.777462 | I59: =+G59+(H59*$I$3) -> 210.3045
B60: DAMPER CORTA FUEGO nacional DE 8"X6" Con fusible UL | C60: und | D60: 1 | F60: 37.638731 | G60: =+E60*D60 -> 0 | H60: =+F60*D60 -> 37.638731 | I60: =+G60+(H60*$I$3) -> 126.08975
B61: VENTILACIÓN DE GRUPO ELECTRÓGENO
B62: EXTRACTOR AXIAL Marca: System air o similar Modelo: AWE Características: 1,400 CFM - 0.15"c.a. - 220V-1F-60Hz | C62: und | D62: 1 | F62: 108.88873 | G62: =+E62*D62 -> 0 | H62: =+F62*D62 -> 108.88873 | I62: =+G62+(H62*$I$3) -> 364.77725
B63: DAMPER CORTA FUEGO nacional DE 23"X23" Con fusible UL | C63: und | D63: 1 | F63: 212.63873 | G63: =+E63*D63 -> 0 | H63: =+F63*D63 -> 212.63873 | I63: =+G63+(H63*$I$3) -> 712.33975
B64: DAMPER CORTA FUEGO nacional DE 30"X30" Con fusible UL | C64: und | D64: 2 | F64: 275.13873 | G64: =+E64*D64 -> 0 | H64: =+F64*D64 -> 550.27746 | I64: =+G64+(H64*$I$3) -> 1843.4295
B65: VENTILACIÓN DE PET ZONTE
B66: EXTRACTOR AXIAL Marca: System air o similar Modelo: AWE Características: 500 CFM - 0.15"c.a. - 220V-1F-60Hz | C66: und | D66: 1 | F66: 63.888731 | G66: =+E66*D66 -> 0 | H66: =+F66*D66 -> 63.888731 | I66: =+G66+(H66*$I$3) -> 214.02725
B67: VENTILACIÓN DE BAÑOS Y CENTRO DE LAVADO
B68: EXTRACTOR AXIAL CON DAMPER Marca: System air o similar Modelo: BF SLIM 150 Características: 100 CFM - 0.1" c.a. - 220V-1F-60Hz | C68: und | D68: 875 | F68: 15.138731 | G68: =+E68*D68 -> 0 | H68: =+F68*D68 -> 13246.39 | I68: =+G68+(H68*$I$3) -> 44375.406
B69: EXTRACTOR EÓLICO suministro e instalación | C69: und | D69: 20 | F69: 300.13873 | G69: =+E69*D69 -> 0 | H69: =+F69*D69 -> 6002.7746 | I69: =+G69+(H69*$I$3) -> 20109.295
B71: VESTIBULO PREVIO VENTILADO Y ESCALERA
B72: Suministro e instalación de ductos metálicos de fierro galvanizado fabricados de acuerdo a la normativa SMACNA | C72: kg | D72: 610 | F72: 3.5137312 | G72: =+E72*D72 -> 0 | H72: =+F72*D72 -> 2143.3761 | I72: =+G72+(H72*$I$3) -> 7180.3098
B73: SUMINISTRO E INSTALACIÓN DE REJILLAS DE FIERRO GALVANIZADO INCLUYE PROTECCIÓN ANTICORROSIVA, PINTADO CON ESMALTE DE COLOR BLANCO AL HORNO y DAMPER DE REGULACIÓN MANUAL
B74: REJILLAS DE INYECCIÓN Y EXTRACCIÓN | C74: pulg2 | D74: 14269 | F74: 0.30123124 | G74: =+E74*D74 -> 0 | H74: =+F74*D74 -> 4298.2686 | I74: =+G74+(H74*$I$3) -> 14399.2
B75: Instalación mecánica de ventilador centrífugo | C75: und | D75: 6 | F75: 131.38873 | G75: =+E75*D75 -> 0 | H75: =+F75*D75 -> 788.33239 | I75: =+G75+(H75*$I$3) -> 2640.9135
B76: tablero de control de (6)Centrífugos (2) Tableros eléctricos fabricado con plancha de fierro galvanizado 2 mm de espesor con recubrimiento anticorrosivo epóxico, hermético al polvo (IP-65) incluye: (3) contactores , (3) selectores MOA, (1) LED, (1) transformador y Borneras. difernecial + timer -se deja bornera para la conección del cuarto del control al tablero | C76: glb | D76: 1 | F76: 2125.1387 | G76: =+E76*D76 -> 0 | H76: =+F76*D76 -> 2125.1387 | I76: =+G76+(H76*$I$3) -> 7119.2147
B77: instalación de sensor de humo | C77: und | D77: 4 | F77: 62.638731 | G77: =+E77*D77 -> 0 | H77: =+F77*D77 -> 250.55492 | I77: =+G77+(H77*$I$3) -> 839.359
B78: EXTRACCIÓN DE MONÓXIDO DE CARBONO
B79: Suministro e instalación de ductos metálicos de fierro galvanizado fabricados de acuerdo a la normativa SMACNA | C79: kg | D79: 3204 | F79: 3.5137312 | G79: =+E79*D79 -> 0 | H79: =+F79*D79 -> 11257.995 | I79: =+G79+(H79*$I$3) -> 37714.283
B80: SUMINISTRO E INSTALACIÓN DE REJILLAS DE FIERRO GALVANIZADO INCLUYE PROTECCIÓN ANTICORROSIVA, PINTADO CON ESMALTE DE COLOR BLANCO AL HORNO y DAMPER DE REGULACIÓN MANUAL
B81: REJILLAS DE INYECCIÓN Y EXTRACCIÓN | C81: pulg2 | D81: 26728 | F81: 0.30123124 | G81: =+E81*D81 -> 0 | H81: =+F81*D81 -> 8051.3086 | I81: =+G81+(H81*$I$3) -> 26971.884
B82: Instalación mecánica extractor AXIAL | C82: und | D82: 13 | F82: 50.138731 | G82: =+E82*D82 -> 0 | H82: =+F82*D82 -> 651.80351 | I82: =+G82+(H82*$I$3) -> 2183.5417
B83: Instalación mecánica intector AXIAL | C83: und | D83: 13 | F83: 43.888731 | G83: =+E83*D83 -> 0 | H83: =+F83*D83 -> 570.55351 | I83: =+G83+(H83*$I$3) -> 1911.3542
B84: Instalación mecánica de jet fan | C84: und | D84: 27 | F84: 62.638731 | G84: =+E84*D84 -> 0 | H84: =+F84*D84 -> 1691.2457 | I84: =+G84+(H84*$I$3) -> 5665.6732
B85: TABLERO DE CONTROL de (27) jet fan, (13) Inyectores y (13) Extractores . (7) Tableros eléctricos fabricado con plancha de fierro galvanizado 2 mm de espesor con recubrimiento anticorrosivo epóxico, hermetico al polvo (IP-55) incluye: (1) contactores jet fan ,(1) contactor extracción, (1) contactor inyector,(1) selectores MOA, (1) LED, (1) transformador y Borneras. difernecial + timer -se deja bornera para la conección del cuarto del control al tablero | C85: glb | D85: 1 | F85: 7250.1387 | G85: =+E85*D85 -> 0 | H85: =+F85*D85 -> 7250.1387 | I85: =+G85+(H85*$I$3) -> 24287.965
B86: Instalación de detector de monóxido de carbono, cableado de comunicación y coneccion eléctrica | C86: und | D86: 33 | F86: 62.638731 | G86: =+E86*D86 -> 0 | H86: =+F86*D86 -> 2067.0781 | I86: =+G86+(H86*$I$3) -> 6924.7117
B87: VENTILACIÓN EN CUARTO DE BOMBAS
B88: Suministro e instalación de ductos metálicos de fierro galvanizado fabricados de acuerdo a la normativa SMACNA, | C88: kg | D88: 425 | F88: 3.5137312 | G88: =+E88*D88 -> 0 | H88: =+F88*D88 -> 1493.3358 | I88: =+G88+(H88*$I$3) -> 5002.6749
B89: SUMINISTRO E INSTALACIÓN DE REJILLAS DE FIERRO GALVANIZADO INCLUYE PROTECCIÓN ANTICORROSIVA, PINTADO CON ESMALTE DE COLOR BLANCO AL HORNO y DAMPER DE REGULACIÓN MANUAL
B90: REJILLAS DE INYECCIÓN Y EXTRACCIÓN | C90: pulg2 | D90: 900 | F90: 0.30123124 | G90: =+E90*D90 -> 0 | H90: =+F90*D90 -> 271.10812 | I90: =+G90+(H90*$I$3) -> 908.21219
B91: Instalación mecánica de ventilador centrífugo | C91: und | D91: 2 | F91: 93.888731 | G91: =+E91*D91 -> 0 | H91: =+F91*D91 -> 187.77746 | I91: =+G91+(H91*$I$3) -> 629.0545
B92: Instalación de damper corta fuego | C92: und | D92: 2 | F92: 15.138731 | G92: =+E92*D92 -> 0 | H92: =+F92*D92 -> 30.277462 | I92: =+G92+(H92*$I$3) -> 101.4295
B93: TABLERO DE CONTROL | C93: glb | D93: 1 | F93: 575.13873 | G93: =+E93*D93 -> 0 | H93: =+F93*D93 -> 575.13873 | I93: =+G93+(H93*$I$3) -> 1926.7147
B94: VENTILACIÓN EN CUARTO DE BASURA
B95: Suministro e instalación de ductos metálicos de fierro galvanizado fabricados de acuerdo a la normativa SMACNA, | C95: kg | D95: 580 | F95: 3.5137312 | G95: =+E95*D95 -> 0 | H95: =+F95*D95 -> 2037.9641 | I95: =+G95+(H95*$I$3) -> 6827.1798
B96: SUMINISTRO E INSTALACIÓN DE REJILLAS DE FIERRO GALVANIZADO INCLUYE PROTECCIÓN ANTICORROSIVA, PINTADO CON ESMALTE DE COLOR BLANCO AL HORNO y DAMPER DE REGULACIÓN MANUAL
B97: REJILLAS DE INYECCIÓN Y EXTRACCIÓN | C97: pulg2 | D97: 644 | F97: 0.30123124 | G97: =+E97*D97 -> 0 | H97: =+F97*D97 -> 193.99292 | I97: =+G97+(H97*$I$3) -> 649.87628
B98: Instalación mecánica de ventilador centrífugo | C98: und | D98: 3 | F98: 62.638731 | G98: =+E98*D98 -> 0 | H98: =+F98*D98 -> 187.91619 | I98: =+G98+(H98*$I$3) -> 629.51925
B99: Instalación de damper corta fuego | C99: und | D99: 6 | F99: 12.638731 | G99: =+E99*D99 -> 0 | H99: =+F99*D99 -> 75.832387 | I99: =+G99+(H99*$I$3) -> 254.0385
B100: TABLERO DE CONTROL | C100: glb | D100: 1 | F100: 750.13873 | G100: =+E100*D100 -> 0 | H100: =+F100*D100 -> 750.13873 | I100: =+G100+(H100*$I$3) -> 2512.9647
B101: VENTILACIÓN DE PASILLOS
B102: Suministro e instalación de ductos metálicos de fierro galvanizado fabricados de acuerdo a la normativa SMACNA, | C102: kg | D102: 85 | F102: 3.5137312 | G102: =+E102*D102 -> 0 | H102: =+F102*D102 -> 298.66716 | I102: =+G102+(H102*$I$3) -> 1000.535
...

Sheet IIEE
A2: INSTALACIONES ELECTRICAS
H3: T.C | I3: 3.35
A4: Presupuesto | B4: GERMANIA
A5: Subpresupuesto | B5: INSTALACIONES ELECTRICAS
A6: Cliente | B6: : V&V Bravo S.A.C | F6: Costo al | G6: 46133
A7: Lugar
A8: ITEM | B8: DESCRIPCION | C8: UND | D8: CANTIDAD | E8: P.U (S/.) | F8: P.U ($.) | G8: PARCIAL (S/.) | H8: PARCIAL ($) | I8: TOTAL
A9: 01 | B9: INSTALACIONES ELECTRICAS | G9: =SUM(G10:G180) -> 2904701.4 | H9: =SUM(H10:H179) -> 492473.21 | I9: =SUM(I10:I180) -> 4554486.6
A10: 01.01 | B10: SISTEMA DE ALUMBRADO
A11: 01.01.01 | B11: SALIDAS DE ALUMBRADO
A12: 01.01.01.01 | B12: SALIDA PARA LUMINARIA EN TECHO | C12: pto | D12: 376 | E12: 49.8 | F12: 5.54 | G12: =+E12*D12 -> 18724.8 | H12: =+F12*D12 -> 2083.04 | I12: =+G12+(H12*$I$3) -> 25702.984
A13: 01.01.01.02 | B13: SALIDA PARA LUMINARIA DE EMERGENCIA | C13: pto | D13: 444 | E13: 50.7 | F13: 5.54 | G13: =+E13*D13 -> 22510.8 | H13: =+F13*D13 -> 2459.76 | I13: =+G13+(H13*$I$3) -> 30750.996
A14: 01.01.01.03 | B14: SALIDA PARA LUMINARIA HERMETICA/FLUORESCENTE | C14: pto | D14: 232 | E14: 60.1 | F14: 5.54 | G14: =+E14*D14 -> 13943.2 | H14: =+F14*D14 -> 1285.28 | I14: =+G14+(H14*$I$3) -> 18248.888
A15: 01.01.01.04 | B15: SALIDA PARA SENSOR DE MOVIMIENTO | C15: pto | D15: 270 | E15: 60.1 | F15: 5.54 | G15: =+E15*D15 -> 16227 | H15: =+F15*D15 -> 1495.8 | I15: =+G15+(H15*$I$3) -> 21237.93
A16: 01.01.01.05 | B16: SALIDA PARA BRAQUETTE | C16: pto | D16: 57 | E16: 60.1 | F16: 5.54 | G16: =+E16*D16 -> 3425.7 | H16: =+F16*D16 -> 315.78 | I16: =+G16+(H16*$I$3) -> 4483.563
A17: 01.01.01.06 | B17: SALIDA PARA PISCINA | C17: pto | D17: 3 | E17: 60.1 | F17: 5.54 | G17: =+E17*D17 -> 180.3 | H17: =+F17*D17 -> 16.62 | I17: =+G17+(H17*$I$3) -> 235.977
A18: 01.01.01.07 | B18: SALIDA PARA CINTA LED | C18: pto | D18: 6 | E18: 60.1 | F18: 5.54 | G18: =+E18*D18 -> 360.6 | H18: =+F18*D18 -> 33.24 | I18: =+G18+(H18*$I$3) -> 471.954
A19: 01.01.01.08 | B19: SALIDA PARA ESTACA | C19: pto | D19: 55 | E19: 60.1 | F19: 5.54 | G19: =+E19*D19 -> 3305.5 | H19: =+F19*D19 -> 304.7 | I19: =+G19+(H19*$I$3) -> 4326.245
A20: 01.01.01.09 | B20: SALIDA PARA LUMINARIA CON SENSOR | C20: pto | D20: 671 | E20: 60.1 | F20: 5.54 | G20: =+E20*D20 -> 40327.1 | H20: =+F20*D20 -> 3717.34 | I20: =+G20+(H20*$I$3) -> 52780.189
A21: 01.01.01.10 | B21: SALIDA PARA EXTRACTOR EN BAÑOS/DEPOSITOS | C21: pto | D21: 866 | E21: 60.1 | F21: 5.54 | G21: =+E21*D21 -> 52046.6 | H21: =+F21*D21 -> 4797.64 | I21: =+G21+(H21*$I$3) -> 68118.694
A22: 01.01.02 | B22: SALIDAS DE ALUMBRADO EN DEPARTAMENTOS | G22: =+E22*D22 -> 0 | H22: =+F22*D22 -> 0 | I22: =+G22+(H22*$I$3) -> 0
A23: 01.01.02.01 | B23: SALIDA PARA BRAQUETTE | C23: pto | D23: 346 | E23: 47.56 | F23: 5.7 | G23: =+E23*D23 -> 16455.76 | H23: =+F23*D23 -> 1972.2 | I23: =+G23+(H23*$I$3) -> 23062.63
A24: 01.01.02.02 | B24: SALIDA PARA LUMINARIA EN TECHO | C24: pto | D24: 2939 | E24: 47.56 | F24: 4.87 | G24: =+E24*D24 -> 139778.84 | H24: =+F24*D24 -> 14312.93 | I24: =+G24+(H24*$I$3) -> 187727.16
A25: 01.01.02.03 | B25: SALIDA PARA LUMINARIA EN BALCONES | C25: pto | D25: 278 | E25: 47.56 | F25: 5.7 | G25: =+E25*D25 -> 13221.68 | H25: =+F25*D25 -> 1584.6 | I25: =+G25+(H25*$I$3) -> 18530.09
A26: 01.01.03 | B26: SALIDAS DE INTERRUPTORES | G26: =+E26*D26 -> 0 | H26: =+F26*D26 -> 0 | I26: =+G26+(H26*$I$3) -> 0
A27: 01.01.03.01 | B27: SALIDA PARA INTERRUPTOR SIMPLE | C27: pto | D27: 1718 | E27: 48.81 | F27: 4.92 | G27: =+E27*D27 -> 83855.58 | H27: =+F27*D27 -> 8452.56 | I27: =+G27+(H27*$I$3) -> 112171.66
A28: 01.01.03.02 | B28: SALIDA PARA INTERRUPTOR DOBLE | C28: pto | D28: 492 | E28: 48.81 | F28: 5.6 | G28: =+E28*D28 -> 24014.52 | H28: =+F28*D28 -> 2755.2 | I28: =+G28+(H28*$I$3) -> 33244.44
A29: 01.01.03.03 | B29: SALIDA PARA INTERRUPTOR DE CONMUTACION SIMPLE | C29: pto | D29: 1089 | E29: 48.81 | F29: 8.84 | G29: =+E29*D29 -> 53154.09 | H29: =+F29*D29 -> 9626.76 | I29: =+G29+(H29*$I$3) -> 85403.736
A30: 01.01.03.04 | B30: SALIDA PARA INTERRUPTOR DE CONMUTACION DOBLE | C30: pto | D30: 276 | E30: 49.26 | F30: 14.69 | G30: =+E30*D30 -> 13595.76 | H30: =+F30*D30 -> 4054.44 | I30: =+G30+(H30*$I$3) -> 27178.134
A31: 01.02 | B31: TABLEROS ELECTRICOS | G31: =+E31*D31 -> 0 | H31: =+F31*D31 -> 0 | I31: =+G31+(H31*$I$3) -> 0
A32: 01.02.01 | B32: SUMINISTRO E INSTALACION DE TABLEROS ELECTRICOS | G32: =+E32*D32 -> 0 | H32: =+F32*D32 -> 0 | I32: =+G32+(H32*$I$3) -> 0
A33: 01.02.01.01 | B33: SUMINISTRO E INSTALACION DE TABLEROS ELECTRICOS | C33: glb | D33: 1 | E33: 457627 | F33: 0 | G33: =+E33*D33 -> 457627 | H33: =+F33*D33 -> 0 | I33: =+G33+(H33*$I$3) -> 457627
A34: 01.03 | B34: SALIDAS DE FUERZA Y ALIMENTADORES | G34: =+E34*D34 -> 0 | H34: =+F34*D34 -> 0 | I34: =+G34+(H34*$I$3) -> 0
A35: 01.03.01 | B35: SALIDAS DE TOMACORRIENTE Y SALIDAS DE FUERZA | G35: =+E35*D35 -> 0 | H35: =+F35*D35 -> 0 | I35: =+G35+(H35*$I$3) -> 0
A36: 01.03.01.01 | B36: SALIDA PARA TOMACORRIENTE BIPOLAR DOBLE CON ESPIGA A TIERRA TIPO 1 | C36: pto | D36: =5137+3 -> 5140 | E36: 47.05 | F36: 7.09 | G36: =+E36*D36 -> 241837 | H36: =+F36*D36 -> 36442.6 | I36: =+G36+(H36*$I$3) -> 363919.71
A37: 01.03.01.02 | B37: SALIDA PARA TOMACORRIENTE BIPOLAR DOBLE CON ESPIGA A TIERRA TIPO 2 | C37: pto | D37: 125 | E37: 59.67 | F37: 5.54 | G37: =+E37*D37 -> 7458.75 | H37: =+F37*D37 -> 692.5 | I37: =+G37+(H37*$I$3) -> 9778.625
A38: 01.03.01.03 | B38: SALIDA PARA TOMACORRIENTE A PRUEBA DE AGUA | C38: pto | D38: 109 | E38: 58.89 | F38: 5.54 | G38: =+E38*D38 -> 6419.01 | H38: =+F38*D38 -> 603.86 | I38: =+G38+(H38*$I$3) -> 8441.941
A39: 01.03.01.04 | B39: SALIDA PARA TIMBRE | C39: pto | D39: 334 | E39: 58.89 | F39: 8.35 | G39: =+E39*D39 -> 19669.26 | H39: =+F39*D39 -> 2788.9 | I39: =+G39+(H39*$I$3) -> 29012.075
A40: 01.03.01.05 | B40: SALIDA PARA PULSADOR DE TIMBRE | C40: pto | D40: 334 | E40: 58.89 | F40: 8.35 | G40: =+E40*D40 -> 19669.26 | H40: =+F40*D40 -> 2788.9 | I40: =+G40+(H40*$I$3) -> 29012.075
A41: 01.03.01.06 | B41: SALIDA PARA CAMPANA EXTRACTORA | C41: pto | D41: 334 | E41: 58.89 | F41: 3.46 | G41: =+E41*D41 -> 19669.26 | H41: =+F41*D41 -> 1155.64 | I41: =+G41+(H41*$I$3) -> 23540.654
A42: 01.03.01.07 | B42: SALIDA DE FUERZA PARA SECADORA ELECTRICA | C42: pto | D42: 334 | E42: 58.89 | F42: 13.66 | G42: =+E42*D42 -> 19669.26 | H42: =+F42*D42 -> 4562.44 | I42: =+G42+(H42*$I$3) -> 34953.434
A43: 01.03.01.08 | B43: SALIDA DE FUERZA PARA LAVADORA Y SECADORA (T-LAV) | C43: pto | D43: 5 | E43: 114.52 | F43: 25.16 | G43: =+E43*D43 -> 572.6 | H43: =+F43*D43 -> 125.8 | I43: =+G43+(H43*$I$3) -> 994.03
A44: 01.03.01.09 | B44: SALIDA PARA CALENTARO DE ACEITE | C44: pto | D44: 1 | E44: 58.89 | F44: 17.97 | G44: =+E44*D44 -> 58.89 | H44: =+F44*D44 -> 17.97 | I44: =+G44+(H44*$I$3) -> 119.0895
A45: 01.03.01.10 | B45: SALIDA PARA MODULO DE CONTROL G.E | C45: pto | D45: 1 | E45: 58.89 | F45: 17.97 | G45: =+E45*D45 -> 58.89 | H45: =+F45*D45 -> 17.97 | I45: =+G45+(H45*$I$3) -> 119.0895
A46: 01.03.01.11 | B46: SALIDA PARA CARGADOR DE BATERIAS | C46: pto | D46: 1 | E46: 58.89 | F46: 17.97 | G46: =+E46*D46 -> 58.89 | H46: =+F46*D46 -> 17.97 | I46: =+G46+(H46*$I$3) -> 119.0895
A47: 01.03.01.12 | B47: SALIDA DE FUERZA PARA BOMBAS DE AGUA | C47: pto | D47: 8 | E47: 114.52 | F47: 68.31 | G47: =+E47*D47 -> 916.16 | H47: =+F47*D47 -> 546.48 | I47: =+G47+(H47*$I$3) -> 2746.868
A48: 01.03.01.13 | B48: SALIDA DE FUERZA PARA BOMBA JOCKEY | C48: pto | D48: 1 | E48: 58.89 | F48: 27.81 | G48: =+E48*D48 -> 58.89 | H48: =+F48*D48 -> 27.81 | I48: =+G48+(H48*$I$3) -> 152.0535
... A65: 01.03.01.30 | B65: SALIDA DE FUERZA PARA ELECTROBOMBA PISCINA | C65: pto | D65: 1 | E65: 58.89 | F65: 17.04 | G65: =+E65*D65 -> 58.89 | H65: =+F65*D65 -> 17.04 | I65: =+G65+(H65*$I$3) -> 115.974
A66: 01.04 | B66: SUMINISTRO E INSTALACION DE ALIMENTADORES ELECTRICOS | G66: =+E66*D66 -> 0 | H66: =+F66*D66 -> 0 | I66: =+G66+(H66*$I$3) -> 0
A67: 01.04.01 | B67: ALIMENTADORES EN AREAS COMUNES | G67: =+E67*D67 -> 0 | H67: =+F67*D67 -> 0 | I67: =+G67+(H67*$I$3) -> 0
A68: 01.04.01.01 | B68: LSOHX 3(3-1x300mm2) + LSOH 1Tx95mm2 | C68: m | D68: 35 | E68: 113.32 | F68: 469.78 | G68: =+E68*D68 -> 3966.2 | H68: =+F68*D68 -> 16442.3 | I68: =+G68+(H68*$I$3) -> 59047.905
A69: 01.04.01.02 | B69: LSOHX 3-1x240mm2 + LSOH 1Tx35mm2 | C69: m | D69: 124 | E69: 113.32 | F69: 125.63 | G69: =+E69*D69 -> 14051.68 | H69: =+F69*D69 -> 15578.12 | I69: =+G69+(H69*$I$3) -> 66238.382
A70: 01.04.01.03 | B70: LSOHX 3-1x150mm2 + LSOH 1Tx25mm2 | C70: m | D70: 63 | E70: 94.58 | F70: 84.74 | G70: =+E70*D70 -> 5958.54 | H70: =+F70*D70 -> 5338.62 | I70: =+G70+(H70*$I$3) -> 23842.917
A71: 01.04.01.04 | B71: LSOHX 3-1x150mm2 + LSOH 1Tx16mm2 | C71: m | D71: 118 | E71: 94.58 | F71: 83.28 | G71: =+E71*D71 -> 11160.44 | H71: =+F71*D71 -> 9827.04 | I71: =+G71+(H71*$I$3) -> 44081.024
A72: 01.04.01.05 | B72: LSOHX 3-1x185mm2 + LSOH 1Tx16mm2 | C72: m | D72: 0 | E72: 113.32 | F72: 94.4 | G72: =+E72*D72 -> 0 | H72: =+F72*D72 -> 0 | I72: =+G72+(H72*$I$3) -> 0
A73: 01.04.01.06 | B73: LSOHX(90°C) 3-1x95mm2 + LSOH(80°C) 1Tx25mm2 | C73: m | D73: 10 | E73: 80.36 | F73: 49.18 | G73: =+E73*D73 -> 803.6 | H73: =+F73*D73 -> 491.8 | I73: =+G73+(H73*$I$3) -> 2451.13
A74: 01.04.01.07 | B74: LSOHX 3-1x70mm2 + LSOH 1Tx16mm2 | C74: m | D74: 12 | E74: 74.25 | F74: 35.56 | G74: =+E74*D74 -> 891 | H74: =+F74*D74 -> 426.72 | I74: =+G74+(H74*$I$3) -> 2320.512
A75: 01.04.01.08 | B75: LSOHX 3-1x70mm2 + LSOH 1Tx10mm2 | C75: m | D75: 122 | E75: 74.25 | F75: 34.65 | G75: =+E75*D75 -> 9058.5 | H75: =+F75*D75 -> 4227.3 | I75: =+G75+(H75*$I$3) -> 23219.955
A76: 01.04.01.09 | B76: LSOHX 3-1x50mm2 + LSOH 1Tx10mm2 | C76: m | D76: 373 | E76: 74.25 | F76: 25.14 | G76: =+E76*D76 -> 27695.25 | H76: =+F76*D76 -> 9377.22 | I76: =+G76+(H76*$I$3) -> 59108.937
A77: 01.04.01.10 | B77: LSOHX 3-1x50mm2 + LSOH 1Tx6mm2 | C77: m | D77: 135 | E77: 74.25 | F77: 24.45 | G77: =+E77*D77 -> 10023.75 | H77: =+F77*D77 -> 3300.75 | I77: =+G77+(H77*$I$3) -> 21081.263
A78: 01.04.01.11 | B78: LSOHX 3-1x35mm2 + LSOH 1Tx10mm2 | C78: m | D78: 89 | E78: 53.09 | F78: 19.72 | G78: =+E78*D78 -> 4725.01 | H78: =+F78*D78 -> 1755.08 | I78: =+G78+(H78*$I$3) -> 10604.528
A79: 01.04.01.12 | B79: LSOHX 3-1x25mm2 + LSOH 1Tx10mm2 | C79: m | D79: 411 | E79: 25.39 | F79: 14.33 | G79: =+E79*D79 -> 10435.29 | H79: =+F79*D79 -> 5889.63 | I79: =+G79+(H79*$I$3) -> 30165.551
... A89: 01.04.01.22 | B89: LS0HX 3-1x4mm2 + LS0HX 1Tx4mm2 | C89: m | D89: 107.4 | E89: 16.22 | F89: 3.24 | G89: =+E89*D89 -> 1742.028 | H89: =+F89*D89 -> 347.976 | I89: =+G89+(H89*$I$3) -> 2907.7476
A90: 01.04.02 | B90: ALIMENTADORES PARA DEPARTAMENTOS | G90: =+E90*D90 -> 0 | H90: =+F90*D90 -> 0 | I90: =+G90+(H90*$I$3) -> 0
A91: 01.04.02.01 | B91: 2-1x16mm2 LSOHX + 1Tx10mm2 LSOH | C91: m | D91: 12482.85 | E91: 9.74 | F91: 7.17 | G91: =+E91*D91 -> 121582.96 | H91: =+F91*D91 -> 89502.035 | I91: =+G91+(H91*$I$3) -> 421414.77
A92: 01.04.02.02 | B92: 2-1x25mm2 LSOHX + 1Tx10mm2 LSOH | C92: m | D92: 18911.5 | E92: 9.74 | F92: 10.11 | G92: =+E92*D92 -> 184198.01 | H92: =+F92*D92 -> 191195.26 | I92: =+G92+(H92*$I$3) -> 824702.15
A93: 01.04.03 | B93: CANALIZACION DE FUERZA Y ALIMENTADORES | G93: =+E93*D93 -> 0 | H93: =+F93*D93 -> 0 | I93: =+G93+(H93*$I$3) -> 0
A94: 01.04.03.01 | B94: TUBERIA ELECTRICA Ø35mm EMT | C94: m | D94: 1750 | E94: 45.89 | F94: 0 | G94: =+E94*D94 -> 80307.5 | H94: =+F94*D94 -> 0 | I94: =+G94+(H94*$I$3) -> 80307.5
A95: 01.04.03.02 | B95: TUBERIA ELECTRICA Ø40mm EMT | C95: m | D95: 76 | E95: 61.71 | F95: 0 | G95: =+E95*D95 -> 4689.96 | H95: =+F95*D95 -> 0 | I95: =+G95+(H95*$I$3) -> 4689.96
A96: 01.04.03.03 | B96: TUBERIA ELECTRICA Ø50mm EMT | C96: m | D96: 80 | E96: 79.69 | F96: 0 | G96: =+E96*D96 -> 6375.2 | H96: =+F96*D96 -> 0 | I96: =+G96+(H96*$I$3) -> 6375.2
A97: 01.04.03.04 | B97: TUBERIA ELECTRICA Ø100mm EMT | C97: m | D97: 53 | E97: 185.1 | F97: 0 | G97: =+E97*D97 -> 9810.3 | H97: =+F97*D97 -> 0 | I97: =+G97+(H97*$I$3) -> 9810.3
A98: 01.04.03.05 | B98: TUBERIA PVC-SAP ELECTRICA DE 25 mm | C98: m | D98: 252 | E98: 13.89 | F98: 0 | G98: =+E98*D98 -> 3500.28 | H98: =+F98*D98 -> 0 | I98: =+G98+(H98*$I$3) -> 3500.28
A99: 01.04.03.06 | B99: TUBERIA PVC-SAP ELECTRICA DE 35 mm | C99: m | D99: 5845 | E99: 14.37 | F99: 0 | G99: =+E99*D99 -> 83992.65 | H99: =+F99*D99 -> 0 | I99: =+G99+(H99*$I$3) -> 83992.65
A100: 01.04.03.07 | B100: TUBERIA PVC-SAP ELECTRICA DE 40 mm | C100: m | D100: 50 | E100: 23.74 | F100: 0 | G100: =+E100*D100 -> 1187 | H100: =+F100*D100 -> 0 | I100: =+G100+(H100*$I$3) -> 1187
A101: 01.04.03.08 | B101: TUBERIA PVC-SAP ELECTRICA DE 65 mm | C101: m | D101: 115 | E101: 34.88 | F101: 0 | G101: =+E101*D101 -> 4011.2 | H101: =+F101*D101 -> 0 | I101: =+G101+(H101*$I$3) -> 4011.2
A102: 01.04.03.09 | B102: TUBERIA PVC-SAP ELECTRICA DE 100 mm | C102: m | D102: 160 | E102: 59.4 | F102: 0 | G102: =+E102*D102 -> 9504 | H102: =+F102*D102 -> 0 | I102: =+G102+(H102*$I$3) -> 9504
A103: 01.04.04 | B103: CAJAS DE PASE | G103: =+E103*D103 -> 0 | H103: =+F103*D103 -> 0 | I103: =+G103+(H103*$I$3) -> 0
A104: 01.04.04.01 | B104: CAJA DE PASE OCTOGONAL | C104: und | D104: 85 | E104: 25.64 | F104: 0 | G104: =+E104*D104 -> 2179.4 | H104: =+F104*D104 -> 0 | I104: =+G104+(H104*$I$3) -> 2179.4
A105: 01.04.04.02 | B105: CAJA DE PASE 100X100X55mm | C105: und | D105: 52 | E105: 25.52 | F105: 0 | G105: =+E105*D105 -> 1327.04 | H105: =+F105*D105 -> 0 | I105: =+G105+(H105*$I$3) -> 1327.04
A106: 01.04.04.03 | B106: CAJA DE PASE 150X150X100mm | C106: und | D106: 36 | E106: 37.11 | F106: 0 | G106: =+E106*D106 -> 1335.96 | H106: =+F106*D106 -> 0 | I106: =+G106+(H106*$I$3) -> 1335.96
A107: 01.04.04.04 | B107: CAJA DE PASE 250X150X100mm | C107: und | D107: 15 | E107: 81.95 | F107: 0 | G107: =+E107*D107 -> 1229.25 | H107: =+F107*D107 -> 0 | I107: =+G107+(H107*$I$3) -> 1229.25
A108: 01.04.04.05 | B108: CAJA DE PASE 1100X700X150MM | C108: und | D108: 36 | E108: 1005.22 | F108: 0 | G108: =+E108*D108 -> 36187.92 | H108: =+F108*D108 -> 0 | I108: =+G108+(H108*$I$3) -> 36187.92
A109: 01.05 | B109: BANDEJAS ELECTRICAS Y DE COMUNICACIONES | G109: =+E109*D109 -> 0 | H109: =+F109*D109 -> 0 | I109: =+G109+(H109*$I$3) -> 0
A110: 01.05.01 | B110: BANDEJA PORTACABLE TIPO RANURADA DE 300X100X2400MM | C110: m | D110: 207 | E110: 132.46 | F110: 0 | G110: =+E110*D110 -> 27419.22 | H110: =+F110*D110 -> 0 | I110: =+G110+(H110*$I$3) -> 27419.22
A111: 01.05.02 | B111: BANDEJA PORTACABLE TIPO RANURADA DE 400X100X2400MM | C111: m | D111: 71 | E111: 159.28 | F111: 0 | G111: =+E111*D111 -> 11308.88 | H111: =+F111*D111 -> 0 | I111: =+G111+(H111*$I$3) -> 11308.88
A112: 01.05.03 | B112: BANDEJA PORTACABLE TIPO RANURADA DE 550X100X2400MM | C112: m | D112: 98 | E112: 178.42 | F112: 0 | G112: =+E112*D112 -> 17485.16 | H112: =+F112*D112 -> 0 | I112: =+G112+(H112*$I$3) -> 17485.16
A113: 01.05.04 | B113: BANDEJA PORTACABLE TIPO RANURADA DE 750X100X2400MM | C113: m | D113: 101 | E113: 203.99 | F113: 0 | G113: =+E113*D113 -> 20602.99 | H113: =+F113*D113 -> 0 | I113: =+G113+(H113*$I$3) -> 20602.99
A114: 01.05.05 | B114: BANDEJA PORTACABLE TIPO RANURADA DE 1000X100X2400MM | C114: m | D114: 187 | E114: 235.89 | F114: 0 | G114: =+E114*D114 -> 44111.43 | H114: =+F114*D114 -> 0 | I114: =+G114+(H114*$I$3) -> 44111.43
A115: 01.05.06 | B115: ATERRAMIENTO DE BANDEJA CON CABLE DESNUDO 1x35mm² | C115: m | D115: 664 | E115: 11.77 | F115: 4.42 | G115: =+E115*D115 -> 7815.28 | H115: =+F115*D115 -> 2934.88 | I115: =+G115+(H115*$I$3) -> 17647.128
A116: 01.05.07 | B116: SALIDA PARA CONEXION A BANDEJA | C116: und | D116: 81 | E116: 49.91 | F116: 0 | G116: =+E116*D116 -> 4042.71 | H116: =+F116*D116 -> 0 | I116: =+G116+(H116*$I$3) -> 4042.71
A117: 01.06 | B117: ACCESORIOS ELECTRICOS/INSTALACION DE LUMINARIAS | G117: =+E117*D117 -> 0 | H117: =+F117*D117 -> 0 | I117: =+G117+(H117*$I$3) -> 0
A118: 01.06.01 | B118: SUMINISTRO E INSTALACION DE PLACA INTERRUPTOR SIMPLE | C118: und | D118: 1718 | E118: 10.63 | F118: 0 | G118: =+E118*D118 -> 18262.34 | H118: =+F118*D118 -> 0 | I118: =+G118+(H118*$I$3) -> 18262.34
A119: 01.06.02 | B119: SUMINISTRO E INSTALACION DE PLACA INTERRUPTOR DOBLE | C119: und | D119: 492 | E119: 12.3 | F119: 0 | G119: =+E119*D119 -> 6051.6 | H119: =+F119*D119 -> 0 | I119: =+G119+(H119*$I$3) -> 6051.6
A120: 01.06.03 | B120: SUMINISTRO E INSTALACION DE PLACA INTERRUPTOR 3 VIAS SIMPLE | C120: und | D120: 1718 | E120: 11.36 | F120: 0 | G120: =+E120*D120 -> 19516.48 | H120: =+F120*D120 -> 0 | I120: =+G120+(H120*$I$3) -> 19516.48
A121: 01.06.04 | B121: SUMINISTRO E INSTALACION DE PLACA INTERRUPTOR 3 VIAS +INT SIMPLE | C121: und | D121: 492 | E121: 14.08 | F121: 0 | G121: =+E121*D121 -> 6927.36 | H121: =+F121*D121 -> 0 | I121: =+G121+(H121*$I$3) -> 6927.36
A122: 01.06.05 | B122: SUMINISTRO E INSTALACION DE PLACA TOMACORRIENTE | C122: und | D122: 4928 | E122: 15.35 | F122: 0 | G122: =+E122*D122 -> 75644.8 | H122: =+F122*D122 -> 0 | I122: =+G122+(H122*$I$3) -> 75644.8
A123: 01.06.06 | B123: SUMINISTRO E INSTALACION DE PLACA TOMACORRIENTE P.A | C123: und | D123: 109 | E123: 49.81 | F123: 0 | G123: =+E123*D123 -> 5429.29 | H123: =+F123*D123 -> 0 | I123: =+G123+(H123*$I$3) -> 5429.29
A124: 01.06.07 | B124: SUMINISTRO E INSTALACION DE PLACA TOMACORRIENTE SCHUCKO | C124: und | D124: 668 | E124: 18.11 | F124: 0 | G124: =+E124*D124 -> 12097.48 | H124: =+F124*D124 -> 0 | I124: =+G124+(H124*$I$3) -> 12097.48
A125: 01.06.08 | B125: SUMINISTRO E INSTALACION DE PLACA PARA CAMPANA (SOLO TAPA CIEGA) | C125: und | D125: 334 | E125: 8.64 | F125: 0 | G125: =+E125*D125 -> 2885.76 | H125: =+F125*D125 -> 0 | I125: =+G125+(H125*$I$3) -> 2885.76
A126: 01.06.09 | B126: SUMINISTRO E INSTALACION DE TIMBRE | C126: und | D126: 334 | E126: 19.01 | F126: 0 | G126: =+E126*D126 -> 6349.34 | H126: =+F126*D126 -> 0 | I126: =+G126+(H126*$I$3) -> 6349.34
...

Sheet IISS
A2: INSTALACIONES SANITARIAS
H3: T.C | I3: 3.35
A4: Presupuesto | B4: GERMANIA
A5: Subpresupuesto | B5: INSTALACIONES SANITARIAS
A6: Cliente | B6: : V&V Bravo S.A.C | F6: Costo al | G6: 46133
A7: Lugar
A8: ITEM | B8: DESCRIPCION | C8: UND | D8: CANTIDAD | E8: P.U (S/.) | F8: P.U ($.) | G8: PARCIAL (S/.) | H8: PARCIAL ($) | I8: TOTAL
A9: 01 | B9: INSTALACIONES SANITARIAS | G9: =SUM(G10:G150) -> 2015202.8 | H9: =SUM(H10:H149) -> 54479.171 | I9: =SUM(I10:I150) -> 2197708
A10: 01.01 | B10: SISTEMA DE AGUA FRÍA
A11: 01.01.01 | B11: SALIDAS DE AGUA FRIA (EN POLIPROPILENO)
A12: 01.01.01.01 | B12: SALIDA AGUA FRIA PPR 20mm (Ø1/2") | C12: pto | D12: 2695 | E12: 60.94 | F12: 0 | G12: =+E12*D12 -> 164233.3 | H12: =+F12*D12 -> 0 | I12: =+G12+(H12*$I$3) -> 164233.3
A13: 01.01.01.02 | B13: SALIDA AGUA FRIA PPR 25mm(3/4") | C13: pto | D13: 337 | E13: 63.89 | F13: 0 | G13: =+E13*D13 -> 21530.93 | H13: =+F13*D13 -> 0 | I13: =+G13+(H13*$I$3) -> 21530.93
A14: 01.01.01.03 | B14: SALIDA AGUA FRIA PPR 32mm(1") | C14: pto | D14: 8 | E14: 78.94 | F14: 0 | G14: =+E14*D14 -> 631.52 | H14: =+F14*D14 -> 0 | I14: =+G14+(H14*$I$3) -> 631.52
A15: 01.01.01.04 | B15: SALIDA AGUA FRIA PPR 40mm(1.1/4") | C15: pto | D15: 0 | E15: 99.49 | F15: 0 | G15: =+E15*D15 -> 0 | H15: =+F15*D15 -> 0 | I15: =+G15+(H15*$I$3) -> 0
A16: 01.01.02 | B16: REDES DE DISTRIBUCION DE AGUA (EN POLIPROPILENO) | G16: =+E16*D16 -> 0 | H16: =+F16*D16 -> 0 | I16: =+G16+(H16*$I$3) -> 0
A17: 01.01.02.01 | B17: TUBERIA PPR PN-10 EMPOTRADA DE 1/2" | C17: m | D17: 2638.77 | E17: 17.24 | F17: 0 | G17: =+E17*D17 -> 45492.395 | H17: =+F17*D17 -> 0 | I17: =+G17+(H17*$I$3) -> 45492.395
A18: 01.01.02.02 | B18: TUBERIA PPR PN-10 EMPOTRADA DE 3/4" | C18: m | D18: 10349.78 | E18: 20.66 | F18: 0 | G18: =+E18*D18 -> 213826.45 | H18: =+F18*D18 -> 0 | I18: =+G18+(H18*$I$3) -> 213826.45
A19: 01.01.02.03 | B19: TUBERIA PPR PN-10 EMPOTRADA DE 1" | C19: m | D19: 60.44 | E19: 26.67 | F19: 0 | G19: =+E19*D19 -> 1611.9348 | H19: =+F19*D19 -> 0 | I19: =+G19+(H19*$I$3) -> 1611.9348
A20: 01.01.02.04 | B20: TUBERIA PPR PN-10 EMPOTRADA DE 1.1/4" | C20: m | D20: 41.13 | E20: 30.71 | F20: 0 | G20: =+E20*D20 -> 1263.1023 | H20: =+F20*D20 -> 0 | I20: =+G20+(H20*$I$3) -> 1263.1023
A21: 01.01.02.05 | B21: TUBERIA PPR PN-10 EMPOTRADA DE 1.1/2" | C21: m | D21: 59.06 | E21: 42.04 | F21: 0 | G21: =+E21*D21 -> 2482.8824 | H21: =+F21*D21 -> 0 | I21: =+G21+(H21*$I$3) -> 2482.8824
A22: 01.01.02.06 | B22: TUBERIA PPR PN-10 EMPOTRADA DE 3" | C22: m | D22: 0 | E22: 90.12 | F22: 0 | G22: =+E22*D22 -> 0 | H22: =+F22*D22 -> 0 | I22: =+G22+(H22*$I$3) -> 0
A23: 01.01.02.07 | B23: TUBERIA PPR PN-10 COLGADA DE 1/2" | C23: m | D23: 66.14 | E23: 26.85 | F23: 0 | G23: =+E23*D23 -> 1775.859 | H23: =+F23*D23 -> 0 | I23: =+G23+(H23*$I$3) -> 1775.859
A24: 01.01.02.08 | B24: TUBERIA PPR PN-10 COLGADA DE 3/4" | C24: m | D24: 59.95 | E24: 29.55 | F24: 0 | G24: =+E24*D24 -> 1771.5225 | H24: =+F24*D24 -> 0 | I24: =+G24+(H24*$I$3) -> 1771.5225
A25: 01.01.02.09 | B25: TUBERIA PPR PN-10 COLGADA DE 1" | C25: m | D25: 69.28 | E25: 36.83 | F25: 0 | G25: =+E25*D25 -> 2551.5824 | H25: =+F25*D25 -> 0 | I25: =+G25+(H25*$I$3) -> 2551.5824
A26: 01.01.02.10 | B26: TUBERIA PPR PN-10 COLGADA DE 1.1/4" | C26: m | D26: 0 | E26: 48.84 | F26: 0 | G26: =+E26*D26 -> 0 | H26: =+F26*D26 -> 0 | I26: =+G26+(H26*$I$3) -> 0
A27: 01.01.02.11 | B27: TUBERIA PPR PN-10 COLGADA DE 1.1/2" | C27: m | D27: 24 | E27: 57.61 | F27: 0 | G27: =+E27*D27 -> 1382.64 | H27: =+F27*D27 -> 0 | I27: =+G27+(H27*$I$3) -> 1382.64
A28: 01.01.02.12 | B28: TUBERIA PPR PN-10 COLGADA DE 2" | C28: m | D28: 64.7 | E28: 69.69 | F28: 0 | G28: =+E28*D28 -> 4508.943 | H28: =+F28*D28 -> 0 | I28: =+G28+(H28*$I$3) -> 4508.943
... A31: 01.01.02.15 | B31: TUBERIA PPR PN-10 COLGADA DE 4" | C31: m | D31: 58.86 | E31: 169.94 | F31: 0 | G31: =+E31*D31 -> 10002.668 | H31: =+F31*D31 -> 0 | I31: =+G31+(H31*$I$3) -> 10002.668
A32: 01.01.03 | B32: MONTANTE DE AGUA FRIA (EN POLIPROPILENO) | G32: =+E32*D32 -> 0 | H32: =+F32*D32 -> 0 | I32: =+G32+(H32*$I$3) -> 0
A33: 01.01.03.01 | B33: TUBERIA PPR PN-10 ADOSADA DE 3/4" | C33: m | D33: 0 | E33: 29.55 | F33: 0 | G33: =+E33*D33 -> 0 | H33: =+F33*D33 -> 0 | I33: =+G33+(H33*$I$3) -> 0
A34: 01.01.03.02 | B34: TUBERIA PPR PN-10 ADOSADA DE 1" | C34: m | D34: 0 | E34: 36.83 | F34: 0 | G34: =+E34*D34 -> 0 | H34: =+F34*D34 -> 0 | I34: =+G34+(H34*$I$3) -> 0
A35: 01.01.03.03 | B35: TUBERIA PPR PN-10 ADOSADA DE 1.1/4" | C35: m | D35: 0 | E35: 48.84 | F35: 0 | G35: =+E35*D35 -> 0 | H35: =+F35*D35 -> 0 | I35: =+G35+(H35*$I$3) -> 0
A36: 01.01.03.04 | B36: TUBERIA PPR PN-10 ADOSADA DE 2" | C36: m | D36: 36 | E36: 69.69 | F36: 0 | G36: =+E36*D36 -> 2508.84 | H36: =+F36*D36 -> 0 | I36: =+G36+(H36*$I$3) -> 2508.84
A37: 01.01.03.05 | B37: TUBERIA PPR PN-10 ADOSADA DE 2.1/2" | C37: m | D37: 42 | E37: 91.35 | F37: 0 | G37: =+E37*D37 -> 3836.7 | H37: =+F37*D37 -> 0 | I37: =+G37+(H37*$I$3) -> 3836.7
A38: 01.01.03.06 | B38: TUBERIA PPR PN-10 ADOSADA DE 3" | C38: m | D38: 36 | E38: 113.23 | F38: 0 | G38: =+E38*D38 -> 4076.28 | H38: =+F38*D38 -> 0 | I38: =+G38+(H38*$I$3) -> 4076.28
A39: 01.01.03.07 | B39: TUBERIA PPR PN-10 ADOSADA DE 4" | C39: m | D39: 228 | E39: 174.77 | F39: 0 | G39: =+E39*D39 -> 39847.56 | H39: =+F39*D39 -> 0 | I39: =+G39+(H39*$I$3) -> 39847.56
A40: 01.01.04 | B40: LLAVES Y VALVULAS - RED DE DESTRIBUCION (SIST. POLIPROPILENO) | G40: =+E40*D40 -> 0 | H40: =+F40*D40 -> 0 | I40: =+G40+(H40*$I$3) -> 0
A41: 01.01.04.01 | B41: LLAVE DE PASO SIST. POLIPROPILENO 20mm (1/2") | C41: und | D41: 370 | E41: 80.68 | F41: 0 | G41: =+E41*D41 -> 29851.6 | H41: =+F41*D41 -> 0 | I41: =+G41+(H41*$I$3) -> 29851.6
A42: 01.01.04.02 | B42: LLAVE DE PASO SIST. POLIPROPILENO 25mm (3/4") | C42: und | D42: 1607 | E42: 98.59 | F42: 0 | G42: =+E42*D42 -> 158434.13 | H42: =+F42*D42 -> 0 | I42: =+G42+(H42*$I$3) -> 158434.13
A43: 01.01.04.03 | B43: LLAVE DE PASO SIST. POLIPROPILENO 32mm (1") | C43: und | D43: 7 | E43: 113.03 | F43: 0 | G43: =+E43*D43 -> 791.21 | H43: =+F43*D43 -> 0 | I43: =+G43+(H43*$I$3) -> 791.21
A44: 01.01.04.04 | B44: LLAVE DE PASO SIST. POLIPROPILENO 40mm (1.1/4") | C44: und | D44: 1 | E44: 224.66 | F44: 0 | G44: =+E44*D44 -> 224.66 | H44: =+F44*D44 -> 0 | I44: =+G44+(H44*$I$3) -> 224.66
A45: 01.01.04.05 | B45: LLAVE DE PASO SIST. POLIPROPILENO (2") | C45: und | D45: 52 | E45: 386.28 | F45: 0 | G45: =+E45*D45 -> 20086.56 | H45: =+F45*D45 -> 0 | I45: =+G45+(H45*$I$3) -> 20086.56
A46: 01.01.05 | B46: PRUEBAS HIDRAULICAS | G46: =+E46*D46 -> 0 | H46: =+F46*D46 -> 0 | I46: =+G46+(H46*$I$3) -> 0
A47: 01.01.05.01 | B47: PRUEBA HIDRAULICA PARA AGUA FRIA | C47: glb | D47: 1 | E47: 12070.25 | F47: 0 | G47: =+E47*D47 -> 12070.25 | H47: =+F47*D47 -> 0 | I47: =+G47+(H47*$I$3) -> 12070.25
A48: 01.01.05.02 | B48: LIMPIEZA Y DESINFECCION DE TUBERIAS AGUA FRIA | C48: glb | D48: 1 | E48: 7680 | F48: 0 | G48: =+E48*D48 -> 7680 | H48: =+F48*D48 -> 0 | I48: =+G48+(H48*$I$3) -> 7680
A49: 01.01.05.03 | B49: LIMPIEZA Y DESINFECCION DE CISTERNAS | C49: glb | D49: 1 | E49: 2850 | F49: 0 | G49: =+E49*D49 -> 2850 | H49: =+F49*D49 -> 0 | I49: =+G49+(H49*$I$3) -> 2850
A50: 01.01.06 | B50: VARIOS | G50: =+E50*D50 -> 0 | H50: =+F50*D50 -> 0 | I50: =+G50+(H50*$I$3) -> 0
A51: 01.01.06.01 | B51: MEDIDOR DE AGUA DE 3/4" (INC. BATERIA) | C51: und | D51: 334 | E51: 387.4 | F51: 0 | G51: =+E51*D51 -> 129391.6 | H51: =+F51*D51 -> 0 | I51: =+G51+(H51*$I$3) -> 129391.6
A52: 01.01.06.02 | B52: MEDIDOR DE AGUA DE 1.1/2" (INC. BATERIA) | C52: und | D52: 1 | E52: 509.94 | F52: 0 | G52: =+E52*D52 -> 509.94 | H52: =+F52*D52 -> 0 | I52: =+G52+(H52*$I$3) -> 509.94
A53: 01.01.06.03 | B53: MEDIDOR DE AGUA DE 2" (INC. BATERIA) | C53: und | D53: 0 | E53: 427.65 | F53: 0 | G53: =+E53*D53 -> 0 | H53: =+F53*D53 -> 0 | I53: =+G53+(H53*$I$3) -> 0
A54: 01.01.06.04 | B54: ESTACIONES REDUCTORAS DE PRESION 4" | C54: und | D54: 1 | E54: 12114.58 | F54: 0 | G54: =+E54*D54 -> 12114.58 | H54: =+F54*D54 -> 0 | I54: =+G54+(H54*$I$3) -> 12114.58
A55: 01.01.06.05 | B55: ESTACIONES REDUCTORAS DE PRESION 3/4" | C55: und | D55: 1 | E55: 3256.55 | F55: 0 | G55: =+E55*D55 -> 3256.55 | H55: =+F55*D55 -> 0 | I55: =+G55+(H55*$I$3) -> 3256.55
A56: 01.01.06.06 | B56: GRIFO DE RIEGO Ø1/2" | C56: und | D56: 14 | E56: 85.24 | F56: 0 | G56: =+E56*D56 -> 1193.36 | H56: =+F56*D56 -> 0 | I56: =+G56+(H56*$I$3) -> 1193.36
A57: 01.01.07 | B57: CUARTO DE BOMBAS | G57: =+E57*D57 -> 0 | H57: =+F57*D57 -> 0 | I57: =+G57+(H57*$I$3) -> 0
A58: 01.01.07.01 | B58: BRIDA ROMPEAGUA 3" | C58: und | D58: 0 | E58: 962.63 | F58: 0 | G58: =+E58*D58 -> 0 | H58: =+F58*D58 -> 0 | I58: =+G58+(H58*$I$3) -> 0
A59: 01.01.07.02 | B59: BRIDA ROMPEAGUA 4" | C59: und | D59: 0 | E59: 1347.08 | F59: 0 | G59: =+E59*D59 -> 0 | H59: =+F59*D59 -> 0 | I59: =+G59+(H59*$I$3) -> 0
A60: 01.01.07.03 | B60: BRIDA ROMPEAGUA 6" | C60: und | D60: 7 | E60: 1760.54 | F60: 0 | G60: =+E60*D60 -> 12323.78 | H60: =+F60*D60 -> 0 | I60: =+G60+(H60*$I$3) -> 12323.78
A61: 01.01.07.04 | B61: BRIDA ROMPEAGUA 8" | C61: und | D61: 0 | E61: 3024.66 | F61: 0 | G61: =+E61*D61 -> 0 | H61: =+F61*D61 -> 0 | I61: =+G61+(H61*$I$3) -> 0
A62: 01.01.07.05 | B62: VALVULA FLOTADORA DE 1.1/2" | C62: und | D62: 3 | E62: 659.47 | F62: 0 | G62: =+E62*D62 -> 1978.41 | H62: =+F62*D62 -> 0 | I62: =+G62+(H62*$I$3) -> 1978.41
A63: 01.01.07.06 | B63: VALVULA COMPUERTADE 1.1/2" | C63: und | D63: 3 | E63: 462.33 | F63: 0 | G63: =+E63*D63 -> 1386.99 | H63: =+F63*D63 -> 0 | I63: =+G63+(H63*$I$3) -> 1386.99
A64: 01.02 | B64: SISTEMA DE AGUA CALIENTE | G64: =+E64*D64 -> 0 | H64: =+F64*D64 -> 0 | I64: =+G64+(H64*$I$3) -> 0
A65: 01.02.01 | B65: SALIDAS DE AGUA CALIENTE (EN POLIPROPILENO) | G65: =+E65*D65 -> 0 | H65: =+F65*D65 -> 0 | I65: =+G65+(H65*$I$3) -> 0
A66: 01.02.01.01 | B66: SALIDA AGUA CALIENTE PPR 20mm (Ø1/2") | C66: pto | D66: 1519 | E66: 60.43 | F66: 0 | G66: =+E66*D66 -> 91793.17 | H66: =+F66*D66 -> 0 | I66: =+G66+(H66*$I$3) -> 91793.17
A67: 01.02.01.02 | B67: SALIDA AGUA CALIENTE PPR 25mm (Ø3/4") | C67: pto | D67: 336 | E67: 66.67 | F67: 0 | G67: =+E67*D67 -> 22401.12 | H67: =+F67*D67 -> 0 | I67: =+G67+(H67*$I$3) -> 22401.12
A68: 01.02.02 | B68: REDES DE DISTRIBUCION DE AGUA CALIENTE (EN POLIPROPILENO) | G68: =+E68*D68 -> 0 | H68: =+F68*D68 -> 0 | I68: =+G68+(H68*$I$3) -> 0
A69: 01.02.02.01 | B69: TUBERIA PPR PN-16 EMPOTRADA DE 1/2" | C69: m | D69: 5190 | E69: 17.3 | F69: 0 | G69: =+E69*D69 -> 89787 | H69: =+F69*D69 -> 0 | I69: =+G69+(H69*$I$3) -> 89787
A70: 01.02.02.02 | B70: TUBERIA PPR PN-16 EMPOTRADA DE 3/4" | C70: m | D70: 745 | E70: 21.37 | F70: 0 | G70: =+E70*D70 -> 15920.65 | H70: =+F70*D70 -> 0 | I70: =+G70+(H70*$I$3) -> 15920.65
A71: 01.02.03 | B71: LLAVES Y VALVULAS - RED DE DESTRIBUCION (SIST. POLIPROPILENO) | G71: =+E71*D71 -> 0 | H71: =+F71*D71 -> 0 | I71: =+G71+(H71*$I$3) -> 0
A72: 01.02.03.01 | B72: LLAVE DE PASO SIST. POLIPROPILENO 20mm (1/2") | C72: und | D72: 929 | E72: 83.86 | F72: 0 | G72: =+E72*D72 -> 77905.94 | H72: =+F72*D72 -> 0 | I72: =+G72+(H72*$I$3) -> 77905.94
A73: 01.02.03.02 | B73: LLAVE DE PASO SIST. POLIPROPILENO 25mm (3/4") | C73: und | D73: 336 | E73: 105.72 | F73: 0 | G73: =+E73*D73 -> 35521.92 | H73: =+F73*D73 -> 0 | I73: =+G73+(H73*$I$3) -> 35521.92
A74: 01.02.04 | B74: PRUEBAS HIDRAULICAS | G74: =+E74*D74 -> 0 | H74: =+F74*D74 -> 0 | I74: =+G74+(H74*$I$3) -> 0
A75: 01.02.04.01 | B75: PRUEBA HIDRAULICA PARA AGUA CALIENTE Y DESINFECCION | C75: glb | D75: 1 | E75: 6445.37 | F75: 0 | G75: =+E75*D75 -> 6445.37 | H75: =+F75*D75 -> 0 | I75: =+G75+(H75*$I$3) -> 6445.37
A76: 01.03 | B76: SISTEMA DE DESAGUE | G76: =+E76*D76 -> 0 | H76: =+F76*D76 -> 0 | I76: =+G76+(H76*$I$3) -> 0
A77: 01.03.01 | B77: SALIDAS DE DRENAJE, DESAGUE Y VENTILACION | G77: =+E77*D77 -> 0 | H77: =+F77*D77 -> 0 | I77: =+G77+(H77*$I$3) -> 0
A78: 01.03.01.01 | B78: SALIDA DESAGUE DE PVC SAP 2" | C78: pto | D78: 1234 | E78: 53.35 | F78: 3.33 | G78: =+E78*D78 -> 65833.9 | H78: =+F78*D78 -> 4109.22 | I78: =+G78+(H78*$I$3) -> 79599.787
A79: 01.03.01.02 | B79: SALIDA DESAGUE DE PVC SAP 2" (SUMIDEROS Y REGISTROS) | C79: pto | D79: 2113 | E79: 39.07 | F79: 0.88 | G79: =+E79*D79 -> 82554.91 | H79: =+F79*D79 -> 1859.44 | I79: =+G79+(H79*$I$3) -> 88784.034
A80: 01.03.01.03 | B80: SALIDA DESAGUE DE PVC SAP 2" (LAVANDERÍA) | C80: pto | D80: 309 | E80: 39.07 | F80: 3 | G80: =+E80*D80 -> 12072.63 | H80: =+F80*D80 -> 927 | I80: =+G80+(H80*$I$3) -> 15178.08
A81: 01.03.01.04 | B81: SALIDA DESAGUE DE PVC SAP 3" (SUMIDEROS Y REGISTROS) | C81: pto | D81: 4 | E81: 56.85 | F81: 3.59 | G81: =+E81*D81 -> 227.4 | H81: =+F81*D81 -> 14.36 | I81: =+G81+(H81*$I$3) -> 275.506
A82: 01.03.01.05 | B82: SALIDA DESAGUE DE PVC SAP 4" | C82: pto | D82: 568 | E82: 61.75 | F82: 7.92 | G82: =+E82*D82 -> 35074 | H82: =+F82*D82 -> 4498.56 | I82: =+G82+(H82*$I$3) -> 50144.176
A83: 01.03.01.06 | B83: SALIDA DESAGUE DE PVC SAP 4" (SUMIDEROS Y REGISTROS) | C83: pto | D83: 161 | E83: 46.56 | F83: 2.79 | G83: =+E83*D83 -> 7496.16 | H83: =+F83*D83 -> 449.19 | I83: =+G83+(H83*$I$3) -> 9000.9465
A84: 01.03.01.07 | B84: SALIDA DESAGUE DE PVC SAP 6" (SUMIDEROS Y REGISTROS) | C84: pto | D84: 13 | E84: 46.71 | F84: 22 | G84: =+E84*D84 -> 607.23 | H84: =+F84*D84 -> 286 | I84: =+G84+(H84*$I$3) -> 1565.33
A85: 01.03.01.08 | B85: SALIDA VENTILACION DE PVC SAP 2" | C85: pto | D85: 711 | E85: 32.29 | F85: 3.33 | G85: =+E85*D85 -> 22958.19 | H85: =+F85*D85 -> 2367.63 | I85: =+G85+(H85*$I$3) -> 30889.75
A86: 01.03.02 | B86: REDES DE DESAGUE Y DRENAJE | G86: =+E86*D86 -> 0 | H86: =+F86*D86 -> 0 | I86: =+G86+(H86*$I$3) -> 0
A87: 01.03.02.01 | B87: TUBERIA PVC SAP EMPOTRADA DE 2" | C87: m | D87: 3295.23 | E87: 12.64 | F87: 2.05 | G87: =+E87*D87 -> 41651.707 | H87: =+F87*D87 -> 6755.2215 | I87: =+G87+(H87*$I$3) -> 64281.699
A88: 01.03.02.02 | B88: TUBERIA PVC SAP EMPOTRADA DE 3" | C88: m | D88: 7 | E88: 14.73 | F88: 3.29 | G88: =+E88*D88 -> 103.11 | H88: =+F88*D88 -> 23.03 | I88: =+G88+(H88*$I$3) -> 180.2605
