Workbook
Name \1: #REF!
Name \A: #REF!
Name \b: #N/A
Name \c: #N/A
Name \f: #N/A
Name \g: #REF!
Name \LL: #REF!
Name \O: #REF!
Name \p: #REF!
Name \PP: #N/A
Name \q: #REF!
Name \R: #REF!
Name \w: #REF!
Name \x: #REF!
Name _?쾴?: #REF!
Name _?쾴?_?: #REF!
Name _?쾴?___P: #REF!
Name _?쾴?_T: #REF!
Name __?쾴?: #REF!
Name __?쾴?_?: #REF!
Name __?쾴?___P: #REF!
Name __?쾴?_T: #REF!
Name ___?쾴?: #REF!
Name ___?쾴?_?: #REF!
Name ___?쾴?___P: #REF!
Name ___?쾴?_T: #REF!
Name ____?쾴?: #REF!
Name ____?쾴?_?: #REF!
Name ____?쾴?___P: #REF!
Name ____?쾴?_T: #REF!
Name _____?쾴?: #REF!
Name _____?쾴?_?: #REF!
Name _____?쾴?___P: #REF!
Name _____?쾴?_T: #REF!
Name ______?쾴?: #REF!
Name ______?쾴?_?: #REF!
Name ______?쾴?___P: #REF!
Name ______?쾴?_T: #REF!
Name _______?쾴?: #REF!
Name _______?쾴?_?: #REF!
Name _______?쾴?___P: #REF!
Name _______?쾴?_T: #REF!
Name ________?쾴?: #REF!
Name ________?쾴?_?: #REF!
Name ________?쾴?___P: #REF!
Name ________?쾴?_T: #REF!
Name _________?쾴?: #REF!
Name _________?쾴?_?: #REF!
Name _________?쾴?___P: #REF!
Name _________?쾴?_T: #REF!
Name ___________?쾴?: #REF!
Name ___________?쾴?_?: #REF!
Name ___________?쾴?___P: #REF!
Name ___________?쾴?_T: #REF!
Name ____________?쾴?: #REF!
Name ____________?쾴?_?: #REF!
Name ____________?쾴?___P: #REF!
Name ____________?쾴?_T: #REF!
Name ______________?쾴?: #REF!
Name ______________?쾴?_?: #REF!

Sheet OP
A2: OBRAS PROVISIONALES
A4: Presupuesto | B4: =#REF! -> #REF!
A5: Subpresupuesto | B5: =$A$2 -> OBRAS PROVISIONALES
A6: Cliente | B6: =#REF! -> #REF!
A7: Lugar | B7: =#REF! -> #REF!
A8: Fecha | B8: =#REF! -> #REF!
A12: ITEM | B12: DESCRIPCION | C12: UND | D12: CANTIDAD | E12: P.U. (PEN) | F12: P.U. (USD) | G12: P.U. (TOTAL) | H12: PRECIO PARCIAL (PEN) | I12: PRECIO PARCIAL (USD) | J12: PRECIO TOTAL (PEN) | K12: TOTAL
A13: 01 | B13: OBRAS PROVISIONALES, TRABAJOS PRELIMINARES
A14: =A13+0.01 -> 1.01 | B14: CONSTRUCCIONES PROVISIONALES | G14: =IFERROR(IF(D14=0,"",(E14+F14*TC)),"") | H14: =IFERROR(IF(D14=0,"",$D14*E14),"") | I14: =IFERROR(IF(D14=0,"",$D14*F14),"") | J14: =IFERROR(IF(D14<>0,(D14*G14)," "),0) | K14: =SUM(J15:J44) -> #REF!
A15: =GG!A13+0.0001 -> 12.0101 | B15: OFICINA DE OBRA PARA CONTRATISTA | C15: glb | D15: 1 | E15: 8315.79 | G15: =IFERROR(IF(D15=0,"",(E15+F15*TC)),"") | H15: =+ROUND(D15*E15,2) -> 8315.79 | I15: =+ROUND(D15*F15,2) -> 0 | J15: =+ROUND(H15+I15*TC,2) -> #REF!
A16: =A15+0.0001 -> 12.0102 | B16: OFICINA DE OBRA PARA SUPERVISIÓN | C16: glb | D16: 0 | G16: =IFERROR(IF(D16=0,"",(E16+F16*TC)),"") | H16: =+ROUND(D16*E16,2) -> 0 | I16: =+ROUND(D16*F16,2) -> 0 | J16: =+ROUND(H16+I16*TC,2) -> #REF!
A17: =A16+0.0001 -> 12.0103 | B17: OFICINA SALA DE REUNIONES | C17: glb | D17: 1 | E17: 3246.71 | G17: =IFERROR(IF(D17=0,"",(E17+F17*TC)),"") | H17: =+ROUND(D17*E17,2) -> 3246.71 | I17: =+ROUND(D17*F17,2) -> 0 | J17: =+ROUND(H17+I17*TC,2) -> #REF!
A18: =A17+0.0001 -> 12.0104 | B18: ALMACEN DE OBRA | C18: glb | D18: 1 | E18: 10690.24 | G18: =IFERROR(IF(D18=0,"",(E18+F18*TC)),"") | H18: =+ROUND(D18*E18,2) -> 10690.24 | I18: =+ROUND(D18*F18,2) -> 0 | J18: =+ROUND(H18+I18*TC,2) -> #REF!
A19: =A18+0.0001 -> 12.0105 | B19: COMEDOR PERSONAL OBRERO | C19: glb | D19: 1 | E19: 6229.18 | G19: =IFERROR(IF(D19=0,"",(E19+F19*TC)),"") | H19: =+ROUND(D19*E19,2) -> 6229.18 | I19: =+ROUND(D19*F19,2) -> 0 | J19: =+ROUND(H19+I19*TC,2) -> #REF!
A20: =A19+0.0001 -> 12.0106 | B20: VESTUARIO PARA OBREROS | C20: glb | D20: 1 | E20: 6906.27 | G20: =IFERROR(IF(D20=0,"",(E20+F20*TC)),"") | H20: =+ROUND(D20*E20,2) -> 6906.27 | I20: =+ROUND(D20*F20,2) -> 0 | J20: =+ROUND(H20+I20*TC,2) -> #REF!
A21: =A20+0.0001 -> 12.0107 | B21: TRASLADO DE CAMPAMENTO PROVISIONAL A SOTANOS | C21: und | D21: 1 | E21: 5282.76 | G21: =IFERROR(IF(D21=0,"",(E21+F21*TC)),"") | H21: =+ROUND(D21*E21,2) -> 5282.76 | I21: =+ROUND(D21*F21,2) -> 0 | J21: =+ROUND(H21+I21*TC,2) -> #REF!
A22: =A21+0.0001 -> 12.0108 | B22: CASETA PARA GUARDIANIA | C22: glb | D22: 1 | E22: 850 | G22: =IFERROR(IF(D22=0,"",(E22+F22*TC)),"") | H22: =+ROUND(D22*E22,2) -> 850 | I22: =+ROUND(D22*F22,2) -> 0 | J22: =+ROUND(H22+I22*TC,2) -> #REF!
A23: =A22+0.0001 -> 12.0109 | B23: BAÑOS PORTATILES DE OBRA PARA PERSONAL STAFF Y SUPERVISION COMPARTIDOS | C23: mes | D23: 10.5 | E23: 780 | G23: =IFERROR(IF(D23=0,"",(E23+F23*TC)),"") | H23: =+ROUND(D23*E23,2) -> 8190 | I23: =+ROUND(D23*F23,2) -> 0 | J23: =+ROUND(H23+I23*TC,2) -> #REF!
A24: =A23+0.0001 -> 12.011 | B24: CONSTRUCCION DE SSHH (1ER NIVEL) | C24: glb | D24: 1 | E24: 9936.3 | G24: =IFERROR(IF(D24=0,"",(E24+F24*TC)),"") | H24: =+ROUND(D24*E24,2) -> 9936.3 | I24: =+ROUND(D24*F24,2) -> 0 | J24: =+ROUND(H24+I24*TC,2) -> #REF!
A25: =A24+0.0001 -> 12.0111 | B25: SSHH PORTATILES PARA OBREROS | C25: glb | D25: 1 | E25: 7590 | G25: =IFERROR(IF(D25=0,"",(E25+F25*TC)),"") | H25: =+ROUND(D25*E25,2) -> 7590 | I25: =+ROUND(D25*F25,2) -> 0 | J25: =+ROUND(H25+I25*TC,2) -> #REF!
A26: =A25+0.0001 -> 12.0112 | B26: DUCHAS PORTATILES PARA OBREROS | C26: mes | D26: 10.5 | E26: 560 | G26: =IFERROR(IF(D26=0,"",(E26+F26*TC)),"") | H26: =+ROUND(D26*E26,2) -> 5880 | I26: =+ROUND(D26*F26,2) -> 0 | J26: =+ROUND(H26+I26*TC,2) -> #REF!
A27: =A26+0.0001 -> 12.0113 | B27: ALQUILER LAVAMANOS PARA OBREROS | C27: mes | D27: 13.5 | E27: 660 | G27: =IFERROR(IF(D27=0,"",(E27+F27*TC)),"") | H27: =+ROUND(D27*E27,2) -> 8910 | I27: =+ROUND(D27*F27,2) -> 0 | J27: =+ROUND(H27+I27*TC,2) -> #REF!
A28: =A27+0.0001 -> 12.0114 | B28: ESCUADRAS METALICAS PARA LAS OFICINAS EN MUROS ANCLADOS | F28: 0 | G28: =IFERROR(IF(D28=0,"",(E28+F28*TC)),"") | H28: =+ROUND(D28*E28,2) -> 0 | I28: =+ROUND(D28*F28,2) -> 0 | J28: =+ROUND(H28+I28*TC,2) -> #REF!
A29: =A28+0.0001 -> 12.0115 | B29: ALQUILER DE ESCUADRAS METÁLICAS | C29: ml | D29: 52 | E29: 712.5 | G29: =IFERROR(IF(D29=0,"",(E29+F29*TC)),"") | H29: =+ROUND(D29*E29,2) -> 37050 | I29: =+ROUND(D29*F29,2) -> 0 | J29: =+ROUND(H29+I29*TC,2) -> #REF!
A30: =A29+0.0001 -> 12.0116 | B30: INSTALACIÓN DE ESCUADRAS METÁLICAS | C30: ml | D30: 52 | E30: 118.82 | G30: =IFERROR(IF(D30=0,"",(E30+F30*TC)),"") | H30: =+ROUND(D30*E30,2) -> 6178.64 | I30: =+ROUND(D30*F30,2) -> 0 | J30: =+ROUND(H30+I30*TC,2) -> #REF!
A31: =A30+0.0001 -> 12.0117 | B31: PERNOS DE EXPANSIÓN | C31: und | D31: 416 | F31: 8.7 | G31: =IFERROR(IF(D31=0,"",(E31+F31*TC)),"") | H31: =+ROUND(D31*E31,2) -> 0 | I31: =+ROUND(D31*F31,2) -> 3619.2 | J31: =+ROUND(H31+I31*TC,2) -> #REF!
A32: =A31+0.0001 -> 12.0118 | B32: DESISTALACION DE ESCUADRAS METÁLICAS | C32: ml | D32: 52 | E32: 46.66 | G32: =IFERROR(IF(D32=0,"",(E32+F32*TC)),"") | H32: =+ROUND(D32*E32,2) -> 2426.32 | I32: =+ROUND(D32*F32,2) -> 0 | J32: =+ROUND(H32+I32*TC,2) -> #REF!
A33: =A32+0.0001 -> 12.0119 | B33: MADERA CACHIMBO 2" X 12" X 10´, SOBRE ESCUADRAS METÁLICAS | C33: und | D33: 112 | E33: 127.5 | G33: =IFERROR(IF(D33=0,"",(E33+F33*TC)),"") | H33: =+ROUND(D33*E33,2) -> 14280 | I33: =+ROUND(D33*F33,2) -> 0 | J33: =+ROUND(H33+I33*TC,2) -> #REF!
A34: =A33+0.0001 -> 12.012 | B34: INSTALACIÓN Y DESISTALACIÓN DE MADERA, SOBRE ESCUADRAS METÁLICAS | C34: ml | D34: 52 | E34: 87.76 | G34: =IFERROR(IF(D34=0,"",(E34+F34*TC)),"") | H34: =+ROUND(D34*E34,2) -> 4563.52 | I34: =+ROUND(D34*F34,2) -> 0 | J34: =+ROUND(H34+I34*TC,2) -> #REF!
A35: =A34+0.0001 -> 12.0121 | B35: VENTILACION PROVISIONAL EN SOTANOS | C35: glb | D35: 1 | E35: 7350 | G35: =IFERROR(IF(D35=0,"",(E35+F35*TC)),"") | H35: =+ROUND(D35*E35,2) -> 7350 | I35: =+ROUND(D35*F35,2) -> 0 | J35: =+ROUND(H35+I35*TC,2) -> #REF!
A36: =A35+0.0001 -> 12.0122 | B36: PROTECCIÓN DE VECINOS CON MALLA RASCHEL (ENCAPSULADO) | C36: glb | D36: 1 | E36: 28599.53 | G36: =IFERROR(IF(D36=0,"",(E36+F36*TC)),"") | H36: =+ROUND(D36*E36,2) -> 28599.53 | I36: =+ROUND(D36*F36,2) -> 0 | J36: =+ROUND(H36+I36*TC,2) -> #REF!
A37: =A36+0.0001 -> 12.0123 | B37: RENOVACIÓN DE MALLA RACHEL | C37: glb | D37: 0 | E37: 3324.88 | G37: =IFERROR(IF(D37=0,"",(E37+F37*TC)),"") | H37: =+ROUND(D37*E37,2) -> 0 | I37: =+ROUND(D37*F37,2) -> 0 | J37: =+ROUND(H37+I37*TC,2) -> #REF!
A38: =A37+0.0001 -> 12.0124 | B38: CERCO METALICO DE OBRA | C38: ml | D38: 0 | E38: 475 | G38: =IFERROR(IF(D38=0,"",(E38+F38*TC)),"") | H38: =+ROUND(D38*E38,2) -> 0 | I38: =+ROUND(D38*F38,2) -> 0 | J38: =+ROUND(H38+I38*TC,2) -> #REF!
A39: =A38+0.0001 -> 12.0125 | B39: BASTIDORES METALICOS PARA FIJAR MALLA DE PROTECCION + MALLA RACHELL | C39: ml | D39: 0 | E39: 98.89 | G39: =IFERROR(IF(D39=0,"",(E39+F39*TC)),"") | H39: =+ROUND(D39*E39,2) -> 0 | I39: =+ROUND(D39*F39,2) -> 0 | J39: =+ROUND(H39+I39*TC,2) -> #REF!
A40: =A39+0.0001 -> 12.0126 | B40: MANTENIMIENTO A MITAD DE OBRA DE CERCO PROVISIONAL DE OBRA | C40: ml | D40: 0 | E40: 74.4 | G40: =IFERROR(IF(D40=0,"",(E40+F40*TC)),"") | H40: =+ROUND(D40*E40,2) -> 0 | I40: =+ROUND(D40*F40,2) -> 0 | J40: =+ROUND(H40+I40*TC,2) -> #REF!
A41: =A40+0.0001 -> 12.0127 | B41: DESMONTAJE DE CERCO PROVISIONAL DE OBRA | C41: ml | D41: 26 | E41: 80.7 | G41: =IFERROR(IF(D41=0,"",(E41+F41*TC)),"") | H41: =+ROUND(D41*E41,2) -> 2098.2 | I41: =+ROUND(D41*F41,2) -> 0 | J41: =+ROUND(H41+I41*TC,2) -> #REF!
A42: =A41+0.0001 -> 12.0128 | B42: PROTECCION PERIMETRAL INICIAL VERTICAL DE VECINOS | C42: glb | D42: 1 | E42: 3250 | G42: =IFERROR(IF(D42=0,"",(E42+F42*TC)),"") | H42: =+ROUND(D42*E42,2) -> 3250 | I42: =+ROUND(D42*F42,2) -> 0 | J42: =+ROUND(H42+I42*TC,2) -> #REF!
A43: =A42+0.0001 -> 12.0129 | B43: PROTECCION HORIZONTAL INICIAL DE VECINOS | C43: glb | D43: 1 | E43: 3000 | G43: =IFERROR(IF(D43=0,"",(E43+F43*TC)),"") | H43: =+ROUND(D43*E43,2) -> 3000 | I43: =+ROUND(D43*F43,2) -> 0 | J43: =+ROUND(H43+I43*TC,2) -> #REF!
A44: =A43+0.0001 -> 12.013 | B44: CARTEL DE OBRA (INC CARTEL PUBLICITARIO EN TORRE GRUA) | C44: glb | D44: 1 | E44: 1400 | G44: =IFERROR(IF(D44=0,"",(E44+F44*TC)),"") | H44: =+ROUND(D44*E44,2) -> 1400 | I44: =+ROUND(D44*F44,2) -> 0 | J44: =+ROUND(H44+I44*TC,2) -> #REF!
A45: =A14+0.01 -> 1.02 | B45: CAMPAMENTO Y SALA DE VENTAS CLIENTE - NO SE CONSIDERA | F45: 0 | K45: =SUM(J46:J49) -> #REF!
A46: =A45+0.0001 -> 1.0201 | B46: ESCUADRAS Y TABLAS PARA CASETA DE VENTAS EN VOLADIZO | C46: ml | D46: 0 | E46: 1281.3025 | F46: 0 | G46: =IFERROR(IF(D46=0,"",(E46+F46*TC)),"") | H46: =+ROUND(D46*E46,2) -> 0 | I46: =+ROUND(D46*F46,2) -> 0 | J46: =+ROUND(H46+I46*TC,2) -> #REF!
A47: =A46+0.0001 -> 1.0202 | B47: TRASLADO DE CONTENEDOR SALA DE VENTAS CLIENTE (MOVIMIENTO 1 VEZ) | C47: und | D47: 0 | E47: 1643.74 | F47: 0 | G47: =IFERROR(IF(D47=0,"",(E47+F47*TC)),"") | H47: =+ROUND(D47*E47,2) -> 0 | I47: =+ROUND(D47*F47,2) -> 0 | J47: =+ROUND(H47+I47*TC,2) -> #REF!
A48: =A47+0.0001 -> 1.0203 | B48: ESCALERA METALICA (1-2 PISO) INGRESO DE SALA VENTAS A DEP PILOTO | C48: glb | D48: 0 | E48: 2400 | F48: 0 | G48: =IFERROR(IF(D48=0,"",(E48+F48*TC)),"") | H48: =+ROUND(D48*E48,2) -> 0 | I48: =+ROUND(D48*F48,2) -> 0 | J48: =+ROUND(H48+I48*TC,2) -> #REF!
A49: =A48+0.0001 -> 1.0204 | B49: PROTECCION A ACCESO VERTICAL (1- PISO) | C49: glb | D49: 0 | E49: 1500 | F49: 0 | G49: =IFERROR(IF(D49=0,"",(E49+F49*TC)),"") | H49: =+ROUND(D49*E49,2) -> 0 | I49: =+ROUND(D49*F49,2) -> 0 | J49: =+ROUND(H49+I49*TC,2) -> #REF!
A50: =A45+0.01 -> 1.03 | B50: MOVILIZACION DE CAMPAMENTO, MAQUINARIA Y HERRAMIENTAS | K50: =SUM(J51:J56) -> #REF!
A51: =A50+0.0001 -> 1.0301 | B51: MOVILIZACION (FLETES DURANTE LA OBRA) | C51: mes | D51: 20.5 | E51: 1250 | G51: =IFERROR(IF(D51=0,"",(E51+F51*TC)),"") | H51: =+ROUND(D51*E51,2) -> 25625 | I51: =+ROUND(D51*F51,2) -> 0 | J51: =+ROUND(H51+I51*TC,2) -> #REF!
A52: =A51+0.0001 -> 1.0302 | B52: ALQUILER DE GRUA TELESCOPICA PARA MONTAJES DE CASETAS | C52: hm | D52: 0 | E52: 0 | F52: 120 | G52: =IFERROR(IF(D52=0,"",(E52+F52*TC)),"") | H52: =+ROUND(D52*E52,2) -> 0 | I52: =+ROUND(D52*F52,2) -> 0 | J52: =+ROUND(H52+I52*TC,2) -> #REF!
A53: =A52+0.0001 -> 1.0303 | B53: MOVILIZACION DE CAMPAMENTO, EQUIPOS Y HERRAMIENTAS | C53: glb | D53: 1 | E53: 2550 | G53: =IFERROR(IF(D53=0,"",(E53+F53*TC)),"") | H53: =+ROUND(D53*E53,2) -> 2550 | I53: =+ROUND(D53*F53,2) -> 0 | J53: =+ROUND(H53+I53*TC,2) -> #REF!
A54: =A53+0.0001 -> 1.0304 | B54: MOVILIZACION DE ESCALERAS DE ACCESO, ANDAMIOS | C54: vje | D54: 10 | E54: 850 | G54: =IFERROR(IF(D54=0,"",(E54+F54*TC)),"") | H54: =+ROUND(D54*E54,2) -> 8500 | I54: =+ROUND(D54*F54,2) -> 0 | J54: =+ROUND(H54+I54*TC,2) -> #REF!
A55: =#REF!+0.0001 -> #REF! | B55: DESMOVILIZACION DE CAMPAMENTO, EQUIPOS Y HERRAMIENTAS | C55: glb | D55: 1 | E55: 2550 | G55: =IFERROR(IF(D55=0,"",(E55+F55*TC)),"") | H55: =+ROUND(D55*E55,2) -> 2550 | I55: =+ROUND(D55*F55,2) -> 0 | J55: =+ROUND(H55+I55*TC,2) -> #REF!
A56: =A55+0.0001 -> #REF! | B56: ALQUILER DE GRUA TELESCOPICA PARA DESMONTAJES DE CASETAS | C56: hm | D56: 0 | E56: 0 | F56: 120 | G56: =IFERROR(IF(D56=0,"",(E56+F56*TC)),"") | H56: =+ROUND(D56*E56,2) -> 0 | I56: =+ROUND(D56*F56,2) -> 0 | J56: =+ROUND(H56+I56*TC,2) -> #REF!
A57: =A50+0.01 -> 1.04 | B57: MAQUINARIA Y HERRAMIENTAS | F57: 0 | G57: =IFERROR(IF(D57=0,"",(E57+F57*TC)),"") | H57: =+ROUND(D57*E57,2) -> 0 | I57: =+ROUND(D57*F57,2) -> 0 | J57: =+ROUND(H57+I57*TC,2) -> #REF! | K57: =SUM(J58:J66) -> #REF!
A58: =A57+0.0001 -> 1.0401 | B58: NIVEL TOPOGRAFICO (INC CUADRILLA TOPOGRAFIA) | C58: glb | D58: 0 | G58: =IFERROR(IF(D58=0,"",(E58+F58*TC)),"") | H58: =+ROUND(D58*E58,2) -> 0 | I58: =+ROUND(D58*F58,2) -> 0 | J58: =+ROUND(H58+I58*TC,2) -> #REF!
A59: =A58+0.0001 -> 1.0402 | B59: TEODOLITO ELECTRICO (INC CUADRILLA TOPOGRAFIA) | C59: glb | D59: 0 | G59: =IFERROR(IF(D59=0,"",(E59+F59*TC)),"") | H59: =+ROUND(D59*E59,2) -> 0 | I59: =+ROUND(D59*F59,2) -> 0 | J59: =+ROUND(H59+I59*TC,2) -> #REF!
A60: =A59+0.0001 -> 1.0403 | B60: VIBRADOR ELECTRICO (INC EN APU DE CONCRETO) | C60: glb | D60: 0 | G60: =IFERROR(IF(D60=0,"",(E60+F60*TC)),"") | H60: =+ROUND(D60*E60,2) -> 0 | I60: =+ROUND(D60*F60,2) -> 0 | J60: =+ROUND(H60+I60*TC,2) -> #REF!
A61: =A60+0.0001 -> 1.0404 | B61: COMPACTADORA TIPO PLANCHA (INC EN APU EST SOT) | C61: glb | D61: 0 | G61: =IFERROR(IF(D61=0,"",(E61+F61*TC)),"") | H61: =+ROUND(D61*E61,2) -> 0 | I61: =+ROUND(D61*F61,2) -> 0 | J61: =+ROUND(H61+I61*TC,2) -> #REF!
A62: =A61+0.0001 -> 1.0405 | B62: APISONADOR TIPO CANGURO (INC EN APU EST SOT) | C62: glb | D62: 0 | G62: =IFERROR(IF(D62=0,"",(E62+F62*TC)),"") | H62: =+ROUND(D62*E62,2) -> 0 | I62: =+ROUND(D62*F62,2) -> 0 | J62: =+ROUND(H62+I62*TC,2) -> #REF!
A63: =A61+0.0001 -> 1.0405 | B63: MARTILLO ELECTRICO | C63: glb | D63: 4 | E63: 4600 | G63: =IFERROR(IF(D63=0,"",(E63+F63*TC)),"") | H63: =+ROUND(D63*E63,2) -> 18400 | I63: =+ROUND(D63*F63,2) -> 0 | J63: =+ROUND(H63+I63*TC,2) -> #REF!
A64: =A63+0.0001 -> 1.0406 | B64: AMOLADORAS Y RADIALES | C64: glb | D64: 10 | E64: 675 | G64: =IFERROR(IF(D64=0,"",(E64+F64*TC)),"") | H64: =+ROUND(D64*E64,2) -> 6750 | I64: =+ROUND(D64*F64,2) -> 0 | J64: =+ROUND(H64+I64*TC,2) -> #REF!
A65: =A64+0.0001 -> 1.0407 | B65: KIT DE SOLAQUEO (ASPIRADORA DE POLVO UNIVERSAL) | C65: glb | D65: 3 | E65: 2250 | G65: =IFERROR(IF(D65=0,"",(E65+F65*TC)),"") | H65: =+ROUND(D65*E65,2) -> 6750 | I65: =+ROUND(D65*F65,2) -> 0 | J65: =+ROUND(H65+I65*TC,2) -> #REF!
A66: =A65+0.0001 -> 1.0408 | B66: HIDROLAVADORA | C66: glb | D66: 1 | E66: 1350 | G66: =IFERROR(IF(D66=0,"",(E66+F66*TC)),"") | H66: =+ROUND(D66*E66,2) -> 1350 | I66: =+ROUND(D66*F66,2) -> 0 | J66: =+ROUND(H66+I66*TC,2) -> #REF!
A67: =A57+0.01 -> 1.05 | B67: TRANSPORTE VERTICAL Y HORIZONTAL | F67: 0 | G67: =IFERROR(IF(D67=0,"",(E67+F67*TC)),"") | K67: =SUM(J69:J109) -> #REF!
A68: =A67+0.0001 -> 1.0501 | B68: ALQUILER GRUA TORRE - AUTOESTABLE | G68: =IFERROR(IF(D68=0,"",(E68+F68*TC)),"")
A69: =A68+0.000001 -> 1.050101 | B69: ALQUILER DE GRÚA TORRE - AUTOESTABLE - AGRUMAQ | C69: mes | D69: 8 | E69: 0 | F69: 6000 | G69: =IFERROR(IF(D69=0,"",(E69+F69*TC)),"") | H69: =+ROUND(D69*E69,2) -> 0 | I69: =+ROUND(D69*F69,2) -> 48000 | J69: =+ROUND(H69+I69*TC,2) -> #REF!
A70: =A69+0.000001 -> 1.050102 | B70: REVISION MENSUAL | C70: mes | D70: 8 | E70: 0 | F70: 275 | G70: =IFERROR(IF(D70=0,"",(E70+F70*TC)),"") | H70: =+ROUND(D70*E70,2) -> 0 | I70: =+ROUND(D70*F70,2) -> 2200 | J70: =+ROUND(H70+I70*TC,2) -> #REF!
A71: =A70+0.000001 -> 1.050103 | B71: SEGURO TREC GRUA (TODO RIESGO Y RESPONSABILIDAD CIVIL) | C71: mes | D71: 8 | E71: 0 | F71: 400 | G71: =IFERROR(IF(D71=0,"",(E71+F71*TC)),"") | H71: =+ROUND(D71*E71,2) -> 0 | I71: =+ROUND(D71*F71,2) -> 3200 | J71: =+ROUND(H71+I71*TC,2) -> #REF!
A72: =A71+0.000001 -> 1.050104 | B72: ALQUILER DE AUTOTRANSFORMADOR | C72: mes | D72: 8 | E72: 0 | F72: 180 | G72: =IFERROR(IF(D72=0,"",(E72+F72*TC)),"") | H72: =+ROUND(D72*E72,2) -> 0 | I72: =+ROUND(D72*F72,2) -> 1440 | J72: =+ROUND(H72+I72*TC,2) -> #REF!
A73: =A71+0.000001 -> 1.050104 | B73: OPERADOR DE GRUA X 200 HORAS MENSUALES | C73: mes | D73: 8 | E73: 0 | F73: 2000 | G73: =IFERROR(IF(D73=0,"",(E73+F73*TC)),"") | H73: =+ROUND(D73*E73,2) -> 0 | I73: =+ROUND(D73*F73,2) -> 16000 | J73: =+ROUND(H73+I73*TC,2) -> #REF!
A74: =A73+0.000001 -> 1.050105 | B74: CERTIFICADO DE INSTALACIÓN Y MONTAJE | C74: glb | D74: 1 | E74: 0 | F74: 275 | G74: =IFERROR(IF(D74=0,"",(E74+F74*TC)),"") | H74: =+ROUND(D74*E74,2) -> 0 | I74: =+ROUND(D74*F74,2) -> 275 | J74: =+ROUND(H74+I74*TC,2) -> #REF!
A75: =A74+0.000001 -> 1.050106 | B75: TRANSPORTE DE PATAS DE EMPOTRAMIENTO A OBRA | C75: glb | D75: 1 | E75: 0 | F75: 300 | G75: =IFERROR(IF(D75=0,"",(E75+F75*TC)),"") | H75: =+ROUND(D75*E75,2) -> 0 | I75: =+ROUND(D75*F75,2) -> 300 | J75: =+ROUND(H75+I75*TC,2) -> #REF!
A76: =A75+0.000001 -> 1.050107 | B76: CERRAMIENTO PATAS DE EMPOTRAMIENTO COMO TRAMO DE TORRE | C76: glb | D76: 1 | E76: 0 | F76: 700 | G76: =IFERROR(IF(D76=0,"",(E76+F76*TC)),"") | H76: =+ROUND(D76*E76,2) -> 0 | I76: =+ROUND(D76*F76,2) -> 700 | J76: =+ROUND(H76+I76*TC,2) -> #REF!
A77: =A76+0.000001 -> 1.050108 | B77: PERNOS DE NIVELACION PARA PATAS DE EMPOTRAMIENTO | C77: glb | D77: 1 | E77: 0 | F77: 500 | G77: =IFERROR(IF(D77=0,"",(E77+F77*TC)),"") | H77: =+ROUND(D77*E77,2) -> 0 | I77: =+ROUND(D77*F77,2) -> 500 | J77: =+ROUND(H77+I77*TC,2) -> #REF!
A78: =A77+0.000001 -> 1.050109 | B78: PATAS DE EMPOTRAMIENTO PARA TORRE GRUA | C78: glb | D78: 1 | E78: 0 | F78: 8500 | G78: =IFERROR(IF(D78=0,"",(E78+F78*TC)),"") | H78: =+ROUND(D78*E78,2) -> 0 | I78: =+ROUND(D78*F78,2) -> 8500 | J78: =+ROUND(H78+I78*TC,2) -> #REF!
A79: =A78+0.000001 -> 1.05011 | B79: CARGA DE TORRE GRUA EN ALMACEN | C79: glb | D79: 1 | E79: 0 | F79: 850 | G79: =IFERROR(IF(D79=0,"",(E79+F79*TC)),"") | H79: =+ROUND(D79*E79,2) -> 0 | I79: =+ROUND(D79*F79,2) -> 850 | J79: =+ROUND(H79+I79*TC,2) -> #REF!
A80: =A79+0.000001 -> 1.050111 | B80: TRANSPORTE DE TORRE GRUA A OBRA | C80: glb | D80: 1 | E80: 0 | F80: 2400 | G80: =IFERROR(IF(D80=0,"",(E80+F80*TC)),"") | H80: =+ROUND(D80*E80,2) -> 0 | I80: =+ROUND(D80*F80,2) -> 2400 | J80: =+ROUND(H80+I80*TC,2) -> #REF!
A81: =A80+0.000001 -> 1.050112 | B81: MANO DE OBRA POR MONTAJE DE TORRE GRUA | C81: glb | D81: 1 | E81: 0 | F81: 3200 | G81: =IFERROR(IF(D81=0,"",(E81+F81*TC)),"") | H81: =+ROUND(D81*E81,2) -> 0 | I81: =+ROUND(D81*F81,2) -> 3200 | J81: =+ROUND(H81+I81*TC,2) -> #REF!
A82: =A81+0.000001 -> 1.050113 | B82: ALQUILER DE GRUA AUXILIAR PARA MONTAJE POR DOS DÍAS DE TRABAJO | C82: glb | D82: 1 | E82: 0 | F82: 6500 | G82: =IFERROR(IF(D82=0,"",(E82+F82*TC)),"") | H82: =+ROUND(D82*E82,2) -> 0 | I82: =+ROUND(D82*F82,2) -> 6500 | J82: =+ROUND(H82+I82*TC,2) -> #REF!
A83: =A82+0.000001 -> 1.050114 | B83: MANO DE OBRA POR DESMONTAJE DE TORRE GRUA | C83: glb | D83: 1 | E83: 0 | F83: 3200 | G83: =IFERROR(IF(D83=0,"",(E83+F83*TC)),"") | H83: =+ROUND(D83*E83,2) -> 0 | I83: =+ROUND(D83*F83,2) -> 3200 | J83: =+ROUND(H83+I83*TC,2) -> #REF!
A84: =A83+0.000001 -> 1.050115 | B84: ALQUILER DE GRUA AUXILIAR DE 300TON PARA DESMONTAJE POR DOS DÍAS DE TRABAJO | C84: glb | D84: 1 | E84: 0 | F84: 6500 | G84: =IFERROR(IF(D84=0,"",(E84+F84*TC)),"") | H84: =+ROUND(D84*E84,2) -> 0 | I84: =+ROUND(D84*F84,2) -> 6500 | J84: =+ROUND(H84+I84*TC,2) -> #REF!
A85: =A84+0.000001 -> 1.050116 | B85: TRANSPORTE DE RETORNO A ALMACEN | C85: glb | D85: 1 | E85: 0 | F85: 2400 | G85: =IFERROR(IF(D85=0,"",(E85+F85*TC)),"") | H85: =+ROUND(D85*E85,2) -> 0 | I85: =+ROUND(D85*F85,2) -> 2400 | J85: =+ROUND(H85+I85*TC,2) -> #REF!
A86: =A85+0.000001 -> 1.050117 | B86: DESCARGA EN ALMACEN | C86: glb | D86: 1 | E86: 0 | F86: 850 | G86: =IFERROR(IF(D86=0,"",(E86+F86*TC)),"") | H86: =+ROUND(D86*E86,2) -> 0 | I86: =+ROUND(D86*F86,2) -> 850 | J86: =+ROUND(H86+I86*TC,2) -> #REF!
A87: =A86+0.000001 -> 1.050118 | B87: TRANSPORTE VERTICAL CON GRUA - COSTO DE 02 RIGGER | C87: mes | D87: 8 | E87: 10811.84 | G87: =IFERROR(IF(D87=0,"",(E87+F87*TC)),"") | H87: =+ROUND(D87*E87,2) -> 86494.72 | I87: =+ROUND(D87*F87,2) -> 0 | J87: =+ROUND(H87+I87*TC,2) -> #REF!
A88: =A68+0.0001 -> 1.0502 | B88: CIMENTACION PARA GRUA TORRE | G88: =IFERROR(IF(D88=0,"",(E88+F88*TC)),"") | H88: =+ROUND(D88*E88,2) -> 0 | I88: =+ROUND(D88*F88,2) -> 0 | J88: =+ROUND(H88+I88*TC,2) -> #REF!
A89: =A87+0.000001 -> 1.050119 | B89: CIMENTACION EN VIGA PARA GRUA TORRE (AGRUMAQ) | C89: glb | D89: 1 | E89: 22804.97 | F89: 9990.62 | G89: =IFERROR(IF(D89=0,"",(E89+F89*TC)),"") | H89: =+ROUND(D89*E89,2) -> 22804.97 | I89: =+ROUND(D89*F89,2) -> 9990.62 | J89: =+ROUND(H89+I89*TC,2) -> #REF!
A90: =A88+0.0001 -> 1.0503 | B90: ALQUILER ELEVADOR VERTICAL | G90: =IFERROR(IF(D90=0,"",(E90+F90*TC)),"") | H90: =+ROUND(D90*E90,2) -> 0 | I90: =+ROUND(D90*F90,2) -> 0 | J90: =+ROUND(H90+I90*TC,2) -> #REF!
A91: =A90+0.000001 -> 1.050301 | B91: ALQUILER DE ELEVADOR DE PERSONAL DE CREMALLERA, CAP. MAX 2 TON | C91: mes | D91: 6 | E91: 0 | F91: 1500 | G91: =IFERROR(IF(D91=0,"",(E91+F91*TC)),"") | H91: =+ROUND(D91*E91,2) -> 0 | I91: =+ROUND(D91*F91,2) -> 9000 | J91: =+ROUND(H91+I91*TC,2) -> #REF!
A92: =A94+0.000001 -> 1.050304 | B92: REVISIÓN MENSUAL DE ELEVADOR DE PERSONAL DE CREMALLERA | C92: mes | D92: 6 | E92: 0 | F92: 350 | G92: =IFERROR(IF(D92=0,"",(E92+F92*TC)),"") | H92: =+ROUND(D92*E92,2) -> 0 | I92: =+ROUND(D92*F92,2) -> 2100 | J92: =+ROUND(H92+I92*TC,2) -> #REF!
A93: =A91+0.000001 -> 1.050302 | B93: ALQUILER DE AUTOTRANSFORMADOR | C93: mes | D93: 6 | E93: 0 | F93: 150 | G93: =IFERROR(IF(D93=0,"",(E93+F93*TC)),"") | H93: =+ROUND(D93*E93,2) -> 0 | I93: =+ROUND(D93*F93,2) -> 900 | J93: =+ROUND(H93+I93*TC,2) -> #REF!
A94: =A93+0.000001 -> 1.050303 | B94: OPERADOR DE ELEVADOR X 200 HORAS | C94: mes | D94: 6 | E94: 0 | F94: 1920 | G94: =IFERROR(IF(D94=0,"",(E94+F94*TC)),"") | H94: =+ROUND(D94*E94,2) -> 0 | I94: =+ROUND(D94*F94,2) -> 11520 | J94: =+ROUND(H94+I94*TC,2) -> #REF!
A95: =A92+0.000001 -> 1.050305 | B95: MONTAJE DE ELEVADOR DE PERSONAL DE CREMALLERA | C95: glb | D95: 1 | E95: 0 | F95: 7120 | G95: =IFERROR(IF(D95=0,"",(E95+F95*TC)),"") | H95: =+ROUND(D95*E95,2) -> 0 | I95: =+ROUND(D95*F95,2) -> 7120 | J95: =+ROUND(H95+I95*TC,2) -> #REF!
A96: =A95+0.000001 -> 1.050306 | B96: DESMONTAJE DE ELEVADOR DE PERSONAL DE CREMALLERA | C96: glb | D96: 1 | E96: 0 | F96: 5980 | G96: =IFERROR(IF(D96=0,"",(E96+F96*TC)),"") | H96: =+ROUND(D96*E96,2) -> 0 | I96: =+ROUND(D96*F96,2) -> 5980 | J96: =+ROUND(H96+I96*TC,2) -> #REF!
A97: =A90+0.0001 -> 1.0504 | B97: ACCESORIOS PARA ACARREO | G97: =IFERROR(IF(D97=0,"",(E97+F97*TC)),"") | H97: =+ROUND(D97*E97,2) -> 0 | I97: =+ROUND(D97*F97,2) -> 0 | J97: =+ROUND(H97+I97*TC,2) -> #REF!
A98: =A97+0.000001 -> 1.050401 | B98: PULPO DE CADENA, ESTROBO Y ESLINGA | C98: glb | D98: 1 | E98: 3967.6 | G98: =IFERROR(IF(D98=0,"",(E98+F98*TC)),"") | H98: =+ROUND(D98*E98,2) -> 3967.6 | I98: =+ROUND(D98*F98,2) -> 0 | J98: =+ROUND(H98+I98*TC,2) -> #REF!
A99: =A98+0.000001 -> 1.050402 | B99: ALQUILER DE BALDE PARA CONCRETO | C99: mes | D99: 8 | E99: 580 | G99: =IFERROR(IF(D99=0,"",(E99+F99*TC)),"") | H99: =+ROUND(D99*E99,2) -> 4640 | I99: =+ROUND(D99*F99,2) -> 0 | J99: =+ROUND(H99+I99*TC,2) -> #REF!
A100: =A98+0.000001 -> 1.050402 | B100: PLATAFORMAS PARA DESCARGAS DE PARIHUELAS (COMPRA 100%) | C100: und | D100: 2 | E100: 4940 | G100: =IFERROR(IF(D100=0,"",(E100+F100*TC)),"") | H100: =+ROUND(D100*E100,2) -> 9880 | I100: =+ROUND(D100*F100,2) -> 0 | J100: =+ROUND(H100+I100*TC,2) -> #REF!
A101: =A100+0.000001 -> 1.050403 | B101: STOCKAS PARA TRANSPORTE DE PARIHUELAS (COMPRA 100%) | C101: und | D101: 2 | F101: 459 | G101: =IFERROR(IF(D101=0,"",(E101+F101*TC)),"") | H101: =+ROUND(D101*E101,2) -> 0 | I101: =+ROUND(D101*F101,2) -> 918 | J101: =+ROUND(H101+I101*TC,2) -> #REF!
A102: =A101+0.000001 -> 1.050404 | B102: INSTALACION Y DESISTALACION DE PLATAFORMA DESCARGA DE PARIHUELAS | C102: und | D102: 21 | E102: 201.25 | G102: =IFERROR(IF(D102=0,"",(E102+F102*TC)),"") | H102: =+ROUND(D102*E102,2) -> 4226.25 | I102: =+ROUND(D102*F102,2) -> 0 | J102: =+ROUND(H102+I102*TC,2) -> #REF!
A103: =A102+0.000001 -> 1.050405 | B103: ALQUILER GRUA TELESCOPICA PARA ACARREO DE ACERO (1 DIA/SEM) ETAPA EXCAVACION - AJUSTE DE CAMPO | C103: día | D103: 0 | E103: 3450 | G103: =IFERROR(IF(D103=0,"",(E103+F103*TC)),"") | H103: =+ROUND(D103*E103,2) -> 0 | I103: =+ROUND(D103*F103,2) -> 0 | J103: =+ROUND(H103+I103*TC,2) -> #REF!
A104: =A97+0.0001 -> 1.0505 | B104: TRASLADO Y ACARREO HORIZONTAL | G104: =IFERROR(IF(D104=0,"",(E104+F104*TC)),"") | H104: =+ROUND(D104*E104,2) -> 0 | I104: =+ROUND(D104*F104,2) -> 0 | J104: =+ROUND(H104+I104*TC,2) -> #REF!
A105: =A104+0.000001 -> 1.050501 | B105: PEON DE MONTACARGA (PISO SUPERIOR) - ACARREO HORIZONTAL | C105: mes | D105: 6 | E105: 1918.8 | G105: =IFERROR(IF(D105=0,"",(E105+F105*TC)),"") | H105: =+ROUND(D105*E105,2) -> 11512.8 | I105: =+ROUND(D105*F105,2) -> 0 | J105: =+ROUND(H105+I105*TC,2) -> #REF!
...

Sheet SEG
A2: SEGURIDAD Y SALUD
A4: Presupuesto | B4: =#REF! -> #REF!
A5: Subpresupuesto | B5: =$A$2 -> SEGURIDAD Y SALUD
A6: Cliente | B6: =#REF! -> #REF!
A7: Lugar | B7: =#REF! -> #REF!
A8: Fecha | B8: =#REF! -> #REF!
A10: ITEM | B10: DESCRIPCION | C10: UND | D10: CANTIDAD | E10: P.U. (PEN) | F10: PARCIAL | G10: TOTAL
A11: 02 | B11: SEGURIDAD Y SALUD
A12: =A11+0.01 -> 2.01 | B12: ELABORACIÓN, IMPLEMENTACIÓN Y ADMINISTRACIÓN DEL PLAN DE SEGURIDAD Y SALUD EN EL TRABAJO | G12: =SUM(F13:F20) -> 569835.75
A13: =A12+0.0001 -> 2.0101 | B13: EQUIPOS DE PROTECCION INDIVIDUAL (STAFF Y OBREROS) | C13: glb | D13: 1 | E13: 145377.82 | F13: =+ROUND(D13*E13,2) -> 145377.82
A14: =A13+0.0001 -> 2.0102 | B14: EQUIPOS DE PROTECCION COLECTIVA | C14: glb | D14: 1 | E14: 162292.96 | F14: =+ROUND(D14*E14,2) -> 162292.96
A15: =A14+0.0001 -> 2.0103 | B15: MONITOREO DE AIRE Y RUIDO EN LA CONSTRUCCION (@ 6 MESES) | C15: und | D15: 4 | E15: 900 | F15: =+ROUND(D15*E15,2) -> 3600
A16: =A15+0.0001 -> 2.0104 | B16: CONTROL DE POLVOS EN MOVIMIENTO DE TIERRAS (EXIGENCIA LEED) | C16: mes | D16: 0 | E16: 1505 | F16: =+ROUND(D16*E16,2) -> 0
A17: =A16+0.0001 -> 2.0105 | B17: EXAMEN MÉDICO PRE-OCUPACIONAL | C17: und | D17: 190 | E17: 130 | F17: =+ROUND(D17*E17,2) -> 24700
A18: =A17+0.0001 -> 2.0106 | B18: MALLA ANTICAIDAS (PERIMETRO EDIFICIO) | C18: glb | D18: 1 | E18: 84895.8 | F18: =+ROUND(D18*E18,2) -> 84895.8
A19: =A18+0.0001 -> 2.0107 | B19: MALLA ANTICAIDAS (DUCTO DE ASCENSOR) | C19: glb | D19: 1 | E19: 12734.37 | F19: =+ROUND(D19*E19,2) -> 12734.37
A20: =A19+0.0001 -> 2.0108 | B20: DESVIO DE TRANSITO (02 SEÑALERO x FRENTE) | C20: mes | D20: 20.5 | E20: 6645.6 | F20: =+ROUND(D20*E20,2) -> 136234.8
A21: =A12+0.01 -> 2.02 | B21: PREVENCIONISTAS | G21: =SUM(F22:F24) -> 157853.28
A22: =A21+0.0001 -> 2.0201 | B22: ASISTENTES DE PDR (01) | C22: mes | D22: 20.5 | E22: 4236.96 | F22: =+ROUND(D22*E22,2) -> 86857.68
A23: =A22+0.0001 -> 2.0202 | B23: AYUDANTE DE PDR N°1 (01) | C23: mes | D23: 10 | E23: 3837.6 | F23: =+ROUND(D23*E23,2) -> 38376
A24: =A23+0.0001 -> 2.0203 | B24: AYUDANTE DE PDR N°2 (01) | C24: mes | D24: 8.5 | E24: 3837.6 | F24: =+ROUND(D24*E24,2) -> 32619.6
A25: =A21+0.01 -> 2.03 | B25: SEGURIDAD POLICIAL | G25: =SUM(F26:F27) -> 7857.5
A26: =A25+0.0001 -> 2.0301 | B26: CAMARAS DE SEGURIDAD | C26: glb | D26: 1 | E26: 5500 | F26: =+ROUND(D26*E26,2) -> 5500
A27: =A26+0.0001 -> 2.0302 | B27: SERVICIO MENSUAL MANTENIMIENTO | C27: mes | D27: 20.5 | E27: 115 | F27: =+ROUND(D27*E27,2) -> 2357.5
D28: COSTO DIRECTO | G28: =SUM(G12:G27) -> 735546.53
F30: S10 | G30: 735546.53
G31: =+G28-G30 -> 0

Sheet GG
A2: GASTOS GENERALES
A4: Presupuesto | B4: =#REF! -> #REF!
A5: Subpresupuesto | B5: =A2 -> GASTOS GENERALES
A6: Cliente | B6: =#REF! -> #REF!
A7: Lugar | B7: =#REF! -> #REF!
A8: Fecha | B8: =#REF! -> #REF!
A11: ITEM | B11: DESCRIPCION | C11: UND | D11: CANTIDAD | E11: MESES | F11: PRECIO (PEN) | H11: PARCIAL | I11: TOTAL
A12: 12 | B12: GASTOS GENERALES
A13: =A12+0.01 -> 12.01 | B13: PERSONAL STAFF | I13: =SUM(H14:H24) -> 1627787.2
A14: =A13+0.0001 -> 12.0101 | B14: GERENTE DE PROYECTOS | C14: mes | D14: 1 | E14: 20.5 | F14: 16200 | H14: =+ROUND(D14*E14*F14,2) -> 332100 | J14: =+D14*E14 -> 20.5
A15: =A14+0.0001 -> 12.0102 | B15: INGENIERO RESIDENTE | C15: mes | D15: 1 | E15: 21.5 | F15: 10500 | H15: =+ROUND(D15*E15*F15,2) -> 225750 | J15: =+D15*E15 -> 21.5
A16: =A15+0.0001 -> 12.0103 | B16: INGENIERO DE OFICINA TECNICA | C16: mes | D16: 1 | E16: 21.5 | F16: 10500.004 | H16: =+ROUND(D16*E16*F16,2) -> 225750.09 | J16: =+D16*E16 -> 21.5
A17: =A16+0.0001 -> 12.0104 | B17: INGENIERO DE CAMPO | C17: mes | D17: 1 | E17: 17.5 | F17: 7500 | H17: =+ROUND(D17*E17*F17,2) -> 131250 | J17: =+D17*E17 -> 17.5
A18: =A17+0.0001 -> 12.0105 | B18: INGENIERO DE CALIDAD | C18: mes | D18: 1 | E18: 13.5 | F18: 7500 | H18: =+ROUND(D18*E18*F18,2) -> 101250 | J18: =+D18*E18 -> 13.5
B19: INGENIERO DE CALIDAD JUNIOR | C19: mes | D19: 1 | E19: 7 | F19: 5250 | H19: =+ROUND(D19*E19*F19,2) -> 36750 | J19: =+D19*E19 -> 7
A20: =A18+0.0001 -> 12.0106 | B20: INGENIERO ELECTROMECANICO | C20: mes | D20: 0.5 | E20: 13.5 | F20: 10500.004 | H20: =+ROUND(D20*E20*F20,2) -> 70875.03 | J20: =+D20*E20 -> 6.75
A21: =A20+0.0001 -> 12.0107 | B21: ARQUITECTO DE ACABADOS | C21: mes | D21: 1 | E21: 13.5 | F21: 9000 | H21: =+ROUND(D21*E21*F21,2) -> 121500 | J21: =+D21*E21 -> 13.5
A22: =A21+0.0001 -> 12.0108 | B22: PREVENCIONISTA DE RIEGOS - SUBJEFE DE PDR | C22: mes | D22: 1 | E22: 20.5 | F22: 6750 | H22: =+ROUND(D22*E22*F22,2) -> 138375 | J22: =+D22*E22 -> 20.5
A23: =A22+0.0001 -> 12.0109 | B23: ADMINISTRADOR DE OBRA | C23: mes | D23: 1 | E23: 21.5 | F23: 6491.2603 | H23: =+ROUND(D23*E23*F23,2) -> 139562.1 | J23: =+D23*E23 -> 21.5
A24: =A23+0.0001 -> 12.011 | B24: INGENIERO BIM | C24: mes | D24: 1 | E24: 15.5 | F24: 6750 | H24: =+ROUND(D24*E24*F24,2) -> 104625 | J24: =+D24*E24 -> 15.5
A25: =A13+0.01 -> 12.02 | B25: PERSONAL TECNICO | H25: =+ROUND(D25*E25*F25,2) -> 0 | I25: =SUM(H26:H32) -> 599894.77 | J25: =+D25*E25 -> 0
A26: =A25+0.0001 -> 12.0201 | B26: ASISTENTE (CAMPO/CALIDAD/ARQ) | C26: mes | D26: 2 | E26: 13.5 | F26: 3990 | H26: =+ROUND(D26*E26*F26,2) -> 107730 | J26: =+D26*E26 -> 27
A27: =A26+0.0001 -> 12.0202 | B27: MAESTRO DE OBRA | C27: mes | D27: 1 | E27: 13.5 | F27: 8102.46 | H27: =+ROUND(D27*E27*F27,2) -> 109383.21 | J27: =+D27*E27 -> 13.5
A28: =A27+0.0001 -> 12.0203 | B28: CAPATAZ DE OBRA ESTRUCTURAS | C28: mes | D28: 1 | E28: 6.5 | F28: 6757.92 | H28: =+ROUND(D28*E28*F28,2) -> 43926.48 | J28: =+D28*E28 -> 6.5
A29: =A28+0.0001 -> 12.0204 | B29: CAPATAZ DE OBRA ARQUITECTURA N°1 | C29: mes | D29: 1 | E29: 11.5 | F29: 6757.92 | H29: =+ROUND(D29*E29*F29,2) -> 77716.08 | J29: =+D29*E29 -> 11.5
A30: =A29+0.0001 -> 12.0205 | B30: JEFE DE ALMACEN | C30: mes | D30: 1 | E30: 21.5 | F30: 5586 | H30: =+ROUND(D30*E30*F30,2) -> 120099 | J30: =+D30*E30 -> 21.5
A31: =A30+0.0001 -> 12.0206 | B31: GUARDIAN DE OBRA Y PORTERIA | C31: mes | D31: 1 | E31: 20.5 | F31: 6880 | H31: =+ROUND(D31*E31*F31,2) -> 141040 | J31: =+D31*E31 -> 20.5
A32: =A31+0.0001 -> 12.0207 | B32: VIGILANTE POLICIAL DE CIVIL (TURNO NOCHE) - SERA COBRADO COMO ADICIONAL | C32: mes | D32: 0 | E32: 11 | F32: 6880 | H32: =+ROUND(D32*E32*F32,2) -> 0 | J32: =+D32*E32 -> 0
A33: =A25+0.01 -> 12.03 | B33: EQUIPO DE OFICINA DE LA OBRA | I33: =SUM(H34:H71) -> 67463.62 | J33: =+D33*E33 -> 0
A34: =A33+0.0001 -> 12.0301 | B34: COMPUTADORAS | C34: mes | H34: =SUM(G36:G49) -> 20607.37 | J34: =+D34*E34 -> 0
A35: =A34+0.0001 -> 12.0302 | B35: DISGREGADO DE COMPUTADORAS | J35: =+D35*E35 -> 0
A36: 12.03.02.01 | B36: =+B15 -> INGENIERO RESIDENTE | C36: und | D36: 1 | E36: 21.5 | F36: 92.30625 | G36: =+D36*E36*F36 -> 1984.5844 | J36: =+D36*E36 -> 21.5
A37: 12.03.02.02 | B37: =+B16 -> INGENIERO DE OFICINA TECNICA | C37: und | D37: 1 | E37: 21.5 | F37: 92.30625 | G37: =+D37*E37*F37 -> 1984.5844 | J37: =+D37*E37 -> 21.5
A38: 12.03.02.03 | B38: =+B17 -> INGENIERO DE CAMPO | C38: und | D38: 1 | E38: 17.5 | F38: 92.30625 | G38: =+D38*E38*F38 -> 1615.3594 | J38: =+D38*E38 -> 17.5
A39: 12.03.02.05 | B39: =+B18 -> INGENIERO DE CALIDAD | C39: und | D39: 1 | E39: 13.5 | F39: 92.30625 | G39: =+D39*E39*F39 -> 1246.1344 | J39: =+D39*E39 -> 13.5
B40: INGENIERO DE CALIDAD JUNIOR | C40: und | D40: 1 | E40: 7 | F40: 92.30625 | G40: =+D40*E40*F40 -> 646.14375 | J40: =+D40*E40 -> 7
A41: 12.03.02.07 | B41: =+B20 -> INGENIERO ELECTROMECANICO | C41: und | D41: 0.5 | E41: 13.5 | F41: 92.30625 | G41: =+D41*E41*F41 -> 623.06719 | J41: =+D41*E41 -> 6.75
A42: 12.03.02.09 | B42: =+B21 -> ARQUITECTO DE ACABADOS | C42: und | D42: 1 | E42: 13.5 | F42: 92.30625 | G42: =+D42*E42*F42 -> 1246.1344 | J42: =+D42*E42 -> 13.5
A43: 12.03.02.12 | B43: =+B22 -> PREVENCIONISTA DE RIEGOS - SUBJEFE DE PDR | C43: und | D43: 1 | E43: 20.5 | F43: 92.30625 | G43: =+D43*E43*F43 -> 1892.2781 | J43: =+D43*E43 -> 20.5
A44: 12.03.02.15 | B44: =+B23 -> ADMINISTRADOR DE OBRA | C44: und | D44: 1 | E44: 21.5 | F44: 92.30625 | G44: =+D44*E44*F44 -> 1984.5844 | J44: =+D44*E44 -> 21.5
A45: 12.03.02.16 | B45: INGENIERO BIM | C45: und | D45: 1 | E45: 15.5 | F45: 92.30625 | G45: =+D45*E45*F45 -> 1430.7469 | J45: =+D45*E45 -> 15.5
A46: 12.03.02.17 | B46: =+B26 -> ASISTENTE (CAMPO/CALIDAD/ARQ) | C46: und | D46: 2 | E46: 13.5 | F46: 92.30625 | G46: =+D46*E46*F46 -> 2492.2687 | J46: =+D46*E46 -> 27
A47: 12.03.02.26 | B47: =+B30 -> JEFE DE ALMACEN | C47: und | D47: 1 | E47: 21.5 | F47: 92.30625 | G47: =+D47*E47*F47 -> 1984.5844 | J47: =+D47*E47 -> 21.5
A48: 12.03.02.28 | B48: TOPOGRAFO 1 (cuadrilla 1) | C48: und | D48: 1 | E48: 12 | F48: 92.30625 | G48: =+D48*E48*F48 -> 1107.675 | J48: =+D48*E48 -> 12
A49: 12.03.02.29 | B49: TOPOGRAFO 2 (cuadrilla 2) | C49: und | D49: 1 | E49: 4 | F49: 92.30625 | G49: =+D49*E49*F49 -> 369.225 | J49: =+D49*E49 -> 4
A50: 12.03.03 | B50: IMPRESORA A3 | C50: mes | D50: 1 | E50: 20.5 | F50: 135 | H50: =+D50*E50*F50 -> 2767.5 | J50: =+D50*E50 -> 20.5
A51: 12.03.04 | B51: COMUNICACION (CELULARES) | C51: mes | H51: =SUM(G53:G66) -> 14868.75 | J51: =+D51*E51 -> 0
A52: 12.03.05 | B52: DISGREGADO DE CELULARES | J52: =+D52*E52 -> 0
A53: 12.03.05.01 | B53: =+B15 -> INGENIERO RESIDENTE | D53: 1 | E53: 21.5 | F53: 65 | G53: =+D53*E53*F53 -> 1397.5 | J53: =+D53*E53 -> 21.5
A54: 12.03.05.02 | B54: =+B16 -> INGENIERO DE OFICINA TECNICA | D54: 1 | E54: 21.5 | F54: 65 | G54: =+D54*E54*F54 -> 1397.5 | J54: =+D54*E54 -> 21.5
A55: 12.03.05.03 | B55: =+B17 -> INGENIERO DE CAMPO | D55: 1 | E55: 17.5 | F55: 65 | G55: =+D55*E55*F55 -> 1137.5 | J55: =+D55*E55 -> 17.5
A56: 12.03.05.05 | B56: =+B18 -> INGENIERO DE CALIDAD | D56: 1 | E56: 13.5 | F56: 65 | G56: =+D56*E56*F56 -> 877.5 | J56: =+D56*E56 -> 13.5
B57: INGENIERO DE CALIDAD JUNIOR | D57: 1 | E57: 7 | F57: 65 | G57: =+D57*E57*F57 -> 455 | J57: =+D57*E57 -> 7
A58: 12.03.05.07 | B58: =+B20 -> INGENIERO ELECTROMECANICO | D58: 0.5 | E58: 13.5 | F58: 65 | G58: =+D58*E58*F58 -> 438.75 | J58: =+D58*E58 -> 6.75
A59: 12.03.05.09 | B59: =+B21 -> ARQUITECTO DE ACABADOS | D59: 1 | E59: 13.5 | F59: 65 | G59: =+D59*E59*F59 -> 877.5 | J59: =+D59*E59 -> 13.5
A60: 12.03.05.12 | B60: =+B22 -> PREVENCIONISTA DE RIEGOS - SUBJEFE DE PDR | D60: 1 | E60: 20.5 | F60: 65 | G60: =+D60*E60*F60 -> 1332.5 | J60: =+D60*E60 -> 20.5
A61: 12.03.05.15 | B61: =+B23 -> ADMINISTRADOR DE OBRA | D61: 1 | E61: 21.5 | F61: 65 | G61: =+D61*E61*F61 -> 1397.5 | J61: =+D61*E61 -> 21.5
A62: 12.03.05.17 | B62: =+B26 -> ASISTENTE (CAMPO/CALIDAD/ARQ) | D62: 2 | E62: 13.5 | F62: 65 | G62: =+D62*E62*F62 -> 1755 | J62: =+D62*E62 -> 27
A63: 12.03.05.25 | B63: =+B30 -> JEFE DE ALMACEN | D63: 1 | E63: 21.5 | F63: 65 | G63: =+D63*E63*F63 -> 1397.5 | J63: =+D63*E63 -> 21.5
A64: 12.03.05.27 | B64: ASISTENTES DE PDR (01)- ENTRA DESPUES DE LA CIM HASTA EL FINAL | D64: 1 | E64: 19 | F64: 65 | G64: =+D64*E64*F64 -> 1235 | J64: =+D64*E64 -> 19
A65: 12.03.05.28 | B65: AYUDANTE DE PDR N°1 (01) | D65: 1 | E65: 10 | F65: 65 | G65: =+D65*E65*F65 -> 650 | J65: =+D65*E65 -> 10
A66: 12.03.05.29 | B66: AYUDANTE DE PDR N°2 (01) | D66: 1 | E66: 8 | F66: 65 | G66: =+D66*E66*F66 -> 520 | J66: =+D66*E66 -> 8
A67: 12.03.06 | B67: COMUNICACION (RADIOS) | C67: und | D67: 15 | E67: 1 | F67: 825 | H67: =+D67*E67*F67 -> 12375 | J67: =+D67*E67 -> 15
A68: 12.03.07 | B68: COMUNICACION TELEFONO EXTERNO / INTERNET | C68: und | D68: 1 | E68: 20.5 | F68: 240 | H68: =+D68*E68*F68 -> 4920 | J68: =+D68*E68 -> 20.5
A69: 12.03.08 | B69: ESCRITORIOS Y SILLAS (CONTRATISTA) | C69: und | D69: 15 | E69: 1 | F69: 250 | H69: =+D69*E69*F69 -> 3750 | J69: =+D69*E69 -> 15
A70: 12.03.09 | B70: MESAS DE TRABAJO Y DE REUNION | C70: und | D70: 1 | E70: 2 | F70: 500 | H70: =+D70*E70*F70 -> 1000 | J70: =+D70*E70 -> 2
A71: 12.03.10 | B71: UTILES DE OFICINA Y ECONOMATO | C71: glb | D71: 1 | E71: 20.5 | F71: 350 | H71: =+D71*E71*F71 -> 7175 | J71: =+D71*E71 -> 20.5
A72: 12.04 | B72: VARIOS | I72: =SUM(H73:H88) -> 486064.67 | J72: =+D72*E72 -> 0
A73: 12.04.01 | B73: INSUMOS PARA LIMPIEZA | C73: mes | D73: 1 | E73: 20.5 | F73: 250 | H73: =+D73*E73*F73 -> 5125 | J73: =+D73*E73 -> 20.5
A74: 12.04.02 | B74: PERSONAL DE LIMPIEZA (OFICINAS) | C74: mes | D74: 0 | E74: 20.5 | F74: 1950 | H74: =+D74*E74*F74 -> 0 | J74: =+D74*E74 -> 0
A75: 12.04.03 | B75: FOTOCOPIADO | C75: mes | D75: 1 | E75: 20.5 | F75: 300 | H75: =+D75*E75*F75 -> 6150 | J75: =+D75*E75 -> 20.5
A76: 12.04.04 | B76: COPIA DE PLANOS Y PLANOS DE REPLANTEO DE OBRA | C76: mes | D76: 1 | E76: 20.5 | F76: 450 | H76: =+D76*E76*F76 -> 9225 | J76: =+D76*E76 -> 20.5
A77: 12.04.05 | B77: PLANOS Y EXPEDIENTE FIRMA DE CONTRATO (3 COPIAS) | C77: mes | D77: 1 | E77: 3 | F77: 1200 | H77: =+D77*E77*F77 -> 3600 | J77: =+D77*E77 -> 3
A78: 12.04.06 | B78: DOSSIER DE CALIDAD | C78: glb | D78: 1 | E78: 1 | F78: 3000 | H78: =+D78*E78*F78 -> 3000 | J78: =+D78*E78 -> 1
A79: 12.04.07 | B79: GASTOS ADMINISTRATIVOS | C79: mes | D79: 1 | E79: 20.5 | F79: 400 | H79: =+D79*E79*F79 -> 8200 | J79: =+D79*E79 -> 20.5
A80: 12.04.08 | B80: AGUA POTABLE PARA PERSONAL | C80: mes | D80: 1 | E80: 20.5 | F80: 522.66667 | H80: =+D80*E80*F80 -> 10714.667 | J80: =+D80*E80 -> 20.5
A81: 12.04.09 | B81: BOTIQUIN DE OBRA | C81: mes | D81: 1 | E81: 2 | F81: 300 | H81: =+D81*E81*F81 -> 600 | J81: =+D81*E81 -> 2
A82: 12.04.10 | B82: MANTENIMIENTO DE EQUIPOS PROPIO | C82: glb | D82: 1 | E82: 1 | F82: 3000 | H82: =+D82*E82*F82 -> 3000 | J82: =+D82*E82 -> 1
A83: 12.04.11 | B83: MOVILIDAD | C83: mes | D83: 1 | E83: 20.5 | F83: 500 | H83: =+D83*E83*F83 -> 10250 | J83: =+D83*E83 -> 20.5
A84: 12.04.12 | B84: CONTRIBUCION OFICINA CENTRAL | C84: mes | D84: 1 | E84: 20.5 | F84: 20000 | H84: =+D84*E84*F84 -> 410000 | J84: =+D84*E84 -> 20.5
... A88: 12.04.16 | B88: GESTION - LUZ DEL SUR, SEDAPAL | C88: glb | D88: 0 | E88: 1 | F88: 4500 | H88: =+D88*E88*F88 -> 0 | J88: =+D88*E88 -> 0
A89: 12.05 | B89: PAZ SOCIAL | I89: =SUM(H90) -> 0 | J89: =+D89*E89 -> 0
A90: 12.05.01 | B90: PAZ SOCIAL - PARTIDA ADMINISTRADA | C90: mes | D90: 0 | E90: 8.5 | F90: 2800 | H90: =+D90*E90*F90 -> 0 | J90: =+D90*E90 -> 0
A91: 12.06 | B91: GASTOS FIJOS | I91: =SUM(H92:H124) -> 275540.98 | J91: =+D91*E91 -> 0
A92: 12.06.01 | B92: POLIZA CAR+RC | C92: glb | D92: 1 | E92: 1 | F92: 67854.751 | H92: =+D92*E92*F92 -> 67854.751 | J92: =+D92*E92 -> 1
A93: 12.06.02 | B93: POLIZA 3D | C93: glb | D93: 1 | E93: 1 | F93: 2000 | H93: =+D93*E93*F93 -> 2000 | J93: =+D93*E93 -> 1
A94: 12.06.08 | B94: SCTR (Pensión y Salud) - Staff Obra | C94: mes | H94: =SUM(G96:G118) -> 21462.399 | J94: =+D94*E94 -> 0
A95: 12.06.09 | B95: DISGREGADO DE SCTR | J95: =+D95*E95 -> 0
A96: 12.06.09.01 | B96: =+B14 -> GERENTE DE PROYECTOS | D96: 1 | E96: 20.5 | F96: 16200 | G96: 2656.8 | J96: =+D96*E96 -> 20.5
A97: 12.06.09.02 | B97: =+B15 -> INGENIERO RESIDENTE | D97: 1 | E97: 21.5 | F97: 10500 | G97: 1806 | J97: =+D97*E97 -> 21.5
A98: 12.06.09.03 | B98: =+B16 -> INGENIERO DE OFICINA TECNICA | D98: 1 | E98: 21.5 | F98: 10500.004 | G98: 1806.0007 | J98: =+D98*E98 -> 21.5
A99: 12.06.09.04 | B99: =+B17 -> INGENIERO DE CAMPO | D99: 1 | E99: 17.5 | F99: 7500 | G99: 1050 | J99: =+D99*E99 -> 17.5
A100: 12.06.09.06 | B100: INGENIERO DE CALIDAD | D100: 1 | E100: 13.5 | F100: 7500 | G100: 810 | J100: =+D100*E100 -> 13.5
B101: INGENIERO DE CALIDAD JUNIOR | D101: 1 | E101: 7 | F101: 5250 | G101: 294 | J101: =+D101*E101 -> 7
A102: 12.06.09.08 | B102: =+B20 -> INGENIERO ELECTROMECANICO | D102: 0.5 | E102: 13.5 | F102: 10500.004 | G102: 567.00023 | J102: =+D102*E102 -> 6.75
A103: 12.06.09.10 | B103: =+B21 -> ARQUITECTO DE ACABADOS | D103: 1 | E103: 13.5 | F103: 9000 | G103: 972 | J103: =+D103*E103 -> 13.5
A104: 12.06.09.13 | B104: =+B22 -> PREVENCIONISTA DE RIEGOS - SUBJEFE DE PDR | D104: 1 | E104: 20.5 | F104: 6750 | G104: 1107 | J104: =+D104*E104 -> 20.5
A105: 12.06.09.16 | B105: =+B23 -> ADMINISTRADOR DE OBRA | D105: 1 | E105: 21.5 | F105: 6491.2603 | G105: 1116.4968 | J105: =+D105*E105 -> 21.5
A106: 12.06.09.17 | B106: INGENIERO BIM | D106: 1 | E106: 15.5 | F106: 6750 | G106: 837 | J106: =+D106*E106 -> 15.5
A107: 12.06.09.18 | B107: =+B26 -> ASISTENTE (CAMPO/CALIDAD/ARQ) | D107: 2 | E107: 13.5 | F107: 3990 | G107: 861.84 | J107: =+D107*E107 -> 27
...

Sheet EST SOTANO
C2: ESTRUCTURAS SÓTANOS
C4: Presupuesto | D4: =OP!$B$4 -> #REF!
C5: Subpresupuesto | D5: =+$C$2 -> ESTRUCTURAS SÓTANOS
C6: Cliente | D6: =OP!$B$6 -> #REF!
C7: Lugar | D7: =OP!$B$7 -> #REF!
C8: Fecha | D8: =#REF! -> #REF!
C10: ITEM | D10: DESCRIPCION | E10: UND | F10: METRADO | G10: P.U. (PEN) | H10: P.U. (USD) | I10: P.U. TOTAL (PEN) | J10: PRECIO PARCIAL (PEN) | K10: PRECIO PARCIAL (USD) | L10: PRECIO TOTAL (PEN) | M10: TOTAL
C11: 03 | D11: =$C$2 -> ESTRUCTURAS SÓTANOS
C12: =C11+0.01 -> 3.01 | D12: OBRAS PRELIMINARES MOVIMIENTOS DE TIERRA | I12: =IFERROR(IF(E12<>0,G12+H12*TC," ")," ") | J12: =IFERROR(IF($F12=0,"",$F12*G12),"") | K12: =IFERROR(IF($F12=0,"",$F12*H12),"") | L12: =IFERROR(IF(F12<>0,(F12*I12)," "),0) | M12: =SUM(J12:J17)+SUM(K12:K17)*TC -> #REF!
C13: =C12+0.0001 -> 3.0101 | D13: MOVILIZACION Y DESMOVILIZACION DE EQUIPOS MOVIMIENTO TIERRAS | E13: glb | F13: 1 | G13: 6000 | I13: =+ROUND(G13+H13*TC,2) -> #REF! | J13: =+ROUND(F13*G13,2) -> 6000 | K13: =+ROUND(F13*H13,2) -> 0 | L13: =+ROUND(J13+K13*TC,2) -> #REF!
C14: =C13+0.0001 -> 3.0102 | D14: EXTRACCION DE 2 MAQUINAS EXCAVADORAS (IZAJE) | E14: glb | F14: 2 | G14: 6000 | I14: =+ROUND(G14+H14*TC,2) -> #REF! | J14: =+ROUND(F14*G14,2) -> 12000 | K14: =+ROUND(F14*H14,2) -> 0 | L14: =+ROUND(J14+K14*TC,2) -> #REF!
C15: =C14+0.0001 -> 3.0103 | D15: INSTALACION Y DESISTALACION DE PLATAFORMA | E15: glb | F15: 1 | G15: 11000 | I15: =+ROUND(G15+H15*TC,2) -> #REF! | J15: =+ROUND(F15*G15,2) -> 11000 | K15: =+ROUND(F15*H15,2) -> 0 | L15: =+ROUND(J15+K15*TC,2) -> #REF!
C16: =C15+0.0001 -> 3.0104 | D16: EXTRACCION DE EQUIPOS PERFORACION CON GRUAS | E16: glb | F16: 4 | H16: 720 | I16: =+ROUND(G16+H16*TC,2) -> #REF! | J16: =+ROUND(F16*G16,2) -> 0 | K16: =+ROUND(F16*H16,2) -> 2880 | L16: =+ROUND(J16+K16*TC,2) -> #REF!
C17: =C16+0.0001 -> 3.0105 | D17: CONTROL DE POLVOS (AGUA EN CISTERNA) | E17: vje | F17: 13 | G17: 340 | I17: =+ROUND(G17+H17*TC,2) -> #REF! | J17: =+ROUND(F17*G17,2) -> 4420 | K17: =+ROUND(F17*H17,2) -> 0 | L17: =+ROUND(J17+K17*TC,2) -> #REF!
C18: =C12+0.01 -> 3.02 | D18: MOVIMIENTO DE TIERRAS | M18: =SUM(J18:J44)+SUM(K18:K44)*TC -> #REF!
C19: =C18+0.0001 -> 3.0201 | D19: EXCAVACIÓN Y ELIMINACIÓN MASIVA POR NIVEL
C20: =C19+0.000001 -> 3.020101 | D20: CORTE Y ELIMINACION DE +0.00 a -3.57 (SOTANO 01) | E20: m3 | F20: 2878.06 | G20: 23 | I20: =+ROUND(G20+H20*TC,2) -> #REF! | J20: =+ROUND(F20*G20,2) -> 66195.38 | K20: =+ROUND(F20*H20,2) -> 0 | L20: =+ROUND(J20+K20*TC,2) -> #REF!
C21: =C20+0.000001 -> 3.020102 | D21: CORTE Y ELIMINACION DE -3.57 a -6.38 (SOTANO 02) | E21: m3 | F21: 2265.37 | G21: 24 | I21: =+ROUND(G21+H21*TC,2) -> #REF! | J21: =+ROUND(F21*G21,2) -> 54368.88 | K21: =+ROUND(F21*H21,2) -> 0 | L21: =+ROUND(J21+K21*TC,2) -> #REF!
C22: =C21+0.000001 -> 3.020103 | D22: CORTE Y ELIMINACION DE -6.38 a -9.08 (SOTANO 03) | E22: m3 | F22: 2176.69 | G22: 25 | I22: =+ROUND(G22+H22*TC,2) -> #REF! | J22: =+ROUND(F22*G22,2) -> 54417.25 | K22: =+ROUND(F22*H22,2) -> 0 | L22: =+ROUND(J22+K22*TC,2) -> #REF!
C23: =C22+0.000001 -> 3.020104 | D23: CORTE Y ELIMINACION DE -9.08 a -11.78 (SOTANO 04) | E23: m3 | F23: 2176.69 | G23: 26 | I23: =+ROUND(G23+H23*TC,2) -> #REF! | J23: =+ROUND(F23*G23,2) -> 56593.94 | K23: =+ROUND(F23*H23,2) -> 0 | L23: =+ROUND(J23+K23*TC,2) -> #REF!
C24: =C23+0.000001 -> 3.020105 | D24: CORTE Y ELIMINACION DE -11.78 a -14.48 (SOTANO 05) | E24: m3 | F24: 2176.69 | G24: 27 | I24: =+ROUND(G24+H24*TC,2) -> #REF! | J24: =+ROUND(F24*G24,2) -> 58770.63 | K24: =+ROUND(F24*H24,2) -> 0 | L24: =+ROUND(J24+K24*TC,2) -> #REF!
C25: =C24+0.000001 -> 3.020106 | D25: CORTE Y ELIMINACION DE -14.48 a -17.84 (SOTANO 06) CON GRUA Y BALDE | E25: m3 | F25: 1918.76 | G25: 40 | I25: =+ROUND(G25+H25*TC,2) -> #REF! | J25: =+ROUND(F25*G25,2) -> 76750.4 | K25: =+ROUND(F25*H25,2) -> 0 | L25: =+ROUND(J25+K25*TC,2) -> #REF!
C26: =C19+0.0001 -> 3.0202 | D26: EXCAVACIÓN Y ELIMINACIÓN LOCALIZADA
C27: =C26+0.000001 -> 3.020201 | D27: EXCAVACION Y ELIIMINACION DE ZAPATAS, FALSAS ZAPATAS Y CIMIENTOS (N -20.60) | E27: m3 | F27: 783.45 | G27: 40 | I27: =+ROUND(G27+H27*TC,2) -> #REF! | J27: =+ROUND(F27*G27,2) -> 31338 | K27: =+ROUND(F27*H27,2) -> 0 | L27: =+ROUND(J27+K27*TC,2) -> #REF!
C28: =C27+0.000001 -> 3.020202 | D28: EXCAVACION Y ELIIMINACION DE CISTERNA Y CUARTO DE BOMBAS (N -19.7) | E28: m3 | F28: 993.48 | G28: 40 | I28: =+ROUND(G28+H28*TC,2) -> #REF! | J28: =+ROUND(F28*G28,2) -> 39739.2 | K28: =+ROUND(F28*H28,2) -> 0 | L28: =+ROUND(J28+K28*TC,2) -> #REF!
C29: =C28+0.000001 -> 3.020203 | D29: EXCAVACION LOCALIZADA PARA VIGAS DE CIMENTACION | E29: m3 | F29: 7.56 | G29: 38.75 | I29: =+ROUND(G29+H29*TC,2) -> #REF! | J29: =+ROUND(F29*G29,2) -> 292.95 | K29: =+ROUND(F29*H29,2) -> 0 | L29: =+ROUND(J29+K29*TC,2) -> #REF!
C30: =C29+0.000001 -> 3.020204 | D30: EXCAVACION LOCALIZADA PARA CIMIENTOS (BATEA DE CIMENTACION) | E30: m3 | F30: 13.36 | G30: 38.75 | I30: =+ROUND(G30+H30*TC,2) -> #REF! | J30: =+ROUND(F30*G30,2) -> 517.7 | K30: =+ROUND(F30*H30,2) -> 0 | L30: =+ROUND(J30+K30*TC,2) -> #REF!
C31: =C30+0.000001 -> 3.020205 | D31: EXCAVACION LOCALIZADA PARA POZO SUMIDERO Y TRAMPA DE GRASA | E31: m3 | F31: 6.62 | G31: 38.75 | I31: =+ROUND(G31+H31*TC,2) -> #REF! | J31: =+ROUND(F31*G31,2) -> 256.53 | K31: =+ROUND(F31*H31,2) -> 0 | L31: =+ROUND(J31+K31*TC,2) -> #REF!
C32: =C31+0.000001 -> 3.020206 | D32: ACARREO Y ELIMINACION DE MATERIAL EXCEDENTE | E32: m3 | F32: 35.8 | G32: 38.08 | I32: =+ROUND(G32+H32*TC,2) -> #REF! | J32: =+ROUND(F32*G32,2) -> 1363.26 | K32: =+ROUND(F32*H32,2) -> 0 | L32: =+ROUND(J32+K32*TC,2) -> #REF!
C33: =C26+0.0001 -> 3.0203 | D33: ELIMINACIÓN DE CIMENTACIÓN EXISTENTE (NO SE CONSIDERA)
C34: =C33+0.000001 -> 3.020301 | D34: DEMOLICIÓN DE CIMENTACIÓN DE VECINOS | E34: ml | F34: 0 | G34: 80 | I34: =+ROUND(G34+H34*TC,2) -> #REF! | J34: =+ROUND(F34*G34,2) -> 0 | K34: =+ROUND(F34*H34,2) -> 0 | L34: =+ROUND(J34+K34*TC,2) -> #REF!
C35: =C34+0.000001 -> 3.020302 | D35: ELIMINACIÓN DE CIMENTACIÓN | E35: m3 | F35: 0 | G35: 35 | I35: =+ROUND(G35+H35*TC,2) -> #REF! | J35: =+ROUND(F35*G35,2) -> 0 | K35: =+ROUND(F35*H35,2) -> 0 | L35: =+ROUND(J35+K35*TC,2) -> #REF!
C36: =C33+0.0001 -> 3.0204 | D36: RELLENO Y COMPACTACIÓN
C37: =C36+0.000001 -> 3.020401 | D37: RELLENO COMPACTADO CON MATERIAL PROPIO | E37: m3 | F37: 144.49 | G37: 52 | I37: =+ROUND(G37+H37*TC,2) -> #REF! | J37: =+ROUND(F37*G37,2) -> 7513.48 | K37: =+ROUND(F37*H37,2) -> 0 | L37: =+ROUND(J37+K37*TC,2) -> #REF!
C38: =C37+0.000001 -> 3.020402 | D38: RELLENO BAJO RAMPA CON MATERIAL PROPIO | E38: m3 | F38: 13.25 | G38: 52 | I38: =+ROUND(G38+H38*TC,2) -> #REF! | J38: =+ROUND(F38*G38,2) -> 689 | K38: =+ROUND(F38*H38,2) -> 0 | L38: =+ROUND(J38+K38*TC,2) -> #REF!
C39: =C36+0.0001 -> 3.0205 | D39: NIVELACIÓN, APISONADO Y BASE DE AFIRMADO | I39: =+ROUND(G39+H39*TC,2) -> #REF! | J39: =+ROUND(F39*G39,2) -> 0 | K39: =+ROUND(F39*H39,2) -> 0 | L39: =+ROUND(J39+K39*TC,2) -> #REF!
C40: =C39+0.000001 -> 3.020501 | D40: NIVELACION Y COMPACTACION DE SUBRASANTE | E40: m2 | F40: 698.47 | G40: 6.39 | I40: =+ROUND(G40+H40*TC,2) -> #REF! | J40: =+ROUND(F40*G40,2) -> 4463.22 | K40: =+ROUND(F40*H40,2) -> 0 | L40: =+ROUND(J40+K40*TC,2) -> #REF!
C41: =C40+0.000001 -> 3.020502 | D41: BASE DE AFIRMADO COMPACTADO, E=15CM (conforme a EMS) | E41: m2 | F41: 698.47 | G41: 38.21 | I41: =+ROUND(G41+H41*TC,2) -> #REF! | J41: =+ROUND(F41*G41,2) -> 26688.54 | K41: =+ROUND(F41*H41,2) -> 0 | L41: =+ROUND(J41+K41*TC,2) -> #REF!
C42: =C39+0.0001 -> 3.0206 | D42: OTROS | I42: =+ROUND(G42+H42*TC,2) -> #REF! | J42: =+ROUND(F42*G42,2) -> 0 | K42: =+ROUND(F42*H42,2) -> 0 | L42: =+ROUND(J42+K42*TC,2) -> #REF!
C43: =C42+0.000001 -> 3.020601 | D43: ALQUILER DE EXCAVADORA MOVIMIENTO DE DADOS, RAMPA, ETC | E43: hm | F43: 550 | G43: 250 | I43: =+ROUND(G43+H43*TC,2) -> #REF! | J43: =+ROUND(F43*G43,2) -> 137500 | K43: =+ROUND(F43*H43,2) -> 0 | L43: =+ROUND(J43+K43*TC,2) -> #REF!
C44: =C43+0.000001 -> 3.020602 | D44: VIGIA P/MAQ EXCAVADORA DURANTE LA EXCAVACION | E44: mes | F44: 5.5 | G44: 3837.6 | I44: =+ROUND(G44+H44*TC,2) -> #REF! | J44: =+ROUND(F44*G44,2) -> 21106.8 | K44: =+ROUND(F44*H44,2) -> 0 | L44: =+ROUND(J44+K44*TC,2) -> #REF!
C45: =C18+0.01 -> 3.03 | D45: CONCRETO SIMPLE | M45: =SUM(J45:J50)+SUM(K45:K50)*TC -> #REF!
C46: =C45+0.0001 -> 3.0301 | D46: SOLADOS
B47: SOLADO | C47: =C46+0.000001 -> 3.030101 | D47: CONCRETO PREMEZCLADO, CEMENTO TIPO I, SOLADO f'c=100 kg/cm2 | E47: m2 | F47: 567.07 | G47: 28.79 | I47: =+ROUND(G47+H47*TC,2) -> #REF! | J47: =+ROUND(F47*G47,2) -> 16325.95 | K47: =+ROUND(F47*H47,2) -> 0 | L47: =+ROUND(J47+K47*TC,2) -> #REF!
C48: =C46+0.0001 -> 3.0302 | D48: FALSA ZAPATA
B49: CIMENTACIÓN | C49: =C48+0.000001 -> 3.030201 | D49: CONCRETO PREMEZCLADO, CEMENTO TIPO I, FALZA ZAPATAS 1:12 + 30%P.G. | E49: m3 | F49: 22.2 | G49: 298.43 | I49: =+ROUND(G49+H49*TC,2) -> #REF! | J49: =+ROUND(F49*G49,2) -> 6625.15 | K49: =+ROUND(F49*H49,2) -> 0 | L49: =+ROUND(J49+K49*TC,2) -> #REF!
A50: E | C50: =C49+0.000001 -> 3.030202 | D50: ENCOFRADO DE FALSA ZAPATAS | E50: m2 | F50: 25.48 | G50: 43 | I50: =+ROUND(G50+H50*TC,2) -> #REF! | J50: =+ROUND(F50*G50,2) -> 1095.64 | K50: =+ROUND(F50*H50,2) -> 0 | L50: =+ROUND(J50+K50*TC,2) -> #REF!
C51: =C45+0.01 -> 3.04 | D51: CONCRETO ARMADO | M51: =SUM(J51:J273)+SUM(K51:K273)*TC -> #REF!
C52: =C51+0.0001 -> 3.0401 | D52: CIMIENTOS ARMADOS MURO PANTALLA
A53: C | B53: MURO PANTALLA | C53: =C52+0.000001 -> 3.040101 | D53: CONCRETO PREMEZCLADO, CEMENTO TIPO I, CIMIENTOS REFORZADOS f'c=210 kg/cm2 | E53: m3 | F53: 0 | G53: 471.04 | I53: =+ROUND(G53+H53*TC,2) -> #REF! | J53: =+ROUND(F53*G53,2) -> 0 | K53: =+ROUND(F53*H53,2) -> 0 | L53: =+ROUND(J53+K53*TC,2) -> #REF!
A54: C | B54: MURO PANTALLA | C54: =C53+0.000001 -> 3.040102 | D54: CONCRETO PREMEZCLADO, CEMENTO TIPO I, CIMIENTOS REFORZADOS f'c=280 kg/cm2 | E54: m3 | F54: 256.96 | G54: 508.15 | I54: =+ROUND(G54+H54*TC,2) -> #REF! | J54: =+ROUND(F54*G54,2) -> 130574.22 | K54: =+ROUND(F54*H54,2) -> 0 | L54: =+ROUND(J54+K54*TC,2) -> #REF!
A55: E | B55: MP | C55: =C54+0.000001 -> 3.040103 | D55: ENCOFRADO Y DESENCOFRADO PARA CIMIENTOS REFORZADOS | E55: m2 | F55: 160.7 | G55: 45 | I55: =+ROUND(G55+H55*TC,2) -> #REF! | J55: =+ROUND(F55*G55,2) -> 7231.5 | K55: =+ROUND(F55*H55,2) -> 0 | L55: =+ROUND(J55+K55*TC,2) -> #REF!
A56: A | B56: MP | C56: =C55+0.000001 -> 3.040104 | D56: ACERO DE REFUERZO FY= 4200 kg/cm2, GRADO 60 (MURO PANTALLA) | E56: kg | F56: 17691.96 | G56: 1.19 | H56: 0.91 | I56: =+ROUND(G56+H56*TC,2) -> #REF! | J56: =+ROUND(F56*G56,2) -> 21053.43 | K56: =+ROUND(F56*H56,2) -> 16099.68 | L56: =+ROUND(J56+K56*TC,2) -> #REF!
C57: =C56+0.000001 -> 3.040105 | D57: CURADO DE ELEMENTOS ESTRUCTURALES EXPUESTOS | E57: m2 | F57: 160.7 | G57: 1.44 | I57: =+ROUND(G57+H57*TC,2) -> #REF! | J57: =+ROUND(F57*G57,2) -> 231.41 | K57: =+ROUND(F57*H57,2) -> 0 | L57: =+ROUND(J57+K57*TC,2) -> #REF!
C58: =C57+0.000001 -> 3.040106 | D58: PINTURA ASFALTICA EN CIMENTACIONES | E58: m2 | F58: 342.19 | G58: 20.09 | I58: =+ROUND(G58+H58*TC,2) -> #REF! | J58: =+ROUND(F58*G58,2) -> 6874.6 | K58: =+ROUND(F58*H58,2) -> 0 | L58: =+ROUND(J58+K58*TC,2) -> #REF!
C59: =C52+0.0001 -> 3.0402 | D59: MURO PANTALLA (ANCLADO)
A60: C | B60: MURO PANTALLA | C60: =C59+0.000001 -> 3.040201 | D60: CONCRETO PREMEZCLADO, CEMENTO TIPO I, MURO PANTALLA f'c=350 kg/cm2 | E60: m3 | F60: 383.09 | G60: 622.76 | I60: =+ROUND(G60+H60*TC,2) -> #REF! | J60: =+ROUND(F60*G60,2) -> 238573.13 | K60: =+ROUND(F60*H60,2) -> 0 | L60: =+ROUND(J60+K60*TC,2) -> #REF!
A61: C | B61: MURO PANTALLA | D61: CONCRETO PREMEZCLADO, CEMENTO TIPO I, MURO PANTALLA f'c=420 kg/cm2 | E61: m3 | F61: 342.83 | G61: 644.43 | I61: =+ROUND(G61+H61*TC,2) -> #REF! | J61: =+ROUND(F61*G61,2) -> 220929.94 | K61: =+ROUND(F61*H61,2) -> 0 | L61: =+ROUND(J61+K61*TC,2) -> #REF!
A62: E | C62: =C60+0.000001 -> 3.040202 | D62: ENCOFRADO Y DESENCOFRADO PARA MURO PANTALLA | E62: m2 | F62: 2159.51 | G62: 58 | I62: =+ROUND(G62+H62*TC,2) -> #REF! | J62: =+ROUND(F62*G62,2) -> 125251.58 | K62: =+ROUND(F62*H62,2) -> 0 | L62: =+ROUND(J62+K62*TC,2) -> #REF!
A63: E | C63: =C62+0.000001 -> 3.040203 | D63: ENCOFRADO Y DESENCOFRADO LATERALES | E63: m2 | F63: 201.38 | G63: 50.5 | I63: =+ROUND(G63+H63*TC,2) -> #REF! | J63: =+ROUND(F63*G63,2) -> 10169.69 | K63: =+ROUND(F63*H63,2) -> 0 | L63: =+ROUND(J63+K63*TC,2) -> #REF!
A64: A | B64: MP | C64: =C63+0.000001 -> 3.040204 | D64: ACERO DE REFUERZO FY= 4200 kg/cm2, GRADO 60 (MURO PANTALLA) | E64: kg | F64: 75073.83 | G64: 1.19 | H64: 0.91 | I64: =+ROUND(G64+H64*TC,2) -> #REF! | J64: =+ROUND(F64*G64,2) -> 89337.86 | K64: =+ROUND(F64*H64,2) -> 68317.19 | L64: =+ROUND(J64+K64*TC,2) -> #REF!
C65: =C64+0.000001 -> 3.040205 | D65: RECARGO POR CONSUMO MINIMO DE BOMBA | E65: m3 | F65: 853 | G65: 37.5 | I65: =+ROUND(G65+H65*TC,2) -> #REF! | J65: =+ROUND(F65*G65,2) -> 31987.5 | K65: =+ROUND(F65*H65,2) -> 0 | L65: =+ROUND(J65+K65*TC,2) -> #REF!
A66: C | B66: MURO PANTALLA | C66: =C65+0.000001 -> 3.040206 | D66: CONCRETO PREMEZCLADO, CEMENTO TIPO I, EN CACHIMBAS f'c=350 kg/cm2 | E66: m3 | F66: 41.14 | G66: 485.71 | I66: =+ROUND(G66+H66*TC,2) -> #REF! | J66: =+ROUND(F66*G66,2) -> 19982.11 | K66: =+ROUND(F66*H66,2) -> 0 | L66: =+ROUND(J66+K66*TC,2) -> #REF!
A67: E | C67: =C66+0.000001 -> 3.040207 | D67: ENCOFRADO Y DESENCOFRADO DE CACHIMBAS | E67: m2 | F67: 205.68 | G67: 50 | I67: =+ROUND(G67+H67*TC,2) -> #REF! | J67: =+ROUND(F67*G67,2) -> 10284 | K67: =+ROUND(F67*H67,2) -> 0 | L67: =+ROUND(J67+K67*TC,2) -> #REF!
C68: =C67+0.000001 -> 3.040208 | D68: PICADO DE CACHIMBAS DE MUROS PANTALLAS | E68: m3 | F68: 41.14 | G68: 105.16 | I68: =+ROUND(G68+H68*TC,2) -> #REF! | J68: =+ROUND(F68*G68,2) -> 4326.28 | K68: =+ROUND(F68*H68,2) -> 0 | L68: =+ROUND(J68+K68*TC,2) -> #REF!
C69: =C68+0.000001 -> 3.040209 | D69: PICADO DE PESTAÑAS DE ORIFICIO DE ANCLAJE | E69: und | F69: 147 | G69: 33.24 | I69: =+ROUND(G69+H69*TC,2) -> #REF! | J69: =+ROUND(F69*G69,2) -> 4886.28 | K69: =+ROUND(F69*H69,2) -> 0 | L69: =+ROUND(J69+K69*TC,2) -> #REF!
C70: =C69+0.000001 -> 3.04021 | D70: TECNOPOR EN ENCUENTRO DE LOSAS CON MURO PANTALLA | E70: ml | F70: 580.05 | G70: 10.77 | I70: =+ROUND(G70+H70*TC,2) -> #REF! | J70: =+ROUND(F70*G70,2) -> 6247.14 | K70: =+ROUND(F70*H70,2) -> 0 | L70: =+ROUND(J70+K70*TC,2) -> #REF!
C71: =C70+0.000001 -> 3.040211 | D71: RETIRO DE TECNOPOR Y ESCARIFICADO EN ENCUENTRO DE LOSAS CON MURO PANTALLA | E71: ml | F71: 580.05 | G71: 7.37 | I71: =+ROUND(G71+H71*TC,2) -> #REF! | J71: =+ROUND(F71*G71,2) -> 4274.97 | K71: =+ROUND(F71*H71,2) -> 0 | L71: =+ROUND(J71+K71*TC,2) -> #REF!
C72: =C71+0.000001 -> 3.040212 | D72: EPOXICO DE UNION Y ESCARIFICADO ENTRE LOSAS DE TECHO DE SOTANOS Y MURO PANTALLA | E72: ml | F72: 580.05 | G72: 44.63 | I72: =+ROUND(G72+H72*TC,2) -> #REF! | J72: =+ROUND(F72*G72,2) -> 25887.63 | K72: =+ROUND(F72*H72,2) -> 0 | L72: =+ROUND(J72+K72*TC,2) -> #REF!
C73: =C72+0.000001 -> 3.040213 | D73: PERFILADO DE BANQUETAS Y TALUDES | E73: m2 | F73: 2159.51 | G73: 7.5 | I73: =+ROUND(G73+H73*TC,2) -> #REF! | J73: =+ROUND(F73*G73,2) -> 16196.33 | K73: =+ROUND(F73*H73,2) -> 0 | L73: =+ROUND(J73+K73*TC,2) -> #REF!
C74: =C73+0.000001 -> 3.040214 | D74: PAÑETEO DE MUROS PANTALLA | E74: m2 | F74: 2159.51 | G74: 16.27 | I74: =+ROUND(G74+H74*TC,2) -> #REF! | J74: =+ROUND(F74*G74,2) -> 35135.23 | K74: =+ROUND(F74*H74,2) -> 0 | L74: =+ROUND(J74+K74*TC,2) -> #REF!
C75: =C74+0.000001 -> 3.040215 | D75: PLASTICO CONTRA TERRENO | E75: m2 | F75: 2159.51 | G75: 2.51 | I75: =+ROUND(G75+H75*TC,2) -> #REF! | J75: =+ROUND(F75*G75,2) -> 5420.37 | K75: =+ROUND(F75*H75,2) -> 0 | L75: =+ROUND(J75+K75*TC,2) -> #REF!
C76: =C75+0.000001 -> 3.040216 | D76: ANCLAJE 5/8", ENCUENTRO DE LOSAS CON MUROS | E76: und | F76: 1161 | G76: 35.15 | H76: 1.35 | I76: =+ROUND(G76+H76*TC,2) -> #REF! | J76: =+ROUND(F76*G76,2) -> 40809.15 | K76: =+ROUND(F76*H76,2) -> 1567.35 | L76: =+ROUND(J76+K76*TC,2) -> #REF!
C77: =C76+0.000001 -> 3.040217 | D77: RESANE DE ORIFICIO DE ANCLAJE | E77: und | F77: 147 | G77: 49.12 | I77: =+ROUND(G77+H77*TC,2) -> #REF! | J77: =+ROUND(F77*G77,2) -> 7220.64 | K77: =+ROUND(F77*H77,2) -> 0 | L77: =+ROUND(J77+K77*TC,2) -> #REF!
C78: =C77+0.000001 -> 3.040218 | D78: RESANE DE CACHIMBAS | E78: ml | F78: 514.2 | G78: 23.93 | I78: =+ROUND(G78+H78*TC,2) -> #REF! | J78: =+ROUND(F78*G78,2) -> 12304.81 | K78: =+ROUND(F78*H78,2) -> 0 | L78: =+ROUND(J78+K78*TC,2) -> #REF!
C79: =C78+0.000001 -> 3.040219 | D79: CURADO DE ELEMENTOS ESTRUCTURALES EXPUESTOS | E79: m2 | F79: 2159.51 | G79: 1.44 | I79: =+ROUND(G79+H79*TC,2) -> #REF! | J79: =+ROUND(F79*G79,2) -> 3109.69 | K79: =+ROUND(F79*H79,2) -> 0 | L79: =+ROUND(J79+K79*TC,2) -> #REF!
C80: =C59+0.0001 -> 3.0403 | D80: MURO PERIMETRAL (SIN ANCLAJES)
A81: C | C81: =C80+0.000001 -> 3.040301 | D81: CONCRETO PREMEZCLADO, CEMENTO TIPO I, MURO PERIMETRAL f'c=350 kg/cm2 | E81: m3 | F81: 12.84 | G81: 488.27 | I81: =+ROUND(G81+H81*TC,2) -> #REF! | J81: =+ROUND(F81*G81,2) -> 6269.39 | K81: =+ROUND(F81*H81,2) -> 0 | L81: =+ROUND(J81+K81*TC,2) -> #REF!
A82: C | C82: =C81+0.000001 -> 3.040302 | D82: CONCRETO PREMEZCLADO, CEMENTO TIPO I, MURO PERIMETRAL f'c=420 kg/cm2 | E82: m3 | F82: 38.78 | G82: 505.61 | I82: =+ROUND(G82+H82*TC,2) -> #REF! | J82: =+ROUND(F82*G82,2) -> 19607.56 | K82: =+ROUND(F82*H82,2) -> 0 | L82: =+ROUND(J82+K82*TC,2) -> #REF!
A83: E | C83: =C82+0.000001 -> 3.040303 | D83: ENCOFRADO Y DESENCOFRADO DE MUROS Y PLACAS | E83: m2 | F83: 166.87 | G83: 43.7 | I83: =+ROUND(G83+H83*TC,2) -> #REF! | J83: =+ROUND(F83*G83,2) -> 7292.22 | K83: =+ROUND(F83*H83,2) -> 0 | L83: =+ROUND(J83+K83*TC,2) -> #REF!
A84: E | C84: =C83+0.000001 -> 3.040304 | D84: ENCOFRADO Y DESENCOFRADO DE MUROS Y PLACAS DOBLE ALTURA | E84: m2 | F84: 0 | G84: 51.7 | I84: =+ROUND(G84+H84*TC,2) -> #REF! | J84: =+ROUND(F84*G84,2) -> 0 | K84: =+ROUND(F84*H84,2) -> 0 | L84: =+ROUND(J84+K84*TC,2) -> #REF!
A85: A | C85: =C84+0.000001 -> 3.040305 | D85: ACERO DE REFUERZO FY= 4200 kg/cm2, GRADO 60 | E85: kg | F85: 4552.19 | G85: 1.19 | H85: 0.91 | I85: =+ROUND(G85+H85*TC,2) -> #REF! | J85: =+ROUND(F85*G85,2) -> 5417.11 | K85: =+ROUND(F85*H85,2) -> 4142.49 | L85: =+ROUND(J85+K85*TC,2) -> #REF!
C86: =C85+0.000001 -> 3.040306 | D86: CURADO DE ELEMENTOS ESTRUCTURALES EXPUESTOS | E86: m2 | F86: 166.87 | G86: 1.44 | I86: =+ROUND(G86+H86*TC,2) -> #REF! | J86: =+ROUND(F86*G86,2) -> 240.29 | K86: =+ROUND(F86*H86,2) -> 0 | L86: =+ROUND(J86+K86*TC,2) -> #REF!
C87: =C80+0.0001 -> 3.0404 | D87: ANCLAJES DE MURO PANTALLA (GEO BUILDING)
C88: =C87+0.000001 -> 3.040401 | D88: MOVILIZACIÓN Y DESMOVILIZACIÓN DE ANCLAJES | E88: glb | F88: 1 | G88: 0 | H88: 3000 | I88: =+ROUND(G88+H88*TC,2) -> #REF! | J88: =+ROUND(F88*G88,2) -> 0 | K88: =+ROUND(F88*H88,2) -> 3000 | L88: =+ROUND(J88+K88*TC,2) -> #REF!
C89: =C88+0.000001 -> 3.040402 | D89: PERFORACIÓN, SUMINISTRO, INSTALACIÓN, INYECCIÓN DE LECHADA DE ANCLAJES POSTENSADOS TEMPORALES (147 anclajes) | E89: ml | F89: 1767 | G89: 0 | H89: 79 | I89: =+ROUND(G89+H89*TC,2) -> #REF! | J89: =+ROUND(F89*G89,2) -> 0 | K89: =+ROUND(F89*H89,2) -> 139593 | L89: =+ROUND(J89+K89*TC,2) -> #REF!
C90: =C89+0.000001 -> 3.040403 | D90: BOLSAS DE CEMENTO PARA TENSADO DE ANCLAJES (inc bolsa de cemento) | E90: bls | F90: 1497 | G90: 22.54 | I90: =+ROUND(G90+H90*TC,2) -> #REF! | J90: =+ROUND(F90*G90,2) -> 33742.38 | K90: =+ROUND(F90*H90,2) -> 0 | L90: =+ROUND(J90+K90*TC,2) -> #REF!
C91: =C90+0.000001 -> 3.040404 | D91: MOVILIZACION Y DESMOVILIZACION DE EQUIPOS MICROPILOTES | E91: glb | F91: 1 | G91: 0 | H91: 2000 | I91: =+ROUND(G91+H91*TC,2) -> #REF! | J91: =+ROUND(F91*G91,2) -> 0 | K91: =+ROUND(F91*H91,2) -> 2000 | L91: =+ROUND(J91+K91*TC,2) -> #REF!
C92: =C91+0.000001 -> 3.040405 | D92: MICROPILOTES SUB HORIZONTALES (LONG EFECTIVA) | E92: ml | F92: 126.5 | G92: 0 | H92: 70 | I92: =+ROUND(G92+H92*TC,2) -> #REF! | J92: =+ROUND(F92*G92,2) -> 0 | K92: =+ROUND(F92*H92,2) -> 8855 | L92: =+ROUND(J92+K92*TC,2) -> #REF!
C93: =C92+0.000001 -> 3.040406 | D93: BOLSAS DE CEMENTO PARA MICROPILOTES (inc bolsa de cemento) | E93: bls | F93: 108 | G93: 22.54 | I93: =+ROUND(G93+H93*TC,2) -> #REF! | J93: =+ROUND(F93*G93,2) -> 2434.32 | K93: =+ROUND(F93*H93,2) -> 0 | L93: =+ROUND(J93+K93*TC,2) -> #REF!
C94: =C87+0.0001 -> 3.0405 | D94: ZAPATAS
A95: C | B95: CIMENTACIÓN | C95: =C94+0.000001 -> 3.040501 | D95: CONCRETO PREMEZCLADO, CEMENTO TIPO I, ZAPATAS f'c=280 kg/cm2 | E95: m3 | F95: 349.58 | G95: 392.69 | I95: =+ROUND(G95+H95*TC,2) -> #REF! | J95: =+ROUND(F95*G95,2) -> 137276.57 | K95: =+ROUND(F95*H95,2) -> 0 | L95: =+ROUND(J95+K95*TC,2) -> #REF!
A96: E | C96: =C95+0.000001 -> 3.040502 | D96: ENCOFRADO Y DESENCOFRADO PARA ZAPATAS | E96: m2 | F96: 296.13 | G96: 47 | I96: =+ROUND(G96+H96*TC,2) -> #REF! | J96: =+ROUND(F96*G96,2) -> 13918.11 | K96: =+ROUND(F96*H96,2) -> 0 | L96: =+ROUND(J96+K96*TC,2) -> #REF!
A97: A | C97: =C96+0.000001 -> 3.040503 | D97: ACERO DE REFUERZO FY= 4200 kg/cm2, GRADO 60 | E97: kg | F97: 17320.82 | G97: 1.19 | H97: 0.91 | I97: =+ROUND(G97+H97*TC,2) -> #REF! | J97: =+ROUND(F97*G97,2) -> 20611.78 | K97: =+ROUND(F97*H97,2) -> 15761.95 | L97: =+ROUND(J97+K97*TC,2) -> #REF!
C98: =C97+0.000001 -> 3.040504 | D98: CURADO DE ELEMENTOS ESTRUCTURALES EXPUESTOS | E98: m2 | F98: 513.14 | G98: 1.44 | I98: =+ROUND(G98+H98*TC,2) -> #REF! | J98: =+ROUND(F98*G98,2) -> 738.92 | K98: =+ROUND(F98*H98,2) -> 0 | L98: =+ROUND(J98+K98*TC,2) -> #REF!
C99: =C98+0.000001 -> 3.040505 | D99: PINTURA ASFALTICA EN CIMENTACIONES | E99: m2 | F99: 513.14 | G99: 20.09 | I99: =+ROUND(G99+H99*TC,2) -> #REF! | J99: =+ROUND(F99*G99,2) -> 10308.98 | K99: =+ROUND(F99*H99,2) -> 0 | L99: =+ROUND(J99+K99*TC,2) -> #REF!
C100: =C94+0.0001 -> 3.0406 | D100: CIMIENTOS ARMADOS INTERIORES
A101: C | B101: CIMENTACIÓN | C101: =C100+0.000001 -> 3.040601 | D101: CONCRETO PREMEZCLADO, CEMENTO TIPO I, ZAPATAS f'c=280 kg/cm2 | E101: m3 | F101: 10.79 | G101: 392.69 | I101: =+ROUND(G101+H101*TC,2) -> #REF! | J101: =+ROUND(F101*G101,2) -> 4237.13 | K101: =+ROUND(F101*H101,2) -> 0 | L101: =+ROUND(J101+K101*TC,2) -> #REF!
A102: E | C102: =C101+0.000001 -> 3.040602 | D102: ENCOFRADO Y DESENCOFRADO PARA ZAPATAS | E102: m2 | F102: 35.98 | G102: 47 | I102: =+ROUND(G102+H102*TC,2) -> #REF! | J102: =+ROUND(F102*G102,2) -> 1691.06 | K102: =+ROUND(F102*H102,2) -> 0 | L102: =+ROUND(J102+K102*TC,2) -> #REF!
A103: A | C103: =C102+0.000001 -> 3.040603 | D103: ACERO DE REFUERZO FY= 4200 kg/cm2, GRADO 60 | E103: kg | F103: 138.35 | G103: 1.19 | H103: 0.91 | I103: =+ROUND(G103+H103*TC,2) -> #REF! | J103: =+ROUND(F103*G103,2) -> 164.64 | K103: =+ROUND(F103*H103,2) -> 125.9 | L103: =+ROUND(J103+K103*TC,2) -> #REF!
...

Sheet EST TORRE
C2: ESTRUCTURAS TORRE
C4: Presupuesto | D4: =#REF! -> #REF!
C5: Subpresupuesto | D5: =+$C$2 -> ESTRUCTURAS TORRE
C6: Cliente | D6: =#REF! -> #REF!
C7: Lugar | D7: =#REF! -> #REF!
C8: Fecha | D8: =#REF! -> #REF!
C10: ITEM | D10: DESCRIPCION | E10: UND | F10: METRADO | G10: P.U. (PEN) | H10: P.U. (USD) | I10: P.U. TOTAL (PEN) | J10: PRECIO PARCIAL (PEN) | K10: PRECIO PARCIAL (USD) | L10: PRECIO TOTAL (PEN) | M10: TOTAL
C11: 04 | D11: =$C$2 -> ESTRUCTURAS TORRE
C12: =C11+0.01 -> 4.01 | D12: CONCRETO ARMADO | I12: =IFERROR(IF(E12<>0,G12+H12*TC," ")," ") | L12: =IFERROR(IF(F12<>0,(F12*I12)," "),0) | M12: =SUM(J12:J135)+SUM(K12:K135)*TC -> #REF!
C13: =C12+0.0001 -> 4.0101 | D13: PLACAS | I13: =IFERROR(IF(E13<>0,(G13+H13*TC)," ")," ") | J13: =IFERROR(IF($F13=0,"",$F13*G13),"") | K13: =IFERROR(IF($F13=0,"",$F13*H13),"") | L13: =IFERROR(IF(F13<>0,(F13*I13)," "),0)
A14: C | B14: CASCO TORRE | C14: =C13+0.000001 -> 4.010101 | D14: CONCRETO PREMEZCLADO, CEMENTO TIPO I, PLACAS f'c=210 kg/cm2 | E14: m3 | F14: 276.82 | G14: 383.31 | I14: =+ROUND(G14+H14*TC,2) -> #REF! | J14: =+ROUND(F14*G14,2) -> 106107.87 | K14: =+ROUND(F14*H14,2) -> 0 | L14: =+ROUND(J14+K14*TC,2) -> #REF!
A15: C | B15: CASCO TORRE | C15: =C14+0.000001 -> 4.010102 | D15: CONCRETO PREMEZCLADO, CEMENTO TIPO I, PLACAS f'c=280 kg/cm2 | E15: m3 | F15: 266.26 | G15: 412.45 | I15: =+ROUND(G15+H15*TC,2) -> #REF! | J15: =+ROUND(F15*G15,2) -> 109818.94 | K15: =+ROUND(F15*H15,2) -> 0 | L15: =+ROUND(J15+K15*TC,2) -> #REF!
A16: C | B16: CASCO TORRE | C16: =C15+0.000001 -> 4.010103 | D16: CONCRETO PREMEZCLADO, CEMENTO TIPO I, PLACAS f'c=350 kg/cm2 | E16: m3 | F16: 298.75 | G16: 451.34 | I16: =+ROUND(G16+H16*TC,2) -> #REF! | J16: =+ROUND(F16*G16,2) -> 134837.83 | K16: =+ROUND(F16*H16,2) -> 0 | L16: =+ROUND(J16+K16*TC,2) -> #REF!
A17: C | B17: CASCO TORRE | C17: =C16+0.000001 -> 4.010104 | D17: CONCRETO PREMEZCLADO, CEMENTO TIPO I, PLACAS f'c=420 kg/cm2 | E17: m3 | F17: 329.7 | G17: 466.93 | I17: =+ROUND(G17+H17*TC,2) -> #REF! | J17: =+ROUND(F17*G17,2) -> 153946.82 | K17: =+ROUND(F17*H17,2) -> 0 | L17: =+ROUND(J17+K17*TC,2) -> #REF!
A18: E | C18: =C15+0.000001 -> 4.010103 | D18: ENCOFRADO Y DESENCOFRADO DE MUROS Y PLACAS | E18: m2 | F18: 9197.56 | G18: 43.7 | I18: =+ROUND(G18+H18*TC,2) -> #REF! | J18: =+ROUND(F18*G18,2) -> 401933.37 | K18: =+ROUND(F18*H18,2) -> 0 | L18: =+ROUND(J18+K18*TC,2) -> #REF!
A19: E | C19: =C18+0.000001 -> 4.010104 | D19: ENCOFRADO Y DESENCOFRADO DE MUROS Y PLACAS DOBLE ALTURA | E19: m2 | F19: 650.41 | G19: 51.7 | I19: =+ROUND(G19+H19*TC,2) -> #REF! | J19: =+ROUND(F19*G19,2) -> 33626.2 | K19: =+ROUND(F19*H19,2) -> 0 | L19: =+ROUND(J19+K19*TC,2) -> #REF!
A20: A | C20: =C18+0.000001 -> 4.010104 | D20: ACERO DE REFUERZO FY= 4200 kg/cm2, GRADO 60 | E20: kg | F20: 148445.43 | G20: 1.19 | H20: 0.91 | I20: =+ROUND(G20+H20*TC,2) -> #REF! | J20: =+ROUND(F20*G20,2) -> 176650.06 | K20: =+ROUND(F20*H20,2) -> 135085.34 | L20: =+ROUND(J20+K20*TC,2) -> #REF!
C21: =C20+0.000001 -> 4.010105 | D21: CURADO DE ELEMENTOS ESTRUCTURALES EXPUESTOS | E21: m2 | F21: 9847.97 | G21: 1.44 | I21: =+ROUND(G21+H21*TC,2) -> #REF! | J21: =+ROUND(F21*G21,2) -> 14181.08 | K21: =+ROUND(F21*H21,2) -> 0 | L21: =+ROUND(J21+K21*TC,2) -> #REF!
C22: =C13+0.0001 -> 4.0102 | D22: MUROS P/ JARDINERAS - CORTES TECHO SOTANO 01 | F22: 0
A23: C | B23: CASCO TORRE | C23: =C22+0.000001 -> 4.010201 | D23: CONCRETO PREMEZCLADO, CEMENTO TIPO I, PISCINA f'c=280 kg/cm2 (W/C=0.50).Por procedimiento constructivo | E23: m3 | F23: 0 | G23: 479.16 | I23: =+ROUND(G23+H23*TC,2) -> #REF! | J23: =+ROUND(F23*G23,2) -> 0 | K23: =+ROUND(F23*H23,2) -> 0 | L23: =+ROUND(J23+K23*TC,2) -> #REF!
A24: E | C24: =C23+0.000001 -> 4.010202 | D24: ENCOFRADO Y DESENCOFRADO DE MUROS Y PLACAS | E24: m2 | F24: 0 | G24: 43.7 | I24: =+ROUND(G24+H24*TC,2) -> #REF! | J24: =+ROUND(F24*G24,2) -> 0 | K24: =+ROUND(F24*H24,2) -> 0 | L24: =+ROUND(J24+K24*TC,2) -> #REF!
A25: A | C25: =C24+0.000001 -> 4.010203 | D25: ACERO DE REFUERZO FY= 4200 kg/cm2, GRADO 60 | E25: kg | F25: 0 | G25: 1.19 | H25: 0.91 | I25: =+ROUND(G25+H25*TC,2) -> #REF! | J25: =+ROUND(F25*G25,2) -> 0 | K25: =+ROUND(F25*H25,2) -> 0 | L25: =+ROUND(J25+K25*TC,2) -> #REF!
C26: =C25+0.000001 -> 4.010204 | D26: CURADO DE ELEMENTOS ESTRUCTURALES EXPUESTOS | E26: m2 | F26: 0 | G26: 1.44 | I26: =+ROUND(G26+H26*TC,2) -> #REF! | J26: =+ROUND(F26*G26,2) -> 0 | K26: =+ROUND(F26*H26,2) -> 0 | L26: =+ROUND(J26+K26*TC,2) -> #REF!
C27: =C22+0.0001 -> 4.0103 | D27: COLUMNAS | F27: 0
A28: C | B28: CASCO TORRE | C28: =C27+0.000001 -> 4.010301 | D28: CONCRETO PREMEZCLADO, CEMENTO TIPO I, COLUMNAS f'c=210 kg/cm2 | E28: m3 | F28: 16.48 | G28: 385.05 | I28: =+ROUND(G28+H28*TC,2) -> #REF! | J28: =+ROUND(F28*G28,2) -> 6345.62 | K28: =+ROUND(F28*H28,2) -> 0 | L28: =+ROUND(J28+K28*TC,2) -> #REF!
A29: C | B29: CASCO TORRE | C29: =C28+0.000001 -> 4.010302 | D29: CONCRETO PREMEZCLADO, CEMENTO TIPO I, COLUMNAS f'c=280 kg/cm2 | E29: m3 | F29: 17.13 | G29: 414.19 | I29: =+ROUND(G29+H29*TC,2) -> #REF! | J29: =+ROUND(F29*G29,2) -> 7095.07 | K29: =+ROUND(F29*H29,2) -> 0 | L29: =+ROUND(J29+K29*TC,2) -> #REF!
A30: C | B30: CASCO TORRE | C30: =C29+0.000001 -> 4.010303 | D30: CONCRETO PREMEZCLADO, CEMENTO TIPO I, COLUMNAS f'c=350 kg/cm2 | E30: m3 | F30: 16.65 | G30: 453.08 | I30: =+ROUND(G30+H30*TC,2) -> #REF! | J30: =+ROUND(F30*G30,2) -> 7543.78 | K30: =+ROUND(F30*H30,2) -> 0 | L30: =+ROUND(J30+K30*TC,2) -> #REF!
A31: C | C31: =C30+0.000001 -> 4.010304 | D31: CONCRETO PREMEZCLADO, CEMENTO TIPO I, COLUMNAS f'c=420 kg/cm2 | E31: m3 | F31: 18.52 | G31: 468.67 | I31: =+ROUND(G31+H31*TC,2) -> #REF! | J31: =+ROUND(F31*G31,2) -> 8679.77 | K31: =+ROUND(F31*H31,2) -> 0 | L31: =+ROUND(J31+K31*TC,2) -> #REF!
A32: E | C32: =C31+0.000001 -> 4.010305 | D32: ENCOFRADO Y DESENCOFRADO DE COLUMNAS | E32: m2 | F32: 486 | G32: 44.1 | I32: =+ROUND(G32+H32*TC,2) -> #REF! | J32: =+ROUND(F32*G32,2) -> 21432.6 | K32: =+ROUND(F32*H32,2) -> 0 | L32: =+ROUND(J32+K32*TC,2) -> #REF!
A33: E | C33: =C32+0.000001 -> 4.010306 | D33: ENCOFRADO Y DESENCOFRADO DE COLUMNAS DOBLE ALTURA | E33: m2 | F33: 41.71 | G33: 52.1 | I33: =+ROUND(G33+H33*TC,2) -> #REF! | J33: =+ROUND(F33*G33,2) -> 2173.09 | K33: =+ROUND(F33*H33,2) -> 0 | L33: =+ROUND(J33+K33*TC,2) -> #REF!
A34: A | C34: =C33+0.000001 -> 4.010307 | D34: ACERO DE REFUERZO FY= 4200 kg/cm2, GRADO 60 | E34: kg | F34: 11853.06 | G34: 1.19 | H34: 0.91 | I34: =+ROUND(G34+H34*TC,2) -> #REF! | J34: =+ROUND(F34*G34,2) -> 14105.14 | K34: =+ROUND(F34*H34,2) -> 10786.28 | L34: =+ROUND(J34+K34*TC,2) -> #REF!
C35: =C34+0.000001 -> 4.010308 | D35: CURADO DE ELEMENTOS ESTRUCTURALES EXPUESTOS | E35: m2 | F35: 527.71 | G35: 1.44 | I35: =+ROUND(G35+H35*TC,2) -> #REF! | J35: =+ROUND(F35*G35,2) -> 759.9 | K35: =+ROUND(F35*H35,2) -> 0 | L35: =+ROUND(J35+K35*TC,2) -> #REF!
C36: =C27+0.0001 -> 4.0104 | D36: VIGAS | F36: 0
A37: C | B37: CASCO TORRE | C37: =C36+0.000001 -> 4.010401 | D37: CONCRETO PREMEZCLADO, CEMENTO TIPO I, VIGAS TORRE f'c=245 kg/cm2 | E37: m3 | F37: 813.69 | G37: 396.14 | I37: =+ROUND(G37+H37*TC,2) -> #REF! | J37: =+ROUND(F37*G37,2) -> 322335.16 | K37: =+ROUND(F37*H37,2) -> 0 | L37: =+ROUND(J37+K37*TC,2) -> #REF!
A38: C | B38: CASCO TORRE | C38: =C37+0.000001 -> 4.010402 | D38: CONCRETO PREMEZCLADO, CEMENTO TIPO I, VIGAS TORRE f'c=350 kg/cm2 (NUCLEOS) | E38: m3 | F38: 31.27 | G38: 449.73 | I38: =+ROUND(G38+H38*TC,2) -> #REF! | J38: =+ROUND(F38*G38,2) -> 14063.06 | K38: =+ROUND(F38*H38,2) -> 0 | L38: =+ROUND(J38+K38*TC,2) -> #REF!
A39: C | B39: CASCO TORRE | C39: =C38+0.000001 -> 4.010403 | D39: CONCRETO PREMEZCLADO, CEMENTO TIPO I, VIGAS TORRE f'c=420 kg/cm2 (NUCLEOS) | E39: m3 | F39: 31 | G39: 465.98 | I39: =+ROUND(G39+H39*TC,2) -> #REF! | J39: =+ROUND(F39*G39,2) -> 14445.38 | K39: =+ROUND(F39*H39,2) -> 0 | L39: =+ROUND(J39+K39*TC,2) -> #REF!
A40: E | C40: =C38+0.000001 -> 4.010403 | D40: ENCOFRADO Y DESENCOFRADO DE VIGAS | E40: m2 | F40: 3986.27 | G40: 54.1 | I40: =+ROUND(G40+H40*TC,2) -> #REF! | J40: =+ROUND(F40*G40,2) -> 215657.21 | K40: =+ROUND(F40*H40,2) -> 0 | L40: =+ROUND(J40+K40*TC,2) -> #REF!
A41: E | C41: =C40+0.000001 -> 4.010404 | D41: ENCOFRADO Y DESENCOFRADO DE VIGAS DOBLE ALTURA | E41: m2 | F41: 191.82 | G41: 62.1 | I41: =+ROUND(G41+H41*TC,2) -> #REF! | J41: =+ROUND(F41*G41,2) -> 11912.02 | K41: =+ROUND(F41*H41,2) -> 0 | L41: =+ROUND(J41+K41*TC,2) -> #REF!
A42: A | C42: =C41+0.000001 -> 4.010405 | D42: ACERO DE REFUERZO FY= 4200 kg/cm2, GRADO 60 | E42: kg | F42: 131302.91 | G42: 1.19 | H42: 0.91 | I42: =+ROUND(G42+H42*TC,2) -> #REF! | J42: =+ROUND(F42*G42,2) -> 156250.46 | K42: =+ROUND(F42*H42,2) -> 119485.65 | L42: =+ROUND(J42+K42*TC,2) -> #REF!
C43: =C42+0.000001 -> 4.010406 | D43: CURADO DE ELEMENTOS ESTRUCTURALES EXPUESTOS | E43: m2 | F43: 4785.96 | G43: 1.44 | I43: =+ROUND(G43+H43*TC,2) -> #REF! | J43: =+ROUND(F43*G43,2) -> 6891.78 | K43: =+ROUND(F43*H43,2) -> 0 | L43: =+ROUND(J43+K43*TC,2) -> #REF!
C44: =C36+0.0001 -> 4.0105 | D44: VIGAS CHATAS | F44: 0
A45: A | C45: =C44+0.000001 -> 4.010501 | D45: ACERO DE REFUERZO FY= 4200 kg/cm2, GRADO 60 | E45: kg | F45: 21404.73 | G45: 1.19 | H45: 0.91 | I45: =+ROUND(G45+H45*TC,2) -> #REF! | J45: =+ROUND(F45*G45,2) -> 25471.63 | K45: =+ROUND(F45*H45,2) -> 19478.3 | L45: =+ROUND(J45+K45*TC,2) -> #REF!
C46: =C45+0.000001 -> 4.010502 | D46: SUMINISTRO DE PRELOSA MACIZA H=20CM | E46: m2 | F46: 607.87 | G46: 45.2 | I46: =+ROUND(G46+H46*TC,2) -> #REF! | J46: =+ROUND(F46*G46,2) -> 27475.72 | K46: =+ROUND(F46*H46,2) -> 0 | L46: =+ROUND(J46+K46*TC,2) -> #REF!
C47: =C46+0.000001 -> 4.010503 | D47: INSTALACIÓN DE PRELOSA E=5CM | E47: m2 | F47: 607.87 | G47: 5.17 | I47: =+ROUND(G47+H47*TC,2) -> #REF! | J47: =+ROUND(F47*G47,2) -> 3142.69 | K47: =+ROUND(F47*H47,2) -> 0 | L47: =+ROUND(J47+K47*TC,2) -> #REF!
A48: E | C48: =C47+0.000001 -> 4.010504 | D48: APUNTALAMIENTO (ENCOFRADO) DE PRELOSA EN VIGAS CHATAS | E48: m2 | F48: 576.47 | G48: 37.12 | I48: =+ROUND(G48+H48*TC,2) -> #REF! | J48: =+ROUND(F48*G48,2) -> 21398.57 | K48: =+ROUND(F48*H48,2) -> 0 | L48: =+ROUND(J48+K48*TC,2) -> #REF!
A49: E | C49: =C48+0.000001 -> 4.010505 | D49: APUNTALAMIENTO (ENCOFRADO) DE PRELOSA EN VIGAS CHATAS DOBLE ALTURA | E49: m2 | F49: 31.4 | G49: 43.3 | I49: =+ROUND(G49+H49*TC,2) -> #REF! | J49: =+ROUND(F49*G49,2) -> 1359.62 | K49: =+ROUND(F49*H49,2) -> 0 | L49: =+ROUND(J49+K49*TC,2) -> #REF!
C50: =C44+0.0001 -> 4.0106 | D50: PRELOSA MACIZA H=0.20M | F50: 0
A51: C | B51: CASCO TORRE | C51: =C50+0.000001 -> 4.010601 | D51: CONCRETO PREMEZCLADO, CEMENTO TIPO I, LOSA MACIZA TORRE f'c=245 kg/cm2 | E51: m3 | F51: 193.72 | G51: 396.14 | I51: =+ROUND(G51+H51*TC,2) -> #REF! | J51: =+ROUND(F51*G51,2) -> 76740.24 | K51: =+ROUND(F51*H51,2) -> 0 | L51: =+ROUND(J51+K51*TC,2) -> #REF!
A52: C | B52: CASCO TORRE | C52: =C50+0.000001 -> 4.010601 | D52: CONCRETO PREMEZCLADO, CEMENTO TIPO I, VIGAS TORRE f'c=350 kg/cm2 (NUCLEOS) | E52: m3 | F52: 4.61 | G52: 449.73 | I52: =+ROUND(G52+H52*TC,2) -> #REF! | J52: =+ROUND(F52*G52,2) -> 2073.26 | K52: =+ROUND(F52*H52,2) -> 0 | L52: =+ROUND(J52+K52*TC,2) -> #REF!
A53: C | B53: CASCO TORRE | C53: =C51+0.000001 -> 4.010602 | D53: CONCRETO PREMEZCLADO, CEMENTO TIPO I, VIGAS TORRE f'c=420 kg/cm2 (NUCLEOS) | E53: m3 | F53: 5.05 | G53: 465.98 | I53: =+ROUND(G53+H53*TC,2) -> #REF! | J53: =+ROUND(F53*G53,2) -> 2353.2 | K53: =+ROUND(F53*H53,2) -> 0 | L53: =+ROUND(J53+K53*TC,2) -> #REF!
A54: E | C54: =C53+0.000001 -> 4.010603 | D54: ENCOFRADO Y DESENCOFRADO DE PRELOSA MACIZA | E54: m2 | F54: 1278.77 | G54: 37.52 | I54: =+ROUND(G54+H54*TC,2) -> #REF! | J54: =+ROUND(F54*G54,2) -> 47979.45 | K54: =+ROUND(F54*H54,2) -> 0 | L54: =+ROUND(J54+K54*TC,2) -> #REF!
A55: E | C55: =C54+0.000001 -> 4.010604 | D55: ENCOFRADO Y DESENCOFRADO DE PRELOSA MACIZA DOBLE ALTURA | E55: m2 | F55: 57.08 | G55: 43.7 | I55: =+ROUND(G55+H55*TC,2) -> #REF! | J55: =+ROUND(F55*G55,2) -> 2494.4 | K55: =+ROUND(F55*H55,2) -> 0 | L55: =+ROUND(J55+K55*TC,2) -> #REF!
C56: =C55+0.000001 -> 4.010605 | D56: SUMINISTRO DE PRELOSA MACIZA H=20CM | E56: m2 | F56: 1335.85 | G56: 45.2 | I56: =+ROUND(G56+H56*TC,2) -> #REF! | J56: =+ROUND(F56*G56,2) -> 60380.42 | K56: =+ROUND(F56*H56,2) -> 0 | L56: =+ROUND(J56+K56*TC,2) -> #REF!
C57: =C56+0.000001 -> 4.010606 | D57: INSTALACIÓN DE PRELOSA E=5CM | E57: m2 | F57: 1335.85 | G57: 5.17 | I57: =+ROUND(G57+H57*TC,2) -> #REF! | J57: =+ROUND(F57*G57,2) -> 6906.34 | K57: =+ROUND(F57*H57,2) -> 0 | L57: =+ROUND(J57+K57*TC,2) -> #REF!
A58: A | C58: =C57+0.000001 -> 4.010607 | D58: ACERO DE REFUERZO FY= 4200 kg/cm2, GRADO 60 (PUESTO EN OBRA) | E58: kg | F58: 11054.27 | G58: 1.19 | H58: 0.91 | I58: =+ROUND(G58+H58*TC,2) -> #REF! | J58: =+ROUND(F58*G58,2) -> 13154.58 | K58: =+ROUND(F58*H58,2) -> 10059.39 | L58: =+ROUND(J58+K58*TC,2) -> #REF!
A59: A | C59: =C58+0.000001 -> 4.010608 | D59: ACERO DE REFUERZO FY= 4200 kg/cm2, GRADO 60 (EMBEBIDO EN PRELOSA) | E59: kg | F59: 13539.5 | G59: 0 | H59: 0.91 | I59: =+ROUND(G59+H59*TC,2) -> #REF! | J59: =+ROUND(F59*G59,2) -> 0 | K59: =+ROUND(F59*H59,2) -> 12320.95 | L59: =+ROUND(J59+K59*TC,2) -> #REF!
A60: A | C60: =C59+0.000001 -> 4.010609 | D60: ACERO DE REFUERZO FY= 4200 kg/cm2, GRADO 60 DE CONTINUIDAD (PUESTO EN OBRA) | E60: kg | F60: 5730.8 | G60: 1.19 | H60: 0.91 | I60: =+ROUND(G60+H60*TC,2) -> #REF! | J60: =+ROUND(F60*G60,2) -> 6819.65 | K60: =+ROUND(F60*H60,2) -> 5215.03 | L60: =+ROUND(J60+K60*TC,2) -> #REF!
C61: =C60+0.000001 -> 4.01061 | D61: CURADO DE ELEMENTOS ESTRUCTURALES EXPUESTOS | E61: m2 | F61: 1335.85 | G61: 1.44 | I61: =+ROUND(G61+H61*TC,2) -> #REF! | J61: =+ROUND(F61*G61,2) -> 1923.62 | K61: =+ROUND(F61*H61,2) -> 0 | L61: =+ROUND(J61+K61*TC,2) -> #REF!
C62: =C50+0.0001 -> 4.0107 | D62: PRELOSA ALIGERADA H=0.20M, UN SENTIDO | F62: 0
A63: C | B63: CASCO TORRE | C63: =C62+0.000001 -> 4.010701 | D63: CONCRETO PREMEZCLADO, CEMENTO TIPO I, LOSA ALIGERADA TORRE f'c=245 kg/cm2 | E63: m3 | F63: 5.26 | G63: 396.14 | I63: =+ROUND(G63+H63*TC,2) -> #REF! | J63: =+ROUND(F63*G63,2) -> 2083.7 | K63: =+ROUND(F63*H63,2) -> 0 | L63: =+ROUND(J63+K63*TC,2) -> #REF!
A64: E | C64: =C63+0.000001 -> 4.010702 | D64: ENCOFRADO Y DESENCOFRADO DE PRELOSA ALIGERADA | E64: m2 | F64: 63.74 | G64: 37.52 | I64: =+ROUND(G64+H64*TC,2) -> #REF! | J64: =+ROUND(F64*G64,2) -> 2391.52 | K64: =+ROUND(F64*H64,2) -> 0 | L64: =+ROUND(J64+K64*TC,2) -> #REF!
A65: E | C65: =C64+0.000001 -> 4.010703 | D65: ENCOFRADO Y DESENCOFRADO DE PRELOSA ALIGERADA DOBLE ALTURA | E65: m2 | F65: 0 | G65: 43.7 | I65: =+ROUND(G65+H65*TC,2) -> #REF! | J65: =+ROUND(F65*G65,2) -> 0 | K65: =+ROUND(F65*H65,2) -> 0 | L65: =+ROUND(J65+K65*TC,2) -> #REF!
C66: =C65+0.000001 -> 4.010704 | D66: SUMINISTRO DE PRELOSA ALIGERADA EN UNA DIRECCION H=20CM | E66: m2 | F66: 63.74 | G66: 57.9 | I66: =+ROUND(G66+H66*TC,2) -> #REF! | J66: =+ROUND(F66*G66,2) -> 3690.55 | K66: =+ROUND(F66*H66,2) -> 0 | L66: =+ROUND(J66+K66*TC,2) -> #REF!
C67: =C66+0.000001 -> 4.010705 | D67: INSTALACIÓN DE PRELOSA E=5CM | E67: m2 | F67: 63.74 | G67: 5.17 | I67: =+ROUND(G67+H67*TC,2) -> #REF! | J67: =+ROUND(F67*G67,2) -> 329.54 | K67: =+ROUND(F67*H67,2) -> 0 | L67: =+ROUND(J67+K67*TC,2) -> #REF!
A68: A | C68: =C67+0.000001 -> 4.010706 | D68: ACERO DE REFUERZO FY= 4200 kg/cm2, GRADO 60 (PUESTO EN OBRA) | E68: kg | F68: 272.66 | G68: 1.19 | H68: 0.91 | I68: =+ROUND(G68+H68*TC,2) -> #REF! | J68: =+ROUND(F68*G68,2) -> 324.47 | K68: =+ROUND(F68*H68,2) -> 248.12 | L68: =+ROUND(J68+K68*TC,2) -> #REF!
A69: A | C69: =C68+0.000001 -> 4.010707 | D69: ACERO DE REFUERZO FY= 4200 kg/cm2, GRADO 60 (EMBEBIDO EN PRELOSA) | E69: kg | F69: 174.79 | G69: 0 | H69: 0.91 | I69: =+ROUND(G69+H69*TC,2) -> #REF! | J69: =+ROUND(F69*G69,2) -> 0 | K69: =+ROUND(F69*H69,2) -> 159.06 | L69: =+ROUND(J69+K69*TC,2) -> #REF!
A70: A | C70: =C69+0.000001 -> 4.010708 | D70: ACERO DE REFUERZO FY= 4200 kg/cm2, GRADO 60 (COSTURA PRELOSA) | E70: kg | F70: 25.5 | G70: 1.19 | H70: 0.91 | I70: =+ROUND(G70+H70*TC,2) -> #REF! | J70: =+ROUND(F70*G70,2) -> 30.35 | K70: =+ROUND(F70*H70,2) -> 23.21 | L70: =+ROUND(J70+K70*TC,2) -> #REF!
A71: A | C71: =C70+0.000001 -> 4.010709 | D71: ACERO DE REFUERZO FY= 4200 kg/cm2, GRADO 60 BASE Y DISTRIBUCIÓN (EMBEBIDO EN PRELOSA) | E71: kg | F71: 127.48 | G71: 0 | H71: 0.91 | I71: =+ROUND(G71+H71*TC,2) -> #REF! | J71: =+ROUND(F71*G71,2) -> 0 | K71: =+ROUND(F71*H71,2) -> 116.01 | L71: =+ROUND(J71+K71*TC,2) -> #REF!
C72: =C71+0.000001 -> 4.01071 | D72: CURADO DE ELEMENTOS ESTRUCTURALES EXPUESTOS | E72: m2 | F72: 63.74 | G72: 1.44 | I72: =+ROUND(G72+H72*TC,2) -> #REF! | J72: =+ROUND(F72*G72,2) -> 91.79 | K72: =+ROUND(F72*H72,2) -> 0 | L72: =+ROUND(J72+K72*TC,2) -> #REF!
C73: =C62+0.0001 -> 4.0108 | D73: PRELOSA ALIGERADA H=0.25M, UN SENTIDO | F73: 0
A74: C | B74: CASCO TORRE | C74: =C73+0.000001 -> 4.010801 | D74: CONCRETO PREMEZCLADO, CEMENTO TIPO I, LOSA ALIGERADA TORRE f'c=245 kg/cm2 | E74: m3 | F74: 478.27 | G74: 396.14 | I74: =+ROUND(G74+H74*TC,2) -> #REF! | J74: =+ROUND(F74*G74,2) -> 189461.88 | K74: =+ROUND(F74*H74,2) -> 0 | L74: =+ROUND(J74+K74*TC,2) -> #REF!
A75: C | B75: CASCO TORRE | C75: =C73+0.000001 -> 4.010801 | D75: CONCRETO PREMEZCLADO, CEMENTO TIPO I, VIGAS TORRE f'c=350 kg/cm2 (NUCLEOS) | E75: m3 | F75: 13.47 | G75: 449.73 | I75: =+ROUND(G75+H75*TC,2) -> #REF! | J75: =+ROUND(F75*G75,2) -> 6057.86 | K75: =+ROUND(F75*H75,2) -> 0 | L75: =+ROUND(J75+K75*TC,2) -> #REF!
A76: C | B76: CASCO TORRE | C76: =C74+0.000001 -> 4.010802 | D76: CONCRETO PREMEZCLADO, CEMENTO TIPO I, VIGAS TORRE f'c=420 kg/cm2 (NUCLEOS) | E76: m3 | F76: 13.61 | G76: 465.98 | I76: =+ROUND(G76+H76*TC,2) -> #REF! | J76: =+ROUND(F76*G76,2) -> 6341.99 | K76: =+ROUND(F76*H76,2) -> 0 | L76: =+ROUND(J76+K76*TC,2) -> #REF!
A77: E | C77: =C75+0.000001 -> 4.010802 | D77: ENCOFRADO Y DESENCOFRADO DE PRELOSA ALIGERADA | E77: m2 | F77: 5429.51 | G77: 37.52 | I77: =+ROUND(G77+H77*TC,2) -> #REF! | J77: =+ROUND(F77*G77,2) -> 203715.22 | K77: =+ROUND(F77*H77,2) -> 0 | L77: =+ROUND(J77+K77*TC,2) -> #REF!
A78: E | C78: =C77+0.000001 -> 4.010803 | D78: ENCOFRADO Y DESENCOFRADO DE PRELOSA ALIGERADA DOBLE ALTURA | E78: m2 | F78: 290.49 | G78: 43.7 | I78: =+ROUND(G78+H78*TC,2) -> #REF! | J78: =+ROUND(F78*G78,2) -> 12694.41 | K78: =+ROUND(F78*H78,2) -> 0 | L78: =+ROUND(J78+K78*TC,2) -> #REF!
C79: =C77+0.000001 -> 4.010803 | D79: SUMINISTRO DE PRELOSA ALIGERADA EN UNA DIRECCION H=25CM | E79: m2 | F79: 5720 | G79: 62.9 | I79: =+ROUND(G79+H79*TC,2) -> #REF! | J79: =+ROUND(F79*G79,2) -> 359788 | K79: =+ROUND(F79*H79,2) -> 0 | L79: =+ROUND(J79+K79*TC,2) -> #REF!
C80: =C79+0.000001 -> 4.010804 | D80: INSTALACIÓN DE PRELOSA E=5CM | E80: m2 | F80: 5720 | G80: 5.17 | I80: =+ROUND(G80+H80*TC,2) -> #REF! | J80: =+ROUND(F80*G80,2) -> 29572.4 | K80: =+ROUND(F80*H80,2) -> 0 | L80: =+ROUND(J80+K80*TC,2) -> #REF!
A81: A | C81: =C80+0.000001 -> 4.010805 | D81: ACERO DE REFUERZO FY= 4200 kg/cm2, GRADO 60 (PUESTO EN OBRA) | E81: kg | F81: 22631.14 | G81: 1.19 | H81: 0.91 | I81: =+ROUND(G81+H81*TC,2) -> #REF! | J81: =+ROUND(F81*G81,2) -> 26931.06 | K81: =+ROUND(F81*H81,2) -> 20594.34 | L81: =+ROUND(J81+K81*TC,2) -> #REF!
A82: A | C82: =C81+0.000001 -> 4.010806 | D82: ACERO DE REFUERZO FY= 4200 kg/cm2, GRADO 60 (EMBEBIDO EN PRELOSA) | E82: kg | F82: 23266.01 | G82: 0 | H82: 0.91 | I82: =+ROUND(G82+H82*TC,2) -> #REF! | J82: =+ROUND(F82*G82,2) -> 0 | K82: =+ROUND(F82*H82,2) -> 21172.07 | L82: =+ROUND(J82+K82*TC,2) -> #REF!
A83: A | C83: =C82+0.000001 -> 4.010807 | D83: ACERO DE REFUERZO FY= 4200 kg/cm2, GRADO 60 (COSTURA PRELOSA) | E83: kg | F83: 2288 | G83: 1.19 | H83: 0.91 | I83: =+ROUND(G83+H83*TC,2) -> #REF! | J83: =+ROUND(F83*G83,2) -> 2722.72 | K83: =+ROUND(F83*H83,2) -> 2082.08 | L83: =+ROUND(J83+K83*TC,2) -> #REF!
A84: A | C84: =C83+0.000001 -> 4.010808 | D84: ACERO DE REFUERZO FY= 4200 kg/cm2, GRADO 60 BASE Y DISTRIBUCIÓN (EMBEBIDO EN PRELOSA) | E84: kg | F84: 11440 | G84: 0 | H84: 0.91 | I84: =+ROUND(G84+H84*TC,2) -> #REF! | J84: =+ROUND(F84*G84,2) -> 0 | K84: =+ROUND(F84*H84,2) -> 10410.4 | L84: =+ROUND(J84+K84*TC,2) -> #REF!
C85: =C84+0.000001 -> 4.010809 | D85: CURADO DE ELEMENTOS ESTRUCTURALES EXPUESTOS | E85: m2 | F85: 5720 | G85: 1.44 | I85: =+ROUND(G85+H85*TC,2) -> #REF! | J85: =+ROUND(F85*G85,2) -> 8236.8 | K85: =+ROUND(F85*H85,2) -> 0 | L85: =+ROUND(J85+K85*TC,2) -> #REF!
C86: =C73+0.0001 -> 4.0109 | D86: PRELOSA ALIGERADA H=0.25M, DOS SENTIDOS | F86: 0
A87: C | B87: CASCO TORRE | C87: =C86+0.000001 -> 4.010901 | D87: CONCRETO PREMEZCLADO, CEMENTO TIPO I, LOSA ALIGERADA TORRE f'c=245 kg/cm2 | E87: m3 | F87: 124.26 | G87: 396.14 | I87: =+ROUND(G87+H87*TC,2) -> #REF! | J87: =+ROUND(F87*G87,2) -> 49224.36 | K87: =+ROUND(F87*H87,2) -> 0 | L87: =+ROUND(J87+K87*TC,2) -> #REF!
A88: C | B88: CASCO TORRE | C88: =C87+0.000001 -> 4.010902 | D88: CONCRETO PREMEZCLADO, CEMENTO TIPO I, VIGAS TORRE f'c=350 kg/cm2 (NUCLEOS) | E88: m3 | F88: 2.55 | G88: 449.73 | I88: =+ROUND(G88+H88*TC,2) -> #REF! | J88: =+ROUND(F88*G88,2) -> 1146.81 | K88: =+ROUND(F88*H88,2) -> 0 | L88: =+ROUND(J88+K88*TC,2) -> #REF!
A89: C | B89: CASCO TORRE | C89: =C87+0.000001 -> 4.010902 | D89: CONCRETO PREMEZCLADO, CEMENTO TIPO I, VIGAS TORRE f'c=420 kg/cm2 (NUCLEOS) | E89: m3 | F89: 2.64 | G89: 465.98 | I89: =+ROUND(G89+H89*TC,2) -> #REF! | J89: =+ROUND(F89*G89,2) -> 1230.19 | K89: =+ROUND(F89*H89,2) -> 0 | L89: =+ROUND(J89+K89*TC,2) -> #REF!
A90: E | C90: =C88+0.000001 -> 4.010903 | D90: ENCOFRADO Y DESENCOFRADO DE PRELOSA ALIGERADA | E90: m2 | F90: 1137.23 | G90: 37.52 | I90: =+ROUND(G90+H90*TC,2) -> #REF! | J90: =+ROUND(F90*G90,2) -> 42668.87 | K90: =+ROUND(F90*H90,2) -> 0 | L90: =+ROUND(J90+K90*TC,2) -> #REF!
A91: E | C91: =C90+0.000001 -> 4.010904 | D91: ENCOFRADO Y DESENCOFRADO DE PRELOSA ALIGERADA DOBLE ALTURA | E91: m2 | F91: 63.46 | G91: 43.7 | I91: =+ROUND(G91+H91*TC,2) -> #REF! | J91: =+ROUND(F91*G91,2) -> 2773.2 | K91: =+ROUND(F91*H91,2) -> 0 | L91: =+ROUND(J91+K91*TC,2) -> #REF!
C92: =C90+0.000001 -> 4.010904 | D92: SUMINISTRO DE PRELOSA ALIGERADA EN DOS DIRECCIONES H=25CM | E92: m2 | F92: 1200.69 | G92: 60.5 | I92: =+ROUND(G92+H92*TC,2) -> #REF! | J92: =+ROUND(F92*G92,2) -> 72641.75 | K92: =+ROUND(F92*H92,2) -> 0 | L92: =+ROUND(J92+K92*TC,2) -> #REF!
C93: =C92+0.000001 -> 4.010905 | D93: INSTALACIÓN DE PRELOSA E=5CM | E93: m2 | F93: 1200.69 | G93: 5.17 | I93: =+ROUND(G93+H93*TC,2) -> #REF! | J93: =+ROUND(F93*G93,2) -> 6207.57 | K93: =+ROUND(F93*H93,2) -> 0 | L93: =+ROUND(J93+K93*TC,2) -> #REF!
A94: A | C94: =C93+0.000001 -> 4.010906 | D94: ACERO DE REFUERZO FY= 4200 kg/cm2, GRADO 60 (PUESTO EN OBRA) | E94: kg | F94: 6031.64 | G94: 1.19 | H94: 0.91 | I94: =+ROUND(G94+H94*TC,2) -> #REF! | J94: =+ROUND(F94*G94,2) -> 7177.65 | K94: =+ROUND(F94*H94,2) -> 5488.79 | L94: =+ROUND(J94+K94*TC,2) -> #REF!
A95: A | C95: =C94+0.000001 -> 4.010907 | D95: ACERO DE REFUERZO FY= 4200 kg/cm2, GRADO 60 (EMBEBIDO EN PRELOSA) | E95: kg | F95: 6844.74 | G95: 0 | H95: 0.91 | I95: =+ROUND(G95+H95*TC,2) -> #REF! | J95: =+ROUND(F95*G95,2) -> 0 | K95: =+ROUND(F95*H95,2) -> 6228.71 | L95: =+ROUND(J95+K95*TC,2) -> #REF!
A96: A | C96: =C95+0.000001 -> 4.010908 | D96: ACERO DE REFUERZO FY= 4200 kg/cm2, GRADO 60 (COSTURA PRELOSA) | E96: kg | F96: 480.28 | G96: 1.19 | H96: 0.91 | I96: =+ROUND(G96+H96*TC,2) -> #REF! | J96: =+ROUND(F96*G96,2) -> 571.53 | K96: =+ROUND(F96*H96,2) -> 437.05 | L96: =+ROUND(J96+K96*TC,2) -> #REF!
C97: =C96+0.000001 -> 4.010909 | D97: CURADO DE ELEMENTOS ESTRUCTURALES EXPUESTOS | E97: m2 | F97: 1200.69 | G97: 1.44 | I97: =+ROUND(G97+H97*TC,2) -> #REF! | J97: =+ROUND(F97*G97,2) -> 1728.99 | K97: =+ROUND(F97*H97,2) -> 0 | L97: =+ROUND(J97+K97*TC,2) -> #REF!
C98: =C86+0.0001 -> 4.011 | D98: ESCALERA | F98: 0
A99: C | B99: CASCO TORRE | C99: =C98+0.000001 -> 4.011001 | D99: CONCRETO PREMEZCLADO, CEMENTO TIPO I, ESCALERAS f'c=245 kg/cm2 | E99: m3 | F99: 80.59 | G99: 417.16 | I99: =+ROUND(G99+H99*TC,2) -> #REF! | J99: =+ROUND(F99*G99,2) -> 33618.92 | K99: =+ROUND(F99*H99,2) -> 0 | L99: =+ROUND(J99+K99*TC,2) -> #REF!
A100: E | C100: =C99+0.000001 -> 4.011002 | D100: ENCOFRADO Y DESENCOFRADO DE ESCALERAS | E100: m2 | F100: 768.86 | G100: 52.1 | I100: =+ROUND(G100+H100*TC,2) -> #REF! | J100: =+ROUND(F100*G100,2) -> 40057.61 | K100: =+ROUND(F100*H100,2) -> 0 | L100: =+ROUND(J100+K100*TC,2) -> #REF!
A101: A | C101: =C100+0.000001 -> 4.011003 | D101: ACERO DE REFUERZO FY= 4200 kg/cm2, GRADO 60 | E101: kg | F101: 3884.94 | G101: 1.19 | H101: 0.91 | I101: =+ROUND(G101+H101*TC,2) -> #REF! | J101: =+ROUND(F101*G101,2) -> 4623.08 | K101: =+ROUND(F101*H101,2) -> 3535.3 | L101: =+ROUND(J101+K101*TC,2) -> #REF!
C102: =C101+0.000001 -> 4.011004 | D102: CURADO DE ELEMENTOS ESTRUCTURALES EXPUESTOS | E102: m2 | F102: 768.86 | G102: 1.44 | I102: =+ROUND(G102+H102*TC,2) -> #REF! | J102: =+ROUND(F102*G102,2) -> 1107.16 | K102: =+ROUND(F102*H102,2) -> 0 | L102: =+ROUND(J102+K102*TC,2) -> #REF!
C103: =C98+0.0001 -> 4.0111 | D103: COLUMNETAS Y VIGAS DE AMARRE | F103: 0
...

Sheet ARQ SOT
B2: ARQUITECTURA SÓTANOS
B4: Presupuesto | C4: EDIFICIO MULTIFAMILIAR SALAVERRY 2431
B5: Subpresupuesto | C5: =$B$2 -> ARQUITECTURA SÓTANOS
B6: Cliente | C6: V&V BRAVO INMOBILIARIA
B7: Lugar | C7: SAN ISIDRO
B8: Fecha | C8: =#REF! -> #REF!
B10: ITEM | C10: DESCRIPCION | D10: UND | E10: METRADO | F10: P.U. (PEN) | G10: P.U. (USD) | H10: P.U. TOTAL (PEN) | I10: PRECIO PARCIAL (PEN) | J10: PRECIO PARCIAL (USD) | K10: PARCIAL TOTAL (PEN) | L10: TOTAL
B11: 05 | C11: =$B$2 -> ARQUITECTURA SÓTANOS
B12: =B11+0.01 -> 5.01 | C12: MUROS Y TABIQUES | H12: =IFERROR(IF(D12<>0,(F12+G12*TC)," ")," ") | I12: =IFERROR(IF($E12=0,"",$E12*F12),"") | J12: =IFERROR(IF($E12=0,"",$E12*G12),"") | K12: =IFERROR(IF(E12<>0,(E12*H12)," "),0) | L12: =SUM(I12:I49)+SUM(J12:J49)*TC -> #REF!
B13: =B12+0.0001 -> 5.0101 | C13: MUROS Y TABIQUES SILICO CALCAREOS | H13: =IFERROR(IF(D13<>0,(F13+G13*TC)," ")," ") | I13: =IFERROR(IF($E13=0,"",$E13*F13),"") | J13: =IFERROR(IF($E13=0,"",$E13*G13),"") | K13: =IFERROR(IF(E13<>0,(E13*H13)," "),0)
B14: =B12+0.0001 -> 5.0101 | C14: ALTURA < 2.60 | H14: =IFERROR(IF(D14<>0,(F14+G14*TC)," ")," ") | I14: =IFERROR(IF($E14=0,"",$E14*F14),"") | J14: =IFERROR(IF($E14=0,"",$E14*G14),"") | K14: =IFERROR(IF(E14<>0,(E14*H14)," "),0)
B15: =B14+0.000001 -> 5.010101 | C15: LADRILLO SILICO CALCAREO TIPO P7 H<2.6M | D15: m2 | E15: 533.66 | F15: 96.71 | H15: =+ROUND(F15+G15*TC,2) -> #REF! | I15: =+ROUND(E15*F15,2) -> 51610.26 | J15: =+ROUND(E15*G15,2) -> 0 | K15: =+ROUND(I15+J15*TC,2) -> #REF!
B16: =B15+0.000001 -> 5.010102 | C16: LADRILLO SILICO CALCAREO TIPO P10 H<2.6M | D16: m2 | E16: 17.75 | F16: 103.71 | H16: =+ROUND(F16+G16*TC,2) -> #REF! | I16: =+ROUND(E16*F16,2) -> 1840.85 | J16: =+ROUND(E16*G16,2) -> 0 | K16: =+ROUND(I16+J16*TC,2) -> #REF!
B17: =B15+0.000001 -> 5.010102 | C17: LADRILLO SILICO CALCAREO TIPO P12 H<2.6M | D17: m2 | E17: 32.35 | F17: 109.71 | H17: =+ROUND(F17+G17*TC,2) -> #REF! | I17: =+ROUND(E17*F17,2) -> 3549.12 | J17: =+ROUND(E17*G17,2) -> 0 | K17: =+ROUND(I17+J17*TC,2) -> #REF!
B18: =B17+0.000001 -> 5.010103 | C18: LADRILLO SILICO CALCAREO TIPO P14 H<2.6M | D18: m2 | E18: 21.64 | F18: 118.21 | H18: =+ROUND(F18+G18*TC,2) -> #REF! | I18: =+ROUND(E18*F18,2) -> 2558.06 | J18: =+ROUND(E18*G18,2) -> 0 | K18: =+ROUND(I18+J18*TC,2) -> #REF!
B19: =B14+0.0001 -> 5.0102 | C19: ALTURA > 2.60
B20: =B19+0.000001 -> 5.010201 | C20: LADRILLO SILICO CALCAREO TIPO P7 H>2.6M | D20: m2 | E20: 73.58 | F20: 104.71 | H20: =+ROUND(F20+G20*TC,2) -> #REF! | I20: =+ROUND(E20*F20,2) -> 7704.56 | J20: =+ROUND(E20*G20,2) -> 0 | K20: =+ROUND(I20+J20*TC,2) -> #REF!
B21: =B20+0.000001 -> 5.010202 | C21: LADRILLO SILICO CALCAREO TIPO P10 H>2.6M | D21: m2 | E21: 28.17 | F21: 111.71 | H21: =+ROUND(F21+G21*TC,2) -> #REF! | I21: =+ROUND(E21*F21,2) -> 3146.87 | J21: =+ROUND(E21*G21,2) -> 0 | K21: =+ROUND(I21+J21*TC,2) -> #REF!
B22: =B21+0.000001 -> 5.010203 | C22: LADRILLO SILICO CALCAREO TIPO P12 H>2.6M | D22: m2 | E22: 37.22 | F22: 117.71 | H22: =+ROUND(F22+G22*TC,2) -> #REF! | I22: =+ROUND(E22*F22,2) -> 4381.17 | J22: =+ROUND(E22*G22,2) -> 0 | K22: =+ROUND(I22+J22*TC,2) -> #REF!
B23: =B22+0.000001 -> 5.010204 | C23: LADRILLO SILICO CALCAREO TIPO P14 H>2.6M | D23: m2 | E23: 9.99 | F23: 126.21 | H23: =+ROUND(F23+G23*TC,2) -> #REF! | I23: =+ROUND(E23*F23,2) -> 1260.84 | J23: =+ROUND(E23*G23,2) -> 0 | K23: =+ROUND(I23+J23*TC,2) -> #REF!
B24: =B19+0.0001 -> 5.0103 | C24: CORTAFUEGO < 2.60 | E24: 0
B25: =B23+0.000001 -> 5.010205 | C25: LADRILLO SILICO CALCAREO TIPO P7 RF:2 HRS H<2.6M (ALVEOLOS COMPLETAMENTE LLENO) | D25: m2 | E25: 6.07 | F25: 106.71 | H25: =+ROUND(F25+G25*TC,2) -> #REF! | I25: =+ROUND(E25*F25,2) -> 647.73 | J25: =+ROUND(E25*G25,2) -> 0 | K25: =+ROUND(I25+J25*TC,2) -> #REF!
B26: =B24+0.000001 -> 5.010301 | C26: LADRILLO SILICO CALCAREO TIPO P10 RF:2 HRS H<2.6M (ALVEOLOS COMPLETAMENTE LLENO) | D26: m2 | E26: 7.82 | F26: 113.71 | H26: =+ROUND(F26+G26*TC,2) -> #REF! | I26: =+ROUND(E26*F26,2) -> 889.21 | J26: =+ROUND(E26*G26,2) -> 0 | K26: =+ROUND(I26+J26*TC,2) -> #REF!
B27: =B26+0.000001 -> 5.010302 | C27: LADRILLO SILICO CALCAREO TIPO P12 RF:2 HRS H<2.6M (ALVEOLOS PARCIALMENTE LLENO) | D27: m2 | E27: 143.68 | F27: 109.71 | H27: =+ROUND(F27+G27*TC,2) -> #REF! | I27: =+ROUND(E27*F27,2) -> 15763.13 | J27: =+ROUND(E27*G27,2) -> 0 | K27: =+ROUND(I27+J27*TC,2) -> #REF!
B28: =B24+0.0001 -> 5.0104 | C28: CORTAFUEGO > 2.60
B29: =B27+0.000001 -> 5.010303 | C29: LADRILLO SILICO CALCAREO TIPO P7 RF:2 HRS H>2.6M (ALVEOLOS COMPLETAMENTE LLENO) | D29: m2 | E29: 4.92 | F29: 114.71 | H29: =+ROUND(F29+G29*TC,2) -> #REF! | I29: =+ROUND(E29*F29,2) -> 564.37 | J29: =+ROUND(E29*G29,2) -> 0 | K29: =+ROUND(I29+J29*TC,2) -> #REF!
B30: =B28+0.000001 -> 5.010401 | C30: LADRILLO SILICO CALCAREO TIPO P10 RF:2 HRS H>2.6M (ALVEOLOS COMPLETAMENTE LLENO) | D30: m2 | E30: 46.38 | F30: 121.71 | H30: =+ROUND(F30+G30*TC,2) -> #REF! | I30: =+ROUND(E30*F30,2) -> 5644.91 | J30: =+ROUND(E30*G30,2) -> 0 | K30: =+ROUND(I30+J30*TC,2) -> #REF!
B31: =B30+0.000001 -> 5.010402 | C31: LADRILLO SILICO CALCAREO TIPO P12 RF:2 HRS H>2.6M (ALVEOLOS PARCIALMENTE LLENO) | D31: m2 | E31: 129.77 | F31: 117.71 | H31: =+ROUND(F31+G31*TC,2) -> #REF! | I31: =+ROUND(E31*F31,2) -> 15275.23 | J31: =+ROUND(E31*G31,2) -> 0 | K31: =+ROUND(I31+J31*TC,2) -> #REF!
B32: =B31+0.000001 -> 5.010403 | C32: LADRILLO SILICO CALCAREO TIPO P14 RF:2 HRS H>2.6M (ALVEOLOS PARCIALMENTE LLENO) | D32: m2 | E32: 11.36 | F32: 126.21 | H32: =+ROUND(F32+G32*TC,2) -> #REF! | I32: =+ROUND(E32*F32,2) -> 1433.75 | J32: =+ROUND(E32*G32,2) -> 0 | K32: =+ROUND(I32+J32*TC,2) -> #REF!
B33: =B28+0.0001 -> 5.0105 | C33: ACERO DE REFUERZO
B34: =B33+0.000001 -> 5.010501 | C34: ACERO DE REFUERZO FY= 4200 kg/cm2 GRADO 60 PARA TABIQUERÍA | D34: kg | E34: 1656.54 | F34: 0 | G34: 0.91 | H34: =+ROUND(F34+G34*TC,2) -> #REF! | I34: =+ROUND(E34*F34,2) -> 0 | J34: =+ROUND(E34*G34,2) -> 1507.45 | K34: =+ROUND(I34+J34*TC,2) -> #REF!
B35: =B33+0.0001 -> 5.0106 | C35: DINTELES
B36: =B35+0.000001 -> 5.010601 | C36: DINTELES DE LADRILLOS SILICO CALCAREO | D36: und | E36: 103 | F36: 120 | H36: =+ROUND(F36+G36*TC,2) -> #REF! | I36: =+ROUND(E36*F36,2) -> 12360 | J36: =+ROUND(E36*G36,2) -> 0 | K36: =+ROUND(I36+J36*TC,2) -> #REF!
B37: =B36+0.000001 -> 5.010602 | C37: DINTELES DE LADRILLO SILICO CALCAREO RF | D37: und | E37: 6 | F37: 125 | H37: =+ROUND(F37+G37*TC,2) -> #REF! | I37: =+ROUND(E37*F37,2) -> 750 | J37: =+ROUND(E37*G37,2) -> 0 | K37: =+ROUND(I37+J37*TC,2) -> #REF!
B38: =B35+0.0001 -> 5.0107 | C38: TRABAJOS COMPLEMENTARIOS DE TABIQUERIA
B39: =B38+0.000001 -> 5.010701 | C39: PASES DE MANGUERA (0.20x20M) DOBLE PLACA DE ROCA DE YESO | D39: und | E39: 6 | F39: 80 | H39: =+ROUND(F39+G39*TC,2) -> #REF! | I39: =+ROUND(E39*F39,2) -> 480 | J39: =+ROUND(E39*G39,2) -> 0 | K39: =+ROUND(I39+J39*TC,2) -> #REF!
B40: =B13+0.0001 -> 5.0102 | C40: TABIQUERIA DE DRYWALL | H40: =IFERROR(IF(D40<>0,(F40+G40*TC)," ")," ") | I40: =IFERROR(IF($E40=0,"",$E40*F40),"") | J40: =IFERROR(IF($E40=0,"",$E40*G40),"") | K40: =IFERROR(IF(E40<>0,(E40*H40)," "),0)
B41: =B40+0.00001 -> 5.01021 | C41: MUROS DE DRYWALL | H41: =IFERROR(IF(D41<>0,(F41+G41*TC)," ")," ") | I41: =IFERROR(IF($E41=0,"",$E41*F41),"") | J41: =IFERROR(IF($E41=0,"",$E41*G41),"") | K41: =IFERROR(IF(E41<>0,(E41*H41)," "),0)
C42: FALSO MURO DRYWALL - GRUPO ELECTRÓGENO | D42: m2 | E42: 5.09 | F42: 145 | H42: =+ROUND(F42+G42*TC,2) -> #REF! | I42: =+ROUND(E42*F42,2) -> 738.05 | J42: =+ROUND(E42*G42,2) -> 0 | K42: =+ROUND(I42+J42*TC,2) -> #REF!
B43: =B41+0.0001 -> 5.01031 | C43: DINTELES DE DRYWALL
C44: DINTELES RF EN ASCENSORES (SOTANOS 2) h=0.21m | D44: m | E44: 1.9 | F44: 145 | H44: =+ROUND(F44+G44*TC,2) -> #REF! | I44: =+ROUND(E44*F44,2) -> 275.5 | J44: =+ROUND(E44*G44,2) -> 0 | K44: =+ROUND(I44+J44*TC,2) -> #REF!
C45: DINTELES RF EN ASCENSORES (SOTANO 1) h=1.23m | D45: m | E45: 1.9 | F45: 145 | H45: =+ROUND(F45+G45*TC,2) -> #REF! | I45: =+ROUND(E45*F45,2) -> 275.5 | J45: =+ROUND(E45*G45,2) -> 0 | K45: =+ROUND(I45+J45*TC,2) -> #REF!
B46: =B40+0.0001 -> 5.0103 | C46: SARDINELES | H46: =IFERROR(IF(D46<>0,(F46+G46*TC)," ")," ") | I46: =IFERROR(IF($E46=0,"",$E46*F46),"") | J46: =IFERROR(IF($E46=0,"",$E46*G46),"") | K46: =IFERROR(IF(E46<>0,(E46*H46)," "),0)
B47: =B46+0.000001 -> 5.010301 | C47: SARDINEL H:0.15M (E=10CM)CUARTO DE BASURA | D47: m | E47: 2.59 | F47: 49.53 | G47: 1.09 | H47: =+ROUND(F47+G47*TC,2) -> #REF! | I47: =+ROUND(E47*F47,2) -> 128.28 | J47: =+ROUND(E47*G47,2) -> 2.82 | K47: =+ROUND(I47+J47*TC,2) -> #REF!
B48: =B47+0.000001 -> 5.010302 | C48: SARDINEL EN PUERTA DE DUCTO P-19,P-10 H:0.10M (E=10CM) | D48: m | E48: 12.73 | F48: 42.92 | G48: 0.73 | H48: =+ROUND(F48+G48*TC,2) -> #REF! | I48: =+ROUND(E48*F48,2) -> 546.37 | J48: =+ROUND(E48*G48,2) -> 9.29 | K48: =+ROUND(I48+J48*TC,2) -> #REF!
B49: =B48+0.000001 -> 5.010303 | C49: SARDINEL EN CLOSET DE LIMPIEZA P-4,P-5 H:0.10M (E=10CM) | D49: m | E49: 7.35 | F49: 42.92 | G49: 0.73 | H49: =+ROUND(F49+G49*TC,2) -> #REF! | I49: =+ROUND(E49*F49,2) -> 315.46 | J49: =+ROUND(E49*G49,2) -> 5.37 | K49: =+ROUND(I49+J49*TC,2) -> #REF!
B50: =B12+0.01 -> 5.02 | C50: REVOQUES Y ENLUCIDOS | L50: =SUM(I51:I56)+SUM(J51:J56)*TC -> #REF!
B51: =B50+0.0001 -> 5.0201 | C51: SOLAQUEO DE MURO PANTALLA | D51: m2 | E51: 1599.43 | F51: 16.03 | H51: =+ROUND(F51+G51*TC,2) -> #REF! | I51: =+ROUND(E51*F51,2) -> 25638.86 | J51: =+ROUND(E51*G51,2) -> 0 | K51: =+ROUND(I51+J51*TC,2) -> #REF!
B52: =B51+0.0001 -> 5.0202 | C52: SOLAQUEO EN COLUMNAS Y PLACAS | D52: m2 | E52: 1989.4 | F52: 15.66 | H52: =+ROUND(F52+G52*TC,2) -> #REF! | I52: =+ROUND(E52*F52,2) -> 31154 | J52: =+ROUND(E52*G52,2) -> 0 | K52: =+ROUND(I52+J52*TC,2) -> #REF!
B53: =B52+0.0001 -> 5.0203 | C53: SOLAQUEO DE DUCTOS DE ASCENSORES | D53: m2 | E53: 234.3 | F53: 23.85 | H53: =+ROUND(F53+G53*TC,2) -> #REF! | I53: =+ROUND(E53*F53,2) -> 5588.06 | J53: =+ROUND(E53*G53,2) -> 0 | K53: =+ROUND(I53+J53*TC,2) -> #REF!
B54: =B53+0.0001 -> 5.0204 | C54: LIMPIEZA DE DUCTOS DE VENTILACION | D54: m2 | E54: 358.44 | F54: 8.28 | H54: =+ROUND(F54+G54*TC,2) -> #REF! | I54: =+ROUND(E54*F54,2) -> 2967.88 | J54: =+ROUND(E54*G54,2) -> 0 | K54: =+ROUND(I54+J54*TC,2) -> #REF!
B55: =B54+0.0001 -> 5.0205 | C55: SOLAQUEO DE MUROS Y PLACAS DE ESCALERA | D55: m2 | E55: 253.92 | F55: 15.98 | H55: =+ROUND(F55+G55*TC,2) -> #REF! | I55: =+ROUND(E55*F55,2) -> 4057.64 | J55: =+ROUND(E55*G55,2) -> 0 | K55: =+ROUND(I55+J55*TC,2) -> #REF!
B56: =B55+0.0001 -> 5.0206 | C56: IMPERMEABILIZACION DE CISTERNAS: LIMPIEZA MANUAL + SELLADO SUPERFICIE Y RESANE DE GRIETAS Y/O FISURAS + LAVADO SUPERFICIE + INSTALACION DE MAPEBAND EASY CON MORTERO FLEXIBLE + IMPERMEABILIZANTE Z TOP FLEXIBLE + CURADO DE AREAS IMPERMEABILIZADAS | D56: m2 | E56: 281.93 | F56: 53 | H56: =+ROUND(F56+G56*TC,2) -> #REF! | I56: =+ROUND(E56*F56,2) -> 14942.29 | J56: =+ROUND(E56*G56,2) -> 0 | K56: =+ROUND(I56+J56*TC,2) -> #REF!
B57: =B50+0.01 -> 5.03 | C57: CIELORASOS | L57: =SUM(I57:I60)+SUM(J57:J60)*TC -> #REF!
B58: =B57+0.0001 -> 5.0301 | C58: LIMPIEZA Y RESANE DE PRELOSAS EN SÓTANOS (INC LIMPIEZA DE TECHO DE CISTERNA Y CTO BOMBAS) | D58: m2 | E58: 3835.64 | F58: 3.7 | H58: =+ROUND(F58+G58*TC,2) -> #REF! | I58: =+ROUND(E58*F58,2) -> 14191.87 | J58: =+ROUND(E58*G58,2) -> 0 | K58: =+ROUND(I58+J58*TC,2) -> #REF!
B59: =B57+0.0001 -> 5.0301 | C59: SOLAQUEO DE CIELO RASO EN ESCALERA | D59: m2 | E59: 32.91 | F59: 18.47 | H59: =+ROUND(F59+G59*TC,2) -> #REF! | I59: =+ROUND(E59*F59,2) -> 607.85 | J59: =+ROUND(E59*G59,2) -> 0 | K59: =+ROUND(I59+J59*TC,2) -> #REF!
B60: =B58+0.0001 -> 5.0302 | C60: SOLAQUEO DE VIGAS EN SOTANOS (EN FONDO Y COSTADO) | D60: m2 | E60: 654.89 | F60: 21.76 | H60: =+ROUND(F60+G60*TC,2) -> #REF! | I60: =+ROUND(E60*F60,2) -> 14250.41 | J60: =+ROUND(E60*G60,2) -> 0 | K60: =+ROUND(I60+J60*TC,2) -> #REF!
B61: =B57+0.01 -> 5.04 | C61: PISOS | L61: =SUM(I61:I79)+SUM(J61:J79)*TC -> #REF!
B62: =B61+0.0001 -> 5.0401 | C62: NIVELACION DE PISOS
B63: =B62+0.000001 -> 5.040101 | C63: NIVELACIÓN DE PISO | D63: m2 | E63: 56.96 | F63: 18.03 | H63: =+ROUND(F63+G63*TC,2) -> #REF! | I63: =+ROUND(E63*F63,2) -> 1026.99 | J63: =+ROUND(E63*G63,2) -> 0 | K63: =+ROUND(I63+J63*TC,2) -> #REF!
B64: =B62+0.0001 -> 5.0402 | C64: CTO MAQUINAS
B65: =B64+0.000001 -> 5.040201 | C65: PISO CEMENTO PULIDO | D65: m2 | E65: 59.57 | F65: 43.71 | H65: =+ROUND(F65+G65*TC,2) -> #REF! | I65: =+ROUND(E65*F65,2) -> 2603.8 | J65: =+ROUND(E65*G65,2) -> 0 | K65: =+ROUND(I65+J65*TC,2) -> #REF!
B66: =B64+0.0001 -> 5.0403 | C66: SUBESTACION/ ACELEROGRAFO/ VESTIBULO PREVIO/ CTO GE
B67: =B66+0.000001 -> 5.040301 | C67: PISO CEMENTO PULIDO | D67: m2 | E67: 70.57 | F67: 43.71 | H67: =+ROUND(F67+G67*TC,2) -> #REF! | I67: =+ROUND(E67*F67,2) -> 3084.61 | J67: =+ROUND(E67*G67,2) -> 0 | K67: =+ROUND(I67+J67*TC,2) -> #REF!
B68: =B66+0.0001 -> 5.0404 | C68: DEPOSITOS / HALL
B69: =B68+0.000001 -> 5.040401 | C69: PISO CEMENTO SEMIPULIDO | D69: m2 | E69: 427.47 | F69: 41.98 | H69: =+ROUND(F69+G69*TC,2) -> #REF! | I69: =+ROUND(E69*F69,2) -> 17945.19 | J69: =+ROUND(E69*G69,2) -> 0 | K69: =+ROUND(I69+J69*TC,2) -> #REF!
B70: =B68+0.0001 -> 5.0405 | C70: ESTACIONAMIENTOS VEHICULARES/ BICICLETAS
B71: =B70+0.000001 -> 5.040501 | C71: PISO CEMENTO BARRIDO | D71: m2 | E71: 2151.7 | F71: 14.23 | H71: =+ROUND(F71+G71*TC,2) -> #REF! | I71: =+ROUND(E71*F71,2) -> 30618.69 | J71: =+ROUND(E71*G71,2) -> 0 | K71: =+ROUND(I71+J71*TC,2) -> #REF!
B72: =B70+0.0001 -> 5.0406 | C72: RAMPAS
B73: =B72+0.000001 -> 5.040601 | C73: PISO CEMENTO BRUÑADO | D73: m2 | E73: 1367.5 | F73: 44.73 | H73: =+ROUND(F73+G73*TC,2) -> #REF! | I73: =+ROUND(E73*F73,2) -> 61168.28 | J73: =+ROUND(E73*G73,2) -> 0 | K73: =+ROUND(I73+J73*TC,2) -> #REF!
B74: =B72+0.0001 -> 5.0407 | C74: CISTERNA
B75: =B74+0.000001 -> 5.040701 | C75: PISO CEMENTO PULIDO IMPERMEABILIZADO EN CISTERNA | D75: m2 | E75: 141.07 | F75: 53 | H75: =+ROUND(F75+G75*TC,2) -> #REF! | I75: =+ROUND(E75*F75,2) -> 7476.71 | J75: =+ROUND(E75*G75,2) -> 0 | K75: =+ROUND(I75+J75*TC,2) -> #REF!
B76: =B74+0.0001 -> 5.0408 | C76: CTO DE ACOPIO
B77: =B76+0.000001 -> 5.040801 | C77: CERAMICO DIAMANTE BLANCO 46X46 cm | D77: m2 | E77: 26.91 | F77: 75.27 | H77: =+ROUND(F77+G77*TC,2) -> #REF! | I77: =+ROUND(E77*F77,2) -> 2025.52 | J77: =+ROUND(E77*G77,2) -> 0 | K77: =+ROUND(I77+J77*TC,2) -> #REF!
B78: =B76+0.0001 -> 5.0409 | C78: CTO DE LIMPIEZA
B79: =B78+0.000001 -> 5.040901 | C79: CERAMICO AMERICA BLANCO 45x45CM. CELIMA | D79: m2 | E79: 6.11 | F79: 71.91 | H79: =+ROUND(F79+G79*TC,2) -> #REF! | I79: =+ROUND(E79*F79,2) -> 439.37 | J79: =+ROUND(E79*G79,2) -> 0 | K79: =+ROUND(I79+J79*TC,2) -> #REF!
B80: =B73+0.01 -> 5.050601 | C80: ZOCALOS | L80: =SUM(I80:I82)+SUM(J80:J82)*TC -> #REF!
B81: 05.05.01 | C81: CERAMICO DIAMANTE BLANCO 46X46 cm | D81: m2 | E81: 54.96 | F81: 75.27 | H81: =+ROUND(F81+G81*TC,2) -> #REF! | I81: =+ROUND(E81*F81,2) -> 4136.84 | J81: =+ROUND(E81*G81,2) -> 0 | K81: =+ROUND(I81+J81*TC,2) -> #REF!
B82: =B80+0.01 -> 5.060601 | C82: CONTRAZÓCALOS | L82: =SUM(I83:I92)+SUM(J83:J92)*TC -> #REF!
B83: =B82+0.0001 -> 5.060701 | C83: CTO GGEE/ DEPOSITOS/ ESTACIONAMIENTO/ CTO BOMBAS /CTOS TECNICOS
B84: =B83+0.000001 -> 5.060702 | C84: CTRZL PINTURA TRAFICO COLOR AMARILLO H=15 CM | D84: ml | E84: 1944.37 | F84: 12.75 | H84: =+ROUND(F84+G84*TC,2) -> #REF! | I84: =+ROUND(E84*F84,2) -> 24790.72 | J84: =+ROUND(E84*G84,2) -> 0 | K84: =+ROUND(I84+J84*TC,2) -> #REF!
B85: =B83+0.0001 -> 5.060801 | C85: VESTIBULO PREVIO Y ESCALERAS
B86: =B85+0.000001 -> 5.060802 | C86: CTRZL PINTURA ESMALTE SINTETICO COLOR NEGRO H=10CM | D86: ml | E86: 120.82 | F86: 12.75 | H86: =+ROUND(F86+G86*TC,2) -> #REF! | I86: =+ROUND(E86*F86,2) -> 1540.46 | J86: =+ROUND(E86*G86,2) -> 0 | K86: =+ROUND(I86+J86*TC,2) -> #REF!
B87: =B85+0.0001 -> 5.060901 | C87: ESTACIONAMIENTOS DE BICICLETAS
B88: =B87+0.000001 -> 5.060902 | C88: PINTURA DE TRAFICO NEGRO H=15CM A NIVEL DE PISO Y A 1.10M SOBRE MURO | D88: ml | E88: 83.67 | F88: 25.5 | H88: =+ROUND(F88+G88*TC,2) -> #REF! | I88: =+ROUND(E88*F88,2) -> 2133.59 | J88: =+ROUND(E88*G88,2) -> 0 | K88: =+ROUND(I88+J88*TC,2) -> #REF!
B89: =B87+0.0001 -> 5.061001 | C89: HALL ASCENSORES
B90: =B89+0.000001 -> 5.061002 | C90: CONTRAZOCALO CERAMICO CONCRETO GRIS 45x45CM. MARCA SAN LORENZO | D90: ml | E90: 31.8 | F90: 22 | H90: =+ROUND(F90+G90*TC,2) -> #REF! | I90: =+ROUND(E90*F90,2) -> 699.6 | J90: =+ROUND(E90*G90,2) -> 0 | K90: =+ROUND(I90+J90*TC,2) -> #REF!
B91: =B89+0.0001 -> 5.061101 | C91: CTO LIMPIEZA
B92: =B91+0.000001 -> 5.061102 | C92: CONTRAZOCALO CERAMICO AMERICA BLANCO 45x45CM. | D92: ml | E92: 23.02 | F92: 21.98 | H92: =+ROUND(F92+G92*TC,2) -> #REF! | I92: =+ROUND(E92*F92,2) -> 505.98 | J92: =+ROUND(E92*G92,2) -> 0 | K92: =+ROUND(I92+J92*TC,2) -> #REF!
B93: =B82+0.01 -> 5.070601 | C93: REVESTIMIENTOS DE ESCALERAS | L93: =SUM(I94:I101)+SUM(J94:J101)*TC -> #REF!
B94: =B93+0.0001 -> 5.070701 | C94: ESCALERA DE EVACUACIÓN
B95: =B94+0.000001 -> 5.070702 | C95: FORJADO DE DESCANSO (ESCALERA DE EVACUACION) | D95: m2 | E95: 29.43 | F95: 72.43 | H95: =+ROUND(F95+G95*TC,2) -> #REF! | I95: =+ROUND(E95*F95,2) -> 2131.61 | J95: =+ROUND(E95*G95,2) -> 0 | K95: =+ROUND(I95+J95*TC,2) -> #REF!
B96: =B95+0.000001 -> 5.070703 | C96: FORJADO DE PASOS Y CONTRAPASOS (ESCALERA DE EVACUACION) | D96: ml | E96: 117.25 | F96: 42.46 | H96: =+ROUND(F96+G96*TC,2) -> #REF! | I96: =+ROUND(E96*F96,2) -> 4978.44 | J96: =+ROUND(E96*G96,2) -> 0 | K96: =+ROUND(I96+J96*TC,2) -> #REF!
B97: =B96+0.000001 -> 5.070704 | C97: ACABADO EN CEMENTO PULIDO DE DESCANSO (ESCALERA DE EVACUACION) | D97: m2 | E97: 29.43 | F97: 19.85 | H97: =+ROUND(F97+G97*TC,2) -> #REF! | I97: =+ROUND(E97*F97,2) -> 584.19 | J97: =+ROUND(E97*G97,2) -> 0 | K97: =+ROUND(I97+J97*TC,2) -> #REF!
B98: =B97+0.000001 -> 5.070705 | C98: ACABADO EN CEMENTO PULIDO DE PASOS Y CONTRAPASOS (ESCALERA DE EVACUACION) | D98: ml | E98: 117.25 | F98: 15.04 | H98: =+ROUND(F98+G98*TC,2) -> #REF! | I98: =+ROUND(E98*F98,2) -> 1763.44 | J98: =+ROUND(E98*G98,2) -> 0 | K98: =+ROUND(I98+J98*TC,2) -> #REF!
B99: =B98+0.000001 -> 5.070706 | C99: CANTONERA DE BRUÑAS (2UND) (ESCALERA DE EVACUACION) | D99: ml | E99: 117.25 | F99: 11.83 | H99: =+ROUND(F99+G99*TC,2) -> #REF! | I99: =+ROUND(E99*F99,2) -> 1387.07 | J99: =+ROUND(E99*G99,2) -> 0 | K99: =+ROUND(I99+J99*TC,2) -> #REF!
B100: =B99+0.000001 -> 5.070707 | C100: SOLAQUEO DE FONDO DE ESCALERA (ESCALERA DE EVACUACION) | D100: m2 | E100: 50.13 | F100: 16.69 | H100: =+ROUND(F100+G100*TC,2) -> #REF! | I100: =+ROUND(E100*F100,2) -> 836.67 | J100: =+ROUND(E100*G100,2) -> 0 | K100: =+ROUND(I100+J100*TC,2) -> #REF!
B101: =B100+0.000001 -> 5.070708 | C101: DERRAME EN COSTADO DE ESCALERA (ESCALERA DE EVACUACION) | D101: ml | E101: 17.25 | F101: 19.31 | H101: =+ROUND(F101+G101*TC,2) -> #REF! | I101: =+ROUND(E101*F101,2) -> 333.1 | J101: =+ROUND(E101*G101,2) -> 0 | K101: =+ROUND(I101+J101*TC,2) -> #REF!
B102: =B93+0.01 -> 5.080601 | C102: PUERTAS | L102: =SUM(I103:I125)+SUM(J103:J125)*TC -> #REF!
B103: =B102+0.0001 -> 5.080701 | C103: PUERTAS CORTAFUEGO
...

Sheet ARQ TORRE
B2: ARQUITECTURA TORRE
B4: Presupuesto | C4: =OP!$B$4 -> #REF!
B5: Subpresupuesto | C5: =$B$2 -> ARQUITECTURA TORRE
B6: Cliente | C6: =OP!$B$6 -> #REF!
B7: Lugar | C7: =OP!$B$7 -> #REF!
B8: Fecha | C8: =#REF! -> #REF!
B10: ITEM | C10: DESCRIPCION | D10: UND | E10: METRADO | F10: P.U. (PEN) | G10: P.U. (USD) | H10: P.U. TOTAL (PEN) | I10: PRECIO PARCIAL (PEN) | J10: PRECIO PARCIAL (USD) | K10: PARCIAL TOTAL (PEN) | L10: TOTAL
B11: 06 | C11: =$B$2 -> ARQUITECTURA TORRE
B12: =B11+0.01 -> 6.01 | C12: MUROS Y TABIQUES | H12: =IFERROR(IF(D12<>0,F12+G12*TC," ")," ") | I12: =IFERROR(IF($E12=0,"",$E12*F12),"") | J12: =IFERROR(IF($E12=0,"",$E12*G12),"") | K12: =IFERROR(IF(E12<>0,(E12*H12)," "),0) | L12: =SUM(I12:I88)+SUM(J12:J88)*TC -> #REF! | M12: =+L12+L124+L128 -> #REF!
B13: =B12+0.0001 -> 6.0101 | C13: MUROS Y TABIQUES SILICO CALCAREOS, ALBAÑILERIA , CONCRETO | H13: =IFERROR(IF(D13<>0,(F13+G13*TC)," ")," ") | I13: =IFERROR(IF($E13=0,"",$E13*F13),"") | J13: =IFERROR(IF($E13=0,"",$E13*G13),"") | K13: =IFERROR(IF(E13<>0,(E13*H13)," "),0)
B14: =B13+0.000001 -> 6.010101 | C14: ALTURA < 2.60 | H14: =IFERROR(IF(D14<>0,(F14+G14*TC)," ")," ") | I14: =IFERROR(IF($E14=0,"",$E14*F14),"") | J14: =IFERROR(IF($E14=0,"",$E14*G14),"") | K14: =IFERROR(IF(E14<>0,(E14*H14)," "),0)
B15: =B14+0.00000001 -> 6.010101 | C15: LADRILLO SILICO CALCAREO TIPO P7 H<2.6M | D15: m2 | E15: 1192.22 | F15: 96.71 | H15: =+ROUND(F15+G15*TC,2) -> #REF! | I15: =+ROUND(E15*F15,2) -> 115299.6 | J15: =+ROUND(E15*G15,2) -> 0 | K15: =+ROUND(I15+J15*TC,2) -> #REF!
B16: =B15+0.00000001 -> 6.010101 | C16: LADRILLO SILICO CALCAREO TIPO P10 H<2.6M | D16: m2 | E16: 3804.01 | F16: 103.71 | H16: =+ROUND(F16+G16*TC,2) -> #REF! | I16: =+ROUND(E16*F16,2) -> 394513.88 | J16: =+ROUND(E16*G16,2) -> 0 | K16: =+ROUND(I16+J16*TC,2) -> #REF!
B17: =B16+0.00000001 -> 6.010101 | C17: LADRILLO SILICO CALCAREO TIPO P12 H<2.6M | D17: m2 | E17: 659.47 | F17: 109.71 | H17: =+ROUND(F17+G17*TC,2) -> #REF! | I17: =+ROUND(E17*F17,2) -> 72350.45 | J17: =+ROUND(E17*G17,2) -> 0 | K17: =+ROUND(I17+J17*TC,2) -> #REF!
B18: =B17+0.00000001 -> 6.010101 | C18: LADRILLO SILICO CALCAREO TIPO P14 H<2.6M | D18: m2 | E18: 1505.43 | F18: 118.21 | H18: =+ROUND(F18+G18*TC,2) -> #REF! | I18: =+ROUND(E18*F18,2) -> 177956.88 | J18: =+ROUND(E18*G18,2) -> 0 | K18: =+ROUND(I18+J18*TC,2) -> #REF!
B19: =B17+0.00000001 -> 6.010101 | C19: LADRILLO SILICO CALCAREO TIPO P20 H<2.6M | D19: m2 | E19: 34.05 | F19: 199.21 | H19: =+ROUND(F19+G19*TC,2) -> #REF! | I19: =+ROUND(E19*F19,2) -> 6783.1 | J19: =+ROUND(E19*G19,2) -> 0 | K19: =+ROUND(I19+J19*TC,2) -> #REF!
B20: =B18+0.00000001 -> 6.010101 | C20: LADRILLO SILICO CALCAREO TIPO P25 H<2.6M | D20: m2 | E20: 55.4 | F20: 211.21 | H20: =+ROUND(F20+G20*TC,2) -> #REF! | I20: =+ROUND(E20*F20,2) -> 11701.03 | J20: =+ROUND(E20*G20,2) -> 0 | K20: =+ROUND(I20+J20*TC,2) -> #REF!
B21: =B18+0.00000001 -> 6.010101 | C21: LADRILLO SILICO CALCAREO TIPO P30 H<2.6M | D21: m2 | E21: 49.5 | F21: 211.21 | H21: =+ROUND(F21+G21*TC,2) -> #REF! | I21: =+ROUND(E21*F21,2) -> 10454.9 | J21: =+ROUND(E21*G21,2) -> 0 | K21: =+ROUND(I21+J21*TC,2) -> #REF!
B22: =B21+0.00000001 -> 6.0101011 | C22: LADRILLO SILICO CALCAREO TIPO P40 H<2.6M | D22: m2 | E22: 4.09 | F22: 211.21 | H22: =+ROUND(F22+G22*TC,2) -> #REF! | I22: =+ROUND(E22*F22,2) -> 863.85 | J22: =+ROUND(E22*G22,2) -> 0 | K22: =+ROUND(I22+J22*TC,2) -> #REF!
B23: =B14+0.000001 -> 6.010102 | C23: ALTURA > 2.60 | E23: 0
B24: =B23+0.00000001 -> 6.010102 | C24: LADRILLO SILICO CALCAREO TIPO P7 H>2.6M | D24: m2 | E24: 36.46 | F24: 104.71 | H24: =+ROUND(F24+G24*TC,2) -> #REF! | I24: =+ROUND(E24*F24,2) -> 3817.73 | J24: =+ROUND(E24*G24,2) -> 0 | K24: =+ROUND(I24+J24*TC,2) -> #REF!
B25: =B23+0.00000001 -> 6.010102 | C25: LADRILLO SILICO CALCAREO TIPO P10 H>2.6M | D25: m2 | E25: 153.89 | F25: 111.71 | H25: =+ROUND(F25+G25*TC,2) -> #REF! | I25: =+ROUND(E25*F25,2) -> 17191.05 | J25: =+ROUND(E25*G25,2) -> 0 | K25: =+ROUND(I25+J25*TC,2) -> #REF!
B26: =B25+0.00000001 -> 6.010102 | C26: LADRILLO SILICO CALCAREO TIPO P12 H>2.6M | D26: m2 | E26: 184.69 | F26: 117.71 | H26: =+ROUND(F26+G26*TC,2) -> #REF! | I26: =+ROUND(E26*F26,2) -> 21739.86 | J26: =+ROUND(E26*G26,2) -> 0 | K26: =+ROUND(I26+J26*TC,2) -> #REF!
B27: =B26+0.00000001 -> 6.010102 | C27: LADRILLO SILICO CALCAREO TIPO P14 H>2.6M | D27: m2 | E27: 157.51 | F27: 126.21 | H27: =+ROUND(F27+G27*TC,2) -> #REF! | I27: =+ROUND(E27*F27,2) -> 19879.34 | J27: =+ROUND(E27*G27,2) -> 0 | K27: =+ROUND(I27+J27*TC,2) -> #REF!
B28: =B27+0.00000001 -> 6.010102 | C28: LADRILLO SILICO CALCAREO TIPO P20 H>2.6M | D28: m2 | E28: 0.95 | F28: 215.21 | H28: =+ROUND(F28+G28*TC,2) -> #REF! | I28: =+ROUND(E28*F28,2) -> 204.45 | J28: =+ROUND(E28*G28,2) -> 0 | K28: =+ROUND(I28+J28*TC,2) -> #REF!
B29: =B28+0.00000001 -> 6.010102 | C29: LADRILLO SILICO CALCAREO TIPO P25 H>2.6M | D29: m2 | E29: 5.18 | F29: 227.21 | H29: =+ROUND(F29+G29*TC,2) -> #REF! | I29: =+ROUND(E29*F29,2) -> 1176.95 | J29: =+ROUND(E29*G29,2) -> 0 | K29: =+ROUND(I29+J29*TC,2) -> #REF!
B30: =B28+0.00000001 -> 6.010102 | C30: LADRILLO SILICO CALCAREO TIPO P35 H>2.6M | D30: m2 | E30: 3.66 | F30: 227.21 | H30: =+ROUND(F30+G30*TC,2) -> #REF! | I30: =+ROUND(E30*F30,2) -> 831.59 | J30: =+ROUND(E30*G30,2) -> 0 | K30: =+ROUND(I30+J30*TC,2) -> #REF!
B31: =B23+0.000001 -> 6.010103 | C31: CORTAFUEGO < 2.60 | E31: 0
B32: =B31+0.00000001 -> 6.010103 | C32: LADRILLO SILICO CALCAREO TIPO P10 RF:2 HRS H<2.6M (ALVEOLOS COMPLETAMENTE LLENO) | D32: m2 | E32: 1455.53 | F32: 113.71 | H32: =+ROUND(F32+G32*TC,2) -> #REF! | I32: =+ROUND(E32*F32,2) -> 165508.32 | J32: =+ROUND(E32*G32,2) -> 0 | K32: =+ROUND(I32+J32*TC,2) -> #REF!
B33: =B32+0.00000001 -> 6.010103 | C33: LADRILLO SILICO CALCAREO TIPO P12 RF:2 HRS H<2.6M (ALVEOLOS PARCIALMENTE LLENO) | D33: m2 | E33: 4994.87 | F33: 109.71 | H33: =+ROUND(F33+G33*TC,2) -> #REF! | I33: =+ROUND(E33*F33,2) -> 547987.19 | J33: =+ROUND(E33*G33,2) -> 0 | K33: =+ROUND(I33+J33*TC,2) -> #REF!
B34: =B33+0.00000001 -> 6.010103 | C34: LADRILLO SILICO CALCAREO TIPO P14 RF:2 HRS H<2.6M (ALVEOLOS PARCIALMENTE LLENO) | D34: m2 | E34: 548.37 | F34: 118.21 | H34: =+ROUND(F34+G34*TC,2) -> #REF! | I34: =+ROUND(E34*F34,2) -> 64822.82 | J34: =+ROUND(E34*G34,2) -> 0 | K34: =+ROUND(I34+J34*TC,2) -> #REF!
B35: =B33+0.00000001 -> 6.010103 | C35: LADRILLO SILICO CALCAREO TIPO P20 RF:2 HRS H<2.6M (ALVEOLOS PARCIALMENTE LLENO) | D35: m2 | E35: 91.37 | F35: 219.21 | H35: =+ROUND(F35+G35*TC,2) -> #REF! | I35: =+ROUND(E35*F35,2) -> 20029.22 | J35: =+ROUND(E35*G35,2) -> 0 | K35: =+ROUND(I35+J35*TC,2) -> #REF!
B36: =B34+0.00000001 -> 6.010103 | C36: LADRILLO SILICO CALCAREO TIPO P25 RF:2 HRS H<2.6M (ALVEOLOS PARCIALMENTE LLENO) | D36: m2 | E36: 164.22 | F36: 211.21 | H36: =+ROUND(F36+G36*TC,2) -> #REF! | I36: =+ROUND(E36*F36,2) -> 34684.91 | J36: =+ROUND(E36*G36,2) -> 0 | K36: =+ROUND(I36+J36*TC,2) -> #REF!
B37: =B34+0.00000001 -> 6.010103 | C37: LADRILLO SILICO CALCAREO TIPO P30 RF:2 HRS H<2.6M (ALVEOLOS PARCIALMENTE LLENO) | D37: m2 | E37: 2 | F37: 211.21 | H37: =+ROUND(F37+G37*TC,2) -> #REF! | I37: =+ROUND(E37*F37,2) -> 422.42 | J37: =+ROUND(E37*G37,2) -> 0 | K37: =+ROUND(I37+J37*TC,2) -> #REF!
B38: =B31+0.000001 -> 6.010104 | C38: CORTAFUEGO > 2.60 | E38: 0
B39: =B38+0.00000001 -> 6.010104 | C39: LADRILLO SILICO CALCAREO TIPO P10 RF:2 HRS H>2.6M (ALVEOLOS COMPLETAMENTE LLENO) | D39: m2 | E39: 141.64 | F39: 121.71 | H39: =+ROUND(F39+G39*TC,2) -> #REF! | I39: =+ROUND(E39*F39,2) -> 17239 | J39: =+ROUND(E39*G39,2) -> 0 | K39: =+ROUND(I39+J39*TC,2) -> #REF!
B40: =B39+0.00000001 -> 6.010104 | C40: LADRILLO SILICO CALCAREO TIPO P12 RF:2 HRS H>2.6M (ALVEOLOS PARCIALMENTE LLENO) | D40: m2 | E40: 313.86 | F40: 117.71 | H40: =+ROUND(F40+G40*TC,2) -> #REF! | I40: =+ROUND(E40*F40,2) -> 36944.46 | J40: =+ROUND(E40*G40,2) -> 0 | K40: =+ROUND(I40+J40*TC,2) -> #REF!
B41: =B40+0.00000001 -> 6.010104 | C41: LADRILLO SILICO CALCAREO TIPO P14 RF:2 HRS H>2.6M (ALVEOLOS PARCIALMENTE LLENO) | D41: m2 | E41: 48.25 | F41: 126.21 | H41: =+ROUND(F41+G41*TC,2) -> #REF! | I41: =+ROUND(E41*F41,2) -> 6089.63 | J41: =+ROUND(E41*G41,2) -> 0 | K41: =+ROUND(I41+J41*TC,2) -> #REF!
B42: =B41+0.00000001 -> 6.010104 | C42: LADRILLO SILICO CALCAREO TIPO P20 RF:2 HRS H>2.6M (ALVEOLOS COMPLETAMENTE LLENO) | D42: m2 | E42: 2.24 | F42: 235.21 | H42: =+ROUND(F42+G42*TC,2) -> #REF! | I42: =+ROUND(E42*F42,2) -> 526.87 | J42: =+ROUND(E42*G42,2) -> 0 | K42: =+ROUND(I42+J42*TC,2) -> #REF!
B43: =B42+0.00000001 -> 6.010104 | C43: LADRILLO SILICO CALCAREO TIPO P25 RF:2 HRS H>2.6M (ALVEOLOS COMPLETAMENTE LLENO) | D43: m2 | E43: 10.63 | F43: 235.21 | H43: =+ROUND(F43+G43*TC,2) -> #REF! | I43: =+ROUND(E43*F43,2) -> 2500.28 | J43: =+ROUND(E43*G43,2) -> 0 | K43: =+ROUND(I43+J43*TC,2) -> #REF!
B44: =B38+0.000001 -> 6.010105 | C44: ACERO DE REFUERZO
B45: =B44+0.00000001 -> 6.010105 | C45: ACERO DE REFUERZO FY= 4200 kg/cm2 GRADO 60 PARA TABIQUERÍA | D45: kg | E45: 23429.24 | F45: 0 | G45: 0.91 | H45: =+ROUND(F45+G45*TC,2) -> #REF! | I45: =+ROUND(E45*F45,2) -> 0 | J45: =+ROUND(E45*G45,2) -> 21320.61 | K45: =+ROUND(I45+J45*TC,2) -> #REF!
B46: =B44+0.000001 -> 6.010106 | C46: DINTELES
B47: =B46+0.00000001 -> 6.010106 | C47: DINTELES DE LADRILLOS SILICO CALCAREO | D47: und | E47: 890 | F47: 120 | H47: =+ROUND(F47+G47*TC,2) -> #REF! | I47: =+ROUND(E47*F47,2) -> 106800 | J47: =+ROUND(E47*G47,2) -> 0 | K47: =+ROUND(I47+J47*TC,2) -> #REF!
B48: =B47+0.00000001 -> 6.010106 | C48: DINTELES DE LADRILLO SILICO CALCAREO RF | D48: und | E48: 66 | F48: 125 | H48: =+ROUND(F48+G48*TC,2) -> #REF! | I48: =+ROUND(E48*F48,2) -> 8250 | J48: =+ROUND(E48*G48,2) -> 0 | K48: =+ROUND(I48+J48*TC,2) -> #REF!
B49: =B46+0.000001 -> 6.010107 | C49: TRABAJOS COMPLEMENTARIOS DE TABIQUERIA
B50: =B49+0.00000001 -> 6.010107 | C50: FORJADO DE TABLEROS | D50: und | E50: 174 | F50: 150 | H50: =+ROUND(F50+G50*TC,2) -> #REF! | I50: =+ROUND(E50*F50,2) -> 26100 | J50: =+ROUND(E50*G50,2) -> 0 | K50: =+ROUND(I50+J50*TC,2) -> #REF!
B51: =B50+0.00000001 -> 6.010107 | C51: ENCOFRADO DE TUBERIAS DE MONTANTE DE VENTILACIÓN | D51: und | E51: 907 | F51: 60 | H51: =+ROUND(F51+G51*TC,2) -> #REF! | I51: =+ROUND(E51*F51,2) -> 54420 | J51: =+ROUND(E51*G51,2) -> 0 | K51: =+ROUND(I51+J51*TC,2) -> #REF!
B52: =B51+0.00000001 -> 6.010107 | C52: PASES DE MANGUERA (0.20x0.20M) | D52: und | E52: 40 | F52: 80 | H52: =+ROUND(F52+G52*TC,2) -> #REF! | I52: =+ROUND(E52*F52,2) -> 3200 | J52: =+ROUND(E52*G52,2) -> 0 | K52: =+ROUND(I52+J52*TC,2) -> #REF!
B53: =B52+0.00000001 -> 6.010107 | C53: NICHOS PARA EXTRACTOR DE SSHH Y VESTIBULOS PREVIOS | D53: und | E53: 489 | F53: 60 | H53: =+ROUND(F53+G53*TC,2) -> #REF! | I53: =+ROUND(E53*F53,2) -> 29340 | J53: =+ROUND(E53*G53,2) -> 0 | K53: =+ROUND(I53+J53*TC,2) -> #REF!
B54: =B53+0.00000001 -> 6.0101071 | C54: NICHOS PARA VALCULAS DE GAS | D54: und | E54: 149 | F54: 60 | H54: =+ROUND(F54+G54*TC,2) -> #REF! | I54: =+ROUND(E54*F54,2) -> 8940 | J54: =+ROUND(E54*G54,2) -> 0 | K54: =+ROUND(I54+J54*TC,2) -> #REF!
B55: =B54+0.00000001 -> 6.0101071 | C55: REJILLAS EN FACHADA PARA EQUIPO "UNICO" (DIAMETRO 20 CM) INC TAPA CIEGA (NO HAY DETALLE) | D55: und | E55: 474 | F55: 150.8 | H55: =+ROUND(F55+G55*TC,2) -> #REF! | I55: =+ROUND(E55*F55,2) -> 71479.2 | J55: =+ROUND(E55*G55,2) -> 0 | K55: =+ROUND(I55+J55*TC,2) -> #REF!
B56: =B49+0.000001 -> 6.010108 | C56: OTROS TABIQUERIA
B57: =B56+0.00000001 -> 6.010108 | C57: CASETA, ALMACEN DE HERRAMIENTAS, VESTIBULO Y BANCAS-SC TABIQUERIA | D57: glb | E57: 1 | F57: 1000 | H57: =+ROUND(F57+G57*TC,2) -> #REF! | I57: =+ROUND(E57*F57,2) -> 1000 | J57: =+ROUND(E57*G57,2) -> 0 | K57: =+ROUND(I57+J57*TC,2) -> #REF!
B58: =B57+0.00000001 -> 6.010108 | C58: SC PREVENCIONISTA DE RIESGO-SC TABIQUERIA | D58: mes | E58: 6 | F58: 4500 | H58: =+ROUND(F58+G58*TC,2) -> #REF! | I58: =+ROUND(E58*F58,2) -> 27000 | J58: =+ROUND(E58*G58,2) -> 0 | K58: =+ROUND(I58+J58*TC,2) -> #REF!
B59: =B56+0.000001 -> 6.010109 | C59: MUORS DE ALBAÑILERIA KK
B60: =B59+0.00000001 -> 6.010109 | C60: MURO DE ALBAÑILERIA KK E:15CM | D60: m2 | E60: 77.22 | F60: 74.04 | H60: =+ROUND(F60+G60*TC,2) -> #REF! | I60: =+ROUND(E60*F60,2) -> 5717.37 | J60: =+ROUND(E60*G60,2) -> 0 | K60: =+ROUND(I60+J60*TC,2) -> #REF!
B61: =B60+0.00000001 -> 6.010109 | C61: MURO DE ALBAÑILERIA KK BANCO DE MEDIDORES H=3.00M, E: 25CM | D61: m2 | E61: 117.61 | F61: 111.41 | H61: =+ROUND(F61+G61*TC,2) -> #REF! | I61: =+ROUND(E61*F61,2) -> 13102.93 | J61: =+ROUND(E61*G61,2) -> 0 | K61: =+ROUND(I61+J61*TC,2) -> #REF!
B62: =B59+0.000001 -> 6.01011 | C62: MUORS DE CONCRETO (SOBREMURO)
B63: =B62+0.00000001 -> 6.01011 | C63: SOBREMURO DE CONCRETO H=2.10 M., PARA INSTALACIONES SANITARIAS - LAVANDERIA COMUN AZOTEA | D63: m2 | E63: 12.43 | F63: 129.76 | G63: 12.74 | H63: =+ROUND(F63+G63*TC,2) -> #REF! | I63: =+ROUND(E63*F63,2) -> 1612.92 | J63: =+ROUND(E63*G63,2) -> 158.36 | K63: =+ROUND(I63+J63*TC,2) -> #REF!
B64: =B13+0.0001 -> 6.0102 | C64: MUROS Y TABIQUES DRYWALL
B65: =B64+0.000001 -> 6.010201 | C65: TABIQUERIA A=0.12M - DRYWALL RH - TORRE (REGISTRO EN DUCTOS SSHH) | D65: m2 | E65: 337.89 | F65: 125 | H65: =+ROUND(F65+G65*TC,2) -> #REF! | I65: =+ROUND(E65*F65,2) -> 42236.25 | J65: =+ROUND(E65*G65,2) -> 0 | K65: =+ROUND(I65+J65*TC,2) -> #REF!
B66: =B65+0.000001 -> 6.010202 | C66: TABIQUERIA A=0.12M - DRYWALL RH - LAVANDERIA COMUN | D66: m2 | E66: 7.76 | F66: 125 | H66: =+ROUND(F66+G66*TC,2) -> #REF! | I66: =+ROUND(E66*F66,2) -> 970 | J66: =+ROUND(E66*G66,2) -> 0 | K66: =+ROUND(I66+J66*TC,2) -> #REF!
B67: =B66+0.000001 -> 6.010203 | C67: DINTELES DRYWALL SUPERBOARD EN MAMPARAS Y VENTANAS | D67: ml | E67: 70.7 | F67: 155 | H67: =+ROUND(F67+G67*TC,2) -> #REF! | I67: =+ROUND(E67*F67,2) -> 10958.5 | J67: =+ROUND(E67*G67,2) -> 0 | K67: =+ROUND(I67+J67*TC,2) -> #REF!
B68: =B67+0.000001 -> 6.010204 | C68: DINTELES DRYWALL RF. EN ASCENSORES (PISO 1) | D68: ml | E68: 5 | F68: 145 | H68: =+ROUND(F68+G68*TC,2) -> #REF! | I68: =+ROUND(E68*F68,2) -> 725 | J68: =+ROUND(E68*G68,2) -> 0 | K68: =+ROUND(I68+J68*TC,2) -> #REF!
B69: =B68+0.000001 -> 6.010205 | C69: DINTELES DRYWALL EN PUERTAS PRINCIPALES (PISO 1) | D69: ml | E69: 40 | F69: 145 | H69: =+ROUND(F69+G69*TC,2) -> #REF! | I69: =+ROUND(E69*F69,2) -> 5800 | J69: =+ROUND(E69*G69,2) -> 0 | K69: =+ROUND(I69+J69*TC,2) -> #REF!
B70: =B64+0.0001 -> 6.0103 | C70: PARAPETOS Y SARDINELES | E70: 0
B71: =B70+0.000001 -> 6.010301 | C71: PARAPETOS EN VENTANAS (E=0.10M, H=VARIADAS) | D71: m2 | E71: 59.18 | F71: 103.71 | H71: =+ROUND(F71+G71*TC,2) -> #REF! | I71: =+ROUND(E71*F71,2) -> 6137.56 | J71: =+ROUND(E71*G71,2) -> 0 | K71: =+ROUND(I71+J71*TC,2) -> #REF!
B72: =B71+0.000001 -> 6.010302 | C72: PARAPETO E=0.10M, H=0.55M/1.1M (JARDINERA 1P Y AZOTEA) | D72: m2 | E72: 74.78 | F72: 103.71 | H72: =+ROUND(F72+G72*TC,2) -> #REF! | I72: =+ROUND(E72*F72,2) -> 7755.43 | J72: =+ROUND(E72*G72,2) -> 0 | K72: =+ROUND(I72+J72*TC,2) -> #REF!
B73: =B72+0.000001 -> 6.010303 | C73: PARAPETO E=0.15M, H=0.70 - 1.10 M (AZOTEA -TECHO) | D73: m2 | E73: 46.24 | F73: 118.21 | H73: =+ROUND(F73+G73*TC,2) -> #REF! | I73: =+ROUND(E73*F73,2) -> 5466.03 | J73: =+ROUND(E73*G73,2) -> 0 | K73: =+ROUND(I73+J73*TC,2) -> #REF!
B74: =B73+0.000001 -> 6.010304 | C74: PARAPETO E=0.20 M, H=1.10 M (AZOTEA ) | D74: m2 | E74: 23.6 | F74: 199.21 | H74: =+ROUND(F74+G74*TC,2) -> #REF! | I74: =+ROUND(E74*F74,2) -> 4701.36 | J74: =+ROUND(E74*G74,2) -> 0 | K74: =+ROUND(I74+J74*TC,2) -> #REF!
B75: =#REF!+0.000001 -> #REF! | C75: SARDINEL DE DUCHA H=0.10M, E=0.10M | D75: ml | E75: 256.74 | F75: 42.92 | G75: 0.73 | H75: =+ROUND(F75+G75*TC,2) -> #REF! | I75: =+ROUND(E75*F75,2) -> 11019.28 | J75: =+ROUND(E75*G75,2) -> 187.42 | K75: =+ROUND(I75+J75*TC,2) -> #REF!
B76: =B75+0.000001 -> #REF! | C76: SARDINEL DE PUERTAS DE DUCTOSH=0.10M, E=0.10M | D76: ml | E76: 332.12 | F76: 42.92 | G76: 0.73 | H76: =+ROUND(F76+G76*TC,2) -> #REF! | I76: =+ROUND(E76*F76,2) -> 14254.59 | J76: =+ROUND(E76*G76,2) -> 242.45 | K76: =+ROUND(I76+J76*TC,2) -> #REF!
B77: =#REF!+0.000001 -> #REF! | C77: SARDINEL DUCTOS JARDINES H=0.45M, E=0.10M | D77: ml | E77: 21.23 | F77: 89.14 | G77: 3.28 | H77: =+ROUND(F77+G77*TC,2) -> #REF! | I77: =+ROUND(E77*F77,2) -> 1892.44 | J77: =+ROUND(E77*G77,2) -> 69.63 | K77: =+ROUND(I77+J77*TC,2) -> #REF!
B78: =B77+0.000001 -> #REF! | C78: SARDINEL DUCTOS JARDINES H=0.45M, E=0.15M | D78: ml | E78: 29.66 | F78: 105.85 | G78: 4.91 | H78: =+ROUND(F78+G78*TC,2) -> #REF! | I78: =+ROUND(E78*F78,2) -> 3139.51 | J78: =+ROUND(E78*G78,2) -> 145.63 | K78: =+ROUND(I78+J78*TC,2) -> #REF!
B79: =B70+0.0001 -> 6.0104 | C79: ESTRUCTURAS DE CONCRETO (TABLEROS, BANCAS)
B80: =B79+0.000001 -> 6.010401 | C80: INGRESO: BANCAS DE CONCRETO (A=0.45 M, H= 0.45 M) | D80: ml | E80: 15.34 | F80: 658.63 | G80: 9.83 | H80: =+ROUND(F80+G80*TC,2) -> #REF! | I80: =+ROUND(E80*F80,2) -> 10103.38 | J80: =+ROUND(E80*G80,2) -> 150.79 | K80: =+ROUND(I80+J80*TC,2) -> #REF!
B81: =B80+0.000001 -> 6.010402 | C81: BANCA DE CONCRETO H=0.45, CON TABLON DE MADERA E=2"- HALL ASC AZOTEA / TERRAZA 1ER NIVEL | D81: ml | E81: 12.82 | F81: 658.63 | G81: 9.83 | H81: =+ROUND(F81+G81*TC,2) -> #REF! | I81: =+ROUND(E81*F81,2) -> 8443.64 | J81: =+ROUND(E81*G81,2) -> 126.02 | K81: =+ROUND(I81+J81*TC,2) -> #REF!
B82: =B81+0.000001 -> 6.010403 | C82: BANCA DE CONCRETO H=0.40, ACABADO EN MICROCEMENTO GRIS- LOBBY | D82: ml | E82: 7.52 | F82: 476.26 | G82: 17.47 | H82: =+ROUND(F82+G82*TC,2) -> #REF! | I82: =+ROUND(E82*F82,2) -> 3581.48 | J82: =+ROUND(E82*G82,2) -> 131.37 | K82: =+ROUND(I82+J82*TC,2) -> #REF!
B83: =B82+0.000001 -> 6.010404 | C83: ESTRUCTURA DE CEMENTO EN TERRAZA PISO 21 | D83: ml | E83: 5.89 | F83: 1066.77 | G83: 39.31 | H83: =+ROUND(F83+G83*TC,2) -> #REF! | I83: =+ROUND(E83*F83,2) -> 6283.28 | J83: =+ROUND(E83*G83,2) -> 231.54 | K83: =+ROUND(I83+J83*TC,2) -> #REF!
B84: =B83+0.000001 -> 6.010405 | C84: BANCA DE CONCRETO H=0.30 - TERRAZA COMUN PISO 18 | D84: ml | E84: 7.02 | F84: 1066.77 | G84: 39.31 | H84: =+ROUND(F84+G84*TC,2) -> #REF! | I84: =+ROUND(E84*F84,2) -> 7488.73 | J84: =+ROUND(E84*G84,2) -> 275.96 | K84: =+ROUND(I84+J84*TC,2) -> #REF!
B85: =B84+0.000001 -> 6.010406 | C85: MESA DE CONCRETO A=0.60M - TERRAZA COMUN PISO 18 | D85: ml | E85: 3 | F85: 314.4 | G85: =+G86 -> 14.56 | H85: =+ROUND(F85+G85*TC,2) -> #REF! | I85: =+ROUND(E85*F85,2) -> 943.2 | J85: =+ROUND(E85*G85,2) -> 43.68 | K85: =+ROUND(I85+J85*TC,2) -> #REF!
B86: =B85+0.000001 -> 6.010407 | C86: MESA DE CONCRETO A=0.98M- TERRAZA COMUN PISO 18 | D86: ml | E86: 2.75 | F86: 314.4 | G86: 14.56 | H86: =+ROUND(F86+G86*TC,2) -> #REF! | I86: =+ROUND(E86*F86,2) -> 864.6 | J86: =+ROUND(E86*G86,2) -> 40.04 | K86: =+ROUND(I86+J86*TC,2) -> #REF!
B87: =B86+0.000001 -> 6.010408 | C87: TABLERO DE CONCRETO - SALA GOURMET | D87: ml | E87: 7.45 | F87: 314.4 | G87: 14.56 | H87: =+ROUND(F87+G87*TC,2) -> #REF! | I87: =+ROUND(E87*F87,2) -> 2342.28 | J87: =+ROUND(E87*G87,2) -> 108.47 | K87: =+ROUND(I87+J87*TC,2) -> #REF!
B88: =#REF!+0.000001 -> #REF! | C88: ESTRUCTURA DE MUEBLE DE COUNTER | D88: ml | E88: 5.55 | F88: 665.47 | G88: 12.38 | H88: =+ROUND(F88+G88*TC,2) -> #REF! | I88: =+ROUND(E88*F88,2) -> 3693.36 | J88: =+ROUND(E88*G88,2) -> 68.71 | K88: =+ROUND(I88+J88*TC,2) -> #REF!
B89: =B12+0.01 -> 6.02 | C89: REVOQUES Y ENLUCIDOS EN INTERIORES | L89: =SUM(I91:I110)+SUM(J91:J110)*TC -> #REF!
B90: =B89+0.0001 -> 6.0201 | C90: INTERIORES (DPTO) Y AREAS COMUNES
B91: =B90+0.000001 -> 6.020101 | C91: SOLAQUEO EN MUROS POSTERIORMENTE A PINTAR | D91: m2 | E91: 1983.04 | F91: 1.72 | H91: =+ROUND(F91+G91*TC,2) -> #REF! | I91: =+ROUND(E91*F91,2) -> 3410.83 | J91: =+ROUND(E91*G91,2) -> 0 | K91: =+ROUND(I91+J91*TC,2) -> #REF!
B92: =B91+0.000001 -> 6.020102 | C92: SOLAQUEO EN MUROS DONDE SE COLOCARA PAPEL MURAL Y ENCHAPES. Costos por: 1. resanes de IIEE e IISS posteriores a la ejeución del muro (% de trabajos históricos que siempre se dan en obra); 2. Muros con demasiadas IISS e IIEE que se tenga que reemplazar con un vaciado de concreto 3. Vanos de ventanas altas o areas de vigas trasnversales menores a 0.5 m2 no se descuentan del área del muro metrado) | D92: m2 | E92: 18024.4 | F92: 1.72 | H92: =+ROUND(F92+G92*TC,2) -> #REF! | I92: =+ROUND(E92*F92,2) -> 31001.97 | J92: =+ROUND(E92*G92,2) -> 0 | K92: =+ROUND(I92+J92*TC,2) -> #REF!
B93: =B92+0.000001 -> 6.020103 | C93: SOLAQUEO EN AREAS COMUNES . Costos por: 1. resanes de IIEE e IISS posteriores a la ejeución del muro (% de trabajos históricos que siempre se dan en obra); 2. Muros con demasiadas IISS e IIEE que se tenga que reemplazar con un vaciado de concreto 3. Vanos de ventanas altas o areas de vigas trasnversales menores a 0.5 m2 no se descuentan del área del muro metrado) | D93: m2 | E93: 4397.38 | F93: 1.72 | H93: =+ROUND(F93+G93*TC,2) -> #REF! | I93: =+ROUND(E93*F93,2) -> 7563.49 | J93: =+ROUND(E93*G93,2) -> 0 | K93: =+ROUND(I93+J93*TC,2) -> #REF!
B94: =B93+0.000001 -> 6.020104 | C94: SOLAQUEO DE DUCTOS DE ASCENSORES | D94: m2 | E94: 1297.72 | F94: 23.85 | H94: =+ROUND(F94+G94*TC,2) -> #REF! | I94: =+ROUND(E94*F94,2) -> 30950.62 | J94: =+ROUND(E94*G94,2) -> 0 | K94: =+ROUND(I94+J94*TC,2) -> #REF!
B95: =B94+0.000001 -> 6.020105 | C95: SOLAQUEO DE MUROS Y PLACAS DE ESCALERA | D95: m2 | E95: 1400.25 | F95: 15.98 | H95: =+ROUND(F95+G95*TC,2) -> #REF! | I95: =+ROUND(E95*F95,2) -> 22376 | J95: =+ROUND(E95*G95,2) -> 0 | K95: =+ROUND(I95+J95*TC,2) -> #REF!
B96: =B95+0.000001 -> 6.020106 | C96: TARRAJEO DE MUROS LADRILLO KK | D96: m2 | E96: 194.83 | F96: 32.45 | H96: =+ROUND(F96+G96*TC,2) -> #REF! | I96: =+ROUND(E96*F96,2) -> 6322.23 | J96: =+ROUND(E96*G96,2) -> 0 | K96: =+ROUND(I96+J96*TC,2) -> #REF!
B97: =B96+0.000001 -> 6.020107 | C97: TARRAJEO DE COLUMNAS Y PLACAS | D97: m2 | E97: 3152.52 | F97: 35.97 | H97: =+ROUND(F97+G97*TC,2) -> #REF! | I97: =+ROUND(E97*F97,2) -> 113396.14 | J97: =+ROUND(E97*G97,2) -> 0 | K97: =+ROUND(I97+J97*TC,2) -> #REF!
B98: =B97+0.000001 -> 6.020108 | C98: LIMPIEZA DE DUCTOS DE VENTILACION | D98: m2 | E98: 5328.74 | F98: 8.28 | H98: =+ROUND(F98+G98*TC,2) -> #REF! | I98: =+ROUND(E98*F98,2) -> 44121.97 | J98: =+ROUND(E98*G98,2) -> 0 | K98: =+ROUND(I98+J98*TC,2) -> #REF!
B99: =B98+0.000001 -> 6.020109 | C99: VESTIDURA DE DERRAMES EN VANOS | D99: ml | E99: 2336.1 | F99: 17.6 | H99: =+ROUND(F99+G99*TC,2) -> #REF! | I99: =+ROUND(E99*F99,2) -> 41115.36 | J99: =+ROUND(E99*G99,2) -> 0 | K99: =+ROUND(I99+J99*TC,2) -> #REF!
B100: =B90+0.0001 -> 6.0202 | C100: IMPERMEABILIZACIONES
B101: =B100+0.000001 -> 6.020201 | C101: IMPERMEABILIZACION DE PISO DE DUCHAS | D101: m2 | E101: 108.92 | F101: 20.16 | H101: =+ROUND(F101+G101*TC,2) -> #REF! | I101: =+ROUND(E101*F101,2) -> 2195.83 | J101: =+ROUND(E101*G101,2) -> 0 | K101: =+ROUND(I101+J101*TC,2) -> #REF!
B102: =B101+0.000001 -> 6.020202 | C102: IMPERMEABILIZACION DE PARED DE DUCHAS (H=0.30M) | D102: m2 | E102: 136.37 | F102: 20.16 | H102: =+ROUND(F102+G102*TC,2) -> #REF! | I102: =+ROUND(E102*F102,2) -> 2749.22 | J102: =+ROUND(E102*G102,2) -> 0 | K102: =+ROUND(I102+J102*TC,2) -> #REF!
B103: =B102+0.000001 -> 6.020203 | C103: PISO PULIDO DE SUPERFICIE PARA IMPERMEABILIZAR - JARDINERAS | D103: m2 | E103: 0 | F103: 43.09 | H103: =+ROUND(F103+G103*TC,2) -> #REF! | I103: =+ROUND(E103*F103,2) -> 0 | J103: =+ROUND(E103*G103,2) -> 0 | K103: =+ROUND(I103+J103*TC,2) -> #REF!
...

Sheet OBRA CIVIL ASCENSOR
B2: DESCRIPCIÓN | C2: UND | D2: CANTIDAD | E2: PRECIO | F2: PARCIAL | G2: TOTAL
B3: ASCENSORES | G3: =SUM(F5:F6) -> 29000
B4: OBRAS CIVILES
B5: OBRAS CIVILES PARA LA COLOCACIÓN DE ASCENSOR | C5: und | D5: 1 | E5: 29000 | F5: =+E5*D5 -> 29000
B6: ESTRUCTURAS (DINTELES METÁLICOS/COLUMNAS METÁLICAS) - INCLUIDAS EN COTI ASCENSOR | C6: glb | D6: 0 | E6: 90335 | F6: =+E6*D6 -> 0

Sheet IISS
A2: INSTALACIONES SANITARIAS
H3: T.C | I3: 3.75
A4: Presupuesto | B4: PARDO 669
A5: Subpresupuesto | B5: INSTALACIONES SANITARIAS
A6: Cliente | B6: : V&V Bravo S.A.C | F6: Costo al | G6: 45394
A7: Lugar
A8: ITEM | B8: DESCRIPCION | C8: UND | D8: CANTIDAD | E8: P.U (S/.) | F8: P.U ($.) | G8: PARCIAL (S/.) | H8: PARCIAL ($) | I8: TOTAL
A9: 01 | B9: INSTALACIONES SANITARIAS | G9: =SUM(G10:G143) -> 1240575.8 | H9: =SUM(H10:H143) -> 42657.42 | I9: =SUM(I10:I143) -> 1400541.2
A10: 01.01 | B10: SISTEMA DE AGUA FRÍA | J10: =SUM(I12:I64) -> 419601.08
A11: 01.01.01 | B11: SALIDAS DE AGUA FRIA (EN POLIPROPILENO)
A12: 01.01.01.01 | B12: SALIDA AGUA FRIA PPR 20mm (Ø1/2") | C12: pto | D12: 1099 | E12: 57.25 | F12: 0 | G12: =+ROUND(E12*D12,2) -> 62917.75 | H12: =+ROUND(F12*D12,2) -> 0 | I12: =+ROUND(G12+(H12*$I$3),2) -> 62917.75
A13: 01.01.01.02 | B13: SALIDA AGUA FRIA PPR 25mm(3/4") | C13: pto | D13: 201 | E13: 59.35 | F13: 0 | G13: =+ROUND(E13*D13,2) -> 11929.35 | H13: =+ROUND(F13*D13,2) -> 0 | I13: =+ROUND(G13+(H13*$I$3),2) -> 11929.35
A14: 01.01.01.03 | B14: SALIDA AGUA FRIA PPR 50mm(1.1/2") | C14: pto | D14: 3 | E14: 132.29 | F14: 0 | G14: =+ROUND(E14*D14,2) -> 396.87 | H14: =+ROUND(F14*D14,2) -> 0 | I14: =+ROUND(G14+(H14*$I$3),2) -> 396.87
A15: 01.01.02 | B15: REDES DE DISTRIBUCION DE AGUA (EN POLIPROPILENO) | G15: =+ROUND(E15*D15,2) -> 0 | H15: =+ROUND(F15*D15,2) -> 0 | I15: =+ROUND(G15+(H15*$I$3),2) -> 0
A16: 01.01.02.01 | B16: TUBERIA PPR PN-10 EMPOTRADA DE 1/2" | C16: m | D16: 1100 | E16: 15.69 | F16: 0 | G16: =+ROUND(E16*D16,2) -> 17259 | H16: =+ROUND(F16*D16,2) -> 0 | I16: =+ROUND(G16+(H16*$I$3),2) -> 17259
A17: 01.01.02.02 | B17: TUBERIA PPR PN-10 EMPOTRADA DE 3/4" | C17: m | D17: 3150 | E17: 18.74 | F17: 0 | G17: =+ROUND(E17*D17,2) -> 59031 | H17: =+ROUND(F17*D17,2) -> 0 | I17: =+ROUND(G17+(H17*$I$3),2) -> 59031
A18: 01.01.02.03 | B18: TUBERIA PPR PN-10 EMPOTRADA DE 1" | C18: m | D18: 888.95 | E18: 24.44 | F18: 0 | G18: =+ROUND(E18*D18,2) -> 21725.94 | H18: =+ROUND(F18*D18,2) -> 0 | I18: =+ROUND(G18+(H18*$I$3),2) -> 21725.94
A19: 01.01.02.04 | B19: TUBERIA PPR PN-10 EMPOTRADA DE 1.1/4" | C19: m | D19: 2 | E19: 29.9 | F19: 0 | G19: =+ROUND(E19*D19,2) -> 59.8 | H19: =+ROUND(F19*D19,2) -> 0 | I19: =+ROUND(G19+(H19*$I$3),2) -> 59.8
A20: 01.01.02.05 | B20: TUBERIA PPR PN-10 EMPOTRADA DE 1.1/2" | C20: m | D20: 28.75 | E20: 40.1 | F20: 0 | G20: =+ROUND(E20*D20,2) -> 1152.88 | H20: =+ROUND(F20*D20,2) -> 0 | I20: =+ROUND(G20+(H20*$I$3),2) -> 1152.88
A21: 01.01.02.07 | B21: TUBERIA PPR PN-10 COLGADA DE 1/2" | C21: m | D21: 20 | E21: 24.17 | F21: 0 | G21: =+ROUND(E21*D21,2) -> 483.4 | H21: =+ROUND(F21*D21,2) -> 0 | I21: =+ROUND(G21+(H21*$I$3),2) -> 483.4
A22: 01.01.02.08 | B22: TUBERIA PPR PN-10 COLGADA DE 3/4" | C22: m | D22: 23 | E22: 26.43 | F22: 0 | G22: =+ROUND(E22*D22,2) -> 607.89 | H22: =+ROUND(F22*D22,2) -> 0 | I22: =+ROUND(G22+(H22*$I$3),2) -> 607.89
A23: 01.01.02.09 | B23: TUBERIA PPR PN-10 COLGADA DE 1" | C23: m | D23: 21 | E23: 33.41 | F23: 0 | G23: =+ROUND(E23*D23,2) -> 701.61 | H23: =+ROUND(F23*D23,2) -> 0 | I23: =+ROUND(G23+(H23*$I$3),2) -> 701.61
A24: 01.01.02.10 | B24: TUBERIA PPR PN-10 COLGADA DE 1.1/2" | C24: m | D24: 22.25 | E24: 47.86 | F24: 0 | G24: =+ROUND(E24*D24,2) -> 1064.89 | H24: =+ROUND(F24*D24,2) -> 0 | I24: =+ROUND(G24+(H24*$I$3),2) -> 1064.89
A25: 01.01.02.11 | B25: TUBERIA PPR PN-10 COLGADA DE 2" | C25: m | D25: 70.95 | E25: 57.45 | F25: 0 | G25: =+ROUND(E25*D25,2) -> 4076.08 | H25: =+ROUND(F25*D25,2) -> 0 | I25: =+ROUND(G25+(H25*$I$3),2) -> 4076.08
A26: 01.01.02.12 | B26: TUBERIA PPR PN-10 COLGADA DE 2 1/2" | C26: m | D26: 48.15 | E26: 88.16 | F26: 0 | G26: =+ROUND(E26*D26,2) -> 4244.9 | H26: =+ROUND(F26*D26,2) -> 0 | I26: =+ROUND(G26+(H26*$I$3),2) -> 4244.9
A27: 01.01.02.13 | B27: TUBERIA PPR PN-10 COLGADA DE 3" | C27: m | D27: 35.33 | E27: 108.03 | F27: 0 | G27: =+ROUND(E27*D27,2) -> 3816.7 | H27: =+ROUND(F27*D27,2) -> 0 | I27: =+ROUND(G27+(H27*$I$3),2) -> 3816.7
A28: 01.01.03 | B28: MONTANTE DE AGUA FRIA (EN POLIPROPILENO) | G28: =+ROUND(E28*D28,2) -> 0 | H28: =+ROUND(F28*D28,2) -> 0 | I28: =+ROUND(G28+(H28*$I$3),2) -> 0
A29: 01.01.03.01 | B29: TUBERIA PPR PN-10 ADOSADA DE 1.1/2" | C29: m | D29: 42 | E29: 47.86 | F29: 0 | G29: =+ROUND(E29*D29,2) -> 2010.12 | H29: =+ROUND(F29*D29,2) -> 0 | I29: =+ROUND(G29+(H29*$I$3),2) -> 2010.12
A30: 01.01.03.02 | B30: TUBERIA PPR PN-10 ADOSADA DE 2" | C30: m | D30: 96 | E30: 66.17 | F30: 0 | G30: =+ROUND(E30*D30,2) -> 6352.32 | H30: =+ROUND(F30*D30,2) -> 0 | I30: =+ROUND(G30+(H30*$I$3),2) -> 6352.32
A31: 01.01.03.03 | B31: TUBERIA PPR PN-10 ADOSADA DE 2.1/2" | C31: m | D31: 61 | E31: 88.16 | F31: 0 | G31: =+ROUND(E31*D31,2) -> 5377.76 | H31: =+ROUND(F31*D31,2) -> 0 | I31: =+ROUND(G31+(H31*$I$3),2) -> 5377.76
A32: 01.01.03.04 | B32: TUBERIA PPR PN-10 ADOSADA DE 3" | C32: m | D32: 101 | E32: 111.49 | F32: 0 | G32: =+ROUND(E32*D32,2) -> 11260.49 | H32: =+ROUND(F32*D32,2) -> 0 | I32: =+ROUND(G32+(H32*$I$3),2) -> 11260.49
A33: 01.01.03.05 | B33: TUBERIA PPR PN-10 ADOSADA DE 4" | C33: m | D33: 18 | E33: 151.68 | F33: 0 | G33: =+ROUND(E33*D33,2) -> 2730.24 | H33: =+ROUND(F33*D33,2) -> 0 | I33: =+ROUND(G33+(H33*$I$3),2) -> 2730.24
A34: 01.01.04 | B34: LLAVES Y VALVULAS - RED DE DESTRIBUCION (SIST. POLIPROPILENO) | G34: =+ROUND(E34*D34,2) -> 0 | H34: =+ROUND(F34*D34,2) -> 0 | I34: =+ROUND(G34+(H34*$I$3),2) -> 0
A35: 01.01.04.01 | B35: LLAVE DE PASO SIST. POLIPROPILENO 20mm (1/2") | C35: und | D35: 358 | E35: 63.61 | F35: 0 | G35: =+ROUND(E35*D35,2) -> 22772.38 | H35: =+ROUND(F35*D35,2) -> 0 | I35: =+ROUND(G35+(H35*$I$3),2) -> 22772.38
A36: 01.01.04.02 | B36: LLAVE DE PASO SIST. POLIPROPILENO 25mm (3/4") | C36: und | D36: 605 | E36: 72.44 | F36: 0 | G36: =+ROUND(E36*D36,2) -> 43826.2 | H36: =+ROUND(F36*D36,2) -> 0 | I36: =+ROUND(G36+(H36*$I$3),2) -> 43826.2
A37: 01.01.04.03 | B37: LLAVE DE PASO SIST. POLIPROPILENO 32mm (1") | C37: und | D37: 69 | E37: 136.35 | F37: 0 | G37: =+ROUND(E37*D37,2) -> 9408.15 | H37: =+ROUND(F37*D37,2) -> 0 | I37: =+ROUND(G37+(H37*$I$3),2) -> 9408.15
A38: 01.01.04.05 | B38: LLAVE DE PASO SIST. POLIPROPILENO (1.1/2") | C38: und | D38: 4 | E38: 359.62 | F38: 0 | G38: =+ROUND(E38*D38,2) -> 1438.48 | H38: =+ROUND(F38*D38,2) -> 0 | I38: =+ROUND(G38+(H38*$I$3),2) -> 1438.48
A39: 01.01.04.06 | B39: LLAVE DE PASO SIST. POLIPROPILENO 63mm (2") | C39: und | D39: 21 | E39: 395.26 | F39: 0 | G39: =+ROUND(E39*D39,2) -> 8300.46 | H39: =+ROUND(F39*D39,2) -> 0 | I39: =+ROUND(G39+(H39*$I$3),2) -> 8300.46
A40: 01.01.04.07 | B40: VALVULA DE AIRE EN MONTANTE | C40: und | D40: 6 | E40: 395.26 | F40: 0 | G40: =+ROUND(E40*D40,2) -> 2371.56 | H40: =+ROUND(F40*D40,2) -> 0 | I40: =+ROUND(G40+(H40*$I$3),2) -> 2371.56
A41: 01.01.05 | B41: PRUEBAS HIDRAULICAS | G41: =+ROUND(E41*D41,2) -> 0 | H41: =+ROUND(F41*D41,2) -> 0 | I41: =+ROUND(G41+(H41*$I$3),2) -> 0
A42: 01.01.05.01 | B42: PRUEBA HIDRAULICA PARA AGUA FRIA | C42: glb | D42: 1 | E42: 16240 | F42: 0 | G42: =+ROUND(E42*D42,2) -> 16240 | H42: =+ROUND(F42*D42,2) -> 0 | I42: =+ROUND(G42+(H42*$I$3),2) -> 16240
A43: 01.01.05.02 | B43: LIMPIEZA Y DESINFECCION DE TUBERIAS AGUA FRIA | C43: glb | D43: 1 | E43: 6960 | F43: 0 | G43: =+ROUND(E43*D43,2) -> 6960 | H43: =+ROUND(F43*D43,2) -> 0 | I43: =+ROUND(G43+(H43*$I$3),2) -> 6960
A44: 01.01.05.03 | B44: LIMPIEZA Y DESINFECCION DE CISTERNAS | C44: glb | D44: 1 | E44: 2850 | F44: 0 | G44: =+ROUND(E44*D44,2) -> 2850 | H44: =+ROUND(F44*D44,2) -> 0 | I44: =+ROUND(G44+(H44*$I$3),2) -> 2850
A45: 01.01.06 | B45: VARIOS | G45: =+ROUND(E45*D45,2) -> 0 | H45: =+ROUND(F45*D45,2) -> 0 | I45: =+ROUND(G45+(H45*$I$3),2) -> 0
A46: 01.01.06.01 | B46: MEDIDOR DE AGUA DE 3/4" (INC. BATERIA) | C46: und | D46: 88 | E46: 320.1 | F46: 0 | G46: =+ROUND(E46*D46,2) -> 28168.8 | H46: =+ROUND(F46*D46,2) -> 0 | I46: =+ROUND(G46+(H46*$I$3),2) -> 28168.8
A47: 01.01.06.02 | B47: MEDIDOR DE AGUA DE 1" (INC. BATERIA) | C47: und | D47: 86 | E47: 436.98 | F47: 0 | G47: =+ROUND(E47*D47,2) -> 37580.28 | H47: =+ROUND(F47*D47,2) -> 0 | I47: =+ROUND(G47+(H47*$I$3),2) -> 37580.28
A48: 01.01.06.04 | B48: GRIFO DE RIEGO 1/2" | C48: und | D48: 20 | E48: 77.76 | F48: 0 | G48: =+ROUND(E48*D48,2) -> 1555.2 | H48: =+ROUND(F48*D48,2) -> 0 | I48: =+ROUND(G48+(H48*$I$3),2) -> 1555.2
A49: 01.01.07 | B49: CUARTO DE BOMBAS | G49: =+ROUND(E49*D49,2) -> 0 | H49: =+ROUND(F49*D49,2) -> 0 | I49: =+ROUND(G49+(H49*$I$3),2) -> 0
A50: 01.01.07.01 | B50: BRIDA ROMPEAGUA 2.1/2" | C50: und | D50: 4 | E50: 726.32 | F50: 0 | G50: =+ROUND(E50*D50,2) -> 2905.28 | H50: =+ROUND(F50*D50,2) -> 0 | I50: =+ROUND(G50+(H50*$I$3),2) -> 2905.28
A51: 01.01.07.02 | B51: BRIDA ROMPEAGUA 6" | C51: und | D51: 7 | E51: 1751.82 | F51: 0 | G51: =+ROUND(E51*D51,2) -> 12262.74 | H51: =+ROUND(F51*D51,2) -> 0 | I51: =+ROUND(G51+(H51*$I$3),2) -> 12262.74
A52: 01.01.07.03 | B52: VALVULA FLOTADORA DE 2" | C52: und | D52: 4 | E52: 786 | F52: 0 | G52: =+ROUND(E52*D52,2) -> 3144 | H52: =+ROUND(F52*D52,2) -> 0 | I52: =+ROUND(G52+(H52*$I$3),2) -> 3144
A53: 01.01.07.04 | B53: VALVULA COMPUERTADE 2" | C53: und | D53: 3 | E53: 374.65 | F53: 0 | G53: =+ROUND(E53*D53,2) -> 1123.95 | H53: =+ROUND(F53*D53,2) -> 0 | I53: =+ROUND(G53+(H53*$I$3),2) -> 1123.95
A54: 01.02 | B54: SISTEMA DE CASCADA DE AGUA | G54: =+ROUND(E54*D54,2) -> 0 | H54: =+ROUND(F54*D54,2) -> 0 | I54: =+ROUND(G54+(H54*$I$3),2) -> 0
A55: 01.02.01 | B55: INSTALACIONES DE AGUA | G55: =+ROUND(E55*D55,2) -> 0 | H55: =+ROUND(F55*D55,2) -> 0 | I55: =+ROUND(G55+(H55*$I$3),2) -> 0
A56: 01.02.01.01 | B56: SALIDA AGUA FRIA PPR 25mm(3/4") | C56: pto | D56: 1 | E56: 59.35 | F56: 0 | G56: =+ROUND(E56*D56,2) -> 59.35 | H56: =+ROUND(F56*D56,2) -> 0 | I56: =+ROUND(G56+(H56*$I$3),2) -> 59.35
A57: 01.02.01.02 | B57: TUBERIA PPR PN-10 COLGADA DE 2" | C57: m | D57: 6.65 | E57: 57.45 | F57: 0 | G57: =+ROUND(E57*D57,2) -> 382.04 | H57: =+ROUND(F57*D57,2) -> 0 | I57: =+ROUND(G57+(H57*$I$3),2) -> 382.04
A58: 01.02.01.03 | B58: VALVULA COMPUERTADE 2" | C58: und | D58: 1 | E58: 374.65 | F58: 0 | G58: =+ROUND(E58*D58,2) -> 374.65 | H58: =+ROUND(F58*D58,2) -> 0 | I58: =+ROUND(G58+(H58*$I$3),2) -> 374.65
A59: 01.02.01.04 | B59: VALVULA CHECK DE 2" | C59: und | D59: 1 | E59: 456.55 | F59: 0 | G59: =+ROUND(E59*D59,2) -> 456.55 | H59: =+ROUND(F59*D59,2) -> 0 | I59: =+ROUND(G59+(H59*$I$3),2) -> 456.55
A60: 01.02.02 | B60: INSTALACIONES DE DESAGUE | G60: =+ROUND(E60*D60,2) -> 0 | H60: =+ROUND(F60*D60,2) -> 0 | I60: =+ROUND(G60+(H60*$I$3),2) -> 0
A61: 01.02.02.01 | B61: SALIDA DESAGUE DE PVC SAP 3" | C61: pto | D61: 1 | E61: 55.46 | F61: 2.99 | G61: =+ROUND(E61*D61,2) -> 55.46 | H61: =+ROUND(F61*D61,2) -> 2.99 | I61: =+ROUND(G61+(H61*$I$3),2) -> 66.67
A62: 01.02.02.02 | B62: TUBERIA PVC SAP EMPOTRADA DE 2" | C62: m | D62: 3 | E62: 14.55 | F62: 1.52 | G62: =+ROUND(E62*D62,2) -> 43.65 | H62: =+ROUND(F62*D62,2) -> 4.56 | I62: =+ROUND(G62+(H62*$I$3),2) -> 60.75
A63: 01.02.02.03 | B63: TUBERIA PVC SAP EMPOTRADA DE 3" | C63: m | D63: 2 | E63: 16.97 | F63: 2.54 | G63: =+ROUND(E63*D63,2) -> 33.94 | H63: =+ROUND(F63*D63,2) -> 5.08 | I63: =+ROUND(G63+(H63*$I$3),2) -> 52.99
A64: 01.02.02.04 | B64: SUMIDERO DE BRONCE, Ø3" | C64: und | D64: 1 | E64: 41.61 | F64: 0 | G64: =+ROUND(E64*D64,2) -> 41.61 | H64: =+ROUND(F64*D64,2) -> 0 | I64: =+ROUND(G64+(H64*$I$3),2) -> 41.61
A65: 01.03 | B65: SISTEMA DE AGUA CALIENTE | G65: =+ROUND(E65*D65,2) -> 0 | H65: =+ROUND(F65*D65,2) -> 0 | I65: =+ROUND(G65+(H65*$I$3),2) -> 0 | J65: =SUM(I67:I76) -> 160989.15
A66: 01.03.01 | B66: SALIDAS DE AGUA CALIENTE (EN POLIPROPILENO) | G66: =+ROUND(E66*D66,2) -> 0 | H66: =+ROUND(F66*D66,2) -> 0 | I66: =+ROUND(G66+(H66*$I$3),2) -> 0
A67: 01.03.01.01 | B67: SALIDA AGUA CALIENTE PPR 20mm (Ø1/2") | C67: pto | D67: 832 | E67: 57.01 | F67: 0 | G67: =+ROUND(E67*D67,2) -> 47432.32 | H67: =+ROUND(F67*D67,2) -> 0 | I67: =+ROUND(G67+(H67*$I$3),2) -> 47432.32
A68: 01.03.01.02 | B68: SALIDA AGUA CALIENTE PPR 25mm (Ø3/4") | C68: pto | D68: 174 | E68: 61.83 | F68: 0 | G68: =+ROUND(E68*D68,2) -> 10758.42 | H68: =+ROUND(F68*D68,2) -> 0 | I68: =+ROUND(G68+(H68*$I$3),2) -> 10758.42
A69: 01.03.02 | B69: REDES DE DISTRIBUCION DE AGUA CALIENTE (EN POLIPROPILENO) | G69: =+ROUND(E69*D69,2) -> 0 | H69: =+ROUND(F69*D69,2) -> 0 | I69: =+ROUND(G69+(H69*$I$3),2) -> 0
A70: 01.03.02.01 | B70: TUBERIA PPR PN-16 EMPOTRADA DE 1/2" | C70: m | D70: 1956.17 | E70: 15.73 | F70: 0 | G70: =+ROUND(E70*D70,2) -> 30770.55 | H70: =+ROUND(F70*D70,2) -> 0 | I70: =+ROUND(G70+(H70*$I$3),2) -> 30770.55
A71: 01.03.02.02 | B71: TUBERIA PPR PN-16 EMPOTRADA DE 3/4" | C71: m | D71: 416.56 | E71: 19.47 | F71: 0 | G71: =+ROUND(E71*D71,2) -> 8110.42 | H71: =+ROUND(F71*D71,2) -> 0 | I71: =+ROUND(G71+(H71*$I$3),2) -> 8110.42
A72: 01.03.03 | B72: LLAVES Y VALVULAS - RED DE DESTRIBUCION (SIST. POLIPROPILENO) | G72: =+ROUND(E72*D72,2) -> 0 | H72: =+ROUND(F72*D72,2) -> 0 | I72: =+ROUND(G72+(H72*$I$3),2) -> 0
A73: 01.03.03.01 | B73: LLAVE DE PASO SIST. POLIPROPILENO 20mm (1/2") | C73: und | D73: 633 | E73: 64.3 | F73: 0 | G73: =+ROUND(E73*D73,2) -> 40701.9 | H73: =+ROUND(F73*D73,2) -> 0 | I73: =+ROUND(G73+(H73*$I$3),2) -> 40701.9
A74: 01.03.03.02 | B74: LLAVE DE PASO SIST. POLIPROPILENO 25mm (3/4") | C74: und | D74: 174 | E74: 78.71 | F74: 0 | G74: =+ROUND(E74*D74,2) -> 13695.54 | H74: =+ROUND(F74*D74,2) -> 0 | I74: =+ROUND(G74+(H74*$I$3),2) -> 13695.54
A75: 01.03.04 | B75: PRUEBAS HIDRAULICAS | G75: =+ROUND(E75*D75,2) -> 0 | H75: =+ROUND(F75*D75,2) -> 0 | I75: =+ROUND(G75+(H75*$I$3),2) -> 0
A76: 01.03.04.01 | B76: PRUEBA HIDRAULICA PARA AGUA CALIENTE Y DESINFECCION | C76: glb | D76: 1 | E76: 9520 | F76: 0 | G76: =+ROUND(E76*D76,2) -> 9520 | H76: =+ROUND(F76*D76,2) -> 0 | I76: =+ROUND(G76+(H76*$I$3),2) -> 9520
A77: 01.03 | B77: SISTEMA DE DESAGUE | G77: =+ROUND(E77*D77,2) -> 0 | H77: =+ROUND(F77*D77,2) -> 0 | I77: =+ROUND(G77+(H77*$I$3),2) -> 0 | J77: =SUM(I79:I143) -> 819950.94
A78: 01.03.01 | B78: SALIDAS DE DRENAJE, DESAGUE Y VENTILACION | G78: =+ROUND(E78*D78,2) -> 0 | H78: =+ROUND(F78*D78,2) -> 0 | I78: =+ROUND(G78+(H78*$I$3),2) -> 0
A79: 01.04.01.01 | B79: SALIDA DESAGUE DE PVC SAP 2" | C79: pto | D79: 617 | E79: 48.66 | F79: 2.48 | G79: =+ROUND(E79*D79,2) -> 30023.22 | H79: =+ROUND(F79*D79,2) -> 1530.16 | I79: =+ROUND(G79+(H79*$I$3),2) -> 35761.32
A80: 01.04.01.02 | B80: SALIDA DESAGUE DE PVC SAP 2" (SUMIDEROS Y REGISTROS) | C80: pto | D80: 2161 | E80: 32.76 | F80: 0.81 | G80: =+ROUND(E80*D80,2) -> 70794.36 | H80: =+ROUND(F80*D80,2) -> 1750.41 | I80: =+ROUND(G80+(H80*$I$3),2) -> 77358.4
A81: 01.04.01.03 | B81: SALIDA DESAGUE DE PVC SAP 2" - AIRE ACONDICIONADO | C81: pto | D81: 247 | E81: 25.83 | F81: 3.04 | G81: =+ROUND(E81*D81,2) -> 6380.01 | H81: =+ROUND(F81*D81,2) -> 750.88 | I81: =+ROUND(G81+(H81*$I$3),2) -> 9195.81
A82: 01.04.01.04 | B82: SALIDA DESAGUE DE PVC SAP 3" | C82: pto | D82: 116 | E82: 55.46 | F82: 2.99 | G82: =+ROUND(E82*D82,2) -> 6433.36 | H82: =+ROUND(F82*D82,2) -> 346.84 | I82: =+ROUND(G82+(H82*$I$3),2) -> 7734.01
A83: 01.04.01.05 | B83: SALIDA DESAGUE DE PVC SAP 4" | C83: pto | D83: 295 | E83: 56.21 | F83: 5.7 | G83: =+ROUND(E83*D83,2) -> 16581.95 | H83: =+ROUND(F83*D83,2) -> 1681.5 | I83: =+ROUND(G83+(H83*$I$3),2) -> 22887.58
A84: 01.04.01.06 | B84: SALIDA DESAGUE DE PVC SAP 6" | C84: pto | D84: 11 | E84: 33.75 | F84: 21.75 | G84: =+ROUND(E84*D84,2) -> 371.25 | H84: =+ROUND(F84*D84,2) -> 239.25 | I84: =+ROUND(G84+(H84*$I$3),2) -> 1268.44
A85: 01.04.01.07 | B85: SALIDA VENTILACION DE PVC SAP 2" | C85: pto | D85: 679 | E85: 29.4 | F85: 2.48 | G85: =+ROUND(E85*D85,2) -> 19962.6 | H85: =+ROUND(F85*D85,2) -> 1683.92 | I85: =+ROUND(G85+(H85*$I$3),2) -> 26277.3
A86: 01.04.02 | B86: REDES DE DESAGUE Y DRENAJE | G86: =+ROUND(E86*D86,2) -> 0 | H86: =+ROUND(F86*D86,2) -> 0 | I86: =+ROUND(G86+(H86*$I$3),2) -> 0
A87: 01.04.02.01 | B87: TUBERIA PVC SAP EMPOTRADA DE 2" | C87: m | D87: 2995.46 | E87: 14.55 | F87: 1.52 | G87: =+ROUND(E87*D87,2) -> 43583.94 | H87: =+ROUND(F87*D87,2) -> 4553.1 | I87: =+ROUND(G87+(H87*$I$3),2) -> 60658.07
A88: 01.04.02.02 | B88: TUBERIA PVC SAP EMPOTRADA DE 3" | C88: m | D88: 4.42 | E88: 16.97 | F88: 2.54 | G88: =+ROUND(E88*D88,2) -> 75.01 | H88: =+ROUND(F88*D88,2) -> 11.23 | I88: =+ROUND(G88+(H88*$I$3),2) -> 117.12
A89: 01.04.02.03 | B89: TUBERIA PVC SAP EMPOTRADA DE 4" | C89: m | D89: 550.01 | E89: 25.85 | F89: 4.18 | G89: =+ROUND(E89*D89,2) -> 14217.76 | H89: =+ROUND(F89*D89,2) -> 2299.04 | I89: =+ROUND(G89+(H89*$I$3),2) -> 22839.16
A90: 01.04.02.04 | B90: TUBERIA VENTILACION PVC SAL EMPOTRADA DE 2" | C90: m | D90: 715.47 | E90: 12.15 | F90: 1.52 | G90: =+ROUND(E90*D90,2) -> 8692.96 | H90: =+ROUND(F90*D90,2) -> 1087.51 | I90: =+ROUND(G90+(H90*$I$3),2) -> 12771.12
A91: 01.04.02.05 | B91: TUBERIA VENTILACION PVC SAL EMPOTRADA DE 3" | C91: m | D91: 119.27 | E91: 13.48 | F91: 2.54 | G91: =+ROUND(E91*D91,2) -> 1607.76 | H91: =+ROUND(F91*D91,2) -> 302.95 | I91: =+ROUND(G91+(H91*$I$3),2) -> 2743.82
A92: 01.04.02.06 | B92: TUBERIA VENTILACION PVC SAL EMPOTRADA DE 4" | C92: m | D92: 247.54 | E92: 24.21 | F92: 4.18 | G92: =+ROUND(E92*D92,2) -> 5992.94 | H92: =+ROUND(F92*D92,2) -> 1034.72 | I92: =+ROUND(G92+(H92*$I$3),2) -> 9873.14
A93: 01.04.03 | B93: REDES ENTERRADAS | G93: =+ROUND(E93*D93,2) -> 0 | H93: =+ROUND(F93*D93,2) -> 0 | I93: =+ROUND(G93+(H93*$I$3),2) -> 0
A94: 01.04.03.01 | B94: TUBERIA PVC SAP DE 3" | C94: m | D94: 89.37 | E94: 13.48 | F94: 2.54 | G94: =+ROUND(E94*D94,2) -> 1204.71 | H94: =+ROUND(F94*D94,2) -> 227 | I94: =+ROUND(G94+(H94*$I$3),2) -> 2055.96
A95: 01.04.03.02 | B95: TUBERIA PVC SAP DE 4" | C95: m | D95: 35.87 | E95: 23.12 | F95: 4.18 | G95: =+ROUND(E95*D95,2) -> 829.31 | H95: =+ROUND(F95*D95,2) -> 149.94 | I95: =+ROUND(G95+(H95*$I$3),2) -> 1391.59
A96: 01.04.03.03 | B96: TUBERIA PVC SAP DE 6" | C96: m | D96: 13.98 | E96: 28.91 | F96: 19.9 | G96: =+ROUND(E96*D96,2) -> 404.16 | H96: =+ROUND(F96*D96,2) -> 278.2 | I96: =+ROUND(G96+(H96*$I$3),2) -> 1447.41
A97: 01.04.03.04 | B97: TRAZO Y REPLANTEO PARA IISS | C97: m | D97: 49.85 | E97: 1.69 | F97: 0 | G97: =+ROUND(E97*D97,2) -> 84.25 | H97: =+ROUND(F97*D97,2) -> 0 | I97: =+ROUND(G97+(H97*$I$3),2) -> 84.25
A98: 01.04.03.05 | B98: EXCAVACIÓN DE ZANJA -COLOCACIÓN DE TUBERÍA | C98: m3 | D98: 23.93 | E98: 51.88 | F98: 0 | G98: =+ROUND(E98*D98,2) -> 1241.49 | H98: =+ROUND(F98*D98,2) -> 0 | I98: =+ROUND(G98+(H98*$I$3),2) -> 1241.49
A99: 01.04.03.06 | B99: CAMA DE ARENA | C99: m3 | D99: 3.99 | E99: 75.2 | F99: 0 | G99: =+ROUND(E99*D99,2) -> 300.05 | H99: =+ROUND(F99*D99,2) -> 0 | I99: =+ROUND(G99+(H99*$I$3),2) -> 300.05
A100: 01.04.03.07 | B100: RELLENO COMPACTADO CON MATERIAL PROPIO | C100: m3 | D100: 19.94 | E100: 50.58 | F100: 0 | G100: =+ROUND(E100*D100,2) -> 1008.57 | H100: =+ROUND(F100*D100,2) -> 0 | I100: =+ROUND(G100+(H100*$I$3),2) -> 1008.57
A101: 01.04.03.08 | B101: ACARREO DE DESMONTE A PUNTO DE ACOPIO (D=30m.) | C101: m3 | D101: 11.17 | E101: 36.46 | F101: 0 | G101: =+ROUND(E101*D101,2) -> 407.26 | H101: =+ROUND(F101*D101,2) -> 0 | I101: =+ROUND(G101+(H101*$I$3),2) -> 407.26
...

Sheet IIEE
A2: INSTALACIONES ELECTRICAS
H3: T.C | I3: 3.75
A4: Presupuesto | B4: PARDO 669
A5: Subpresupuesto | B5: INSTALACIONES ELECTRICAS
A6: Cliente | B6: : V&V Bravo S.A.C | F6: Costo al | G6: 45394
A7: Lugar
A8: ITEM | B8: DESCRIPCION | C8: UND | D8: CANTIDAD | E8: P.U (S/.) | F8: P.U ($.) | G8: PARCIAL (S/.) | H8: PARCIAL ($) | I8: TOTAL
A9: 01 | B9: INSTALACIONES ELECTRICAS | G9: =SUM(G10:G189) -> 1471999.8 | H9: =SUM(H10:H189) -> 232473.31 | I9: =SUM(I10:I189) -> 2343774.8
A10: 01.01 | B10: SISTEMA DE ALUMBRADO | J10: =SUM(I12:I23,I124:I127,I135) -> 434173.61
A11: 01.01.01 | B11: SALIDAS DE ALUMBRADO
A12: 01.01.01.01 | B12: SALIDA PARA LUMINARIA EN TECHO | C12: pto | D12: 1973 | E12: 46.79 | F12: 7.9 | G12: =+ROUND(E12*D12,2) -> 92316.67 | H12: =+ROUND(F12*D12,2) -> 15586.7 | I12: =+ROUND(G12+(H12*$I$3),2) -> 150766.8
A13: 01.01.01.02 | B13: SALIDA PARA LUMINARIA DE EMERGENCIA | C13: pto | D13: 277 | E13: 46.79 | F13: 7.9 | G13: =+ROUND(E13*D13,2) -> 12960.83 | H13: =+ROUND(F13*D13,2) -> 2188.3 | I13: =+ROUND(G13+(H13*$I$3),2) -> 21166.96
A14: 01.01.01.03 | B14: SALIDA PARA LUMINARIA HERMETICA/FLUORESCENTE | C14: pto | D14: 228 | E14: 46.79 | F14: 7.9 | G14: =+ROUND(E14*D14,2) -> 10668.12 | H14: =+ROUND(F14*D14,2) -> 1801.2 | I14: =+ROUND(G14+(H14*$I$3),2) -> 17422.62
A15: 01.01.01.04 | B15: SALIDA PARA LUMINARIA TIPO ESTACA | C15: pto | D15: 37 | E15: 46.79 | F15: 7.9 | G15: =+ROUND(E15*D15,2) -> 1731.23 | H15: =+ROUND(F15*D15,2) -> 292.3 | I15: =+ROUND(G15+(H15*$I$3),2) -> 2827.36
A16: 01.01.01.05 | B16: SALIDA PARA EXTRACTOR EN BAÑOS/DEPOSITOS | C16: pto | D16: 460 | E16: 46.79 | F16: 7.9 | G16: =+ROUND(E16*D16,2) -> 21523.4 | H16: =+ROUND(F16*D16,2) -> 3634 | I16: =+ROUND(G16+(H16*$I$3),2) -> 35150.9
A17: 01.01.01.06 | B17: SALIDA PARA BRAQUETTE | C17: pto | D17: 373 | E17: 46.79 | F17: 7.9 | G17: =+ROUND(E17*D17,2) -> 17452.67 | H17: =+ROUND(F17*D17,2) -> 2946.7 | I17: =+ROUND(G17+(H17*$I$3),2) -> 28502.8
A18: 01.01.01.07 | B18: SALIDA PARA CINTA LED | C18: pto | D18: 116 | E18: 46.79 | F18: 7.9 | G18: =+ROUND(E18*D18,2) -> 5427.64 | H18: =+ROUND(F18*D18,2) -> 916.4 | I18: =+ROUND(G18+(H18*$I$3),2) -> 8864.14
A19: 01.01.02 | B19: SALIDAS DE INTERRUPTORES | G19: =+ROUND(E19*D19,2) -> 0 | H19: =+ROUND(F19*D19,2) -> 0 | I19: =+ROUND(G19+(H19*$I$3),2) -> 0
A20: 01.01.02.01 | B20: SALIDA PARA INTERRUPTOR SIMPLE | C20: pto | D20: 675 | E20: 43.77 | F20: 7.9 | G20: =+ROUND(E20*D20,2) -> 29544.75 | H20: =+ROUND(F20*D20,2) -> 5332.5 | I20: =+ROUND(G20+(H20*$I$3),2) -> 49541.63
A21: 01.01.02.02 | B21: SALIDA PARA INTERRUPTOR DOBLE | C21: pto | D21: 472 | E21: 43.77 | F21: 7.9 | G21: =+ROUND(E21*D21,2) -> 20659.44 | H21: =+ROUND(F21*D21,2) -> 3728.8 | I21: =+ROUND(G21+(H21*$I$3),2) -> 34642.44
A22: 01.01.02.03 | B22: SALIDA PARA INTERRUPTOR TRIPLE | C22: pto | D22: 15 | E22: 43.77 | F22: 7.9 | G22: =+ROUND(E22*D22,2) -> 656.55 | H22: =+ROUND(F22*D22,2) -> 118.5 | I22: =+ROUND(G22+(H22*$I$3),2) -> 1100.93
A23: 01.01.02.04 | B23: SALIDA PARA INTERRUPTOR DE CONMUTACION SIMPLE | C23: pto | D23: 361 | E23: 43.77 | F23: 7.9 | G23: =+ROUND(E23*D23,2) -> 15800.97 | H23: =+ROUND(F23*D23,2) -> 2851.9 | I23: =+ROUND(G23+(H23*$I$3),2) -> 26495.6
A24: 01.02 | B24: TABLEROS ELECTRICOS | G24: =+ROUND(E24*D24,2) -> 0 | H24: =+ROUND(F24*D24,2) -> 0 | I24: =+ROUND(G24+(H24*$I$3),2) -> 0 | J24: =SUM(I26:I48) -> 315538.36
A25: 01.02.01 | B25: SUMINISTRO E INSTALACION DE TABLEROS ELÉCTRICOS | G25: =+ROUND(E25*D25,2) -> 0 | H25: =+ROUND(F25*D25,2) -> 0 | I25: =+ROUND(G25+(H25*$I$3),2) -> 0
A26: 01.02.01.01 | B26: SUMINISTRO E INSTALACION DE TABLERO TG-N | C26: und | D26: 1 | E26: 31160.26 | F26: 0 | G26: =+ROUND(E26*D26,2) -> 31160.26 | H26: =+ROUND(F26*D26,2) -> 0 | I26: =+ROUND(G26+(H26*$I$3),2) -> 31160.26
A27: 01.02.01.02 | B27: SUMINISTRO E INSTALACION DE TABLERO TTA | C27: und | D27: 1 | E27: 31120.47 | F27: 0 | G27: =+ROUND(E27*D27,2) -> 31120.47 | H27: =+ROUND(F27*D27,2) -> 0 | I27: =+ROUND(G27+(H27*$I$3),2) -> 31120.47
A28: 01.02.01.03 | B28: SUMINISTRO E INSTALACION DE TABLERO TG-E | C28: und | D28: 1 | E28: 31400.46 | F28: 0 | G28: =+ROUND(E28*D28,2) -> 31400.46 | H28: =+ROUND(F28*D28,2) -> 0 | I28: =+ROUND(G28+(H28*$I$3),2) -> 31400.46
A29: 01.02.01.04 | B29: SUMINISTRO E INSTALACION DE TABLERO T-BCI | C29: und | D29: 1 | E29: 17681.26 | F29: 0 | G29: =+ROUND(E29*D29,2) -> 17681.26 | H29: =+ROUND(F29*D29,2) -> 0 | I29: =+ROUND(G29+(H29*$I$3),2) -> 17681.26
A30: 01.02.01.05 | B30: SUMINISTRO E INSTALACION DE TABLERO TN-S1al6 | C30: und | D30: 6 | E30: 2481.53 | F30: 0 | G30: =+ROUND(E30*D30,2) -> 14889.18 | H30: =+ROUND(F30*D30,2) -> 0 | I30: =+ROUND(G30+(H30*$I$3),2) -> 14889.18
A31: 01.02.01.06 | B31: SUMINISTRO E INSTALACION DE TABLERO TN-P1.1 | C31: und | D31: 1 | E31: 3236.3 | F31: 0 | G31: =+ROUND(E31*D31,2) -> 3236.3 | H31: =+ROUND(F31*D31,2) -> 0 | I31: =+ROUND(G31+(H31*$I$3),2) -> 3236.3
A32: 01.02.01.07 | B32: SUMINISTRO E INSTALACION DE TABLERO TN-P1.2 | C32: und | D32: 1 | E32: 3314.7 | F32: 0 | G32: =+ROUND(E32*D32,2) -> 3314.7 | H32: =+ROUND(F32*D32,2) -> 0 | I32: =+ROUND(G32+(H32*$I$3),2) -> 3314.7
A33: 01.02.01.08 | B33: SUMINISTRO E INSTALACION DE TABLERO TN-AZ | C33: und | D33: 1 | E33: 3003.26 | F33: 0 | G33: =+ROUND(E33*D33,2) -> 3003.26 | H33: =+ROUND(F33*D33,2) -> 0 | I33: =+ROUND(G33+(H33*$I$3),2) -> 3003.26
A34: 01.02.01.09 | B34: SUMINISTRO E INSTALACION DE TABLERO TE-S1 | C34: und | D34: 1 | E34: 2986.07 | F34: 0 | G34: =+ROUND(E34*D34,2) -> 2986.07 | H34: =+ROUND(F34*D34,2) -> 0 | I34: =+ROUND(G34+(H34*$I$3),2) -> 2986.07
A35: 01.02.01.10 | B35: SUMINISTRO E INSTALACION DE TABLERO TE-P12.1 | C35: und | D35: 1 | E35: 2764.69 | F35: 0 | G35: =+ROUND(E35*D35,2) -> 2764.69 | H35: =+ROUND(F35*D35,2) -> 0 | I35: =+ROUND(G35+(H35*$I$3),2) -> 2764.69
A36: 01.02.01.11 | B36: SUMINISTRO E INSTALACION DE TABLERO TE-P11.2 | C36: und | D36: 1 | E36: 2624.57 | F36: 0 | G36: =+ROUND(E36*D36,2) -> 2624.57 | H36: =+ROUND(F36*D36,2) -> 0 | I36: =+ROUND(G36+(H36*$I$3),2) -> 2624.57
A37: 01.02.01.12 | B37: SUMINISTRO E INSTALACION DE TABLERO TN-TE | C37: und | D37: 1 | E37: 1820.24 | F37: 0 | G37: =+ROUND(E37*D37,2) -> 1820.24 | H37: =+ROUND(F37*D37,2) -> 0 | I37: =+ROUND(G37+(H37*$I$3),2) -> 1820.24
... A48: 01.02.01.23 | B48: SUMINISTRO E INSTALACION DE TABLERO T-D1 | C48: und | D48: 149 | E48: 816.22 | F48: 0 | G48: =+ROUND(E48*D48,2) -> 121616.78 | H48: =+ROUND(F48*D48,2) -> 0 | I48: =+ROUND(G48+(H48*$I$3),2) -> 121616.78
A49: 01.03 | B49: SALIDAS DE FUERZA Y ALIMENTADORES | G49: =+ROUND(E49*D49,2) -> 0 | H49: =+ROUND(F49*D49,2) -> 0 | I49: =+ROUND(G49+(H49*$I$3),2) -> 0
A50: 01.03.01 | B50: SALIDAS DE TOMACORRIENTE Y SALIDAS DE FUERZA | G50: =+ROUND(E50*D50,2) -> 0 | H50: =+ROUND(F50*D50,2) -> 0 | I50: =+ROUND(G50+(H50*$I$3),2) -> 0 | J50: =SUM(I51:I74,I128:I134) -> 373809.94
A51: 01.03.01.01 | B51: SALIDA PARA TOMACORRIENTE BIPOLAR DOBLE CON ESPIGA A TIERRA | C51: pto | D51: 2592 | E51: 42.66 | F51: 7.54 | G51: =+ROUND(E51*D51,2) -> 110574.72 | H51: =+ROUND(F51*D51,2) -> 19543.68 | I51: =+ROUND(G51+(H51*$I$3),2) -> 183863.52
A52: 01.03.01.02 | B52: SALIDA PARA TOMACORRIENTE A PRUEBA DE AGUA | C52: pto | D52: 8 | E52: 42.66 | F52: 7.74 | G52: =+ROUND(E52*D52,2) -> 341.28 | H52: =+ROUND(F52*D52,2) -> 61.92 | I52: =+ROUND(G52+(H52*$I$3),2) -> 573.48
A53: 01.03.01.03 | B53: SALIDA PARA TOMACORRIENTE LAVADORA | C53: pto | D53: 174 | E53: 42.66 | F53: 21.8 | G53: =+ROUND(E53*D53,2) -> 7422.84 | H53: =+ROUND(F53*D53,2) -> 3793.2 | I53: =+ROUND(G53+(H53*$I$3),2) -> 21647.34
A54: 01.03.01.04 | B54: SALIDA PARA COCINA ELECTRICA | C54: pto | D54: 25 | E54: 46.22 | F54: 21.8 | G54: =+ROUND(E54*D54,2) -> 1155.5 | H54: =+ROUND(F54*D54,2) -> 545 | I54: =+ROUND(G54+(H54*$I$3),2) -> 3199.25
A55: 01.03.01.05 | B55: SALIDA PARA HORNO ELECTRICO | C55: pto | D55: 25 | E55: 46.22 | F55: 21.8 | G55: =+ROUND(E55*D55,2) -> 1155.5 | H55: =+ROUND(F55*D55,2) -> 545 | I55: =+ROUND(G55+(H55*$I$3),2) -> 3199.25
A56: 01.03.01.06 | B56: SALIDA PARA THERMA ELECTRICA | C56: pto | D56: 25 | E56: 46.22 | F56: 13.8 | G56: =+ROUND(E56*D56,2) -> 1155.5 | H56: =+ROUND(F56*D56,2) -> 345 | I56: =+ROUND(G56+(H56*$I$3),2) -> 2449.25
A57: 01.03.01.07 | B57: SALIDA PARA INTERRUPTOR TERMOMAGNETICO 2X20A | C57: pto | D57: 25 | E57: 128.68 | F57: 0 | G57: =+ROUND(E57*D57,2) -> 3217 | H57: =+ROUND(F57*D57,2) -> 0 | I57: =+ROUND(G57+(H57*$I$3),2) -> 3217
A58: 01.03.01.08 | B58: SALIDA PARA EXTRACTOR EN COCINA | C58: pto | D58: 174 | E58: 42.1 | F58: 7.78 | G58: =+ROUND(E58*D58,2) -> 7325.4 | H58: =+ROUND(F58*D58,2) -> 1353.72 | I58: =+ROUND(G58+(H58*$I$3),2) -> 12401.85
A59: 01.03.01.09 | B59: SALIDA PARA TIMBRE | C59: pto | D59: 174 | E59: 46.22 | F59: 7.8 | G59: =+ROUND(E59*D59,2) -> 8042.28 | H59: =+ROUND(F59*D59,2) -> 1357.2 | I59: =+ROUND(G59+(H59*$I$3),2) -> 13131.78
A60: 01.03.01.10 | B60: SALIDA PARA PULSADOR DE TIMBRE | C60: pto | D60: 174 | E60: 46.22 | F60: 7.8 | G60: =+ROUND(E60*D60,2) -> 8042.28 | H60: =+ROUND(F60*D60,2) -> 1357.2 | I60: =+ROUND(G60+(H60*$I$3),2) -> 13131.78
A61: 01.03.01.12 | B61: SALIDA PARA AIRE ACONDICIONADO | C61: pto | D61: 237 | E61: 39.06 | F61: 4.08 | G61: =+ROUND(E61*D61,2) -> 9257.22 | H61: =+ROUND(F61*D61,2) -> 966.96 | I61: =+ROUND(G61+(H61*$I$3),2) -> 12883.32
A62: 01.03.01.13 | B62: SALIDA DE FUERZA PARA PUERTA ENROLLABLE | C62: pto | D62: 1 | E62: 46.22 | F62: 71.72 | G62: =+ROUND(E62*D62,2) -> 46.22 | H62: =+ROUND(F62*D62,2) -> 71.72 | I62: =+ROUND(G62+(H62*$I$3),2) -> 315.17
... A74: 01.03.01.25 | B74: SALIDA DE FUERZA PARA EQUIPOS DE VENTILACION EN TECHO | C74: pto | D74: 10 | E74: 46.22 | F74: 43.75 | G74: =+ROUND(E74*D74,2) -> 462.2 | H74: =+ROUND(F74*D74,2) -> 437.5 | I74: =+ROUND(G74+(H74*$I$3),2) -> 2102.83
A75: 01.03.02 | B75: SUMINISTRO E INSTALACION DE ALIMENTADORES ELECTRICOS | G75: =+ROUND(E75*D75,2) -> 0 | H75: =+ROUND(F75*D75,2) -> 0 | I75: =+ROUND(G75+(H75*$I$3),2) -> 0 | J75: =SUM(I77:I122) -> 833496.86
A76: 01.03.02.01 | B76: ALIMENTADORES EN AREAS COMUNES | G76: =+ROUND(E76*D76,2) -> 0 | H76: =+ROUND(F76*D76,2) -> 0 | I76: =+ROUND(G76+(H76*$I$3),2) -> 0
A77: 01.03.02.01.01 | B77: 2(3-1x240mm²N2XOH) | C77: m | D77: 30.73 | E77: 74.07 | F77: 194.36 | G77: =+ROUND(E77*D77,2) -> 2276.17 | H77: =+ROUND(F77*D77,2) -> 5972.68 | I77: =+ROUND(G77+(H77*$I$3),2) -> 24673.72
A78: 01.03.02.01.02 | B78: 2(3-1x150mm²N2XOH)+1x70mm²/T | C78: m | D78: 17.88 | E78: 51.95 | F78: 128.86 | G78: =+ROUND(E78*D78,2) -> 928.87 | H78: =+ROUND(F78*D78,2) -> 2304.02 | I78: =+ROUND(G78+(H78*$I$3),2) -> 9568.95
A79: 01.03.02.01.03 | B79: 2x(3-1x240mm2 N2X0H) + 95mm2/T | C79: m | D79: 60 | E79: 74.07 | F79: 207.41 | G79: =+ROUND(E79*D79,2) -> 4444.2 | H79: =+ROUND(F79*D79,2) -> 12444.6 | I79: =+ROUND(G79+(H79*$I$3),2) -> 51111.45
A80: 01.03.02.01.04 | B80: 3-1x95mm²N2XOH+1x35mm²/T | C80: m | D80: 51.6 | E80: 68.95 | F80: 44.11 | G80: =+ROUND(E80*D80,2) -> 3557.82 | H80: =+ROUND(F80*D80,2) -> 2276.08 | I80: =+ROUND(G80+(H80*$I$3),2) -> 12093.12
A81: 01.03.02.01.05 | B81: 3-1x50mm²N2XOH+1x16mm²/T | C81: m | D81: 97.6 | E81: 68.95 | F81: 22.73 | G81: =+ROUND(E81*D81,2) -> 6729.52 | H81: =+ROUND(F81*D81,2) -> 2218.45 | I81: =+ROUND(G81+(H81*$I$3),2) -> 15048.71
A82: 01.03.02.01.06 | B82: 3-1x35mm2 N2XOH + 16mm2/T | C82: m | D82: 105.6 | E82: 13.27 | F82: 17.25 | G82: =+ROUND(E82*D82,2) -> 1401.31 | H82: =+ROUND(F82*D82,2) -> 1821.6 | I82: =+ROUND(G82+(H82*$I$3),2) -> 8232.31
A83: 01.03.02.01.07 | B83: 3-1x25mm²N2XOH+1x10mm²/T | C83: m | D83: 543.4 | E83: 13.27 | F83: 12.6 | G83: =+ROUND(E83*D83,2) -> 7210.92 | H83: =+ROUND(F83*D83,2) -> 6846.84 | I83: =+ROUND(G83+(H83*$I$3),2) -> 32886.57
A84: 01.03.02.01.08 | B84: 3-1x10mm²N2XOH+1x10mm²/T | C84: m | D84: 186.66 | E84: 13.27 | F84: 6.43 | G84: =+ROUND(E84*D84,2) -> 2476.98 | H84: =+ROUND(F84*D84,2) -> 1200.22 | I84: =+ROUND(G84+(H84*$I$3),2) -> 6977.81
A85: 01.03.02.01.09 | B85: 3-1x16mm²N2XOH+1x10mm²/T | C85: m | D85: 86.29 | E85: 11.02 | F85: 8.76 | G85: =+ROUND(E85*D85,2) -> 950.92 | H85: =+ROUND(F85*D85,2) -> 755.9 | I85: =+ROUND(G85+(H85*$I$3),2) -> 3785.55
A86: 01.03.02.01.10 | B86: 3-1x10mm²N2XOH+1x6mm²/T | C86: m | D86: 396.59 | E86: 13.27 | F86: 4.63 | G86: =+ROUND(E86*D86,2) -> 5262.75 | H86: =+ROUND(F86*D86,2) -> 1836.21 | I86: =+ROUND(G86+(H86*$I$3),2) -> 12148.54
A87: 01.03.02.01.11 | B87: 3-1x6mm²N2XOH+1x4mm²/T | C87: m | D87: 903.36 | E87: 13.27 | F87: 3.61 | G87: =+ROUND(E87*D87,2) -> 11987.59 | H87: =+ROUND(F87*D87,2) -> 3261.13 | I87: =+ROUND(G87+(H87*$I$3),2) -> 24216.83
A88: 01.03.02.02 | B88: ALIMENTADORES PARA DEPARTAMENTOS | G88: =+ROUND(E88*D88,2) -> 0 | H88: =+ROUND(F88*D88,2) -> 0 | I88: =+ROUND(G88+(H88*$I$3),2) -> 0
A89: 01.03.02.02.01 | B89: 2-1x10mm2 LSOH-90 | C89: m | D89: 191.4 | E89: 8.2 | F89: 3.21 | G89: =+ROUND(E89*D89,2) -> 1569.48 | H89: =+ROUND(F89*D89,2) -> 614.39 | I89: =+ROUND(G89+(H89*$I$3),2) -> 3873.44
A90: 01.03.02.02.02 | B90: 2-1x16mm2 LSOH-90 | C90: m | D90: 5454.34 | E90: 8.2 | F90: 4.77 | G90: =+ROUND(E90*D90,2) -> 44725.59 | H90: =+ROUND(F90*D90,2) -> 26017.2 | I90: =+ROUND(G90+(H90*$I$3),2) -> 142290.09
A91: 01.03.02.02.03 | B91: 2-1x25mm2 LSOH-90 | C91: m | D91: 4779.22 | E91: 8.2 | F91: 7.33 | G91: =+ROUND(E91*D91,2) -> 39189.6 | H91: =+ROUND(F91*D91,2) -> 35031.68 | I91: =+ROUND(G91+(H91*$I$3),2) -> 170558.4
A92: 01.03.02.02.04 | B92: 2-1x35mm2 LSOH-90 | C92: m | D92: 246.38 | E92: 10 | F92: 9.91 | G92: =+ROUND(E92*D92,2) -> 2463.8 | H92: =+ROUND(F92*D92,2) -> 2441.63 | I92: =+ROUND(G92+(H92*$I$3),2) -> 11619.91
A93: 01.03.02.02.05 | B93: 2-1x10mm2 LSOH-90+1x10mm2 LSOH-90(T) | C93: m | D93: 51.47 | E93: 10 | F93: 4.82 | G93: =+ROUND(E93*D93,2) -> 514.7 | H93: =+ROUND(F93*D93,2) -> 248.09 | I93: =+ROUND(G93+(H93*$I$3),2) -> 1445.04
A94: 01.03.02.02.06 | B94: 2-1x16mm2 LSOH-90+1x10mm2 LSOH-90(T) | C94: m | D94: 1318.57 | E94: 10 | F94: 6.38 | G94: =+ROUND(E94*D94,2) -> 13185.7 | H94: =+ROUND(F94*D94,2) -> 8412.48 | I94: =+ROUND(G94+(H94*$I$3),2) -> 44732.5
A95: 01.03.02.02.07 | B95: 2-1x25mm2 LSOH-90+1x10mm2 LSOH-90(T) | C95: m | D95: 904.57 | E95: 10 | F95: 8.94 | G95: =+ROUND(E95*D95,2) -> 9045.7 | H95: =+ROUND(F95*D95,2) -> 8086.86 | I95: =+ROUND(G95+(H95*$I$3),2) -> 39371.43
A96: 01.03.02.02.08 | B96: 2-1x35mm2 LSOH-90+1x10mm2 LSOH-90(T) | C96: m | D96: 24.06 | E96: 10 | F96: 11.52 | G96: =+ROUND(E96*D96,2) -> 240.6 | H96: =+ROUND(F96*D96,2) -> 277.17 | I96: =+ROUND(G96+(H96*$I$3),2) -> 1279.99
A97: 01.03.03 | B97: CANALIZACION DE FUERZA Y ALIMENTADORES | G97: =+ROUND(E97*D97,2) -> 0 | H97: =+ROUND(F97*D97,2) -> 0 | I97: =+ROUND(G97+(H97*$I$3),2) -> 0
A98: 01.03.03.01 | B98: TUBERIA ELECTRICA Ø65mm EMT | C98: m | D98: 10 | E98: 71.07 | F98: 0 | G98: =+ROUND(E98*D98,2) -> 710.7 | H98: =+ROUND(F98*D98,2) -> 0 | I98: =+ROUND(G98+(H98*$I$3),2) -> 710.7
A99: 01.03.03.02 | B99: TUBERIA ELECTRICA Ø100mm EMT | C99: m | D99: 20 | E99: 144.45 | F99: 0 | G99: =+ROUND(E99*D99,2) -> 2889 | H99: =+ROUND(F99*D99,2) -> 0 | I99: =+ROUND(G99+(H99*$I$3),2) -> 2889
A100: 01.03.03.03 | B100: TUBERIA PVC-SAP ELECTRICA DE 20 mm | C100: m | D100: 38 | E100: 8.96 | F100: 0.5 | G100: =+ROUND(E100*D100,2) -> 340.48 | H100: =+ROUND(F100*D100,2) -> 19 | I100: =+ROUND(G100+(H100*$I$3),2) -> 411.73
A101: 01.03.03.04 | B101: TUBERIA PVC-SAP ELECTRICA DE 25 mm | C101: m | D101: 1645 | E101: 8.64 | F101: 0.67 | G101: =+ROUND(E101*D101,2) -> 14212.8 | H101: =+ROUND(F101*D101,2) -> 1102.15 | I101: =+ROUND(G101+(H101*$I$3),2) -> 18345.86
A102: 01.03.03.05 | B102: TUBERIA PVC-SAP ELECTRICA DE 35 mm | C102: m | D102: 948.55 | E102: 10.47 | F102: 0.74 | G102: =+ROUND(E102*D102,2) -> 9931.32 | H102: =+ROUND(F102*D102,2) -> 701.93 | I102: =+ROUND(G102+(H102*$I$3),2) -> 12563.56
A103: 01.03.03.06 | B103: TUBERIA PVC-SAP ELECTRICA DE 40 mm | C103: m | D103: 184 | E103: 11.6 | F103: 1.46 | G103: =+ROUND(E103*D103,2) -> 2134.4 | H103: =+ROUND(F103*D103,2) -> 268.64 | I103: =+ROUND(G103+(H103*$I$3),2) -> 3141.8
A104: 01.03.03.07 | B104: TUBERIA PVC-SAP ELECTRICA DE 50 mm | C104: m | D104: 28 | E104: 11.81 | F104: 3.15 | G104: =+ROUND(E104*D104,2) -> 330.68 | H104: =+ROUND(F104*D104,2) -> 88.2 | I104: =+ROUND(G104+(H104*$I$3),2) -> 661.43
A105: 01.03.03.08 | B105: TUBERIA PVC-SAP ELECTRICA DE 80 mm | C105: m | D105: 20 | E105: 16.41 | F105: 7.24 | G105: =+ROUND(E105*D105,2) -> 328.2 | H105: =+ROUND(F105*D105,2) -> 144.8 | I105: =+ROUND(G105+(H105*$I$3),2) -> 871.2
A106: 01.03.03.09 | B106: TUBERIA PVC-SAP ELECTRICA DE 100 mm | C106: m | D106: 378 | E106: 20.39 | F106: 7.04 | G106: =+ROUND(E106*D106,2) -> 7707.42 | H106: =+ROUND(F106*D106,2) -> 2661.12 | I106: =+ROUND(G106+(H106*$I$3),2) -> 17686.62
A107: 01.03.04 | B107: CAJAS DE PASE | G107: =+ROUND(E107*D107,2) -> 0 | H107: =+ROUND(F107*D107,2) -> 0 | I107: =+ROUND(G107+(H107*$I$3),2) -> 0
A108: 01.03.04.01 | B108: CAJA DE PASE OCTOGONAL | C108: und | D108: 66 | E108: 21.15 | F108: 0 | G108: =+ROUND(E108*D108,2) -> 1395.9 | H108: =+ROUND(F108*D108,2) -> 0 | I108: =+ROUND(G108+(H108*$I$3),2) -> 1395.9
A109: 01.03.04.02 | B109: CAJA DE PASE 150X150X100mm | C109: und | D109: 62 | E109: 35.48 | F109: 0 | G109: =+ROUND(E109*D109,2) -> 2199.76 | H109: =+ROUND(F109*D109,2) -> 0 | I109: =+ROUND(G109+(H109*$I$3),2) -> 2199.76
A110: 01.03.04.03 | B110: CAJA DE PASE 200X200X100mm | C110: und | D110: 276 | E110: 48.56 | F110: 0 | G110: =+ROUND(E110*D110,2) -> 13402.56 | H110: =+ROUND(F110*D110,2) -> 0 | I110: =+ROUND(G110+(H110*$I$3),2) -> 13402.56
A111: 01.03.04.04 | B111: CAJA DE PASE 300X300X100mm | C111: und | D111: 40 | E111: 116.06 | F111: 0 | G111: =+ROUND(E111*D111,2) -> 4642.4 | H111: =+ROUND(F111*D111,2) -> 0 | I111: =+ROUND(G111+(H111*$I$3),2) -> 4642.4
A112: 01.03.04.05 | B112: CAJA DE PASE 400X400X200mm | C112: und | D112: 27 | E112: 196.33 | F112: 0 | G112: =+ROUND(E112*D112,2) -> 5300.91 | H112: =+ROUND(F112*D112,2) -> 0 | I112: =+ROUND(G112+(H112*$I$3),2) -> 5300.91
A113: 01.03.04.06 | B113: CAJA DE PASE 500X500X200mm | C113: und | D113: 25 | E113: 264.95 | F113: 0 | G113: =+ROUND(E113*D113,2) -> 6623.75 | H113: =+ROUND(F113*D113,2) -> 0 | I113: =+ROUND(G113+(H113*$I$3),2) -> 6623.75
A114: 01.03.04.07 | B114: CAJA DE PASE 600X600X200mm | C114: und | D114: 5 | E114: 429.35 | F114: 0 | G114: =+ROUND(E114*D114,2) -> 2146.75 | H114: =+ROUND(F114*D114,2) -> 0 | I114: =+ROUND(G114+(H114*$I$3),2) -> 2146.75
A115: 01.03.04.08 | B115: CAJA DE PASE 1700X250X200mm | C115: und | D115: 12 | E115: 911.48 | F115: 0 | G115: =+ROUND(E115*D115,2) -> 10937.76 | H115: =+ROUND(F115*D115,2) -> 0 | I115: =+ROUND(G115+(H115*$I$3),2) -> 10937.76
A116: 01.04 | B116: BANDEJAS ELECTRICAS Y DE COMUNICACIONES | G116: =+ROUND(E116*D116,2) -> 0 | H116: =+ROUND(F116*D116,2) -> 0 | I116: =+ROUND(G116+(H116*$I$3),2) -> 0
A117: 01.04.01 | B117: BANDEJA PORTACABLE TIPO RANURADA DE 300X100X2400MM | C117: m | D117: 224.95 | E117: 74.12 | F117: 19.13 | G117: =+ROUND(E117*D117,2) -> 16673.29 | H117: =+ROUND(F117*D117,2) -> 4303.29 | I117: =+ROUND(G117+(H117*$I$3),2) -> 32810.63
A118: 01.04.02 | B118: BANDEJA PORTACABLE TIPO RANURADA DE 400X100X2400MM | C118: m | D118: 79 | E118: 85.85 | F118: 25.93 | G118: =+ROUND(E118*D118,2) -> 6782.15 | H118: =+ROUND(F118*D118,2) -> 2048.47 | I118: =+ROUND(G118+(H118*$I$3),2) -> 14463.91
A119: 01.04.03 | B119: BANDEJA PORTACABLE TIPO RANURADA DE 500X100X2400MM | C119: m | D119: 225.44 | E119: 85.85 | F119: 27.43 | G119: =+ROUND(E119*D119,2) -> 19354.02 | H119: =+ROUND(F119*D119,2) -> 6183.82 | I119: =+ROUND(G119+(H119*$I$3),2) -> 42543.35
A120: 01.04.04 | B120: BANDEJA PORTACABLE TIPO RANURADA DE 700X100X2400MM | C120: m | D120: 30.15 | E120: 91.99 | F120: 46.71 | G120: =+ROUND(E120*D120,2) -> 2773.5 | H120: =+ROUND(F120*D120,2) -> 1408.31 | I120: =+ROUND(G120+(H120*$I$3),2) -> 8054.66
A121: 01.04.05 | B121: ATERRAMIENTO DE BANDEJA CON CABLE DESNUDO 1x35mm² | C121: m | D121: 560 | E121: 11.27 | F121: 3.66 | G121: =+ROUND(E121*D121,2) -> 6311.2 | H121: =+ROUND(F121*D121,2) -> 2049.6 | I121: =+ROUND(G121+(H121*$I$3),2) -> 13997.2
A122: 01.04.06 | B122: SALIDA PARA CONEXION A BANDEJA | C122: und | D122: 38 | E122: 46.87 | F122: 0 | G122: =+ROUND(E122*D122,2) -> 1781.06 | H122: =+ROUND(F122*D122,2) -> 0 | I122: =+ROUND(G122+(H122*$I$3),2) -> 1781.06
...

Sheet CTO BOMBAS-ACIySPC
A2: CUARTO DE BOMBAS - ACI
H3: T.C | I3: =+TC -> #REF!
A4: Presupuesto | B4: SAN FELIPE
A5: Subpresupuesto | B5: EQUIPAMIENTO CUARTO DE BOMBAS
A6: Cliente | B6: : V&V Bravo S.A.C | F6: Costo al | G6: 45392
A7: Lugar
A8: ITEM | B8: DESCRIPCION | C8: UND | D8: CANTIDAD | E8: P.U (S/.) | F8: P.U ($.) | G8: PARCIAL (S/.) | H8: PARCIAL ($) | I8: TOTAL
A9: 01 | B9: SISTEMA DE PRESION CONSTANTE Y SUMIDEROS | I9: =SUM(H11:H17) -> 52695.72
A10: 01.01 | B10: SISTEMA DE PRESION CONSTANTE #1 | J10: =+I11+I13+I15 -> #REF!
A11: 01.01.01 | B11: Bombas de Presión Constante marca SYNERGY o USR tipo Centrifuga Vertical Multietápica construida completamente en Acero Inoxidable. 2 Electrobombas 20HP | C11: und | D11: 2 | F11: 9761.78 | G11: =+E11*D11 -> 0 | H11: =+ROUND(F11*D11,2) -> 19523.56 | I11: =+ROUND(G11+(H11*$I$3),2) -> #REF!
A12: 01.02 | B12: SISTEMA DE PRESION CONSTANTE #2
A13: 01.02.01 | B13: Bombas de Presión Constante marca SYNERGY o USR tipo Centrifuga Vertical Multietápica construida completamente en Acero Inoxidable 2 Electrobombas 20HP | C13: und | D13: 2 | F13: 8047.66 | G13: =+E13*D13 -> 0 | H13: =+ROUND(F13*D13,2) -> 16095.32 | I13: =+ROUND(G13+(H13*$I$3),2) -> #REF!
A14: 01.02 | B14: SISTEMA DE PRESION CONSTANTE #3 | J14: =+I15+I17 -> #REF!
A15: 01.02.01 | B15: Bombas de Presión Constante marca SYNERGY o USR tipo Centrifuga Vertical Multietápica construida completamente en Acero Inoxidable 2 Electrobombas 7.5HP | C15: und | D15: 2 | F15: 6188.32 | G15: =+E15*D15 -> 0 | H15: =+ROUND(F15*D15,2) -> 12376.64 | I15: =+ROUND(G15+(H15*$I$3),2) -> #REF!
A16: 01.04 | B16: SISTEMA DE BOMBEO DE SUMIDERO #1 | H16: =+ROUND(F16*D16,2) -> 0 | I16: =+ROUND(G16+(H16*$I$3),2) -> #REF!
A17: 01.05 | B17: Bombas sumergibles marca USR 2 Electrobombas 7.5HP | C17: und | D17: 2 | F17: 2350.1 | G17: =+E17*D17 -> 0 | H17: =+ROUND(F17*D17,2) -> 4700.2 | I17: =+ROUND(G17+(H17*$I$3),2) -> #REF!
A18: 01.01 | B18: Sistema de Motobomba de Protección de Incendios 500 GPM - LISTADO UL-FM | I18: =+H19 -> 65538.57
A19: 01.01.01 | B19: Bomba contra incendio Listada UL/FM tipo Horizontal De Carcaza Partida de 750 GPM @ 255 PSI con motor Eléctrico de 200 HP | C19: glb | D19: 1 | F19: 65538.57 | G19: =+ROUND(E19*D19,2) -> 0 | H19: =+ROUND(F19*D19,2) -> 65538.57 | I19: =+G19+(H19*$I$3) -> #REF!
A20: 01.01.02 | B20: Electrobomba Jockey de 15 GPM @ 265 PSI , Con motor trifásico asincrónico de 5.5 HP de 220 V @ 60 Hz
A21: 01.01.03 | B21: Accesorios de Fabrica Incluyendo: Manovacuómetro, Manómetro, Válvula de Alivio de Recirculación, Válvula Automática de Purga de Aire y Medidor de Caudal de 6 y 750 GPM
A22: 01.01 | B22: SISTEMA DE AGUA CONTRAINCENDIO - ROCIADORES Y GABINETES | I22: =SUM(H24:H27) -> 137302.59
B23: RED DE TUBERIA COLGADA Y ADOSADAS DE ACERO SCH-10 Y SCH-40
B24: Materiales para la instalación de la red contra incendios compuesto de tuberías de acero negro con costura. El espesor será Cedula 10 para tuberías ranuradas y soldadas y Cedula 40 para tuberías roscadas, Incluye el Suministro de Rociadores de respuesta estándar, con orificio de 1/2" NPT y factor K=5.6, con bulbo de vidrio de 5 mms rateado a 1550 F (680C). | C24: glb | D24: 1 | F24: 65361.7 | G24: =+E24*D24 -> 0 | H24: =+F24*D24 -> 65361.7 | I24: =+G24+(H24*$I$3) -> #REF!
B25: GABINETES Y ACCESORIOS | C25: und | D25: 49 | F25: 814.26 | G25: =+E25*D25 -> 0 | H25: =+F25*D25 -> 39898.74 | I25: =+G25+(H25*$I$3) -> #REF!
B26: MANO DE OBRA | F26: 0
B27: Instalación del sistema contra incendios a todo costo, Incluyendo mano de obra especializada, Suministro de Herramientas, Equipos y Materiales necesarios para la instalación, Trazo y Replanteo de Trabajos, Habilitación y acarreo de materiales, | C27: glb | D27: 1 | F27: 32042.15 | G27: =+E27*D27 -> 0 | H27: =+F27*D27 -> 32042.15 | I27: =+G27+(H27*$I$3) -> #REF!

Sheet IIMM
A2: INSTALACIONES MECANICAS
H3: T.C | I3: 3.75
A4: Presupuesto | B4: PARDO 669
A5: Subpresupuesto | B5: INSTALACIONS MECANICAS
A6: Cliente | B6: : V&V Bravo S.A.C | F6: Costo al | G6: 45394
A7: Lugar
A8: ITEM | B8: DESCRIPCION | C8: UND | D8: CANTIDAD | E8: P.U (S/.) | F8: P.U ($.) | G8: PARCIAL (S/.) | H8: PARCIAL ($) | I8: TOTAL
B9: SISTEMA DE VENTILACION MECANICA | I9: =SUM(H11:H121) -> 108816.75
B10: VESTIBULO PREVIO VENTILADO Y ESCALERA
B11: INYECTOR CENTRÍFUGO DE SIMPLE ENTRADA Marca: SYSTEM AIR Modelo: BCSB Características: 4,980 CFM - 1.1"c.a. - 220V-3F-60Hz | D11: 1 | F11: 1348.85 | G11: =+ROUND(E11*D11,2) -> 0 | H11: =+ROUND(F11*D11,2) -> 1348.85 | I11: =+ROUND(G11+(H11*$I$3),2) -> 5058.19
B12: INYECTOR CENTRÍFUGO DE SIMPLE ENTRADA Marca: SYSTEM AIR Modelo: BCSB Características: 5,300 CFM - 1.1"c.a. - 220V-3F-60Hz | D12: 1 | F12: 1521.35 | G12: =+ROUND(E12*D12,2) -> 0 | H12: =+ROUND(F12*D12,2) -> 1521.35 | I12: =+ROUND(G12+(H12*$I$3),2) -> 5705.06
B13: INYECTOR CENTRÍFUGO EN GABINETE Marca: SYSTEM AIR Modelo: KVB Características: 5,500 CFM - 1.0"c.a. - 220V-3F-60Hz | D13: 1 | F13: 965.1 | G13: =+ROUND(E13*D13,2) -> 0 | H13: =+ROUND(F13*D13,2) -> 965.1 | I13: =+ROUND(G13+(H13*$I$3),2) -> 3619.13
B14: INYECTOR CENTRÍFUGO EN GABINETE Marca: SYSTEM AIR Modelo: KVB Características: 5,720 CFM - 1.0"c.a. - 220V-3F-60Hz | D14: 1 | F14: 965.1 | G14: =+ROUND(E14*D14,2) -> 0 | H14: =+ROUND(F14*D14,2) -> 965.1 | I14: =+ROUND(G14+(H14*$I$3),2) -> 3619.13
B15: EXTRACTOR CENTRÍFUGO DE SIMPLE ENTRADA Marca: SYSTEM AIR Modelo: BCSB Características: 7,470 CFM - 1.0"c.a. - 220V-3F-60Hz | D15: 1 | F15: 2030.1 | G15: =+ROUND(E15*D15,2) -> 0 | H15: =+ROUND(F15*D15,2) -> 2030.1 | I15: =+ROUND(G15+(H15*$I$3),2) -> 7612.88
B16: EXTRACTOR CENTRÍFUGO EN GABINETE Marca: SYSTEM AIR Modelo: KVB Características: 8,580 CFM - 1.0"c.a. - 220V-3F-60Hz | D16: 1 | F16: 1658.85 | G16: =+ROUND(E16*D16,2) -> 0 | H16: =+ROUND(F16*D16,2) -> 1658.85 | I16: =+ROUND(G16+(H16*$I$3),2) -> 6220.69
B17: SENSOR DE HUMO | D17: 4 | F17: 175.1 | G17: =+ROUND(E17*D17,2) -> 0 | H17: =+ROUND(F17*D17,2) -> 700.4 | I17: =+ROUND(G17+(H17*$I$3),2) -> 2626.5
B18: DAMPER BAROMÉTRICO 24"X24" ACP | D18: 2 | F18: 412.6 | G18: =+ROUND(E18*D18,2) -> 0 | H18: =+ROUND(F18*D18,2) -> 825.2 | I18: =+ROUND(G18+(H18*$I$3),2) -> 3094.5
B19: FILTRO DE MALLA DE ALUMINIO DE 38"X38"X1" | D19: 1 | F19: 200.1 | G19: =+ROUND(E19*D19,2) -> 0 | H19: =+ROUND(F19*D19,2) -> 200.1 | I19: =+ROUND(G19+(H19*$I$3),2) -> 750.38
B20: FILTRO DE MALLA DE ALUMINIO DE 40"X40"X1" | D20: 2 | F20: 225.1 | G20: =+ROUND(E20*D20,2) -> 0 | H20: =+ROUND(F20*D20,2) -> 450.2 | I20: =+ROUND(G20+(H20*$I$3),2) -> 1688.25
B21: FILTRO DE MALLA DE ALUMINIO DE 41"X41"X1" | D21: 1 | F21: 231.35 | G21: =+ROUND(E21*D21,2) -> 0 | H21: =+ROUND(F21*D21,2) -> 231.35 | I21: =+ROUND(G21+(H21*$I$3),2) -> 867.56
B22: EXTRACCIÓN DE MONÓXIDO DE CARBONO | F22: 0.1 | G22: =+ROUND(E22*D22,2) -> 0 | H22: =+ROUND(F22*D22,2) -> 0 | I22: =+ROUND(G22+(H22*$I$3),2) -> 0
B23: INYECTOR AXIAL Marca: SYSTEM AIR Modelo: WPA Características: 1,840 CFM - 0.5"c.a. - 220V-3F-60Hz | D23: 2 | F23: 551.35 | G23: =+ROUND(E23*D23,2) -> 0 | H23: =+ROUND(F23*D23,2) -> 1102.7 | I23: =+ROUND(G23+(H23*$I$3),2) -> 4135.13
B24: INYECTOR AXIAL Marca: SYSTEM AIR Modelo: WPA Características: 1,800 CFM - 0.5"c.a. - 220V-3F-60Hz | D24: 2 | F24: 551.35 | G24: =+ROUND(E24*D24,2) -> 0 | H24: =+ROUND(F24*D24,2) -> 1102.7 | I24: =+ROUND(G24+(H24*$I$3),2) -> 4135.13
B25: INYECTOR AXIAL Marca: SYSTEM AIR Modelo: WPA Características: 1,920 CFM - 0.5"c.a. - 220V-3F-60Hz | D25: 2 | F25: 551.35 | G25: =+ROUND(E25*D25,2) -> 0 | H25: =+ROUND(F25*D25,2) -> 1102.7 | I25: =+ROUND(G25+(H25*$I$3),2) -> 4135.13
B26: INYECTOR AXIAL Marca: SYSTEM AIR Modelo: WPA Características: 2,000 CFM - 0.5"c.a. - 220V-3F-60Hz | D26: 1 | F26: 551.35 | G26: =+ROUND(E26*D26,2) -> 0 | H26: =+ROUND(F26*D26,2) -> 551.35 | I26: =+ROUND(G26+(H26*$I$3),2) -> 2067.56
B27: INYECTOR AXIAL Marca: SYSTEM AIR Modelo: WPA Características: 2,040 CFM - 0.5"c.a. - 220V-3F-60Hz | D27: 2 | F27: 551.35 | G27: =+ROUND(E27*D27,2) -> 0 | H27: =+ROUND(F27*D27,2) -> 1102.7 | I27: =+ROUND(G27+(H27*$I$3),2) -> 4135.13
B28: INYECTOR AXIAL Marca: SYSTEM AIR Modelo: WPA Características: 2,800 CFM - 0.5"c.a. - 220V-3F-60Hz | D28: 1.5 | F28: 551.35 | G28: =+ROUND(E28*D28,2) -> 0 | H28: =+ROUND(F28*D28,2) -> 827.03 | I28: =+ROUND(G28+(H28*$I$3),2) -> 3101.36
B29: EXTRACTOR AXIAL Marca: SYSTEM AIR Modelo: WPA Características: 2,250 CFM - 1.0"c.a. - 220V-3F-60Hz | D29: 2 | F29: 565.1 | G29: =+ROUND(E29*D29,2) -> 0 | H29: =+ROUND(F29*D29,2) -> 1130.2 | I29: =+ROUND(G29+(H29*$I$3),2) -> 4238.25
B30: EXTRACTOR AXIAL Marca: SYSTEM AIR Modelo: WPA Características: 2,300 CFM - 1.0"c.a. - 220V-3F-60Hz | D30: 2 | F30: 565.1 | G30: =+ROUND(E30*D30,2) -> 0 | H30: =+ROUND(F30*D30,2) -> 1130.2 | I30: =+ROUND(G30+(H30*$I$3),2) -> 4238.25
B31: EXTRACTOR AXIAL Marca: SYSTEM AIR Modelo: WPA Características: 2,340 CFM - 1.0"c.a. - 220V-3F-60Hz | D31: 3 | F31: 565.1 | G31: =+ROUND(E31*D31,2) -> 0 | H31: =+ROUND(F31*D31,2) -> 1695.3 | I31: =+ROUND(G31+(H31*$I$3),2) -> 6357.38
B32: EXTRACTOR AXIAL Marca: SYSTEM AIR Modelo: WPA Características: 2,400 CFM - 1.0"c.a. - 220V-3F-60Hz | D32: 2 | F32: 565.1 | G32: =+ROUND(E32*D32,2) -> 0 | H32: =+ROUND(F32*D32,2) -> 1130.2 | I32: =+ROUND(G32+(H32*$I$3),2) -> 4238.25
B33: EXTRACTOR AXIAL Marca: SYSTEM AIR Modelo: WPA Características: 2,500 CFM - 1.0"c.a. - 220V-3F-60Hz | D33: 1 | F33: 565.1 | G33: =+ROUND(E33*D33,2) -> 0 | H33: =+ROUND(F33*D33,2) -> 565.1 | I33: =+ROUND(G33+(H33*$I$3),2) -> 2119.13
B34: EXTRACTOR AXIAL Marca: SYSTEM AIR Modelo: WPA Características: 2,550 CFM - 1.0"c.a. - 220V-3F-60Hz | D34: 2 | F34: 565.1 | G34: =+ROUND(E34*D34,2) -> 0 | H34: =+ROUND(F34*D34,2) -> 1130.2 | I34: =+ROUND(G34+(H34*$I$3),2) -> 4238.25
... B37: Damper de gravedad de fabricación nacional | D37: 23 | F37: 68.85 | G37: =+ROUND(E37*D37,2) -> 0 | H37: =+ROUND(F37*D37,2) -> 1583.55 | I37: =+ROUND(G37+(H37*$I$3),2) -> 5938.31
B38: VENTILACIÓN EN CUARTO DE BOMBAS | F38: 0.1 | G38: =+ROUND(E38*D38,2) -> 0 | H38: =+ROUND(F38*D38,2) -> 0 | I38: =+ROUND(G38+(H38*$I$3),2) -> 0
B39: INYECTOR CENTRÍFUGO EN LINEA Marca: SYSTEM AIR Modelo: KVB Características: 2,200 CFM - 0.5"c.a. - 220V-3F-60Hz | D39: 1 | F39: 608.85 | G39: =+ROUND(E39*D39,2) -> 0 | H39: =+ROUND(F39*D39,2) -> 608.85 | I39: =+ROUND(G39+(H39*$I$3),2) -> 2283.19
B40: EXTRACTOR CENTRÍFUGO EN LINEA Marca: SYSTEM AIR Modelo: KVB Características: 2,200 CFM - 0.3"c.a. - 220V-3F-60Hz | D40: 1 | F40: 608.85 | G40: =+ROUND(E40*D40,2) -> 0 | H40: =+ROUND(F40*D40,2) -> 608.85 | I40: =+ROUND(G40+(H40*$I$3),2) -> 2283.19
B41: DAMPER CORTA FUEGO DE 26"X12" Con fusible | D41: 2 | F41: 312.6 | G41: =+ROUND(E41*D41,2) -> 0 | H41: =+ROUND(F41*D41,2) -> 625.2 | I41: =+ROUND(G41+(H41*$I$3),2) -> 2344.5
B42: VENTILACIÓN EN CUARTO DE BASURA | F42: 0.1 | G42: =+ROUND(E42*D42,2) -> 0 | H42: =+ROUND(F42*D42,2) -> 0 | I42: =+ROUND(G42+(H42*$I$3),2) -> 0
B43: EXTRACTOR CENTRÍFUGO EN LINEA Marca: SYSTEM AIR Modelo: KVB Características: 1,150 CFM - 1.0"c.a. - 220V-3F-60Hz | D43: 1 | F43: 533.85 | G43: =+ROUND(E43*D43,2) -> 0 | H43: =+ROUND(F43*D43,2) -> 533.85 | I43: =+ROUND(G43+(H43*$I$3),2) -> 2001.94
B44: DAMPER CORTA FUEGO DE 20"X18" Con fusible | D44: 1 | F44: 300.1 | G44: =+ROUND(E44*D44,2) -> 0 | H44: =+ROUND(F44*D44,2) -> 300.1 | I44: =+ROUND(G44+(H44*$I$3),2) -> 1125.38
B45: VENTILACIÓN GRUPO ELECTRÓGENO | F45: 0.1 | G45: =+ROUND(E45*D45,2) -> 0 | H45: =+ROUND(F45*D45,2) -> 0 | I45: =+ROUND(G45+(H45*$I$3),2) -> 0
B46: EXTRACTOR AXIAL Marca: SYSTEM AIR Modelo: AW E Características: 1,000 CFM - 0.2"c.a. - 220V-1F-60Hz | D46: 1 | F46: 112.6 | G46: =+ROUND(E46*D46,2) -> 0 | H46: =+ROUND(F46*D46,2) -> 112.6 | I46: =+ROUND(G46+(H46*$I$3),2) -> 422.25
B47: DAMPER CORTA FUEGO DE 18"X18" Con fusible | D47: 1 | F47: 275.1 | G47: =+ROUND(E47*D47,2) -> 0 | H47: =+ROUND(F47*D47,2) -> 275.1 | I47: =+ROUND(G47+(H47*$I$3),2) -> 1031.63
B48: DAMPER CORTA FUEGO DE 40"X40" Con fusible | D48: 1 | F48: 525.1 | G48: =+ROUND(E48*D48,2) -> 0 | H48: =+ROUND(F48*D48,2) -> 525.1 | I48: =+ROUND(G48+(H48*$I$3),2) -> 1969.13
B49: VENTILACIÓN DE GIMNASIO | F49: 0.1 | G49: =+ROUND(E49*D49,2) -> 0 | H49: =+ROUND(F49*D49,2) -> 0 | I49: =+ROUND(G49+(H49*$I$3),2) -> 0
B50: INYECTOR AXIAL Marca: SYSTEM AIR Modelo: AW E Características: 480 CFM - 0.1"c.a. - 220V-1F-60Hz | D50: 1 | F50: 78.85 | G50: =+ROUND(E50*D50,2) -> 0 | H50: =+ROUND(F50*D50,2) -> 78.85 | I50: =+ROUND(G50+(H50*$I$3),2) -> 295.69
B51: EXTRACTOR AXIAL Marca: SYSTEM AIR Modelo: AW E Características: 480 CFM - 0.1"c.a. - 220V-1F-60Hz | D51: 1 | F51: 78.85 | G51: =+ROUND(E51*D51,2) -> 0 | H51: =+ROUND(F51*D51,2) -> 78.85 | I51: =+ROUND(G51+(H51*$I$3),2) -> 295.69
B52: VENTILACIÓN CO WORKING | F52: 0.1 | G52: =+ROUND(E52*D52,2) -> 0 | H52: =+ROUND(F52*D52,2) -> 0 | I52: =+ROUND(G52+(H52*$I$3),2) -> 0
B53: INYECTOR AXIAL Marca: SYSTEM AIR Modelo: AW E Características: 560 CFM - 0.1"c.a. - 220V-1F-60Hz | D53: 1 | F53: 81.35 | G53: =+ROUND(E53*D53,2) -> 0 | H53: =+ROUND(F53*D53,2) -> 81.35 | I53: =+ROUND(G53+(H53*$I$3),2) -> 305.06
B54: EXTRACTOR AXIAL Marca: SYSTEM AIR Modelo: AW E Características: 560 CFM - 0.1"c.a. - 220V-1F-60Hz | D54: 1 | F54: 81.35 | G54: =+ROUND(E54*D54,2) -> 0 | H54: =+ROUND(F54*D54,2) -> 81.35 | I54: =+ROUND(G54+(H54*$I$3),2) -> 305.06
B55: VENTILACIÓN DE PASILLOS Y HALL DE ASCENSORES | F55: 0.1 | G55: =+ROUND(E55*D55,2) -> 0 | H55: =+ROUND(F55*D55,2) -> 0 | I55: =+ROUND(G55+(H55*$I$3),2) -> 0
B56: INYECTOR CENTRIFUGO DE SIMPLE ENTRADA Marca: SYSTEM AIR Modelo: BCSB Características: 1,880 CFM - 1.0"c.a. - 220V-3F-60Hz | D56: 1 | F56: 711.35 | G56: =+ROUND(E56*D56,2) -> 0 | H56: =+ROUND(F56*D56,2) -> 711.35 | I56: =+ROUND(G56+(H56*$I$3),2) -> 2667.56
B57: INYECTOR CENTRIFUGO DE SIMPLE ENTRADA Marca: SYSTEM AIR Modelo: BCSB Características: 2,070 CFM - 1.0"c.a. - 220V-3F-60Hz | D57: 1 | F57: 836.35 | G57: =+ROUND(E57*D57,2) -> 0 | H57: =+ROUND(F57*D57,2) -> 836.35 | I57: =+ROUND(G57+(H57*$I$3),2) -> 3136.31
B58: EXTRACTOR CENTRIFUGO DE SIMPLE ENTRADA Marca: SYSTEM AIR Modelo: BCSB Características: 1,880 CFM - 1.0"c.a. - 220V-3F-60Hz | D58: 1 | F58: 711.35 | G58: =+ROUND(E58*D58,2) -> 0 | H58: =+ROUND(F58*D58,2) -> 711.35 | I58: =+ROUND(G58+(H58*$I$3),2) -> 2667.56
B59: EXTRACTOR CENTRIFUGO EN GABINETE Marca: SYSTEM AIR Modelo: BCSB Características: 2,070 CFM - 1.0"c.a. - 220V-3F-60Hz | D59: 1 | F59: 836.35 | G59: =+ROUND(E59*D59,2) -> 0 | H59: =+ROUND(F59*D59,2) -> 836.35 | I59: =+ROUND(G59+(H59*$I$3),2) -> 3136.31
B60: FILTRO DE MALLA DE ALUMINIO 24"X24"X1" | D60: 1 | F60: 81.35 | G60: =+ROUND(E60*D60,2) -> 0 | H60: =+ROUND(F60*D60,2) -> 81.35 | I60: =+ROUND(G60+(H60*$I$3),2) -> 305.06
B61: FILTRO DE MALLA DE ALUMINIO 25"X25"X1" | D61: 1 | F61: 87.6 | G61: =+ROUND(E61*D61,2) -> 0 | H61: =+ROUND(F61*D61,2) -> 87.6 | I61: =+ROUND(G61+(H61*$I$3),2) -> 328.5
B62: VENTILACIÓN DE BAÑOS Y CENTRO DE LAVADO | F62: 0.1 | G62: =+ROUND(E62*D62,2) -> 0 | H62: =+ROUND(F62*D62,2) -> 0 | I62: =+ROUND(G62+(H62*$I$3),2) -> 0
B63: EXTRACTOR AXIAL CON DAMPER Marca: LAVFILL Modelo: LWWF13-L Características: 100 CFM - 0.1" c.a. - 220V-1F-60Hz | D63: 460 | F63: 21.35 | G63: =+ROUND(E63*D63,2) -> 0 | H63: =+ROUND(F63*D63,2) -> 9821 | I63: =+ROUND(G63+(H63*$I$3),2) -> 36828.75
B64: EXTRACTOR EÓLICO | D64: 9 | F64: 375.1 | G64: =+ROUND(E64*D64,2) -> 0 | H64: =+ROUND(F64*D64,2) -> 3375.9 | I64: =+ROUND(G64+(H64*$I$3),2) -> 12659.63
B65: INSTALACION DEL SISTEMA | F65: 0.1 | G65: =+ROUND(E65*D65,2) -> 0 | H65: =+ROUND(F65*D65,2) -> 0 | I65: =+ROUND(G65+(H65*$I$3),2) -> 0
B66: VESTIBULO PREVIO VENTILADO Y ESCALERA | F66: 0.1 | G66: =+ROUND(E66*D66,2) -> 0 | H66: =+ROUND(F66*D66,2) -> 0 | I66: =+ROUND(G66+(H66*$I$3),2) -> 0
B67: Suministro e instalación de ductos metálicos de fierro galvanizado fabricados de acuerdo a la normativa SMACNA | D67: 405 | F67: 3.57 | G67: =+ROUND(E67*D67,2) -> 0 | H67: =+ROUND(F67*D67,2) -> 1445.85 | I67: =+ROUND(G67+(H67*$I$3),2) -> 5421.94
B68: SUMINISTRO E INSTALACIÓN DE REJILLAS DE FIERRO GALVANIZADO INCLUYE PROTECCIÓN ANTICORROSIVA, PINTADO CON ESMALTE DE COLOR BLANCO AL HORNO y DAMPER DE REGULACIÓN MANUAL | F68: 0.1 | G68: =+ROUND(E68*D68,2) -> 0 | H68: =+ROUND(F68*D68,2) -> 0 | I68: =+ROUND(G68+(H68*$I$3),2) -> 0
B69: REJILLAS DE INYECCIÓN Y EXTRACCIÓN | D69: 13520 | F69: 0.28 | G69: =+ROUND(E69*D69,2) -> 0 | H69: =+ROUND(F69*D69,2) -> 3785.6 | I69: =+ROUND(G69+(H69*$I$3),2) -> 14196
B70: Instalacion mecánica de ventilador centrífugo | D70: 6 | F70: 120.1 | G70: =+ROUND(E70*D70,2) -> 0 | H70: =+ROUND(F70*D70,2) -> 720.6 | I70: =+ROUND(G70+(H70*$I$3),2) -> 2702.25
B71: tablero de control de (6)Centrífugos. (1) Tableros eléctricos fabricado con plancha de fierro galvanizado 2 mm de espesor con recubrimiento anticorrosivo epóxico, hermético al polvo (IP-65) incluye: (6) contactores , (6) selectores MOA, (1) LED, (1) transformador y Borneras. -se deja bornera para la conección del cuarto del control al tablero | D71: 1 | F71: 2266.77 | G71: =+ROUND(E71*D71,2) -> 0 | H71: =+ROUND(F71*D71,2) -> 2266.77 | I71: =+ROUND(G71+(H71*$I$3),2) -> 8500.39
B72: instalación de sensor de humo | D72: 4 | F72: 66.77 | G72: =+ROUND(E72*D72,2) -> 0 | H72: =+ROUND(F72*D72,2) -> 267.08 | I72: =+ROUND(G72+(H72*$I$3),2) -> 1001.55
B73: EXTRACCIÓN DE MONÓXIDO DE CARBONO | F73: 0.1 | G73: =+ROUND(E73*D73,2) -> 0 | H73: =+ROUND(F73*D73,2) -> 0 | I73: =+ROUND(G73+(H73*$I$3),2) -> 0
B74: Suministro e instalación de ductos metálicos de fierro galvanizado fabricados de acuerdo a la normativa SMACNA | D74: 875 | F74: 3.57 | G74: =+ROUND(E74*D74,2) -> 0 | H74: =+ROUND(F74*D74,2) -> 3123.75 | I74: =+ROUND(G74+(H74*$I$3),2) -> 11714.06
B75: SUMINISTRO E INSTALACIÓN DE REJILLAS DE FIERRO GALVANIZADO INCLUYE PROTECCIÓN ANTICORROSIVA, PINTADO CON ESMALTE DE COLOR BLANCO AL HORNO y DAMPER DE REGULACIÓN MANUAL | F75: 0.1 | G75: =+ROUND(E75*D75,2) -> 0 | H75: =+ROUND(F75*D75,2) -> 0 | I75: =+ROUND(G75+(H75*$I$3),2) -> 0
B76: REJILLAS DE INYECCIÓN Y EXTRACCIÓN | D76: 23520 | F76: 0.28 | G76: =+ROUND(E76*D76,2) -> 0 | H76: =+ROUND(F76*D76,2) -> 6585.6 | I76: =+ROUND(G76+(H76*$I$3),2) -> 24696
B77: Instalación mecánica extractor AXIAL | D77: 12 | F77: 46.77 | G77: =+ROUND(E77*D77,2) -> 0 | H77: =+ROUND(F77*D77,2) -> 561.24 | I77: =+ROUND(G77+(H77*$I$3),2) -> 2104.65
B78: Instalación mecánica intector AXIAL | D78: 11 | F78: 46.77 | G78: =+ROUND(E78*D78,2) -> 0 | H78: =+ROUND(F78*D78,2) -> 514.47 | I78: =+ROUND(G78+(H78*$I$3),2) -> 1929.26
B79: Instalación mecánica de jet fan | D79: 11 | F79: 66.77 | G79: =+ROUND(E79*D79,2) -> 0 | H79: =+ROUND(F79*D79,2) -> 734.47 | I79: =+ROUND(G79+(H79*$I$3),2) -> 2754.26
B80: TABLERO DE CONTROL de (11) Jet Fan, (11) Inyectores y (12) Extractores . (1) Tableros eléctricos fabricado con plancha de fierro galvanizado 2 mm de espesor con recubrimiento anticorrosivo epóxico, hermetico al polvo (IP-55) incluye: (1) contactores jet fan ,(1) contactor extracción, (1) contactor inyector,(1) selectores MOA, (1) LED, (1) transformador y Borneras. -se deja bornera para la conección del cuarto del control al tablero | D80: 1 | F80: 5200.1 | G80: =+ROUND(E80*D80,2) -> 0 | H80: =+ROUND(F80*D80,2) -> 5200.1 | I80: =+ROUND(G80+(H80*$I$3),2) -> 19500.38
B81: Instalación de detector de monóxido de carbono, cableado de comunicación y coneccion eléctrica | D81: 11 | F81: 66.77 | G81: =+ROUND(E81*D81,2) -> 0 | H81: =+ROUND(F81*D81,2) -> 734.47 | I81: =+ROUND(G81+(H81*$I$3),2) -> 2754.26
B82: VENTILACIÓN EN CUARTO DE BOMBAS | F82: 0.1 | G82: =+ROUND(E82*D82,2) -> 0 | H82: =+ROUND(F82*D82,2) -> 0 | I82: =+ROUND(G82+(H82*$I$3),2) -> 0
B83: Suministro e instalación de ductos metálicos de fierro galvanizado fabricados de acuerdo a la normativa SMACNA, | D83: 55 | F83: 3.57 | G83: =+ROUND(E83*D83,2) -> 0 | H83: =+ROUND(F83*D83,2) -> 196.35 | I83: =+ROUND(G83+(H83*$I$3),2) -> 736.31
B84: SUMINISTRO E INSTALACIÓN DE REJILLAS DE FIERRO GALVANIZADO INCLUYE PROTECCIÓN ANTICORROSIVA, PINTADO CON ESMALTE DE COLOR BLANCO AL HORNO y DAMPER DE REGULACIÓN MANUAL | F84: 0.1 | G84: =+ROUND(E84*D84,2) -> 0 | H84: =+ROUND(F84*D84,2) -> 0 | I84: =+ROUND(G84+(H84*$I$3),2) -> 0
B85: REJILLAS DE INYECCIÓN Y EXTRACCIÓN | D85: 580 | F85: 0.28 | G85: =+ROUND(E85*D85,2) -> 0 | H85: =+ROUND(F85*D85,2) -> 162.4 | I85: =+ROUND(G85+(H85*$I$3),2) -> 609
B86: Instalación mecánica de ventilador centrífugo | D86: 2 | F86: 66.77 | G86: =+ROUND(E86*D86,2) -> 0 | H86: =+ROUND(F86*D86,2) -> 133.54 | I86: =+ROUND(G86+(H86*$I$3),2) -> 500.78
B87: Instalación de damper corta fuego | D87: 2 | F87: 13.44 | G87: =+ROUND(E87*D87,2) -> 0 | H87: =+ROUND(F87*D87,2) -> 26.88 | I87: =+ROUND(G87+(H87*$I$3),2) -> 100.8
B88: TABLERO DE CONTROL | D88: 1 | F88: 533.44 | G88: =+ROUND(E88*D88,2) -> 0 | H88: =+ROUND(F88*D88,2) -> 533.44 | I88: =+ROUND(G88+(H88*$I$3),2) -> 2000.4
B89: VENTILACIÓN EN CUARTO DE BASURA | F89: 0.1 | G89: =+ROUND(E89*D89,2) -> 0 | H89: =+ROUND(F89*D89,2) -> 0 | I89: =+ROUND(G89+(H89*$I$3),2) -> 0
B90: Suministro e instalación de ductos metálicos de fierro galvanizado fabricados de acuerdo a la normativa SMACNA, | D90: 40 | F90: 3.57 | G90: =+ROUND(E90*D90,2) -> 0 | H90: =+ROUND(F90*D90,2) -> 142.8 | I90: =+ROUND(G90+(H90*$I$3),2) -> 535.5
B91: SUMINISTRO E INSTALACIÓN DE REJILLAS DE FIERRO GALVANIZADO INCLUYE PROTECCIÓN ANTICORROSIVA, PINTADO CON ESMALTE DE COLOR BLANCO AL HORNO y DAMPER DE REGULACIÓN MANUAL | F91: 0.1 | G91: =+ROUND(E91*D91,2) -> 0 | H91: =+ROUND(F91*D91,2) -> 0 | I91: =+ROUND(G91+(H91*$I$3),2) -> 0
B92: REJILLAS DE INYECCIÓN Y EXTRACCIÓN | D92: 810 | F92: 0.28 | G92: =+ROUND(E92*D92,2) -> 0 | H92: =+ROUND(F92*D92,2) -> 226.8 | I92: =+ROUND(G92+(H92*$I$3),2) -> 850.5
B93: Instalación mecánica de ventilador centrífugo | D93: 1 | F93: 66.77 | G93: =+ROUND(E93*D93,2) -> 0 | H93: =+ROUND(F93*D93,2) -> 66.77 | I93: =+ROUND(G93+(H93*$I$3),2) -> 250.39
B94: Instalación de damper corta fuego | D94: 1 | F94: 13.44 | G94: =+ROUND(E94*D94,2) -> 0 | H94: =+ROUND(F94*D94,2) -> 13.44 | I94: =+ROUND(G94+(H94*$I$3),2) -> 50.4
B95: Encendido de equipos mediante botonera o timer | D95: 1 | F95: 266.77 | G95: =+ROUND(E95*D95,2) -> 0 | H95: =+ROUND(F95*D95,2) -> 266.77 | I95: =+ROUND(G95+(H95*$I$3),2) -> 1000.39
B96: VENTILACIÓN EN CUARTO DE BASURA | F96: 0.1 | G96: =+ROUND(E96*D96,2) -> 0 | H96: =+ROUND(F96*D96,2) -> 0 | I96: =+ROUND(G96+(H96*$I$3),2) -> 0
B97: SUMINISTRO E INSTALACIÓN DE REJILLAS DE FIERRO GALVANIZADO INCLUYE PROTECCIÓN ANTICORROSIVA, PINTADO CON ESMALTE DE COLOR BLANCO AL HORNO y DAMPER DE REGULACIÓN MANUAL | F97: 0.1 | G97: =+ROUND(E97*D97,2) -> 0 | H97: =+ROUND(F97*D97,2) -> 0 | I97: =+ROUND(G97+(H97*$I$3),2) -> 0
B98: REJILLAS DE INYECCIÓN Y EXTRACCIÓN | D98: 1925 | F98: 0.28 | G98: =+ROUND(E98*D98,2) -> 0 | H98: =+ROUND(F98*D98,2) -> 539 | I98: =+ROUND(G98+(H98*$I$3),2) -> 2021.25
B99: Instalación mecánica de ventilador AXIAL | D99: 1 | F99: 26.77 | G99: =+ROUND(E99*D99,2) -> 0 | H99: =+ROUND(F99*D99,2) -> 26.77 | I99: =+ROUND(G99+(H99*$I$3),2) -> 100.39
B100: Instalación de damper corta fuego | D100: 2 | F100: 26.77 | G100: =+ROUND(E100*D100,2) -> 0 | H100: =+ROUND(F100*D100,2) -> 53.54 | I100: =+ROUND(G100+(H100*$I$3),2) -> 200.78
B101: Encendido de equipos mediante botonera o timer | D101: 1 | F101: 266.77 | G101: =+ROUND(E101*D101,2) -> 0 | H101: =+ROUND(F101*D101,2) -> 266.77 | I101: =+ROUND(G101+(H101*$I$3),2) -> 1000.39
B102: VENTILACIÓN DE GIMNASIO | F102: 0.1 | G102: =+ROUND(E102*D102,2) -> 0 | H102: =+ROUND(F102*D102,2) -> 0 | I102: =+ROUND(G102+(H102*$I$3),2) -> 0
B103: SUMINISTRO E INSTALACIÓN DE REJILLAS DE FIERRO GALVANIZADO INCLUYE PROTECCIÓN ANTICORROSIVA, PINTADO CON ESMALTE DE COLOR BLANCO AL HORNO y DAMPER DE REGULACIÓN MANUAL | F103: 0.1 | G103: =+ROUND(E103*D103,2) -> 0 | H103: =+ROUND(F103*D103,2) -> 0 | I103: =+ROUND(G103+(H103*$I$3),2) -> 0
...

Sheet INSTALACIONES
A2: INSTALACIONES
H3: T.C | I3: 3.7
A4: Presupuesto | B4: SAN FELIPE
A5: Subpresupuesto | B5: INSTALACIONES
A6: Cliente | B6: : V&V Bravo S.A.C | F6: Costo al | G6: 45392
A7: Lugar
A8: ITEM | B8: DESCRIPCION | C8: UND | D8: CANTIDAD | E8: P.U (S/.) | F8: P.U ($.) | G8: PARCIAL (S/.) | H8: PARCIAL ($) | I8: TOTAL
A9: 01.01 | B9: INTERCOMUNICADORES | I9: =SUM(H10:H18) -> 13589.69
A10: 01.01.01.01 | B10: Central de conserjería de audio/vídeo con pantalla LCD 7" | C10: und | D10: 1 | F10: 948.23 | G10: =+ROUND(E10*D10,2) -> 0 | H10: =+ROUND(F10*D10,2) -> 948.23 | I10: =+ROUND(G10+(H10*$I$3),2) -> 3508.45
B11: AudioPortero Alfanumerico Digital | C11: und | D11: 1 | F11: 338.66 | G11: =+ROUND(E11*D11,2) -> 0 | H11: =+ROUND(F11*D11,2) -> 338.66 | I11: =+ROUND(G11+(H11*$I$3),2) -> 1253.04
B12: Intercomunicador tipo telefono Sprint L2 | C12: und | D12: 180 | F12: 38.24 | G12: =+ROUND(E12*D12,2) -> 0 | H12: =+ROUND(F12*D12,2) -> 6883.2 | I12: =+ROUND(G12+(H12*$I$3),2) -> 25467.84
B13: COMPLEMENTOS DEL SISTEMA | G13: =+ROUND(E13*D13,2) -> 0 | H13: =+ROUND(F13*D13,2) -> 0 | I13: =+ROUND(G13+(H13*$I$3),2) -> 0
B14: Interfaz de expansión de anexos/longitud | C14: und | D14: 3 | F14: 305.88 | G14: =+ROUND(E14*D14,2) -> 0 | H14: =+ROUND(F14*D14,2) -> 917.64 | I14: =+ROUND(G14+(H14*$I$3),2) -> 3395.27
B15: Fuente de poder de 1.2A para sistemas de audio/video | C15: und | D15: 4 | F15: 119.29 | G15: =+ROUND(E15*D15,2) -> 0 | H15: =+ROUND(F15*D15,2) -> 477.16 | I15: =+ROUND(G15+(H15*$I$3),2) -> 1765.49
B16: Configuradores (Paquete de 10 piezas) | C16: und | D16: 57 | F16: 9.22 | G16: =+ROUND(E16*D16,2) -> 0 | H16: =+ROUND(F16*D16,2) -> 525.54 | I16: =+ROUND(G16+(H16*$I$3),2) -> 1944.5
B17: MATERIALES | C17: glb | D17: 1 | F17: 2124.05 | G17: =+ROUND(E17*D17,2) -> 0 | H17: =+ROUND(F17*D17,2) -> 2124.05 | I17: =+ROUND(G17+(H17*$I$3),2) -> 7858.99
B18: MANO DE OBRA | C18: glb | D18: 1 | F18: 1375.21 | G18: =+ROUND(E18*D18,2) -> 0 | H18: =+ROUND(F18*D18,2) -> 1375.21 | I18: =+ROUND(G18+(H18*$I$3),2) -> 5088.28
A19: 01.02 | B19: DETECCION CONTRAINCENDIOS | I19: =SUM(H21:H37) -> 41537.14
B20: PANEL DE ALARMA CONTRA INCENDIOS Y COMPLEMENTOS
B21: Panel de Detección y Alarma Contra Incendio Direccionable con Certificado UL-864, para sistemas DACI en edificios | C21: und | D21: 1 | F21: 640.37 | G21: =+E21*D21 -> 0 | H21: =+ROUND(F21*D21,2) -> 640.37 | I21: =+ROUND(G21+(H21*$I$3),2) -> 2369.37
B22: Fuente de alimentación para dtectores convencionales. Certificado UL | C22: und | D22: 1 | F22: 471.54 | G22: =+E22*D22 -> 0 | H22: =+ROUND(F22*D22,2) -> 471.54 | I22: =+ROUND(G22+(H22*$I$3),2) -> 1744.7
B23: Bateria de 12v/7Ah | C23: und | D23: 4 | F23: 15.05 | G23: =+E23*D23 -> 0 | H23: =+ROUND(F23*D23,2) -> 60.2 | I23: =+ROUND(G23+(H23*$I$3),2) -> 222.74
B24: DISPOSITIVOS DE INICIACIÓN | F24: 0 | H24: =+ROUND(F24*D24,2) -> 0 | I24: =+ROUND(G24+(H24*$I$3),2) -> 0
B25: Detector de Humo Convencional. Certificado UL | C25: und | D25: 595 | F25: 14.95 | G25: =+E25*D25 -> 0 | H25: =+ROUND(F25*D25,2) -> 8895.25 | I25: =+ROUND(G25+(H25*$I$3),2) -> 32912.43
B26: Detector de Temperatura Convencional. Certificado UL | C26: und | D26: 175 | F26: 15.52 | G26: =+E26*D26 -> 0 | H26: =+ROUND(F26*D26,2) -> 2716 | I26: =+ROUND(G26+(H26*$I$3),2) -> 10049.2
B27: Detector de Humo/Temperatura Convencional. | C27: und | D27: 5 | F27: 12.01 | G27: =+E27*D27 -> 0 | H27: =+ROUND(F27*D27,2) -> 60.05 | I27: =+ROUND(G27+(H27*$I$3),2) -> 222.19
B28: Estación manual acción doble Convencional UL | C28: und | D28: 63 | F28: 32.88 | G28: =+E28*D28 -> 0 | H28: =+ROUND(F28*D28,2) -> 2071.44 | I28: =+ROUND(G28+(H28*$I$3),2) -> 7664.33
B29: Sensor de aniego + Procesador | C29: und | D29: 1 | F29: 92.4 | G29: =+E29*D29 -> 0 | H29: =+ROUND(F29*D29,2) -> 92.4 | I29: =+ROUND(G29+(H29*$I$3),2) -> 341.88
B30: Detector fotoeléctrico de humo para ducto UL. Incluye tubo de muestreo de 8" | C30: und | D30: 8 | F30: 97.83 | G30: =+E30*D30 -> 0 | H30: =+ROUND(F30*D30,2) -> 782.64 | I30: =+ROUND(G30+(H30*$I$3),2) -> 2895.77
B31: DISPOSITIVOS DE NOTIFICACIÓN | F31: 0 | H31: =+ROUND(F31*D31,2) -> 0 | I31: =+ROUND(G31+(H31*$I$3),2) -> 0
B32: Sirena con Luz Estroboscópica multicandela. Certicado UL | C32: und | D32: 245 | F32: 29.23 | G32: =+E32*D32 -> 0 | H32: =+ROUND(F32*D32,2) -> 7161.35 | I32: =+ROUND(G32+(H32*$I$3),2) -> 26497
B33: Fuente de alimentación Booster NACs para sirenas. Certificado UL | C33: und | D33: 4 | F33: 471.54 | G33: =+E33*D33 -> 0 | H33: =+ROUND(F33*D33,2) -> 1886.16 | I33: =+ROUND(G33+(H33*$I$3),2) -> 6978.79
B34: Bateria de 12v/7Ah | C34: und | D34: 8 | F34: 15.05 | G34: =+E34*D34 -> 0 | H34: =+ROUND(F34*D34,2) -> 120.4 | I34: =+ROUND(G34+(H34*$I$3),2) -> 445.48
B35: MÓDULOS | C35: glb | D35: 1 | F35: 5798.01 | G35: =+E35*D35 -> 0 | H35: =+ROUND(F35*D35,2) -> 5798.01 | I35: =+ROUND(G35+(H35*$I$3),2) -> 21452.64
B36: MATERIALES | C36: glb | D36: 1 | F36: 8945.25 | G36: =+E36*D36 -> 0 | H36: =+ROUND(F36*D36,2) -> 8945.25 | I36: =+ROUND(G36+(H36*$I$3),2) -> 33097.43
B37: MANO DE OBRA | C37: glb | D37: 1 | F37: 1836.08 | G37: =+E37*D37 -> 0 | H37: =+ROUND(F37*D37,2) -> 1836.08 | I37: =+ROUND(G37+(H37*$I$3),2) -> 6793.5
A38: 01.03 | B38: CCTV | I38: =+H39 -> 2556.7
A39: 01.01.01.05 | B39: Sistema de Circuito cerrado de Televisión | C39: glb | D39: 1 | F39: 2556.7 | G39: =+ROUND(E39*D39,2) -> 0 | H39: =+ROUND(F39*D39,2) -> 2556.7 | I39: =+ROUND(G39+(H39*$I$3),2) -> 9459.79
A40: 01.03 | B40: SISTEMA DE GAS | I40: =+G41 -> 190389.22
A41: 01.01.01.05 | B41: Sistema de gas 2 puntos (cocina/horno - therma) 149 Departamentos Redes internas PealPe Montantes de cobre | C41: glb | D41: 1 | E41: 190389.22 | G41: =+ROUND(E41*D41,2) -> 190389.22 | H41: =+ROUND(F41*D41,2) -> 0 | I41: =+ROUND(G41+(H41*$I$3),2) -> 190389.22
A42: 01.05 | B42: PISCINA | I42: =SUM(I43:I48) -> 63573.6
