Workbook
Name tc: #REF!

Sheet OP
A2: OBRAS PROVISIONALES
A4: Presupuesto | B4: =#REF! -> #REF!
A5: Subpresupuesto | B5: =$A$2 -> OBRAS PROVISIONALES
A6: Cliente | B6: =#REF! -> #REF!
A7: Lugar | B7: =#REF! -> #REF!
A8: Fecha | B8: =#REF! -> #REF!
A12: ITEM | B12: DESCRIPCION | C12: UND | D12: CANTIDAD | E12: P.U. (PEN) | F12: P.U. (USD) | G12: P.U. (TOTAL) | H12: PRECIO PARCIAL (PEN) | I12: PRECIO PARCIAL (USD) | J12: PRECIO TOTAL (PEN) | K12: TOTAL
A13: 01 | B13: OBRAS PROVISIONALES, TRABAJOS PRELIMINARES
A14: =A13+0.01 -> 1.01 | B14: CONSTRUCCIONES PROVISIONALES | H14: =IFERROR(IF(D14=0,"",$D14*E14),"") | I14: =IFERROR(IF(D14=0,"",$D14*F14),"") | K14: 375184.22
A15: =GG!A13+0.0001 -> 12.0101 | B15: OFICINA DE OBRA PARA CONTRATISTA | C15: glb | D15: 1 | E15: 8532.17 | G15: 8532.17 | H15: =+ROUND(D15*E15,2) -> 8532.17 | I15: =+ROUND(D15*F15,2) -> 0 | J15: 8532.17
A16: =A15+0.0001 -> 12.0102 | B16: OFICINA DE OBRA PARA SUPERVISIÓN | C16: glb | D16: 1 | E16: 3318.85 | G16: 3318.85 | H16: =+ROUND(D16*E16,2) -> 3318.85 | I16: =+ROUND(D16*F16,2) -> 0 | J16: 3318.85
A17: =A16+0.0001 -> 12.0103 | B17: OFICINA SALA DE REUNIONES | C17: glb | D17: 1 | E17: 3318.85 | G17: 3318.85 | H17: =+ROUND(D17*E17,2) -> 3318.85 | I17: =+ROUND(D17*F17,2) -> 0 | J17: 3318.85
A18: =A17+0.0001 -> 12.0104 | B18: ALMACEN DE OBRA | C18: glb | D18: 1 | E18: 10767.51 | G18: 10767.51 | H18: =+ROUND(D18*E18,2) -> 10767.51 | I18: =+ROUND(D18*F18,2) -> 0 | J18: 10767.51
A19: =A18+0.0001 -> 12.0105 | B19: COMEDOR PERSONAL OBRERO | C19: glb | D19: 1 | E19: 6265.24 | G19: 6265.24 | H19: =+ROUND(D19*E19,2) -> 6265.24 | I19: =+ROUND(D19*F19,2) -> 0 | J19: 6265.24
A20: =A19+0.0001 -> 12.0106 | B20: VESTUARIO PARA OBREROS | C20: glb | D20: 1 | E20: 6960.37 | G20: 6960.37 | H20: =+ROUND(D20*E20,2) -> 6960.37 | I20: =+ROUND(D20*F20,2) -> 0 | J20: 6960.37
A21: =A20+0.0001 -> 12.0107 | B21: TRASLADO DE CAMPAMENTO PROVISIONAL A SOTANOS | C21: und | D21: 1 | E21: 5553.24 | G21: 5553.24 | H21: =+ROUND(D21*E21,2) -> 5553.24 | I21: =+ROUND(D21*F21,2) -> 0 | J21: 5553.24
A22: =A21+0.0001 -> 12.0108 | B22: CASETA PARA GUARDIANIA | C22: glb | D22: 1 | E22: 850 | G22: 850 | H22: =+ROUND(D22*E22,2) -> 850 | I22: =+ROUND(D22*F22,2) -> 0 | J22: 850
A23: =A22+0.0001 -> 12.0109 | B23: BAÑOS PORTATILES DE OBRA PARA PERSONAL STAFF Y SUPERVISION COMPARTIDOS | C23: mes | D23: 9.5 | E23: 780 | G23: 780 | H23: =+ROUND(D23*E23,2) -> 7410 | I23: =+ROUND(D23*F23,2) -> 0 | J23: 7410
A24: =A23+0.0001 -> 12.011 | B24: CONSTRUCCION DE SSHH (1ER NIVEL) | C24: glb | D24: 1 | E24: 10044.5 | G24: 10044.5 | H24: =+ROUND(D24*E24,2) -> 10044.5 | I24: =+ROUND(D24*F24,2) -> 0 | J24: 10044.5
A25: =A24+0.0001 -> 12.0111 | B25: SSHH PORTATILES PARA OBREROS | C25: mes | D25: 22 | E25: 330 | G25: 330 | H25: =+ROUND(D25*E25,2) -> 7260 | I25: =+ROUND(D25*F25,2) -> 0 | J25: 7260
A26: =A25+0.0001 -> 12.0112 | B26: DUCHAS PORTATILES PARA OBREROS | C26: mes | D26: 9.5 | E26: 560 | G26: 560 | H26: =+ROUND(D26*E26,2) -> 5320 | I26: =+ROUND(D26*F26,2) -> 0 | J26: 5320
A27: =A26+0.0001 -> 12.0113 | B27: ALQUILER LAVAMANOS PARA OBREROS | C27: mes | D27: 17 | E27: 660 | G27: 660 | H27: =+ROUND(D27*E27,2) -> 11220 | I27: =+ROUND(D27*F27,2) -> 0 | J27: 11220
A28: =A27+0.0001 -> 12.0114 | B28: ESCUADRAS METALICAS PARA LAS OFICINAS EN MUROS ANCLADOS | F28: 0 | H28: =+ROUND(D28*E28,2) -> 0 | I28: =+ROUND(D28*F28,2) -> 0 | J28: 0
A29: =A28+0.0001 -> 12.0115 | B29: ALQUILER DE ESCUADRAS METÁLICAS | C29: ml | D29: 65 | E29: 760 | G29: 760 | H29: =+ROUND(D29*E29,2) -> 49400 | I29: =+ROUND(D29*F29,2) -> 0 | J29: 49400
A30: =A29+0.0001 -> 12.0116 | B30: INSTALACIÓN DE ESCUADRAS METÁLICAS | C30: ml | D30: 65 | E30: 124.59 | G30: 124.59 | H30: =+ROUND(D30*E30,2) -> 8098.35 | I30: =+ROUND(D30*F30,2) -> 0 | J30: 8098.35
A31: =A30+0.0001 -> 12.0117 | B31: PERNOS DE EXPANSIÓN | C31: und | D31: 520 | F31: 8.7 | G31: 32.625 | H31: =+ROUND(D31*E31,2) -> 0 | I31: =+ROUND(D31*F31,2) -> 4524 | J31: 16965
A32: =A31+0.0001 -> 12.0118 | B32: DESISTALACION DE ESCUADRAS METÁLICAS | C32: ml | D32: 65 | E32: 49.06 | G32: 49.06 | H32: =+ROUND(D32*E32,2) -> 3188.9 | I32: =+ROUND(D32*F32,2) -> 0 | J32: 3188.9
A33: =A32+0.0001 -> 12.0119 | B33: MADERA CACHIMBO 2" X 12" X 10´, SOBRE ESCUADRAS METÁLICAS | C33: und | D33: 140 | E33: 127.5 | G33: 127.5 | H33: =+ROUND(D33*E33,2) -> 17850 | I33: =+ROUND(D33*F33,2) -> 0 | J33: 17850
A34: =A33+0.0001 -> 12.012 | B34: INSTALACIÓN Y DESISTALACIÓN DE MADERA, SOBRE ESCUADRAS METÁLICAS | C34: ml | D34: 65 | E34: 92.13 | G34: 92.13 | H34: =+ROUND(D34*E34,2) -> 5988.45 | I34: =+ROUND(D34*F34,2) -> 0 | J34: 5988.45
A35: =A34+0.0001 -> 12.0121 | B35: VENTILACION PROVISIONAL EN SOTANOS | C35: glb | D35: 1 | E35: 5250 | G35: 5250 | H35: =+ROUND(D35*E35,2) -> 5250 | I35: =+ROUND(D35*F35,2) -> 0 | J35: 5250
A36: =A35+0.0001 -> 12.0122 | B36: PROTECCIÓN DE VECINOS CON MALLA RASCHEL (ENCAPSULADO) | C36: glb | D36: 1 | E36: 104538.67 | G36: 104538.67 | H36: =+ROUND(D36*E36,2) -> 104538.67 | I36: =+ROUND(D36*F36,2) -> 0 | J36: 104538.67
A37: =A36+0.0001 -> 12.0123 | B37: RENOVACIÓN DE MALLA RACHEL | C37: glb | D37: 1 | E37: 11741.72 | G37: 11741.72 | H37: =+ROUND(D37*E37,2) -> 11741.72 | I37: =+ROUND(D37*F37,2) -> 0 | J37: 11741.72
A38: =A37+0.0001 -> 12.0124 | B38: CERCO METALICO DE OBRA | C38: ml | D38: 60 | E38: 475 | G38: 475 | H38: =+ROUND(D38*E38,2) -> 28500 | I38: =+ROUND(D38*F38,2) -> 0 | J38: 28500
A39: =A38+0.0001 -> 12.0125 | B39: BASTIDORES METALICOS PARA FIJAR MALLA DE PROTECCION + MALLA RACHELL | C39: ml | D39: 100 | E39: 100.8 | G39: 100.8 | H39: =+ROUND(D39*E39,2) -> 10080 | I39: =+ROUND(D39*F39,2) -> 0 | J39: 10080
A40: =A39+0.0001 -> 12.0126 | B40: MANTENIMIENTO A MITAD DE OBRA DE CERCO PROVISIONAL DE OBRA | C40: ml | D40: 100 | E40: 74.4 | G40: 74.4 | H40: =+ROUND(D40*E40,2) -> 7440 | I40: =+ROUND(D40*F40,2) -> 0 | J40: 7440
A41: =A40+0.0001 -> 12.0127 | B41: REUBICACION DE CERCO DE OBRA EXISTENTE | C41: ml | D41: 40 | E41: 97.21 | G41: 97.21 | H41: =+ROUND(D41*E41,2) -> 3888.4 | I41: =+ROUND(D41*F41,2) -> 0 | J41: 3888.4
A42: =A40+0.0001 -> 12.0127 | B42: DESMONTAJE DE CERCO PROVISIONAL DE OBRA | C42: ml | D42: 100 | E42: 84.84 | G42: 84.84 | H42: =+ROUND(D42*E42,2) -> 8484 | I42: =+ROUND(D42*F42,2) -> 0 | J42: 8484
A43: =A42+0.0001 -> 12.0128 | B43: PROTECCION PERIMETRAL INICIAL VERTICAL DE VECINOS | C43: glb | D43: 1 | E43: 3250 | G43: 3250 | H43: =+ROUND(D43*E43,2) -> 3250 | I43: =+ROUND(D43*F43,2) -> 0 | J43: 3250
A44: =A43+0.0001 -> 12.0129 | B44: PROTECCION HORIZONTAL INICIAL DE VECINOS | C44: glb | D44: 1 | E44: 3000 | G44: 3000 | H44: =+ROUND(D44*E44,2) -> 3000 | I44: =+ROUND(D44*F44,2) -> 0 | J44: 3000
A45: =A44+0.0001 -> 12.013 | B45: CARTEL DE OBRA | C45: glb | D45: 1 | E45: 700 | G45: 700 | H45: =+ROUND(D45*E45,2) -> 700 | I45: =+ROUND(D45*F45,2) -> 0 | J45: 700
A46: =A14+0.01 -> 1.02 | B46: CAMPAMENTO Y SALA DE VENTAS CLIENTE - NO SE CONSIDERA | F46: 0 | K46: 0
A47: =A46+0.0001 -> 1.0201 | B47: ESCUADRAS Y TABLAS PARA CASETA DE VENTAS EN VOLADIZO | C47: ml | D47: 0 | E47: 1341.3425 | F47: 0 | H47: =+ROUND(D47*E47,2) -> 0 | I47: =+ROUND(D47*F47,2) -> 0 | J47: 0
A48: =A47+0.0001 -> 1.0202 | B48: TRASLADO DE CONTENEDOR SALA DE VENTAS CLIENTE (MOVIMIENTO 1 VEZ) | C48: und | D48: 0 | E48: 1695.26 | F48: 0 | H48: =+ROUND(D48*E48,2) -> 0 | I48: =+ROUND(D48*F48,2) -> 0 | J48: 0
A49: =A48+0.0001 -> 1.0203 | B49: ESCALERA METALICA (1-2 PISO) INGRESO DE SALA VENTAS A DEP PILOTO | C49: glb | D49: 0 | E49: 2400 | F49: 0 | H49: =+ROUND(D49*E49,2) -> 0 | I49: =+ROUND(D49*F49,2) -> 0 | J49: 0
A50: =A49+0.0001 -> 1.0204 | B50: PROTECCION A ACCESO VERTICAL (1- PISO) | C50: glb | D50: 0 | E50: 1500 | F50: 0 | H50: =+ROUND(D50*E50,2) -> 0 | I50: =+ROUND(D50*F50,2) -> 0 | J50: 0
A51: =A46+0.01 -> 1.03 | B51: MOVILIZACION DE CAMPAMENTO, MAQUINARIA Y HERRAMIENTAS | K51: 41100
A52: =A51+0.0001 -> 1.0301 | B52: MOVILIZACION (FLETES DURANTE LA OBRA) | C52: mes | D52: 22 | E52: 1250 | G52: 1250 | H52: =+ROUND(D52*E52,2) -> 27500 | I52: =+ROUND(D52*F52,2) -> 0 | J52: 27500
A53: =A52+0.0001 -> 1.0302 | B53: ALQUILER DE GRUA TELESCOPICA PARA MONTAJES DE CASETAS | C53: hm | D53: 0 | E53: 0 | F53: 120 | H53: =+ROUND(D53*E53,2) -> 0 | I53: =+ROUND(D53*F53,2) -> 0 | J53: 0
A54: =A53+0.0001 -> 1.0303 | B54: MOVILIZACION DE CAMPAMENTO, EQUIPOS Y HERRAMIENTAS | C54: glb | D54: 1 | E54: 2550 | G54: 2550 | H54: =+ROUND(D54*E54,2) -> 2550 | I54: =+ROUND(D54*F54,2) -> 0 | J54: 2550
A55: =A54+0.0001 -> 1.0304 | B55: MOVILIZACION DE ESCALERAS DE ACCESO, ANDAMIOS | C55: vje | D55: 10 | E55: 850 | G55: 850 | H55: =+ROUND(D55*E55,2) -> 8500 | I55: =+ROUND(D55*F55,2) -> 0 | J55: 8500
A56: =A55+0.0001 -> 1.0305 | B56: MOVILIZACION DE ENCOFRADOS MURO PANTALLA | C56: vje | D56: 0 | E56: 800 | H56: =+ROUND(D56*E56,2) -> 0 | I56: =+ROUND(D56*F56,2) -> 0 | J56: 0
A57: =A56+0.0001 -> 1.0306 | B57: MOVILIZACION DE ENCOFRADOS CISTERNA | C57: vje | D57: 0 | E57: 850 | H57: =+ROUND(D57*E57,2) -> 0 | I57: =+ROUND(D57*F57,2) -> 0 | J57: 0
A58: =A57+0.0001 -> 1.0307 | B58: MOVILIZACION DE ENCOFRADOS LOSAS Y VIGAS (2 TECHOS Y MEDIO) | C58: vje | D58: 0 | E58: 850 | F58: 0 | H58: =+ROUND(D58*E58,2) -> 0 | I58: =+ROUND(D58*F58,2) -> 0 | J58: 0
A59: =A58+0.0001 -> 1.0308 | B59: MOVILIZACION DE ENCOFRADOS PLACAS Y COLUMNAS | C59: vje | D59: 0 | E59: 800 | F59: 0 | H59: =+ROUND(D59*E59,2) -> 0 | I59: =+ROUND(D59*F59,2) -> 0 | J59: 0
A60: =A59+0.0001 -> 1.0309 | B60: DESMOVILIZACION DE CAMPAMENTO, EQUIPOS Y HERRAMIENTAS | C60: glb | D60: 1 | E60: 2550 | G60: 2550 | H60: =+ROUND(D60*E60,2) -> 2550 | I60: =+ROUND(D60*F60,2) -> 0 | J60: 2550
A61: =A60+0.0001 -> 1.031 | B61: ALQUILER DE GRUA TELESCOPICA PARA DESMONTAJES DE CASETAS | C61: hm | D61: 0 | E61: 0 | F61: 120 | H61: =+ROUND(D61*E61,2) -> 0 | I61: =+ROUND(D61*F61,2) -> 0 | J61: 0
A62: =A51+0.01 -> 1.04 | B62: MAQUINARIA Y HERRAMIENTAS | F62: 0 | H62: =+ROUND(D62*E62,2) -> 0 | I62: =+ROUND(D62*F62,2) -> 0 | J62: 0 | K62: 33250
A63: =A62+0.0001 -> 1.0401 | B63: NIVEL TOPOGRAFICO (INC CUADRILLA TOPOGRAFIA) | C63: glb | D63: 0 | H63: =+ROUND(D63*E63,2) -> 0 | I63: =+ROUND(D63*F63,2) -> 0 | J63: 0
A64: =A63+0.0001 -> 1.0402 | B64: TEODOLITO ELECTRICO (INC CUADRILLA TOPOGRAFIA) | C64: glb | D64: 0 | H64: =+ROUND(D64*E64,2) -> 0 | I64: =+ROUND(D64*F64,2) -> 0 | J64: 0
A65: =A64+0.0001 -> 1.0403 | B65: VIBRADOR ELECTRICO (INC EN APU DE CONCRETO) | C65: glb | D65: 0 | H65: =+ROUND(D65*E65,2) -> 0 | I65: =+ROUND(D65*F65,2) -> 0 | J65: 0
A66: =A65+0.0001 -> 1.0404 | B66: COMPACTADORA TIPO PLANCHA (INC EN APU EST SOT) | C66: glb | D66: 0 | H66: =+ROUND(D66*E66,2) -> 0 | I66: =+ROUND(D66*F66,2) -> 0 | J66: 0
A67: =A66+0.0001 -> 1.0405 | B67: APISONADOR TIPO CANGURO (INC EN APU EST SOT) | C67: glb | D67: 0 | H67: =+ROUND(D67*E67,2) -> 0 | I67: =+ROUND(D67*F67,2) -> 0 | J67: 0
A68: =A66+0.0001 -> 1.0405 | B68: MARTILLO ELECTRICO | C68: glb | D68: 4 | E68: 4600 | G68: 4600 | H68: =+ROUND(D68*E68,2) -> 18400 | I68: =+ROUND(D68*F68,2) -> 0 | J68: 18400
A69: =A68+0.0001 -> 1.0406 | B69: AMOLADORAS Y RADIALES | C69: glb | D69: 10 | E69: 675 | G69: 675 | H69: =+ROUND(D69*E69,2) -> 6750 | I69: =+ROUND(D69*F69,2) -> 0 | J69: 6750
A70: =A69+0.0001 -> 1.0407 | B70: KIT DE SOLAQUEO (ASPIRADORA DE POLVO UNIVERSAL) | C70: glb | D70: 3 | E70: 2250 | G70: 2250 | H70: =+ROUND(D70*E70,2) -> 6750 | I70: =+ROUND(D70*F70,2) -> 0 | J70: 6750
A71: =A70+0.0001 -> 1.0408 | B71: HIDROLAVADORA | C71: glb | D71: 1 | E71: 1350 | G71: 1350 | H71: =+ROUND(D71*E71,2) -> 1350 | I71: =+ROUND(D71*F71,2) -> 0 | J71: 1350
A72: =A62+0.01 -> 1.05 | B72: TRANSPORTE VERTICAL Y HORIZONTAL | F72: 0 | K72: 1200488.1
A73: =A72+0.0001 -> 1.0501 | B73: ALQUILER GRUA TORRE - TREPADORA
A74: =A73+0.000001 -> 1.050101 | B74: OPERADOR DE GRUA X 200 HORAS MENSUALES | C74: mes | D74: 11 | E74: 0 | F74: 2218 | G74: 8317.5 | H74: =+ROUND(D74*E74,2) -> 0 | I74: =+ROUND(D74*F74,2) -> 24398 | J74: 91492.5
A75: =A74+0.000001 -> 1.050102 | B75: TRANSPORTE VERTICAL CON GRUA - COSTO DE 02 RIGGER | C75: mes | D75: 11 | E75: 11369.28 | G75: 11369.28 | H75: =+ROUND(D75*E75,2) -> 125062.08 | I75: =+ROUND(D75*F75,2) -> 0 | J75: 125062.08
A76: =A75+0.000001 -> 1.050103 | B76: CIMENTACIÓN PARA TORRE GRÚA | C76: glb | D76: 1 | E76: 22692.38 | F76: 7563.44 | G76: 51055.28 | H76: =+ROUND(D76*E76,2) -> 22692.38 | I76: =+ROUND(D76*F76,2) -> 7563.44 | J76: 51055.28
A77: =A76+0.000001 -> 1.050104 | B77: PATAS DE EMPOTRAMIENTO PARA TORRE GRUA | C77: glb | D77: 1 | E77: 0 | F77: 7775 | G77: 29156.25 | H77: =+ROUND(D77*E77,2) -> 0 | I77: =+ROUND(D77*F77,2) -> 7775 | J77: 29156.25
A78: =A77+0.000001 -> 1.050105 | B78: CARGA DE TORRE GRUA EN ALMACEN | C78: glb | D78: 1 | E78: 0 | F78: 7250 | G78: 27187.5 | H78: =+ROUND(D78*E78,2) -> 0 | I78: =+ROUND(D78*F78,2) -> 7250 | J78: 27187.5
A79: =A78+0.000001 -> 1.050106 | B79: CARGA Y TRANSPORTE DE VIGAS Y MARCOS A OBRA | C79: glb | D79: 1 | E79: 0 | F79: 18200 | G79: 68250 | H79: =+ROUND(D79*E79,2) -> 0 | I79: =+ROUND(D79*F79,2) -> 18200 | J79: 68250
A80: =A79+0.000001 -> 1.050107 | B80: DESMONTAJE DE GRUA | C80: glb | D80: 1 | E80: 0 | F80: 14350 | G80: 53812.5 | H80: =+ROUND(D80*E80,2) -> 0 | I80: =+ROUND(D80*F80,2) -> 14350 | J80: 53812.5
A81: =A80+0.000001 -> 1.050108 | B81: ALQUILER MENSUAL DE GRUA | C81: mes | D81: 11 | E81: 0 | F81: 6425 | G81: 24093.75 | H81: =+ROUND(D81*E81,2) -> 0 | I81: =+ROUND(D81*F81,2) -> 70675 | J81: 265031.25
A82: =A73+0.0001 -> 1.0502 | B82: ALQUILER ELEVADOR VERTICAL | H82: =+ROUND(D82*E82,2) -> 0 | I82: =+ROUND(D82*F82,2) -> 0 | J82: 0
A83: =A82+0.000001 -> 1.050201 | B83: ALQUILER DE ELEVADOR DE PERSONAL DE CREMALLERA, CAP. MAX 2 TON | C83: mes | D83: 10 | E83: 8900 | G83: 8900 | H83: =+ROUND(D83*E83,2) -> 89000 | I83: =+ROUND(D83*F83,2) -> 0 | J83: 89000
A84: =A83+0.000001 -> 1.050202 | B84: REVISIÓN MENSUAL DE ELEVADOR DE PERSONAL DE CREMALLERA | C84: mes | D84: 10 | E84: 0 | G84: 0 | H84: =+ROUND(D84*E84,2) -> 0 | I84: =+ROUND(D84*F84,2) -> 0 | J84: 0
A85: =A84+0.000001 -> 1.050203 | B85: ALQUILER DE AUTOTRANSFORMADOR | C85: mes | D85: 10 | E85: 0 | G85: 0 | H85: =+ROUND(D85*E85,2) -> 0 | I85: =+ROUND(D85*F85,2) -> 0 | J85: 0
A86: =A85+0.000001 -> 1.050204 | B86: OPERADOR DE ELEVADOR X 200 HORAS | C86: mes | D86: 10 | E86: 5684.64 | G86: 5684.64 | H86: =+ROUND(D86*E86,2) -> 56846.4 | I86: =+ROUND(D86*F86,2) -> 0 | J86: 56846.4
A87: =A86+0.000001 -> 1.050205 | B87: MONTAJE DE ELEVADOR DE PERSONAL DE CREMALLERA | C87: glb | D87: 1 | E87: 34700 | G87: 34700 | H87: =+ROUND(D87*E87,2) -> 34700 | I87: =+ROUND(D87*F87,2) -> 0 | J87: 34700
A88: =A87+0.000001 -> 1.050206 | B88: DESMONTAJE DE ELEVADOR DE PERSONAL DE CREMALLERA | C88: glb | D88: 1 | E88: 15500 | G88: 15500 | H88: =+ROUND(D88*E88,2) -> 15500 | I88: =+ROUND(D88*F88,2) -> 0 | J88: 15500
A89: =A88+0.000001 -> 1.050207 | B89: RECRECIMIENTO DE MONTACARGA (CADA 2 PISOS) | C89: glb | D89: 1 | E89: 25500 | G89: 25500 | H89: =+ROUND(D89*E89,2) -> 25500 | I89: =+ROUND(D89*F89,2) -> 0 | J89: 25500
A90: =A82+0.0001 -> 1.0503 | B90: ACCESORIOS PARA ACARREO | H90: =+ROUND(D90*E90,2) -> 0 | I90: =+ROUND(D90*F90,2) -> 0 | J90: 0
A91: =A90+0.000001 -> 1.050301 | B91: PULPO DE CADENA, ESTROBO Y ESLINGA | C91: glb | D91: 1 | E91: 3967.6 | G91: 3967.6 | H91: =+ROUND(D91*E91,2) -> 3967.6 | I91: =+ROUND(D91*F91,2) -> 0 | J91: 3967.6
A92: =A91+0.000001 -> 1.050302 | B92: PLATAFORMAS PARA DESCARGAS DE PARIHUELAS (COMPRA 100%) | C92: und | D92: 2 | E92: 4940 | G92: 4940 | H92: =+ROUND(D92*E92,2) -> 9880 | I92: =+ROUND(D92*F92,2) -> 0 | J92: 9880
A93: =A92+0.000001 -> 1.050303 | B93: STOCKAS PARA TRANSPORTE DE PARIHUELAS (COMPRA 100%) | C93: und | D93: 2 | F93: 459 | G93: 1721.25 | H93: =+ROUND(D93*E93,2) -> 0 | I93: =+ROUND(D93*F93,2) -> 918 | J93: 3442.5
A94: =A93+0.000001 -> 1.050304 | B94: INSTALACION Y DESISTALACION DE PLATAFORMA DESCARGA DE PARIHUELAS | C94: und | D94: 24 | E94: 211.56 | G94: 211.56 | H94: =+ROUND(D94*E94,2) -> 5077.44 | I94: =+ROUND(D94*F94,2) -> 0 | J94: 5077.44
A95: =A94+0.000001 -> 1.050305 | B95: ALQUILER GRUA TELESCOPICA PARA ACARREO DE ACERO (1 DIA/SEM) ETAPA EXCAVACION - AJUSTE DE CAMPO | C95: día | D95: 0 | E95: 3450 | H95: =+ROUND(D95*E95,2) -> 0 | I95: =+ROUND(D95*F95,2) -> 0 | J95: 0
A96: =A90+0.0001 -> 1.0504 | B96: TRASLADO Y ACARREO HORIZONTAL | H96: =+ROUND(D96*E96,2) -> 0 | I96: =+ROUND(D96*F96,2) -> 0 | J96: 0
A97: =A96+0.000001 -> 1.050401 | B97: PEON DE MONTACARGA (PISO SUPERIOR) - ACARREO HORIZONTAL | C97: mes | D97: 10 | E97: 2016.56 | G97: 2016.56 | H97: =+ROUND(D97*E97,2) -> 20165.6 | I97: =+ROUND(D97*F97,2) -> 0 | J97: 20165.6
A98: =A97+0.000001 -> 1.050402 | B98: TRASLADO Y ACARREO HORIZONTAL (PEONES) ETAPA EXCAV+MP | C98: mes | D98: 3 | E98: 2016.56 | G98: 2016.56 | H98: =+ROUND(D98*E98,2) -> 6049.68 | I98: =+ROUND(D98*F98,2) -> 0 | J98: 6049.68
A99: =A98+0.000001 -> 1.050403 | B99: TRASLADO Y ACARREO HORIZONTAL (PEONES) CASCO (SOT+TORRE) | C99: mes | D99: 10 | E99: 4033.12 | G99: 4033.12 | H99: =+ROUND(D99*E99,2) -> 40331.2 | I99: =+ROUND(D99*F99,2) -> 0 | J99: 40331.2
A100: =A99+0.000001 -> 1.050404 | B100: TRASLADO Y ACARREO HORIZONTAL (PEONES) ETAPA ACABADOS (desde inicio acabados) | C100: mes | D100: 14.5 | E100: 6049.68 | G100: 6049.68 | H100: =+ROUND(D100*E100,2) -> 87720.36 | I100: =+ROUND(D100*F100,2) -> 0 | J100: 87720.36
A101: =A100+0.000001 -> 1.050405 | B101: ALQUILER DE EQUIPO BOBCAT Y MONTACARGA | C101: mes | D101: 10 | E101: 9126 | G101: 9126 | H101: =+ROUND(D101*E101,2) -> 91260 | I101: =+ROUND(D101*F101,2) -> 0 | J101: 91260
A102: =A72+0.01 -> 1.06 | B102: INSTALACIONES PROVISIONALES, AGUA Y ENERGIA | F102: 0 | K102: 541260.96
A103: =A102+0.0001 -> 1.0601 | B103: INSTALACIONES PROVISIONALES
A104: =A103+0.000001 -> 1.060101 | B104: INSTALACIÓN PROVISIONAL DE AGUA Y DESAGUE PARA LA CONSTRUCCIÓN | C104: glb | D104: 1 | E104: 14063.6 | G104: 14063.6 | H104: =+ROUND(D104*E104,2) -> 14063.6 | I104: =+ROUND(D104*F104,2) -> 0 | J104: 14063.6
A105: =A104+0.000001 -> 1.060102 | B105: INSTALACIÓN PROVISIONAL DE ENERGÍA PARA LA CONSTRUCCIÓN (VENTA DEL 60% A ALMACEN) | C105: glb | D105: 1 | E105: 57535.92 | G105: 57535.92 | H105: =+ROUND(D105*E105,2) -> 57535.92 | I105: =+ROUND(D105*F105,2) -> 0 | J105: 57535.92
...

Sheet SEG
A2: SEGURIDAD Y SALUD
A4: Presupuesto | B4: =#REF! -> #REF!
A5: Subpresupuesto | B5: =$A$2 -> SEGURIDAD Y SALUD
A6: Cliente | B6: =#REF! -> #REF!
A7: Lugar | B7: =#REF! -> #REF!
A8: Fecha | B8: =#REF! -> #REF!
A10: ITEM | B10: DESCRIPCION | C10: UND | D10: CANTIDAD | E10: P.U. (PEN) | F10: PARCIAL | G10: TOTAL
A11: 02 | B11: SEGURIDAD Y SALUD
A12: =A11+0.01 -> 2.01 | B12: ELABORACIÓN, IMPLEMENTACIÓN Y ADMINISTRACIÓN DEL PLAN DE SEGURIDAD Y SALUD EN EL TRABAJO | G12: =SUM(F13:F20) -> 768718.84
A13: =A12+0.0001 -> 2.0101 | B13: EQUIPOS DE PROTECCION INDIVIDUAL (STAFF Y OBREROS) | C13: glb | D13: 1 | E13: 153265.84 | F13: =+D13*E13 -> 153265.84
A14: =A13+0.0001 -> 2.0102 | B14: EQUIPOS DE PROTECCION COLECTIVA | C14: glb | D14: 1 | E14: 182518 | F14: =+D14*E14 -> 182518
A15: =A14+0.0001 -> 2.0103 | B15: MONITOREO DE AIRE Y RUIDO EN LA CONSTRUCCION (@ 6 MESES) | C15: und | D15: 4 | E15: 900 | F15: =+D15*E15 -> 3600
A16: =A15+0.0001 -> 2.0104 | B16: CONTROL DE POLVOS EN MOVIMIENTO DE TIERRAS (EXIGENCIA LEED) | C16: mes | D16: 0 | E16: 1505 | F16: =+D16*E16 -> 0
A17: =A16+0.0001 -> 2.0105 | B17: EXAMEN MÉDICO PRE-OCUPACIONAL | C17: und | D17: 190 | E17: 130 | F17: =+D17*E17 -> 24700
A18: =A17+0.0001 -> 2.0106 | B18: MALLA ANTICAIDAS (PERIMETRO EDIFICIO) | C18: glb | D18: 1 | E18: 92334 | F18: =+D18*E18 -> 92334
A19: =A18+0.0001 -> 2.0107 | B19: MALLA ANTICAIDAS (DUCTO DE ASCENSOR) | C19: glb | D19: 1 | E19: 13850.1 | F19: =+D19*E19 -> 13850.1
A20: =A19+0.0001 -> 2.0108 | B20: DESVIO DE TRANSITO (02 SEÑALERO x FRENTE) | C20: mes | D20: 22 | E20: 13565.95 | F20: =+D20*E20 -> 298450.9
A21: =A12+0.01 -> 2.02 | B21: PREVENCIONISTAS | G21: =SUM(F22:F24) -> 222950
A22: =A21+0.0001 -> 2.0201 | B22: ASISTENTES DE PDR (01) | C22: mes | D22: 17 | E22: 4455.36 | F22: =+D22*E22 -> 75741.12
A23: =A22+0.0001 -> 2.0202 | B23: AYUDANTE DE PDR N°1 (01) | C23: mes | D23: 22 | E23: 4033.12 | F23: =+D23*E23 -> 88728.64
A24: =A23+0.0001 -> 2.0203 | B24: AYUDANTE DE PDR N°2 (01) | C24: mes | D24: 14.5 | E24: 4033.12 | F24: =+D24*E24 -> 58480.24
A25: =A21+0.01 -> 2.03 | B25: SEGURIDAD POLICIAL | G25: =SUM(F26:F27) -> 8030
A26: =A25+0.0001 -> 2.0301 | B26: CAMARAS DE SEGURIDAD | C26: glb | D26: 1 | E26: 5500 | F26: =+D26*E26 -> 5500
A27: =A26+0.0001 -> 2.0302 | B27: SERVICIO MENSUAL MANTENIMIENTO | C27: mes | D27: 22 | E27: 115 | F27: =+D27*E27 -> 2530
D28: COSTO DIRECTO | G28: =SUM(G12:G27) -> 999698.84

Sheet GG
A2: GASTOS GENERALES
A4: Presupuesto | B4: =#REF! -> #REF!
A5: Subpresupuesto | B5: =A2 -> GASTOS GENERALES
A6: Cliente | B6: =#REF! -> #REF!
A7: Lugar | B7: =#REF! -> #REF!
A8: Fecha | B8: =#REF! -> #REF!
A11: ITEM | B11: DESCRIPCION | C11: UND | D11: CANTIDAD | E11: MESES | F11: PRECIO (PEN) | H11: PARCIAL | I11: TOTAL
A12: 12 | B12: GASTOS GENERALES
A13: =A12+0.01 -> 12.01 | B13: PERSONAL STAFF | I13: =SUM(H14:H28) -> 1962075
A14: =A13+0.0001 -> 12.0101 | B14: SUPERINTENDENCIA | C14: mes | D14: 1 | E14: 22 | F14: 6000 | H14: =+ROUND(D14*E14*F14,2) -> 132000
A15: =A14+0.0001 -> 12.0102 | B15: INGENIERO RESIDENTE | C15: mes | D15: 1 | E15: 23 | F15: 19500 | H15: =+ROUND(D15*E15*F15,2) -> 448500
A16: =A15+0.0001 -> 12.0103 | B16: INGENIERO DE OFICINA TECNICA | C16: mes | D16: 1 | E16: 23 | F16: 10500 | H16: =+ROUND(D16*E16*F16,2) -> 241500
A17: =A16+0.0001 -> 12.0104 | B17: INGENIERO DE CAMPO | C17: mes | D17: 1 | E17: 19 | F17: 10500 | H17: =+ROUND(D17*E17*F17,2) -> 199500
A18: =A17+0.0001 -> 12.0105 | B18: SUPERVISOR DE PROYECTOS | C18: mes | D18: 0 | E18: 22 | F18: 15000 | H18: =+ROUND(D18*E18*F18,2) -> 0
A19: =A18+0.0001 -> 12.0106 | B19: INGENIERO DE CALIDAD | C19: mes | D19: 1 | E19: 17 | F19: 8550 | H19: =+ROUND(D19*E19*F19,2) -> 145350
B20: INGENIERO DE CALIDAD JUNIOR | C20: mes | D20: 1 | E20: 6 | F20: 5250 | H20: =+ROUND(D20*E20*F20,2) -> 31500
A21: =A19+0.0001 -> 12.0107 | B21: INGENIERO ELECTROMECANICO | C21: mes | D21: 0.5 | E21: 17 | F21: 10500 | H21: =+ROUND(D21*E21*F21,2) -> 89250
A22: =A21+0.0001 -> 12.0108 | B22: ARQUITECTO DE ACABADOS | C22: mes | D22: 1 | E22: 17 | F22: 10500 | H22: =+ROUND(D22*E22*F22,2) -> 178500
B23: ARQUITECTO DE ACABADOS JUNIOR | C23: mes | D23: 1 | E23: 13.5 | F23: 5250 | H23: =+ROUND(D23*E23*F23,2) -> 70875
A24: =A22+0.0001 -> 12.0109 | B24: PREVENCIONISTA DE RIEGOS - SUBJEFE DE PDR | C24: mes | D24: 1 | E24: 22 | F24: 6750 | H24: =+ROUND(D24*E24*F24,2) -> 148500
B25: ASISTENTES DE PDR (01) | C25: mes | D25: 0 | E25: 17 | F25: 4455.36 | H25: =+ROUND(D25*E25*F25,2) -> 0
B26: AYUDANTE DE PDR N°1 (01) | C26: mes | D26: 0 | E26: 22 | F26: 4033.12 | H26: =+ROUND(D26*E26*F26,2) -> 0
A27: =A24+0.0001 -> 12.011 | B27: ADMINISTRADOR DE OBRA | C27: mes | D27: 1 | E27: 23 | F27: 6450 | H27: =+ROUND(D27*E27*F27,2) -> 148350
A28: =A27+0.0001 -> 12.0111 | B28: INGENIERO BIM | C28: mes | D28: 1 | E28: 19 | F28: 6750 | H28: =+ROUND(D28*E28*F28,2) -> 128250
A29: =A13+0.01 -> 12.02 | B29: PERSONAL TECNICO | I29: =SUM(H30:H40) -> 694399.6
A30: =A29+0.0001 -> 12.0201 | B30: ASISTENTE (CAMPO/CALIDAD/ARQ) | C30: mes | D30: 2 | E30: 12 | F30: 4200 | H30: =+ROUND(D30*E30*F30,2) -> 100800
A31: =A30+0.0001 -> 12.0202 | B31: MAESTRO DE OBRA | C31: mes | D31: 1 | E31: 15 | F31: 8010.5 | H31: =+ROUND(D31*E31*F31,2) -> 120157.5
A32: =A31+0.0001 -> 12.0203 | B32: CAPATAZ DE OBRA ESTRUCTURAS | C32: mes | D32: 1 | E32: 10 | F32: 7105.8 | H32: =+ROUND(D32*E32*F32,2) -> 71058
B33: CAPATAZ N°2 EST CASCO | C33: mes | D33: 0 | E33: 6.5 | F33: 7105.8 | H33: =+ROUND(D33*E33*F33,2) -> 0
A34: =A32+0.0001 -> 12.0204 | B34: CAPATAZ DE OBRA ARQUITECTURA N°1 | C34: mes | D34: 1 | E34: 14.5 | F34: 7105.8 | H34: =+ROUND(D34*E34*F34,2) -> 103034.1
B35: CAPATAZ DE OBRA ARQUITECTURA N°2 | C35: mes | D35: 0 | E35: 14.5 | F35: 7105.8 | H35: =+ROUND(D35*E35*F35,2) -> 0
B36: ASISTENTE DE INSTALACIONES | C36: mes | D36: 0 | E36: 17 | F36: 3100 | H36: =+ROUND(D36*E36*F36,2) -> 0
A37: =A34+0.0001 -> 12.0205 | B37: JEFE DE ALMACEN | C37: mes | D37: 1 | E37: 23 | F37: 5550 | H37: =+ROUND(D37*E37*F37,2) -> 127650
B38: ASISTENTE DE ALMACEN | C38: mes | D38: 1 | E38: 8 | F38: 4500 | H38: =+ROUND(D38*E38*F38,2) -> 36000
A39: =A37+0.0001 -> 12.0206 | B39: GUARDIAN DE OBRA Y PORTERIA | C39: mes | D39: 1 | E39: 23 | F39: 5900 | H39: =+ROUND(D39*E39*F39,2) -> 135700
B40: VIGILANTE POLICIAL DE CIVIL (TURNO NOCHE) - SERA COBRADO COMO ADICIONAL | C40: mes | D40: 0 | E40: 13.5 | F40: 6880 | H40: =+D40*E40*F40 -> 0
A41: =A29+0.01 -> 12.03 | B41: EQUIPO DE OFICINA DE LA OBRA | I41: =SUM(H42:H100) -> 71560.93
A42: =A41+0.0001 -> 12.0301 | B42: COMPUTADORAS | C42: mes | H42: =ROUND(SUM(G44:G67),2) -> 24185.22
A43: =A42+0.0001 -> 12.0302 | B43: DISGREGADO DE COMPUTADORAS
A44: 12.03.02.01 | B44: =+B15 -> INGENIERO RESIDENTE | C44: und | D44: 1 | E44: 23 | F44: 92.31 | G44: 2123.13
A45: 12.03.02.02 | B45: =+B16 -> INGENIERO DE OFICINA TECNICA | C45: und | D45: 1 | E45: 23 | F45: 92.31 | G45: 2123.13
A46: 12.03.02.03 | B46: =+B17 -> INGENIERO DE CAMPO | C46: und | D46: 1 | E46: 19 | F46: 92.31 | G46: 1753.89
A47: 12.03.02.05 | B47: =+B19 -> INGENIERO DE CALIDAD | C47: und | D47: 1 | E47: 17 | F47: 92.31 | G47: 1569.27
A48: 12.03.02.06 | B48: =B20 -> INGENIERO DE CALIDAD JUNIOR | C48: und | D48: 1 | E48: 6 | F48: 92.31 | G48: 553.86
A49: 12.03.02.07 | B49: =+B21 -> INGENIERO ELECTROMECANICO | C49: und | D49: 0.5 | E49: 17 | F49: 92.31 | G49: 784.635
A50: 12.03.02.09 | B50: =+B22 -> ARQUITECTO DE ACABADOS | C50: und | D50: 1 | E50: 17 | F50: 92.31 | G50: 1569.27
A51: 12.03.02.10 | B51: =+B23 -> ARQUITECTO DE ACABADOS JUNIOR | C51: und | D51: 1 | E51: 13.5 | F51: 92.31 | G51: 1246.185
A52: 12.03.02.12 | B52: =+B24 -> PREVENCIONISTA DE RIEGOS - SUBJEFE DE PDR | C52: und | D52: 1 | E52: 22 | F52: 92.31 | G52: 2030.82
A53: 12.03.02.13 | B53: =+B25 -> ASISTENTES DE PDR (01) | D53: 0 | E53: 17 | F53: 92.31 | G53: 0
A54: 12.03.02.14 | B54: =+B26 -> AYUDANTE DE PDR N°1 (01) | D54: 0 | E54: 22 | F54: 92.31 | G54: 0
A55: 12.03.02.15 | B55: =+B27 -> ADMINISTRADOR DE OBRA | C55: und | D55: 1 | E55: 23 | F55: 92.31 | G55: 2123.13
A56: 12.03.02.16 | B56: INGENIERO BIM | C56: und | D56: 1 | E56: 19 | F56: 92.31 | G56: 1753.89
A57: 12.03.02.17 | B57: =+B30 -> ASISTENTE (CAMPO/CALIDAD/ARQ) | C57: und | D57: 2 | E57: 12 | F57: 92.31 | G57: 2215.44
A58: 12.03.02.19 | B58: =+B31 -> MAESTRO DE OBRA | D58: 0 | E58: 15 | F58: 92.31 | G58: 0
A59: 12.03.02.20 | B59: =+B32 -> CAPATAZ DE OBRA ESTRUCTURAS | D59: 0 | E59: 10 | F59: 92.31 | G59: 0
A60: 12.03.02.21 | B60: =+B33 -> CAPATAZ N°2 EST CASCO | D60: 0 | E60: 6.5 | F60: 92.31 | G60: 0
A61: 12.03.02.22 | B61: =+B34 -> CAPATAZ DE OBRA ARQUITECTURA N°1 | D61: 0 | E61: 14.5 | F61: 92.31 | G61: 0
A62: 12.03.02.23 | B62: =+B35 -> CAPATAZ DE OBRA ARQUITECTURA N°2 | D62: 0 | E62: 14.5 | F62: 92.31 | G62: 0
A63: 12.03.02.24 | B63: =+B36 -> ASISTENTE DE INSTALACIONES | D63: 0 | E63: 17 | F63: 92.31 | G63: 0
A64: 12.03.02.26 | B64: =+B37 -> JEFE DE ALMACEN | C64: und | D64: 1 | E64: 23 | F64: 92.31 | G64: 2123.13
A65: 12.03.02.27 | B65: =+B38 -> ASISTENTE DE ALMACEN | C65: und | D65: 1 | E65: 8 | F65: 92.31 | G65: 738.48
A66: 12.03.02.28 | B66: TOPOGRAFO 1 (cuadrilla 1) | C66: und | D66: 1 | E66: 12 | F66: 92.31 | G66: 1107.72
A67: 12.03.02.29 | B67: TOPOGRAFO 2 (cuadrilla 2) | C67: und | D67: 1 | E67: 4 | F67: 92.31 | G67: 369.24
A68: 12.03.03 | B68: IMPRESORA A3 | C68: mes | D68: 1 | E68: 22 | F68: 135 | H68: =+D68*E68*F68 -> 2970
A69: 12.03.04 | B69: COMUNICACION (CELULARES) | C69: mes | H69: =ROUND(SUM(G71:G95),2) -> 17160
A70: 12.03.05 | B70: DISGREGADO DE CELULARES
A71: 12.03.05.01 | B71: =+B15 -> INGENIERO RESIDENTE | D71: 1 | E71: 23 | F71: 65 | G71: 1495
A72: 12.03.05.02 | B72: =+B16 -> INGENIERO DE OFICINA TECNICA | D72: 1 | E72: 23 | F72: 65 | G72: 1495
A73: 12.03.05.03 | B73: =+B17 -> INGENIERO DE CAMPO | D73: 1 | E73: 19 | F73: 65 | G73: 1235
A74: 12.03.05.05 | B74: =+B19 -> INGENIERO DE CALIDAD | D74: 1 | E74: 17 | F74: 65 | G74: 1105
A75: 12.03.05.06 | B75: =B20 -> INGENIERO DE CALIDAD JUNIOR | D75: 1 | E75: 6 | F75: 65 | G75: 390
A76: 12.03.05.07 | B76: =+B21 -> INGENIERO ELECTROMECANICO | D76: 0.5 | E76: 17 | F76: 65 | G76: 552.5
A77: 12.03.05.09 | B77: =+B22 -> ARQUITECTO DE ACABADOS | D77: 1 | E77: 17 | F77: 65 | G77: 1105
A78: 12.03.05.10 | B78: =+B23 -> ARQUITECTO DE ACABADOS JUNIOR | D78: 1 | E78: 13.5 | F78: 65 | G78: 877.5
A79: 12.03.05.12 | B79: =+B24 -> PREVENCIONISTA DE RIEGOS - SUBJEFE DE PDR | D79: 1 | E79: 22 | F79: 65 | G79: 1430
A80: 12.03.05.13 | B80: =+B25 -> ASISTENTES DE PDR (01) | D80: 0 | E80: 17 | F80: 65 | G80: 0
A81: 12.03.05.14 | B81: =+B26 -> AYUDANTE DE PDR N°1 (01) | D81: 0 | E81: 22 | F81: 65 | G81: 0
A82: 12.03.05.15 | B82: =+B27 -> ADMINISTRADOR DE OBRA | D82: 1 | E82: 23 | F82: 65 | G82: 1495
A83: 12.03.05.16 | B83: =+B29 -> PERSONAL TECNICO | D83: 0 | E83: 0 | F83: 65 | G83: 0
A84: 12.03.05.17 | B84: =+B30 -> ASISTENTE (CAMPO/CALIDAD/ARQ) | D84: 2 | E84: 12 | F84: 65 | G84: 1560
A85: 12.03.05.19 | B85: =+B31 -> MAESTRO DE OBRA | D85: 0 | E85: 15 | F85: 65 | G85: 0
A86: 12.03.05.20 | B86: =+B32 -> CAPATAZ DE OBRA ESTRUCTURAS | D86: 0 | E86: 10 | F86: 65 | G86: 0
A87: 12.03.05.21 | B87: =+B33 -> CAPATAZ N°2 EST CASCO | D87: 0 | E87: 6.5 | F87: 65 | G87: 0
A88: 12.03.05.22 | B88: =+B34 -> CAPATAZ DE OBRA ARQUITECTURA N°1 | D88: 0 | E88: 14.5 | F88: 65 | G88: 0
A89: 12.03.05.23 | B89: =+B35 -> CAPATAZ DE OBRA ARQUITECTURA N°2 | D89: 0 | E89: 14.5 | F89: 65 | G89: 0
A90: 12.03.05.24 | B90: =+B36 -> ASISTENTE DE INSTALACIONES | D90: 0 | E90: 17 | F90: 65 | G90: 0
A91: 12.03.05.25 | B91: =+B37 -> JEFE DE ALMACEN | D91: 1 | E91: 23 | F91: 65 | G91: 1495
A92: 12.03.05.26 | B92: =+B38 -> ASISTENTE DE ALMACEN | D92: 1 | E92: 8 | F92: 65 | G92: 520
A93: 12.03.05.27 | B93: ASISTENTES DE PDR (01)- ENTRA DESPUES DE LA CIM HASTA EL FINAL | D93: 1 | E93: 19 | F93: 65 | G93: 1235
A94: 12.03.05.28 | B94: AYUDANTE DE PDR N°1 (01) | D94: 1 | E94: 10 | F94: 65 | G94: 650
A95: 12.03.05.29 | B95: AYUDANTE DE PDR N°2 (01) | D95: 1 | E95: 8 | F95: 65 | G95: 520
A96: 12.03.06 | B96: COMUNICACION (RADIOS) | C96: und | D96: 17 | E96: 1 | F96: 515.63 | H96: =+ROUND(D96*E96*F96,2) -> 8765.71
A97: 12.03.07 | B97: COMUNICACION TELEFONO EXTERNO / INTERNET | C97: und | D97: 1 | E97: 22 | F97: 240 | H97: =+ROUND(D97*E97*F97,2) -> 5280
A98: 12.03.08 | B98: ESCRITORIOS Y SILLAS (CONTRATISTA) | C98: und | D98: 18 | E98: 1 | F98: 250 | H98: =+ROUND(D98*E98*F98,2) -> 4500
A99: 12.03.09 | B99: MESAS DE TRABAJO Y DE REUNION | C99: und | D99: 1 | E99: 2 | F99: 500 | H99: =+ROUND(D99*E99*F99,2) -> 1000
A100: 12.03.10 | B100: UTILES DE OFICINA Y ECONOMATO | C100: glb | D100: 1 | E100: 22 | F100: 350 | H100: =+ROUND(D100*E100*F100,2) -> 7700
A101: 12.04 | B101: VARIOS | I101: =SUM(H102:H118) -> 799910.97
A102: 12.04.01 | B102: INSUMOS PARA LIMPIEZA | C102: mes | D102: 1 | E102: 22 | F102: 250 | H102: =+ROUND(D102*E102*F102,2) -> 5500
A103: 12.04.02 | B103: PERSONAL DE LIMPIEZA (OFICINAS) | C103: mes | D103: 0.5 | E103: 22 | F103: 1950 | H103: =+ROUND(D103*E103*F103,2) -> 21450
A104: 12.04.03 | B104: FOTOCOPIADO | C104: mes | D104: 1 | E104: 22 | F104: 300 | H104: =+ROUND(D104*E104*F104,2) -> 6600
...

Sheet EST SOTANO
A2: ESTRUCTURAS SÓTANOS
A4: Presupuesto | B4: =OP!$B$4 -> #REF!
A5: Subpresupuesto | B5: =+$A$2 -> ESTRUCTURAS SÓTANOS
A6: Cliente | B6: =OP!$B$6 -> #REF!
A7: Lugar | B7: =OP!$B$7 -> #REF!
A8: Fecha | B8: =#REF! -> #REF!
L9: PARTIDAS ABIERTAS
A10: ITEM | B10: DESCRIPCION | C10: UND | D10: METRADO | E10: P.U. (PEN) | F10: P.U. (USD) | G10: P.U. TOTAL (PEN) | H10: PRECIO PARCIAL (PEN) | I10: PRECIO PARCIAL (USD) | J10: PRECIO TOTAL (PEN) | K10: TOTAL | L10: P.U. (PEN) | M10: PRECIO PARCIAL (PEN) | N10: P.U. (PEN) | O10: PRECIO PARCIAL (PEN) | P10: P.U. (USD) | Q10: PRECIO PARCIAL (USD)
A11: 03 | B11: =$A$2 -> ESTRUCTURAS SÓTANOS
A12: =A11+0.01 -> 3.01 | B12: OBRAS PRELIMINARES MOVIMIENTOS DE TIERRA | H12: =IFERROR(IF($D12=0,"",$D12*E12),"") | I12: =IFERROR(IF($D12=0,"",$D12*F12),"") | K12: 47280
A13: =A12+0.0001 -> 3.0101 | B13: MOVILIZACION Y DESMOVILIZACION DE EQUIPOS MOVIMIENTO TIERRAS | C13: glb | D13: 1 | E13: 6000 | G13: 6000 | H13: =+ROUND(D13*E13,2) -> 6000 | I13: =+ROUND(D13*F13,2) -> 0 | J13: 6000
A14: =A13+0.0001 -> 3.0102 | B14: EXTRACCION DE EQUIPOS MOVIMIENTO TIERRAS CON GRUAS | C14: glb | D14: 2 | E14: 6000 | G14: 6000 | H14: =+ROUND(D14*E14,2) -> 12000 | I14: =+ROUND(D14*F14,2) -> 0 | J14: 12000
A15: =A14+0.0001 -> 3.0103 | B15: INSTALACION Y DESISTALACION DE PLATAFORMA | C15: glb | D15: 1 | E15: 11000 | G15: 11000 | H15: =+ROUND(D15*E15,2) -> 11000 | I15: =+ROUND(D15*F15,2) -> 0 | J15: 11000
A16: =A15+0.0001 -> 3.0104 | B16: EXTRACCION DE EQUIPOS PERFORACION CON GRUAS | C16: glb | D16: 4 | F16: 720 | G16: 2700 | H16: =+ROUND(D16*E16,2) -> 0 | I16: =+ROUND(D16*F16,2) -> 2880 | J16: 10800
A17: =A16+0.0001 -> 3.0105 | B17: CONTROL DE POLVOS (AGUA EN CISTERNA) | C17: vje | D17: 22 | E17: 340 | G17: 340 | H17: =+ROUND(D17*E17,2) -> 7480 | I17: =+ROUND(D17*F17,2) -> 0 | J17: 7480
A18: =A12+0.01 -> 3.02 | B18: MOVIMIENTO DE TIERRAS | K18: 937375.07
A19: =A18+0.0001 -> 3.0201 | B19: EXCAVACIÓN Y ELIMINACIÓN MASIVA POR NIVEL
A20: =A19+0.000001 -> 3.020101 | B20: CORTE Y ELIMINACION DE +0.00 a -3.80 (SOTANO 01) | C20: m3 | D20: 5291.24 | E20: 23 | G20: 23 | H20: =+ROUND(D20*E20,2) -> 121698.52 | I20: =+ROUND(D20*F20,2) -> 0 | J20: 121698.52
A21: =A20+0.000001 -> 3.020102 | B21: CORTE Y ELIMINACION DE -3.88 a -6.68 (SOTANO 02) | C21: m3 | D21: 3823.35 | E21: 24 | G21: 24 | H21: =+ROUND(D21*E21,2) -> 91760.4 | I21: =+ROUND(D21*F21,2) -> 0 | J21: 91760.4
A22: =A21+0.000001 -> 3.020103 | B22: CORTE Y ELIMINACION DE -6.68 a -9.40 (SOTANO 03) | C22: m3 | D22: 3823.35 | E22: 25 | G22: 25 | H22: =+ROUND(D22*E22,2) -> 95583.75 | I22: =+ROUND(D22*F22,2) -> 0 | J22: 95583.75
A23: =A22+0.000001 -> 3.020104 | B23: CORTE Y ELIMINACION DE -9.40 a -12.20 (SOTANO 04) | C23: m3 | D23: 3823.35 | E23: 28 | G23: 28 | H23: =+ROUND(D23*E23,2) -> 107053.8 | I23: =+ROUND(D23*F23,2) -> 0 | J23: 107053.8
A24: =A23+0.000001 -> 3.020105 | B24: CORTE Y ELIMINACION DE -12.28 a -15,08 (SOTANO 05) | C24: m3 | D24: 3823.35 | E24: 28 | G24: 28 | H24: =+ROUND(D24*E24,2) -> 107053.8 | I24: =+ROUND(D24*F24,2) -> 0 | J24: 107053.8
A25: =A24+0.000001 -> 3.020106 | B25: CORTE Y ELIMINACION DE -15,08 a -18,28 (SOTANO 06) CON BALDE Y GRUA | C25: m3 | D25: 2847.93 | E25: 38 | G25: 38 | H25: =+ROUND(D25*E25,2) -> 108221.34 | I25: =+ROUND(D25*F25,2) -> 0 | J25: 108221.34
A26: =A19+0.0001 -> 3.0202 | B26: EXCAVACIÓN Y ELIMINACIÓN LOCALIZADA | G26: 0 | H26: =+ROUND(D26*E26,2) -> 0 | I26: =+ROUND(D26*F26,2) -> 0 | J26: 0
A27: =A26+0.000001 -> 3.020201 | B27: EXCAVACION Y ELIIMINACION DE ZAPATAS Y CIMIENTOS (N -20,87) CON BALDE Y GRUA | C27: m3 | D27: 568.11 | E27: 38 | G27: 38 | H27: =+ROUND(D27*E27,2) -> 21588.18 | I27: =+ROUND(D27*F27,2) -> 0 | J27: 21588.18
A28: =A27+0.000001 -> 3.020202 | B28: EXCAVACION Y ELIIMINACION DE CISTERNA Y CUARTO DE BOMBAS (N -20.80) CON BALDE Y GRUA | C28: m3 | D28: 1298.68 | E28: 38 | G28: 38 | H28: =+ROUND(D28*E28,2) -> 49349.84 | I28: =+ROUND(D28*F28,2) -> 0 | J28: 49349.84
A29: =A28+0.000001 -> 3.020203 | B29: EXCAVACION LOCALIZADA PARA VIGAS DE CIMENTACION | C29: m3 | D29: 2.6 | E29: 40.72 | G29: 40.72 | H29: =+ROUND(D29*E29,2) -> 105.87 | I29: =+ROUND(D29*F29,2) -> 0 | J29: 105.87
A30: =A29+0.000001 -> 3.020204 | B30: EXCAVACION LOCALIZADA PARA CIMIENTOS (BATEA DE CIMENTACION) | C30: m3 | D30: 3.49 | E30: 40.72 | G30: 40.72 | H30: =+ROUND(D30*E30,2) -> 142.11 | I30: =+ROUND(D30*F30,2) -> 0 | J30: 142.11
A31: =A30+0.000001 -> 3.020205 | B31: EXCAVACION LOCALIZADA PARA POZO SUMIDERO Y TRAMPA DE GRASA | C31: m3 | D31: 3.74 | E31: 40.72 | G31: 40.72 | H31: =+ROUND(D31*E31,2) -> 152.29 | I31: =+ROUND(D31*F31,2) -> 0 | J31: 152.29
A32: =A31+0.000001 -> 3.020206 | B32: EXCAVACION LOCALIZADA PARA FALSA ZAPATA | C32: m3 | D32: 87.16 | E32: 40.72 | G32: 40.72 | H32: =+ROUND(D32*E32,2) -> 3549.16 | I32: =+ROUND(D32*F32,2) -> 0 | J32: 3549.16
A33: =A31+0.000001 -> 3.020206 | B33: ACARREO Y ELIMINACION DE MATERIAL EXCEDENTE | C33: m3 | D33: 126.09 | E33: 38.52 | G33: 38.52 | H33: =+ROUND(D33*E33,2) -> 4856.99 | I33: =+ROUND(D33*F33,2) -> 0 | J33: 4856.99
A34: =A26+0.0001 -> 3.0203 | B34: ELIMINACIÓN DE CIMENTACIÓN EXISTENTE
A35: =A34+0.000001 -> 3.020301 | B35: DEMOLICIÓN DE CIMENTACIÓN DE VECINOS | C35: ml | D35: 0 | E35: 75 | G35: 75 | H35: =+ROUND(D35*E35,2) -> 0 | I35: =+ROUND(D35*F35,2) -> 0 | J35: 0
A36: =A35+0.000001 -> 3.020302 | B36: ELIMINACIÓN DE CIMENTACIÓN | C36: m3 | D36: 0 | E36: 35 | G36: 35 | H36: =+ROUND(D36*E36,2) -> 0 | I36: =+ROUND(D36*F36,2) -> 0 | J36: 0
A37: =A34+0.0001 -> 3.0204 | B37: RELLENO Y COMPACTACIÓN
A38: =A37+0.000001 -> 3.020401 | B38: RELLENO COMPACTADO CON MATERIAL PROPIO | C38: m3 | D38: 106.37 | E38: 54.02 | G38: 54.02 | H38: =+ROUND(D38*E38,2) -> 5746.11 | I38: =+ROUND(D38*F38,2) -> 0 | J38: 5746.11
A39: =A38+0.000001 -> 3.020402 | B39: RELLENO BAJO RAMPA CON MATERIAL PROPIO | C39: m3 | D39: 238.86 | E39: 54.02 | G39: 54.02 | H39: =+ROUND(D39*E39,2) -> 12903.22 | I39: =+ROUND(D39*F39,2) -> 0 | J39: 12903.22
A40: =A37+0.0001 -> 3.0205 | B40: NIVELACIÓN, APISONADO Y BASE DE AFIRMADO | G40: 0 | H40: =+ROUND(D40*E40,2) -> 0 | I40: =+ROUND(D40*F40,2) -> 0 | J40: 0
A41: =A40+0.000001 -> 3.020501 | B41: NIVELACION Y COMPACTACION DE SUBRASANTE | C41: m2 | D41: 1313.23 | E41: 6.6 | G41: 6.6 | H41: =+ROUND(D41*E41,2) -> 8667.32 | I41: =+ROUND(D41*F41,2) -> 0 | J41: 8667.32
A42: =A41+0.000001 -> 3.020502 | B42: BASE DE AFIRMADO COMPACTADO, E=20CM (conforme a EMS) | C42: m2 | D42: 1313.23 | E42: 40.95 | G42: 40.95 | H42: =+ROUND(D42*E42,2) -> 53776.77 | I42: =+ROUND(D42*F42,2) -> 0 | J42: 53776.77
A43: =A40+0.0001 -> 3.0206 | B43: OTROS | G43: 0 | H43: =+ROUND(D43*E43,2) -> 0 | I43: =+ROUND(D43*F43,2) -> 0 | J43: 0
A44: =A43+0.000001 -> 3.020601 | B44: ALQUILER DE EXCAVADORA MOVIMIENTO DE DADOS, RAMPA, ETC | C44: hm | D44: 500 | E44: 250 | G44: 250 | H44: =+ROUND(D44*E44,2) -> 125000 | I44: =+ROUND(D44*F44,2) -> 0 | J44: 125000
A45: =A44+0.000001 -> 3.020602 | B45: VIGIA P/MAQ EXCAVADORA DURANTE LA EXCAVACION | C45: mes | D45: 5 | E45: 4033.12 | G45: 4033.12 | H45: =+ROUND(D45*E45,2) -> 20165.6 | I45: =+ROUND(D45*F45,2) -> 0 | J45: 20165.6
A46: =A18+0.01 -> 3.03 | B46: CONCRETO SIMPLE | K46: 56656.43
A47: =A46+0.0001 -> 3.0301 | B47: SOLADOS
A48: =A47+0.000001 -> 3.030101 | B48: CONCRETO PREMEZCLADO, CEMENTO TIPO I, SOLADO f'c=100 kg/cm2 | C48: m2 | D48: 891.39 | E48: 29.14 | G48: 29.14 | H48: =+ROUND(D48*E48,2) -> 25975.1 | I48: =+ROUND(D48*F48,2) -> 0 | J48: 25975.1
A49: =A47+0.0001 -> 3.0302 | B49: FALSA ZAPATA
A50: =A49+0.000001 -> 3.030201 | B50: CONCRETO PREMEZCLADO, CEMENTO TIPO I, FALZA ZAPATAS 1:12 + 30%P.G. | C50: m3 | D50: 87.16 | E50: 298.75 | G50: 298.75 | H50: =+ROUND(D50*E50,2) -> 26039.05 | I50: =+ROUND(D50*F50,2) -> 0 | J50: 26039.05
A51: =A50+0.000001 -> 3.030202 | B51: ENCOFRADO DE FALSA ZAPATAS | C51: m2 | D51: 107.96 | E51: 43 | G51: 43 | H51: =+ROUND(D51*E51,2) -> 4642.28 | I51: =+ROUND(D51*F51,2) -> 0 | J51: 4642.28
A52: =A46+0.01 -> 3.04 | B52: CONCRETO ARMADO | K52: 5795976.1
A53: =A52+0.0001 -> 3.0401 | B53: CIMIENTOS ARMADOS MURO PANTALLA
A54: =A53+0.000001 -> 3.040101 | B54: CONCRETO PREMEZCLADO, CEMENTO TIPO I, CIMIENTOS REFORZADOS f'c=210 kg/cm2 | C54: m3 | D54: 0 | E54: 475.42 | G54: 475.42 | H54: =+ROUND(D54*E54,2) -> 0 | I54: =+ROUND(D54*F54,2) -> 0 | J54: 0
A55: =A54+0.000001 -> 3.040102 | B55: CONCRETO PREMEZCLADO, CEMENTO TIPO I, CIMIENTOS REFORZADOS f'c=280 kg/cm2 | C55: m3 | D55: 108.41 | E55: 521.98 | G55: 521.98 | H55: =+ROUND(D55*E55,2) -> 56587.85 | I55: =+ROUND(D55*F55,2) -> 0 | J55: 56587.85 | N55: 427.58 | O55: =+N55*D55 -> 46353.948
A56: =A55+0.000001 -> 3.040103 | B56: ENCOFRADO Y DESENCOFRADO PARA CIMIENTOS REFORZADOS | C56: m2 | D56: 112.88 | E56: 45 | G56: 45 | H56: =+ROUND(D56*E56,2) -> 5079.6 | I56: =+ROUND(D56*F56,2) -> 0 | J56: 5079.6
A57: =A56+0.000001 -> 3.040104 | B57: ACERO DE REFUERZO FY= 4200 kg/cm2, GRADO 60 (MURO PANTALLA) | C57: kg | D57: 8826.94 | E57: 1.15 | F57: 0.94 | G57: 4.68 | H57: =+ROUND(D57*E57,2) -> 10150.98 | I57: =+ROUND(D57*F57,2) -> 8297.32 | J57: 41265.93 | P57: 0.94 | Q57: =+P57*D57 -> 8297.3236
A58: =A57+0.000001 -> 3.040105 | B58: CURADO DE ELEMENTOS ESTRUCTURALES EXPUESTOS | C58: m2 | D58: 281.92 | E58: 1.5 | G58: 1.5 | H58: =+ROUND(D58*E58,2) -> 422.88 | I58: =+ROUND(D58*F58,2) -> 0 | J58: 422.88
A59: =A58+0.000001 -> 3.040106 | B59: PINTURA ASFALTICA EN CIMENTACIONES | C59: m2 | D59: 281.92 | E59: 20.27 | G59: 20.27 | H59: =+ROUND(D59*E59,2) -> 5714.52 | I59: =+ROUND(D59*F59,2) -> 0 | J59: 5714.52
A60: =A53+0.0001 -> 3.0402 | B60: MURO PANTALLA (ANCLADO)
A61: =A60+0.000001 -> 3.040201 | B61: CONCRETO PREMEZCLADO, CEMENTO TIPO I, MURO PANTALLA f'c=210 kg/cm2 (a 3 días) | C61: m3 | D61: 1079.64 | E61: 637.69 | G61: 637.69 | H61: =+ROUND(D61*E61,2) -> 688475.63 | I61: =+ROUND(D61*F61,2) -> 0 | J61: 688475.63 | N61: 572.6 | O61: =+N61*D61 -> 618201.86
A62: =A61+0.000001 -> 3.040202 | B62: CONCRETO PREMEZCLADO, CEMENTO TIPO I, MURO PANTALLA f'c=245 (columnas embebidas) | C62: m3 | D62: 31.07 | E62: 637.69 | G62: 637.69 | H62: =+ROUND(D62*E62,2) -> 19813.03 | I62: =+ROUND(D62*F62,2) -> 0 | J62: 19813.03 | N62: 572.6 | O62: =+N62*D62 -> 17790.682
A63: =A62+0.000001 -> 3.040203 | B63: CONCRETO PREMEZCLADO, CEMENTO TIPO I, MURO PANTALLA f'c=350 (columnas embebidas) | C63: m3 | D63: 126.29 | E63: 637.69 | G63: 637.69 | H63: =+ROUND(D63*E63,2) -> 80533.87 | I63: =+ROUND(D63*F63,2) -> 0 | J63: 80533.87 | N63: 572.6 | O63: =+N63*D63 -> 72313.654
A64: =A63+0.000001 -> 3.040204 | B64: CONCRETO PREMEZCLADO, CEMENTO TIPO I, MURO PANTALLA f'c=420 (columnas embebidas) | C64: m3 | D64: 12.42 | E64: 637.69 | G64: 637.69 | H64: =+ROUND(D64*E64,2) -> 7920.11 | I64: =+ROUND(D64*F64,2) -> 0 | J64: 7920.11 | N64: 572.6 | O64: =+N64*D64 -> 7111.692
A65: =A61+0.000001 -> 3.040202 | B65: CONCRETO PREMEZCLADO, CEMENTO TIPO I, MURO PANTALLA f'c=280 kg/cm2 , w/c = 0,45 (Cisterna) | C65: m3 | D65: 17.05 | E65: 637.62 | G65: 637.62 | H65: =+ROUND(D65*E65,2) -> 10871.42 | I65: =+ROUND(D65*F65,2) -> 0 | J65: 10871.42 | N65: 572.53 | O65: =+N65*D65 -> 9761.6365
A66: =A61+0.000001 -> 3.040202 | B66: ENCOFRADO Y DESENCOFRADO PARA MURO PANTALLA | C66: m2 | D66: 3151.2 | E66: 58 | G66: 58 | H66: =+ROUND(D66*E66,2) -> 182769.6 | I66: =+ROUND(D66*F66,2) -> 0 | J66: 182769.6
A67: =A66+0.000001 -> 3.040203 | B67: ENCOFRADO Y DESENCOFRADO LATERALES | C67: m2 | D67: 268.4 | E67: 50.5 | G67: 50.5 | H67: =+ROUND(D67*E67,2) -> 13554.2 | I67: =+ROUND(D67*F67,2) -> 0 | J67: 13554.2
A68: =A67+0.000001 -> 3.040204 | B68: ACERO DE REFUERZO FY= 4200 kg/cm2, GRADO 60 (MURO PANTALLA) | C68: kg | D68: 156740.89 | E68: 1.15 | F68: 0.94 | G68: 4.68 | H68: =+ROUND(D68*E68,2) -> 180252.02 | I68: =+ROUND(D68*F68,2) -> 147336.44 | J68: 732763.67 | P68: 0.94 | Q68: =+P68*D68 -> 147336.44
A69: =A68+0.000001 -> 3.040205 | B69: RECARGO POR CONSUMO MINIMO DE BOMBA | C69: m3 | D69: 246 | E69: 37.5 | G69: 37.5 | H69: =+ROUND(D69*E69,2) -> 9225 | I69: =+ROUND(D69*F69,2) -> 0 | J69: 9225
A70: =A69+0.000001 -> 3.040206 | B70: CONCRETO PREMEZCLADO, CEMENTO TIPO I, EN CACHIMBAS f'c=210 kg/cm2 A 3 DIAS | C70: m3 | D70: 71.04 | E70: 507.56 | G70: 507.56 | H70: =+ROUND(D70*E70,2) -> 36057.06 | I70: =+ROUND(D70*F70,2) -> 0 | J70: 36057.06 | N70: 429.46 | O70: =+N70*D70 -> 30508.838
A71: =A70+0.000001 -> 3.040207 | B71: ENCOFRADO Y DESENCOFRADO DE CACHIMBAS | C71: m2 | D71: 284.16 | E71: 50 | G71: 50 | H71: =+ROUND(D71*E71,2) -> 14208 | I71: =+ROUND(D71*F71,2) -> 0 | J71: 14208
A72: =A71+0.000001 -> 3.040208 | B72: PICADO DE CACHIMBAS DE MUROS PANTALLAS | C72: m3 | D72: 71.04 | E72: 107.56 | G72: 107.56 | H72: =+ROUND(D72*E72,2) -> 7641.06 | I72: =+ROUND(D72*F72,2) -> 0 | J72: 7641.06
A73: =A72+0.000001 -> 3.040209 | B73: PICADO DE PESTAÑAS DE ORIFICIO DE ANCLAJE | C73: und | D73: 114 | E73: 34.76 | G73: 34.76 | H73: =+ROUND(D73*E73,2) -> 3962.64 | I73: =+ROUND(D73*F73,2) -> 0 | J73: 3962.64
A74: =A73+0.000001 -> 3.04021 | B74: TECNOPOR EN ENCUENTRO DE LOSAS CON MURO PANTALLA | C74: ml | D74: 850.85 | E74: 10.88 | G74: 10.88 | H74: =+ROUND(D74*E74,2) -> 9257.25 | I74: =+ROUND(D74*F74,2) -> 0 | J74: 9257.25
A75: =A74+0.000001 -> 3.040211 | B75: RETIRO DE TECNOPOR Y ESCARIFICADO EN ENCUENTRO DE LOSAS CON MURO PANTALLA | C75: ml | D75: 850.85 | E75: 7.76 | G75: 7.76 | H75: =+ROUND(D75*E75,2) -> 6602.6 | I75: =+ROUND(D75*F75,2) -> 0 | J75: 6602.6
A76: =A75+0.000001 -> 3.040212 | B76: EPOXICO DE UNION Y ESCARIFICADO ENTRE LOSAS DE TECHO DE SOTANOS Y MURO PANTALLA | C76: ml | D76: 850.85 | E76: 45.27 | G76: 45.27 | H76: =+ROUND(D76*E76,2) -> 38517.98 | I76: =+ROUND(D76*F76,2) -> 0 | J76: 38517.98
A77: =A76+0.000001 -> 3.040213 | B77: PERFILADO DE BANQUETAS Y TALUDES | C77: m2 | D77: 3151.2 | E77: 7.5 | G77: 7.5 | H77: =+ROUND(D77*E77,2) -> 23634 | I77: =+ROUND(D77*F77,2) -> 0 | J77: 23634
A78: =A77+0.000001 -> 3.040214 | B78: PAÑETEO DE MUROS PANTALLA | C78: m2 | D78: 3151.2 | E78: 16.8 | G78: 16.8 | H78: =+ROUND(D78*E78,2) -> 52940.16 | I78: =+ROUND(D78*F78,2) -> 0 | J78: 52940.16
A79: =A78+0.000001 -> 3.040215 | B79: PLASTICO CONTRA TERRENO | C79: m2 | D79: 3151.2 | E79: 2.55 | G79: 2.55 | H79: =+ROUND(D79*E79,2) -> 8035.56 | I79: =+ROUND(D79*F79,2) -> 0 | J79: 8035.56
A80: =A79+0.000001 -> 3.040216 | B80: ANCLAJE 1/2", ENCUENTRO DE LOSAS CON MUROS | C80: und | D80: 2128 | E80: 34.56 | F80: 0.78 | G80: 37.49 | H80: =+ROUND(D80*E80,2) -> 73543.68 | I80: =+ROUND(D80*F80,2) -> 1659.84 | J80: 79768.08
A81: =A80+0.000001 -> 3.040217 | B81: RESANE DE ORIFICIO DE ANCLAJE | C81: und | D81: 114 | E81: 51.4 | G81: 51.4 | H81: =+ROUND(D81*E81,2) -> 5859.6 | I81: =+ROUND(D81*F81,2) -> 0 | J81: 5859.6
A82: =A81+0.000001 -> 3.040218 | B82: RESANE DE CACHIMBAS | C82: ml | D82: 850.85 | E82: 24.98 | G82: 24.98 | H82: =+ROUND(D82*E82,2) -> 21254.23 | I82: =+ROUND(D82*F82,2) -> 0 | J82: 21254.23
A83: =A82+0.000001 -> 3.040219 | B83: CURADO DE ELEMENTOS ESTRUCTURALES EXPUESTOS | C83: m2 | D83: 3151.2 | E83: 1.5 | G83: 1.5 | H83: =+ROUND(D83*E83,2) -> 4726.8 | I83: =+ROUND(D83*F83,2) -> 0 | J83: 4726.8
A84: =A60+0.0001 -> 3.0403 | B84: MURO PERIMETRAL (SIN ANCLAJES)
A85: =A84+0.000001 -> 3.040301 | B85: CONCRETO PREMEZCLADO, CEMENTO TIPO I, MURO PERIMETRAL f'c=210 kg/cm2 | C85: m3 | D85: 0 | E85: 453.94 | G85: 453.94 | H85: =+ROUND(D85*E85,2) -> 0 | I85: =+ROUND(D85*F85,2) -> 0 | J85: 0 | O85: =+N85*D85 -> 0
A86: =A85+0.000001 -> 3.040302 | B86: CONCRETO PREMEZCLADO, CEMENTO TIPO I, MURO PERIMETRAL f'c=280 kg/cm2 | C86: m3 | D86: 0 | E86: 485.86 | G86: 485.86 | H86: =+ROUND(D86*E86,2) -> 0 | I86: =+ROUND(D86*F86,2) -> 0 | J86: 0 | O86: =+N86*D86 -> 0
A87: =A86+0.000001 -> 3.040303 | B87: ENCOFRADO Y DESENCOFRADO DE MUROS Y PLACAS | C87: m2 | D87: 0 | E87: 43.7 | G87: 43.7 | H87: =+ROUND(D87*E87,2) -> 0 | I87: =+ROUND(D87*F87,2) -> 0 | J87: 0
A88: =A87+0.000001 -> 3.040304 | B88: ENCOFRADO Y DESENCOFRADO DE MUROS Y PLACAS DOBLE ALTURA | C88: m2 | D88: 0 | E88: 48.7 | G88: 48.7 | H88: =+ROUND(D88*E88,2) -> 0 | I88: =+ROUND(D88*F88,2) -> 0 | J88: 0
A89: =A88+0.000001 -> 3.040305 | B89: ACERO DE REFUERZO FY= 4200 kg/cm2, GRADO 60 | C89: kg | D89: 0 | E89: 1.15 | F89: 0.94 | G89: 4.68 | H89: =+ROUND(D89*E89,2) -> 0 | I89: =+ROUND(D89*F89,2) -> 0 | J89: 0 | P89: 0.94 | Q89: =+P89*D89 -> 0
A90: =A89+0.000001 -> 3.040306 | B90: CURADO DE ELEMENTOS ESTRUCTURALES EXPUESTOS | C90: m2 | D90: 0 | E90: 1.5 | G90: 1.5 | H90: =+ROUND(D90*E90,2) -> 0 | I90: =+ROUND(D90*F90,2) -> 0 | J90: 0
A91: =A84+0.0001 -> 3.0404 | B91: ANCLAJES DE MURO PANTALLA (FLESAN)
A92: =A91+0.000001 -> 3.040401 | B92: MOVILIZACIÓN Y DESMOVILIZACIÓN DE ANCLAJES | C92: vje | D92: 4 | E92: 0 | F92: 1200 | G92: 4500 | H92: =+ROUND(D92*E92,2) -> 0 | I92: =+ROUND(D92*F92,2) -> 4800 | J92: 18000
A93: =A92+0.000001 -> 3.040402 | B93: PERFORACIÓN, SUMINISTRO, INSTALACIÓN, INYECCIÓN DE LECHADA DE ANCLAJES POSTENSADOS TEMPORALES | C93: und | D93: 114 | E93: 0 | F93: 1034.9 | G93: 3880.88 | H93: =+ROUND(D93*E93,2) -> 0 | I93: =+ROUND(D93*F93,2) -> 117978.6 | J93: 442419.75
A94: =A93+0.000001 -> 3.040403 | B94: BOLSAS DE CEMENTO PARA TENSADO DE ANCLAJES (inc bolsa de cemento) | C94: bls | D94: 0 | E94: 22.54 | G94: 22.54 | H94: =+ROUND(D94*E94,2) -> 0 | I94: =+ROUND(D94*F94,2) -> 0 | J94: 0
A95: =A91+0.0001 -> 3.0405 | B95: ZAPATAS Y CIMIENTOS ARMADO
A96: =A95+0.000001 -> 3.040501 | B96: CONCRETO PREMEZCLADO, CEMENTO TIPO I, ZAPATAS f'c=280 kg/cm2 | C96: m3 | D96: 261.2 | E96: 401.81 | G96: 401.81 | H96: =+ROUND(D96*E96,2) -> 104952.77 | I96: =+ROUND(D96*F96,2) -> 0 | J96: 104952.77 | N96: 374.14 | O96: =+N96*D96 -> 97725.368
A97: =A96+0.000001 -> 3.040502 | B97: ENCOFRADO Y DESENCOFRADO PARA ZAPATAS | C97: m2 | D97: 224.55 | E97: 47 | G97: 47 | H97: =+ROUND(D97*E97,2) -> 10553.85 | I97: =+ROUND(D97*F97,2) -> 0 | J97: 10553.85
A98: =A97+0.000001 -> 3.040503 | B98: ACERO DE REFUERZO FY= 4200 kg/cm2, GRADO 60 | C98: kg | D98: 22706.09 | E98: 1.15 | F98: 0.94 | G98: 4.68 | H98: =+ROUND(D98*E98,2) -> 26112 | I98: =+ROUND(D98*F98,2) -> 21343.72 | J98: 106150.95 | P98: 0.94 | Q98: =+P98*D98 -> 21343.725
A99: =A98+0.000001 -> 3.040504 | B99: CURADO DE ELEMENTOS ESTRUCTURALES EXPUESTOS | C99: m2 | D99: 571.11 | E99: 1.5 | G99: 1.5 | H99: =+ROUND(D99*E99,2) -> 856.67 | I99: =+ROUND(D99*F99,2) -> 0 | J99: 856.67
A100: =A99+0.000001 -> 3.040505 | B100: PINTURA ASFALTICA EN CIMENTACIONES | C100: m2 | D100: 571.11 | E100: 20.27 | G100: 20.27 | H100: =+ROUND(D100*E100,2) -> 11576.4 | I100: =+ROUND(D100*F100,2) -> 0 | J100: 11576.4
A101: =A95+0.0001 -> 3.0406 | B101: VIGAS DE CIMENTACION
A102: =A101+0.000001 -> 3.040601 | B102: CONCRETO PREMEZCLADO, CEMENTO TIPO I, VIGAS DE CIMENTACION f'c=280 kg/cm2 | C102: m3 | D102: 2.84 | E102: 421.2 | G102: 421.2 | H102: =+ROUND(D102*E102,2) -> 1196.21 | I102: =+ROUND(D102*F102,2) -> 0 | J102: 1196.21 | N102: 372.3 | O102: =+N102*D102 -> 1057.332
...

Sheet EST TORRE
A2: ESTRUCTURAS TORRE
A4: Presupuesto | B4: =#REF! -> #REF!
A5: Subpresupuesto | B5: =+$A$2 -> ESTRUCTURAS TORRE
A6: Cliente | B6: =#REF! -> #REF!
A7: Lugar | B7: =#REF! -> #REF!
A8: Fecha | B8: =#REF! -> #REF!
L9: PARTIDAS ABIERTAS
A10: ITEM | B10: DESCRIPCION | C10: UND | D10: METRADO | E10: P.U. (PEN) | F10: P.U. (USD) | G10: P.U. TOTAL (PEN) | H10: PRECIO PARCIAL (PEN) | I10: PRECIO PARCIAL (USD) | J10: PRECIO TOTAL (PEN) | K10: TOTAL | L10: P.U. (PEN) | M10: PRECIO PARCIAL (PEN) | N10: P.U. (PEN) | O10: PRECIO PARCIAL (PEN) | P10: P.U. (USD) | Q10: PRECIO PARCIAL (USD)
A11: 04 | B11: =$A$2 -> ESTRUCTURAS TORRE
A12: =A11+0.01 -> 4.01 | B12: CONCRETO ARMADO | K12: 8736275.2
A13: =A12+0.0001 -> 4.0101 | B13: PLACAS | H13: =IFERROR(IF($D13=0,"",$D13*E13),"") | I13: =IFERROR(IF($D13=0,"",$D13*F13),"")
A14: =A13+0.000001 -> 4.010101 | B14: CONCRETO PREMEZCLADO, CEMENTO TIPO I, PLACAS f'c=210 kg/cm2 | C14: m3 | D14: 0 | E14: 385.27 | G14: 385.27 | H14: =+ROUND(D14*E14,2) -> 0 | I14: =+ROUND(D14*F14,2) -> 0 | J14: 0
A15: =A13+0.000001 -> 4.010101 | B15: CONCRETO PREMEZCLADO, CEMENTO TIPO I, PLACAS f'c=245 kg/cm2 | C15: m3 | D15: 288.37 | E15: 397.9 | G15: 397.9 | H15: =+ROUND(D15*E15,2) -> 114742.42 | I15: =+ROUND(D15*F15,2) -> 0 | J15: 114742.42 | N15: 355.79 | O15: =+N15*D15 -> 102599.16
A16: =A14+0.000001 -> 4.010102 | B16: CONCRETO PREMEZCLADO, CEMENTO TIPO I, PLACAS f'c=280 kg/cm2 | C16: m3 | D16: 561.5 | E16: 414.41 | G16: 414.41 | H16: =+ROUND(D16*E16,2) -> 232691.22 | I16: =+ROUND(D16*F16,2) -> 0 | J16: 232691.22 | N16: 372.3 | O16: =+N16*D16 -> 209046.45
A17: =A15+0.000001 -> 4.010102 | B17: CONCRETO PREMEZCLADO, CEMENTO TIPO I, PLACAS f'c=350 kg/cm2 | C17: m3 | D17: 128.38 | E17: 453.3 | G17: 453.3 | H17: =+ROUND(D17*E17,2) -> 58194.65 | I17: =+ROUND(D17*F17,2) -> 0 | J17: 58194.65 | N17: 411.19 | O17: =+N17*D17 -> 52788.572
A18: =A16+0.000001 -> 4.010103 | B18: CONCRETO PREMEZCLADO, CEMENTO TIPO I, PLACAS f'c=420 kg/cm2 | C18: m3 | D18: 0 | E18: 469.55 | G18: 469.55 | H18: =+ROUND(D18*E18,2) -> 0 | I18: =+ROUND(D18*F18,2) -> 0 | J18: 0 | O18: =+N18*D18 -> 0
A19: =A16+0.000001 -> 4.010103 | B19: ENCOFRADO Y DESENCOFRADO DE MUROS Y PLACAS | C19: m2 | D19: 5184.73 | E19: 43.7 | G19: 43.7 | H19: =+ROUND(D19*E19,2) -> 226572.7 | I19: =+ROUND(D19*F19,2) -> 0 | J19: 226572.7
A20: =A19+0.000001 -> 4.010104 | B20: ENCOFRADO Y DESENCOFRADO DE MUROS Y PLACAS DOBLE ALTURA | C20: m2 | D20: 313.4 | E20: 48.7 | G20: 48.7 | H20: =+ROUND(D20*E20,2) -> 15262.58 | I20: =+ROUND(D20*F20,2) -> 0 | J20: 15262.58
A21: =A19+0.000001 -> 4.010104 | B21: ACERO DE REFUERZO FY= 4200 kg/cm2, GRADO 60 | C21: kg | D21: 109660.91 | E21: 1.15 | F21: 0.94 | G21: 4.68 | H21: =+ROUND(D21*E21,2) -> 126110.05 | I21: =+ROUND(D21*F21,2) -> 103081.26 | J21: 512664.78 | P21: 0.94 | Q21: =+P21*D21 -> 103081.26
A22: =A21+0.000001 -> 4.010105 | B22: CURADO DE ELEMENTOS ESTRUCTURALES EXPUESTOS | C22: m2 | D22: 5498.13 | E22: 1.5 | G22: 1.5 | H22: =+ROUND(D22*E22,2) -> 8247.2 | I22: =+ROUND(D22*F22,2) -> 0 | J22: 8247.2
A23: =A13+0.0001 -> 4.0102 | B23: MUROS P/ JARDINERAS - CORTES TECHO SOTANO 01 | D23: 0
A24: =A23+0.000001 -> 4.010201 | B24: CONCRETO PREMEZCLADO, CEMENTO TIPO I, PISCINA f'c=280 kg/cm2 (W/C=0.50).Por procedimiento constructivo | C24: m3 | D24: 18.69 | E24: 481.45 | G24: 481.45 | H24: =+ROUND(D24*E24,2) -> 8998.3 | I24: =+ROUND(D24*F24,2) -> 0 | J24: 8998.3 | N24: 432.55 | O24: =+N24*D24 -> 8084.3595
A25: =A24+0.000001 -> 4.010202 | B25: ENCOFRADO Y DESENCOFRADO DE MUROS Y PLACAS | C25: m2 | D25: 266.96 | E25: 43.7 | G25: 43.7 | H25: =+ROUND(D25*E25,2) -> 11666.15 | I25: =+ROUND(D25*F25,2) -> 0 | J25: 11666.15
A26: =A25+0.000001 -> 4.010203 | B26: ACERO DE REFUERZO FY= 4200 kg/cm2, GRADO 60 | C26: kg | D26: 2093.41 | E26: 1.15 | F26: 0.94 | G26: 4.68 | H26: =+ROUND(D26*E26,2) -> 2407.42 | I26: =+ROUND(D26*F26,2) -> 1967.81 | J26: 9786.71 | P26: 0.94 | Q26: =+P26*D26 -> 1967.8054
A27: =A26+0.000001 -> 4.010204 | B27: CURADO DE ELEMENTOS ESTRUCTURALES EXPUESTOS | C27: m2 | D27: 266.96 | E27: 1.5 | G27: 1.5 | H27: =+ROUND(D27*E27,2) -> 400.44 | I27: =+ROUND(D27*F27,2) -> 0 | J27: 400.44
A28: =A23+0.0001 -> 4.0103 | B28: COLUMNAS | D28: 0
A29: =A28+0.000001 -> 4.010301 | B29: CONCRETO PREMEZCLADO, CEMENTO TIPO I, COLUMNAS f'c=210 kg/cm2 | C29: m3 | D29: 0 | E29: 387.1 | G29: 387.1 | H29: =+ROUND(D29*E29,2) -> 0 | I29: =+ROUND(D29*F29,2) -> 0 | J29: 0 | O29: =+N29*D29 -> 0
A30: =A28+0.000001 -> 4.010301 | B30: CONCRETO PREMEZCLADO, CEMENTO TIPO I, COLUMNAS f'c=245 kg/cm2 | C30: m3 | D30: 335.96 | E30: 399.73 | G30: 399.73 | H30: =+ROUND(D30*E30,2) -> 134293.29 | I30: =+ROUND(D30*F30,2) -> 0 | J30: 134293.29 | N30: 355.79 | O30: =+N30*D30 -> 119531.21
A31: =A29+0.000001 -> 4.010302 | B31: CONCRETO PREMEZCLADO, CEMENTO TIPO I, COLUMNAS f'c=280 kg/cm2 | C31: m3 | D31: 257.65 | E31: 416.24 | G31: 416.24 | H31: =+ROUND(D31*E31,2) -> 107244.24 | I31: =+ROUND(D31*F31,2) -> 0 | J31: 107244.24 | N31: 372.3 | O31: =+N31*D31 -> 95923.095
A32: =A31+0.000001 -> 4.010303 | B32: CONCRETO PREMEZCLADO, CEMENTO TIPO I, COLUMNAS f'c=350 kg/cm2 | C32: m3 | D32: 173.33 | E32: 455.13 | G32: 455.13 | H32: =+ROUND(D32*E32,2) -> 78887.68 | I32: =+ROUND(D32*F32,2) -> 0 | J32: 78887.68 | N32: 411.19 | O32: =+N32*D32 -> 71271.563
A33: =A32+0.000001 -> 4.010304 | B33: CONCRETO PREMEZCLADO, CEMENTO TIPO I, COLUMNAS f'c=420 kg/cm2 | C33: m3 | D33: 132.64 | E33: 471.38 | G33: 471.38 | H33: =+ROUND(D33*E33,2) -> 62523.84 | I33: =+ROUND(D33*F33,2) -> 0 | J33: 62523.84 | N33: 427.44 | O33: =+N33*D33 -> 56695.642
A34: =A33+0.000001 -> 4.010305 | B34: ENCOFRADO Y DESENCOFRADO DE COLUMNAS | C34: m2 | D34: 5545.95 | E34: 44.6 | G34: 44.6 | H34: =+ROUND(D34*E34,2) -> 247349.37 | I34: =+ROUND(D34*F34,2) -> 0 | J34: 247349.37
A35: =A34+0.000001 -> 4.010306 | B35: ENCOFRADO Y DESENCOFRADO DE COLUMNAS DOBLE ALTURA | C35: m2 | D35: 379.72 | E35: 49.6 | G35: 49.6 | H35: =+ROUND(D35*E35,2) -> 18834.11 | I35: =+ROUND(D35*F35,2) -> 0 | J35: 18834.11
A36: =A35+0.000001 -> 4.010307 | B36: ACERO DE REFUERZO FY= 4200 kg/cm2, GRADO 60 | C36: kg | D36: 261703.74 | E36: 1.15 | F36: 0.94 | G36: 4.68 | H36: =+ROUND(D36*E36,2) -> 300959.3 | I36: =+ROUND(D36*F36,2) -> 246001.52 | J36: 1223465 | P36: 0.94 | Q36: =+P36*D36 -> 246001.52
A37: =A36+0.000001 -> 4.010308 | B37: CURADO DE ELEMENTOS ESTRUCTURALES EXPUESTOS | C37: m2 | D37: 5925.67 | E37: 1.5 | G37: 1.5 | H37: =+ROUND(D37*E37,2) -> 8888.51 | I37: =+ROUND(D37*F37,2) -> 0 | J37: 8888.51
A38: =A28+0.0001 -> 4.0104 | B38: VIGAS | D38: 0
A39: =A38+0.000001 -> 4.010401 | B39: CONCRETO PREMEZCLADO, CEMENTO TIPO I, VIGAS TORRE f'c=245 kg/cm2 | C39: m3 | D39: 1665.61 | E39: 392.8 | G39: 392.8 | H39: =+ROUND(D39*E39,2) -> 654251.61 | I39: =+ROUND(D39*F39,2) -> 0 | J39: 654251.61 | N39: 352.38 | O39: =+N39*D39 -> 586927.65
A40: =A39+0.000001 -> 4.010402 | B40: CONCRETO PREMEZCLADO, CEMENTO TIPO I, VIGAS TORRE f'c=350 kg/cm2 (NUCLEOS) | C40: m3 | D40: 13.45 | E40: 451.61 | G40: 451.61 | H40: =+ROUND(D40*E40,2) -> 6074.15 | I40: =+ROUND(D40*F40,2) -> 0 | J40: 6074.15 | N40: 411.19 | O40: =+N40*D40 -> 5530.5055
A41: =A40+0.000001 -> 4.010403 | B41: CONCRETO PREMEZCLADO, CEMENTO TIPO I, VIGAS TORRE f'c=420 kg/cm2 (NUCLEOS) | C41: m3 | D41: 25.26 | E41: 467.86 | G41: 467.86 | H41: =+ROUND(D41*E41,2) -> 11818.14 | I41: =+ROUND(D41*F41,2) -> 0 | J41: 11818.14 | N41: 427.44 | O41: =+N41*D41 -> 10797.134
A42: =A41+0.000001 -> 4.010404 | B42: ENCOFRADO Y DESENCOFRADO DE VIGAS | C42: m2 | D42: 6882.68 | E42: 54.6 | G42: 54.6 | H42: =+ROUND(D42*E42,2) -> 375794.33 | I42: =+ROUND(D42*F42,2) -> 0 | J42: 375794.33
A43: =A42+0.000001 -> 4.010405 | B43: ENCOFRADO Y DESENCOFRADO DE VIGAS DOBLE ALTURA | C43: m2 | D43: 31.74 | E43: 62.6 | G43: 62.6 | H43: =+ROUND(D43*E43,2) -> 1986.92 | I43: =+ROUND(D43*F43,2) -> 0 | J43: 1986.92
A44: =A43+0.000001 -> 4.010406 | B44: ACERO DE REFUERZO FY= 4200 kg/cm2, GRADO 60 | C44: kg | D44: 181073.35 | E44: 1.15 | F44: 0.94 | G44: 4.68 | H44: =+ROUND(D44*E44,2) -> 208234.35 | I44: =+ROUND(D44*F44,2) -> 170208.95 | J44: 846517.91 | P44: 0.94 | Q44: =+P44*D44 -> 170208.95
A45: =A44+0.000001 -> 4.010407 | B45: CURADO DE ELEMENTOS ESTRUCTURALES EXPUESTOS | C45: m2 | D45: 8541.37 | E45: 1.5 | G45: 1.5 | H45: =+ROUND(D45*E45,2) -> 12812.06 | I45: =+ROUND(D45*F45,2) -> 0 | J45: 12812.06
A46: =A38+0.0001 -> 4.0105 | B46: VIGAS CHATAS | D46: 0
A47: =A46+0.000001 -> 4.010501 | B47: ACERO DE REFUERZO FY= 4200 kg/cm2, GRADO 60 | C47: kg | D47: 74670.9 | E47: 1.15 | F47: 0.94 | G47: 4.68 | H47: =+ROUND(D47*E47,2) -> 85871.54 | I47: =+ROUND(D47*F47,2) -> 70190.65 | J47: 349086.48 | P47: 0.94 | Q47: =+P47*D47 -> 70190.646
A48: =A47+0.000001 -> 4.010502 | B48: SUMINISTRO DE PRELOSA MACIZA H=20CM | C48: m2 | D48: 1626.95 | E48: 45.2 | G48: 45.2 | H48: =+ROUND(D48*E48,2) -> 73538.14 | I48: =+ROUND(D48*F48,2) -> 0 | J48: 73538.14 | L48: 45.2 | M48: =+L48*D48 -> 73538.14
A49: =A48+0.000001 -> 4.010503 | B49: INSTALACIÓN DE PRELOSA E=5CM | C49: m2 | D49: 1626.95 | E49: 5.43 | G49: 5.43 | H49: =+ROUND(D49*E49,2) -> 8834.34 | I49: =+ROUND(D49*F49,2) -> 0 | J49: 8834.34
A50: =A48+0.000001 -> 4.010503 | B50: APUNTALAMIENTO (ENCOFRADO) DE PRELOSA EN VIGAS CHATAS | C50: m2 | D50: 1570.63 | E50: 37.1 | G50: 37.1 | H50: =+ROUND(D50*E50,2) -> 58270.37 | I50: =+ROUND(D50*F50,2) -> 0 | J50: 58270.37
A51: =A49+0.000001 -> 4.010504 | B51: APUNTALAMIENTO (ENCOFRADO) DE PRELOSA EN VIGAS CHATAS DOBLE ALTURA | C51: m2 | D51: 56.32 | E51: 43.1 | G51: 43.1 | H51: =+ROUND(D51*E51,2) -> 2427.39 | I51: =+ROUND(D51*F51,2) -> 0 | J51: 2427.39
A52: =A38+0.0001 -> 4.0105 | B52: PRELOSA MACIZA H=0.20M | D52: 0
A53: =A52+0.000001 -> 4.010501 | B53: CONCRETO PREMEZCLADO, CEMENTO TIPO I, LOSA MACIZA TORRE f'c=245 kg/cm2 | C53: m3 | D53: 320.92 | E53: 392.8 | G53: 392.8 | H53: =+ROUND(D53*E53,2) -> 126057.38 | I53: =+ROUND(D53*F53,2) -> 0 | J53: 126057.38 | N53: 352.38 | O53: =+N53*D53 -> 113085.79
A54: =A53+0.000001 -> 4.010502 | B54: CONCRETO PREMEZCLADO, CEMENTO TIPO I, VIGAS TORRE f'c=350 kg/cm2 (NUCLEOS) | C54: m3 | D54: 2.54 | E54: 451.61 | G54: 451.61 | H54: =+ROUND(D54*E54,2) -> 1147.09 | I54: =+ROUND(D54*F54,2) -> 0 | J54: 1147.09 | N54: 411.19 | O54: =+N54*D54 -> 1044.4226
A55: =A54+0.000001 -> 4.010503 | B55: CONCRETO PREMEZCLADO, CEMENTO TIPO I, VIGAS TORRE f'c=420 kg/cm2 (NUCLEOS) | C55: m3 | D55: 3.13 | E55: 467.86 | G55: 467.86 | H55: =+ROUND(D55*E55,2) -> 1464.4 | I55: =+ROUND(D55*F55,2) -> 0 | J55: 1464.4 | N55: 427.44 | O55: =+N55*D55 -> 1337.8872
A56: =A53+0.000001 -> 4.010502 | B56: ENCOFRADO Y DESENCOFRADO DE PRELOSA MACIZA | C56: m2 | D56: 2120.37 | E56: 37.5 | G56: 37.5 | H56: =+ROUND(D56*E56,2) -> 79513.88 | I56: =+ROUND(D56*F56,2) -> 0 | J56: 79513.88
A57: =A56+0.000001 -> 4.010503 | B57: ENCOFRADO Y DESENCOFRADO DE PRELOSA MACIZA DOBLE ALTURA | C57: m2 | D57: 56.87 | E57: 43.5 | G57: 43.5 | H57: =+ROUND(D57*E57,2) -> 2473.85 | I57: =+ROUND(D57*F57,2) -> 0 | J57: 2473.85
A58: =A57+0.000001 -> 4.010504 | B58: SUMINISTRO DE PRELOSA MACIZA H=20CM | C58: m2 | D58: 2177.24 | E58: 45.2 | G58: 45.2 | H58: =+ROUND(D58*E58,2) -> 98411.25 | I58: =+ROUND(D58*F58,2) -> 0 | J58: 98411.25 | L58: 45.2 | M58: =+L58*D58 -> 98411.248
A59: =A58+0.000001 -> 4.010505 | B59: INSTALACIÓN DE PRELOSA E=5CM | C59: m2 | D59: 2177.24 | E59: 5.43 | G59: 5.43 | H59: =+ROUND(D59*E59,2) -> 11822.41 | I59: =+ROUND(D59*F59,2) -> 0 | J59: 11822.41
A60: =A59+0.000001 -> 4.010506 | B60: ACERO DE REFUERZO FY= 4200 kg/cm2, GRADO 60 (PUESTO EN OBRA) | C60: kg | D60: 42187.6 | E60: 1.15 | F60: 0.94 | G60: 4.68 | H60: =+ROUND(D60*E60,2) -> 48515.74 | I60: =+ROUND(D60*F60,2) -> 39656.34 | J60: 197227.02 | P60: 0.94 | Q60: =+P60*D60 -> 39656.344
A61: =A60+0.000001 -> 4.010507 | B61: ACERO DE REFUERZO FY= 4200 kg/cm2, GRADO 60 (EMBEBIDO EN PRELOSA) | C61: kg | D61: 22725.55 | E61: 0 | F61: 0.94 | G61: 3.53 | H61: =+ROUND(D61*E61,2) -> 0 | I61: =+ROUND(D61*F61,2) -> 21362.02 | J61: 80107.58 | P61: 0.94 | Q61: =+P61*D61 -> 21362.017
A62: =A61+0.000001 -> 4.010508 | B62: ACERO DE REFUERZO FY= 4200 kg/cm2, GRADO 60 DE CONTINUIDAD (PUESTO EN OBRA) | C62: kg | D62: 9340.36 | E62: 1.15 | F62: 0.94 | G62: 4.68 | H62: =+ROUND(D62*E62,2) -> 10741.41 | I62: =+ROUND(D62*F62,2) -> 8779.94 | J62: 43666.19 | P62: 0.94 | Q62: =+P62*D62 -> 8779.9384
A63: =A62+0.000001 -> 4.010509 | B63: CURADO DE ELEMENTOS ESTRUCTURALES EXPUESTOS | C63: m2 | D63: 2177.24 | E63: 1.5 | G63: 1.5 | H63: =+ROUND(D63*E63,2) -> 3265.86 | I63: =+ROUND(D63*F63,2) -> 0 | J63: 3265.86
A64: =A46+0.0001 -> 4.0106 | B64: PRELOSA MACIZA H=0.25M | D64: 0
A65: =A64+0.000001 -> 4.010601 | B65: CONCRETO PREMEZCLADO, CEMENTO TIPO I, LOSA MACIZA TORRE f'c=245 kg/cm2 | C65: m3 | D65: 271.34 | E65: 392.8 | G65: 392.8 | H65: =+ROUND(D65*E65,2) -> 106582.35 | I65: =+ROUND(D65*F65,2) -> 0 | J65: 106582.35 | N65: 352.38 | O65: =+N65*D65 -> 95614.789
A66: =A64+0.000001 -> 4.010601 | B66: CONCRETO PREMEZCLADO, CEMENTO TIPO I, VIGAS TORRE f'c=350 kg/cm2 (NUCLEOS) | C66: m3 | D66: 2.41 | E66: 451.61 | G66: 451.61 | H66: =+ROUND(D66*E66,2) -> 1088.38 | I66: =+ROUND(D66*F66,2) -> 0 | J66: 1088.38 | N66: 411.19 | O66: =+N66*D66 -> 990.9679
A67: =A65+0.000001 -> 4.010602 | B67: CONCRETO PREMEZCLADO, CEMENTO TIPO I, VIGAS TORRE f'c=420 kg/cm2 (NUCLEOS) | C67: m3 | D67: 5.42 | E67: 467.86 | G67: 467.86 | H67: =+ROUND(D67*E67,2) -> 2535.8 | I67: =+ROUND(D67*F67,2) -> 0 | J67: 2535.8 | N67: 427.44 | O67: =+N67*D67 -> 2316.7248
A68: =A67+0.000001 -> 4.010603 | B68: ENCOFRADO Y DESENCOFRADO DE PRELOSA MACIZA | C68: m2 | D68: 1204.82 | E68: 37.5 | G68: 37.5 | H68: =+ROUND(D68*E68,2) -> 45180.75 | I68: =+ROUND(D68*F68,2) -> 0 | J68: 45180.75
A69: =A68+0.000001 -> 4.010604 | B69: ENCOFRADO Y DESENCOFRADO DE PRELOSA MACIZA DOBLE ALTURA | C69: m2 | D69: 191.04 | E69: 43.5 | G69: 43.5 | H69: =+ROUND(D69*E69,2) -> 8310.24 | I69: =+ROUND(D69*F69,2) -> 0 | J69: 8310.24
A70: =A69+0.000001 -> 4.010605 | B70: SUMINISTRO DE PRELOSA MACIZA H=25CM | C70: m2 | D70: 1395.86 | E70: 45.2 | G70: 45.2 | H70: =+ROUND(D70*E70,2) -> 63092.87 | I70: =+ROUND(D70*F70,2) -> 0 | J70: 63092.87 | L70: 45.2 | M70: =+L70*D70 -> 63092.872
A71: =A70+0.000001 -> 4.010606 | B71: INSTALACIÓN DE PRELOSA E=5CM | C71: m2 | D71: 1395.86 | E71: 5.43 | G71: 5.43 | H71: =+ROUND(D71*E71,2) -> 7579.52 | I71: =+ROUND(D71*F71,2) -> 0 | J71: 7579.52
A72: =A71+0.000001 -> 4.010607 | B72: ACERO DE REFUERZO FY= 4200 kg/cm2, GRADO 60 (PUESTO EN OBRA) | C72: kg | D72: 13476.46 | E72: 1.15 | F72: 0.94 | G72: 4.68 | H72: =+ROUND(D72*E72,2) -> 15497.93 | I72: =+ROUND(D72*F72,2) -> 12667.87 | J72: 63002.44 | P72: 0.94 | Q72: =+P72*D72 -> 12667.872
A73: =A72+0.000001 -> 4.010608 | B73: ACERO DE REFUERZO FY= 4200 kg/cm2, GRADO 60 (EMBEBIDO EN PRELOSA) | C73: kg | D73: 11841.47 | E73: 0 | F73: 0.94 | G73: 3.53 | H73: =+ROUND(D73*E73,2) -> 0 | I73: =+ROUND(D73*F73,2) -> 11130.98 | J73: 41741.18 | P73: 0.94 | Q73: =+P73*D73 -> 11130.982
A74: =A73+0.000001 -> 4.010609 | B74: ACERO DE REFUERZO FY= 4200 kg/cm2, GRADO 60 DE CONTINUIDAD (PUESTO EN OBRA) | C74: kg | D74: 5988.24 | E74: 1.15 | F74: 0.94 | G74: 4.68 | H74: =+ROUND(D74*E74,2) -> 6886.48 | I74: =+ROUND(D74*F74,2) -> 5628.95 | J74: 27995.04 | P74: 0.94 | Q74: =+P74*D74 -> 5628.9456
A75: =A74+0.000001 -> 4.01061 | B75: CURADO DE ELEMENTOS ESTRUCTURALES EXPUESTOS | C75: m2 | D75: 1395.86 | E75: 1.5 | G75: 1.5 | H75: =+ROUND(D75*E75,2) -> 2093.79 | I75: =+ROUND(D75*F75,2) -> 0 | J75: 2093.79
A76: =A64+0.0001 -> 4.0107 | B76: PRELOSA ALIGERADA H=0.20M, UN SENTIDO | D76: 0
A77: =A76+0.000001 -> 4.010701 | B77: CONCRETO PREMEZCLADO, CEMENTO TIPO I, LOSA ALIGERADA TORRE f'c=245 kg/cm2 | C77: m3 | D77: 4.83 | E77: 392.8 | G77: 392.8 | H77: =+ROUND(D77*E77,2) -> 1897.22 | I77: =+ROUND(D77*F77,2) -> 0 | J77: 1897.22 | N77: 352.38 | O77: =+N77*D77 -> 1701.9954
A78: =A77+0.000001 -> 4.010702 | B78: ENCOFRADO Y DESENCOFRADO DE PRELOSA ALIGERADA | C78: m2 | D78: 63.87 | E78: 37.5 | G78: 37.5 | H78: =+ROUND(D78*E78,2) -> 2395.13 | I78: =+ROUND(D78*F78,2) -> 0 | J78: 2395.13
A79: =A78+0.000001 -> 4.010703 | B79: ENCOFRADO Y DESENCOFRADO DE PRELOSA ALIGERADA DOBLE ALTURA | C79: m2 | D79: 0 | E79: 43.5 | G79: 43.5 | H79: =+ROUND(D79*E79,2) -> 0 | I79: =+ROUND(D79*F79,2) -> 0 | J79: 0
A80: =A79+0.000001 -> 4.010704 | B80: SUMINISTRO DE PRELOSA ALIGERADA EN UNA DIRECCION H=20CM | C80: m2 | D80: 63.87 | E80: 57.9 | G80: 57.9 | H80: =+ROUND(D80*E80,2) -> 3698.07 | I80: =+ROUND(D80*F80,2) -> 0 | J80: 3698.07 | L80: 57.9 | M80: =+L80*D80 -> 3698.073
A81: =A80+0.000001 -> 4.010705 | B81: INSTALACIÓN DE PRELOSA E=5CM | C81: m2 | D81: 63.87 | E81: 5.43 | G81: 5.43 | H81: =+ROUND(D81*E81,2) -> 346.81 | I81: =+ROUND(D81*F81,2) -> 0 | J81: 346.81
A82: =A81+0.000001 -> 4.010706 | B82: ACERO DE REFUERZO FY= 4200 kg/cm2, GRADO 60 (PUESTO EN OBRA) | C82: kg | D82: 447.42 | E82: 1.15 | F82: 0.94 | G82: 4.68 | H82: =+ROUND(D82*E82,2) -> 514.53 | I82: =+ROUND(D82*F82,2) -> 420.57 | J82: 2091.67 | P82: 0.94 | Q82: =+P82*D82 -> 420.5748
A83: =A82+0.000001 -> 4.010707 | B83: ACERO DE REFUERZO FY= 4200 kg/cm2, GRADO 60 (EMBEBIDO EN PRELOSA) | C83: kg | D83: 349.92 | E83: 0 | F83: 0.94 | G83: 3.53 | H83: =+ROUND(D83*E83,2) -> 0 | I83: =+ROUND(D83*F83,2) -> 328.92 | J83: 1233.45 | P83: 0.94 | Q83: =+P83*D83 -> 328.9248
A84: =A83+0.000001 -> 4.010708 | B84: ACERO DE REFUERZO FY= 4200 kg/cm2, GRADO 60 (COSTURA PRELOSA) | C84: kg | D84: 25.55 | E84: 1.15 | F84: 0.94 | G84: 4.68 | H84: =+ROUND(D84*E84,2) -> 29.38 | I84: =+ROUND(D84*F84,2) -> 24.02 | J84: 119.46 | P84: 0.94 | Q84: =+P84*D84 -> 24.017
A85: =A84+0.000001 -> 4.010709 | B85: ACERO DE REFUERZO FY= 4200 kg/cm2, GRADO 60 BASE Y DISTRIBUCIÓN (EMBEBIDO EN PRELOSA) | C85: kg | D85: 127.74 | E85: 0 | F85: 0.94 | G85: 3.53 | H85: =+ROUND(D85*E85,2) -> 0 | I85: =+ROUND(D85*F85,2) -> 120.08 | J85: 450.3 | P85: 0.94 | Q85: =+P85*D85 -> 120.0756
A86: =A85+0.000001 -> 4.01071 | B86: CURADO DE ELEMENTOS ESTRUCTURALES EXPUESTOS | C86: m2 | D86: 63.87 | E86: 1.5 | G86: 1.5 | H86: =+ROUND(D86*E86,2) -> 95.81 | I86: =+ROUND(D86*F86,2) -> 0 | J86: 95.81
A87: =A76+0.0001 -> 4.0108 | B87: PRELOSA ALIGERADA H=0.225M, UN SENTIDO | D87: 0
A88: =A87+0.000001 -> 4.010801 | B88: CONCRETO PREMEZCLADO, CEMENTO TIPO I, LOSA ALIGERADA TORRE f'c=245 kg/cm2 | C88: m3 | D88: 0 | E88: 392.8 | G88: 392.8 | H88: =+ROUND(D88*E88,2) -> 0 | I88: =+ROUND(D88*F88,2) -> 0 | J88: 0 | O88: =+N88*D88 -> 0
A89: =A88+0.000001 -> 4.010802 | B89: CONCRETO PREMEZCLADO, CEMENTO TIPO I, VIGAS TORRE f'c=350 kg/cm2 (NUCLEOS) | C89: m3 | D89: 0 | E89: 451.61 | G89: 451.61 | H89: =+ROUND(D89*E89,2) -> 0 | I89: =+ROUND(D89*F89,2) -> 0 | J89: 0 | O89: =+N89*D89 -> 0
A90: =A89+0.000001 -> 4.010803 | B90: ENCOFRADO Y DESENCOFRADO DE PRELOSA ALIGERADA | C90: m2 | D90: 0 | E90: 37.5 | G90: 37.5 | H90: =+ROUND(D90*E90,2) -> 0 | I90: =+ROUND(D90*F90,2) -> 0 | J90: 0
A91: =A90+0.000001 -> 4.010804 | B91: ENCOFRADO Y DESENCOFRADO DE PRELOSA ALIGERADA DOBLE ALTURA | C91: m2 | D91: 0 | E91: 43.5 | G91: 43.5 | H91: =+ROUND(D91*E91,2) -> 0 | I91: =+ROUND(D91*F91,2) -> 0 | J91: 0
A92: =A91+0.000001 -> 4.010805 | B92: SUMINISTRO DE PRELOSA ALIGERADA EN UNA DIRECCION H=22.5CM | C92: m2 | D92: 0 | E92: 60.9 | G92: 60.9 | H92: =+ROUND(D92*E92,2) -> 0 | I92: =+ROUND(D92*F92,2) -> 0 | J92: 0 | L92: 60.9 | M92: =+L92*D92 -> 0
A93: =A92+0.000001 -> 4.010806 | B93: INSTALACIÓN DE PRELOSA E=5CM | C93: m2 | D93: 0 | E93: 5.43 | G93: 5.43 | H93: =+ROUND(D93*E93,2) -> 0 | I93: =+ROUND(D93*F93,2) -> 0 | J93: 0
A94: =A93+0.000001 -> 4.010807 | B94: ACERO DE REFUERZO FY= 4200 kg/cm2, GRADO 60 (PUESTO EN OBRA) | C94: kg | D94: 0 | E94: 1.15 | F94: 0.94 | G94: 4.68 | H94: =+ROUND(D94*E94,2) -> 0 | I94: =+ROUND(D94*F94,2) -> 0 | J94: 0 | P94: 0.94 | Q94: =+P94*D94 -> 0
A95: =A94+0.000001 -> 4.010808 | B95: ACERO DE REFUERZO FY= 4200 kg/cm2, GRADO 60 (EMBEBIDO EN PRELOSA) | C95: kg | D95: 0 | E95: 0 | F95: 0.94 | G95: 3.53 | H95: =+ROUND(D95*E95,2) -> 0 | I95: =+ROUND(D95*F95,2) -> 0 | J95: 0 | P95: 0.94 | Q95: =+P95*D95 -> 0
A96: =A95+0.000001 -> 4.010809 | B96: ACERO DE REFUERZO FY= 4200 kg/cm2, GRADO 60 (COSTURA PRELOSA) | C96: kg | D96: 0 | E96: 1.15 | F96: 0.94 | G96: 4.68 | H96: =+ROUND(D96*E96,2) -> 0 | I96: =+ROUND(D96*F96,2) -> 0 | J96: 0 | P96: 0.94 | Q96: =+P96*D96 -> 0
A97: =A96+0.000001 -> 4.01081 | B97: ACERO DE REFUERZO FY= 4200 kg/cm2, GRADO 60 BASE Y DISTRIBUCIÓN (EMBEBIDO EN PRELOSA) | C97: kg | D97: 0 | E97: 0 | F97: 0.94 | G97: 3.53 | H97: =+ROUND(D97*E97,2) -> 0 | I97: =+ROUND(D97*F97,2) -> 0 | J97: 0 | P97: 0.94 | Q97: =+P97*D97 -> 0
A98: =A97+0.000001 -> 4.010811 | B98: CURADO DE ELEMENTOS ESTRUCTURALES EXPUESTOS | C98: m2 | D98: 0 | E98: 1.5 | G98: 1.5 | H98: =+ROUND(D98*E98,2) -> 0 | I98: =+ROUND(D98*F98,2) -> 0 | J98: 0
A99: =A87+0.0001 -> 4.0109 | B99: PRELOSA ALIGERADA H=0.25M, UN SENTIDO | D99: 0
A100: =A99+0.000001 -> 4.010901 | B100: CONCRETO PREMEZCLADO, CEMENTO TIPO I, LOSA ALIGERADA TORRE f'c=245 kg/cm2 | C100: m3 | D100: 778.01 | E100: 392.8 | G100: 392.8 | H100: =+ROUND(D100*E100,2) -> 305602.33 | I100: =+ROUND(D100*F100,2) -> 0 | J100: 305602.33 | N100: 352.38 | O100: =+N100*D100 -> 274155.16
A101: =A100+0.000001 -> 4.010902 | B101: CONCRETO PREMEZCLADO, CEMENTO TIPO I, VIGAS TORRE f'c=350 kg/cm2 (NUCLEOS) | C101: m3 | D101: 16.03 | E101: 451.61 | G101: 451.61 | H101: =+ROUND(D101*E101,2) -> 7239.31 | I101: =+ROUND(D101*F101,2) -> 0 | J101: 7239.31 | N101: 411.19 | O101: =+N101*D101 -> 6591.3757
A102: =A100+0.000001 -> 4.010902 | B102: CONCRETO PREMEZCLADO, CEMENTO TIPO I, VIGAS TORRE f'c=420 kg/cm2 (NUCLEOS) | C102: m3 | D102: 10.5 | E102: 467.86 | G102: 467.86 | H102: =+ROUND(D102*E102,2) -> 4912.53 | I102: =+ROUND(D102*F102,2) -> 0 | J102: 4912.53 | N102: 427.44 | O102: =+N102*D102 -> 4488.12
...

Sheet ARQ SOT
B2: ARQUITECTURA SÓTANOS
B4: Presupuesto | C4: =+#REF! -> #REF!
B5: Subpresupuesto | C5: =$B$2 -> ARQUITECTURA SÓTANOS
B6: Cliente | C6: =+#REF! -> #REF!
B7: Lugar | C7: SAN ISIDRO
B8: Fecha | C8: =+#REF! -> #REF!
M9: Partidas abiertas
B10: ITEM | C10: DESCRIPCION | D10: UND | E10: METRADO | F10: P.U. (PEN) | G10: P.U. (USD) | H10: P.U. TOTAL (PEN) | I10: PRECIO PARCIAL (PEN) | J10: PRECIO PARCIAL (USD) | K10: PARCIAL TOTAL (PEN) | L10: TOTAL | M10: P.U. (PEN) | N10: PRECIO PARCIAL (PEN) | O10: P.U. (USD) | P10: PRECIO PARCIAL (USD)
B11: 05 | C11: =$B$2 -> ARQUITECTURA SÓTANOS
B12: =B11+0.01 -> 5.01 | C12: MUROS Y TABIQUES | I12: =IFERROR(IF($E12=0,"",$E12*F12),"") | J12: =IFERROR(IF($E12=0,"",$E12*G12),"") | L12: 232941.24
B13: =B12+0.0001 -> 5.0101 | C13: MUROS Y TABIQUES SILICO CALCAREOS | I13: =IFERROR(IF($E13=0,"",$E13*F13),"") | J13: =IFERROR(IF($E13=0,"",$E13*G13),"")
B14: =B12+0.0001 -> 5.0101 | C14: ALTURA < 2.60 | I14: =IFERROR(IF($E14=0,"",$E14*F14),"") | J14: =IFERROR(IF($E14=0,"",$E14*G14),"")
B15: =B14+0.000001 -> 5.010101 | C15: LADRILLO SILICO CALCAREO TIPO P7 H<2.6M | D15: m2 | F15: 99.22 | H15: 99.22 | I15: =+ROUND(E15*F15,2) -> 0 | J15: =+ROUND(E15*G15,2) -> 0 | K15: 0 | M15: 99.22 | N15: =+M15*E15 -> 0
B16: =B15+0.000001 -> 5.010102 | C16: LADRILLO SILICO CALCAREO TIPO P10 H<2.6M | D16: m2 | E16: 413.25 | F16: 108.22 | H16: 108.22 | I16: =+ROUND(E16*F16,2) -> 44721.92 | J16: =+ROUND(E16*G16,2) -> 0 | K16: 44721.92 | M16: 108.22 | N16: =+M16*E16 -> 44721.915
B17: =B16+0.000001 -> 5.010103 | C17: LADRILLO SILICO CALCAREO TIPO P12 H<2.6M | D17: m2 | E17: 116.3 | F17: 113.22 | H17: 113.22 | I17: =+ROUND(E17*F17,2) -> 13167.49 | J17: =+ROUND(E17*G17,2) -> 0 | K17: 13167.49 | M17: 113.22 | N17: =+M17*E17 -> 13167.486
B18: =B17+0.000001 -> 5.010104 | C18: LADRILLO SILICO CALCAREO TIPO P14 H<2.6M | D18: m2 | E18: 27.64 | F18: 119.22 | H18: 119.22 | I18: =+ROUND(E18*F18,2) -> 3295.24 | J18: =+ROUND(E18*G18,2) -> 0 | K18: 3295.24 | M18: 119.22 | N18: =+M18*E18 -> 3295.2408
B19: =B18+0.000001 -> 5.010105 | C19: LADRILLO SILICO CALCAREO TIPO P20 H<2.6M | D19: m2 | E19: 40.91 | F19: 198.22 | H19: 198.22 | I19: =+ROUND(E19*F19,2) -> 8109.18 | J19: =+ROUND(E19*G19,2) -> 0 | K19: 8109.18 | M19: 198.22 | N19: =+M19*E19 -> 8109.1802
B20: =B19+0.000001 -> 5.010106 | C20: LADRILLO SILICO CALCAREO TIPO P25 H<2.6M | D20: m2 | E20: 8.62 | F20: 198.22 | H20: 198.22 | I20: =+ROUND(E20*F20,2) -> 1708.66 | J20: =+ROUND(E20*G20,2) -> 0 | K20: 1708.66 | M20: 198.22 | N20: =+M20*E20 -> 1708.6564
B21: =B20+0.000001 -> 5.010107 | C21: LADRILLO SILICO CALCAREO TIPO P30 H<2.6M | D21: m2 | E21: 49.78 | F21: 198.22 | H21: 198.22 | I21: =+ROUND(E21*F21,2) -> 9867.39 | J21: =+ROUND(E21*G21,2) -> 0 | K21: 9867.39 | M21: 198.22 | N21: =+M21*E21 -> 9867.3916
B22: =B21+0.000001 -> 5.010108 | C22: LADRILLO SILICO CALCAREO TIPO P40 H<2.6M | D22: m2 | E22: 53.3 | F22: 236.22 | H22: 236.22 | I22: =+ROUND(E22*F22,2) -> 12590.53 | J22: =+ROUND(E22*G22,2) -> 0 | K22: 12590.53 | M22: 236.22 | N22: =+M22*E22 -> 12590.526
B23: =B14+0.0001 -> 5.0102 | C23: ALTURA > 2.60 | M23: 0 | N23: =+M23*E23 -> 0
B24: =B23+0.000001 -> 5.010201 | C24: LADRILLO SILICO CALCAREO TIPO P7 H>2.6M | D24: m2 | F24: 99.22 | H24: 99.22 | I24: =+ROUND(E24*F24,2) -> 0 | J24: =+ROUND(E24*G24,2) -> 0 | K24: 0 | M24: 99.22 | N24: =+M24*E24 -> 0
B25: =B24+0.000001 -> 5.010202 | C25: LADRILLO SILICO CALCAREO TIPO P10 H>2.6M | D25: m2 | E25: 148.3 | F25: 110.22 | H25: 110.22 | I25: =+ROUND(E25*F25,2) -> 16345.63 | J25: =+ROUND(E25*G25,2) -> 0 | K25: 16345.63 | M25: 110.22 | N25: =+M25*E25 -> 16345.626
B26: =B25+0.000001 -> 5.010203 | C26: LADRILLO SILICO CALCAREO TIPO P12 H>2.6M | D26: m2 | E26: 24.82 | F26: 116.22 | H26: 116.22 | I26: =+ROUND(E26*F26,2) -> 2884.58 | J26: =+ROUND(E26*G26,2) -> 0 | K26: 2884.58 | M26: 116.22 | N26: =+M26*E26 -> 2884.5804
B27: =B26+0.000001 -> 5.010204 | C27: LADRILLO SILICO CALCAREO TIPO P14 H>2.6M | D27: m2 | E27: 5.24 | F27: 124.22 | H27: 124.22 | I27: =+ROUND(E27*F27,2) -> 650.91 | J27: =+ROUND(E27*G27,2) -> 0 | K27: 650.91 | M27: 124.22 | N27: =+M27*E27 -> 650.9128
B28: =B27+0.000001 -> 5.010205 | C28: LADRILLO SILICO CALCAREO TIPO P20 H>2.6M | D28: m2 | E28: 20.83 | F28: 208.22 | H28: 208.22 | I28: =+ROUND(E28*F28,2) -> 4337.22 | J28: =+ROUND(E28*G28,2) -> 0 | K28: 4337.22 | M28: 208.22 | N28: =+M28*E28 -> 4337.2226
B29: =B28+0.000001 -> 5.010206 | C29: LADRILLO SILICO CALCAREO TIPO P40 H>2.6M | D29: m2 | E29: 19.95 | F29: 230.22 | H29: 230.22 | I29: =+ROUND(E29*F29,2) -> 4592.89 | J29: =+ROUND(E29*G29,2) -> 0 | K29: 4592.89 | M29: 230.22 | N29: =+M29*E29 -> 4592.889
B30: =B27+0.0001 -> 5.010304 | C30: CORTAFUEGO < 2.60 | M30: 0 | N30: =+M30*E30 -> 0
B31: =B30+0.000001 -> 5.010305 | C31: LADRILLO SILICO CALCAREO TIPO P10 RF:2 HRS H<2.6M (ALVEOLOS COMPLETAMENTE LLENO) | D31: m2 | E31: 97 | F31: 112.22 | H31: 112.22 | I31: =+ROUND(E31*F31,2) -> 10885.34 | J31: =+ROUND(E31*G31,2) -> 0 | K31: 10885.34 | M31: 112.22 | N31: =+M31*E31 -> 10885.34
B32: =B31+0.000001 -> 5.010306 | C32: LADRILLO SILICO CALCAREO TIPO P12 RF:2 HRS H<2.6M (ALVEOLOS PARCIALMENTE LLENO) | D32: m2 | E32: 281.5 | F32: 113.22 | H32: 113.22 | I32: =+ROUND(E32*F32,2) -> 31871.43 | J32: =+ROUND(E32*G32,2) -> 0 | K32: 31871.43 | M32: 113.22 | N32: =+M32*E32 -> 31871.43
B33: =B32+0.000001 -> 5.010307 | C33: LADRILLO SILICO CALCAREO TIPO P14 RF:2 HRS H<2.6M (ALVEOLOS PARCIALMENTE LLENO) | D33: m2 | E33: 56.01 | F33: 119.22 | H33: 119.22 | I33: =+ROUND(E33*F33,2) -> 6677.51 | J33: =+ROUND(E33*G33,2) -> 0 | K33: 6677.51 | M33: 119.22 | N33: =+M33*E33 -> 6677.5122
B34: =B23+0.0001 -> 5.0103 | C34: CORTAFUEGO > 2.60 | M34: 0 | N34: =+M34*E34 -> 0
B35: =B34+0.000001 -> 5.010301 | C35: LADRILLO SILICO CALCAREO TIPO P10 RF:2 HRS H>2.6M (ALVEOLOS COMPLETAMENTE LLENO) | D35: m2 | E35: 34.42 | F35: 116.22 | H35: 116.22 | I35: =+ROUND(E35*F35,2) -> 4000.29 | J35: =+ROUND(E35*G35,2) -> 0 | K35: 4000.29 | M35: 116.22 | N35: =+M35*E35 -> 4000.2924
B36: =B35+0.000001 -> 5.010302 | C36: LADRILLO SILICO CALCAREO TIPO P12 RF:2 HRS H>2.6M (ALVEOLOS PARCIALMENTE LLENO) | D36: m2 | E36: 233.11 | F36: 116.22 | H36: 116.22 | I36: =+ROUND(E36*F36,2) -> 27092.04 | J36: =+ROUND(E36*G36,2) -> 0 | K36: 27092.04 | M36: 116.22 | N36: =+M36*E36 -> 27092.044
B37: =B36+0.000001 -> 5.010303 | C37: LADRILLO SILICO CALCAREO TIPO P14 RF:2 HRS H>2.6M (ALVEOLOS PARCIALMENTE LLENO) | D37: m2 | E37: 29.36 | F37: 124.22 | H37: 124.22 | I37: =+ROUND(E37*F37,2) -> 3647.1 | J37: =+ROUND(E37*G37,2) -> 0 | K37: 3647.1 | M37: 124.22 | N37: =+M37*E37 -> 3647.0992
B38: =B37+0.000001 -> 5.010304 | C38: LADRILLO SILICO CALCAREO TIPO P30 RF:2 HRS H>2.6M (ALVEOLOS COMPLETAMENTE LLENO) | D38: m2 | E38: 4.46 | F38: 232.44 | H38: 232.44 | I38: =+ROUND(E38*F38,2) -> 1036.68 | J38: =+ROUND(E38*G38,2) -> 0 | K38: 1036.68 | M38: 232.44 | N38: =+M38*E38 -> 1036.6824
B39: =B34+0.0001 -> 5.0104 | C39: ACERO DE REFUERZO
B40: =B39+0.000001 -> 5.010401 | C40: ACERO DE REFUERZO FY= 4200 kg/cm2 GRADO 60 PARA TABIQUERÍA | D40: kg | E40: 2846.85 | F40: 0 | G40: 0.94 | H40: 3.53 | I40: =+ROUND(E40*F40,2) -> 0 | J40: =+ROUND(E40*G40,2) -> 2676.04 | K40: 10035.15 | O40: 0.94 | P40: =+O40*E40 -> 2676.039
B41: =B39+0.0001 -> 5.0105 | C41: DINTELES
B42: =B41+0.000001 -> 5.010501 | C42: DINTELES DE LADRILLOS SILICO CALCAREO | D42: und | E42: 52 | F42: 120 | H42: 120 | I42: =+ROUND(E42*F42,2) -> 6240 | J42: =+ROUND(E42*G42,2) -> 0 | K42: 6240 | M42: 120 | N42: =+M42*E42 -> 6240
B43: =B42+0.000001 -> 5.010502 | C43: DINTELES DE LADRILLO SILICO CALCAREO RF | D43: und | E43: 16 | F43: 125 | H43: 125 | I43: =+ROUND(E43*F43,2) -> 2000 | J43: =+ROUND(E43*G43,2) -> 0 | K43: 2000 | M43: 125 | N43: =+M43*E43 -> 2000
B44: =B43+0.000001 -> 5.010503 | C44: DINTELES DE DRYWALL (SOBRE CLOSET DE DEPOSITOS) | D44: ml | E44: 41.17 | F44: 100 | H44: 100 | I44: =+ROUND(E44*F44,2) -> 4117 | J44: =+ROUND(E44*G44,2) -> 0 | K44: 4117
B45: =B41+0.0001 -> 5.0106 | C45: TRABAJOS COMPLEMENTARIOS DE TABIQUERIA
B46: =B45+0.000001 -> 5.010601 | C46: PASES DE MANGUERA (0.20x20M) DOBLE PLACA DE ROCA DE YESO | D46: und | E46: 11 | F46: 80 | H46: 80 | I46: =+ROUND(E46*F46,2) -> 880 | J46: =+ROUND(E46*G46,2) -> 0 | K46: 880
B47: =B45+0.0001 -> 5.0107 | C47: PARAPETOS Y SARDINELES | H47: 0 | I47: =+ROUND(E47*F47,2) -> 0 | J47: =+ROUND(E47*G47,2) -> 0 | K47: 0
B48: =B47+0.000001 -> 5.010701 | C48: SARDINEL EN CUARTO DE ACOPIO H:0.10M (E=10CM) | D48: ml | E48: 4 | F48: 44.43 | G48: 0.75 | H48: 47.24 | I48: =+ROUND(E48*F48,2) -> 177.72 | J48: =+ROUND(E48*G48,2) -> 3 | K48: 188.97
B49: =B48+0.000001 -> 5.010702 | C49: SARDINEL H:0.10M, ACABADO TER-02- SSHH | D49: ml | H49: 0 | I49: =+ROUND(E49*F49,2) -> 0 | J49: =+ROUND(E49*G49,2) -> 0 | K49: 0
B50: =B49+0.000001 -> 5.010703 | C50: SARDINEL EN CLOSET DE DEPOSITOS H:0.10M (E=10CM) | D50: ml | E50: 41.17 | F50: 45.72 | G50: 0.75 | H50: 48.53 | I50: =+ROUND(E50*F50,2) -> 1882.29 | J50: =+ROUND(E50*G50,2) -> 30.88 | K50: 1998.09
B51: =B12+0.01 -> 5.02 | C51: REVOQUES Y ENLUCIDOS | L51: 110632.09
B52: =B51+0.0001 -> 5.0201 | C52: SOLAQUEO DE MURO PANTALLA | D52: m2 | E52: 2713.01 | F52: 16.74 | H52: 16.74 | I52: =+ROUND(E52*F52,2) -> 45415.79 | J52: =+ROUND(E52*G52,2) -> 0 | K52: 45415.79
B53: =B52+0.0001 -> 5.0202 | C53: SOLAQUEO EN COLUMNAS Y PLACAS | D53: m2 | E53: 1696.2 | F53: 16.37 | H53: 16.37 | I53: =+ROUND(E53*F53,2) -> 27766.79 | J53: =+ROUND(E53*G53,2) -> 0 | K53: 27766.79
B54: =B53+0.0001 -> 5.0203 | C54: SOLAQUEO EN COLUMNAS Y PLACAS A DOBLE ALTURA | D54: m2 | E54: 513.14 | F54: 22.64 | H54: 22.64 | I54: =+ROUND(E54*F54,2) -> 11617.49 | J54: =+ROUND(E54*G54,2) -> 0 | K54: 11617.49
B55: =B53+0.0001 -> 5.0203 | C55: SOLAQUEO DE DUCTOS DE ASCENSORES | D55: m2 | E55: 167.36 | F55: 24.61 | H55: 24.61 | I55: =+ROUND(E55*F55,2) -> 4118.73 | J55: =+ROUND(E55*G55,2) -> 0 | K55: 4118.73
B56: =B55+0.0001 -> 5.0204 | C56: LIMPIEZA DE DUCTOS DE VENTILACION | D56: m2 | E56: 360.01 | F56: 8.7 | H56: 8.7 | I56: =+ROUND(E56*F56,2) -> 3132.09 | J56: =+ROUND(E56*G56,2) -> 0 | K56: 3132.09
B57: =B56+0.0001 -> 5.0205 | C57: SOLAQUEO DE MUROS Y PLACAS DE ESCALERA | D57: m2 | F57: 16.71 | H57: 16.71 | I57: =+ROUND(E57*F57,2) -> 0 | J57: =+ROUND(E57*G57,2) -> 0 | K57: 0
B58: =B57+0.0001 -> 5.0206 | C58: IMPERMEABILIZACION DE CISTERNAS | D58: m2 | E58: 337.84 | F58: 55 | H58: 55 | I58: =+ROUND(E58*F58,2) -> 18581.2 | J58: =+ROUND(E58*G58,2) -> 0 | K58: 18581.2
B59: =B51+0.01 -> 5.03 | C59: CIELORASOS | L59: 87543.02
B60: =B59+0.0001 -> 5.0301 | C60: LIMPIEZA Y RESANE DE PRELOSAS EN SÓTANOS (INC LIMPIEZA DE TECHO DE CISTERNA Y CTO BOMBAS) | D60: m2 | E60: 5272.26 | F60: 3.89 | H60: 3.89 | I60: =+ROUND(E60*F60,2) -> 20509.09 | J60: =+ROUND(E60*G60,2) -> 0 | K60: 20509.09
B61: =B60+0.0001 -> 5.0302 | C61: LIMPIEZA Y RESANE DE PRELOSAS EN SÓTANOS (INC LIMPIEZA DE TECHO DE CISTERNA Y CTO BOMBAS) A DOBLE ALTURA | D61: m2 | E61: 1402.94 | F61: 4.44 | H61: 4.44 | I61: =+ROUND(E61*F61,2) -> 6229.05 | J61: =+ROUND(E61*G61,2) -> 0 | K61: 6229.05
B62: =B61+0.0001 -> 5.0303 | C62: SOLAQUEO DE VIGAS EN SOTANOS (EN FONDO Y COSTADO) | D62: m2 | E62: 1503.2 | F62: 22.78 | H62: 22.78 | I62: =+ROUND(E62*F62,2) -> 34242.9 | J62: =+ROUND(E62*G62,2) -> 0 | K62: 34242.9
B63: =B62+0.0001 -> 5.0304 | C63: SOLAQUEO DE VIGAS EN SOTANOS (EN FONDO Y COSTADO)A DOBLE ALTURA | D63: m2 | E63: 433.28 | F63: 27.95 | H63: 27.95 | I63: =+ROUND(E63*F63,2) -> 12110.18 | J63: =+ROUND(E63*G63,2) -> 0 | K63: 12110.18
B64: =B63+0.0001 -> 5.0305 | C64: IMPERMEABILIZACION DE CISTERNAS | D64: m2 | E64: 262.76 | F64: 55 | H64: 55 | I64: =+ROUND(E64*F64,2) -> 14451.8 | J64: =+ROUND(E64*G64,2) -> 0 | K64: 14451.8
B65: =B59+0.01 -> 5.04 | C65: PISOS | L65: 212921.27
B66: =B65+0.0001 -> 5.0401 | C66: NIVELACIÓN DE PISO
B67: =B66+0.0001 -> 5.0402 | C67: NIVELACIÓN DE PISO | D67: m2 | E67: 40.87 | F67: 21.54 | H67: 21.54 | I67: =+ROUND(E67*F67,2) -> 880.34 | J67: =+ROUND(E67*G67,2) -> 0 | K67: 880.34
B68: =B67+0.0001 -> 5.0403 | C68: CONTRAPISO | D68: m2 | E68: 295.63 | F68: 43.36 | H68: 43.36 | I68: =+ROUND(E68*F68,2) -> 12818.52 | J68: =+ROUND(E68*G68,2) -> 0 | K68: 12818.52
B69: =B68+0.0001 -> 5.0404 | C69: CTO ACOPIO Y RECICLAJE
B70: =B69+0.0001 -> 5.0405 | C70: CERAMICO AMERICA BLANCO 45x45CM. CELIMA | D70: m2 | E70: 40.87 | F70: 69.4 | H70: 69.4 | I70: =+ROUND(E70*F70,2) -> 2836.38 | J70: =+ROUND(E70*G70,2) -> 0 | K70: 2836.38
B71: =B70+0.0001 -> 5.0406 | C71: HALL DE ASCENSORES
B72: =B71+0.0001 -> 5.0407 | C72: PISO CEMENTO PULIDO | D72: m2 | E72: 178.5 | F72: 45.33 | H72: 45.33 | I72: =+ROUND(E72*F72,2) -> 8091.41 | J72: =+ROUND(E72*G72,2) -> 0 | K72: 8091.41
B73: =B72+0.0001 -> 5.0408 | C73: VESTIBULO PREVIO Y ESCALERA
B74: =B73+0.0001 -> 5.0409 | C74: PISO CEMENTO PULIDO | D74: m2 | E74: 57.98 | F74: 45.33 | H74: 45.33 | I74: =+ROUND(E74*F74,2) -> 2628.23 | J74: =+ROUND(E74*G74,2) -> 0 | K74: 2628.23
B75: =B74+0.0001 -> 5.041 | C75: DEPOSITOS Y CLOSETS DE ESTACIONAMIENTOS
B76: =B75+0.0001 -> 5.0411 | C76: PISO CEMENTO PULIDO | D76: m2 | E76: 295.63 | F76: 45.33 | H76: 45.33 | I76: =+ROUND(E76*F76,2) -> 13400.91 | J76: =+ROUND(E76*G76,2) -> 0 | K76: 13400.91
B77: =B76+0.0001 -> 5.0412 | C77: ESTACIONAMIENTOS VEHICULARES
B78: =B77+0.0001 -> 5.0413 | C78: CEMENTO FROTACHADO | D78: m2 | E78: 5458.32 | F78: 20.67 | H78: 20.67 | I78: =+ROUND(E78*F78,2) -> 112823.47 | J78: =+ROUND(E78*G78,2) -> 0 | K78: 112823.47
B79: =B78+0.0001 -> 5.0414 | C79: RAMPAS
B80: =B79+0.0001 -> 5.0415 | C80: PISO CEMENTO BRUÑADO | D80: m2 | E80: 732.69 | F80: 45.95 | H80: 45.95 | I80: =+ROUND(E80*F80,2) -> 33667.11 | J80: =+ROUND(E80*G80,2) -> 0 | K80: 33667.11
B81: =B80+0.0001 -> 5.0416 | C81: CTO BOMBAS, CAMARA DESAGUE, CTO GRUPO ELECTROGENO, CTO ACELEROGRAFO, SUBESTACION
B82: =B81+0.0001 -> 5.0417 | C82: PISO CEMENTO PULIDO | D82: m2 | E82: 158.38 | F82: 45.33 | H82: 45.33 | I82: =+ROUND(E82*F82,2) -> 7179.37 | J82: =+ROUND(E82*G82,2) -> 0 | K82: 7179.37
B83: =B82+0.0001 -> 5.0418 | C83: ESTACIONAMIENTO DE BICICLETAS
B84: =B83+0.0001 -> 5.0419 | C84: PISO CEMENTO PULIDO | D84: m2 | E84: 127.06 | F84: 45.33 | H84: 45.33 | I84: =+ROUND(E84*F84,2) -> 5759.63 | J84: =+ROUND(E84*G84,2) -> 0 | K84: 5759.63
B85: =B84+0.0001 -> 5.042 | C85: CISTERNA
B86: =B85+0.0001 -> 5.0421 | C86: IMPERMEABILIZACION | D86: m2 | E86: 233.38 | F86: 55 | H86: 55 | I86: =+ROUND(E86*F86,2) -> 12835.9 | J86: =+ROUND(E86*G86,2) -> 0 | K86: 12835.9
B87: =B53+0.01 -> 5.0302 | C87: ZÓCALOS | L87: 4980.14
B88: =B87+0.0001 -> 5.0303 | C88: CTO ACOPIO Y RECICLAJE
B89: =B88+0.0001 -> 5.0304 | C89: CERAMICO AMERICA BLANCO 45x45CM. CELIMA | D89: m2 | E89: 71.76 | F89: 69.4 | H89: 69.4 | I89: =+ROUND(E89*F89,2) -> 4980.14 | J89: =+ROUND(E89*G89,2) -> 0 | K89: 4980.14
B90: =B65+0.01 -> 5.05 | C90: CONTRAZÓCALOS | L90: 28970.34
B91: =B90+0.0001 -> 5.0501 | C91: ESCLUSA, CTO BOMBAS, CTO GRUPO ELECTROGENO, CTO ACELEROGRAFO, SUBESTACION)
B92: =B91+0.0001 -> 5.0502 | C92: CZ DE PINTURA DE TRAFICO COLOR GRAFITO H=15CM - CUARTOS TECNICOS | D92: ml | E92: 116 | F92: 10.5 | H92: 10.5 | I92: =+ROUND(E92*F92,2) -> 1218 | J92: =+ROUND(E92*G92,2) -> 0 | K92: 1218
B93: =B92+0.0001 -> 5.0503 | C93: DEPOSITOS Y CLOSETS DE ESTACIONAMIENTOS
B94: =B93+0.0001 -> 5.0504 | C94: CZ DE PINTURA DE TRAFICO COLOR GRAFITO H=15CM | D94: ml | E94: 668.56 | F94: 10.5 | H94: 10.5 | I94: =+ROUND(E94*F94,2) -> 7019.88 | J94: =+ROUND(E94*G94,2) -> 0 | K94: 7019.88
B95: =B94+0.0001 -> 5.0505 | C95: HALL DE ASCENSORES
B96: =B95+0.0001 -> 5.0506 | C96: CZ DE PINTURA DE TRAFICO COLOR GRAFITO H=15CM | D96: ml | E96: 155.24 | F96: 10.5 | H96: 10.5 | I96: =+ROUND(E96*F96,2) -> 1630.02 | J96: =+ROUND(E96*G96,2) -> 0 | K96: 1630.02
B97: =B96+0.0001 -> 5.0507 | C97: VESTIBULO PREVIO Y ESCALERA
B98: =B97+0.0001 -> 5.0508 | C98: CZ DE PINTURA DE TRAFICO COLOR GRAFITO H=15CM | D98: ml | E98: 174.91 | F98: 10.5 | H98: 10.5 | I98: =+ROUND(E98*F98,2) -> 1836.56 | J98: =+ROUND(E98*G98,2) -> 0 | K98: 1836.56
B99: =B98+0.0001 -> 5.0509 | C99: CZ CIRCULACION VEHICULAR, ESTACIONAMIENTOS Y RAMPAS
B100: =B99+0.0001 -> 5.051 | C100: CZ DE PINTURA DE TRAFICO COLOR AMARILLO H=15CM | D100: ml | E100: 1487.27 | F100: 10.5 | H100: 10.5 | I100: =+ROUND(E100*F100,2) -> 15616.34 | J100: =+ROUND(E100*G100,2) -> 0 | K100: 15616.34
B101: =B100+0.0001 -> 5.0511 | C101: ESTACIONAMIENTO DE BICICLETAS
B102: =B101+0.0001 -> 5.0512 | C102: CZ DE PINTURA DE TRAFICO COLOR GRAFITO H=15CM | D102: ml | E102: 79.94 | F102: 10.5 | H102: 10.5 | I102: =+ROUND(E102*F102,2) -> 839.37 | J102: =+ROUND(E102*G102,2) -> 0 | K102: 839.37
...

Sheet ARQ TORRE
B2: ARQUITECTURA TORRE
B4: Presupuesto | C4: =OP!$B$4 -> #REF!
B5: Subpresupuesto | C5: =$B$2 -> ARQUITECTURA TORRE
B6: Cliente | C6: =OP!$B$6 -> #REF!
B7: Lugar | C7: =OP!$B$7 -> #REF!
B8: Fecha | C8: =#REF! -> #REF!
M9: Partidas abiertas
B10: ITEM | C10: DESCRIPCION | D10: UND | E10: METRADO | F10: P.U. (PEN) | G10: P.U. (USD) | H10: P.U. TOTAL (PEN) | I10: PRECIO PARCIAL (PEN) | J10: PRECIO PARCIAL (USD) | K10: PARCIAL TOTAL (PEN) | L10: TOTAL | M10: P.U. (PEN) | N10: PRECIO PARCIAL (PEN) | O10: P.U. (USD) | P10: PRECIO PARCIAL (USD)
B11: 06 | C11: =$B$2 -> ARQUITECTURA TORRE
B12: =B11+0.01 -> 6.01 | C12: MUROS Y TABIQUES | I12: =IFERROR(IF($E12=0,"",$E12*F12),"") | J12: =IFERROR(IF($E12=0,"",$E12*G12),"") | L12: 4448978.1
B13: =B12+0.0001 -> 6.0101 | C13: MUROS Y TABIQUES SILICO CALCAREOS | I13: =IFERROR(IF($E13=0,"",$E13*F13),"") | J13: =IFERROR(IF($E13=0,"",$E13*G13),"")
B14: =B13+0.000001 -> 6.010101 | C14: ALTURA < 2.60 | I14: =IFERROR(IF($E14=0,"",$E14*F14),"") | J14: =IFERROR(IF($E14=0,"",$E14*G14),"")
B15: =B14+0.00000001 -> 6.010101 | C15: LADRILLO SILICO CALCAREO TIPO P7 H<2.6M | D15: m2 | E15: 1213.6 | F15: 99.22 | H15: 99.22 | I15: =+ROUND(E15*F15,2) -> 120413.39 | J15: =+ROUND(E15*G15,2) -> 0 | K15: 120413.39 | M15: 99.22 | N15: =+M15*E15 -> 120413.39
B16: =B15+0.00000001 -> 6.010101 | C16: LADRILLO SILICO CALCAREO TIPO P10 H<2.6M | D16: m2 | E16: 12991.58 | F16: 108.22 | H16: 108.22 | I16: =+ROUND(E16*F16,2) -> 1405948.8 | J16: =+ROUND(E16*G16,2) -> 0 | K16: 1405948.8 | M16: 108.22 | N16: =+M16*E16 -> 1405948.8
B17: =B16+0.00000001 -> 6.010101 | C17: LADRILLO SILICO CALCAREO TIPO P12 H<2.6M | D17: m2 | E17: 79.21 | F17: 113.22 | H17: 113.22 | I17: =+ROUND(E17*F17,2) -> 8968.16 | J17: =+ROUND(E17*G17,2) -> 0 | K17: 8968.16 | M17: 113.22 | N17: =+M17*E17 -> 8968.1562
B18: =B17+0.00000001 -> 6.010101 | C18: LADRILLO SILICO CALCAREO TIPO P14 H<2.6M | D18: m2 | E18: 533.65 | F18: 119.22 | H18: 119.22 | I18: =+ROUND(E18*F18,2) -> 63621.75 | J18: =+ROUND(E18*G18,2) -> 0 | K18: 63621.75 | M18: 119.22 | N18: =+M18*E18 -> 63621.753
B19: =B18+0.00000001 -> 6.010101 | C19: LADRILLO SILICO CALCAREO TIPO P20 H<2.6M | D19: m2 | E19: 47.05 | F19: 198.22 | H19: 198.22 | I19: =+ROUND(E19*F19,2) -> 9326.25 | J19: =+ROUND(E19*G19,2) -> 0 | K19: 9326.25 | M19: 198.22 | N19: =+M19*E19 -> 9326.251
B20: =B19+0.00000001 -> 6.0101011 | C20: LADRILLO SILICO CALCAREO TIPO P25 H<2.6M | D20: m2 | E20: 11.54 | F20: 198.22 | H20: 198.22 | I20: =+ROUND(E20*F20,2) -> 2287.46 | J20: =+ROUND(E20*G20,2) -> 0 | K20: 2287.46 | M20: 198.22 | N20: =+M20*E20 -> 2287.4588
B21: =B20+0.00000001 -> 6.0101011 | C21: LADRILLO SILICO CALCAREO TIPO P30 H<2.6M | D21: m2 | E21: 8.17 | F21: 198.22 | H21: 198.22 | I21: =+ROUND(E21*F21,2) -> 1619.46 | J21: =+ROUND(E21*G21,2) -> 0 | K21: 1619.46 | M21: 198.22 | N21: =+M21*E21 -> 1619.4574
B22: =B21+0.00000001 -> 6.0101011 | C22: LADRILLO SILICO CALCAREO TIPO P40 H<2.6M | D22: m2 | E22: 11.15 | F22: 236.22 | H22: 236.22 | I22: =+ROUND(E22*F22,2) -> 2633.85 | J22: =+ROUND(E22*G22,2) -> 0 | K22: 2633.85 | M22: 236.22 | N22: =+M22*E22 -> 2633.853
B23: =B14+0.000001 -> 6.010102 | C23: ALTURA > 2.60 | E23: 0 | K23: 0 | M23: 0 | N23: =+M23*E23 -> 0
B24: =B23+0.00000001 -> 6.010102 | C24: LADRILLO SILICO CALCAREO TIPO P10 H>2.6M | D24: m2 | E24: 346.42 | F24: 110.22 | H24: 110.22 | I24: =+ROUND(E24*F24,2) -> 38182.41 | J24: =+ROUND(E24*G24,2) -> 0 | K24: 38182.41 | M24: 110.22 | N24: =+M24*E24 -> 38182.412
B25: =B24+0.00000001 -> 6.010102 | C25: LADRILLO SILICO CALCAREO TIPO P12 H>2.6M | D25: m2 | E25: 158.5 | F25: 116.22 | H25: 116.22 | I25: =+ROUND(E25*F25,2) -> 18420.87 | J25: =+ROUND(E25*G25,2) -> 0 | K25: 18420.87 | M25: 116.22 | N25: =+M25*E25 -> 18420.87
B26: =B25+0.00000001 -> 6.010102 | C26: LADRILLO SILICO CALCAREO TIPO P14 H>2.6M | D26: m2 | E26: 97.6 | F26: 124.22 | H26: 124.22 | I26: =+ROUND(E26*F26,2) -> 12123.87 | J26: =+ROUND(E26*G26,2) -> 0 | K26: 12123.87 | M26: 124.22 | N26: =+M26*E26 -> 12123.872
B27: =B26+0.00000001 -> 6.010102 | C27: LADRILLO SILICO CALCAREO TIPO P20 H>2.6M | D27: m2 | E27: 6.75 | F27: 208.22 | H27: 208.22 | I27: =+ROUND(E27*F27,2) -> 1405.49 | J27: =+ROUND(E27*G27,2) -> 0 | K27: 1405.49 | M27: 208.22 | N27: =+M27*E27 -> 1405.485
B28: =B27+0.00000001 -> 6.010102 | C28: LADRILLO SILICO CALCAREO TIPO P25 H>2.6M | D28: m2 | E28: 56.41 | F28: 208.22 | H28: 208.22 | I28: =+ROUND(E28*F28,2) -> 11745.69 | J28: =+ROUND(E28*G28,2) -> 0 | K28: 11745.69 | M28: 208.22 | N28: =+M28*E28 -> 11745.69
B29: =B28+0.00000001 -> 6.0101021 | C29: LADRILLO SILICO CALCAREO TIPO P30 H>2.6M | D29: m2 | E29: 13.85 | F29: 208.22 | H29: 208.22 | I29: =+ROUND(E29*F29,2) -> 2883.85 | J29: =+ROUND(E29*G29,2) -> 0 | K29: 2883.85 | M29: 208.22 | N29: =+M29*E29 -> 2883.847
B30: =B23+0.000001 -> 6.010103 | C30: CORTAFUEGO < 2.60 | E30: 0 | K30: 0 | M30: 0 | N30: =+M30*E30 -> 0
B31: =B30+0.00000001 -> 6.010103 | C31: LADRILLO SILICO CALCAREO TIPO P7 RF:2 HRS H<2.6M (ALVEOLOS COMPLETAMENTE LLENO) | D31: m2 | E31: 4.23 | F31: 105.22 | H31: 105.22 | I31: =+ROUND(E31*F31,2) -> 445.08 | J31: =+ROUND(E31*G31,2) -> 0 | K31: 445.08 | M31: 105.22 | N31: =+M31*E31 -> 445.0806
B32: =B31+0.00000001 -> 6.010103 | C32: LADRILLO SILICO CALCAREO TIPO P10 RF:2 HRS H<2.6M (ALVEOLOS COMPLETAMENTE LLENO) | D32: m2 | E32: 2265.48 | F32: 112.22 | H32: 112.22 | I32: =+ROUND(E32*F32,2) -> 254232.17 | J32: =+ROUND(E32*G32,2) -> 0 | K32: 254232.17 | M32: 112.22 | N32: =+M32*E32 -> 254232.17
B33: =B32+0.00000001 -> 6.010103 | C33: LADRILLO SILICO CALCAREO TIPO P12 RF:2 HRS H<2.6M (ALVEOLOS PARCIALMENTE LLENO) | D33: m2 | E33: 10438.42 | F33: 113.22 | H33: 113.22 | I33: =+ROUND(E33*F33,2) -> 1181837.9 | J33: =+ROUND(E33*G33,2) -> 0 | K33: 1181837.9 | M33: 113.22 | N33: =+M33*E33 -> 1181837.9
B34: =B33+0.00000001 -> 6.010103 | C34: LADRILLO SILICO CALCAREO TIPO P14 RF:2 HRS H<2.6M (ALVEOLOS PARCIALMENTE LLENO) | D34: m2 | E34: 410.97 | F34: 119.22 | H34: 119.22 | I34: =+ROUND(E34*F34,2) -> 48995.84 | J34: =+ROUND(E34*G34,2) -> 0 | K34: 48995.84 | M34: 119.22 | N34: =+M34*E34 -> 48995.843
B35: =B34+0.00000001 -> 6.010103 | C35: LADRILLO SILICO CALCAREO TIPO P20 RF:2 HRS H<2.6M (ALVEOLOS PARCIALMENTE LLENO) | D35: m2 | E35: 327.32 | F35: 210.22 | H35: 210.22 | I35: =+ROUND(E35*F35,2) -> 68809.21 | J35: =+ROUND(E35*G35,2) -> 0 | K35: 68809.21 | M35: 210.22 | N35: =+M35*E35 -> 68809.21
B36: =B35+0.00000001 -> 6.0101031 | C36: LADRILLO SILICO CALCAREO TIPO P30 RF:2 HRS H<2.6M (ALVEOLOS PARCIALMENTE LLENO) | D36: m2 | E36: 130.95 | F36: 210.22 | H36: 210.22 | I36: =+ROUND(E36*F36,2) -> 27528.31 | J36: =+ROUND(E36*G36,2) -> 0 | K36: 27528.31 | M36: 210.22 | N36: =+M36*E36 -> 27528.309
B37: =B36+0.00000001 -> 6.0101031 | C37: LADRILLO SILICO CALCAREO TIPO P35 RF:2 HRS H<2.6M (ALVEOLOS PARCIALMENTE LLENO) | D37: m2 | F37: 224.22 | H37: 224.22 | I37: =+ROUND(E37*F37,2) -> 0 | J37: =+ROUND(E37*G37,2) -> 0 | K37: 0 | M37: 224.22 | N37: =+M37*E37 -> 0
B38: =B37+0.00000001 -> 6.0101031 | C38: LADRILLO SILICO CALCAREO TIPO P40 RF:2 HRS H<2.6M (ALVEOLOS PARCIALMENTE LLENO) | D38: m2 | E38: 2.92 | F38: 224.22 | H38: 224.22 | I38: =+ROUND(E38*F38,2) -> 654.72 | J38: =+ROUND(E38*G38,2) -> 0 | K38: 654.72 | M38: 224.22 | N38: =+M38*E38 -> 654.7224
B39: =B38+0.00000001 -> 6.0101031 | C39: LADRILLO SILICO CALCAREO TIPO P45 RF:2 HRS H<2.6M (ALVEOLOS PARCIALMENTE LLENO) | D39: m2 | F39: 224.22 | H39: 224.22 | I39: =+ROUND(E39*F39,2) -> 0 | J39: =+ROUND(E39*G39,2) -> 0 | K39: 0 | M39: 224.22 | N39: =+M39*E39 -> 0
B40: =B39+0.00000001 -> 6.0101031 | C40: LADRILLO SILICO CALCAREO TIPO P50 RF:2 HRS H<2.6M (ALVEOLOS PARCIALMENTE LLENO) | D40: m2 | F40: 224.22 | H40: 224.22 | I40: =+ROUND(E40*F40,2) -> 0 | J40: =+ROUND(E40*G40,2) -> 0 | K40: 0 | M40: 224.22 | N40: =+M40*E40 -> 0
B41: =B30+0.000001 -> 6.010104 | C41: CORTAFUEGO > 2.60 | K41: 0 | M41: 0 | N41: =+M41*E41 -> 0
B42: =B39+0.00000001 -> 6.0101031 | C42: LADRILLO SILICO CALCAREO TIPO P7 RF:2 HRS H>2.6M (ALVEOLOS COMPLETAMENTE LLENO) | D42: m2 | E42: 4.88 | F42: 105.22 | H42: 105.22 | I42: =+ROUND(E42*F42,2) -> 513.47 | J42: =+ROUND(E42*G42,2) -> 0 | K42: 513.47 | M42: 105.22 | N42: =+M42*E42 -> 513.4736
B43: =B41+0.00000001 -> 6.010104 | C43: LADRILLO SILICO CALCAREO TIPO P10 RF:2 HRS H>2.6M (ALVEOLOS COMPLETAMENTE LLENO) | D43: m2 | E43: 38.11 | F43: 116.22 | H43: 116.22 | I43: =+ROUND(E43*F43,2) -> 4429.14 | J43: =+ROUND(E43*G43,2) -> 0 | K43: 4429.14 | M43: 116.22 | N43: =+M43*E43 -> 4429.1442
B44: =B43+0.00000001 -> 6.010104 | C44: LADRILLO SILICO CALCAREO TIPO P12 RF:2 HRS H>2.6M (ALVEOLOS PARCIALMENTE LLENO) | D44: m2 | E44: 660.88 | F44: 116.22 | H44: 116.22 | I44: =+ROUND(E44*F44,2) -> 76807.47 | J44: =+ROUND(E44*G44,2) -> 0 | K44: 76807.47 | M44: 116.22 | N44: =+M44*E44 -> 76807.474
B45: =B44+0.00000001 -> 6.010104 | C45: LADRILLO SILICO CALCAREO TIPO P14 RF:2 HRS H>2.6M (ALVEOLOS PARCIALMENTE LLENO) | D45: m2 | E45: 77.92 | F45: 124.22 | H45: 124.22 | I45: =+ROUND(E45*F45,2) -> 9679.22 | J45: =+ROUND(E45*G45,2) -> 0 | K45: 9679.22 | M45: 124.22 | N45: =+M45*E45 -> 9679.2224
B46: =B45+0.00000001 -> 6.010104 | C46: LADRILLO SILICO CALCAREO TIPO P20 RF:2 HRS H>2.6M (ALVEOLOS COMPLETAMENTE LLENO) | D46: m2 | E46: 17.97 | F46: 224.22 | H46: 224.22 | I46: =+ROUND(E46*F46,2) -> 4029.23 | J46: =+ROUND(E46*G46,2) -> 0 | K46: 4029.23 | M46: 224.22 | N46: =+M46*E46 -> 4029.2334
B47: =B46+0.00000001 -> 6.010104 | C47: LADRILLO SILICO CALCAREO TIPO P30 RF:2 HRS H>2.6M (ALVEOLOS COMPLETAMENTE LLENO) | D47: m2 | E47: 26.83 | F47: 232.44 | H47: 232.44 | I47: =+ROUND(E47*F47,2) -> 6236.37 | J47: =+ROUND(E47*G47,2) -> 0 | K47: 6236.37 | M47: 232.44 | N47: =+M47*E47 -> 6236.3652
B48: =B41+0.000001 -> 6.010105 | C48: ACERO DE REFUERZO | K48: 0 | M48: 0 | N48: =+M48*E48 -> 0
B49: =B48+0.00000001 -> 6.010105 | C49: ACERO DE REFUERZO FY= 4200 kg/cm2 GRADO 60 PARA TABIQUERÍA | D49: kg | E49: 44973.54 | F49: 0 | G49: 0.94 | H49: 3.53 | J49: =+ROUND(E49*G49,2) -> 42275.13 | K49: 158531.74 | N49: =+M49*E49 -> 0 | O49: 0.94 | P49: =+O49*E49 -> 42275.128
B50: =B48+0.000001 -> 6.010106 | C50: DINTELES | K50: 0 | N50: =+M50*E50 -> 0
B51: =B50+0.00000001 -> 6.010106 | C51: DINTELES DE LADRILLOS SILICO CALCAREO | D51: und | E51: 1089 | F51: 120 | H51: 120 | I51: =+ROUND(E51*F51,2) -> 130680 | J51: =+ROUND(E51*G51,2) -> 0 | K51: 130680 | M51: 120 | N51: =+M51*E51 -> 130680
B52: =B51+0.00000001 -> 6.010106 | C52: DINTELES DE LADRILLO SILICO CALCAREO RF | D52: und | E52: 42 | F52: 125 | H52: 125 | I52: =+ROUND(E52*F52,2) -> 5250 | J52: =+ROUND(E52*G52,2) -> 0 | K52: 5250 | M52: 125 | N52: =+M52*E52 -> 5250
B53: =B50+0.000001 -> 6.010107 | C53: TRABAJOS COMPLEMENTARIOS DE TABIQUERIA | K53: 0 | M53: 0 | N53: =+M53*E53 -> 0
B54: =B53+0.00000001 -> 6.010107 | C54: FORJADO DE TABLEROS | D54: und | E54: 237 | F54: 130 | H54: 130 | I54: =+ROUND(E54*F54,2) -> 30810 | J54: =+ROUND(E54*G54,2) -> 0 | K54: 30810 | M54: 130 | N54: =+M54*E54 -> 30810
B55: =B54+0.00000001 -> 6.010107 | C55: ENCOFRADO DE TUBERIAS DE MONTANTE DE VENTILACIÓN | D55: und | E55: 1812 | F55: 80 | H55: 80 | I55: =+ROUND(E55*F55,2) -> 144960 | J55: =+ROUND(E55*G55,2) -> 0 | K55: 144960 | M55: 80 | N55: =+M55*E55 -> 144960
B56: =B55+0.00000001 -> 6.010107 | C56: PASES DE MANGUERA (0.20x0.20M) | D56: und | E56: 102 | F56: 80 | H56: 80 | I56: =+ROUND(E56*F56,2) -> 8160 | J56: =+ROUND(E56*G56,2) -> 0 | K56: 8160 | M56: 80 | N56: =+M56*E56 -> 8160
B57: =B56+0.00000001 -> 6.010107 | C57: NICHOS PARA EXTRACTOR DE SSHH Y VESTIBULOS PREVIOS | D57: und | E57: 670 | F57: 80 | H57: 80 | I57: =+ROUND(E57*F57,2) -> 53600 | J57: =+ROUND(E57*G57,2) -> 0 | K57: 53600 | M57: 80 | N57: =+M57*E57 -> 53600
B58: =B898+0.0001 -> 6.3001 | C58: NICHOS PARA VALVULAS DE GAS (EN CASO DE CONSIDERARSE GAS) | D58: und | E58: 237 | F58: 80 | H58: 80 | I58: =+ROUND(E58*F58,2) -> 18960 | J58: =+ROUND(E58*G58,2) -> 0 | K58: 18960 | M58: 80 | N58: =+M58*E58 -> 18960
B59: =B53+0.000001 -> 6.010108 | C59: OTROS TABIQUERIA | K59: 0 | M59: 0 | N59: =+M59*E59 -> 0
B60: =B59+0.00000001 -> 6.010108 | C60: CASETA, ALMACEN DE HERRAMIENTAS, VESTIBULO Y BANCAS-SC TABIQUERIA | D60: glb | E60: 0 | F60: 1000 | H60: 1000 | I60: =+ROUND(E60*F60,2) -> 0 | J60: =+ROUND(E60*G60,2) -> 0 | K60: 0 | M60: 1000 | N60: =+M60*E60 -> 0
B61: =B60+0.00000001 -> 6.010108 | C61: SC PREVENCIONISTA DE RIESGO-SC TABIQUERIA | D61: mes | E61: 7 | F61: 4500 | H61: 4500 | I61: =+ROUND(E61*F61,2) -> 31500 | J61: =+ROUND(E61*G61,2) -> 0 | K61: 31500 | M61: 4500 | N61: =+M61*E61 -> 31500
B62: =B59+0.000001 -> 6.010109 | C62: MUROS Y TABIQUES KING KONG | K62: 0 | M62: 0 | N62: =+M62*E62 -> 0
B63: =B62+0.00000001 -> 6.010109 | C63: MURO DE ALBAÑILERIA KK PERIMETRO H:6.00M E:12CM | D63: m2 | E63: 108.12 | F63: 92.62 | H63: 92.62 | I63: =+ROUND(E63*F63,2) -> 10014.07 | J63: =+ROUND(E63*G63,2) -> 0 | K63: 10014.07
B64: =B63+0.00000001 -> 6.010109 | C64: MURO DE ALBAÑILERIA KK PERIMETRO H:6.00M E:15CM | D64: m2 | E64: 33.24 | F64: 100.12 | H64: 100.12 | I64: =+ROUND(E64*F64,2) -> 3327.99 | J64: =+ROUND(E64*G64,2) -> 0 | K64: 3327.99
B65: =B64+0.00000001 -> 6.010109 | C65: MURO DE ALBAÑILERIA KK E:25CM | D65: m2 | F65: 111.42 | H65: 111.42 | I65: =+ROUND(E65*F65,2) -> 0 | J65: =+ROUND(E65*G65,2) -> 0 | K65: 0
B66: =B65+0.00000001 -> 6.010109 | C66: MURO DE ALBAÑILERIA KK BANCO MEDIDORES H:4.05M E:20CM | D66: m2 | E66: 25.76 | F66: 111.42 | H66: 111.42 | I66: =+ROUND(E66*F66,2) -> 2870.18 | J66: =+ROUND(E66*G66,2) -> 0 | K66: 2870.18
B67: =B66+0.00000001 -> 6.0101091 | C67: MURO DE ALBAÑILERIA KK BANCO MEDIDORES H:2.30M E:30CM | D67: m2 | E67: 11.5 | F67: 167.88 | H67: 167.88 | I67: =+ROUND(E67*F67,2) -> 1930.62 | J67: =+ROUND(E67*G67,2) -> 0 | K67: 1930.62
B68: =B67+0.00000001 -> 6.0101091 | C68: MURO DE ALBAÑILERIA KK BANCO MEDIDORES H:3.75M E:30CM | D68: m2 | E68: 91.8 | F68: 167.88 | H68: 167.88 | I68: =+ROUND(E68*F68,2) -> 15411.38 | J68: =+ROUND(E68*G68,2) -> 0 | K68: 15411.38
B69: =B13+0.0001 -> 6.0102 | C69: MUROS Y TABIQUES DRYWALL | K69: 0
B70: =B69+0.00000001 -> 6.0102 | C70: TABIQUERIA A=0.12M - DRYWALL RF - TORRE (REGISTRO EN DUCTOS) | D70: m2 | E70: 38.58 | F70: 145 | H70: 145 | I70: =+ROUND(E70*F70,2) -> 5594.1 | J70: =+ROUND(E70*G70,2) -> 0 | K70: 5594.1
B71: =B70+0.00000001 -> 6.0102 | C71: DINTELES DE DRYWALL (SOBRE LAVANDERIAS) | D71: ml | E71: 258.27 | F71: 105 | H71: 105 | I71: =+ROUND(E71*F71,2) -> 27118.35 | J71: =+ROUND(E71*G71,2) -> 0 | K71: 27118.35
B72: =B71+0.00000001 -> 6.0102 | C72: DINTEL DE DRYWALL ST (MONTANTES DE DUCTO) | D72: ml | E72: 59.64 | F72: 115 | H72: 115 | I72: =+ROUND(E72*F72,2) -> 6858.6 | J72: =+ROUND(E72*G72,2) -> 0 | K72: 6858.6
B73: =B72+0.00000001 -> 6.0102 | C73: DINTELES DE DRYWALL (VENTANAS Y/O FACHADA) | D73: ml | E73: 1001.49 | F73: 105 | H73: 105 | I73: =+ROUND(E73*F73,2) -> 105156.45 | J73: =+ROUND(E73*G73,2) -> 0 | K73: 105156.45
B74: =B73+0.00000001 -> 6.0102 | C74: SOBRE MURO BAJO ESP.: 0.10M DRYWALL RH (SSHH Y/O COCINAS) | D74: und | E74: 586 | F74: 125 | H74: 125 | I74: =+ROUND(E74*F74,2) -> 73250 | J74: =+ROUND(E74*G74,2) -> 0 | K74: 73250
B75: =B74+0.00000001 -> 6.0102001 | C75: ESTRUCTURA TIPO MARCO PARA PUERTA METALICA DE INGRESO A ESTACIONAMIENTOS PM-02 | D75: m2 | E75: 6.5 | F75: 1550 | H75: 1550 | I75: =+ROUND(E75*F75,2) -> 10075 | J75: =+ROUND(E75*G75,2) -> 0 | K75: 10075
B76: =B75+0.00000001 -> 6.0102001 | C76: ESTRUCTURA DE DRYWALL PARA CERCO PERIMETRAL | D76: m2 | E76: 155.85 | F76: 180 | H76: 180 | I76: =+ROUND(E76*F76,2) -> 28053 | J76: =+ROUND(E76*G76,2) -> 0 | K76: 28053
B77: =B76+0.00000001 -> 6.0102001 | C77: ESTRUCTURA PARA SOPORTE DE DRYWALL | D77: m2 | E77: 155.85 | F77: 130 | H77: 130 | I77: =+ROUND(E77*F77,2) -> 20260.5 | J77: =+ROUND(E77*G77,2) -> 0 | K77: 20260.5
B78: =B69+0.0001 -> 6.0103 | C78: PARAPETOS Y SARDINELES | K78: 0
B79: =B78+0.00000001 -> 6.0103 | C79: PARAPETOS EN VENTANAS (E=0.10M, H=VARIADAS) | D79: m2 | F79: 108.22 | H79: 108.22 | I79: =+ROUND(E79*F79,2) -> 0 | J79: =+ROUND(E79*G79,2) -> 0 | K79: 0
B80: =B79+0.00000001 -> 6.0103 | C80: PARAPETO E=0.10M, H=0.40M/0.50M (JARDINERA 1P Y AZOTEA) | D80: m2 | F80: 108.22 | H80: 108.22 | I80: =+ROUND(E80*F80,2) -> 0 | J80: =+ROUND(E80*G80,2) -> 0 | K80: 0
B81: =B80+0.00000001 -> 6.0103 | C81: PARAPETO E=0.10M, H=0.60M (JARDINERA FACHADA INTERNA) | D81: m2 | F81: 108.22 | H81: 108.22 | I81: =+ROUND(E81*F81,2) -> 0 | J81: =+ROUND(E81*G81,2) -> 0 | K81: 0
B82: =B81+0.00000001 -> 6.0103 | C82: PARAPETO E=0.10M, H=0.90M (JARDINERA 1P Y AZOTEA) | D82: m2 | F82: 108.22 | H82: 108.22 | I82: =+ROUND(E82*F82,2) -> 0 | J82: =+ROUND(E82*G82,2) -> 0 | K82: 0
B83: =B82+0.00000001 -> 6.0103 | C83: PARAPETO E=0.12M, H=1.89M (JARDINERA 1P) | D83: m2 | F83: 113.22 | H83: 113.22 | I83: =+ROUND(E83*F83,2) -> 0 | J83: =+ROUND(E83*G83,2) -> 0 | K83: 0
B84: =B83+0.00000001 -> 6.0103001 | C84: PARAPETO E=0.10M, H=1.20M/1.30M (AZOTEA - JARDINERA) | D84: m2 | F84: 108.22 | H84: 108.22 | I84: =+ROUND(E84*F84,2) -> 0 | J84: =+ROUND(E84*G84,2) -> 0 | K84: 0
B85: =B84+0.00000001 -> 6.0103001 | C85: PARAPETO E=0.15M, H=1.30M (AZOTEA -JARDINERA) | D85: m2 | F85: 119.22 | H85: 119.22 | I85: =+ROUND(E85*F85,2) -> 0 | J85: =+ROUND(E85*G85,2) -> 0 | K85: 0
B86: =B85+0.00000001 -> 6.0103001 | C86: SARDINELES DUCHAS (A=0.10M) , H=0.15M | D86: ml | E86: 566.93 | F86: 51.03 | G86: 1.13 | H86: 55.27 | I86: =+ROUND(E86*F86,2) -> 28930.44 | J86: =+ROUND(E86*G86,2) -> 640.63 | K86: 31332.8
B87: =B86+0.00000001 -> 6.0103001 | C87: SARDINEL LAVANDERIAS H=0.10M, E=0.10M | D87: ml | E87: 217.67 | F87: 44.43 | G87: 0.75 | H87: 47.24 | I87: =+ROUND(E87*F87,2) -> 9671.08 | J87: =+ROUND(E87*G87,2) -> 163.25 | K87: 10283.27
B88: =B87+0.00000001 -> 6.0103001 | C88: SARDINEL TECHO H=0.10M, E=0.10M | D88: ml | F88: 44.43 | G88: 0.75 | H88: 47.24 | I88: =+ROUND(E88*F88,2) -> 0 | J88: =+ROUND(E88*G88,2) -> 0 | K88: 0
B89: =B88+0.00000001 -> 6.0103001 | C89: SARDINEL DUCTOS TECNICOS H=0.10M, E=0.12M | D89: ml | E89: 64.63 | F89: 45.93 | G89: 0.9 | H89: 49.31 | I89: =+ROUND(E89*F89,2) -> 2968.46 | J89: =+ROUND(E89*G89,2) -> 58.17 | K89: 3186.6
B90: =B89+0.00000001 -> 6.0103001 | C90: SARDINEL DUCTOS JARDINES H=0.20M, E=0.10M | D90: ml | F90: 57.63 | G90: 1.5 | H90: 63.26 | I90: =+ROUND(E90*F90,2) -> 0 | J90: =+ROUND(E90*G90,2) -> 0 | K90: 0
B91: =B90+0.00000001 -> 6.0103001 | C91: SARDINEL DUCTOS JARDINES H=0.25M, E=0.10M | D91: ml | F91: 64.22 | G91: 1.88 | H91: 71.27 | I91: =+ROUND(E91*F91,2) -> 0 | J91: =+ROUND(E91*G91,2) -> 0 | K91: 0
B92: =B91+0.00000001 -> 6.0103001 | C92: SARDINEL EN VENTANAS H:0.30M (E=10CM) | D92: ml | E92: 13.99 | F92: 70.8 | G92: 2.26 | H92: 79.28 | I92: =+ROUND(E92*F92,2) -> 990.49 | J92: =+ROUND(E92*G92,2) -> 31.62 | K92: 1109.07
B93: =B92+0.00000001 -> 6.0103001 | C93: SARDINEL DUCTOS JARDINES H=0.35M, E=0.10M | D93: ml | E93: 98.3 | F93: 77.41 | G93: 2.63 | H93: 87.27 | I93: =+ROUND(E93*F93,2) -> 7609.4 | J93: =+ROUND(E93*G93,2) -> 258.53 | K93: 8578.89
B94: =B93+0.00000001 -> 6.0103002 | C94: SARDINEL DE JARDINERA h=40cm (TERRAZA P1, AREA PARRILLAS) | D94: ml | E94: 18.78 | F94: 81.23 | G94: 3.01 | H94: 92.52 | I94: =+ROUND(E94*F94,2) -> 1525.5 | J94: =+ROUND(E94*G94,2) -> 56.53 | K94: 1737.49
B95: =B94+0.00000001 -> 6.0103002 | C95: SARDINEL DE JARDINERA h=45cm (TERRAZA GIMNASIO) | D95: ml | E95: 14.42 | F95: 86.62 | G95: 3.38 | H95: 99.3 | I95: =+ROUND(E95*F95,2) -> 1249.06 | J95: =+ROUND(E95*G95,2) -> 48.74 | K95: 1431.84
B96: =B95+0.00000001 -> 6.0103002 | C96: SARDINEL DE JARDINERA INCLINADA h=60cm (COWORKING) | D96: ml | E96: 5.3 | F96: 103.07 | G96: 4.51 | H96: 119.98 | I96: =+ROUND(E96*F96,2) -> 546.27 | J96: =+ROUND(E96*G96,2) -> 23.9 | K96: 635.9
B97: =B96+0.00000001 -> 6.0103002 | C97: SARDINEL DE JARDINERA h=72cm (INGRESO) | D97: ml | E97: 25.91 | F97: 111.92 | G97: 5.41 | H97: 132.21 | I97: =+ROUND(E97*F97,2) -> 2899.85 | J97: =+ROUND(E97*G97,2) -> 140.17 | K97: 3425.49
B98: =B97+0.00000001 -> 6.0103002 | C98: SARDINEL PARA BARANDA AZOTEA H=10cm (DECK PISCINA) | D98: ml | E98: 48.02 | F98: 45.93 | G98: 0.9 | H98: 49.31 | I98: =+ROUND(E98*F98,2) -> 2205.56 | J98: =+ROUND(E98*G98,2) -> 43.22 | K98: 2367.64
B99: =B98+0.00000001 -> 6.0103002 | C99: MURETE PARA BARANDA AZOTEA H=30cm (FACAHDA INTERIOR) | D99: ml | E99: 39.57 | F99: 70.8 | G99: 2.26 | H99: 79.28 | I99: =+ROUND(E99*F99,2) -> 2801.56 | J99: =+ROUND(E99*G99,2) -> 89.43 | K99: 3136.92
B100: =B99+0.00000001 -> 6.0103002 | C100: MURETE PARA BARANDA AZOTEA H=40cm (FACHADA EXTERIOR) | D100: ml | E100: 35.98 | F100: 81.23 | G100: 3.01 | H100: 92.52 | I100: =+ROUND(E100*F100,2) -> 2922.66 | J100: =+ROUND(E100*G100,2) -> 108.3 | K100: 3328.79
B101: =B78+0.0001 -> 6.0104 | C101: ESTRUCTURAS DE CONCRETO (TABLEROS, BANCAS) | K101: 0
B102: =B101+0.00000001 -> 6.0104 | C102: MESON DE CONCRETO A=60cm (PET SPA) | D102: ml | E102: 2.63 | F102: 509.56 | G102: 11.28 | H102: 551.86 | I102: =+ROUND(E102*F102,2) -> 1340.14 | J102: =+ROUND(E102*G102,2) -> 29.67 | K102: 1451.4
...

Sheet INSTALACIONES
A2: INSTALACIONES
H3: T.C | I3: 3.75
A4: Presupuesto | B4: JUAN DE ALIAGA 750
A5: Subpresupuesto | B5: INSTALACIONES
A6: Cliente | B6: : V&V Bravo S.A.C
A7: Lugar
A8: ITEM | B8: DESCRIPCION | C8: UND | D8: CANTIDAD | E8: P.U (S/.) | F8: P.U ($.) | G8: PARCIAL (S/.) | H8: PARCIAL ($) | I8: TOTAL
A9: 01.01 | B9: INTERCOMUNICADORES | I9: 15833.975
A10: 1.01.01 | B10: DISPOSITIVOS PRINCIPALES DE COMUNICACIÓN | G10: =+E10*D10 -> 0 | H10: =+F10*D10 -> 0 | I10: 0
A11: 1.01.02 | B11: Central de conserjería de audio/vídeo con pantalla LCD 7" | C11: Und. | D11: 1 | F11: 891.3362 | G11: =+E11*D11 -> 0 | H11: =+F11*D11 -> 891.3362 | I11: 3342.5107
A12: 1.01.03 | B12: Placa de Calle Digital sólo audio | C12: Und. | D12: 1 | F12: 318.3404 | G12: =+E12*D12 -> 0 | H12: =+F12*D12 -> 318.3404 | I12: 1193.7765
A13: 1.01.04 | B13: Intercomunicador tipo telefono Sprint L2 | C13: Und. | D13: 251 | F13: 35.9456 | G13: =+E13*D13 -> 0 | H13: =+F13*D13 -> 9022.3456 | I13: 33833.796
A14: 1.01.05 | B14: COMPLEMENTOS DEL SISTEMA | G14: =+E14*D14 -> 0 | H14: =+F14*D14 -> 0 | I14: 0
A15: 1.01.06 | B15: Interfaz de expansión de anexos/longitud | C15: Und. | D15: 3 | F15: 287.5272 | G15: =+E15*D15 -> 0 | H15: =+F15*D15 -> 862.5816 | I15: 3234.681
A16: 1.01.07 | B16: Fuente de poder de 1.2A para sistemas de audio/video | C16: Und. | D16: 4 | F16: 112.1326 | G16: =+E16*D16 -> 0 | H16: =+F16*D16 -> 448.5304 | I16: 1681.989
A17: 1.01.08 | B17: Configuradores (Paquete de 10 piezas) | C17: Und. | D17: 75 | F17: 8.6668 | G17: =+E17*D17 -> 0 | H17: =+F17*D17 -> 650.01 | I17: 2437.5375
A18: 1.01.09 | B18: MATERIALES | C18: Glb. | D18: 1 | F18: 2451.4354 | G18: =+E18*D18 -> 0 | H18: =+F18*D18 -> 2451.4354 | I18: 9192.8827
A19: 1.01.10 | B19: Cable de par trenzado para difusión sonora | G19: =+E19*D19 -> 0 | H19: =+F19*D19 -> 0 | I19: 0
A20: 1.01.11 | B20: Cable UTP cat. 5e 100% cobre para distribución | G20: =+E20*D20 -> 0 | H20: =+F20*D20 -> 0 | I20: 0
A21: 1.01.12 | B21: Elementos auxiliares para la adecuacion de sistemas (autorroscantes, tarugos, cintillos, terminales, etc) | G21: =+E21*D21 -> 0 | H21: =+F21*D21 -> 0 | I21: 0
A22: 1.01.13 | B22: MANO DE OBRA | C22: Glb. | D22: 1 | F22: 920.2168 | G22: =+E22*D22 -> 0 | H22: =+F22*D22 -> 920.2168 | I22: 3450.813
A23: 1.01.14 | B23: Enrutamiento y verificación de canalizaciones | G23: =+E23*D23 -> 0 | H23: =+F23*D23 -> 0 | I23: 0
A24: 1.01.15 | B24: Cableado de bus de comunicación | G24: =+E24*D24 -> 0 | H24: =+F24*D24 -> 0 | I24: 0
A25: 1.01.16 | B25: Instalación de centralitas | G25: =+E25*D25 -> 0 | H25: =+F25*D25 -> 0 | I25: 0
A26: 1.01.17 | B26: Instalación de portero digital y unidades internas | G26: =+E26*D26 -> 0 | H26: =+F26*D26 -> 0 | I26: 0
A27: 1.01.18 | B27: Instalación de módulo alimentadores y extensiones. | G27: =+E27*D27 -> 0 | H27: =+F27*D27 -> 0 | I27: 0
A28: 1.01.19 | B28: Configuración de aplicación en centralita | G28: =+E28*D28 -> 0 | H28: =+F28*D28 -> 0 | I28: 0
A29: 1.01.20 | B29: Pruebas de funcionamiento y puesta en marcha | G29: =+E29*D29 -> 0 | H29: =+F29*D29 -> 0 | I29: 0
A30: 1.01.21 | B30: Capacitación y manual de uso | G30: =+E30*D30 -> 0 | H30: =+F30*D30 -> 0 | I30: 0
A31: 1.01.22 | B31: TRANSPORTE, SEGUROS Y GASTOS GENERALES | C31: Glb. | D31: 1 | F31: 269.1784 | G31: =+E31*D31 -> 0 | H31: =+F31*D31 -> 269.1784 | I31: 1009.419
A32: 1.01.23 | B32: Examen médico ocupacional, SCTR salud - Pensión y EPPs | G32: =+E32*D32 -> 0 | H32: =+F32*D32 -> 0 | I32: 0
A33: 1.01.24 | B33: Transporte de Personal, Herramientas y Materiales | G33: =+E33*D33 -> 0 | H33: =+F33*D33 -> 0 | I33: 0
A34: 01.02 | B34: DETECCION CONTRAINCENDIOS | I34: 47250.565
A35: 1.02.01 | B35: PANEL DE ALARMA CONTRA INCENDIOS Y COMPLEMENTOS
A36: 1.02.02 | B36: Panel de Detección y Alarma Contra Incendio Direccionable con Certificado UL-864, para sistemas DACI en edificios. | C36: Und. | D36: 1 | F36: 739.7352 | G36: =+E36*D36 -> 0 | H36: =+F36*D36 -> 739.7352 | I36: 2774.007
A37: 1.02.03 | B37: Tarjeta de expasión de direcciones dual 250det/250mod | C37: Und. | D37: 2 | F37: 904.7464 | G37: =+E37*D37 -> 0 | H37: =+F37*D37 -> 1809.4928 | I37: 6785.598
A38: 1.02.04 | B38: Teclado LCD para control remoto | C38: Und. | D38: 2 | F38: 389.3992 | G38: =+E38*D38 -> 0 | H38: =+F38*D38 -> 778.7984 | I38: 2920.494
A39: 1.02.05 | B39: Batería 12 Voltios 17 Amperios | C39: Und. | D39: 2 | F39: 45.6596 | G39: =+E39*D39 -> 0 | H39: =+F39*D39 -> 91.3192 | I39: 342.447
A40: 1.02.06
A41: 1.02.07 | B41: DISPOSITIVOS DE INICIACIÓN
A42: 1.02.08 | B42: Detector de Humo Direccionable UL | C42: Und. | D42: 237 | F42: 34.96 | G42: =+E42*D42 -> 0 | H42: =+F42*D42 -> 8285.52 | I42: 31070.7
A43: 1.02.09 | B43: Detector de Temperatura Direccionable UL | C43: Und. | D43: 237 | F43: 25.8428 | G43: =+E43*D43 -> 0 | H43: =+F43*D43 -> 6124.7436 | I43: 22967.788
A44: 1.02.10 | B44: Base estándar para detectores | C44: Und. | D44: 474 | F44: 4.1032 | G44: =+E44*D44 -> 0 | H44: =+F44*D44 -> 1944.9168 | I44: 7293.438
A45: 1.02.11 | B45: Estación Manual convencional. Certificado UL | C45: Und. | D45: 68 | F45: 23.046 | G45: =+E45*D45 -> 0 | H45: =+F45*D45 -> 1567.128 | I45: 5876.73
A46: 1.02.12 | B46: Detector de Humo Convencional. Certificado UL | C46: Und. | D46: 272 | F46: 13.1008 | G46: =+E46*D46 -> 0 | H46: =+F46*D46 -> 3563.4176 | I46: 13362.816
A47: 1.02.13 | B47: Sensor de aniego + sonda | C47: Und. | D47: 1 | F47: 151.4964 | G47: =+E47*D47 -> 0 | H47: =+F47*D47 -> 151.4964 | I47: 568.1115
A48: 1.02.14 | C48: Und.
A49: 1.02.15 | B49: DISPOSITIVOS DE NOTIFICACIÓN | C49: Und.
A50: 1.02.16 | B50: Sirena con luz estroboscópica 12V/24V, certificada UL | C50: Und. | D50: 132 | F50: 33.6904 | G50: =+E50*D50 -> 0 | H50: =+F50*D50 -> 4447.1328 | I50: 16676.748
A51: 1.02.17 | B51: Fuente de alimentación para sirenas -Booster NAC de 10 Amp | C51: Und. | D51: 1 | F51: 492.8992 | G51: =+E51*D51 -> 0 | H51: =+F51*D51 -> 492.8992 | I51: 1848.372
A52: 1.02.18 | B52: Baterias 9 AH,12 Volt | C52: Und. | D52: 2 | F52: 29.6608 | G52: =+E52*D52 -> 0 | H52: =+F52*D52 -> 59.3216 | I52: 222.456
A53: 1.02.19
A54: 1.02.20 | B54: MÓDULOS
A55: 1.02.21 | B55: Módulo de monitoreo dual para válvula de sectorización y sensor de flujo | C55: Und. | D55: 53 | F55: 46.9292 | G55: =+E55*D55 -> 0 | H55: =+F55*D55 -> 2487.2476 | I55: 9327.1785
A56: 1.02.22 | B56: Módulo de monitoreo para zonificación de detectores convencionales* 33 zonas (1 zona por cada sótano / 1 zona por área común en pisos) | C56: Und. | D56: 33 | F56: 26.8088 | G56: =+E56*D56 -> 0 | H56: =+F56*D56 -> 884.6904 | I56: 3317.589
A57: 1.02.23 | B57: Módulo de monitoreo para interconexion en cuarto de bomba * 1 para cada Valvula de succión/ 1 descarga / 1 prueba | C57: Und. | D57: 3 | F57: 26.8088 | G57: =+E57*D57 -> 0 | H57: =+F57*D57 -> 80.4264 | I57: 301.599
A58: 1.02.24 | B58: Módulo de monitoreo para interconexion con Tablero ACI * 2 en tablero BACI para monitoreo de encendido / falla / * 1 para monitoreo de sensor de aniego | C58: Und. | D58: 3 | F58: 26.8088 | G58: =+E58*D58 -> 0 | H58: =+F58*D58 -> 80.4264 | I58: 301.599
A59: 1.02.25 | B59: Módulo de control para interconexión con Grupo Electrógeno * 1 en Tablero TC-TTA para el control del sistema | C59: Und. | D59: 2 | F59: 36.9472 | G59: =+E59*D59 -> 0 | H59: =+F59*D59 -> 73.8944 | I59: 277.104
A60: 1.02.26 | B60: Módulo de control para interconexión con sistema Extracción de CO * 1 en Tablero TC-CO para el control del sistema | C60: Und. | D60: 6 | F60: 36.9472 | G60: =+E60*D60 -> 0 | H60: =+F60*D60 -> 221.6832 | I60: 831.312
A61: 1.02.27 | B61: Módulo de control para interconexión con sist. De ascensores * 3 en Tablero de ascensor 1/2 para control de funcion de emergencia 1/2/3 * 3 en Tablero de ascensor 3/4 para control de funcion de emergencia 1/2/3 | C61: Und. | D61: 6 | F61: 36.9472 | G61: =+E61*D61 -> 0 | H61: =+F61*D61 -> 221.6832 | I61: 831.312
A62: 1.02.28 | B62: Módulo de control para interconexión con sistema presurizado y vest. Previo * 4 en Tableros de ventilación para control de encendido y apagado | C62: Und. | D62: 4 | F62: 36.9472 | G62: =+E62*D62 -> 0 | H62: =+F62*D62 -> 147.7888 | I62: 554.208
A63: 1.02.29 | B63: Módulo de señal para zonificación de sirenas por nivel | C63: Und. | D63: 32 | F63: 39.5876 | G63: =+E63*D63 -> 0 | H63: =+F63*D63 -> 1266.8032 | I63: 4750.512
A64: 1.02.30
A65: 1.02.31 | B65: MATERIALES | C65: Glb. | D65: 1 | F65: 9184.5624 | G65: =+E65*D65 -> 0 | H65: =+F65*D65 -> 9184.5624 | I65: 34442.109
A66: 1.02.32 | B66: Cable cobre solido de incendio 2X18 / 2x16 FPL Cajas de 300m. Listado UL
A67: 1.02.33 | B67: Elementos auxiliares para la adecuación de Sistemas (autorroscantes, tarugos, cintillos, terminales, etc)
A68: 1.02.34 | B68: MANO DE OBRA | C68: Glb. | D68: 1 | F68: 2032.5744 | G68: =+E68*D68 -> 0 | H68: =+F68*D68 -> 2032.5744 | I68: 7622.154
A69: 1.02.35 | B69: Enrutamiento y verificación de canalizaciones
A70: 1.02.36 | B70: Cableado en montante de comunicación y energía
A71: 1.02.37 | B71: Cableado horizontal para dispositivosCableado horizontal para dispositivos
A72: 1.02.38 | B72: Instalación de equipos de iniciación: Detectores y estaciones manuales
A73: 1.02.39 | B73: Instalación de equipos de notificación: Sirenas y módulos.
A74: 1.02.40 | B74: Instalación y distribución de Fuente NAC para sirenas
A75: 1.02.41 | B75: Instalación de Panel DACI y complementos
A76: 1.02.42 | B76: Configuración de panel, pruebas de funcionamiento y puesta en marcha
A77: 1.02.43 | B77: TRANSPORTE, SEGUROS Y GASTOS GENERALES | C77: Glb. | D77: 1 | F77: 512.8632 | G77: =+E77*D77 -> 0 | H77: =+F77*D77 -> 512.8632 | I77: 1923.237
A78: 1.02.44 | B78: Examen médico ocupacional, SCTR salud - Pensión y EPPs
A79: 1.02.45 | B79: Transporte de Personal, Herramientas y Materiales
A80: 01.03 | B80: SISTEMA CCTV HIKVISION | I80: 60348.12
A81: 1.03.01 | B81: CÁMARAS Y COMPLEMENTO
A82: 1.03.02 | B82: NVR 32 CANALES HIKVSION | C82: Und. | D82: 2 | E82: 1316.95 | F82: 0 | G82: =+E82*D82 -> 2633.9 | H82: =+F82*D82 -> 0 | I82: 2633.9
A83: 1.03.03 | B83: NVR 16 CANALES HIKVISION | C83: Und. | D83: 1 | E83: 1135.13 | F83: 0 | G83: =+E83*D83 -> 1135.13 | H83: =+F83*D83 -> 0 | I83: 1135.13
A84: 1.03.04 | B84: DISCO DURO 8TB WESTERN DIGITAL | C84: Und. | D84: 3 | E84: 1031.94 | F84: 0 | G84: =+E84*D84 -> 3095.82 | H84: =+F84*D84 -> 0 | I84: 3095.82
A85: 1.03.06 | B85: EQUIPAMIENTO
A86: 1.03.07 | B86: TUBO IR BULLET 2MP LENTE 2.8MM | C86: Und. | D86: 11 | E86: 186.73 | G86: =+E86*D86 -> 2054.03 | H86: =+F86*D86 -> 0 | I86: 2054.03
A87: 1.03.08 | B87: DOMO IP CON IR EXTERIOR 2MP 2.8MM | C87: Und. | D87: 64 | E87: 186.73 | G87: =+E87*D87 -> 11950.72 | H87: =+F87*D87 -> 0 | I87: 11950.72
A88: 1.03.09 | B88: SWITCH 24PTOS POE | C88: Und. | D88: 3 | E88: 1371.01 | G88: =+E88*D88 -> 4113.03 | H88: =+F88*D88 -> 0 | I88: 4113.03
A89: 1.03.10 | B89: SWITCH 8PTOS POE | C89: Und. | D89: 1 | E89: 712.53 | G89: =+E89*D89 -> 712.53 | H89: =+F89*D89 -> 0 | I89: 712.53
A90: 1.03.11 | B90: ORDENADORES DE CABLE | C90: Und. | D90: 5 | E90: 127.76 | G90: =+E90*D90 -> 638.8 | H90: =+F90*D90 -> 0 | I90: 638.8
A91: 1.03.12 | B91: GABINETE 20 RU | C91: Und. | D91: 1 | E91: 768 | G91: =+E91*D91 -> 768 | H91: =+F91*D91 -> 0 | I91: 768
A92: 1.03.13 | B92: MONITOR DE 32" LG | C92: Und. | D92: 6 | E92: 958.23 | G92: =+E92*D92 -> 5749.38 | H92: =+F92*D92 -> 0 | I92: 5749.38
A93: 1.03.13 | B93: ESTABILIZADOR 1000W | C93: Und. | D93: 1 | E93: 221.13 | G93: =+E93*D93 -> 221.13 | H93: =+F93*D93 -> 0 | I93: 221.13
A94: 1.03.13 | B94: SPLITER HDMI | C94: Und. | D94: 3 | E94: 171.99 | G94: =+E94*D94 -> 515.97 | H94: =+F94*D94 -> 0 | I94: 515.97
A95: 1.03.13 | B95: EXTENSOR HDMI | C95: Und. | D95: 6 | E95: 171.99 | G95: =+E95*D95 -> 1031.94 | H95: =+F95*D95 -> 0 | I95: 1031.94
A96: 1.03.13 | B96: REGLETTA DE PODER | C96: Und. | D96: 2 | E96: 221.13 | G96: =+E96*D96 -> 442.26 | H96: =+F96*D96 -> 0 | I96: 442.26
A97: 1.03.15 | B97: ELEMENTOS AUXILIARES PARA LA ADECUACIÓN DE SISTEMA, AUTORROSCANTES, CINTILLOS, TERMINALES, ETC | C97: glb | D97: 1 | E97: 1228.5 | G97: =+E97*D97 -> 1228.5 | H97: =+F97*D97 -> 0 | I97: 1228.5
... A100: 1.03.25 | B100: TRANSPORTE, SEGUROS Y GASTOS GENERALES | C100: Glb. | D100: 1 | E100: 1600 | G100: =+E100*D100 -> 1600 | H100: =+F100*D100 -> 0 | I100: 1600
A101: 1.05 | B101: SISTEMA DE GAS | I101: 293406
A102: 01.01.01.05 | B102: Sistema de gas 2 puntos (cocina/horno - therma) 237 Departamentos Redes internas PealPe Montantes de cobre | C102: glb | D102: 1 | E102: 293406 | G102: =+E102*D102 -> 293406 | H102: =+F102*D102 -> 0 | I102: 293406
A103: 01.06 | B103: PANELES SOLARES | I103: 9140
...

Sheet ACIySPC
A2: CUARTO DE BOMBAS - ACI
H3: T.C | I3: 3.75
A4: Presupuesto | B4: JUAN DE ALIAGA 750
A5: Subpresupuesto | B5: EQUIPAMIENTO CUARTO DE BOMBAS
A6: Cliente | B6: : V&V Bravo S.A.C | F6: Costo al | G6: 45538
A7: Lugar
A8: ITEM | B8: DESCRIPCION | C8: UND | D8: CANTIDAD | E8: P.U (S/.) | F8: P.U ($.) | G8: PARCIAL (S/.) | H8: PARCIAL ($) | I8: TOTAL
A9: 1.00 | B9: SISTEMA DE PRESION CONSTANTE Y SUMIDEROS | I9: =SUM(H11:H19) -> 66276.881
A10: 1.01 | B10: SUMINISTRO E INSTALACIÓN SISTEMA DE PRESIÓN CONSTANTE Y VELOCIDAD VARIABLE ALTA PRESIÓN - 03 UND
A11: 1.02 | B11: ELECTROBOMBA MULTIETAPICA VERTICAL MARCA: BARNES MODELO: VSE 20 6-150 PUNTO DE OPERACIÓN: 6.78 lps // 68.5 m Potencia: 15 HP IMPULSOR Y VOLUTA EN INOX 304 TENSION DE TRABAJO : 220 V / TRIFÁSICO / 60 HZ SUCCION (2 1/2") DESCARGA (2 1/2") TABLERO VARIADOR 3X15 HP CON PLC 220 V 3F PLC Marca: Schneider 03 Variadores Marca: LS | C11: Glb | D11: 1 | F11: 14357.304 | G11: =+E11*D11 -> 0 | H11: =+F11*D11 -> 14357.304 | I11: =+G11+(H11*$I$3) -> 53839.89
A12: 1.09 | B12: SUMINISTRO E INSTALACIÓN SISTEMA DE PRESIÓN CONSTANTE Y VELOCIDAD VARIABLE MEDIA PRESIÓN - 03 UND
A13: 1.10 | B13: ELECTROBOMBA MULTIETAPICA VERTICAL MARCA: BARNES MODELO: VSE 15 8-150 PUNTO DE OPERACIÓN: 4.95 lps // 88.16 m Potencia: 15 HP IMPULSOR Y VOLUTA EN INOX 304 TENSION DE TRABAJO : 220 V / TRIFÁSICO / 60 HZ SUCCION (2 1/2") DESCARGA (2 1/2") TABLERO VARIADOR 3X15 HP CON PLC 220 V 3F PLC Marca: Schneider 03 Variadores Marca: LS | C13: Glb | D13: 1 | F13: 13549.401 | G13: =+E13*D13 -> 0 | H13: =+F13*D13 -> 13549.401 | I13: =+G13+(H13*$I$3) -> 50810.253
A14: 1.17 | B14: SUMINISTRO E INSTALACIÓN SISTEMA DE PRESIÓN CONSTANTE Y VELOCIDAD VARIABLE BAJA PRESIÓN - 03 UND
A15: 1.18 | B15: ELECTROBOMBA MULTIETAPICA VERTICAL MARCA: BARNES MODELO: VSE 15 8-150 PUNTO DE OPERACIÓN: 4.63 lps // 107.8 m Potencia: 15 HP IMPULSOR Y VOLUTA EN INOX 304 TENSION DE TRABAJO : 220 V / TRIFÁSICO / 60 HZ SUCCION (2 1/2") DESCARGA (2 1/2") TABLERO VARIADOR 3X15 HP CON PLC 220 V 3F PLC Marca: Schneider 03 Variadores Marca: LS | C15: Glb | D15: 1 | F15: 14619.467 | G15: =+E15*D15 -> 0 | H15: =+F15*D15 -> 14619.467 | I15: =+G15+(H15*$I$3) -> 54823.002
A16: 1.25 | B16: SUMINISTRO E INSTALACIÓN SISTEMA DE BOMBEO DE SUMIDERO - 02 UND
A17: 1.26 | B17: BOMBA SUMERGIBLE PARA AGUAS RESIDUALES MARCA: BARNES MODELO: NHE 3 30-2 PUNTO DE OPERACIÓN: 4.13 lps // 26.4 m Potencia: 3 HP CUERPO, CARCASA, IMPULSOR: Hierro fundido ASTM A-48, Clase 30 CON IMPULSOR DE 5.118" DESCARGA: 3" | C17: Glb | D17: 1 | F17: 3455.4312 | G17: =+E17*D17 -> 0 | H17: =+F17*D17 -> 3455.4312 | I17: =+G17+(H17*$I$3) -> 12957.867
A18: 1.33 | B18: Instalación de sistema de presión constante de 09 bombas con succión de 6", descarga de 4"; manifold de succión de 6", manifold de descarga de 4" - Se considera la succión en Inoxidable 304. - Manifold en Acero Galvanizado. | C18: Glb | D18: 1 | F18: 17568.366 | G18: =+E18*D18 -> 0 | H18: =+F18*D18 -> 17568.366 | I18: =+G18+(H18*$I$3) -> 65881.374
A19: 1.34 | B19: Instalación en sistema de sumidero de 02 bombas, con descarga de 3" | C19: Glb | D19: 1 | F19: 2726.9112 | G19: =+E19*D19 -> 0 | H19: =+F19*D19 -> 2726.9112 | I19: =+G19+(H19*$I$3) -> 10225.917
A20: 2.00 | B20: EQUIPAMIENTO DE AGUA CONTRAINCENDIO - ELECTROBOMBA LISTADA | I20: =SUM(H22:H30) -> 55414.94
A21: 2.01 | B21: Equipo de Bombeo Contraincendios Electrobomba 500GPM @ 245PSI 125HP (LISTADA Y APROBADA)
A22: 2.02 | B22: ElectrobombaContraIncendiosTipoSPLITCASEmarcaPATTERSONmodelo5x3DMDseleccionada a 500GPM a 245 PSI de 125HP 230V 3Ø 60HZ | C22: Glb | D22: 1 | F22: 35945.5 | G22: =+E22*D22 -> 0 | H22: =+F22*D22 -> 35945.5 | I22: =+G22+(H22*$I$3) -> 134795.62
A23: 2.03 | B23: TableroEstrellatrianguloFiretrolUL/FMmodeloFTA1300-AM125A para motor 125HP/230V/3Ø/60HZ | C23: Glb | D23: 1 | F23: 8750 | G23: =+E23*D23 -> 0 | H23: =+F23*D23 -> 8750 | I23: =+G23+(H23*$I$3) -> 32812.5
A24: 2.04 | B24: ElectrobombamultietapicaverticalenaceroinoxtipoJockeymarcaWILOmodeloHelixFIRSTV218de4HP230V 3Ø 60HZ Caudal 5GPM @ 255 PSI | C24: Glb | D24: 1 | F24: 1585.24 | G24: =+E24*D24 -> 0 | H24: =+F24*D24 -> 1585.24 | I24: =+G24+(H24*$I$3) -> 5944.65
A25: 2.05 | B25: TablerodeControldeBombatipoJockeyFIRETROLFTA560F- AG004 A 3Ø/230V | C25: Glb | D25: 1 | F25: 988.13 | G25: =+E25*D25 -> 0 | H25: =+F25*D25 -> 988.13 | I25: =+G25+(H25*$I$3) -> 3705.4875
A26: 2.06 | B26: MedidordeflujoranuradomarcaGlobalVisionmodelo6-500 de 6” UL/FM | C26: Glb | D26: 1 | F26: 1191.38 | G26: =+E26*D26 -> 0 | H26: =+F26*D26 -> 1191.38 | I26: =+G26+(H26*$I$3) -> 4467.675
A27: 2.07
A28: 2.08 | B28: Instalación Equipo de Bombeo contraincendio en sala de Bombas succion de 6", descarga de 6" y retorno de pruebas de 4".
A29: 2.09 | B29: Suministro de materiales Sala de Bombas | C29: Glb | D29: 1 | F29: 4454.69 | G29: =+E29*D29 -> 0 | H29: =+F29*D29 -> 4454.69 | I29: =+G29+(H29*$I$3) -> 16705.087
A30: 2.10 | B30: MontajeelectromecanicodelEquipodeBombeoSaladebombas | C30: Glb | D30: 1 | F30: 2500 | G30: =+E30*D30 -> 0 | H30: =+F30*D30 -> 2500 | I30: =+G30+(H30*$I$3) -> 9375
A31: 3.00 | B31: SISTEMA DE AGUA CONTRAINCENDIO - ROCIADORES Y GABINETES | I31: =SUM(H32:H35) -> 363487.31
A32: 3.01 | B32: Suministro e Instalación de Sistema de la Red de Rociadores y Gabinetes
A33: 3.02 | B33: Suministro de materiales red de Gabinetes y Rociadores. | C33: Glb | D33: 1 | F33: 249987.01 | G33: =+E33*D33 -> 0 | H33: =+F33*D33 -> 249987.01 | I33: =+G33+(H33*$I$3) -> 937451.29
A34: 3.03 | B34: Montaje mecanico del sistema de Gabinetes y Rociadores | C34: Glb | D34: 1 | F34: 98449.28 | G34: =+E34*D34 -> 0 | H34: =+F34*D34 -> 98449.28 | I34: =+G34+(H34*$I$3) -> 369184.8
A35: 3.04 | B35: Gastos generales | C35: Glb | D35: 1 | F35: 15051.02 | G35: =+E35*D35 -> 0 | H35: =+F35*D35 -> 15051.02 | I35: =+G35+(H35*$I$3) -> 56441.325

Sheet OBRA CIVIL ASCENSOR
B2: DESCRIPCIÓN | C2: UND | D2: CANTIDAD | E2: PRECIO | F2: PARCIAL | G2: TOTAL
B3: ASCENSORES | G3: =SUM(F5:F6) -> 103726
B4: OBRAS CIVILES
B5: OBRAS CIVILES PARA LA COLOCACIÓN DE ASCENSOR | C5: und | D5: 1 | E5: 21700 | F5: =+E5*D5 -> 21700
B6: ESTRUCTURAS (DINTELES METÁLICOS/COLUMNAS METÁLICAS) | C6: glb | D6: 1 | E6: 82026 | F6: =+E6*D6 -> 82026

Sheet MECANICAS
A2: INSTALACIONES MECANICAS
H3: T.C | I3: 3.75
A4: Presupuesto | B4: JUAN DE ALIAGA 750
A5: Subpresupuesto | B5: INSTALACIONS MECANICAS
A6: Cliente | B6: : V&V Bravo S.A.C | F6: Costo al | G6: 45538
A7: Lugar
A8: ITEM | B8: DESCRIPCION | C8: UND | D8: CANTIDAD | E8: P.U (S/.) | F8: P.U ($.) | G8: PARCIAL (S/.) | H8: PARCIAL ($) | I8: TOTAL
A9: 1.01 | B9: VENTILACION MECANICA | I9: =SUM(H11:H136) -> 233305.23
A10: 1 | B10: SISTEMA DE EXTRACCION DE MONOXIDO
A11: 1.1 | B11: EQUIPOS DE VENTILACION
A12: 1.1.1 | B12: EXTRACTOR AXIAL . Código: EA-01 Marca: SYSTEMAIR Caudal: 5,700 CFM@0.90" c.a. Tensión: 220 Volt-3F-60Hz | C12: Unid. | D12: 1 | F12: 750 | G12: =+E12*D12 -> 0 | H12: =+F12*D12 -> 750 | I12: =+G12+(H12*$I$3) -> 2812.5
A13: 1.1.2 | B13: EXTRACTOR AXIAL . Código: EA-02 Marca: SYSTEMAIR Caudal: 4,700 CFM@0.90" c.a. Tensión: 220 Volt-3F-60Hz | C13: Unid. | D13: 6 | F13: 750 | G13: =+E13*D13 -> 0 | H13: =+F13*D13 -> 4500 | I13: =+G13+(H13*$I$3) -> 16875
A14: 1.1.3 | B14: EXTRACTOR AXIAL . Código: EA-03 Marca: SYSTEMAIR Caudal: 4,450 CFM@0.90" c.a. Tensión: 220 Volt-3F-60Hz | C14: Unid. | D14: 2 | F14: 750 | G14: =+E14*D14 -> 0 | H14: =+F14*D14 -> 1500 | I14: =+G14+(H14*$I$3) -> 5625
A15: 1.1.4 | B15: EXTRACTOR AXIAL . Código: EA-04 Marca: SYSTEMAIR Caudal: 5,850 CFM@0.90" c.a. Tensión: 220 Volt-3F-60Hz | C15: Unid. | D15: 2 | F15: 750 | G15: =+E15*D15 -> 0 | H15: =+F15*D15 -> 1500 | I15: =+G15+(H15*$I$3) -> 5625
A16: 1.1.5 | B16: INYECTOR AXIAL . Código: IA-01 Marca: SYSYTEM AIR Caudal: 5,700 CFM@0.50" c.a. Tensión: 220 Volt-3F-60Hz | C16: Unid. | D16: 1 | F16: 722.22 | G16: =+E16*D16 -> 0 | H16: =+F16*D16 -> 722.22 | I16: =+G16+(H16*$I$3) -> 2708.325
A17: 1.1.6 | B17: INYECTOR AXIAL . Código: IA-02 Marca: SYSTEMAIR Caudal: 4,700 CFM@0.50" c.a. Tensión: 220 Volt-3F-60Hz | C17: Unid. | D17: 6 | F17: 722.22 | G17: =+E17*D17 -> 0 | H17: =+F17*D17 -> 4333.32 | I17: =+G17+(H17*$I$3) -> 16249.95
A18: 1.1.7 | B18: INYECTOR AXIAL . Código: IA-05 Marca: SYSTEMAIR Caudal: 4,450 CFM@0.50" c.a. Tensión: 220 Volt-3F-60Hz | C18: Unid. | D18: 2 | F18: 722.22 | G18: =+E18*D18 -> 0 | H18: =+F18*D18 -> 1444.44 | I18: =+G18+(H18*$I$3) -> 5416.65
A19: 1.1.8 | B19: EXTRACTOR TIPO JET FAN Código: VTI-01 Marca: SYSTEMAIR Caudal: 4,100 CFM @0.00" C.A. Tensión: 220 Volt-3F-60Hz 300°F por 2 Horas | C19: Unid. | D19: 23 | F19: 1500 | G19: =+E19*D19 -> 0 | H19: =+F19*D19 -> 34500 | I19: =+G19+(H19*$I$3) -> 129375
A20: 1.1.9 | B20: Suministro e instalacion de Sensor de Monoxido, Marca GREYSTONE, CANADA, alimentación 24 VAC/VDC, Señal de 0- 10V/ 4-20mA y Rango lectura 0-200ppm CO, para montaje en pared. | C20: Unid. | D20: 23 | F20: 227.78 | G20: =+E20*D20 -> 0 | H20: =+F20*D20 -> 5238.94 | I20: =+G20+(H20*$I$3) -> 19646.025
A21: 1.2 | B21: DUCTERIA PARA LA VENTILACION
A22: 1.2.1 | B22: Suministro e instalación de ductos fabricados en plancha galvanizada, para Extraccion de Monoxido, según norma internacional SMACNA, incluye anclaje y soporteria. | C22: Kgrs. | D22: 525 | F22: 3 | G22: =+E22*D22 -> 0 | H22: =+F22*D22 -> 1575 | I22: =+G22+(H22*$I$3) -> 5906.25
A23: 1.2.2 | B23: Suministro e instalación de rejillas de extracción de aire de Fabricación Nacional, fabricada en plancha galvanizada pintado al horno y acabado de color blanco o de acuerdo de arquitectura. | C23: Plg2. | D23: 25140 | F23: 0.16 | G23: =+E23*D23 -> 0 | H23: =+F23*D23 -> 4022.4 | I23: =+G23+(H23*$I$3) -> 15084
A24: 1.2.3 | B24: Suministro e instalación de Dampers de Gravedad, de Fabricación Nacional, fabricada en marco de plancha galvanizada y aletas de aluminio. | C24: Unid. | D24: 20 | F24: 166.67 | G24: =+E24*D24 -> 0 | H24: =+F24*D24 -> 3333.4 | I24: =+G24+(H24*$I$3) -> 12500.25
A25: 1.2.4 | B25: Cableado de sensores de monóxido. | C25: Unid. | D25: 23 | F25: 42.22 | G25: =+E25*D25 -> 0 | H25: =+F25*D25 -> 971.06 | I25: =+G25+(H25*$I$3) -> 3641.475
A26: 1.3 | B26: INSTALACION DE VENTILADORES
A27: 1.3.1 | B27: Instalaciòn de equipos de ventilacion. Montaje de equipo incluye anclajes y soporteria. Tablero de control marca Himell. Contactores y Relays, marca Schneider Leds, Pulsadores y MOA. Conexión eléctrica de fuerza ( Punto dejado máx 1 metro del equipo) Pruebas y ajustes. Puesta en marcha. | C27: Globo. | D27: 1 | F27: 11422.22 | G27: =+E27*D27 -> 0 | H27: =+F27*D27 -> 11422.22 | I27: =+G27+(H27*$I$3) -> 42833.325
A28: 2 | B28: SISTEMA DE VESTIBULOS PREVIOS - ESCALERAS
A29: 2.1 | B29: EQUIPOS DE VENTILACION
A30: 2.1.1 | B30: INYECTOR AXIAL. Código: IA-05 Marca: SYSYTEM AIR Caudal: 385 CFM@0.20" c.a. Tensión: 220 Volt-1F-60Hz | C30: Unid. | D30: 25 | F30: 85 | G30: =+E30*D30 -> 0 | H30: =+F30*D30 -> 2125 | I30: =+G30+(H30*$I$3) -> 7968.75
A31: 2.1.2 | B31: EXTRACTOR AXIAL. Código: EA-05 Marca: SYSYTEM AIR Caudal: 580 CFM@0.20" c.a. Tensión: 220 Volt-1F-60Hz | C31: Unid. | D31: 25 | F31: 85 | G31: =+E31*D31 -> 0 | H31: =+F31*D31 -> 2125 | I31: =+G31+(H31*$I$3) -> 7968.75
A32: 2.1.3 | B32: INYECTOR AXIAL. Código: IA-06 Marca: SYSYTEM AIR Caudal: 440 CFM@0.20" c.a. Tensión: 220 Volt-1F-60Hz | C32: Unid. | D32: 25 | F32: 85 | G32: =+E32*D32 -> 0 | H32: =+F32*D32 -> 2125 | I32: =+G32+(H32*$I$3) -> 7968.75
A33: 2.1.4 | B33: EXTRACTOR AXIAL. Código: EA-06 Marca: SYSYTEM AIR Caudal: 330 CFM@0.20" c.a. Tensión: 220 Volt-1F-60Hz | C33: Unid. | D33: 50 | F33: 85 | G33: =+E33*D33 -> 0 | H33: =+F33*D33 -> 4250 | I33: =+G33+(H33*$I$3) -> 15937.5
A34: 2.1.5 | B34: EXTRACTOR CENTRIFUGO. Código: EC-02 Marca: SYSYTEM AIR Caudal: 14,500 CFM@0.70" c.a. Tensión: 220 Volt-3F-60Hz | C34: Unid. | D34: 1 | F34: 3277.78 | G34: =+E34*D34 -> 0 | H34: =+F34*D34 -> 3277.78 | I34: =+G34+(H34*$I$3) -> 12291.675
A35: 2.1.6 | B35: EXTRACTOR CENTRIFUGO. Código: EC-03 Marca: SYSYTEM AIR Caudal: 16,500 CFM@0.70" c.a. Tensión: 220 Volt-3F-60Hz | C35: Unid. | D35: 1 | F35: 3277.78 | G35: =+E35*D35 -> 0 | H35: =+F35*D35 -> 3277.78 | I35: =+G35+(H35*$I$3) -> 12291.675
A36: 2.1.7 | B36: INYECTOR CENTRIFUGO. Código: IC-02 Marca: SYSYTEM AIR Caudal: 9,625 CFM@0.50" c.a. Tensión: 220 Volt-3F-60Hz | C36: Unid. | D36: 1 | F36: 2944.44 | G36: =+E36*D36 -> 0 | H36: =+F36*D36 -> 2944.44 | I36: =+G36+(H36*$I$3) -> 11041.65
A37: 2.1.8 | B37: INYECTOR CENTRIFUGO. Código: IC-03 Marca: SYSYTEM AIR Caudal: 11,000 CFM@0.50" c.a. Tensión: 220 Volt-3F-60Hz | C37: Unid. | D37: 1 | F37: 2944.44 | G37: =+E37*D37 -> 0 | H37: =+F37*D37 -> 2944.44 | I37: =+G37+(H37*$I$3) -> 11041.65
A38: 2.1.9 | B38: INYECTOR CENTRIFUGO. Código: IC-05 Marca: SYSYTEM AIR Caudal: 5,700 CFM@1.20" c.a. Tensión: 220 Volt-3F-60Hz | C38: Unid. | D38: 2 | F38: 1666.67 | G38: =+E38*D38 -> 0 | H38: =+F38*D38 -> 3333.34 | I38: =+G38+(H38*$I$3) -> 12500.025
A39: 2.1.10 | B39: Suministro e instalacion de Detector de humo en ducto, Marca GREYSTONE, modelo SM-501-N, 230VAC/60Hz, con 2 alarmas , reset, con cabeza intercambiable ionizable-fotoeléctrica, compatible con sistemas de alarma conta incendio, (Standars - UL & CUL listed) | C39: Unid. | D39: 4 | F39: 222.22 | G39: =+E39*D39 -> 0 | H39: =+F39*D39 -> 888.88 | I39: =+G39+(H39*$I$3) -> 3333.3
A40: 2.2 | B40: DUCTERIA PARA LA VENTILACION
A41: 2.2.1 | B41: Suministro e instalación de ductos fabricados en plancha galvanizada, para inyeccion de aire fresco, según norma internacional SMACNA, incluye anclaje y soporteria. | C41: Kgrs. | D41: 350 | F41: 3 | G41: =+E41*D41 -> 0 | H41: =+F41*D41 -> 1050 | I41: =+G41+(H41*$I$3) -> 3937.5
A42: 2.2.2 | B42: Suministro e instalación de rejillas de extracción de aire de Fabricación Nacional, fabricada en plancha galvanizada pintado al horno y acabado de color blanco o de acuerdo de arquitectura. | C42: Plg2. | D42: 13434 | F42: 0.16 | G42: =+E42*D42 -> 0 | H42: =+F42*D42 -> 2149.44 | I42: =+G42+(H42*$I$3) -> 8060.4
A43: 2.2.3 | B43: Suministro e instalación de Damper barométrico, Marca ENERTECH O SIMILAR, modelo BR-30, instalación vertical, flujo horizontal, excéntricamente articulado para bajas velocidades, marco galvanizado: - 19" x 19". | C43: Unid. | D43: 2 | F43: 250 | G43: =+E43*D43 -> 0 | H43: =+F43*D43 -> 500 | I43: =+G43+(H43*$I$3) -> 1875
A44: 2.2.4 | B44: Suministro e instalación de filtro de malla sintética color azul de 1" de espesor, con marco de plancha galvanizada y refuerzo respectivo. | C44: Globo. | D44: 1 | F44: 916.67 | G44: =+E44*D44 -> 0 | H44: =+F44*D44 -> 916.67 | I44: =+G44+(H44*$I$3) -> 3437.5125
A45: 2.3 | B45: INSTALACION DE VENTILADORES
A46: 2.3.1 | B46: Instalaciòn de equipos de ventilacion. Montaje de equipo incluye anclajes y soporteria. Tablero de control marca Himell. Contactores y Relays, marca Schneider Leds, Pulsadores y MOA. Conexión eléctrica de fuerza ( Punto dejado máx 1 metro del equipo) Pruebas y ajustes. Puesta en marcha. | C46: Globo. | D46: 1 | F46: 6583.33 | G46: =+E46*D46 -> 0 | H46: =+F46*D46 -> 6583.33 | I46: =+G46+(H46*$I$3) -> 24687.487
A47: 3 | B47: SISTEMA DE VENTILACION DE BAÑOS.
A48: 3.1 | B48: EQUIPOS DE VENTILACION DE BAÑOS.
A49: 3.1.1 | B49: EXTRACTOR AXIAL Código: EA-07 Marca: SYSTEMAIR Caudal: 100 CFM@0.03"c.a. Tensión: 220 Volt-1F-60Hz | C49: Unid. | D49: 379 | F49: 17.78 | G49: =+E49*D49 -> 0 | H49: =+F49*D49 -> 6738.62 | I49: =+G49+(H49*$I$3) -> 25269.825
A50: 3.1.2 | B50: EXTRACTOR AXIAL Código: EA-08 Marca: SYSTEMAIR Caudal: 120 CFM@0.04"c.a. Tensión: 220 Volt-1F-60Hz | C50: Unid. | D50: 47 | F50: 17.78 | G50: =+E50*D50 -> 0 | H50: =+F50*D50 -> 835.66 | I50: =+G50+(H50*$I$3) -> 3133.725
A51: 3.1.3 | B51: EXTRACTOR AXIAL Código: EA-09 Marca: SYSTEMAIR Caudal: 155 CFM@0.04"c.a. Tensión: 220 Volt-1F-60Hz | C51: Unid. | D51: 240 | F51: 17.78 | G51: =+E51*D51 -> 0 | H51: =+F51*D51 -> 4267.2 | I51: =+G51+(H51*$I$3) -> 16002
A52: 3.1.4 | B52: EXTRACTOR HELICOCENTRIFUGO Código: EHC-02 Marca: SYSTEMAIR Caudal: 220 CFM@0.20"c.a. Tensión: 220 Volt-1F-60Hz | C52: Unid. | D52: 4 | F52: 125 | G52: =+E52*D52 -> 0 | H52: =+F52*D52 -> 500 | I52: =+G52+(H52*$I$3) -> 1875
A53: 3.1.5 | B53: EXTRACTOR HELICOCENTRIFUGO Código: EHC-03 Marca: SYSTEMAIR Caudal: 265 CFM@0.20"c.a. Tensión: 220 Volt-1F-60Hz | C53: Unid. | D53: 1 | F53: 172.22 | G53: =+E53*D53 -> 0 | H53: =+F53*D53 -> 172.22 | I53: =+G53+(H53*$I$3) -> 645.825
A54: 3.1.6 | B54: EXTRACTOR CENTRIFUGO Código: EC-06 Marca: SYSTEMAIR Caudal: 2,985 CFM@0.50"c.a. Tensión: 220 Volt-3F-60Hz | C54: Unid. | D54: 1 | F54: 794.44 | G54: =+E54*D54 -> 0 | H54: =+F54*D54 -> 794.44 | I54: =+G54+(H54*$I$3) -> 2979.15
A55: 3.1.7 | B55: EXTRACTOR CENTRIFUGO Código: EC-07 Marca: SYSTEMAIR Caudal: 1,150 CFM@0.50"c.a. Tensión: 220 Volt-3F-60Hz | C55: Unid. | D55: 1 | F55: 611.11 | G55: =+E55*D55 -> 0 | H55: =+F55*D55 -> 611.11 | I55: =+G55+(H55*$I$3) -> 2291.6625
A56: 3.1.8 | B56: EXTRACTOR CENTRIFUGO Código: EC-08 Marca: SYSTEMAIR Caudal: 3,090 CFM@0.50"c.a. Tensión: 220 Volt-3F-60Hz | C56: Unid. | D56: 1 | F56: 794.44 | G56: =+E56*D56 -> 0 | H56: =+F56*D56 -> 794.44 | I56: =+G56+(H56*$I$3) -> 2979.15
A57: 3.1.9 | B57: EXTRACTOR CENTRIFUGO Código: EC-09 Marca: SYSTEMAIR Caudal: 3,170 CFM@0.50"c.a. Tensión: 220 Volt-3F-60Hz | C57: Unid. | D57: 1 | F57: 794.44 | G57: =+E57*D57 -> 0 | H57: =+F57*D57 -> 794.44 | I57: =+G57+(H57*$I$3) -> 2979.15
A58: 3.1.10 | B58: EXTRACTOR CENTRIFUGO Código: EC-10 Marca: SYSTEMAIR Caudal: 1,200 CFM@0.50"c.a. Tensión: 220 Volt-3F-60Hz | C58: Unid. | D58: 3 | F58: 611.11 | G58: =+E58*D58 -> 0 | H58: =+F58*D58 -> 1833.33 | I58: =+G58+(H58*$I$3) -> 6874.9875
A59: 3.1.11 | B59: EXTRACTOR CENTRIFUGO Código: EC-11 Marca: SYSTEMAIR Caudal: 1,300 CFM@0.50"c.a. Tensión: 220 Volt-3F-60Hz | C59: Unid. | D59: 1 | F59: 611.11 | G59: =+E59*D59 -> 0 | H59: =+F59*D59 -> 611.11 | I59: =+G59+(H59*$I$3) -> 2291.6625
A60: 3.1.12 | B60: EXTRACTOR CENTRIFUGO Código: EC-12 Marca: SYSTEMAIR Caudal: 1,320 CFM@0.50"c.a. Tensión: 220 Volt-3F-60Hz | C60: Unid. | D60: 1 | F60: 611.11 | G60: =+E60*D60 -> 0 | H60: =+F60*D60 -> 611.11 | I60: =+G60+(H60*$I$3) -> 2291.6625
... A64: 3.1.16 | B64: EXTRACTOR CENTRIFUGO Código: EC-16 Marca: SYSTEMAIR Caudal: 2,935 CFM@0.50"c.a. Tensión: 220 Volt-3F-60Hz | C64: Unid. | D64: 2 | F64: 794.44 | G64: =+E64*D64 -> 0 | H64: =+F64*D64 -> 1588.88 | I64: =+G64+(H64*$I$3) -> 5958.3
A65: 3.2 | B65: DUCTERIA PARA LA VENTILACION
A66: 3.2.1 | B66: Suministro e instalación de ductos fabricados en plancha galvanizada, para inyeccion de aire fresco, según norma internacional SMACNA, incluye anclaje y soporteria. | C66: Kgrs. | D66: 765 | F66: 3 | G66: =+E66*D66 -> 0 | H66: =+F66*D66 -> 2295 | I66: =+G66+(H66*$I$3) -> 8606.25
A67: 3.2.2 | B67: Suministro e instalación de rejillas de extracción de aire de Fabricación Nacional, fabricada en plancha galvanizada pintado al horno y acabado de color blanco o de acuerdo de arquitectura. | C67: Plg2. | D67: 325 | F67: 0.16 | G67: =+E67*D67 -> 0 | H67: =+F67*D67 -> 52 | I67: =+G67+(H67*$I$3) -> 195
A68: 3.2.3 | B68: Suministro e instalación de Dampers de Gravedad, de Fabricación Nacional, fabricada en marco de plancha galvanizada y aletas de aluminio. | C68: Unid. | D68: 27 | F68: 127.78 | G68: =+E68*D68 -> 0 | H68: =+F68*D68 -> 3450.06 | I68: =+G68+(H68*$I$3) -> 12937.725
A69: 3.2.4 | B69: Suministro e instalación de Damper Cortafuego de fusible, Marca ENERTECH O SIMILAR, , instalación vertical, flujo horizontal, marco galvanizado. | C69: Unid. | D69: 666 | F69: 38.89 | G69: =+E69*D69 -> 0 | H69: =+F69*D69 -> 25900.74 | I69: =+G69+(H69*$I$3) -> 97127.775
A70: 3.3 | B70: INSTALACION DE VENTILADORES | G70: =+E70*D70 -> 0 | H70: =+F70*D70 -> 0 | I70: =+G70+(H70*$I$3) -> 0
A71: 3.3.1 | B71: Instalaciòn de equipos de ventilacion. Montaje de equipo incluye anclajes. Conexión eléctrica de fuerza ( Punto dejado máx 1 metro del equipo) Pruebas y ajustes. Puesta en marcha. Nota: El ventilador axial funcionara con la luminaria. | C71: Globo. | D71: 1 | F71: 13694.44 | G71: =+E71*D71 -> 0 | H71: =+F71*D71 -> 13694.44 | I71: =+G71+(H71*$I$3) -> 51354.15
A72: 4 | B72: SISTEMA DE VENTILACION DE CUARTO DE BASURA.
A73: 4.1 | B73: EQUIPOS DE VENTILACION DE CUARTO DE BASURA.
A74: 4.1.1 | B74: EXTRACTOR CENTRIFUGO Código: EC-05 Marca: SYSYTEM AIR Caudal: 1,510 CFM@0.50"c.a. Tensión: 220 Volt-3F-60Hz | C74: Unid. | D74: 1 | F74: 627.78 | G74: =+E74*D74 -> 0 | H74: =+F74*D74 -> 627.78 | I74: =+G74+(H74*$I$3) -> 2354.175
A75: 4.1.2 | B75: EXTRACTOR HELICOCENTRIFUGO Código: EHC-01 Marca: SYSYTEM AIR Caudal: 260 CFM@0.20"c.a. Tensión: 220 Volt-1F-60Hz | C75: Unid. | D75: 1 | F75: 166.67 | G75: =+E75*D75 -> 0 | H75: =+F75*D75 -> 166.67 | I75: =+G75+(H75*$I$3) -> 625.0125
A76: 4.2 | B76: DUCTERIA PARA LA VENTILACION | G76: =+E76*D76 -> 0 | H76: =+F76*D76 -> 0 | I76: =+G76+(H76*$I$3) -> 0
A77: 4.2.1 | B77: Suministro e instalación de ductos fabricados en plancha galvanizada, para inyeccion de aire fresco, según norma internacional SMACNA, incluye anclaje y soporteria. | C77: Kgrs. | D77: 215 | F77: 3 | G77: =+E77*D77 -> 0 | H77: =+F77*D77 -> 645 | I77: =+G77+(H77*$I$3) -> 2418.75
A78: 4.2.2 | B78: Suministro e instalación de rejillas de extracción de aire de Fabricación Nacional, fabricada en plancha galvanizada pintado al horno y acabado de color blanco o de acuerdo de arquitectura. | C78: Plg2. | D78: 1286 | F78: 0.16 | G78: =+E78*D78 -> 0 | H78: =+F78*D78 -> 205.76 | I78: =+G78+(H78*$I$3) -> 771.6
A79: 4.2.3 | B79: Suministro e instalación de Damper Cortafuego de fusible, Marca ENERTECH O SIMILAR, , instalación vertical, flujo horizontal, marco galvanizado. | C79: Unid. | D79: 1 | F79: 622.22 | G79: =+E79*D79 -> 0 | H79: =+F79*D79 -> 622.22 | I79: =+G79+(H79*$I$3) -> 2333.325
A80: 4.3 | B80: INSTALACION DE VENTILADORES
A81: 4.3.1 | B81: Instalaciòn de equipos de ventilacion. Montaje de equipo incluye anclajes y soporteria. Tablero de control marca Himell. Contactores y Relays, marca Schneider Leds, Pulsadores y MOA. Conexión eléctrica de fuerza ( Punto dejado máx 1 metro del equipo) Pruebas y ajustes. Puesta en marcha. | C81: Globo. | D81: 1 | F81: 777.78 | G81: =+E81*D81 -> 0 | H81: =+F81*D81 -> 777.78 | I81: =+G81+(H81*$I$3) -> 2916.675
A82: 5 | B82: SISTEMA DE VENTILACION DE CUARTO DE BOMBAS
A83: 5.1 | B83: EQUIPOS DE VENTILACION DE CUARTO DE BOMBAS.
A84: 5.1.1 | B84: EXTRACTOR CENTRIFUGO Código: EC-01 Marca: SYSYTEM AIR Caudal: 2,920 CFM@0.70"c.a. Tensión: 220 Volt-3F-60Hz | C84: Unid. | D84: 1 | F84: 805.56 | G84: =+E84*D84 -> 0 | H84: =+F84*D84 -> 805.56 | I84: =+G84+(H84*$I$3) -> 3020.85
A85: 5.1.2 | B85: INYECTOR CENTRIFUFO Código: IC-01 Marca: SYSYTEM AIR Caudal: 2,950 CFM@0.70"c.a. Tensión: 220 Volt-3F-60Hz | C85: Unid. | D85: 1 | F85: 805.56 | G85: =+E85*D85 -> 0 | H85: =+F85*D85 -> 805.56 | I85: =+G85+(H85*$I$3) -> 3020.85
A86: 5.2 | B86: DUCTERIA PARA LA VENTILACION
A87: 5.2.1 | B87: Suministro e instalación de ductos fabricados en plancha galvanizada, para inyeccion de aire fresco, según norma internacional SMACNA, incluye anclaje y soporteria. | C87: Kgrs. | D87: 295 | F87: 3 | G87: =+E87*D87 -> 0 | H87: =+F87*D87 -> 885 | I87: =+G87+(H87*$I$3) -> 3318.75
A88: 5.2.2 | B88: Suministro e instalación de rejillas de extracción de aire de Fabricación Nacional, fabricada en plancha galvanizada pintado al horno y acabado de color blanco o de acuerdo de arquitectura. | C88: Plg2. | D88: 2432 | F88: 0.16 | G88: =+E88*D88 -> 0 | H88: =+F88*D88 -> 389.12 | I88: =+G88+(H88*$I$3) -> 1459.2
A89: 5.2.3 | B89: Suministro e instalación de Damper Cortafuego de fusible, Marca ENERTECH O SIMILAR, , instalación vertical, flujo horizontal, marco galvanizado. | C89: Unid. | D89: 1 | F89: 866.67 | G89: =+E89*D89 -> 0 | H89: =+F89*D89 -> 866.67 | I89: =+G89+(H89*$I$3) -> 3250.0125
A90: 5.2.4 | B90: Suministro e instalación de filtro de malla sintética color azul de 1" de espesor, con marco de plancha galvanizada y refuerzo respectivo. | C90: Unid. | D90: 1 | F90: 83.33 | G90: =+E90*D90 -> 0 | H90: =+F90*D90 -> 83.33 | I90: =+G90+(H90*$I$3) -> 312.4875
A91: 5.3 | B91: INSTALACION DE VENTILADORES | G91: =+E91*D91 -> 0 | H91: =+F91*D91 -> 0 | I91: =+G91+(H91*$I$3) -> 0
A92: 5.3.1 | B92: Instalaciòn de equipos de ventilacion. Montaje de equipo incluye anclajes y soporteria. Tablero de control marca Himell. Contactores y Relays, marca Schneider Leds, Pulsadores y MOA. Conexión eléctrica de fuerza ( Punto dejado máx 1 metro del equipo) Pruebas y ajustes. Puesta en marcha. | C92: Globo. | D92: 1 | F92: 777.78 | G92: =+E92*D92 -> 0 | H92: =+F92*D92 -> 777.78 | I92: =+G92+(H92*$I$3) -> 2916.675
A93: 6 | B93: SISTEMA DE VENTILACION DE CUARTOS DE GRUPO ELECTROGENO
A94: 6.1 | B94: DUCTERIA PARA LA VENTILACION
A95: 6.2.1 | B95: Suministro e instalación de ductos fabricados en plancha galvanizada, para inyeccion de aire fresco, según norma internacional SMACNA, incluye anclaje y soporteria. | C95: Kgrs. | D95: 160 | F95: 3 | G95: =+E95*D95 -> 0 | H95: =+F95*D95 -> 480 | I95: =+G95+(H95*$I$3) -> 1800
A96: 6.2.2 | B96: Suministro e instalación de rejillas de extracción de aire de Fabricación Nacional, fabricada en plancha galvanizada pintado al horno y acabado de color blanco o de acuerdo de arquitectura. | C96: Plg2. | D96: 6238 | F96: 0.16 | G96: =+E96*D96 -> 0 | H96: =+F96*D96 -> 998.08 | I96: =+G96+(H96*$I$3) -> 3742.8
A97: 7 | B97: SISTEMA DE VENTILACION DE PASILLOS
A98: 7.1 | B98: EQUIPOS DE VENTILACION DE PASILLOS,
A99: 7.1.1 | B99: INYECTOR CENTRIFUGO Código: IC-04 Marca: SYSTEMAIR Caudal: 6,740 CFM@1.00"c.a. Tensión: 220 Volt-3F-60Hz | C99: Unid. | D99: 1 | F99: 1277.78 | G99: =+E99*D99 -> 0 | H99: =+F99*D99 -> 1277.78 | I99: =+G99+(H99*$I$3) -> 4791.675
A100: 7.1.2 | B100: EXTRACTOR CENTRIFUGO Código: EC-04 Marca: SYSTEMAIR Caudal: 6,740 CFM@1.00"c.a. Tensión: 220 Volt-3F-60Hz | C100: Unid. | D100: 1 | F100: 1277.78 | G100: =+E100*D100 -> 0 | H100: =+F100*D100 -> 1277.78 | I100: =+G100+(H100*$I$3) -> 4791.675
A101: 7.2 | B101: DUCTERIA PARA LA VENTILACION
A102: 7.2.1 | B102: Suministro e instalación de ductos fabricados en plancha galvanizada, para inyeccion de aire fresco, según norma internacional SMACNA, incluye anclaje y soporteria. | C102: Kgrs. | D102: 85 | F102: 3 | G102: =+E102*D102 -> 0 | H102: =+F102*D102 -> 255 | I102: =+G102+(H102*$I$3) -> 956.25
A103: 7.2.2 | B103: Suministro e instalación de rejillas de extracción de aire de Fabricación Nacional, fabricada en plancha galvanizada pintado al horno y acabado de color blanco o de acuerdo de arquitectura. | C103: Plg2. | D103: 4888 | F103: 0.16 | G103: =+E103*D103 -> 0 | H103: =+F103*D103 -> 782.08 | I103: =+G103+(H103*$I$3) -> 2932.8
A104: 7.2.3 | B104: Suministro e instalación de filtro de malla sintética color azul de 1" de espesor, con marco de plancha galvanizada y refuerzo respectivo. | C104: Unid. | D104: 1 | F104: 138.89 | G104: =+E104*D104 -> 0 | H104: =+F104*D104 -> 138.89 | I104: =+G104+(H104*$I$3) -> 520.8375
...

Sheet IISS
A2: INSTALACIONES SANITARIAS
H3: T.C | I3: =+tc -> #REF!
A4: Presupuesto | B4: JUAN DE ALIAGA 750
A5: Subpresupuesto | B5: INSTALACIONES SANITARIAS
A6: Cliente | B6: : V&V Bravo S.A.C | F6: Costo al | G6: 45538
A7: Lugar
A8: ITEM | B8: DESCRIPCION | C8: UND | D8: CANTIDAD | E8: P.U (S/.) | F8: P.U ($.) | G8: PARCIAL (S/.) | H8: PARCIAL ($) | I8: TOTAL
A9: 01 | B9: INSTALACIONES SANITARIAS | I9: =SUM(I10:I129) -> #REF!
A10: 01.01 | B10: SISTEMA DE AGUA FRÍA
A11: 01.01.01 | B11: SALIDAS DE AGUA FRIA (EN POLIPROPILENO)
A12: 01.01.01.01 | B12: SALIDA AGUA FRIA PPR 20mm (Ø1/2") | C12: pto | D12: 2110 | E12: 55.79 | G12: =ROUND(E12*D12,2) -> 117716.9 | H12: =ROUND(F12*D12,2) -> 0 | I12: =+G12+(H12*$I$3) -> #REF!
A13: 01.01.01.02 | B13: SALIDA AGUA FRIA PPR 25mm(3/4") | C13: pto | D13: 266 | E13: 58.25 | G13: =ROUND(E13*D13,2) -> 15494.5 | H13: =ROUND(F13*D13,2) -> 0 | I13: =+G13+(H13*$I$3) -> #REF!
A14: 01.01.01.04 | B14: SALIDA AGUA FRIA PPR 50mm(1.1/2") | C14: pto | D14: 12 | E14: 115.91 | G14: =ROUND(E14*D14,2) -> 1390.92 | H14: =ROUND(F14*D14,2) -> 0 | I14: =+G14+(H14*$I$3) -> #REF!
A15: 01.01.02 | B15: REDES DE DISTRIBUCION DE AGUA (EN POLIPROPILENO) | G15: =ROUND(E15*D15,2) -> 0 | H15: =ROUND(F15*D15,2) -> 0
A16: 01.01.02.01 | B16: TUBERIA PPR PN-10 EMPOTRADA DE 1/2" | C16: m | D16: 4054.34 | E16: 13.23 | G16: =ROUND(E16*D16,2) -> 53638.92 | H16: =ROUND(F16*D16,2) -> 0 | I16: =+G16+(H16*$I$3) -> #REF!
A17: 01.01.02.02 | B17: TUBERIA PPR PN-10 EMPOTRADA DE 3/4" | C17: m | D17: 1814.38 | E17: 16.33 | G17: =ROUND(E17*D17,2) -> 29628.83 | H17: =ROUND(F17*D17,2) -> 0 | I17: =+G17+(H17*$I$3) -> #REF!
A18: 01.01.02.03 | B18: TUBERIA PPR PN-10 EMPOTRADA DE 1" | C18: m | D18: 4635 | E18: 19.79 | G18: =ROUND(E18*D18,2) -> 91726.65 | H18: =ROUND(F18*D18,2) -> 0 | I18: =+G18+(H18*$I$3) -> #REF!
A19: 01.01.02.04 | B19: TUBERIA PPR PN-10 EMPOTRADA DE 1.1/4" | C19: m | D19: 40.33 | E19: 26.23 | G19: =ROUND(E19*D19,2) -> 1057.86 | H19: =ROUND(F19*D19,2) -> 0 | I19: =+G19+(H19*$I$3) -> #REF!
A20: 01.01.02.05 | B20: TUBERIA PPR PN-10 EMPOTRADA DE 1.1/2" | C20: m | D20: 48.67 | E20: 37.53 | G20: =ROUND(E20*D20,2) -> 1826.59 | H20: =ROUND(F20*D20,2) -> 0 | I20: =+G20+(H20*$I$3) -> #REF!
A21: 01.01.02.06 | B21: TUBERIA PPR PN-10 EMPOTRADA DE 2" | C21: m | D21: 60 | E21: 52.73 | G21: =ROUND(E21*D21,2) -> 3163.8 | H21: =ROUND(F21*D21,2) -> 0 | I21: =+G21+(H21*$I$3) -> #REF!
A22: 01.01.02.09 | B22: TUBERIA PPR PN-10 COLGADA DE 1/2" | C22: m | D22: 40.87 | E22: 19.6 | G22: =ROUND(E22*D22,2) -> 801.05 | H22: =ROUND(F22*D22,2) -> 0 | I22: =+G22+(H22*$I$3) -> #REF!
A23: 01.01.02.10 | B23: TUBERIA PPR PN-10 COLGADA DE 3/4" | C23: m | D23: 103.49 | E23: 20.91 | G23: =ROUND(E23*D23,2) -> 2163.98 | H23: =ROUND(F23*D23,2) -> 0 | I23: =+G23+(H23*$I$3) -> #REF!
A24: 01.01.02.11 | B24: TUBERIA PPR PN-10 COLGADA DE 1" | C24: m | D24: 85.95 | E24: 34.01 | G24: =ROUND(E24*D24,2) -> 2923.16 | H24: =ROUND(F24*D24,2) -> 0 | I24: =+G24+(H24*$I$3) -> #REF!
A25: 01.01.02.12 | B25: TUBERIA PPR PN-10 COLGADA DE 1.1/2" | C25: m | D25: 66.01 | E25: 45.36 | G25: =ROUND(E25*D25,2) -> 2994.21 | H25: =ROUND(F25*D25,2) -> 0 | I25: =+G25+(H25*$I$3) -> #REF!
A26: 01.01.02.16 | B26: TUBERIA PPR PN-10 COLGADA DE 4" | C26: m | D26: 136.35 | E26: 155.09 | G26: =ROUND(E26*D26,2) -> 21146.52 | H26: =ROUND(F26*D26,2) -> 0 | I26: =+G26+(H26*$I$3) -> #REF!
A27: 01.01.03 | B27: MONTANTE DE AGUA FRIA (EN POLIPROPILENO) | G27: =ROUND(E27*D27,2) -> 0 | H27: =ROUND(F27*D27,2) -> 0
A28: 01.01.03.02 | B28: TUBERIA PPR PN-10 ADOSADA DE 1.1/2" | C28: m | D28: 116 | E28: 45.36 | G28: =ROUND(E28*D28,2) -> 5261.76 | H28: =ROUND(F28*D28,2) -> 0 | I28: =+G28+(H28*$I$3) -> #REF!
A29: 01.01.03.04 | B29: TUBERIA PPR PN-10 ADOSADA DE 2.1/2" | C29: m | D29: 33 | E29: 88.33 | G29: =ROUND(E29*D29,2) -> 2914.89 | H29: =ROUND(F29*D29,2) -> 0 | I29: =+G29+(H29*$I$3) -> #REF!
A30: 01.01.03.05 | B30: TUBERIA PPR PN-10 ADOSADA DE 3" | C30: m | D30: 18 | E30: 113.33 | G30: =ROUND(E30*D30,2) -> 2039.94 | H30: =ROUND(F30*D30,2) -> 0 | I30: =+G30+(H30*$I$3) -> #REF!
A31: 01.01.03.06 | B31: TUBERIA PPR PN-10 ADOSADA DE 4" | C31: m | D31: 275.75 | E31: 169.21 | G31: =ROUND(E31*D31,2) -> 46659.66 | H31: =ROUND(F31*D31,2) -> 0 | I31: =+G31+(H31*$I$3) -> #REF!
A32: 01.01.04 | B32: LLAVES Y VALVULAS - RED DE DESTRIBUCION (SIST. POLIPROPILENO) | G32: =ROUND(E32*D32,2) -> 0 | H32: =ROUND(F32*D32,2) -> 0
A33: 01.01.04.01 | B33: LLAVE DE PASO SIST. POLIPROPILENO 20mm (1/2") | C33: und | D33: 754 | E33: 80.39 | G33: =ROUND(E33*D33,2) -> 60614.06 | H33: =ROUND(F33*D33,2) -> 0 | I33: =+G33+(H33*$I$3) -> #REF!
A34: 01.01.04.02 | B34: LLAVE DE PASO SIST. POLIPROPILENO 25mm (3/4") | C34: und | D34: 742 | E34: 95.3 | G34: =ROUND(E34*D34,2) -> 70712.6 | H34: =ROUND(F34*D34,2) -> 0 | I34: =+G34+(H34*$I$3) -> #REF!
A35: 01.01.04.03 | B35: LLAVE DE PASO SIST. POLIPROPILENO 32mm (1") | C35: und | D35: 215 | E35: 159.85 | G35: =ROUND(E35*D35,2) -> 34367.75 | H35: =ROUND(F35*D35,2) -> 0 | I35: =+G35+(H35*$I$3) -> #REF!
A36: 01.01.04.05 | B36: LLAVE DE PASO SIST. POLIPROPILENO (1.1/2") | C36: und | D36: 50 | E36: 394.5 | G36: =ROUND(E36*D36,2) -> 19725 | H36: =ROUND(F36*D36,2) -> 0 | I36: =+G36+(H36*$I$3) -> #REF!
A37: 01.01.05 | B37: PRUEBAS HIDRAULICAS | G37: =ROUND(E37*D37,2) -> 0 | H37: =ROUND(F37*D37,2) -> 0
A38: 01.01.05.01 | B38: PRUEBA HIDRAULICA PARA AGUA FRIA | C38: glb | D38: 1 | E38: 25146 | G38: =ROUND(E38*D38,2) -> 25146 | H38: =ROUND(F38*D38,2) -> 0 | I38: =+G38+(H38*$I$3) -> #REF!
A39: 01.01.05.02 | B39: LIMPIEZA Y DESINFECCION DE TUBERIAS AGUA FRIA | C39: glb | D39: 1 | E39: 11430 | G39: =ROUND(E39*D39,2) -> 11430 | H39: =ROUND(F39*D39,2) -> 0 | I39: =+G39+(H39*$I$3) -> #REF!
A40: 01.01.05.03 | B40: LIMPIEZA Y DESINFECCION DE CISTERNAS | C40: glb | D40: 1 | E40: 2353.08 | G40: =ROUND(E40*D40,2) -> 2353.08 | H40: =ROUND(F40*D40,2) -> 0 | I40: =+G40+(H40*$I$3) -> #REF!
A41: 01.01.06 | B41: VARIOS | G41: =ROUND(E41*D41,2) -> 0 | H41: =ROUND(F41*D41,2) -> 0
A42: 01.01.06.01 | B42: MEDIDOR DE AGUA DE 3/4" (INC. BATERIA) | C42: und | D42: 132 | E42: 385.57 | G42: =ROUND(E42*D42,2) -> 50895.24 | H42: =ROUND(F42*D42,2) -> 0 | I42: =+G42+(H42*$I$3) -> #REF!
A43: 01.01.06.02 | B43: MEDIDOR DE AGUA DE 1" (INC. BATERIA) | C43: und | D43: 114 | E43: 461.15 | G43: =ROUND(E43*D43,2) -> 52571.1 | H43: =ROUND(F43*D43,2) -> 0 | I43: =+G43+(H43*$I$3) -> #REF!
A44: 01.01.06.04 | B44: GRIFO DE RIEGO 1/2" | C44: und | D44: 1 | E44: 79.83 | G44: =ROUND(E44*D44,2) -> 79.83 | H44: =ROUND(F44*D44,2) -> 0 | I44: =+G44+(H44*$I$3) -> #REF!
A45: 01.01.07 | B45: CUARTO DE BOMBAS | G45: =ROUND(E45*D45,2) -> 0 | H45: =ROUND(F45*D45,2) -> 0
A46: 01.01.07.01 | B46: BRIDA ROMPEAGUA3" | C46: und | D46: 3 | E46: 733.17 | G46: =ROUND(E46*D46,2) -> 2199.51 | H46: =ROUND(F46*D46,2) -> 0 | I46: =+G46+(H46*$I$3) -> #REF!
A47: 01.01.07.02 | B47: BRIDA ROMPEAGUA 4" | C47: und | D47: 3 | E47: 1059.37 | G47: =ROUND(E47*D47,2) -> 3178.11 | H47: =ROUND(F47*D47,2) -> 0 | I47: =+G47+(H47*$I$3) -> #REF!
A48: 01.01.07.03 | B48: BRIDA ROMPEAGUA 6" | C48: und | D48: 4 | E48: 1762.09 | G48: =ROUND(E48*D48,2) -> 7048.36 | H48: =ROUND(F48*D48,2) -> 0 | I48: =+G48+(H48*$I$3) -> #REF!
A49: 01.01.07.04 | B49: VALVULA FLOTADORA DE 2" | C49: und | D49: 3 | E49: 789.45 | G49: =ROUND(E49*D49,2) -> 2368.35 | H49: =ROUND(F49*D49,2) -> 0 | I49: =+G49+(H49*$I$3) -> #REF!
A50: 01.01.07.05 | B50: VALVULA COMPUERTA DE 2" | C50: und | D50: 3 | E50: 378.1 | G50: =ROUND(E50*D50,2) -> 1134.3 | H50: =ROUND(F50*D50,2) -> 0 | I50: =+G50+(H50*$I$3) -> #REF!
A51: 01.01.07.06 | B51: VALVULA COMPUERTA DE 4" | C51: und | D51: 2 | E51: 577.66 | G51: =ROUND(E51*D51,2) -> 1155.32 | H51: =ROUND(F51*D51,2) -> 0 | I51: =+G51+(H51*$I$3) -> #REF!
A52: 01.02 | B52: SISTEMA DE AGUA CALIENTE | G52: =ROUND(E52*D52,2) -> 0 | H52: =ROUND(F52*D52,2) -> 0
A53: 01.02.01 | B53: SALIDAS DE AGUA CALIENTE (EN POLIPROPILENO) | G53: =ROUND(E53*D53,2) -> 0 | H53: =ROUND(F53*D53,2) -> 0
A54: 01.02.01.01 | B54: SALIDA AGUA CALIENTE PPR 20mm (Ø1/2") | C54: pto | D54: =1366-194*0 -> 1366 | E54: 57.12 | G54: =ROUND(E54*D54,2) -> 78025.92 | H54: =ROUND(F54*D54,2) -> 0 | I54: =+G54+(H54*$I$3) -> #REF!
A55: 01.02.01.02 | B55: SALIDA AGUA CALIENTE PPR 25mm (Ø3/4") | C55: pto | D55: 237 | E55: 61.63 | G55: =ROUND(E55*D55,2) -> 14606.31 | H55: =ROUND(F55*D55,2) -> 0 | I55: =+G55+(H55*$I$3) -> #REF!
A56: 01.02.02 | B56: REDES DE DISTRIBUCION DE AGUA CALIENTE (EN POLIPROPILENO) | G56: =ROUND(E56*D56,2) -> 0 | H56: =ROUND(F56*D56,2) -> 0
A57: 01.02.02.01 | B57: TUBERIA PPR PN-16 EMPOTRADA DE 1/2" | C57: m | D57: =3770.05-1.5*194*0 -> 3770.05 | E57: 13.55 | G57: =ROUND(E57*D57,2) -> 51084.18 | H57: =ROUND(F57*D57,2) -> 0 | I57: =+G57+(H57*$I$3) -> #REF!
A58: 01.02.02.02 | B58: TUBERIA PPR PN-16 EMPOTRADA DE 3/4" | C58: m | D58: 1003.82 | E58: 17.22 | G58: =ROUND(E58*D58,2) -> 17285.78 | H58: =ROUND(F58*D58,2) -> 0 | I58: =+G58+(H58*$I$3) -> #REF!
A59: 01.02.03 | B59: LLAVES Y VALVULAS - RED DE DESTRIBUCION (SIST. POLIPROPILENO) | G59: =ROUND(E59*D59,2) -> 0 | H59: =ROUND(F59*D59,2) -> 0
A60: 01.02.03.01 | B60: LLAVE DE PASO SIST. POLIPROPILENO 20mm (1/2") | C60: und | D60: 706 | E60: 92.63 | G60: =ROUND(E60*D60,2) -> 65396.78 | H60: =ROUND(F60*D60,2) -> 0 | I60: =+G60+(H60*$I$3) -> #REF!
A61: 01.02.03.02 | B61: LLAVE DE PASO SIST. POLIPROPILENO 25mm (3/4") | C61: und | D61: 237 | E61: 89.76 | G61: =ROUND(E61*D61,2) -> 21273.12 | H61: =ROUND(F61*D61,2) -> 0 | I61: =+G61+(H61*$I$3) -> #REF!
A62: 01.02.04 | B62: PRUEBAS HIDRAULICAS | G62: =ROUND(E62*D62,2) -> 0 | H62: =ROUND(F62*D62,2) -> 0
A63: 01.02.04.01 | B63: PRUEBA HIDRAULICA PARA AGUA CALIENTE Y DESINFECCION | C63: glb | D63: 1 | E63: 15276.38 | G63: =ROUND(E63*D63,2) -> 15276.38 | H63: =ROUND(F63*D63,2) -> 0 | I63: =+G63+(H63*$I$3) -> #REF!
A64: 01.03 | B64: SISTEMA DE DESAGUE | G64: =ROUND(E64*D64,2) -> 0 | H64: =ROUND(F64*D64,2) -> 0
A65: 01.03.01 | B65: SALIDAS DE DRENAJE, DESAGUE Y VENTILACION | G65: =ROUND(E65*D65,2) -> 0 | H65: =ROUND(F65*D65,2) -> 0
A66: 01.03.01.01 | B66: SALIDA DESAGUE DE PVC SAP 2" | C66: pto | D66: 3149 | E66: 56.02 | G66: =ROUND(E66*D66,2) -> 176406.98 | H66: =ROUND(F66*D66,2) -> 0 | I66: =+G66+(H66*$I$3) -> #REF!
A67: 01.03.01.02 | B67: SALIDA DESAGUE DE PVC SAP 2" (VALVULA DE ADMISION) | C67: pto | D67: 244 | E67: 106.79 | G67: =ROUND(E67*D67,2) -> 26056.76 | H67: =ROUND(F67*D67,2) -> 0 | I67: =+G67+(H67*$I$3) -> #REF!
A68: 01.03.01.04 | B68: SALIDA DESAGUE DE PVC SAP 3" | C68: pto | D68: 105 | E68: 61.11 | G68: =ROUND(E68*D68,2) -> 6416.55 | H68: =ROUND(F68*D68,2) -> 0 | I68: =+G68+(H68*$I$3) -> #REF!
A69: 01.03.01.05 | B69: SALIDA DESAGUE DE PVC SAP 4" | C69: pto | D69: 496 | E69: 74.38 | G69: =ROUND(E69*D69,2) -> 36892.48 | H69: =ROUND(F69*D69,2) -> 0 | I69: =+G69+(H69*$I$3) -> #REF!
A70: 01.03.01.06 | B70: SALIDA DESAGUE DE PVC SAP 6" | C70: pto | D70: 15 | E70: 115.07 | G70: =ROUND(E70*D70,2) -> 1726.05 | H70: =ROUND(F70*D70,2) -> 0 | I70: =+G70+(H70*$I$3) -> #REF!
A71: 01.03.01.07 | B71: SALIDA VENTILACION DE PVC SAP 2" | C71: pto | D71: 1044 | E71: 39.23 | G71: =ROUND(E71*D71,2) -> 40956.12 | H71: =ROUND(F71*D71,2) -> 0 | I71: =+G71+(H71*$I$3) -> #REF!
A72: 01.03.02 | B72: REDES DE DESAGUE Y DRENAJE | G72: =ROUND(E72*D72,2) -> 0 | H72: =ROUND(F72*D72,2) -> 0
A73: 01.03.02.01 | B73: TUBERIA PVC SAP EMPOTRADA DE 2" | C73: m | D73: 3010.48 | E73: 19.8 | G73: =ROUND(E73*D73,2) -> 59607.5 | H73: =ROUND(F73*D73,2) -> 0 | I73: =+G73+(H73*$I$3) -> #REF!
A74: 01.03.02.02 | B74: TUBERIA PVC SAP EMPOTRADA DE 3" | C74: m | D74: 15.72 | E74: 30.28 | G74: =ROUND(E74*D74,2) -> 476 | H74: =ROUND(F74*D74,2) -> 0 | I74: =+G74+(H74*$I$3) -> #REF!
A75: 01.03.02.03 | B75: TUBERIA PVC SAP EMPOTRADA DE 4" | C75: m | D75: 877.54 | E75: 42.96 | G75: =ROUND(E75*D75,2) -> 37699.12 | H75: =ROUND(F75*D75,2) -> 0 | I75: =+G75+(H75*$I$3) -> #REF!
A76: 01.03.02.04 | B76: TUBERIA VENTILACION PVC SAL EMPOTRADA DE 2" | C76: m | D76: 1701.23 | E76: 19.3 | G76: =ROUND(E76*D76,2) -> 32833.74 | H76: =ROUND(F76*D76,2) -> 0 | I76: =+G76+(H76*$I$3) -> #REF!
A77: 01.03.02.05 | B77: TUBERIA VENTILACION PVC SAL EMPOTRADA DE 3" | C77: m | D77: 32.58 | E77: 26.63 | G77: =ROUND(E77*D77,2) -> 867.61 | H77: =ROUND(F77*D77,2) -> 0 | I77: =+G77+(H77*$I$3) -> #REF!
A78: 01.03.02.06 | B78: TUBERIA VENTILACION PVC SAL EMPOTRADA DE 4" | C78: m | D78: 141.09 | E78: 44.5 | G78: =ROUND(E78*D78,2) -> 6278.51 | H78: =ROUND(F78*D78,2) -> 0 | I78: =+G78+(H78*$I$3) -> #REF!
A79: 01.03.03 | B79: REDES ENTERRADAS | G79: =ROUND(E79*D79,2) -> 0 | H79: =ROUND(F79*D79,2) -> 0
A80: 01.03.03.02 | B80: TUBERIA PVC SAP DE 3" | C80: m | D80: 128.66 | E80: 26.63 | G80: =ROUND(E80*D80,2) -> 3426.22 | H80: =ROUND(F80*D80,2) -> 0 | I80: =+G80+(H80*$I$3) -> #REF!
A81: 01.03.03.03 | B81: TUBERIA PVC SAP DE 4" | C81: m | D81: 31.22 | E81: 43.34 | G81: =ROUND(E81*D81,2) -> 1353.07 | H81: =ROUND(F81*D81,2) -> 0 | I81: =+G81+(H81*$I$3) -> #REF!
A82: 01.03.03.04 | B82: TUBERIA PVC SAP DE 6" | C82: m | D82: 16.43 | E82: 119.47 | G82: =ROUND(E82*D82,2) -> 1962.89 | H82: =ROUND(F82*D82,2) -> 0 | I82: =+G82+(H82*$I$3) -> #REF!
A83: 01.03.03.05 | B83: TRAZO Y REPLANTEO PARA IISS | C83: m | D83: 156.31 | E83: 1.78 | G83: =ROUND(E83*D83,2) -> 278.23 | H83: =ROUND(F83*D83,2) -> 0 | I83: =+G83+(H83*$I$3) -> #REF!
A84: 01.03.03.06 | B84: EXCAVACIÓN DE ZANJA -COLOCACIÓN DE TUBERÍA | C84: m3 | D84: 40.64 | E84: 54.54 | G84: =ROUND(E84*D84,2) -> 2216.51 | H84: =ROUND(F84*D84,2) -> 0 | I84: =+G84+(H84*$I$3) -> #REF!
A85: 01.03.03.07 | B85: CAMA DE ARENA | C85: m3 | D85: 6.25 | E85: 76.36 | G85: =ROUND(E85*D85,2) -> 477.25 | H85: =ROUND(F85*D85,2) -> 0 | I85: =+G85+(H85*$I$3) -> #REF!
A86: 01.03.03.08 | B86: RELLENO COMPACTADO CON MATERIAL PROPIO | C86: m3 | D86: 34.39 | E86: 255.9 | G86: =ROUND(E86*D86,2) -> 8800.4 | H86: =ROUND(F86*D86,2) -> 0 | I86: =+G86+(H86*$I$3) -> #REF!
A87: 01.03.03.09 | B87: ACARREO DE DESMONTE A PUNTO DE ACOPIO (D=30m.) | C87: m3 | D87: 24.44 | E87: 38.31 | G87: =ROUND(E87*D87,2) -> 936.3 | H87: =ROUND(F87*D87,2) -> 0 | I87: =+G87+(H87*$I$3) -> #REF!
A88: 01.03.04 | B88: REDES COLGADAS (INC. ACCESORIOS) | G88: =ROUND(E88*D88,2) -> 0 | H88: =ROUND(F88*D88,2) -> 0
A89: 01.03.04.01 | B89: TUBERIA PVC SAP COLGADA DE 2" | C89: m | D89: 61.77 | E89: 22.46 | G89: =ROUND(E89*D89,2) -> 1387.35 | H89: =ROUND(F89*D89,2) -> 0 | I89: =+G89+(H89*$I$3) -> #REF!
A90: 01.03.04.02 | B90: TUBERIA PVC SAP COLGADA DE 3" | C90: m | D90: 387.21 | E90: 33.41 | G90: =ROUND(E90*D90,2) -> 12936.69 | H90: =ROUND(F90*D90,2) -> 0 | I90: =+G90+(H90*$I$3) -> #REF!
A91: 01.03.04.03 | B91: TUBERIA PVC SAP COLGADA DE 4" | C91: m | D91: 29 | E91: 40.3 | G91: =ROUND(E91*D91,2) -> 1168.7 | H91: =ROUND(F91*D91,2) -> 0 | I91: =+G91+(H91*$I$3) -> #REF!
A92: 01.03.04.04 | B92: TUBERIA PVC SAP COLGADA DE 6" | C92: m | D92: 291.98 | E92: 121.18 | G92: =ROUND(E92*D92,2) -> 35382.14 | H92: =ROUND(F92*D92,2) -> 0 | I92: =+G92+(H92*$I$3) -> #REF!
A93: 01.03.04.05 | B93: TUBERIA PPR PN-10 COLGADA DE 3" IMPULSION | C93: m | D93: 56.78 | E93: 124.1 | G93: =ROUND(E93*D93,2) -> 7046.4 | H93: =ROUND(F93*D93,2) -> 0 | I93: =+G93+(H93*$I$3) -> #REF!
A94: 01.03.04.06 | B94: REGISTRO COLGADO TIPO DADO, Ø2" | C94: und | D94: 6 | E94: 40.92 | G94: =ROUND(E94*D94,2) -> 245.52 | H94: =ROUND(F94*D94,2) -> 0 | I94: =+G94+(H94*$I$3) -> #REF!
A95: 01.03.04.07 | B95: REGISTRO COLGADO TIPO DADO, Ø3" | C95: und | D95: 30 | E95: 58.71 | G95: =ROUND(E95*D95,2) -> 1761.3 | H95: =ROUND(F95*D95,2) -> 0 | I95: =+G95+(H95*$I$3) -> #REF!
A96: 01.03.04.08 | B96: REGISTRO COLGADO TIPO DADO, Ø4" | C96: und | D96: 55 | E96: 113.58 | G96: =ROUND(E96*D96,2) -> 6246.9 | H96: =ROUND(F96*D96,2) -> 0 | I96: =+G96+(H96*$I$3) -> #REF!
A97: 01.03.04.09 | B97: REGISTRO COLGADO TIPO DADO, Ø6" | C97: und | D97: 15 | E97: 152.44 | G97: =ROUND(E97*D97,2) -> 2286.6 | H97: =ROUND(F97*D97,2) -> 0 | I97: =+G97+(H97*$I$3) -> #REF!
A98: 01.03.04.10 | B98: PASES EN VIGA DE 3" | C98: und | D98: 36 | E98: 37.48 | G98: =ROUND(E98*D98,2) -> 1349.28 | H98: =ROUND(F98*D98,2) -> 0 | I98: =+G98+(H98*$I$3) -> #REF!
A99: 01.03.04.11 | B99: PASES EN VIGA DE 4" | C99: und | D99: 21 | E99: 53.68 | G99: =ROUND(E99*D99,2) -> 1127.28 | H99: =ROUND(F99*D99,2) -> 0 | I99: =+G99+(H99*$I$3) -> #REF!
A100: 01.03.04.12 | B100: PASES EN VIGA DE 6" | C100: und | D100: 18 | E100: 108.28 | G100: =ROUND(E100*D100,2) -> 1949.04 | H100: =ROUND(F100*D100,2) -> 0 | I100: =+G100+(H100*$I$3) -> #REF!
A101: 01.03.05 | B101: MONTANTES DE DESAGUE Y VENTILACION | G101: =ROUND(E101*D101,2) -> 0 | H101: =ROUND(F101*D101,2) -> 0
...

Sheet IIEE
A2: INSTALACIONES ELECTRICAS
H3: T.C | I3: 3.75
A4: Presupuesto | B4: JUAN DE ALIAGA 750
A5: Subpresupuesto | B5: INSTALACIONES ELECTRICAS
A6: Cliente | B6: : V&V Bravo S.A.C | F6: Costo al | G6: 45538
A7: Lugar
A8: ITEM | B8: DESCRIPCION | C8: UND | D8: CANTIDAD | E8: P.U (S/.) | F8: P.U ($.) | G8: PARCIAL (S/.) | H8: PARCIAL ($) | I8: TOTAL
A9: 01 | B9: INSTALACIONES ELECTRICAS | G9: =SUM(G10:G194) -> 2529563.2 | H9: =SUM(H12:H194) -> 319707.26 | I9: =SUM(I10:I194) -> 3728465.5
A10: 01.01 | B10: SISTEMA DE ALUMBRADO
A11: 01.01.01 | B11: SALIDAS DE ALUMBRADO
A12: 01.01.01.01 | B12: SALIDA PARA LUMINARIA EN TECHO | C12: pto | D12: 835 | E12: 57.87 | F12: 5.88 | G12: =ROUND(E12*D12,2) -> 48321.45 | H12: =ROUND(F12*D12,2) -> 4909.8 | I12: =+G12+(H12*$I$3) -> 66733.2
A13: 01.01.01.02 | B13: SALIDA PARA LUMINARIA EN TECHO DPTO | C13: pto | D13: 2659 | E13: 61.55 | F13: 4.25 | G13: =ROUND(E13*D13,2) -> 163661.45 | H13: =ROUND(F13*D13,2) -> 11300.75 | I13: =+G13+(H13*$I$3) -> 206039.26
A14: 01.01.01.03 | B14: SALIDA PARA BRAQUETTE EN DPTO | C14: pto | D14: 232 | E14: 61.55 | F14: 4.25 | G14: =ROUND(E14*D14,2) -> 14279.6 | H14: =ROUND(F14*D14,2) -> 986 | I14: =+G14+(H14*$I$3) -> 17977.1
A15: 01.01.01.04 | B15: SALIDA PARA LUMINARIA DE EMERGENCIA | C15: pto | D15: 370 | E15: 61.55 | F15: 5.88 | G15: =ROUND(E15*D15,2) -> 22773.5 | H15: =ROUND(F15*D15,2) -> 2175.6 | I15: =+G15+(H15*$I$3) -> 30932
A16: 01.01.01.04 | B16: SALIDA PARA LUMINARIA CINTA LED | C16: pto | D16: 34 | E16: 61.55 | F16: 5.88 | G16: =ROUND(E16*D16,2) -> 2092.7 | H16: =ROUND(F16*D16,2) -> 199.92 | I16: =+G16+(H16*$I$3) -> 2842.4
A17: 01.01.01.04 | B17: SALIDA PARA LUMINARIA TIPO ESTACA | C17: pto | D17: 100 | E17: 61.55 | F17: 5.88 | G17: =ROUND(E17*D17,2) -> 6155 | H17: =ROUND(F17*D17,2) -> 588 | I17: =+G17+(H17*$I$3) -> 8360
A18: 01.01.01.05 | B18: SALIDA PARA LUMINARIA HERMETICA/FLUORESCENTE | C18: pto | D18: 227 | E18: 61.55 | F18: 6.05 | G18: =ROUND(E18*D18,2) -> 13971.85 | H18: =ROUND(F18*D18,2) -> 1373.35 | I18: =+G18+(H18*$I$3) -> 19121.912
A19: 01.01.01.06 | B19: SALIDA PARA BRAQUETTE | C19: pto | D19: 240 | E19: 61.55 | F19: 6.05 | G19: =ROUND(E19*D19,2) -> 14772 | H19: =ROUND(F19*D19,2) -> 1452 | I19: =+G19+(H19*$I$3) -> 20217
A20: 01.01.01.07 | B20: SALIDA PARA EXTRACTOR EN BAÑOS/DEPOSITOS | C20: pto | D20: 670 | E20: 52.2 | F20: 6.05 | G20: =ROUND(E20*D20,2) -> 34974 | H20: =ROUND(F20*D20,2) -> 4053.5 | I20: =+G20+(H20*$I$3) -> 50174.625
A21: 01.01.02 | B21: SALIDAS DE INTERRUPTORES | G21: =ROUND(E21*D21,2) -> 0 | H21: =ROUND(F21*D21,2) -> 0
A22: 01.01.02.01 | B22: SALIDA PARA INTERRUPTOR SIMPLE | C22: pto | D22: 1389 | E22: 55.43 | F22: 5.88 | G22: =ROUND(E22*D22,2) -> 76992.27 | H22: =ROUND(F22*D22,2) -> 8167.32 | I22: =+G22+(H22*$I$3) -> 107619.72
A23: 01.01.02.02 | B23: SALIDA PARA INTERRUPTOR DOBLE | C23: pto | D23: 798 | E23: 55.43 | F23: 5.88 | G23: =ROUND(E23*D23,2) -> 44233.14 | H23: =ROUND(F23*D23,2) -> 4692.24 | I23: =+G23+(H23*$I$3) -> 61829.04
A24: 01.01.02.03 | B24: SALIDA PARA INTERRUPTOR TRIPLE | C24: pto | D24: 199 | E24: 55.43 | F24: 14.29 | G24: =ROUND(E24*D24,2) -> 11030.57 | H24: =ROUND(F24*D24,2) -> 2843.71 | I24: =+G24+(H24*$I$3) -> 21694.482
A25: 01.01.02.04 | B25: SALIDA PARA INTERRUPTOR DE CONMUTACION SIMPLE | C25: pto | D25: 24 | E25: 55.43 | F25: 6.05 | G25: =ROUND(E25*D25,2) -> 1330.32 | H25: =ROUND(F25*D25,2) -> 145.2 | I25: =+G25+(H25*$I$3) -> 1874.82
A26: 01.01.02.05 | B26: SALIDA PARA INTERRUPTOR DE CONMUTACION DOBLE | C26: pto | D26: 0 | E26: 55.43 | F26: 14 | G26: =ROUND(E26*D26,2) -> 0 | H26: =ROUND(F26*D26,2) -> 0 | I26: =+G26+(H26*$I$3) -> 0
A27: 01.01.02.06 | B27: SALIDA PARA INTERRUPTOR DE CONMUTACION TRIPLE | C27: pto | D27: 0 | E27: 55.43 | F27: 19.35 | G27: =ROUND(E27*D27,2) -> 0 | H27: =ROUND(F27*D27,2) -> 0 | I27: =+G27+(H27*$I$3) -> 0
A28: 01.02 | B28: TABLEROS ELECTRICOS | G28: =ROUND(E28*D28,2) -> 0 | H28: =ROUND(F28*D28,2) -> 0
A29: 01.02.01 | B29: SUMINISTRO E INSTALACION DE TABLEROS ELÉCTRICOS | G29: =ROUND(E29*D29,2) -> 0 | H29: =ROUND(F29*D29,2) -> 0
A30: 01.02.01.01 | B30: SUMINISTRO E INSTALACION DE TABLERO DE SERVICIOS GENERALES NORMAL " TSG " | C30: und | D30: 1 | E30: 34764.61 | G30: =ROUND(E30*D30,2) -> 34764.61 | H30: =ROUND(F30*D30,2) -> 0 | I30: =+G30+(H30*$I$3) -> 34764.61
A31: 01.02.01.02 | B31: SUMINISTRO E INSTALACION DE TABLERO DE TRANSFERENCIA AUTOMATICA " TTA-1 " | C31: und | D31: 1 | E31: 81230.04 | G31: =ROUND(E31*D31,2) -> 81230.04 | H31: =ROUND(F31*D31,2) -> 0 | I31: =+G31+(H31*$I$3) -> 81230.04
A32: 01.02.01.03 | B32: SUMINISTRO E INSTALACION DE TABLERO DE SERVICIOS GENERALES DE EMERGENCIA " TGE " | C32: und | D32: 1 | E32: 23004.37 | G32: =ROUND(E32*D32,2) -> 23004.37 | H32: =ROUND(F32*D32,2) -> 0 | I32: =+G32+(H32*$I$3) -> 23004.37
A33: 01.02.01.04 | B33: SUMINISTRO E INSTALACION DE TABLERO DE TRANSFERENCIA AUTOMATICA " TTA-2 " | C33: und | D33: 1 | E33: 21939.72 | G33: =ROUND(E33*D33,2) -> 21939.72 | H33: =ROUND(F33*D33,2) -> 0 | I33: =+G33+(H33*$I$3) -> 21939.72
A34: 01.02.01.05 | B34: SUMINISTRO E INSTALACION DE TABLERO DE DISTRIBUCION DE SOTANO " TS-1 " | C34: und | D34: 1 | E34: 6225.23 | G34: =ROUND(E34*D34,2) -> 6225.23 | H34: =ROUND(F34*D34,2) -> 0 | I34: =+G34+(H34*$I$3) -> 6225.23
A35: 01.02.01.06 | B35: SUMINISTRO E INSTALACION DE TABLERO DE DISTRIBUCION DE SOTANO " TS-2/3/4/5/6 " | C35: und | D35: 5 | E35: 3480.41 | G35: =ROUND(E35*D35,2) -> 17402.05 | H35: =ROUND(F35*D35,2) -> 0 | I35: =+G35+(H35*$I$3) -> 17402.05
A36: 01.02.01.07 | B36: SUMINISTRO E INSTALACION DE TABLERO DE FUERZA DE BOMBA CONTRA INCENDIO " TC-BCI " | C36: und | D36: 1 | E36: 6283.53 | G36: =ROUND(E36*D36,2) -> 6283.53 | H36: =ROUND(F36*D36,2) -> 0 | I36: =+G36+(H36*$I$3) -> 6283.53
A37: 01.02.01.08 | B37: SUMINISTRO E INSTALACION DE TABLERO DE FUERZA AZOTEA " TF-BA1 " | C37: und | D37: 1 | E37: 2010.14 | G37: =ROUND(E37*D37,2) -> 2010.14 | H37: =ROUND(F37*D37,2) -> 0 | I37: =+G37+(H37*$I$3) -> 2010.14
A38: 01.02.01.09 | B38: SUMINISTRO E INSTALACION DE TABLERO DE DISTRIBUCION " TD-HALL-1 " | C38: und | D38: 1 | E38: 12238.4 | G38: =ROUND(E38*D38,2) -> 12238.4 | H38: =ROUND(F38*D38,2) -> 0 | I38: =+G38+(H38*$I$3) -> 12238.4
A39: 01.02.01.10 | B39: SUMINISTRO E INSTALACION DE TABLERO DE DISTRIBUCION DE AZOTEA " TD-AZ-1 " | C39: und | D39: 1 | E39: 4584.37 | G39: =ROUND(E39*D39,2) -> 4584.37 | H39: =ROUND(F39*D39,2) -> 0 | I39: =+G39+(H39*$I$3) -> 4584.37
A40: 01.02.01.11 | B40: SUMINISTRO E INSTALACION DE TABLERO DE DISTRIBUCION DE CINE " TD-CINE " | C40: und | D40: 1 | E40: 1901.14 | G40: =ROUND(E40*D40,2) -> 1901.14 | H40: =ROUND(F40*D40,2) -> 0 | I40: =+G40+(H40*$I$3) -> 1901.14
A41: 01.02.01.12 | B41: SUMINISTRO E INSTALACION DE TABLERO DE DISTRIBUCION " TD-HALL-2 " | C41: und | D41: 1 | E41: 13526.05 | G41: =ROUND(E41*D41,2) -> 13526.05 | H41: =ROUND(F41*D41,2) -> 0 | I41: =+G41+(H41*$I$3) -> 13526.05
... A54: 01.02.01.25 | B54: SUMINISTRO E INSTALACION DE TABLERO TD-2 | C54: und | D54: 209 | E54: 1014.58 | G54: =ROUND(E54*D54,2) -> 212047.22 | H54: =ROUND(F54*D54,2) -> 0 | I54: =+G54+(H54*$I$3) -> 212047.22
A55: 01.03 | B55: SALIDAS DE FUERZA Y ALIMENTADORES | G55: =ROUND(E55*D55,2) -> 0 | H55: =ROUND(F55*D55,2) -> 0 | I55: =+G55+(H55*$I$3) -> 0
A56: 01.03.01 | B56: SALIDAS DE TOMACORRIENTE Y SALIDAS DE FUERZA | G56: =ROUND(E56*D56,2) -> 0 | H56: =ROUND(F56*D56,2) -> 0 | I56: =+G56+(H56*$I$3) -> 0
A57: 01.03.01.01 | B57: SALIDA PARA TOMACORRIENTE BIPOLAR DOBLE CON ESPIGA A TIERRA | C57: pto | D57: 4291 | E57: 51.69 | F57: 5.66 | G57: =ROUND(E57*D57,2) -> 221801.79 | H57: =ROUND(F57*D57,2) -> 24287.06 | I57: =+G57+(H57*$I$3) -> 312878.27
A58: 01.03.01.02 | B58: SALIDA PARA TOMACORRIENTE A PRUEBA DE AGUA | C58: pto | D58: 29 | E58: 52.28 | F58: 5.66 | G58: =ROUND(E58*D58,2) -> 1516.12 | H58: =ROUND(F58*D58,2) -> 164.14 | I58: =+G58+(H58*$I$3) -> 2131.645
A59: 01.03.01.05 | B59: SALIDA PARA TIMBRE | C59: pto | D59: 237 | E59: 54.52 | F59: 5.66 | G59: =ROUND(E59*D59,2) -> 12921.24 | H59: =ROUND(F59*D59,2) -> 1341.42 | I59: =+G59+(H59*$I$3) -> 17951.565
A60: 01.03.01.06 | B60: SALIDA PARA PULSADOR DE TIMBRE | C60: pto | D60: 237 | E60: 54.52 | F60: 5.66 | G60: =ROUND(E60*D60,2) -> 12921.24 | H60: =ROUND(F60*D60,2) -> 1341.42 | I60: =+G60+(H60*$I$3) -> 17951.565
A61: 01.03.01.07 | B61: SALIDA PARA ASCENSORES | C61: pto | D61: 5 | E61: 103.1 | F61: 123.53 | G61: =ROUND(E61*D61,2) -> 515.5 | H61: =ROUND(F61*D61,2) -> 617.65 | I61: =+G61+(H61*$I$3) -> 2831.6875
A62: 01.03.01.09 | B62: SALIDA DE FUERZA PARA BOMBAS DE AGUA | C62: pto | D62: 9 | E62: 103.1 | F62: 49.05 | G62: =ROUND(E62*D62,2) -> 927.9 | H62: =ROUND(F62*D62,2) -> 441.45 | I62: =+G62+(H62*$I$3) -> 2583.3375
A63: 01.03.01.10 | B63: SALIDA DE FUERZA PARA BOMBAS ACI | C63: pto | D63: 1 | E63: 247.4 | F63: 915.36 | G63: =ROUND(E63*D63,2) -> 247.4 | H63: =ROUND(F63*D63,2) -> 915.36 | I63: =+G63+(H63*$I$3) -> 3680
A64: 01.03.01.11 | B64: SALIDA DE FUERZA PARA BOMBA JOCKEY | C64: pto | D64: 1 | E64: 111.1 | F64: 20.16 | G64: =ROUND(E64*D64,2) -> 111.1 | H64: =ROUND(F64*D64,2) -> 20.16 | I64: =+G64+(H64*$I$3) -> 186.7
A65: 01.03.01.12 | B65: SALIDA DE FUERZA PARA BOMBA SUMIDERO | C65: pto | D65: 2 | E65: 102.36 | F65: 37.14 | G65: =ROUND(E65*D65,2) -> 204.72 | H65: =ROUND(F65*D65,2) -> 74.28 | I65: =+G65+(H65*$I$3) -> 483.27
A66: 01.03.01.13 | B66: SALIDA PARA CONTROL DE NIVEL | C66: pto | D66: 5 | E66: 45.55 | G66: =ROUND(E66*D66,2) -> 227.75 | H66: =ROUND(F66*D66,2) -> 0 | I66: =+G66+(H66*$I$3) -> 227.75
A67: 01.03.01.14 | B67: SALIDA DE FUERZA PARA JET FAN | C67: pto | D67: 23 | E67: 167.22 | F67: 72.42 | G67: =ROUND(E67*D67,2) -> 3846.06 | H67: =ROUND(F67*D67,2) -> 1665.66 | I67: =+G67+(H67*$I$3) -> 10092.285
A68: 01.03.01.15 | B68: SALIDA DE FUERZA EXTRAC E INYETOR EN VESTIVULO PREVIO | C68: pto | D68: 125 | E68: 125 | F68: 12.21 | G68: =ROUND(E68*D68,2) -> 15625 | H68: =ROUND(F68*D68,2) -> 1526.25 | I68: =+G68+(H68*$I$3) -> 21348.438
A69: 01.03.01.16 | B69: SALIDA DE FUERZA PARA EXTRACTORES E INYECTORES EN NIVELES INFERIORES | C69: pto | D69: 24 | E69: 125 | F69: 48.02 | G69: =ROUND(E69*D69,2) -> 3000 | H69: =ROUND(F69*D69,2) -> 1152.48 | I69: =+G69+(H69*$I$3) -> 7321.8
A70: 01.03.01.17 | B70: SALIDA DE FUERZA PARA EXTRACTORES E INYECTORES EN NIVELES SUPERIORES | C70: pto | D70: 21 | E70: 125 | F70: 49.96 | G70: =ROUND(E70*D70,2) -> 2625 | H70: =ROUND(F70*D70,2) -> 1049.16 | I70: =+G70+(H70*$I$3) -> 6559.35
A71: 01.03.02 | B71: SUMINISTRO E INSTALACION DE ALIMENTADORES ELECTRICOS | G71: =ROUND(E71*D71,2) -> 0 | H71: =ROUND(F71*D71,2) -> 0 | I71: =+G71+(H71*$I$3) -> 0
A72: 01.03.02.01 | B72: ALIMENTADORES EN AREAS COMUNES | G72: =ROUND(E72*D72,2) -> 0 | H72: =ROUND(F72*D72,2) -> 0 | I72: =+G72+(H72*$I$3) -> 0
A73: 01.03.02.01.01 | B73: 4(3-1x185mm2LSOH90+1x25/Tmm2LSOH80) | C73: m | D73: 49 | E73: 73.56 | F73: 320.8 | G73: =ROUND(E73*D73,2) -> 3604.44 | H73: =ROUND(F73*D73,2) -> 15719.2 | I73: =+G73+(H73*$I$3) -> 62551.44
A74: 01.03.02.01.02 | B74: 2(3-1x240mm2LSOH90+1x35/Tmm2LSOH80) | C74: m | D74: 42 | E74: 73.56 | F74: 209.93 | G74: =ROUND(E74*D74,2) -> 3089.52 | H74: =ROUND(F74*D74,2) -> 8817.06 | I74: =+G74+(H74*$I$3) -> 36153.495
A75: 01.03.02.01.03 | B75: 2(3-1x240mm2N2XOH+1x70/Tmm2N2XOH) | C75: m | D75: 99.66 | E75: 73.56 | F75: 218.19 | G75: =ROUND(E75*D75,2) -> 7330.99 | H75: =ROUND(F75*D75,2) -> 21744.82 | I75: =+G75+(H75*$I$3) -> 88874.065
A76: 01.03.02.01.04 | B76: 3-1x240mm2N2XOH+1x70/Tmm2N2XOH | C76: m | D76: 55.48 | E76: 73.56 | F76: 109.09 | G76: =ROUND(E76*D76,2) -> 4081.11 | H76: =ROUND(F76*D76,2) -> 6052.31 | I76: =+G76+(H76*$I$3) -> 26777.273
A77: 01.03.02.01.05 | B77: 2(3-1x240mm2LSOH90+1x16/Tmm2LSOH80) | C77: m | D77: 77.8 | E77: 73.56 | F77: 205.12 | G77: =ROUND(E77*D77,2) -> 5722.97 | H77: =ROUND(F77*D77,2) -> 15958.34 | I77: =+G77+(H77*$I$3) -> 65566.745
A78: 01.03.02.01.06 | B78: 3-1x150mm2LSOH90+1x16/Tmm2LSOH80 | C78: m | D78: 43.9 | E78: 57.38 | F78: 57.17 | G78: =ROUND(E78*D78,2) -> 2518.98 | H78: =ROUND(F78*D78,2) -> 2509.76 | I78: =+G78+(H78*$I$3) -> 11930.58
A79: 01.03.02.01.07 | B79: 3-1x120mm2LSOH90+1x25/Tmm2LSOH80 | C79: m | D79: 27 | E79: 57.38 | F79: 52.61 | G79: =ROUND(E79*D79,2) -> 1549.26 | H79: =ROUND(F79*D79,2) -> 1420.47 | I79: =+G79+(H79*$I$3) -> 6876.0225
A80: 01.03.02.01.08 | B80: 3-1x50mm2LSOH90+1x16/Tmm2LSOH80 | C80: m | D80: 120.6 | E80: 72.44 | F80: 21.1 | G80: =ROUND(E80*D80,2) -> 8736.26 | H80: =ROUND(F80*D80,2) -> 2544.66 | I80: =+G80+(H80*$I$3) -> 18278.735
A81: 01.03.02.01.09 | B81: 3-1x70mm2LSOH90+1x16/Tmm2LSOH80 | C81: m | D81: 161.72 | E81: 57.38 | F81: 28.16 | G81: =ROUND(E81*D81,2) -> 9279.49 | H81: =ROUND(F81*D81,2) -> 4554.04 | I81: =+G81+(H81*$I$3) -> 26357.14
A82: 01.03.02.01.10 | B82: 3-1x95mm2LSOH90+1x16/Tmm2LSOH80 | C82: m | D82: 405.44 | E82: 60.52 | F82: 41.36 | G82: =ROUND(E82*D82,2) -> 24537.23 | H82: =ROUND(F82*D82,2) -> 16769 | I82: =+G82+(H82*$I$3) -> 87420.98
A83: 01.03.02.01.11 | B83: 3-1x35mm2LSOH90 | C83: m | D83: 488.28 | E83: 30.79 | F83: 14.87 | G83: =ROUND(E83*D83,2) -> 15034.14 | H83: =ROUND(F83*D83,2) -> 7260.72 | I83: =+G83+(H83*$I$3) -> 42261.84
A84: 01.03.02.01.12 | B84: 3-1x35mm2LSOH90+1x10/Tmm2LSOH80 | C84: m | D84: 241.32 | E84: 30.79 | F84: 16.33 | G84: =ROUND(E84*D84,2) -> 7430.24 | H84: =ROUND(F84*D84,2) -> 3940.76 | I84: =+G84+(H84*$I$3) -> 22208.09
... A89: 01.03.02.01.17 | B89: 3-1x4mm2LSOH90+1x4/Tmm2LSOH80 | C89: m | D89: 31 | E89: 13.91 | F89: 2.56 | G89: =ROUND(E89*D89,2) -> 431.21 | H89: =ROUND(F89*D89,2) -> 79.36 | I89: =+G89+(H89*$I$3) -> 728.81
A90: 01.03.02.02 | B90: ALIMENTADORES PARA DEPARTAMENTOS | G90: =ROUND(E90*D90,2) -> 0 | H90: =ROUND(F90*D90,2) -> 0 | I90: =+G90+(H90*$I$3) -> 0
A91: 01.03.02.02.01 | B91: 2-1x6mm2LSOH90+1x10/Tmm2LSOH80 | C91: m | D91: 143.21 | E91: 8.86 | F91: 3.31 | G91: =ROUND(E91*D91,2) -> 1268.84 | H91: =ROUND(F91*D91,2) -> 474.03 | I91: =+G91+(H91*$I$3) -> 3046.4525
A92: 01.03.02.02.02 | B92: 2-1x10mm2LSOH90+1x10/Tmm2LSOH80 | C92: m | D92: 5031.17 | E92: 8.86 | F92: 4.72 | G92: =ROUND(E92*D92,2) -> 44576.17 | H92: =ROUND(F92*D92,2) -> 23747.12 | I92: =+G92+(H92*$I$3) -> 133627.87
A93: 01.03.02.02.03 | B93: 2-1x16mm2LSOH90+1x10/Tmm2LSOH80 | C93: m | D93: 11802 | E93: 8.86 | F93: 6.27 | G93: =ROUND(E93*D93,2) -> 104565.72 | H93: =ROUND(F93*D93,2) -> 73998.54 | I93: =+G93+(H93*$I$3) -> 382060.24
A94: 01.03.02.02.04 | B94: 2-1x25mm2LSOH90+1x10/Tmm2LSOH80 | C94: m | D94: 1878.33 | E94: 9.41 | F94: 8.26 | G94: =ROUND(E94*D94,2) -> 17675.09 | H94: =ROUND(F94*D94,2) -> 15515.01 | I94: =+G94+(H94*$I$3) -> 75856.378
A95: 01.03.03 | B95: CANALIZACION DE FUERZA Y ALIMENTADORES | G95: =ROUND(E95*D95,2) -> 0 | H95: =ROUND(F95*D95,2) -> 0 | I95: =+G95+(H95*$I$3) -> 0
A96: 01.03.03.04 | B96: TUBERIA ELECTRICA Ø65mm EMT | C96: m | D96: 160 | E96: 73.26 | G96: =ROUND(E96*D96,2) -> 11721.6 | H96: =ROUND(F96*D96,2) -> 0 | I96: =+G96+(H96*$I$3) -> 11721.6
A97: 01.03.03.06 | B97: TUBERIA ELECTRICA Ø100mm EMT | C97: m | D97: 161 | E97: 146.72 | G97: =ROUND(E97*D97,2) -> 23621.92 | H97: =ROUND(F97*D97,2) -> 0 | I97: =+G97+(H97*$I$3) -> 23621.92
A98: 01.03.03.07 | B98: TUBERIA PVC-SAP ELECTRICA DE 25 mm | C98: m | D98: 3184 | E98: 12.33 | G98: =ROUND(E98*D98,2) -> 39258.72 | H98: =ROUND(F98*D98,2) -> 0 | I98: =+G98+(H98*$I$3) -> 39258.72
A99: 01.03.03.08 | B99: TUBERIA PVC-SAP ELECTRICA DE 35 mm | C99: m | D99: 9993 | E99: 14.91 | G99: =ROUND(E99*D99,2) -> 148995.63 | H99: =ROUND(F99*D99,2) -> 0 | I99: =+G99+(H99*$I$3) -> 148995.63
A100: 01.03.03.09 | B100: TUBERIA PVC-SAP ELECTRICA DE 40 mm | C100: m | D100: 495 | E100: 20.56 | G100: =ROUND(E100*D100,2) -> 10177.2 | H100: =ROUND(F100*D100,2) -> 0 | I100: =+G100+(H100*$I$3) -> 10177.2
A101: 01.03.03.10 | B101: TUBERIA PVC-SAP ELECTRICA DE 50 mm | C101: m | D101: 26 | E101: 26.89 | G101: =ROUND(E101*D101,2) -> 699.14 | H101: =ROUND(F101*D101,2) -> 0 | I101: =+G101+(H101*$I$3) -> 699.14
A102: 01.03.03.11 | B102: TUBERIA PVC-SAP ELECTRICA DE 65 mm | C102: m | D102: 185 | E102: 34.19 | G102: =ROUND(E102*D102,2) -> 6325.15 | H102: =ROUND(F102*D102,2) -> 0 | I102: =+G102+(H102*$I$3) -> 6325.15
A103: 01.03.03.12 | B103: TUBERIA PVC-SAP ELECTRICA DE 80 mm | C103: m | D103: 35 | E103: 45.48 | G103: =ROUND(E103*D103,2) -> 1591.8 | H103: =ROUND(F103*D103,2) -> 0 | I103: =+G103+(H103*$I$3) -> 1591.8
A104: 01.03.03.13 | B104: TUBERIA PVC-SAP ELECTRICA DE 100 mm | C104: m | D104: 174.78 | E104: 58.4 | G104: =ROUND(E104*D104,2) -> 10207.15 | H104: =ROUND(F104*D104,2) -> 0 | I104: =+G104+(H104*$I$3) -> 10207.15
A105: 01.03.04 | B105: CAJAS DE PASE | G105: =ROUND(E105*D105,2) -> 0 | H105: =ROUND(F105*D105,2) -> 0 | I105: =+G105+(H105*$I$3) -> 0
A106: 01.03.04.01 | B106: CAJA DE PASE OCTOGONAL | C106: und | D106: 111 | E106: 24.84 | G106: =ROUND(E106*D106,2) -> 2757.24 | H106: =ROUND(F106*D106,2) -> 0 | I106: =+G106+(H106*$I$3) -> 2757.24
A107: 01.03.04.02 | B107: CAJA DE PASE 100X100X55mm | C107: und | D107: 58 | E107: 23.35 | G107: =ROUND(E107*D107,2) -> 1354.3 | H107: =ROUND(F107*D107,2) -> 0 | I107: =+G107+(H107*$I$3) -> 1354.3
A108: 01.03.04.03 | B108: CAJA DE PASE 150X150X100mm | C108: und | D108: 12 | E108: 36.31 | G108: =ROUND(E108*D108,2) -> 435.72 | H108: =ROUND(F108*D108,2) -> 0 | I108: =+G108+(H108*$I$3) -> 435.72
A109: 01.03.04.04 | B109: CAJA DE PASE 200X200X100mm | C109: und | D109: 16 | E109: 55.6 | G109: =ROUND(E109*D109,2) -> 889.6 | H109: =ROUND(F109*D109,2) -> 0 | I109: =+G109+(H109*$I$3) -> 889.6
A110: 01.03.04.05 | B110: CAJA DE PASE 250X250X100mm | C110: und | D110: 16 | E110: 61.82 | G110: =ROUND(E110*D110,2) -> 989.12 | H110: =ROUND(F110*D110,2) -> 0 | I110: =+G110+(H110*$I$3) -> 989.12
A111: 01.03.04.06 | B111: CAJA DE PASE 300X300X100mm | C111: und | D111: 5 | E111: 73.26 | G111: =ROUND(E111*D111,2) -> 366.3 | H111: =ROUND(F111*D111,2) -> 0 | I111: =+G111+(H111*$I$3) -> 366.3
A112: 01.03.04.07 | B112: CAJA DE PASE 450X450X300mm | C112: und | D112: 22 | E112: 227.65 | G112: =ROUND(E112*D112,2) -> 5008.3 | H112: =ROUND(F112*D112,2) -> 0 | I112: =+G112+(H112*$I$3) -> 5008.3
A113: 01.03.04.08 | B113: CAJA DE PASE 600X600X200mm | C113: und | D113: 3 | E113: 261.17 | G113: =ROUND(E113*D113,2) -> 783.51 | H113: =ROUND(F113*D113,2) -> 0 | I113: =+G113+(H113*$I$3) -> 783.51
A114: 01.03.04.09 | B114: CAJA DE PASE 700X700X200mm | C114: und | D114: 8 | E114: 266.43 | G114: =ROUND(E114*D114,2) -> 2131.44 | H114: =ROUND(F114*D114,2) -> 0 | I114: =+G114+(H114*$I$3) -> 2131.44
A115: 01.03.04.10 | B115: CAJA DE PASE 1100X400X400mm | C115: und | D115: 2 | E115: 1092.28 | G115: =ROUND(E115*D115,2) -> 2184.56 | H115: =ROUND(F115*D115,2) -> 0 | I115: =+G115+(H115*$I$3) -> 2184.56
A116: 01.03.04.11 | B116: CAJA DE PASE 400X900X400mm | C116: und | D116: 1 | E116: 186.29 | G116: =ROUND(E116*D116,2) -> 186.29 | H116: =ROUND(F116*D116,2) -> 0 | I116: =+G116+(H116*$I$3) -> 186.29
A117: 01.03.04.12 | B117: CAJA DE PASE 300X700X300mm | C117: und | D117: 2 | E117: 127.57 | G117: =ROUND(E117*D117,2) -> 255.14 | H117: =ROUND(F117*D117,2) -> 0 | I117: =+G117+(H117*$I$3) -> 255.14
...
